Workbook
Name tc: Set!$N$1
Name tc: Ago!$N$1

Sheet Abr (2)
A1: Período de Cálculo: | E1: 43191 | U1: Días en el mes | W1: =DATE(YEAR(E1),MONTH(E1)+1,1)-DATE(YEAR(E1),MONTH(E1),1) -> 30
A2: PERUPETRO S.A.
A3: DETERMINACION DEL CANON, SOBRECANON y PARTICIPACION (US$)
A4: ="Correspondiente a "&TEXT(E1,"MMMMMMM YYYY") -> Correspondiente a Abril 2018
A5: ="Tipo de Cambio= "&TEXT(F1,"0.000") -> Tipo de Cambio= 0.000
A7: Localidad | C7: Modalidad de Contrato | D7: Calculo del Canon | F7: Volumen Producción / Venta | I7: Canasta o Valor Venta (US$/Unidad) | K7: Deducción de Gastos para determinación de valor de producción en Punto de Fiscalización (US$) | O7: Valor de la Producción (US$) | P7: Canon y Sobrecanon / Participación (US$) | U7: Resumen por Petróleo y Condensados | AA7: Resumen por Gas Natural | AG7: Control
A8: - Lote | D8: Período | E8: Fórmula | F8: Unidades | G8: 1ra. Q | H8: 2da. Q / Mes | I8: 1ra. Q | J8: 2da. Q / Mes | K8: Flete Marítimo | L8: Comercialización | M8: Oleoducto | N8: Fiscalización | P8: Total | Q8: Localidad 1 | S8: Localidad 2 | U8: Producción / Venta | X8: Valor Prod | Y8: Valor Canon | AA8: Producción / Venta | AD8: Valor Prod | AE8: Valor Canon | AG8: Total
A9: Piura / Tumbes | Q9: Piura | S9: Tumbes | U9: Bls/Mes | V9: V P (US$) | W9: Bls/Día | X9: US$/Bl | Y9: US$/Bl | Z9: US$ | AA9: MM BTU/Mes | AB9: V P (US$) | AC9: MM BTU/Día | AD9: US$/MM BTU | AE9: US$/MM BTU | AF9: US$ | AG9: Canon
A10: - | B10: I | C10: Servicios | D10: Mes | E10: F1 | F10: Bls | H10: 21812 | J10: 69.0374 | N10: 675.6 | O10: =ROUND(G10*I10,2)+ROUND(H10*J10,2)-K10-L10-M10-N10 -> 1505168.2 | P10: =ROUND(18.75%*O10,2) -> 282219.03 | Q10: =ROUND($O10*R10,2) -> 225775.23 | R10: 0.15 | S10: =ROUND($O10*T10,2) -> 56443.81 | T10: 0.0375 | U10: =IF($F10&"/Día"=W$9,SUM($G10:$H10),"") -> 21812 | V10: =IF(U10<>"",$O10,"") -> 1505168.2 | W10: =IF($F10&"/Día"=W$9,ROUND(U10/$W$1,1),"") -> 727.1 | X10: =IF(U10=0,0,IF($F10&"/Día"=W$9,ROUND(V10/U10,4),"")) -> 69.0064 | Y10: =IF(U10=0,0,IF($F10&"/Día"=W$9,ROUND(Z10/U10,4),"")) -> 12.9387 | Z10: =IF(U10<>"",$P10,"") -> 282219.03 | AA10: =IF($F10&"/Día"=AC$9,SUM($G10:$H10),"") | AB10: =IF(AA10<>"",$O10,"") | AC10: =IF($F10&"/Día"=AC$9,ROUND(AA10/$W$1,1),"") | AD10: =IF(AA10=0,0,IF($F10&"/Día"=AC$9,ROUND(AB10/AA10,4),"")) | AE10: =IF(AA10=0,0,IF($F10&"/Día"=AC$9,ROUND(AF10/AA10,4),"")) | AF10: =IF(AA10<>"",$P10,"")
A11: - | B11: I GAS | C11: Servicios | D11: Mes | E11: F1 | F11: MM BTU | H11: 207427.64 | J11: 2.934 | N11: 1891.7 | O11: =ROUND(G11*I11,2)+ROUND(H11*J11,2)-K11-L11-M11-N11 -> 606701 | P11: =ROUND(18.75%*O11,2) -> 113756.44 | Q11: =ROUND($O11*R11,2) -> 91005.15 | R11: 0.15 | S11: =ROUND($O11*T11,2) -> 22751.29 | T11: 0.0375 | U11: =IF($F11&"/Día"=W$9,SUM($G11:$H11),"") | V11: =IF(U11<>"",$O11,"") | W11: =IF($F11&"/Día"=W$9,ROUND(U11/$W$1,1),"") | X11: =IF(U11=0,0,IF($F11&"/Día"=W$9,ROUND(V11/U11,4),"")) | Y11: =IF(U11=0,0,IF($F11&"/Día"=W$9,ROUND(Z11/U11,4),"")) | Z11: =IF(U11<>"",$P11,"") | AA11: =IF($F11&"/Día"=AC$9,SUM($G11:$H11),"") -> 207427.64 | AB11: =IF(AA11<>"",$O11,"") -> 606701 | AC11: =IF($F11&"/Día"=AC$9,ROUND(AA11/$W$1,1),"") -> 6914.3 | AD11: =IF(AA11=0,0,IF($F11&"/Día"=AC$9,ROUND(AB11/AA11,4),"")) -> 2.9249 | AE11: =IF(AA11=0,0,IF($F11&"/Día"=AC$9,ROUND(AF11/AA11,4),"")) -> 0.5484 | AF11: =IF(AA11<>"",$P11,"") -> 113756.44
A12: - | B12: II | C12: Licencia | D12: Quincena | E12: F2 | F12: Bls | G12: 4240 | H12: 4760 | I12: 65.1052 | J12: 68.4188 | N12: 1744.22 | O12: =ROUND(G12*I12,2)+ROUND(H12*J12,2)-K12-L12-M12-N12 -> 599975.32 | P12: =ROUND(18.75%*O12,2) -> 112495.37 | Q12: =ROUND($O12*R12,2) -> 89996.3 | R12: 0.15 | S12: =ROUND($O12*T12,2) -> 22499.07 | T12: 0.0375 | U12: =IF($F12&"/Día"=W$9,SUM($G12:$H12),"") -> 9000 | V12: =IF(U12<>"",$O12,"") -> 599975.32 | W12: =IF($F12&"/Día"=W$9,ROUND(U12/$W$1,1),"") -> 300 | X12: =IF(U12=0,0,IF($F12&"/Día"=W$9,ROUND(V12/U12,4),"")) -> 66.6639 | Y12: =IF(U12=0,0,IF($F12&"/Día"=W$9,ROUND(Z12/U12,4),"")) -> 12.4995 | Z12: =IF(U12<>"",$P12,"") -> 112495.37 | AA12: =IF($F12&"/Día"=AC$9,SUM($G12:$H12),"") | AB12: =IF(AA12<>"",$O12,"") | AC12: =IF($F12&"/Día"=AC$9,ROUND(AA12/$W$1,1),"") | AD12: =IF(AA12=0,0,IF($F12&"/Día"=AC$9,ROUND(AB12/AA12,4),"")) | AE12: =IF(AA12=0,0,IF($F12&"/Día"=AC$9,ROUND(AF12/AA12,4),"")) | AF12: =IF(AA12<>"",$P12,"")
A13: - | B13: II-GAS | C13: Servicios | D13: Mes | E13: F1 | F13: MM BTU | G13: 38460.027 | H13: 37277.294 | I13: 2.1591 | J13: 2.1609 | N13: 1862.53 | O13: =ROUND(G13*I13,2)+ROUND(H13*J13,2)-K13-L13-M13-N13 -> 161729.01 | P13: =ROUND(18.75%*O13,2) -> 30324.19 | Q13: =ROUND($P13*R13/(R13+T13),2) -> 24259.35 | R13: 0.15 | S13: =P13-Q13 -> 6064.84 | T13: 0.0375 | U13: =IF($F13&"/Día"=W$9,SUM($G13:$H13),"") | V13: =IF(U13<>"",$O13,"") | W13: =IF($F13&"/Día"=W$9,ROUND(U13/$W$1,1),"") | X13: =IF(U13=0,0,IF($F13&"/Día"=W$9,ROUND(V13/U13,4),"")) | Y13: =IF(U13=0,0,IF($F13&"/Día"=W$9,ROUND(Z13/U13,4),"")) | Z13: =IF(U13<>"",$P13,"") | AA13: =IF($F13&"/Día"=AC$9,SUM($G13:$H13),"") -> 75737.321 | AB13: =IF(AA13<>"",$O13,"") -> 161729.01 | AC13: =IF($F13&"/Día"=AC$9,ROUND(AA13/$W$1,1),"") -> 2524.6 | AD13: =IF(AA13=0,0,IF($F13&"/Día"=AC$9,ROUND(AB13/AA13,4),"")) -> 2.1354 | AE13: =IF(AA13=0,0,IF($F13&"/Día"=AC$9,ROUND(AF13/AA13,4),"")) -> 0.4004 | AF13: =IF(AA13<>"",$P13,"") -> 30324.19
A14: - | B14: III | C14: Licencia | D14: Quincena | E14: F2 | F14: Bls | G14: 11055 | H14: 11288 | I14: 66.8811 | J14: 70.8015 | N14: 1242.63 | O14: =ROUND(G14*I14,2)+ROUND(H14*J14,2)-K14-L14-M14-N14 -> 1537335.3 | P14: =ROUND(18.75%*O14,2) -> 288250.36 | Q14: =ROUND($O14*R14,2) -> 230600.29 | R14: 0.15 | S14: =ROUND($O14*T14,2) -> 57650.07 | T14: 0.0375 | U14: =IF($F14&"/Día"=W$9,SUM($G14:$H14),"") -> 22343 | V14: =IF(U14<>"",$O14,"") -> 1537335.3 | W14: =IF($F14&"/Día"=W$9,ROUND(U14/$W$1,1),"") -> 744.8 | X14: =IF(U14=0,0,IF($F14&"/Día"=W$9,ROUND(V14/U14,4),"")) -> 68.8061 | Y14: =IF(U14=0,0,IF($F14&"/Día"=W$9,ROUND(Z14/U14,4),"")) -> 12.9011 | Z14: =IF(U14<>"",$P14,"") -> 288250.36 | AA14: =IF($F14&"/Día"=AC$9,SUM($G14:$H14),"") | AB14: =IF(AA14<>"",$O14,"") | AC14: =IF($F14&"/Día"=AC$9,ROUND(AA14/$W$1,1),"") | AD14: =IF(AA14=0,0,IF($F14&"/Día"=AC$9,ROUND(AB14/AA14,4),"")) | AE14: =IF(AA14=0,0,IF($F14&"/Día"=AC$9,ROUND(AF14/AA14,4),"")) | AF14: =IF(AA14<>"",$P14,"")
A15: - | B15: IV | C15: Licencia | D15: Quincena | E15: F2 | F15: Bls | G15: 30621 | H15: 31021 | I15: 66.8811 | J15: 70.8015 | N15: 3209.33 | O15: =ROUND(G15*I15,2)+ROUND(H15*J15,2)-K15-L15-M15-N15 -> 4241090.2 | P15: =ROUND(18.75%*O15,2) -> 795204.41 | Q15: =ROUND($O15*R15,2) -> 636163.52 | R15: 0.15 | S15: =ROUND($O15*T15,2) -> 159040.88 | T15: 0.0375 | U15: =IF($F15&"/Día"=W$9,SUM($G15:$H15),"") -> 61642 | V15: =IF(U15<>"",$O15,"") -> 4241090.2 | W15: =IF($F15&"/Día"=W$9,ROUND(U15/$W$1,1),"") -> 2054.7 | X15: =IF(U15=0,0,IF($F15&"/Día"=W$9,ROUND(V15/U15,4),"")) -> 68.802 | Y15: =IF(U15=0,0,IF($F15&"/Día"=W$9,ROUND(Z15/U15,4),"")) -> 12.9004 | Z15: =IF(U15<>"",$P15,"") -> 795204.41 | AA15: =IF($F15&"/Día"=AC$9,SUM($G15:$H15),"") | AB15: =IF(AA15<>"",$O15,"") | AC15: =IF($F15&"/Día"=AC$9,ROUND(AA15/$W$1,1),"") | AD15: =IF(AA15=0,0,IF($F15&"/Día"=AC$9,ROUND(AB15/AA15,4),"")) | AE15: =IF(AA15=0,0,IF($F15&"/Día"=AC$9,ROUND(AF15/AA15,4),"")) | AF15: =IF(AA15<>"",$P15,"")
A16: - | B16: V | C16: Servicios | D16: Mes | E16: F1 | F16: Bls | H16: 4328 | J16: 69.0374 | N16: 1470.21 | O16: =ROUND(G16*I16,2)+ROUND(H16*J16,2)-K16-L16-M16-N16 -> 297323.66 | P16: =ROUND(18.75%*O16,2) -> 55748.19 | Q16: =ROUND($O16*R16,2) -> 44598.55 | R16: 0.15 | S16: =ROUND($O16*T16,2) -> 11149.64 | T16: 0.0375 | U16: =IF($F16&"/Día"=W$9,SUM($G16:$H16),"") -> 4328 | V16: =IF(U16<>"",$O16,"") -> 297323.66 | W16: =IF($F16&"/Día"=W$9,ROUND(U16/$W$1,1),"") -> 144.3 | X16: =IF(U16=0,0,IF($F16&"/Día"=W$9,ROUND(V16/U16,4),"")) -> 68.6977 | Y16: =IF(U16=0,0,IF($F16&"/Día"=W$9,ROUND(Z16/U16,4),"")) -> 12.8808 | Z16: =IF(U16<>"",$P16,"") -> 55748.19 | AA16: =IF($F16&"/Día"=AC$9,SUM($G16:$H16),"") | AB16: =IF(AA16<>"",$O16,"") | AC16: =IF($F16&"/Día"=AC$9,ROUND(AA16/$W$1,1),"") | AD16: =IF(AA16=0,0,IF($F16&"/Día"=AC$9,ROUND(AB16/AA16,4),"")) | AE16: =IF(AA16=0,0,IF($F16&"/Día"=AC$9,ROUND(AF16/AA16,4),"")) | AF16: =IF(AA16<>"",$P16,"")
A17: - | B17: VII/VI | C17: Licencia | D17: Quincena | E17: F2 | F17: Bls | G17: 53887 | H17: 57472 | I17: 66.3311 | J17: 70.2515 | N17: 2195.94 | O17: =ROUND(G17*I17,2)+ROUND(H17*J17,2)-K17-L17-M17-N17 -> 7609682.3 | P17: =ROUND(18.75%*O17,2) -> 1426815.4 | Q17: =ROUND($O17*R17,2) -> 1141452.3 | R17: 0.15 | S17: =ROUND($O17*T17,2) -> 285363.08 | T17: 0.0375 | U17: =IF($F17&"/Día"=W$9,SUM($G17:$H17),"") -> 111359 | V17: =IF(U17<>"",$O17,"") -> 7609682.3 | W17: =IF($F17&"/Día"=W$9,ROUND(U17/$W$1,1),"") -> 3712 | X17: =IF(U17=0,0,IF($F17&"/Día"=W$9,ROUND(V17/U17,4),"")) -> 68.3347 | Y17: =IF(U17=0,0,IF($F17&"/Día"=W$9,ROUND(Z17/U17,4),"")) -> 12.8128 | Z17: =IF(U17<>"",$P17,"") -> 1426815.4 | AA17: =IF($F17&"/Día"=AC$9,SUM($G17:$H17),"") | AB17: =IF(AA17<>"",$O17,"") | AC17: =IF($F17&"/Día"=AC$9,ROUND(AA17/$W$1,1),"") | AD17: =IF(AA17=0,0,IF($F17&"/Día"=AC$9,ROUND(AB17/AA17,4),"")) | AE17: =IF(AA17=0,0,IF($F17&"/Día"=AC$9,ROUND(AF17/AA17,4),"")) | AF17: =IF(AA17<>"",$P17,"")
A18: - | B18: VII | C18: Servicios | D18: Mes | E18: F1 | F18: Bls | O18: =ROUND(G18*I18,2)+ROUND(H18*J18,2)-K18-L18-M18-N18 -> 0 | P18: =ROUND(18.75%*O18,2) -> 0 | Q18: =ROUND($O18*R18,2) -> 0 | R18: 0.15 | S18: =ROUND($O18*T18,2) -> 0 | T18: 0.0375 | U18: =IF($F18&"/Día"=W$9,SUM($G18:$H18),"") -> 0 | V18: =IF(U18<>"",$O18,"") -> 0 | W18: =IF($F18&"/Día"=W$9,ROUND(U18/$W$1,1),"") -> 0 | X18: =IF(U18=0,0,IF($F18&"/Día"=W$9,ROUND(V18/U18,4),"")) -> 0 | Y18: =IF(U18=0,0,IF($F18&"/Día"=W$9,ROUND(Z18/U18,4),"")) -> 0 | Z18: =IF(U18<>"",$P18,"") -> 0 | AA18: =IF($F18&"/Día"=AC$9,SUM($G18:$H18),"") | AB18: =IF(AA18<>"",$O18,"") | AC18: =IF($F18&"/Día"=AC$9,ROUND(AA18/$W$1,1),"") | AD18: =IF(AA18=0,0,IF($F18&"/Día"=AC$9,ROUND(AB18/AA18,4),"")) | AE18: =IF(AA18=0,0,IF($F18&"/Día"=AC$9,ROUND(AF18/AA18,4),"")) | AF18: =IF(AA18<>"",$P18,"")
A19: - | B19: VII/VI-GAS | C19: Licencia | D19: Quincena | E19: F2 | F19: MM BTU | G19: 57333.39 | H19: 47484.57 | I19: 0.8 | J19: 0.8 | N19: 2096.88 | O19: =ROUND(G19*I19,2)+ROUND(H19*J19,2)-K19-L19-M19-N19 -> 81757.49 | P19: =ROUND(18.75%*O19,2) -> 15329.53 | Q19: =ROUND($O19*R19,2) -> 12263.62 | R19: 0.15 | S19: =ROUND($O19*T19,2) -> 3065.91 | T19: 0.0375 | U19: =IF($F19&"/Día"=W$9,SUM($G19:$H19),"") | V19: =IF(U19<>"",$O19,"") | W19: =IF($F19&"/Día"=W$9,ROUND(U19/$W$1,1),"") | X19: =IF(U19=0,0,IF($F19&"/Día"=W$9,ROUND(V19/U19,4),"")) | Y19: =IF(U19=0,0,IF($F19&"/Día"=W$9,ROUND(Z19/U19,4),"")) | Z19: =IF(U19<>"",$P19,"") | AA19: =IF($F19&"/Día"=AC$9,SUM($G19:$H19),"") -> 104817.96 | AB19: =IF(AA19<>"",$O19,"") -> 81757.49 | AC19: =IF($F19&"/Día"=AC$9,ROUND(AA19/$W$1,1),"") -> 3493.9 | AD19: =IF(AA19=0,0,IF($F19&"/Día"=AC$9,ROUND(AB19/AA19,4),"")) -> 0.78 | AE19: =IF(AA19=0,0,IF($F19&"/Día"=AC$9,ROUND(AF19/AA19,4),"")) -> 0.1462 | AF19: =IF(AA19<>"",$P19,"") -> 15329.53
A20: - | B20: IX | C20: Licencia | D20: Quincena | E20: F2 | F20: Bls | G20: 2124 | H20: 3038 | I20: 66.8811 | J20: 70.8015 | N20: 729.17 | O20: =ROUND(G20*I20,2)+ROUND(H20*J20,2)-K20-L20-M20-N20 -> 356421.25 | P20: =ROUND(18.75%*O20,2) -> 66828.98 | Q20: =ROUND($O20*R20,2) -> 53463.19 | R20: 0.15 | S20: =ROUND($O20*T20,2) -> 13365.8 | T20: 0.0375 | U20: =IF($F20&"/Día"=W$9,SUM($G20:$H20),"") -> 5162 | V20: =IF(U20<>"",$O20,"") -> 356421.25 | W20: =IF($F20&"/Día"=W$9,ROUND(U20/$W$1,1),"") -> 172.1 | X20: =IF(U20=0,0,IF($F20&"/Día"=W$9,ROUND(V20/U20,4),"")) -> 69.0471 | Y20: =IF(U20=0,0,IF($F20&"/Día"=W$9,ROUND(Z20/U20,4),"")) -> 12.9463 | Z20: =IF(U20<>"",$P20,"") -> 66828.98 | AA20: =IF($F20&"/Día"=AC$9,SUM($G20:$H20),"") | AB20: =IF(AA20<>"",$O20,"") | AC20: =IF($F20&"/Día"=AC$9,ROUND(AA20/$W$1,1),"") | AD20: =IF(AA20=0,0,IF($F20&"/Día"=AC$9,ROUND(AB20/AA20,4),"")) | AE20: =IF(AA20=0,0,IF($F20&"/Día"=AC$9,ROUND(AF20/AA20,4),"")) | AF20: =IF(AA20<>"",$P20,"")
A21: - | B21: X | C21: Licencia | D21: Quincena | E21: F2 | F21: Bls | G21: 192441 | H21: 192657 | I21: 66.8811 | J21: 70.8015 | N21: 4283.58 | O21: =ROUND(G21*I21,2)+ROUND(H21*J21,2)-K21-L21-M21-N21 -> 26506787 | P21: =ROUND(18.75%*O21,2) -> 4970022.5 | Q21: =ROUND($O21*R21,2) -> 3976018 | R21: 0.15 | S21: =ROUND($O21*T21,2) -> 994004.5 | T21: 0.0375 | U21: =IF($F21&"/Día"=W$9,SUM($G21:$H21),"") -> 385098 | V21: =IF(U21<>"",$O21,"") -> 26506787 | W21: =IF($F21&"/Día"=W$9,ROUND(U21/$W$1,1),"") -> 12836.6 | X21: =IF(U21=0,0,IF($F21&"/Día"=W$9,ROUND(V21/U21,4),"")) -> 68.8313 | Y21: =IF(U21=0,0,IF($F21&"/Día"=W$9,ROUND(Z21/U21,4),"")) -> 12.9059 | Z21: =IF(U21<>"",$P21,"") -> 4970022.5 | AA21: =IF($F21&"/Día"=AC$9,SUM($G21:$H21),"") | AB21: =IF(AA21<>"",$O21,"") | AC21: =IF($F21&"/Día"=AC$9,ROUND(AA21/$W$1,1),"") | AD21: =IF(AA21=0,0,IF($F21&"/Día"=AC$9,ROUND(AB21/AA21,4),"")) | AE21: =IF(AA21=0,0,IF($F21&"/Día"=AC$9,ROUND(AF21/AA21,4),"")) | AF21: =IF(AA21<>"",$P21,"")
A22: - | B22: X-GAS | C22: Licencia | D22: Mes | E22: F2 | F22: MM BTU | G22: 245652.84 | H22: 253188.98 | I22: 1.7112 | J22: 1.7112 | N22: 2209.07 | O22: =ROUND(G22*I22,2)+ROUND(H22*J22,2)-K22-L22-M22-N22 -> 851409.05 | P22: =ROUND(18.75%*O22,2) -> 159639.2 | Q22: =ROUND($O22*R22,2) -> 127711.36 | R22: 0.15 | S22: =ROUND($O22*T22,2) -> 31927.84 | T22: 0.0375 | U22: =IF($F22&"/Día"=W$9,SUM($G22:$H22),"") | V22: =IF(U22<>"",$O22,"") | W22: =IF($F22&"/Día"=W$9,ROUND(U22/$W$1,1),"") | X22: =IF(U22=0,0,IF($F22&"/Día"=W$9,ROUND(V22/U22,4),"")) | Y22: =IF(U22=0,0,IF($F22&"/Día"=W$9,ROUND(Z22/U22,4),"")) | Z22: =IF(U22<>"",$P22,"") | AA22: =IF($F22&"/Día"=AC$9,SUM($G22:$H22),"") -> 498841.82 | AB22: =IF(AA22<>"",$O22,"") -> 851409.05 | AC22: =IF($F22&"/Día"=AC$9,ROUND(AA22/$W$1,1),"") -> 16628.1 | AD22: =IF(AA22=0,0,IF($F22&"/Día"=AC$9,ROUND(AB22/AA22,4),"")) -> 1.7068 | AE22: =IF(AA22=0,0,IF($F22&"/Día"=AC$9,ROUND(AF22/AA22,4),"")) -> 0.32 | AF22: =IF(AA22<>"",$P22,"") -> 159639.2
A23: - | B23: XIV | C23: Licencia | D23: Mes | E23: F2 | F23: Bls | O23: =ROUND(G23*I23,2)+ROUND(H23*J23,2)-K23-L23-M23-N23 -> 0 | P23: =ROUND(18.75%*O23,2) -> 0 | Q23: =ROUND($O23*R23,2) -> 0 | R23: 0.15 | S23: =ROUND($O23*T23,2) -> 0 | T23: 0.0375 | U23: =IF($F23&"/Día"=W$9,SUM($G23:$H23),"") -> 0 | V23: =IF(U23<>"",$O23,"") -> 0 | W23: =IF($F23&"/Día"=W$9,ROUND(U23/$W$1,1),"") -> 0 | X23: =IF(U23=0,0,IF($F23&"/Día"=W$9,ROUND(V23/U23,4),"")) -> 0 | Y23: =IF(U23=0,0,IF($F23&"/Día"=W$9,ROUND(Z23/U23,4),"")) -> 0 | Z23: =IF(U23<>"",$P23,"") -> 0 | AA23: =IF($F23&"/Día"=AC$9,SUM($G23:$H23),"") | AB23: =IF(AA23<>"",$O23,"") | AC23: =IF($F23&"/Día"=AC$9,ROUND(AA23/$W$1,1),"") | AD23: =IF(AA23=0,0,IF($F23&"/Día"=AC$9,ROUND(AB23/AA23,4),"")) | AE23: =IF(AA23=0,0,IF($F23&"/Día"=AC$9,ROUND(AF23/AA23,4),"")) | AF23: =IF(AA23<>"",$P23,"")
A24: - | B24: XV | C24: Licencia | D24: Quincena | E24: F2 | F24: Bls | G24: 557 | H24: 544 | I24: 67.6937 | J24: 70.8609 | N24: 792.9 | O24: =ROUND(G24*I24,2)+ROUND(H24*J24,2)-K24-L24-M24-N24 -> 75460.82 | P24: =ROUND(18.75%*O24,2) -> 14148.9 | Q24: =ROUND($O24*R24,2) -> 11319.12 | R24: 0.15 | S24: =ROUND($O24*T24,2) -> 2829.78 | T24: 0.0375 | U24: =IF($F24&"/Día"=W$9,SUM($G24:$H24),"") -> 1101 | V24: =IF(U24<>"",$O24,"") -> 75460.82 | W24: =IF($F24&"/Día"=W$9,ROUND(U24/$W$1,1),"") -> 36.7 | X24: =IF(U24=0,0,IF($F24&"/Día"=W$9,ROUND(V24/U24,4),"")) -> 68.5384 | Y24: =IF(U24=0,0,IF($F24&"/Día"=W$9,ROUND(Z24/U24,4),"")) -> 12.851 | Z24: =IF(U24<>"",$P24,"") -> 14148.9 | AA24: =IF($F24&"/Día"=AC$9,SUM($G24:$H24),"") | AB24: =IF(AA24<>"",$O24,"") | AC24: =IF($F24&"/Día"=AC$9,ROUND(AA24/$W$1,1),"") | AD24: =IF(AA24=0,0,IF($F24&"/Día"=AC$9,ROUND(AB24/AA24,4),"")) | AE24: =IF(AA24=0,0,IF($F24&"/Día"=AC$9,ROUND(AF24/AA24,4),"")) | AF24: =IF(AA24<>"",$P24,"")
A25: - | B25: XIII Crudo | C25: Licencia | D25: Quincena | E25: F2 | F25: Bls | G25: 25730 | H25: 31508 | I25: 66.8811 | J25: 70.8015 | N25: 1512.61 | O25: =ROUND(G25*I25,2)+ROUND(H25*J25,2)-K25-L25-M25-N25 -> 3950151.8 | P25: =ROUND(18.75%*O25,2) -> 740653.45 | Q25: =ROUND($O25*R25,2) -> 592522.76 | R25: 0.15 | S25: =ROUND($O25*T25,2) -> 148130.69 | T25: 0.0375 | U25: =IF($F25&"/Día"=W$9,SUM($G25:$H25),"") -> 57238 | V25: =IF(U25<>"",$O25,"") -> 3950151.8 | W25: =IF($F25&"/Día"=W$9,ROUND(U25/$W$1,1),"") -> 1907.9 | X25: =IF(U25=0,0,IF($F25&"/Día"=W$9,ROUND(V25/U25,4),"")) -> 69.0127 | Y25: =IF(U25=0,0,IF($F25&"/Día"=W$9,ROUND(Z25/U25,4),"")) -> 12.9399 | Z25: =IF(U25<>"",$P25,"") -> 740653.45 | AA25: =IF($F25&"/Día"=AC$9,SUM($G25:$H25),"") | AB25: =IF(AA25<>"",$O25,"") | AC25: =IF($F25&"/Día"=AC$9,ROUND(AA25/$W$1,1),"") | AD25: =IF(AA25=0,0,IF($F25&"/Día"=AC$9,ROUND(AB25/AA25,4),"")) | AE25: =IF(AA25=0,0,IF($F25&"/Día"=AC$9,ROUND(AF25/AA25,4),"")) | AF25: =IF(AA25<>"",$P25,"")
A26: - | B26: XIII COND | C26: Licencia | D26: Quincena | E26: F2 | F26: Bls | O26: =ROUND(G26*I26,2)+ROUND(H26*J26,2)-K26-L26-M26-N26 -> 0 | P26: =ROUND(18.75%*O26,2) -> 0 | Q26: =ROUND($O26*R26,2) -> 0 | R26: 0.15 | S26: =ROUND($O26*T26,2) -> 0 | T26: 0.0375 | U26: =IF($F26&"/Día"=W$9,SUM($G26:$H26),"") -> 0 | V26: =IF(U26<>"",$O26,"") -> 0 | W26: =IF($F26&"/Día"=W$9,ROUND(U26/$W$1,1),"") -> 0 | X26: =IF(U26=0,0,IF($F26&"/Día"=W$9,ROUND(V26/U26,4),"")) -> 0 | Y26: =IF(U26=0,0,IF($F26&"/Día"=W$9,ROUND(Z26/U26,4),"")) -> 0 | Z26: =IF(U26<>"",$P26,"") -> 0 | AA26: =IF($F26&"/Día"=AC$9,SUM($G26:$H26),"") | AB26: =IF(AA26<>"",$O26,"") | AC26: =IF($F26&"/Día"=AC$9,ROUND(AA26/$W$1,1),"") | AD26: =IF(AA26=0,0,IF($F26&"/Día"=AC$9,ROUND(AB26/AA26,4),"")) | AE26: =IF(AA26=0,0,IF($F26&"/Día"=AC$9,ROUND(AF26/AA26,4),"")) | AF26: =IF(AA26<>"",$P26,"")
A27: - | B27: XIII Gas | C27: Licencia | D27: Quincena | E27: F2 | F27: MM BTU | G27: =104778.0799+72373.8704 -> 177151.95 | H27: =107745.4041+80578.4653 -> 188323.87 | I27: 2.5397374 | J27: 2.5926134 | N27: 3126.36 | O27: =ROUND(G27*I27,2)+ROUND(H27*J27,2)-K27-L27-M27-N27 -> 935044.05 | P27: =ROUND(18.75%*O27,2) -> 175320.76 | Q27: =ROUND($O27*R27,2) -> 140256.61 | R27: 0.15 | S27: =ROUND($O27*T27,2) -> 35064.15 | T27: 0.0375 | U27: =IF($F27&"/Día"=W$9,SUM($G27:$H27),"") | V27: =IF(U27<>"",$O27,"") | W27: =IF($F27&"/Día"=W$9,ROUND(U27/$W$1,1),"") | X27: =IF(U27=0,0,IF($F27&"/Día"=W$9,ROUND(V27/U27,4),"")) | Y27: =IF(U27=0,0,IF($F27&"/Día"=W$9,ROUND(Z27/U27,4),"")) | Z27: =IF(U27<>"",$P27,"") | AA27: =IF($F27&"/Día"=AC$9,SUM($G27:$H27),"") -> 365475.82 | AB27: =IF(AA27<>"",$O27,"") -> 935044.05 | AC27: =IF($F27&"/Día"=AC$9,ROUND(AA27/$W$1,1),"") -> 12182.5 | AD27: =IF(AA27=0,0,IF($F27&"/Día"=AC$9,ROUND(AB27/AA27,4),"")) -> 2.5584 | AE27: =IF(AA27=0,0,IF($F27&"/Día"=AC$9,ROUND(AF27/AA27,4),"")) -> 0.4797 | AF27: =IF(AA27<>"",$P27,"") -> 175320.76
A28: - | B28: Z-2B | C28: Servicios | D28: Mes | E28: F1 | F28: Bls | G28: =41580+38551+37557+37373+40740+39453+34290 -> 269544 | H28: =38140+200235 -> 238375 | I28: 3.0405943 | J28: 66.808616 | N28: 2417.19 | O28: =ROUND(G28*I28,2)+ROUND(H28*J28,2)-K28-L28-M28-N28 -> 16742661 | P28: =ROUND(18.75%*O28,2) -> 3139248.9 | Q28: =ROUND($O28*R28,2) -> 2511399.1 | R28: 0.15 | S28: =ROUND($O28*T28,2) -> 627849.77 | T28: 0.0375 | U28: =IF($F28&"/Día"=W$9,SUM($G28:$H28),"") -> 507919 | V28: =IF(U28<>"",$O28,"") -> 16742661 | W28: =IF($F28&"/Día"=W$9,ROUND(U28/$W$1,1),"") -> 16930.6 | X28: =IF(U28=0,0,IF($F28&"/Día"=W$9,ROUND(V28/U28,4),"")) -> 32.9632 | Y28: =IF(U28=0,0,IF($F28&"/Día"=W$9,ROUND(Z28/U28,4),"")) -> 6.1806 | Z28: =IF(U28<>"",$P28,"") -> 3139248.9 | AA28: =IF($F28&"/Día"=AC$9,SUM($G28:$H28),"") | AB28: =IF(AA28<>"",$O28,"") | AC28: =IF($F28&"/Día"=AC$9,ROUND(AA28/$W$1,1),"") | AD28: =IF(AA28=0,0,IF($F28&"/Día"=AC$9,ROUND(AB28/AA28,4),"")) | AE28: =IF(AA28=0,0,IF($F28&"/Día"=AC$9,ROUND(AF28/AA28,4),"")) | AF28: =IF(AA28<>"",$P28,"")
A29: - | B29: Z-2B GAS | C29: Servicios | D29: Mes | E29: F1 | F29: MM BTU | H29: =1153.36+20956.56+116077.1 -> 138187.02 | J29: 5.5796026 | N29: 2131.57 | O29: =ROUND(G29*I29,2)+ROUND(H29*J29,2)-K29-L29-M29-N29 -> 768897.09 | P29: =ROUND(18.75%*O29,2) -> 144168.2 | Q29: =ROUND($O29*R29,2) -> 115334.56 | R29: 0.15 | S29: =ROUND($O29*T29,2) -> 28833.64 | T29: 0.0375 | U29: =IF($F29&"/Día"=W$9,SUM($G29:$H29),"") | V29: =IF(U29<>"",$O29,"") | W29: =IF($F29&"/Día"=W$9,ROUND(U29/$W$1,1),"") | X29: =IF(U29=0,0,IF($F29&"/Día"=W$9,ROUND(V29/U29,4),"")) | Y29: =IF(U29=0,0,IF($F29&"/Día"=W$9,ROUND(Z29/U29,4),"")) | Z29: =IF(U29<>"",$P29,"") | AA29: =IF($F29&"/Día"=AC$9,SUM($G29:$H29),"") -> 138187.02 | AB29: =IF(AA29<>"",$O29,"") -> 768897.09 | AC29: =IF($F29&"/Día"=AC$9,ROUND(AA29/$W$1,1),"") -> 4606.2 | AD29: =IF(AA29=0,0,IF($F29&"/Día"=AC$9,ROUND(AB29/AA29,4),"")) -> 5.5642 | AE29: =IF(AA29=0,0,IF($F29&"/Día"=AC$9,ROUND(AF29/AA29,4),"")) -> 1.0433 | AF29: =IF(AA29<>"",$P29,"") -> 144168.2
A30: - | B30: XX | C30: Licencia | D30: Quincena | E30: F2 | F30: Bls | G30: 329 | H30: 329 | I30: 66.8811 | J30: 70.8015 | N30: 465.7 | O30: =ROUND(G30*I30,2)+ROUND(H30*J30,2)-K30-L30-M30-N30 -> 44831.87 | P30: =ROUND(18.75%*O30,2) -> 8405.98 | Q30: =ROUND($O30*R30,2) -> 1681.2 | R30: 0.0375 | S30: =ROUND($O30*T30,2) -> 6724.78 | T30: 0.15 | U30: =IF($F30&"/Día"=W$9,SUM($G30:$H30),"") -> 658 | V30: =IF(U30<>"",$O30,"") -> 44831.87 | W30: =IF($F30&"/Día"=W$9,ROUND(U30/$W$1,1),"") -> 21.9 | X30: =IF(U30=0,0,IF($F30&"/Día"=W$9,ROUND(V30/U30,4),"")) -> 68.1335 | Y30: =IF(U30=0,0,IF($F30&"/Día"=W$9,ROUND(Z30/U30,4),"")) -> 12.775 | Z30: =IF(U30<>"",$P30,"") -> 8405.98 | AA30: =IF($F30&"/Día"=AC$9,SUM($G30:$H30),"") | AB30: =IF(AA30<>"",$O30,"") | AC30: =IF($F30&"/Día"=AC$9,ROUND(AA30/$W$1,1),"") | AD30: =IF(AA30=0,0,IF($F30&"/Día"=AC$9,ROUND(AB30/AA30,4),"")) | AE30: =IF(AA30=0,0,IF($F30&"/Día"=AC$9,ROUND(AF30/AA30,4),"")) | AF30: =IF(AA30<>"",$P30,"")
A31: - | B31: Z1 Crudo | C31: Licencia | D31: Quincena | E31: F2 | F31: Bls | N31: 1434.04 | O31: =ROUND(G31*I31,2)+ROUND(H31*J31,2)-K31-L31-M31-N31 -> -1434.04 | P31: =ROUND(18.75%*O31,2) -> -268.88 | Q31: =ROUND($O31*R31,2) -> -53.78 | R31: 0.0375 | S31: =ROUND($O31*T31,2) -> -215.11 | T31: 0.15 | U31: =IF($F31&"/Día"=W$9,SUM($G31:$H31),"") -> 0 | V31: =IF(U31<>"",$O31,"") -> -1434.04 | W31: =IF($F31&"/Día"=W$9,ROUND(U31/$W$1,1),"") -> 0 | X31: =IF(U31=0,0,IF($F31&"/Día"=W$9,ROUND(V31/U31,4),"")) -> 0 | Y31: =IF(U31=0,0,IF($F31&"/Día"=W$9,ROUND(Z31/U31,4),"")) -> 0 | Z31: =IF(U31<>"",$P31,"") -> -268.88 | AA31: =IF($F31&"/Día"=AC$9,SUM($G31:$H31),"") | AB31: =IF(AA31<>"",$O31,"") | AC31: =IF($F31&"/Día"=AC$9,ROUND(AA31/$W$1,1),"") | AD31: =IF(AA31=0,0,IF($F31&"/Día"=AC$9,ROUND(AB31/AA31,4),"")) | AE31: =IF(AA31=0,0,IF($F31&"/Día"=AC$9,ROUND(AF31/AA31,4),"")) | AF31: =IF(AA31<>"",$P31,"")
A32: - | B32: Z1 Gas | C32: Licencia | D32: Quincena | E32: F2 | F32: MM BTU | O32: =ROUND(G32*I32,2)+ROUND(H32*J32,2)-K32-L32-M32-N32 -> 0 | P32: =ROUND(18.75%*O32,2) -> 0 | Q32: =ROUND($O32*R32,2) -> 0 | R32: 0.0375 | S32: =ROUND($O32*T32,2) -> 0 | T32: 0.15 | U32: =IF($F32&"/Día"=W$9,SUM($G32:$H32),"") | V32: =IF(U32<>"",$O32,"") | W32: =IF($F32&"/Día"=W$9,ROUND(U32/$W$1,1),"") | X32: =IF(U32=0,0,IF($F32&"/Día"=W$9,ROUND(V32/U32,4),"")) | Y32: =IF(U32=0,0,IF($F32&"/Día"=W$9,ROUND(Z32/U32,4),"")) | Z32: =IF(U32<>"",$P32,"") | AA32: =IF($F32&"/Día"=AC$9,SUM($G32:$H32),"") -> 0 | AB32: =IF(AA32<>"",$O32,"") -> 0 | AC32: =IF($F32&"/Día"=AC$9,ROUND(AA32/$W$1,1),"") -> 0 | AD32: =IF(AA32=0,0,IF($F32&"/Día"=AC$9,ROUND(AB32/AA32,4),"")) -> 0 | AE32: =IF(AA32=0,0,IF($F32&"/Día"=AC$9,ROUND(AF32/AA32,4),"")) -> 0 | AF32: =IF(AA32<>"",$P32,"") -> 0
A33: - | B33: Z-2B - LGN | C33: Servicios | D33: Mes | E33: F1 | F33: Bls | H33: =27634+5264 -> 32898 | J33: 54.9433 | N33: 2321.9 | O33: =ROUND(G33*I33,2)+ROUND(H33*J33,2)-K33-L33-M33-N33 -> 1805202.8 | P33: =ROUND(18.75%*O33,2) -> 338475.52 | Q33: =ROUND($O33*R33,2) -> 270780.42 | R33: 0.15 | S33: =ROUND($O33*T33,2) -> 67695.1 | T33: 0.0375 | U33: =IF($F33&"/Día"=W$9,SUM($G33:$H33),"") -> 32898 | V33: =IF(U33<>"",$O33,"") -> 1805202.8 | W33: =IF($F33&"/Día"=W$9,ROUND(U33/$W$1,1),"") -> 1096.6 | X33: =IF(U33=0,0,IF($F33&"/Día"=W$9,ROUND(V33/U33,4),"")) -> 54.8727 | Y33: =IF(U33=0,0,IF($F33&"/Día"=W$9,ROUND(Z33/U33,4),"")) -> 10.2886 | Z33: =IF(U33<>"",$P33,"") -> 338475.52 | AA33: =IF($F33&"/Día"=AC$9,SUM($G33:$H33),"") | AB33: =IF(AA33<>"",$O33,"") | AC33: =IF($F33&"/Día"=AC$9,ROUND(AA33/$W$1,1),"") | AD33: =IF(AA33=0,0,IF($F33&"/Día"=AC$9,ROUND(AB33/AA33,4),"")) | AE33: =IF(AA33=0,0,IF($F33&"/Día"=AC$9,ROUND(AF33/AA33,4),"")) | AF33: =IF(AA33<>"",$P33,"")
A34: - | B34: Z-6 | C34: Licencia | D34: Quincena | E34: F2 | F34: MM BTU | O34: =ROUND(G34*I34,2)+ROUND(H34*J34,2)-K34-L34-M34-N34 -> 0 | P34: =ROUND(18.75%*O34,2) -> 0 | Q34: =ROUND($O34*R34,2) -> 0 | R34: 0.15 | S34: =ROUND($O34*T34,2) -> 0 | T34: 0.0375
A35: - | B35: Ajustes meses anteriores (1) | O35: =O440 -> -23593.12 | P35: =P440 -> -4423.71 | Q35: =Q440 -> -3538.97 | S35: =S440 -> -884.74 | U35: =IF($F35&"/Día"=W$9,SUM($G35:$H35),"") | V35: =IF(U35<>"",$O35,"") | W35: =IF($F35&"/Día"=W$9,ROUND(U35/$W$1,1),"") | X35: =IF(U35=0,0,IF($F35&"/Día"=W$9,ROUND(V35/U35,4),"")) | Y35: =IF(U35=0,0,IF($F35&"/Día"=W$9,ROUND(Z35/U35,4),"")) | Z35: =IF(U35<>"",$P35,"") | AA35: =IF($F35&"/Día"=AC$9,SUM($G35:$H35),"") | AB35: =IF(AA35<>"",$O35,"") | AC35: =IF($F35&"/Día"=AC$9,ROUND(AA35/$W$1,1),"") | AD35: =IF(AA35=0,0,IF($F35&"/Día"=AC$9,ROUND(AB35/AA35,4),"")) | AE35: =IF(AA35=0,0,IF($F35&"/Día"=AC$9,ROUND(AF35/AA35,4),"")) | AF35: =IF(AA35<>"",$P35,"")
B36: Subtotal | C36: =TEXT(A$9,)&" US$" -> Piura / Tumbes US$ | O36: =SUM(O10:O35) -> 68652601 | P36: =SUM(P10:P35) -> 12872363 | Q36: =SUM(Q10:Q35) -> 10293008 | S36: =SUM(S10:S35) -> 2579354.8 | U36: =SUM(U10:U35) -> 1220558 | V36: =SUM(V10:V35) -> 65270657 | W36: =SUM(W10:W35) -> 40685.3 | X36: =ROUND(V36/U36,4) -> 53.4761 | Y36: =ROUND(Z36/U36,4) -> 10.0268 | Z36: =SUM(Z10:Z35) -> 12238248 | AA36: =SUM(AA10:AA35) -> 1390487.6 | AB36: =SUM(AB10:AB35) -> 3405537.7 | AC36: =SUM(AC10:AC35) -> 46349.6 | AD36: =ROUND(AB36/AA36,4) -> 2.4492 | AE36: =ROUND(AF36/AA36,4) -> 0.4592 | AF36: =SUM(AF10:AF35) -> 638538.32 | AG36: =P36-Z36-AF36 -> -4423.71
C37: =TEXT(A$9,)&" S/." -> Piura / Tumbes S/. | P37: =ROUND($F$1*P36,2) -> 0 | Q37: =ROUND($F$1*Q36,2) -> 0 | S37: =ROUND($F$1*S36,2) -> 0
A38: Provincia Puerto Inca Huanuco | Q38: Puerto Inca
A39: - | B39: 31-D | C39: Licencia | D39: Quincena | E39: F2 | F39: Bls | N39: 1099.45 | O39: =ROUND(G39*I39,2)+ROUND(H39*J39,2)-K39-L39-M39-N39 -> -1099.45 | P39: =ROUND(15%*O39,2) -> -164.92 | Q39: =ROUND($O39*R39,2) -> -164.92 | R39: 0.15 | U39: =IF($F39&"/Día"=W$9,SUM($G39:$H39),"") -> 0 | V39: =IF(U39<>"",$O39,"") -> -1099.45 | W39: =IF($F39&"/Día"=W$9,ROUND(U39/$W$1,1),"") -> 0 | X39: =IF(U39=0,0,IF($F39&"/Día"=W$9,ROUND(V39/U39,4),"")) -> 0 | Y39: =IF(U39=0,0,IF($F39&"/Día"=W$9,ROUND(Z39/U39,4),"")) -> 0 | Z39: =IF(U39<>"",$P39,"") -> -164.92 | AA39: =IF($F39&"/Día"=AC$9,SUM($G39:$H39),"") | AB39: =IF(AA39<>"",$O39,"") | AC39: =IF($F39&"/Día"=AC$9,ROUND(AA39/$W$1,1),"") | AD39: =IF(AA39=0,0,IF($F39&"/Día"=AC$9,ROUND(AB39/AA39,4),"")) | AE39: =IF(AA39=0,0,IF($F39&"/Día"=AC$9,ROUND(AF39/AA39,4),"")) | AF39: =IF(AA39<>"",$P39,"")
A40: - | B40: 131 | C40: Licencia | D40: Quincena | E40: F2 | F40: Bls | G40: 44053 | H40: 44299 | I40: 65.1058 | J40: 68.7299 | N40: 9334.62 | O40: =ROUND(G40*I40,2)+ROUND(H40*J40,2)-K40-L40-M40-N40 -> 5903437 | P40: =ROUND(15%*O40,2) -> 885515.55 | Q40: =ROUND($O40*R40,2) -> 885515.55 | R40: 0.15 | U40: =IF($F40&"/Día"=W$9,SUM($G40:$H40),"") -> 88352 | V40: =IF(U40<>"",$O40,"") -> 5903437 | W40: =IF($F40&"/Día"=W$9,ROUND(U40/$W$1,1),"") -> 2945.1 | X40: =IF(U40=0,0,IF($F40&"/Día"=W$9,ROUND(V40/U40,4),"")) -> 66.8172 | Y40: =IF(U40=0,0,IF($F40&"/Día"=W$9,ROUND(Z40/U40,4),"")) -> 10.0226 | Z40: =IF(U40<>"",$P40,"") -> 885515.55 | AA40: =IF($F40&"/Día"=AC$9,SUM($G40:$H40),"") | AB40: =IF(AA40<>"",$O40,"") | AC40: =IF($F40&"/Día"=AC$9,ROUND(AA40/$W$1,1),"") | AD40: =IF(AA40=0,0,IF($F40&"/Día"=AC$9,ROUND(AB40/AA40,4),"")) | AE40: =IF(AA40=0,0,IF($F40&"/Día"=AC$9,ROUND(AF40/AA40,4),"")) | AF40: =IF(AA40<>"",$P40,"")
A41: - | B41: Ajustes meses anteriores (2) | O41: =O442 -> 147042.22 | P41: =P442 -> 22056.33 | Q41: =Q442 -> 22056.33 | U41: =IF($F41&"/Día"=W$9,SUM($G41:$H41),"") | V41: =IF(U41<>"",$O41,"") | W41: =IF($F41&"/Día"=W$9,ROUND(U41/$W$1,1),"") | X41: =IF(U41=0,0,IF($F41&"/Día"=W$9,ROUND(V41/U41,4),"")) | Y41: =IF(U41=0,0,IF($F41&"/Día"=W$9,ROUND(Z41/U41,4),"")) | Z41: =IF(U41<>"",$P41,"") | AA41: =IF($F41&"/Día"=AC$9,SUM($G41:$H41),"") | AB41: =IF(AA41<>"",$O41,"") | AC41: =IF($F41&"/Día"=AC$9,ROUND(AA41/$W$1,1),"") | AD41: =IF(AA41=0,0,IF($F41&"/Día"=AC$9,ROUND(AB41/AA41,4),"")) | AE41: =IF(AA41=0,0,IF($F41&"/Día"=AC$9,ROUND(AF41/AA41,4),"")) | AF41: =IF(AA41<>"",$P41,"")
B42: Subtotal | C42: =TEXT(A$38,)&" US$" -> Provincia Puerto Inca Huanuco US$ | O42: =SUM(O39:O41) -> 6049379.8 | P42: =SUM(P39:P41) -> 907406.96 | Q42: =SUM(Q39:Q41) -> 907406.96 | S42: =SUM(S39:S41) -> 0 | U42: =SUM(U39:U41) -> 88352 | V42: =SUM(V39:V41) -> 5902337.6 | W42: =SUM(W39:W41) -> 2945.1 | X42: =ROUND(V42/U42,4) -> 66.8048 | Y42: =ROUND(Z42/U42,4) -> 10.0207 | Z42: =SUM(Z39:Z41) -> 885350.63 | AA42: =SUM(AA39:AA41) -> 0 | AB42: =SUM(AB39:AB41) -> 0 | AC42: =SUM(AC39:AC41) -> 0 | AD42: =IF(AA42=0,0,ROUND(AB42/AA42,4)) -> 0 | AE42: =IF(AA42=0,0,ROUND(AF42/AA42,4)) -> 0 | AF42: =SUM(AF39:AF41) -> 0 | AG42: =P42-Z42-AF42 -> 22056.33
C43: =TEXT(A$38,)&" S/." -> Provincia Puerto Inca Huanuco S/. | P43: =ROUND($F$1*P42,2) -> 0 | Q43: =ROUND($F$1*Q42,2) -> 0 | S43: =ROUND($F$1*S42,2) -> 0
A44: Loreto / Ucayali | Q44: Loreto | S44: Ucayali
A45: - | B45: 31-E | C45: Licencia | D45: Mes | E45: F2 | F45: Bls | N45: 3.72 | O45: =ROUND(G45*I45,2)+ROUND(H45*J45,2)-K45-L45-M45-N45 -> -3.72 | P45: =ROUND(18.75%*O45,2) -> -0.7 | Q45: =ROUND($O45*R45,2) -> -0.56 | R45: 0.15 | S45: =ROUND($O45*T45,2) -> -0.14 | T45: 0.0375 | U45: =IF($F45&"/Día"=W$9,SUM($G45:$H45),"") -> 0 | V45: =IF(U45<>"",$O45,"") -> -3.72 | W45: =IF($F45&"/Día"=W$9,ROUND(U45/$W$1,1),"") -> 0 | X45: =IF(U45=0,0,IF($F45&"/Día"=W$9,ROUND(V45/U45,4),"")) -> 0 | Y45: =IF(U45=0,0,IF($F45&"/Día"=W$9,ROUND(Z45/U45,4),"")) -> 0 | Z45: =IF(U45<>"",$P45,"") -> -0.7 | AA45: =IF($F45&"/Día"=AC$9,SUM($G45:$H45),"") | AB45: =IF(AA45<>"",$O45,"") | AC45: =IF($F45&"/Día"=AC$9,ROUND(AA45/$W$1,1),"") | AD45: =IF(AA45=0,0,IF($F45&"/Día"=AC$9,ROUND(AB45/AA45,4),"")) | AE45: =IF(AA45=0,0,IF($F45&"/Día"=AC$9,ROUND(AF45/AA45,4),"")) | AF45: =IF(AA45<>"",$P45,"")
A46: - | B46: 192 | C46: Servicios | D46: Mes | E46: F1 | F46: Bls | H46: 258757 | J46: 56.3849 | M46: 11586.45 | N46: 10503.2 | O46: =ROUND(G46*I46,2)+ROUND(H46*J46,2)-K46-L46-M46-N46 -> 14567898 | P46: =ROUND(18.75%*O46,2) -> 2731480.9 | Q46: =ROUND($O46*R46,2) -> 2185184.7 | R46: 0.15 | S46: =ROUND($O46*T46,2) -> 546296.17 | T46: 0.0375 | U46: =IF($F46&"/Día"=W$9,SUM($G46:$H46),"") -> 258757 | V46: =IF(U46<>"",$O46,"") -> 14567898 | W46: =IF($F46&"/Día"=W$9,ROUND(U46/$W$1,1),"") -> 8625.2 | X46: =IF(U46=0,0,IF($F46&"/Día"=W$9,ROUND(V46/U46,4),"")) -> 56.2995 | Y46: =IF(U46=0,0,IF($F46&"/Día"=W$9,ROUND(Z46/U46,4),"")) -> 10.5562 | Z46: =IF(U46<>"",$P46,"") -> 2731480.9 | AA46: =IF($F46&"/Día"=AC$9,SUM($G46:$H46),"") | AB46: =IF(AA46<>"",$O46,"") | AC46: =IF($F46&"/Día"=AC$9,ROUND(AA46/$W$1,1),"") | AD46: =IF(AA46=0,0,IF($F46&"/Día"=AC$9,ROUND(AB46/AA46,4),"")) | AE46: =IF(AA46=0,0,IF($F46&"/Día"=AC$9,ROUND(AF46/AA46,4),"")) | AF46: =IF(AA46<>"",$P46,"")
A47: - | B47: 8 | C47: Licencia | D47: Quincena | E47: F2 | F47: Bls | G47: 87029 | H47: 95302 | I47: 51.5364 | J47: 55.1583 | N47: 12506.51 | O47: =ROUND(G47*I47,2)+ROUND(H47*J47,2)-K47-L47-M47-N47 -> 9729351.2 | P47: =ROUND(18.75%*O47,2) -> 1824253.3 | Q47: =ROUND($O47*R47,2) -> 1459402.7 | R47: 0.15 | S47: =ROUND($O47*T47,2) -> 364850.67 | T47: 0.0375 | U47: =IF($F47&"/Día"=W$9,SUM($G47:$H47),"") -> 182331 | V47: =IF(U47<>"",$O47,"") -> 9729351.2 | W47: =IF($F47&"/Día"=W$9,ROUND(U47/$W$1,1),"") -> 6077.7 | X47: =IF(U47=0,0,IF($F47&"/Día"=W$9,ROUND(V47/U47,4),"")) -> 53.3609 | Y47: =IF(U47=0,0,IF($F47&"/Día"=W$9,ROUND(Z47/U47,4),"")) -> 10.0052 | Z47: =IF(U47<>"",$P47,"") -> 1824253.3 | AA47: =IF($F47&"/Día"=AC$9,SUM($G47:$H47),"") | AB47: =IF(AA47<>"",$O47,"") | AC47: =IF($F47&"/Día"=AC$9,ROUND(AA47/$W$1,1),"") | AD47: =IF(AA47=0,0,IF($F47&"/Día"=AC$9,ROUND(AB47/AA47,4),"")) | AE47: =IF(AA47=0,0,IF($F47&"/Día"=AC$9,ROUND(AF47/AA47,4),"")) | AF47: =IF(AA47<>"",$P47,"")
A48: - | B48: 31-B | C48: Licencia | D48: Quincena | E48: F2 | F48: Bls | N48: 4.76 | O48: =ROUND(G48*I48,2)+ROUND(H48*J48,2)-K48-L48-M48-N48 -> -4.76 | P48: =ROUND(18.75%*O48,2) -> -0.89 | Q48: =ROUND($O48*R48,2) -> -0.71 | R48: 0.15 | S48: =ROUND($O48*T48,2) -> -0.18 | T48: 0.0375 | U48: =IF($F48&"/Día"=W$9,SUM($G48:$H48),"") -> 0 | V48: =IF(U48<>"",$O48,"") -> -4.76 | W48: =IF($F48&"/Día"=W$9,ROUND(U48/$W$1,1),"") -> 0 | X48: =IF(U48=0,0,IF($F48&"/Día"=W$9,ROUND(V48/U48,4),"")) -> 0 | Y48: =IF(U48=0,0,IF($F48&"/Día"=W$9,ROUND(Z48/U48,4),"")) -> 0 | Z48: =IF(U48<>"",$P48,"") -> -0.89 | AA48: =IF($F48&"/Día"=AC$9,SUM($G48:$H48),"") | AB48: =IF(AA48<>"",$O48,"") | AC48: =IF($F48&"/Día"=AC$9,ROUND(AA48/$W$1,1),"") | AD48: =IF(AA48=0,0,IF($F48&"/Día"=AC$9,ROUND(AB48/AA48,4),"")) | AE48: =IF(AA48=0,0,IF($F48&"/Día"=AC$9,ROUND(AF48/AA48,4),"")) | AF48: =IF(AA48<>"",$P48,"")
A49: - | B49: 31-C GAS | C49: Licencia | D49: Quincena | E49: F2 | F49: MM BTU | G49: 11653.68 | H49: 45676.72 | I49: 3.7418 | J49: 3.742 | N49: 1170.43 | O49: =ROUND(G49*I49,2)+ROUND(H49*J49,2)-K49-L49-M49-N49 -> 213357.6 | P49: =ROUND(18.75%*O49,2) -> 40004.55 | Q49: =ROUND($O49*R49,2) -> 8000.91 | R49: 0.0375 | S49: =ROUND($O49*T49,2) -> 32003.64 | T49: 0.15 | U49: =IF($F49&"/Día"=W$9,SUM($G49:$H49),"") | V49: =IF(U49<>"",$O49,"") | W49: =IF($F49&"/Día"=W$9,ROUND(U49/$W$1,1),"") | X49: =IF(U49=0,0,IF($F49&"/Día"=W$9,ROUND(V49/U49,4),"")) | Y49: =IF(U49=0,0,IF($F49&"/Día"=W$9,ROUND(Z49/U49,4),"")) | Z49: =IF(U49<>"",$P49,"") | AA49: =IF($F49&"/Día"=AC$9,SUM($G49:$H49),"") -> 57330.4 | AB49: =IF(AA49<>"",$O49,"") -> 213357.6 | AC49: =IF($F49&"/Día"=AC$9,ROUND(AA49/$W$1,1),"") -> 1911 | AD49: =IF(AA49=0,0,IF($F49&"/Día"=AC$9,ROUND(AB49/AA49,4),"")) -> 3.7215 | AE49: =IF(AA49=0,0,IF($F49&"/Día"=AC$9,ROUND(AF49/AA49,4),"")) -> 0.6978 | AF49: =IF(AA49<>"",$P49,"") -> 40004.55
A50: - | B50: 31-C LGN (*) | C50: Licencia | D50: Quincena | E50: F3 | F50: Bls | G50: 18290 | H50: 18612 | I50: 54.8279 | J50: 56.9789 | N50: 5297.01 | O50: =ROUND(G50*I50,2)+ROUND(H50*J50,2)-K50-L50-M50-N50 -> 2057996.6 | P50: =ROUND(18.75%*O50,2) -> 385874.36 | Q50: =ROUND($O50*R50,2) -> 77174.87 | R50: 0.0375 | S50: =ROUND($O50*T50,2) -> 308699.49 | T50: 0.15 | U50: =IF($F50&"/Día"=W$9,SUM($G50:$H50),"") -> 36902 | V50: =IF(U50<>"",$O50,"") -> 2057996.6 | W50: =IF($F50&"/Día"=W$9,ROUND(U50/$W$1,1),"") -> 1230.1 | X50: =IF(U50=0,0,IF($F50&"/Día"=W$9,ROUND(V50/U50,4),"")) -> 55.7692 | Y50: =IF(U50=0,0,IF($F50&"/Día"=W$9,ROUND(Z50/U50,4),"")) -> 10.4567 | Z50: =IF(U50<>"",$P50,"") -> 385874.36 | AA50: =IF($F50&"/Día"=AC$9,SUM($G50:$H50),"") | AB50: =IF(AA50<>"",$O50,"") | AC50: =IF($F50&"/Día"=AC$9,ROUND(AA50/$W$1,1),"") | AD50: =IF(AA50=0,0,IF($F50&"/Día"=AC$9,ROUND(AB50/AA50,4),"")) | AE50: =IF(AA50=0,0,IF($F50&"/Día"=AC$9,ROUND(AF50/AA50,4),"")) | AF50: =IF(AA50<>"",$P50,"")
A51: - | B51: 31-C COND | C51: Licencia | D51: Quincena | E51: F2 | F51: Bls | O51: =ROUND(G51*I51,2)+ROUND(H51*J51,2)-K51-L51-M51-N51 -> 0 | P51: =ROUND(18.75%*O51,2) -> 0 | Q51: =ROUND($O51*R51,2) -> 0 | R51: 0.0375 | S51: =ROUND($O51*T51,2) -> 0 | T51: 0.15 | U51: =IF($F51&"/Día"=W$9,SUM($G51:$H51),"") -> 0 | V51: =IF(U51<>"",$O51,"") -> 0 | W51: =IF($F51&"/Día"=W$9,ROUND(U51/$W$1,1),"") -> 0 | X51: =IF(U51=0,0,IF($F51&"/Día"=W$9,ROUND(V51/U51,4),"")) -> 0 | Y51: =IF(U51=0,0,IF($F51&"/Día"=W$9,ROUND(Z51/U51,4),"")) -> 0 | Z51: =IF(U51<>"",$P51,"") -> 0 | AA51: =IF($F51&"/Día"=AC$9,SUM($G51:$H51),"") | AB51: =IF(AA51<>"",$O51,"") | AC51: =IF($F51&"/Día"=AC$9,ROUND(AA51/$W$1,1),"") | AD51: =IF(AA51=0,0,IF($F51&"/Día"=AC$9,ROUND(AB51/AA51,4),"")) | AE51: =IF(AA51=0,0,IF($F51&"/Día"=AC$9,ROUND(AF51/AA51,4),"")) | AF51: =IF(AA51<>"",$P51,"")
A52: - | B52: 102 | C52: Licencia | D52: Quincena | E52: F2 | F52: Bls | O52: =ROUND(G52*I52,2)+ROUND(H52*J52,2)-K52-L52-M52-N52 -> 0 | P52: =ROUND(18.75%*O52,2) -> 0 | Q52: =P52-S52 -> 0 | R52: 0.15 | S52: =ROUND($O52*T52,2) -> 0 | T52: 0.0375 | U52: =IF($F52&"/Día"=W$9,SUM($G52:$H52),"") -> 0 | V52: =IF(U52<>"",$O52,"") -> 0 | W52: =IF($F52&"/Día"=W$9,ROUND(U52/$W$1,1),"") -> 0 | X52: =IF(U52=0,0,IF($F52&"/Día"=W$9,ROUND(V52/U52,4),"")) -> 0 | Y52: =IF(U52=0,0,IF($F52&"/Día"=W$9,ROUND(Z52/U52,4),"")) -> 0 | Z52: =IF(U52<>"",$P52,"") -> 0 | AA52: =IF($F52&"/Día"=AC$9,SUM($G52:$H52),"") | AB52: =IF(AA52<>"",$O52,"") | AC52: =IF($F52&"/Día"=AC$9,ROUND(AA52/$W$1,1),"") | AD52: =IF(AA52=0,0,IF($F52&"/Día"=AC$9,ROUND(AB52/AA52,4),"")) | AE52: =IF(AA52=0,0,IF($F52&"/Día"=AC$9,ROUND(AF52/AA52,4),"")) | AF52: =IF(AA52<>"",$P52,"")
A53: - | B53: 95 | C53: Licencia | D53: Quincena | E53: F2 | F53: Bls | O53: =ROUND(G53*I53,2)+ROUND(H53*J53,2)-K53-L53-M53-N53 -> 0 | P53: =ROUND(18.75%*O53,2) -> 0 | Q53: =P53-S53 -> 0 | R53: 0.15 | S53: =ROUND($O53*T53,2) -> 0 | T53: 0.0375 | U53: =IF($F53&"/Día"=W$9,SUM($G53:$H53),"") -> 0 | V53: =IF(U53<>"",$O53,"") -> 0 | W53: =IF($F53&"/Día"=W$9,ROUND(U53/$W$1,1),"") -> 0 | X53: =IF(U53=0,0,IF($F53&"/Día"=W$9,ROUND(V53/U53,4),"")) -> 0 | Y53: =IF(U53=0,0,IF($F53&"/Día"=W$9,ROUND(Z53/U53,4),"")) -> 0 | Z53: =IF(U53<>"",$P53,"") -> 0 | AA53: =IF($F53&"/Día"=AC$9,SUM($G53:$H53),"") | AB53: =IF(AA53<>"",$O53,"") | AC53: =IF($F53&"/Día"=AC$9,ROUND(AA53/$W$1,1),"") | AD53: =IF(AA53=0,0,IF($F53&"/Día"=AC$9,ROUND(AB53/AA53,4),"")) | AE53: =IF(AA53=0,0,IF($F53&"/Día"=AC$9,ROUND(AF53/AA53,4),"")) | AF53: =IF(AA53<>"",$P53,"")
A54: - | B54: 67 | C54: Licencia | D54: Quincena | E54: F2 | F54: Bls | O54: =ROUND(G54*I54,2)+ROUND(H54*J54,2)-K54-L54-M54-N54 -> 0 | P54: =ROUND(18.75%*O54,2) -> 0 | Q54: =P54-S54 -> 0 | R54: 0.15 | S54: =ROUND($O54*T54,2) -> 0 | T54: 0.0375 | U54: =IF($F54&"/Día"=W$9,SUM($G54:$H54),"") -> 0 | V54: =IF(U54<>"",$O54,"") -> 0 | W54: =IF($F54&"/Día"=W$9,ROUND(U54/$W$1,1),"") -> 0 | X54: =IF(U54=0,0,IF($F54&"/Día"=W$9,ROUND(V54/U54,4),"")) -> 0 | Y54: =IF(U54=0,0,IF($F54&"/Día"=W$9,ROUND(Z54/U54,4),"")) -> 0 | Z54: =IF(U54<>"",$P54,"") -> 0 | AA54: =IF($F54&"/Día"=AC$9,SUM($G54:$H54),"") | AB54: =IF(AA54<>"",$O54,"") | AC54: =IF($F54&"/Día"=AC$9,ROUND(AA54/$W$1,1),"") | AD54: =IF(AA54=0,0,IF($F54&"/Día"=AC$9,ROUND(AB54/AA54,4),"")) | AE54: =IF(AA54=0,0,IF($F54&"/Día"=AC$9,ROUND(AF54/AA54,4),"")) | AF54: =IF(AA54<>"",$P54,"")
A55: - | B55: Ajustes meses anteriores (3) | O55: =O447 -> 172254.86 | P55: =P447 -> 32297.79 | Q55: =Q447 -> 25838.23 | S55: =S447 -> 6459.56 | U55: =IF($F55&"/Día"=W$9,SUM($G55:$H55),"") | V55: =IF(U55<>"",$O55,"") | W55: =IF($F55&"/Día"=W$9,ROUND(U55/$W$1,1),"") | X55: =IF(U55=0,0,IF($F55&"/Día"=W$9,ROUND(V55/U55,4),"")) | Y55: =IF(U55=0,0,IF($F55&"/Día"=W$9,ROUND(Z55/U55,4),"")) | Z55: =IF(U55<>"",$P55,"") | AA55: =IF($F55&"/Día"=AC$9,SUM($G55:$H55),"") | AB55: =IF(AA55<>"",$O55,"") | AC55: =IF($F55&"/Día"=AC$9,ROUND(AA55/$W$1,1),"") | AD55: =IF(AA55=0,0,IF($F55&"/Día"=AC$9,ROUND(AB55/AA55,4),"")) | AE55: =IF(AA55=0,0,IF($F55&"/Día"=AC$9,ROUND(AF55/AA55,4),"")) | AF55: =IF(AA55<>"",$P55,"")
B56: Subtotal | C56: =TEXT(A$44,)&" US$" -> Loreto / Ucayali US$ | O56: =SUM(O45:O55) -> 26740850 | P56: =SUM(P45:P55) -> 5013909.3 | Q56: =SUM(Q45:Q55) -> 3755600.1 | S56: =SUM(S45:S55) -> 1258309.2 | U56: =SUM(U45:U55) -> 477990 | V56: =SUM(V45:V55) -> 26355237 | W56: =SUM(W45:W55) -> 15933 | X56: =ROUND(V56/U56,4) -> 55.1376 | Y56: =ROUND(Z56/U56,4) -> 10.3383 | Z56: =SUM(Z45:Z55) -> 4941607 | AA56: =SUM(AA45:AA55) -> 57330.4 | AB56: =SUM(AB45:AB55) -> 213357.6 | AC56: =SUM(AC45:AC55) -> 1911 | AD56: =ROUND(AB56/AA56,4) -> 3.7215 | AE56: =ROUND(AF56/AA56,4) -> 0.6978 | AF56: =SUM(AF45:AF55) -> 40004.55 | AG56: =P56-Z56-AF56 -> 32297.79
C57: =TEXT(A$44,)&" S/." -> Loreto / Ucayali S/. | P57: =ROUND($F$1*P56,2) -> 0 | Q57: =ROUND($F$1*Q56,2) -> 0 | S57: =ROUND($F$1*S56,2) -> 0
A58: Cusco | P58: V. Regalías | Q58: Cusco
A59: - | B59: 88 LGN | C59: Licencia | D59: Quincena | E59: F4 | F59: Bls | G59: 704947 | H59: 757358 | I59: 40.6421 | J59: 44.0333 | O59: =G59*I59+H59*J59 -> 61999498 | P59: =ROUND(37.24%*(G59*I59+H59*J59),2) -> 23088613 | Q59: =ROUND(R59*P59,2) -> 11544307 | R59: 0.5 | U59: =IF($F59&"/Día"=W$9,SUM($G59:$H59),"") -> 1462305 | V59: =IF(U59<>"",$O59,"") -> 61999498 | W59: =IF($F59&"/Día"=W$9,ROUND(U59/$W$1,1),"") -> 48743.5 | X59: =IF(U59=0,0,IF($F59&"/Día"=W$9,ROUND(V59/U59,4),"")) -> 42.3985 | Y59: =IF(U59=0,0,IF($F59&"/Día"=W$9,ROUND(Z59/U59,4),"")) -> 7.8946 | Z59: =IF(U59<>"",$Q59,"") -> 11544307 | AA59: =IF($F59&"/Día"=AC$9,SUM($G59:$H59),"") | AB59: =IF(AA59<>"",$O59,"") | AC59: =IF($F59&"/Día"=AC$9,ROUND(AA59/$W$1,1),"") | AD59: =IF(AA59=0,0,IF($F59&"/Día"=AC$9,ROUND(AB59/AA59,4),"")) | AE59: =IF(AA59=0,0,IF($F59&"/Día"=AC$9,ROUND(AF59/AA59,4),"")) | AF59: =IF(AA59<>"",$Q59,"")
A60: - | B60: 88 GAS | C60: Licencia | D60: Quincena | E60: F4 | F60: MM BTU | G60: 7520607 | H60: 8539048.7 | I60: 2.0621 | J60: 2.0621 | O60: =G60*I60+H60*J60 -> 33116616 | P60: =ROUND(37.24%*(G60*I60+H60*J60),2) -> 12332628 | Q60: =ROUND(R60*P60,2) -> 6166313.9 | R60: 0.5 | U60: =IF($F60&"/Día"=W$9,SUM($G60:$H60),"") | V60: =IF(U60<>"",$O60,"") | W60: =IF($F60&"/Día"=W$9,ROUND(U60/$W$1,1),"") | X60: =IF(U60=0,0,IF($F60&"/Día"=W$9,ROUND(V60/U60,4),"")) | Y60: =IF(U60=0,0,IF($F60&"/Día"=W$9,ROUND(Z60/U60,4),"")) | Z60: =IF(U60<>"",$Q60,"") | AA60: =IF($F60&"/Día"=AC$9,SUM($G60:$H60),"") -> 16059656 | AB60: =IF(AA60<>"",$O60,"") -> 33116616 | AC60: =IF($F60&"/Día"=AC$9,ROUND(AA60/$W$1,1),"") -> 535321.9 | AD60: =IF(AA60=0,0,IF($F60&"/Día"=AC$9,ROUND(AB60/AA60,4),"")) -> 2.0621 | AE60: =IF(AA60=0,0,IF($F60&"/Día"=AC$9,ROUND(AF60/AA60,4),"")) -> 0.384 | AF60: =IF(AA60<>"",$Q60,"") -> 6166313.9
A61: - | B61: 88 GAS -Mlocal | C61: Licencia | D61: Quincena | E61: F4 | F61: MM BTU | G61: 30736.478 | H61: 31362.119 | I61: 2.8684 | J61: 2.8684 | O61: =G61*I61+H61*J61 -> 178123.62 | P61: =ROUND(37.24%*O61,2) -> 66333.23 | Q61: =ROUND(R61*P61,2) -> 33166.62 | R61: 0.5 | U61: =IF($F61&"/Día"=W$9,SUM($G61:$H61),"") | V61: =IF(U61<>"",$O61,"") | W61: =IF($F61&"/Día"=W$9,ROUND(U61/$W$1,1),"") | X61: =IF(U61=0,0,IF($F61&"/Día"=W$9,ROUND(V61/U61,4),"")) | Y61: =IF(U61=0,0,IF($F61&"/Día"=W$9,ROUND(Z61/U61,4),"")) | Z61: =IF(U61<>"",$Q61,"") | AA61: =IF($F61&"/Día"=AC$9,SUM($G61:$H61),"") -> 62098.597 | AB61: =IF(AA61<>"",$O61,"") -> 178123.62 | AC61: =IF($F61&"/Día"=AC$9,ROUND(AA61/$W$1,1),"") -> 2070 | AD61: =IF(AA61=0,0,IF($F61&"/Día"=AC$9,ROUND(AB61/AA61,4),"")) -> 2.8684 | AE61: =IF(AA61=0,0,IF($F61&"/Día"=AC$9,ROUND(AF61/AA61,4),"")) -> 0.5341 | AF61: =IF(AA61<>"",$Q61,"") -> 33166.62
A62: - | B62: 88 GAS -PM | C62: Licencia | D62: Quincena | E62: F4 | F62: MM BTU | G62: 878493.54 | H62: 926493.38 | I62: 1.821 | J62: 2.218 | O62: =G62*I62+H62*J62 -> 3654699.1 | P62: =ROUND(38%*G62*I62,2)+ROUND(38%*H62*J62,2) -> 1388785.6 | Q62: =ROUND(R62*P62,2) -> 694392.82 | R62: 0.5 | U62: =IF($F62&"/Día"=W$9,SUM($G62:$H62),"") | V62: =IF(U62<>"",$O62,"") | W62: =IF($F62&"/Día"=W$9,ROUND(U62/$W$1,1),"") | X62: =IF(U62=0,0,IF($F62&"/Día"=W$9,ROUND(V62/U62,4),"")) | Y62: =IF(U62=0,0,IF($F62&"/Día"=W$9,ROUND(Z62/U62,4),"")) | Z62: =IF(U62<>"",$Q62,"") | AA62: =IF($F62&"/Día"=AC$9,SUM($G62:$H62),"") -> 1804986.9 | AB62: =IF(AA62<>"",$O62,"") -> 3654699.1 | AC62: =IF($F62&"/Día"=AC$9,ROUND(AA62/$W$1,1),"") -> 60166.2 | AD62: =IF(AA62=0,0,IF($F62&"/Día"=AC$9,ROUND(AB62/AA62,4),"")) -> 2.0248 | AE62: =IF(AA62=0,0,IF($F62&"/Día"=AC$9,ROUND(AF62/AA62,4),"")) -> 0.3847 | AF62: =IF(AA62<>"",$Q62,"") -> 694392.82
A63: - | B63: 56 LGN | C63: Licencia | D63: Quincena | E63: F4 | F63: Bls | G63: 419837 | H63: 448419 | I63: 40.6415 | J63: 44.0327 | O63: =G63*I63+H63*J63 -> 36807905 | P63: =ROUND(40%*G63*I63,2)+ROUND(40%*H63*J63,2) -> 14723162 | Q63: =ROUND(R63*P63,2) -> 7361581 | R63: 0.5 | U63: =IF($F63&"/Día"=W$9,SUM($G63:$H63),"") -> 868256 | V63: =IF(U63<>"",$O63,"") -> 36807905 | W63: =IF($F63&"/Día"=W$9,ROUND(U63/$W$1,1),"") -> 28941.9 | X63: =IF(U63=0,0,IF($F63&"/Día"=W$9,ROUND(V63/U63,4),"")) -> 42.3929 | Y63: =IF(U63=0,0,IF($F63&"/Día"=W$9,ROUND(Z63/U63,4),"")) -> 8.4786 | Z63: =IF(U63<>"",$Q63,"") -> 7361581 | AA63: =IF($F63&"/Día"=AC$9,SUM($G63:$H63),"") | AB63: =IF(AA63<>"",$O63,"") | AC63: =IF($F63&"/Día"=AC$9,ROUND(AA63/$W$1,1),"") | AD63: =IF(AA63=0,0,IF($F63&"/Día"=AC$9,ROUND(AB63/AA63,4),"")) | AE63: =IF(AA63=0,0,IF($F63&"/Día"=AC$9,ROUND(AF63/AA63,4),"")) | AF63: =IF(AA63<>"",$Q63,"")
A64: - | B64: 56 GAS | C64: Licencia | D64: Quincena | E64: F4 | F64: MM BTU | G64: 6224075.9 | H64: 6695796.4 | I64: 1.821 | J64: 2.218 | O64: =G64*I64+H64*J64 -> 26185319 | P64: =ROUND(38%*G64*I64,2)+ROUND(38%*H64*J64,2) -> 9950421.1 | Q64: =ROUND(R64*P64,2) -> 4975210.5 | R64: 0.5 | U64: =IF($F64&"/Día"=W$9,SUM($G64:$H64),"") | V64: =IF(U64<>"",$O64,"") | W64: =IF($F64&"/Día"=W$9,ROUND(U64/$W$1,1),"") | X64: =IF(U64=0,0,IF($F64&"/Día"=W$9,ROUND(V64/U64,4),"")) | Y64: =IF(U64=0,0,IF($F64&"/Día"=W$9,ROUND(Z64/U64,4),"")) | Z64: =IF(U64<>"",$Q64,"") | AA64: =IF($F64&"/Día"=AC$9,SUM($G64:$H64),"") -> 12919872 | AB64: =IF(AA64<>"",$O64,"") -> 26185319 | AC64: =IF($F64&"/Día"=AC$9,ROUND(AA64/$W$1,1),"") -> 430662.4 | AD64: =IF(AA64=0,0,IF($F64&"/Día"=AC$9,ROUND(AB64/AA64,4),"")) -> 2.0267 | AE64: =IF(AA64=0,0,IF($F64&"/Día"=AC$9,ROUND(AF64/AA64,4),"")) -> 0.3851 | AF64: =IF(AA64<>"",$Q64,"") -> 4975210.5
A65: - | B65: 56 GAS-Mlocal | C65: Licencia | D65: Quincena | E65: F4 | F65: MM BTU | G65: 249670.41 | H65: 262965.1 | I65: 1.8303 | J65: 1.8303 | O65: =G65*I65+H65*J65 -> 938276.78 | P65: =ROUND(37.24%*(G65*I65+H65*J65),2) -> 349414.27 | Q65: =ROUND(R65*P65,2) -> 174707.14 | R65: 0.5 | U65: =IF($F65&"/Día"=W$9,SUM($G65:$H65),"") | V65: =IF(U65<>"",$O65,"") | W65: =IF($F65&"/Día"=W$9,ROUND(U65/$W$1,1),"") | X65: =IF(U65=0,0,IF($F65&"/Día"=W$9,ROUND(V65/U65,4),"")) | Y65: =IF(U65=0,0,IF($F65&"/Día"=W$9,ROUND(Z65/U65,4),"")) | Z65: =IF(U65<>"",$Q65,"") | AA65: =IF($F65&"/Día"=AC$9,SUM($G65:$H65),"") -> 512635.51 | AB65: =IF(AA65<>"",$O65,"") -> 938276.78 | AC65: =IF($F65&"/Día"=AC$9,ROUND(AA65/$W$1,1),"") -> 17087.9 | AD65: =IF(AA65=0,0,IF($F65&"/Día"=AC$9,ROUND(AB65/AA65,4),"")) -> 1.8303 | AE65: =IF(AA65=0,0,IF($F65&"/Día"=AC$9,ROUND(AF65/AA65,4),"")) -> 0.3408 | AF65: =IF(AA65<>"",$Q65,"") -> 174707.14
A66: - | B66: 57 LGN | C66: Licencia | D66: Quincena | E66: F4 | F66: Bls | G66: 209845 | H66: 225889 | I66: 36.5524 | J66: 39.9458 | O66: =G66*I66+H66*J66 -> 16693655 | P66: =ROUND(G66*I66,2)*6.42%+ROUND(H66*J66,2)*6.59% -> 1087072.3 | Q66: =ROUND(R66*P66,2) -> 543536.15 | R66: 0.5 | U66: =IF($F66&"/Día"=W$9,SUM($G66:$H66),"") -> 435734 | V66: =IF(U66<>"",$O66,"") -> 16693655 | W66: =IF($F66&"/Día"=W$9,ROUND(U66/$W$1,1),"") -> 14524.5 | X66: =IF(U66=0,0,IF($F66&"/Día"=W$9,ROUND(V66/U66,4),"")) -> 38.3116 | Y66: =IF(U66=0,0,IF($F66&"/Día"=W$9,ROUND(Z66/U66,4),"")) -> 1.2474 | Z66: =IF(U66<>"",$Q66,"") -> 543536.15 | AA66: =IF($F66&"/Día"=AC$9,SUM($G66:$H66),"") | AB66: =IF(AA66<>"",$O66,"") | AC66: =IF($F66&"/Día"=AC$9,ROUND(AA66/$W$1,1),"") | AD66: =IF(AA66=0,0,IF($F66&"/Día"=AC$9,ROUND(AB66/AA66,4),"")) | AE66: =IF(AA66=0,0,IF($F66&"/Día"=AC$9,ROUND(AF66/AA66,4),"")) | AF66: =IF(AA66<>"",$Q66,"")
A67: - | B67: 57 GAS | C67: Licencia | D67: Quincena | E67: F4 | F67: MM BTU | G67: 2998626.1 | H67: 3222616.1 | I67: 2.504 | J67: 2.504 | O67: =G67*I67+H67*J67 -> 15577990 | P67: =ROUND(G67*I67,2)*9.47%+ROUND(H67*J67,2)*9.86% -> 1506706.5 | Q67: =ROUND(R67*P67,2) -> 753353.23 | R67: 0.5 | U67: =IF($F67&"/Día"=W$9,SUM($G67:$H67),"") | V67: =IF(U67<>"",$O67,"") | W67: =IF($F67&"/Día"=W$9,ROUND(U67/$W$1,1),"") | X67: =IF(U67=0,0,IF($F67&"/Día"=W$9,ROUND(V67/U67,4),"")) | Y67: =IF(U67=0,0,IF($F67&"/Día"=W$9,ROUND(Z67/U67,4),"")) | Z67: =IF(U67<>"",$Q67,"") | AA67: =IF($F67&"/Día"=AC$9,SUM($G67:$H67),"") -> 6221242.2 | AB67: =IF(AA67<>"",$O67,"") -> 15577990 | AC67: =IF($F67&"/Día"=AC$9,ROUND(AA67/$W$1,1),"") -> 207374.7 | AD67: =IF(AA67=0,0,IF($F67&"/Día"=AC$9,ROUND(AB67/AA67,4),"")) -> 2.504 | AE67: =IF(AA67=0,0,IF($F67&"/Día"=AC$9,ROUND(AF67/AA67,4),"")) -> 0.1211 | AF67: =IF(AA67<>"",$Q67,"") -> 753353.23
A68: - | B68: Ajustes meses anteriores (4) | O68: =O454 -> 2326688.6 | P68: =P454 -> -127757.11 | Q68: =Q454 -> -63878.55 | U68: =IF($F68&"/Día"=W$9,SUM($G68:$H68),"") | V68: =IF(U68<>"",$O68,"") | W68: =IF($F68&"/Día"=W$9,ROUND(U68/$W$1,1),"") | X68: =IF(U68=0,0,IF($F68&"/Día"=W$9,ROUND(V68/U68,4),"")) | Y68: =IF(U68=0,0,IF($F68&"/Día"=W$9,ROUND(Z68/U68,4),"")) | Z68: =IF(U68<>"",$Q68,"") | AA68: =IF($F68&"/Día"=AC$9,SUM($G68:$H68),"") | AB68: =IF(AA68<>"",$O68,"") | AC68: =IF($F68&"/Día"=AC$9,ROUND(AA68/$W$1,1),"") | AD68: =IF(AA68=0,0,IF($F68&"/Día"=AC$9,ROUND(AB68/AA68,4),"")) | AE68: =IF(AA68=0,0,IF($F68&"/Día"=AC$9,ROUND(AF68/AA68,4),"")) | AF68: =IF(AA68<>"",$Q68,"")
B69: Subtotal | C69: =TEXT(A$58,)&" US$" -> Cusco US$ | G69: =SUM(G64:G65) -> 6473746.3 | H69: =SUM(H64:H65) -> 6958761.5 | O69: =SUM(O59:O68) -> 1.9747877e+08 | P69: =SUM(P59:P68) -> 64365379 | Q69: =SUM(Q59:Q68) -> 32182689 | U69: =SUM(U59:U68) -> 2766295 | V69: =SUM(V59:V68) -> 1.1550106e+08 | W69: =SUM(W59:W68) -> 92209.9 | X69: =ROUND(V69/U69,4) -> 41.753 | Y69: =ROUND(Z69/U69,4) -> 7.0309 | Z69: =SUM(Z59:Z68) -> 19449424 | AA69: =SUM(AA59:AA68) -> 37580491 | AB69: =SUM(AB59:AB68) -> 79651024 | AC69: =SUM(AC59:AC68) -> 1252683.1 | AD69: =ROUND(AB69/AA69,4) -> 2.1195 | AE69: =ROUND(AF69/AA69,4) -> 0.3405 | AF69: =SUM(AF59:AF68) -> 12797144 | AG69: =Q69-Z69-AF69 -> -63878.55
C70: =TEXT(A$58,)&" S/." -> Cusco S/. | G70: =SUMPRODUCT(I64:I65,G64:G65)/SUM(G64:G65) -> 1.8213587 | H70: =SUMPRODUCT(J64:J65,H64:H65)/SUM(H64:H65) -> 2.2033492 | J70: =+N70+M70 -> 0 | Q70: =Q69*F1 -> 0
A71: Total General | G71: =G69*G70 -> 11791014 | H71: =H69*H70 -> 15332581 | I71: =H71+G71 -> 27123595 | J71: =O64+O65 -> 27123595 | K71: =I71-J71 -> 0 | M71: =SUM(M10:M68) -> 11586.45 | N71: =SUM(N10:N68) -> 77732.83 | O71: =O36+O42+O56+O69 -> 2.989216e+08 | P71: =Q69+P56+P42+P36 -> 50976368 | Q71: =Q70+P57+P43+P37 -> 0 | U71: =U36+U42+U56+U69 -> 4553195 | V71: =V36+V42+V56+V69 -> 2.1302929e+08 | W71: =W36+W42+W56+W69 -> 151773.3 | X71: =ROUND(V71/U71,4) -> 46.7868 | Y71: =ROUND(Z71/U71,4) -> 8.2392 | Z71: =Z36+Z42+Z56+Z69 -> 37514629 | AA71: =AA36+AA42+AA56+AA69 -> 39028309 | AB71: =AB36+AB42+AB56+AB69 -> 83269920 | AC71: =AC36+AC42+AC56+AC69 -> 1300943.7 | AD71: =ROUND(AB71/AA71,4) -> 2.1336 | AE71: =ROUND(AF71/AA71,4) -> 0.3453 | AF71: =AF36+AF42+AF56+AF69 -> 13475687 | AG71: =P71-Z71-AF71 -> -13948.14
A73: (*) | B73: Determinación de Canasta de los Líquidos de Gas Natural (VLGNF) | H73: = ( VC * %P + (PB - TF - TT) * (1 - %P)) | O73: =120853382.49+139352381.96+36326849.05-6337.84-11586.45-77732.83+2622270.38 -> 2.9905923e+08 | U73: Regalía 1Q | V73: =6376757.84-V80 -> 5654249 | W73: =+P36 -> 12872363 | X73: Piura / Tumbes
B74: Simbolo | C74: Descripcion | E74: 1ra. Q | F74: 2da. Q | H74: 1ra. Q | U74: Regalía 2Q | V74: =6872699.93-V83 -> 6177558.7 | W74: =+P56 -> 5013909.3 | X74: Loreto / Ucayali
B75: VC | C75: Canasta de Petróleo | H75: ="= ("&TEXT(E75,"0.0000")&" * "&TEXT(E78,"0.00%")&" + ("&TEXT(E76,"0.0000")&" - "&TEXT(E77,"0.0000")&" - "&TEXT(E80,"0.0000")&") * (1 - "&TEXT(E78,"0.00%")&"))" -> = (0.0000 * 0.00% + (0.0000 - 0.0000 - 0.0000) * (1 - 0.00%)) | O75: =+O71-O73 -> -137624.78 | U75: Servicios | V75: 6805097.1 | W75: =+P42 -> 907406.96 | X75: Huanuco
B76: PB | C76: Precio del GLP | H76: =((85.98%*E75+4.4221)*E78+(E76-E77-E80)*(1-E78)) -> 0 | U76: Otras quinc. | V76: =16534.58+15763.21+22056.33 -> 54354.12
B77: TF | C77: Tarifa de Fraccionam. | O77: =32320129.05+1807524.68+1379621.36+920500.01-100926.05 -> 36326849 | V77: =SUM(V73:V76) -> 18691259 | W77: =SUM(W73:W75) -> 18793679 | X77: =V77-W77 -> -102420.03 | Z77: Maple 31-D | AA77: 1Q. Abril
B78: %P | C78: % Contenido Pentanos | H78: 2da. Q | O78: 2622270.4 | U78: Lote 56 1Q | V78: 5651197.2 | Z78: Regalias no pagadas
B79: QLGNF | C79: Volumen de LGN | H79: ="= ("&TEXT(F75,"0.0000")&" * "&TEXT(F78,"0.00%")&" + ("&TEXT(F76,"0.0000")&" - "&TEXT(F77,"0.0000")&" - "&TEXT(F80,"0.0000")&") * (1 - "&TEXT(F78,"0.00%")&"))" -> = (0.0000 * 0.00% + (0.0000 - 0.0000 - 0.0000) * (1 - 0.00%)) | O79: =+O78-O75 -> 2759895.2 | U79: Lote 88 1Q | V79: 8360344.3 | Z79: V. Producción | AA79: Regalías | AB79: Canon/ Particip.
B80: TT | C80: Tarifa de Transporte | H80: =((85.98%*F75+4.4221)*F78+(F76-F77-F80)*(1-F78)) -> 0 | U80: Lote 57 1Q | V80: 722508.82 | Z80: 137745.71 | AA80: 41323.71 | AB80: =+Z80*15% -> 20661.856
U81: Lote 56 2Q | V81: 6860381.4
U82: Lote 88 2Q | V82: 9893093.8
A83: ="AJUSTES PARA "&UPPER(TEXT(E1,"MMMMMMM YYYY")) -> AJUSTES PARA ABRIL 2018 | U83: Lote 57 2Q | V83: 695141.22
V84: =SUM(V78:V83) -> 32182667 | W84: =Q69 -> 32182689 | X84: =V84-W84 -> -22.78
A85: (4) | B85: Ajuste correspondiente de Febrero 2018 (Reporte de Regalía 1ra. Quincena de Marzo 2018) - Liq. 1196
A86: Cusco | D86: Período | E86: Fórmula | F86: Unidades | G86: 1ra. Q | H86: 2da. Q / Mes | I86: 1ra. Q | J86: 2da. Q / Mes | K86: Flete Marítimo | L86: Comercialización | M86: Oleoducto | N86: Fiscalización | O86: Valor Producción | P86: V. Regalías | Q86: Cuzco | V86: =+V73+V78+V79+V80 -> 20388299
A87: - | B87: 56 GAS-Mlocal | C87: Licencia | D87: Calculo Efectuado | F87: MM BTU | G87: 256658.83 | H87: 220308.01 | I87: 1.8294 | J87: 1.8294 | O87: =G87*I87+H87*J87 -> 872563.15 | P87: =ROUND(37.24%*(G87*I87+H87*J87),2) -> 324942.52 | Q87: =ROUND(R87*P87,2) -> 162471.26 | R87: 0.5 | V87: =+V74+V81+V82+V83 -> 23626175
A88: - | B88: =B87 -> 56 GAS-Mlocal | C88: Licencia | D88: Modificación | F88: =F87 -> MM BTU | G88: =+G87 -> 256658.83 | H88: =+H87 -> 220308.01 | I88: 1.8303 | J88: 1.8303 | O88: =G88*I88+H88*J88 -> 872992.42 | P88: =ROUND(37.24%*(G88*I88+H88*J88),2) -> 325102.38 | Q88: =ROUND(R88*P88,2) -> 162551.19 | R88: 0.5 | V88: =+V75 -> 6805097.1
B89: Ajuste | G89: =G88-G87 -> 0 | H89: =H88-H87 -> 0 | I89: =I88-I87 -> 0.0009 | J89: =J88-J87 -> 0.0009 | K89: =K88-K87 -> 0 | L89: =L88-L87 -> 0 | M89: =M88-M87 -> 0 | N89: =N88-N87 -> 0 | ... Q89: =Q88-Q87 -> 79.93 | S89: ok | V89: =SUM(V86:V88) -> 50819571 | X89: =+V89-P71 -> -156796.93
V90: =P71 -> 50976368
B91: Ajuste correspondiente de Febrero 2018 (Reporte de Regalía 1ra. Quincena de Marzo 2018) - Liq. 1196 | V91: =+V89-V90 -> -156796.93
A92: Cusco | D92: Período | E92: Fórmula | F92: Unidades | G92: 1ra. Q | H92: 2da. Q / Mes | I92: 1ra. Q | J92: 2da. Q / Mes | K92: Flete Marítimo | L92: Comercialización | M92: Oleoducto | N92: Fiscalización | O92: Valor Producción | P92: V. Regalías | Q92: Cuzco
A93: - | B93: 57 GAS | C93: Licencia | D93: Quincena | E93: F4 | F93: MM BTU | G93: 3185893.5 | H93: 2793721 | I93: 2.356 | J93: 2.356 | O93: =G93*I93+H93*J93 -> 14087972 | P93: =ROUND(G93*I93,2)*9.8%+ROUND(H93*J93,2)*9.46% -> 1358242.4 | Q93: =ROUND(R93*P93,2) -> 679121.2 | R93: 0.5
A94: - | B94: =B93 -> 57 GAS | C94: Licencia | D94: Modificación | F94: =F93 -> MM BTU | G94: =+G93 -> 3185893.5 | H94: =+H93 -> 2793721 | I94: 2.504 | J94: 2.504 | O94: =G94*I94+H94*J94 -> 14972955 | P94: =ROUND(G94*I94,2)*9.8%+ROUND(H94*J94,2)*9.46% -> 1443564.9 | Q94: =ROUND(R94*P94,2) -> 721782.47 | R94: 0.5
B95: Ajuste | G95: =G94-G93 -> 0 | H95: =H94-H93 -> 0 | I95: =I94-I93 -> 0.148 | J95: =J94-J93 -> 0.148 | K95: =K94-K93 -> 0 | L95: =L94-L93 -> 0 | M95: =M94-M93 -> 0 | N95: =N94-N93 -> 0 | ... Q95: =Q94-Q93 -> 42661.27 | S95: ok
B97: Ajuste correspondiente de Enero 2018 (Reporte de Regalía 1ra. Quincena de Marzo 2018) - Liq. 1196
A98: Cusco | D98: Período | E98: Fórmula | F98: Unidades | G98: 1ra. Q | H98: 2da. Q / Mes | I98: 1ra. Q | J98: 2da. Q / Mes | K98: Flete Marítimo | L98: Comercialización | M98: Oleoducto | N98: Fiscalización | O98: Valor Producción | P98: V. Regalías | Q98: Cuzco
A99: - | B99: 88 GAS | C99: Licencia | D99: Quincena | E99: F4 | F99: MM BTU | G99: 6714461.6 | H99: 6354405.1 | I99: 2.1133 | J99: 2.1133 | O99: =G99*I99+H99*J99 -> 27618436 | P99: =ROUND(37.24%*(G99*I99+H99*J99),2) -> 10285106 | Q99: =ROUND(R99*P99,2) -> 5142552.8 | R99: 0.5
A100: - | B100: =B99 -> 88 GAS | C100: Licencia | D100: Modificación | F100: =F99 -> MM BTU | G100: =+G99 -> 6714461.6 | H100: =+H99 -> 6354405.1 | I100: 2.1038 | J100: 2.1038 | O100: =G100*I100+H100*J100 -> 27494282 | P100: =ROUND(37.24%*(G100*I100+H100*J100),2) -> 10238870 | Q100: =ROUND(R100*P100,2) -> 5119435.2 | R100: 0.5
B101: Ajuste | G101: =G100-G99 -> 0 | H101: =H100-H99 -> 0 | I101: =I100-I99 -> -0.0095 | J101: =J100-J99 -> -0.0095 | K101: =K100-K99 -> 0 | L101: =L100-L99 -> 0 | M101: =M100-M99 -> 0 | N101: =N100-N99 -> 0 | ... Q101: =Q100-Q99 -> -23117.51 | S101: ok
B103: Ajuste correspondiente de Enero 2018 (Reporte de Regalía 1ra. Quincena de Marzo 2018) - Liq. 1196
A104: Cusco | D104: Período | E104: Fórmula | F104: Unidades | G104: 1ra. Q | H104: 2da. Q / Mes | I104: 1ra. Q | J104: 2da. Q / Mes | K104: Flete Marítimo | L104: Comercialización | M104: Oleoducto | N104: Fiscalización | O104: Valor Producción | P104: V. Regalías | Q104: Cuzco
...

Sheet Ene
A1: Período de Cálculo: | E1: 45688 | F1: 3.69
A2: PERUPETRO S.A.
A3: DETERMINACION DEL CANON, SOBRECANON y PARTICIPACION (US$)
A4: Correspondiente a Enero 2025
A5: Tipo de Cambio= 3.690
A7: Localidad | C7: Modalidad de Contrato | D7: Calculo del Canon | F7: Volumen Producción / Venta | I7: Canasta o Valor Venta (US$/Unidad) | K7: Deducción de Gastos para determinación de valor de producción en Punto de Fiscalización (US$) | O7: Valor de la Producción (US$) | P7: Canon y Sobrecanon / Participación (US$)
A8: - Lote | D8: Período | E8: Fórmula | F8: Unidades | G8: 1ra. Q | H8: 2da. Q / Mes | I8: 1ra. Q | J8: 2da. Q / Mes | K8: Flete Marítimo | L8: Comercialización | M8: Oleoducto | N8: Fiscalización | P8: Total | Q8: Localidad 1 | S8: Localidad 2
A9: Piura / Tumbes | Q9: Piura | S9: Tumbes
A10: - | B10: I | C10: Licencia | D10: Quincena | E10: F2 | F10: Bls | G10: 4669 | H10: 12235 | I10: 78.909 | J10: 80.6475 | N10: 79.05 | O10: 1355069.2 | P10: 254075.48 | Q10: 203260.38 | R10: 0.15 | S10: 50815.1 | T10: 0.0375
A11: - | B11: I GAS | C11: Licencia | D11: Quincena | E11: F2 | F11: MM BTU | G11: 46200.457 | H11: 52886.764 | I11: 3.8633 | J11: 3.8633 | N11: 221.34 | O11: 382582.32 | P11: 71734.19 | Q11: 57387.35 | R11: 0.15 | S11: 14346.84 | T11: 0.0375
A12: - | B12: II | C12: Licencia | D12: Quincena | E12: F2 | F12: Bls | G12: 4868 | H12: 5386 | I12: 78.4058 | J12: 78.2365 | N12: 635.56 | O12: 802425.66 | P12: 150454.81 | Q12: 120363.85 | R12: 0.15 | S12: 30090.96 | T12: 0.0375
A13: - | B13: II-GAS | C13: Licencia | D13: Quincena | E13: F2 | F13: MM BTU | G13: 11396.981 | H13: 16566.773 | I13: 2.8114 | J13: 2.8114 | N13: 679.83 | O13: 77937.46 | P13: 14613.27 | Q13: 11690.62 | R13: 0.15 | S13: 2922.65 | T13: 0.0375
A14: - | B14: III | C14: Licencia | D14: Quincena | E14: F2 | F14: Bls | G14: 29174 | H14: 31872 | I14: 78.909 | J14: 80.6475 | N14: 1053.85 | O14: 4871434.4 | P14: 913393.96 | Q14: 730715.17 | R14: 0.15 | S14: 182678.79 | T14: 0.0375
A15: - | B15: III-GAS | C15: Licencia | D15: Quincena | E15: F2 | F15: MM BTU | G15: 8444.6128 | H15: 13057.577 | I15: 3.2 | J15: 3.2 | O15: 68807.01 | P15: 12901.31 | Q15: 10321.05 | R15: 0.15 | S15: 2580.26 | T15: 0.0375
A16: - | B16: IV | C16: Licencia | D16: Quincena | E16: F2 | F16: Bls | G16: 40970 | H16: 44264 | I16: 78.909 | J16: 80.6475 | N16: 1771.63 | O16: 6800911 | P16: 1275170.8 | Q16: 1020136.7 | R16: 0.15 | S16: 255034.16 | T16: 0.0375
A17: - | B17: IV-GAS | C17: Licencia | D17: Quincena | E17: F2 | F17: Bls | G17: 55338.229 | H17: 40417.509 | I17: 3.6086 | J17: 3.6086 | N17: 601.69 | O17: 344942.46 | P17: 64676.71 | Q17: 51741.37 | R17: 0.15 | S17: 12935.34 | T17: 0.0375
A18: - | B18: V | C18: Licencia | D18: Quincena | E18: F2 | F18: Bls | G18: 3925 | H18: 3200 | I18: 78.4158 | J18: 78.2507 | N18: 414.22 | O18: 557770.04 | P18: 104581.88 | Q18: 83665.51 | R18: 0.15 | S18: 20916.38 | T18: 0.0375
A19: - | B19: VI (T) | C19: Licencia | D19: Quincena | E19: F2 | F19: Bls | G19: 20783 | H19: 27532 | I19: 78.909 | J19: 80.6475 | N19: 499.59 | O19: 3859853.1 | P19: 723722.46 | Q19: 578977.97 | R19: 0.15 | S19: 144744.49 | T19: 0.0375
A20: - | B20: VI - GAS | C20: Licencia | D20: Quincena | E20: F2 | F20: MM BTU | G20: 58375.693 | H20: 57555.927 | I20: 3.8449 | J20: 3.8449 | N20: 215.02 | O20: 445530.46 | P20: 83536.96 | Q20: 66829.57 | R20: 0.15 | S20: 16707.39 | T20: 0.0375
A21: - | B21: VII (T) | C21: Licencia | D21: Quincena | E21: F2 | F21: Bls | G21: 14360 | H21: 17820 | I21: 78.4158 | J21: 78.2507 | N21: 246.63 | O21: 2520231.7 | P21: 472543.45 | Q21: 378034.76 | R21: 0.15 | S21: 94508.69 | T21: 0.0375
A22: - | B22: IX | C22: Licencia | D22: Quincena | E22: F2 | F22: Bls | G22: 1515 | H22: 3095 | I22: 78.909 | J22: 80.6475 | N22: 265.61 | O22: 368885.54 | P22: 69166.04 | Q22: 55332.83 | R22: 0.15 | S22: 13833.21 | T22: 0.0375
A23: - | B23: X | C23: Licencia | D23: Quincena | E23: F2 | F23: Bls | G23: 116840 | H23: 127940 | I23: 79.663 | J23: 79.6289 | N23: 1207.9 | O23: 19494338 | P23: 3655188.5 | Q23: 2924150.8 | R23: 0.15 | S23: 731037.69 | T23: 0.0375
A24: - | B24: X-GAS | C24: Licencia | D24: Quincena | E24: F2 | F24: MM BTU | G24: 204250.66 | H24: 226421.16 | I24: 2.9 | J24: 2.9 | N24: 916.99 | O24: 1248031.3 | P24: 234005.87 | Q24: 187204.69 | R24: 0.15 | S24: 46801.17 | T24: 0.0375
A25: - | B25: XV | C25: Licencia | D25: Quincena | E25: F2 | F25: Bls | G25: 286 | H25: 273 | I25: 78.4158 | J25: 78.2507 | N25: 287.74 | O25: 43501.62 | P25: 8156.55 | Q25: 6525.24 | R25: 0.15 | S25: 1631.31 | T25: 0.0375
A26: - | B26: XIII Crudo | C26: Licencia | D26: Quincena | E26: F2 | F26: Bls | G26: 14571 | H26: 15247 | I26: 76.269 | J26: 80.5775 | N26: 2741.44 | O26: 2337139.3 | P26: 438213.62 | Q26: 350570.9 | R26: 0.15 | S26: 87642.72 | T26: 0.0375
A27: - | B27: XIII Gas | C27: Licencia | D27: Quincena | E27: F2 | F27: MM BTU | G27: 407996.3 | H27: 427347.64 | I27: 3.1923192 | J27: 3.3871628 | N27: 1141.48 | O27: 2748809 | P27: 515401.68 | Q27: 412321.35 | R27: 0.15 | S27: 103080.34 | T27: 0.0375
A28: - | B28: XX | C28: Licencia | D28: Quincena | E28: F2 | F28: Bls | G28: 174 | H28: 180 | I28: 78.909 | J28: 80.6475 | N28: 170.75 | O28: 28075.97 | P28: 5264.24 | Q28: 1052.85 | R28: 0.0375 | S28: 4211.4 | T28: 0.15
A29: - | B29: Z1 Crudo | C29: Licencia | D29: Quincena | E29: F2 | F29: Bls | H29: 57356 | J29: 77.8975 | N29: 863.22 | O29: 4467025.8 | P29: 837567.34 | Q29: 167513.47 | R29: 0.0375 | S29: 670053.87 | T29: 0.15
A30: - | B30: Z-69 Crudo | C30: Licencia | D30: Quincena | E30: F2 | F30: Bls | G30: 48651 | H30: 66320 | I30: 78.159 | J30: 78.5075 | N30: 439.52 | O30: 9008691.4 | P30: 1689129.6 | Q30: 1351303.7 | R30: 0.15 | S30: 337825.93 | T30: 0.0375
A31: - | B31: Z-69 Gas | C31: Licencia | D31: Quincena | E31: F2 | F31: MM BTU | G31: 120928.26 | H31: 149821.44 | I31: 2.8377994 | J31: 2.8284847 | N31: 388.92 | O31: 766548.87 | P31: 143727.91 | Q31: 114982.34 | R31: 0.15 | S31: 28745.58 | T31: 0.0375
A32: - | B32: Z-69 Lgn | C32: Licencia | D32: Quincena | E32: F2 | F32: Bls | G32: 10318 | H32: 11016 | I32: 61.4685 | J32: 47.6842 | N32: 423.71 | O32: 1159097.4 | P32: 217330.77 | Q32: 173864.61 | R32: 0.15 | S32: 43466.15 | T32: 0.0375
A33: - | B33: Ajustes meses anteriores (1) | O33: -11688.41 | P33: -2191.58 | Q33: -1753.27 | S33: -438.31
B34: Subtotal | C34: Piura / Tumbes US$ | O34: 63745951 | P34: 11952366 | Q34: 9056193.8 | S34: 2896172.1 | T34: 0
C35: Piura / Tumbes S/. | P35: 44104230 | Q35: 33417355 | S35: 10686875
A36: Provincia Puerto Inca Huanuco | Q36: Puerto Inca
A37: - | B37: 131 | C37: Licencia | D37: Quincena | E37: F2 | F37: Bls | G37: 8116 | H37: 10054 | I37: 67.261 | J37: 67.1331 | N37: 3402.29 | O37: 1217444.2 | P37: 182616.63 | Q37: 182616.63 | R37: 0.15
A38: - | B38: Ajustes meses anteriores (2)
B39: Subtotal | C39: Provincia Puerto Inca Huanuco US$ | O39: 1217444.2 | P39: 182616.63 | Q39: 182616.63 | S39: 0
C40: Provincia Puerto Inca Huanuco S/. | P40: 673855.36 | Q40: 673855.36 | S40: 0
A41: Loreto / Ucayali | Q41: Loreto | S41: Ucayali
A42: - | B42: 8 | C42: Licencia | D42: Quincena | E42: F2 | F42: Bls | G42: 9752 | H42: 16409 | I42: 64.6038 | J42: 65.0821 | N42: 4559.58 | O42: 1693388.9 | P42: 317510.41 | Q42: 254008.33 | R42: 0.15 | S42: 63502.08 | T42: 0.0375
A43: - | B43: 31-C GAS | C43: Licencia | D43: Quincena | E43: F2 | F43: MM BTU | G43: 9951.3265 | H43: 58273.916 | I43: 3.6055 | J43: 3.6059 | N43: 1630.26 | O43: 244379.16 | P43: 45821.09 | Q43: 9164.22 | R43: 0.0375 | S43: 36656.87 | T43: 0.15
A44: - | B44: 31-C LGN (*) | C44: Licencia | D44: Quincena | E44: F3 | F44: Bls | H44: 36 | J44: 65.2656 | N44: 3138.52 | O44: -788.96 | P44: -147.93 | Q44: -29.59 | R44: 0.0375 | S44: -118.34 | T44: 0.15
A45: - | B45: 95 | C45: Licencia | D45: Quincena | E45: F2 | F45: Bls | G45: 335917 | H45: 357171 | I45: 58.262 | J45: 58.3343 | N45: 4562.74 | O45: 40401954 | P45: 7575366.3 | Q45: 6060293.1 | R45: 0.15 | S45: 1515073.3 | T45: 0.0375
A46: - | B46: 67 | C46: Licencia | D46: Quincena | E46: F2 | F46: Bls | O46: 0 | P46: 0 | Q46: 0 | R46: 0.15 | S46: 0 | T46: 0.0375
A47: - | B47: Ajustes meses anteriores (3) | O47: -318742.3 | P47: -59764.18 | Q47: -47811.35 | S47: -11952.83
B48: Subtotal | C48: Loreto / Ucayali US$ | O48: 42020191 | P48: 7878785.7 | Q48: 6275624.7 | S48: 1603161.1
C49: Loreto / Ucayali S/. | P49: 29072719 | Q49: 23157055 | S49: 5915664.3
A50: Cusco | P50: V. Regalías | Q50: Cusco
A51: - | B51: 88 LGN | C51: Licencia | D51: Quincena | E51: F4 | F51: Bls | G51: 696480 | H51: 677278 | I51: 46.9611 | J51: 46.8254 | O51: 64421280 | P51: 23990485 | Q51: 11995242 | R51: 0.5
A52: - | B52: 88 GAS | C52: Licencia | D52: Quincena | E52: F4 | F52: MM BTU | G52: 9514193.3 | H52: 11953698 | I52: 3.0875 | J52: 3.0168 | O52: 65436505 | P52: 24445882 | Q52: 12222941 | R52: 0.5
A53: - | B53: 56 LGN | C53: Licencia | D53: Quincena | E53: F4 | F53: Bls | G53: 153684 | H53: 135325 | I53: 46.9634 | J53: 46.7311 | O53: 13541409 | P53: 5416563.7 | Q53: 2708281.9 | R53: 0.5
A54: - | B54: 56 GAS | C54: Licencia | D54: Quincena | E54: F4 | F54: MM BTU | G54: 4425452.8 | H54: 3816614.5 | I54: 6.248 | J54: 6.088 | O54: 50885779 | P54: 19336596 | Q54: 9668297.9 | R54: 0.5
A55: - | B55: 57 LGN | C55: Licencia | D55: Quincena | E55: F4 | F55: Bls | G55: 220877 | H55: 162482 | I55: 45.9073 | J55: 44.1323 | O55: 17310571 | P55: 1148335.1 | Q55: 574167.57 | R55: 0.5
A56: - | B56: 57 GAS | C56: Licencia | D56: Quincena | E56: F4 | F56: MM BTU | G56: 3777923.7 | H56: 2726026.3 | I56: 5.804 | J56: 5.804 | O56: 37748926 | P56: 4173861.9 | Q56: 2086930.9 | R56: 0.5
A57: - | B57: Ajustes meses anteriores (4) | O57: 15735463 | P57: 2365478.3 | Q57: 1182739.1
B58: Subtotal | C58: Cusco US$ | G58: 4425452.8 | H58: 3816614.5 | O58: 2.6507993e+08 | P58: 80877201 | Q58: 40438601
C59: Cusco S/. | G59: 6.248 | H59: 6.088 | Q59: 1.4921844e+08
A60: Total General | G60: 27650229 | H60: 23235549 | I60: 50885779 | J60: #REF! | K60: #REF! | M60: 0 | N60: 32559.08 | O60: 3.7206352e+08 | P60: 60452369 | Q60: 2.2306924e+08
A62: (*) | B62: Determinación de Canasta de los Líquidos de Gas Natural (VLGNF) | H62: = ( VC * %P + (PB - TF - TT) * (1 - %P)) | I62: = ( VC * %P + (PB - TF - TT) * (1 - %P))
B63: Simbolo | C63: Descripcion | E63: 1ra. Q | F63: 2da. Q | H63: 1ra. Q
B64: VC | C64: Canasta de Petróleo | H64: = (0.0000 * 0.00% + (0.0000 - 0.0000 - 0.0000) * (1 - 0.00%))
B65: PB | C65: Precio del GLP | H65: 0
B66: TF | C66: Tarifa de Fraccionam.
B67: %P | C67: % Contenido Pentanos | H67: 2da. Q
B68: QLGNF | C68: Volumen de LGN | H68: = (0.0000 * 0.00% + (0.0000 - 0.0000 - 0.0000) * (1 - 0.00%))
B69: TT | C69: Tarifa de Transporte | H69: 0

Sheet Ene-2
A1: Período de Cálculo: | E1: 43101 | U1: Días en el mes | W1: =DATE(YEAR(E1),MONTH(E1)+1,1)-DATE(YEAR(E1),MONTH(E1),1) -> 31
A2: PERUPETRO S.A.
A3: DETERMINACION DEL CANON, SOBRECANON y PARTICIPACION (US$)
A4: ="Correspondiente a "&TEXT(E1,"MMMMMMM YYYY") -> Correspondiente a Enero 2018
A5: ="Tipo de Cambio= "&TEXT(F1,"0.000") -> Tipo de Cambio= 0.000
A7: Localidad | C7: Modalidad de Contrato | D7: Calculo del Canon | F7: Volumen Producción / Venta | I7: Canasta o Valor Venta (US$/Unidad) | K7: Deducción de Gastos para determinación de valor de producción en Punto de Fiscalización (US$) | O7: Valor de la Producción (US$) | P7: Canon y Sobrecanon / Participación (US$) | U7: Resumen por Petróleo y Condensados | AA7: Resumen por Gas Natural | AG7: Control
A8: - Lote | D8: Período | E8: Fórmula | F8: Unidades | G8: 1ra. Q | H8: 2da. Q / Mes | I8: 1ra. Q | J8: 2da. Q / Mes | K8: Flete Marítimo | L8: Comercialización | M8: Oleoducto | N8: Fiscalización | P8: Total | Q8: Localidad 1 | S8: Localidad 2 | U8: Producción / Venta | X8: Valor Prod | Y8: Valor Canon | AA8: Producción / Venta | AD8: Valor Prod | AE8: Valor Canon | AG8: Total
A9: Piura / Tumbes | Q9: Piura | S9: Tumbes | U9: Bls/Mes | V9: V P (US$) | W9: Bls/Día | X9: US$/Bl | Y9: US$/Bl | Z9: US$ | AA9: MM BTU/Mes | AB9: V P (US$) | AC9: MM BTU/Día | AD9: US$/MM BTU | AE9: US$/MM BTU | AF9: US$ | AG9: Canon
A10: - | B10: I | C10: Servicios | D10: Mes | E10: F1 | F10: Bls | H10: 24582 | J10: 67.0812 | N10: 683.58 | O10: =ROUND(G10*I10,2)+ROUND(H10*J10,2)-K10-L10-M10-N10 -> 1648306.5 | P10: =ROUND(18.75%*O10,2) -> 309057.47 | Q10: =ROUND($O10*R10,2) -> 247245.97 | R10: 0.15 | S10: =ROUND($O10*T10,2) -> 61811.49 | T10: 0.0375 | U10: =IF($F10&"/Día"=W$9,SUM($G10:$H10),"") -> 24582 | V10: =IF(U10<>"",$O10,"") -> 1648306.5 | W10: =IF($F10&"/Día"=W$9,ROUND(U10/$W$1,1),"") -> 793 | X10: =IF(U10=0,0,IF($F10&"/Día"=W$9,ROUND(V10/U10,4),"")) -> 67.0534 | Y10: =IF(U10=0,0,IF($F10&"/Día"=W$9,ROUND(Z10/U10,4),"")) -> 12.5725 | Z10: =IF(U10<>"",$P10,"") -> 309057.47 | AA10: =IF($F10&"/Día"=AC$9,SUM($G10:$H10),"") | AB10: =IF(AA10<>"",$O10,"") | AC10: =IF($F10&"/Día"=AC$9,ROUND(AA10/$W$1,1),"") | AD10: =IF(AA10=0,0,IF($F10&"/Día"=AC$9,ROUND(AB10/AA10,4),"")) | AE10: =IF(AA10=0,0,IF($F10&"/Día"=AC$9,ROUND(AF10/AA10,4),"")) | AF10: =IF(AA10<>"",$P10,"")
A11: - | B11: I GAS | C11: Servicios | D11: Mes | E11: F1 | F11: MM BTU | H11: 253218.78 | J11: 2.9822 | N11: 1914.05 | O11: =ROUND(G11*I11,2)+ROUND(H11*J11,2)-K11-L11-M11-N11 -> 753235 | P11: =ROUND(18.75%*O11,2) -> 141231.56 | Q11: =ROUND($O11*R11,2) -> 112985.25 | R11: 0.15 | S11: =ROUND($O11*T11,2) -> 28246.31 | T11: 0.0375 | U11: =IF($F11&"/Día"=W$9,SUM($G11:$H11),"") | V11: =IF(U11<>"",$O11,"") | W11: =IF($F11&"/Día"=W$9,ROUND(U11/$W$1,1),"") | X11: =IF(U11=0,0,IF($F11&"/Día"=W$9,ROUND(V11/U11,4),"")) | Y11: =IF(U11=0,0,IF($F11&"/Día"=W$9,ROUND(Z11/U11,4),"")) | Z11: =IF(U11<>"",$P11,"") | AA11: =IF($F11&"/Día"=AC$9,SUM($G11:$H11),"") -> 253218.78 | AB11: =IF(AA11<>"",$O11,"") -> 753235 | AC11: =IF($F11&"/Día"=AC$9,ROUND(AA11/$W$1,1),"") -> 8168.3 | AD11: =IF(AA11=0,0,IF($F11&"/Día"=AC$9,ROUND(AB11/AA11,4),"")) -> 2.9746 | AE11: =IF(AA11=0,0,IF($F11&"/Día"=AC$9,ROUND(AF11/AA11,4),"")) -> 0.5577 | AF11: =IF(AA11<>"",$P11,"") -> 141231.56
A12: - | B12: II | C12: Licencia | D12: Quincena | E12: F2 | F12: Bls | G12: 4562 | H12: 4721 | I12: 64.1613 | J12: 65.1575 | N12: 1764.83 | O12: =ROUND(G12*I12,2)+ROUND(H12*J12,2)-K12-L12-M12-N12 -> 598547.58 | P12: =ROUND(18.75%*O12,2) -> 112227.67 | Q12: =ROUND($O12*R12,2) -> 89782.14 | R12: 0.15 | S12: =ROUND($O12*T12,2) -> 22445.53 | T12: 0.0375 | U12: =IF($F12&"/Día"=W$9,SUM($G12:$H12),"") -> 9283 | V12: =IF(U12<>"",$O12,"") -> 598547.58 | W12: =IF($F12&"/Día"=W$9,ROUND(U12/$W$1,1),"") -> 299.5 | X12: =IF(U12=0,0,IF($F12&"/Día"=W$9,ROUND(V12/U12,4),"")) -> 64.4778 | Y12: =IF(U12=0,0,IF($F12&"/Día"=W$9,ROUND(Z12/U12,4),"")) -> 12.0896 | Z12: =IF(U12<>"",$P12,"") -> 112227.67 | AA12: =IF($F12&"/Día"=AC$9,SUM($G12:$H12),"") | AB12: =IF(AA12<>"",$O12,"") | AC12: =IF($F12&"/Día"=AC$9,ROUND(AA12/$W$1,1),"") | AD12: =IF(AA12=0,0,IF($F12&"/Día"=AC$9,ROUND(AB12/AA12,4),"")) | AE12: =IF(AA12=0,0,IF($F12&"/Día"=AC$9,ROUND(AF12/AA12,4),"")) | AF12: =IF(AA12<>"",$P12,"")
A13: - | B13: II-GAS | C13: Servicios | D13: Mes | E13: F1 | F13: MM BTU | G13: 40281.697 | H13: 44653.33 | I13: 2.55 | J13: 2.55 | N13: 1884.53 | O13: =ROUND(G13*I13,2)+ROUND(H13*J13,2)-K13-L13-M13-N13 -> 214699.79 | P13: =ROUND(18.75%*O13,2) -> 40256.21 | Q13: =ROUND($P13*R13/(R13+T13),2) -> 32204.97 | R13: 0.15 | S13: =P13-Q13 -> 8051.24 | T13: 0.0375 | U13: =IF($F13&"/Día"=W$9,SUM($G13:$H13),"") | V13: =IF(U13<>"",$O13,"") | W13: =IF($F13&"/Día"=W$9,ROUND(U13/$W$1,1),"") | X13: =IF(U13=0,0,IF($F13&"/Día"=W$9,ROUND(V13/U13,4),"")) | Y13: =IF(U13=0,0,IF($F13&"/Día"=W$9,ROUND(Z13/U13,4),"")) | Z13: =IF(U13<>"",$P13,"") | AA13: =IF($F13&"/Día"=AC$9,SUM($G13:$H13),"") -> 84935.027 | AB13: =IF(AA13<>"",$O13,"") -> 214699.79 | AC13: =IF($F13&"/Día"=AC$9,ROUND(AA13/$W$1,1),"") -> 2739.8 | AD13: =IF(AA13=0,0,IF($F13&"/Día"=AC$9,ROUND(AB13/AA13,4),"")) -> 2.5278 | AE13: =IF(AA13=0,0,IF($F13&"/Día"=AC$9,ROUND(AF13/AA13,4),"")) -> 0.474 | AF13: =IF(AA13<>"",$P13,"") -> 40256.21
A14: - | B14: III | C14: Licencia | D14: Quincena | E14: F2 | F14: Bls | G14: 11836 | H14: 12495 | I14: 66.7972 | J14: 67.3179 | N14: 1257.31 | O14: =ROUND(G14*I14,2)+ROUND(H14*J14,2)-K14-L14-M14-N14 -> 1630491.5 | P14: =ROUND(18.75%*O14,2) -> 305717.16 | Q14: =ROUND($O14*R14,2) -> 244573.73 | R14: 0.15 | S14: =ROUND($O14*T14,2) -> 61143.43 | T14: 0.0375 | U14: =IF($F14&"/Día"=W$9,SUM($G14:$H14),"") -> 24331 | V14: =IF(U14<>"",$O14,"") -> 1630491.5 | W14: =IF($F14&"/Día"=W$9,ROUND(U14/$W$1,1),"") -> 784.9 | X14: =IF(U14=0,0,IF($F14&"/Día"=W$9,ROUND(V14/U14,4),"")) -> 67.0129 | Y14: =IF(U14=0,0,IF($F14&"/Día"=W$9,ROUND(Z14/U14,4),"")) -> 12.5649 | Z14: =IF(U14<>"",$P14,"") -> 305717.16 | AA14: =IF($F14&"/Día"=AC$9,SUM($G14:$H14),"") | AB14: =IF(AA14<>"",$O14,"") | AC14: =IF($F14&"/Día"=AC$9,ROUND(AA14/$W$1,1),"") | AD14: =IF(AA14=0,0,IF($F14&"/Día"=AC$9,ROUND(AB14/AA14,4),"")) | AE14: =IF(AA14=0,0,IF($F14&"/Día"=AC$9,ROUND(AF14/AA14,4),"")) | AF14: =IF(AA14<>"",$P14,"")
A15: - | B15: IV | C15: Licencia | D15: Quincena | E15: F2 | F15: Bls | G15: 17378 | H15: 20845 | I15: 66.7972 | J15: 67.3179 | N15: 3247.24 | O15: =ROUND(G15*I15,2)+ROUND(H15*J15,2)-K15-L15-M15-N15 -> 2560796.1 | P15: =ROUND(18.75%*O15,2) -> 480149.27 | Q15: =ROUND($O15*R15,2) -> 384119.42 | R15: 0.15 | S15: =ROUND($O15*T15,2) -> 96029.85 | T15: 0.0375 | U15: =IF($F15&"/Día"=W$9,SUM($G15:$H15),"") -> 38223 | V15: =IF(U15<>"",$O15,"") -> 2560796.1 | W15: =IF($F15&"/Día"=W$9,ROUND(U15/$W$1,1),"") -> 1233 | X15: =IF(U15=0,0,IF($F15&"/Día"=W$9,ROUND(V15/U15,4),"")) -> 66.9962 | Y15: =IF(U15=0,0,IF($F15&"/Día"=W$9,ROUND(Z15/U15,4),"")) -> 12.5618 | Z15: =IF(U15<>"",$P15,"") -> 480149.27 | AA15: =IF($F15&"/Día"=AC$9,SUM($G15:$H15),"") | AB15: =IF(AA15<>"",$O15,"") | AC15: =IF($F15&"/Día"=AC$9,ROUND(AA15/$W$1,1),"") | AD15: =IF(AA15=0,0,IF($F15&"/Día"=AC$9,ROUND(AB15/AA15,4),"")) | AE15: =IF(AA15=0,0,IF($F15&"/Día"=AC$9,ROUND(AF15/AA15,4),"")) | AF15: =IF(AA15<>"",$P15,"")
A16: - | B16: V | C16: Servicios | D16: Mes | E16: F1 | F16: Bls | H16: 2532 | J16: 67.0812 | N16: 1487.58 | O16: =ROUND(G16*I16,2)+ROUND(H16*J16,2)-K16-L16-M16-N16 -> 168362.02 | P16: =ROUND(18.75%*O16,2) -> 31567.88 | Q16: =ROUND($O16*R16,2) -> 25254.3 | R16: 0.15 | S16: =ROUND($O16*T16,2) -> 6313.58 | T16: 0.0375 | U16: =IF($F16&"/Día"=W$9,SUM($G16:$H16),"") -> 2532 | V16: =IF(U16<>"",$O16,"") -> 168362.02 | W16: =IF($F16&"/Día"=W$9,ROUND(U16/$W$1,1),"") -> 81.7 | X16: =IF(U16=0,0,IF($F16&"/Día"=W$9,ROUND(V16/U16,4),"")) -> 66.4937 | Y16: =IF(U16=0,0,IF($F16&"/Día"=W$9,ROUND(Z16/U16,4),"")) -> 12.4676 | Z16: =IF(U16<>"",$P16,"") -> 31567.88 | AA16: =IF($F16&"/Día"=AC$9,SUM($G16:$H16),"") | AB16: =IF(AA16<>"",$O16,"") | AC16: =IF($F16&"/Día"=AC$9,ROUND(AA16/$W$1,1),"") | AD16: =IF(AA16=0,0,IF($F16&"/Día"=AC$9,ROUND(AB16/AA16,4),"")) | AE16: =IF(AA16=0,0,IF($F16&"/Día"=AC$9,ROUND(AF16/AA16,4),"")) | AF16: =IF(AA16<>"",$P16,"")
A17: - | B17: VII/VI | C17: Licencia | D17: Quincena | E17: F2 | F17: Bls | G17: 46815 | H17: 59830 | I17: 66.2472 | J17: 66.7679 | N17: 2221.88 | O17: =ROUND(G17*I17,2)+ROUND(H17*J17,2)-K17-L17-M17-N17 -> 7093864.2 | P17: =ROUND(18.75%*O17,2) -> 1330099.6 | Q17: =ROUND($O17*R17,2) -> 1064079.6 | R17: 0.15 | S17: =ROUND($O17*T17,2) -> 266019.91 | T17: 0.0375 | U17: =IF($F17&"/Día"=W$9,SUM($G17:$H17),"") -> 106645 | V17: =IF(U17<>"",$O17,"") -> 7093864.2 | W17: =IF($F17&"/Día"=W$9,ROUND(U17/$W$1,1),"") -> 3440.2 | X17: =IF(U17=0,0,IF($F17&"/Día"=W$9,ROUND(V17/U17,4),"")) -> 66.5185 | Y17: =IF(U17=0,0,IF($F17&"/Día"=W$9,ROUND(Z17/U17,4),"")) -> 12.4722 | Z17: =IF(U17<>"",$P17,"") -> 1330099.6 | AA17: =IF($F17&"/Día"=AC$9,SUM($G17:$H17),"") | AB17: =IF(AA17<>"",$O17,"") | AC17: =IF($F17&"/Día"=AC$9,ROUND(AA17/$W$1,1),"") | AD17: =IF(AA17=0,0,IF($F17&"/Día"=AC$9,ROUND(AB17/AA17,4),"")) | AE17: =IF(AA17=0,0,IF($F17&"/Día"=AC$9,ROUND(AF17/AA17,4),"")) | AF17: =IF(AA17<>"",$P17,"")
A18: - | B18: VII | C18: Servicios | D18: Mes | E18: F1 | F18: Bls | O18: =ROUND(G18*I18,2)+ROUND(H18*J18,2)-K18-L18-M18-N18 -> 0 | P18: =ROUND(18.75%*O18,2) -> 0 | Q18: =ROUND($O18*R18,2) -> 0 | R18: 0.15 | S18: =ROUND($O18*T18,2) -> 0 | T18: 0.0375 | U18: =IF($F18&"/Día"=W$9,SUM($G18:$H18),"") -> 0 | V18: =IF(U18<>"",$O18,"") -> 0 | W18: =IF($F18&"/Día"=W$9,ROUND(U18/$W$1,1),"") -> 0 | X18: =IF(U18=0,0,IF($F18&"/Día"=W$9,ROUND(V18/U18,4),"")) -> 0 | Y18: =IF(U18=0,0,IF($F18&"/Día"=W$9,ROUND(Z18/U18,4),"")) -> 0 | Z18: =IF(U18<>"",$P18,"") -> 0 | AA18: =IF($F18&"/Día"=AC$9,SUM($G18:$H18),"") | AB18: =IF(AA18<>"",$O18,"") | AC18: =IF($F18&"/Día"=AC$9,ROUND(AA18/$W$1,1),"") | AD18: =IF(AA18=0,0,IF($F18&"/Día"=AC$9,ROUND(AB18/AA18,4),"")) | AE18: =IF(AA18=0,0,IF($F18&"/Día"=AC$9,ROUND(AF18/AA18,4),"")) | AF18: =IF(AA18<>"",$P18,"")
A19: - | B19: VII/VI-GAS | C19: Licencia | D19: Quincena | E19: F2 | F19: MM BTU | G19: 58474.37 | H19: 64682.42 | I19: 2.1708 | J19: 2.1708 | N19: 2121.65 | O19: =ROUND(G19*I19,2)+ROUND(H19*J19,2)-K19-L19-M19-N19 -> 265227.11 | P19: =ROUND(18.75%*O19,2) -> 49730.08 | Q19: =ROUND($O19*R19,2) -> 39784.07 | R19: 0.15 | S19: =ROUND($O19*T19,2) -> 9946.02 | T19: 0.0375 | U19: =IF($F19&"/Día"=W$9,SUM($G19:$H19),"") | V19: =IF(U19<>"",$O19,"") | W19: =IF($F19&"/Día"=W$9,ROUND(U19/$W$1,1),"") | X19: =IF(U19=0,0,IF($F19&"/Día"=W$9,ROUND(V19/U19,4),"")) | Y19: =IF(U19=0,0,IF($F19&"/Día"=W$9,ROUND(Z19/U19,4),"")) | Z19: =IF(U19<>"",$P19,"") | AA19: =IF($F19&"/Día"=AC$9,SUM($G19:$H19),"") -> 123156.79 | AB19: =IF(AA19<>"",$O19,"") -> 265227.11 | AC19: =IF($F19&"/Día"=AC$9,ROUND(AA19/$W$1,1),"") -> 3972.8 | AD19: =IF(AA19=0,0,IF($F19&"/Día"=AC$9,ROUND(AB19/AA19,4),"")) -> 2.1536 | AE19: =IF(AA19=0,0,IF($F19&"/Día"=AC$9,ROUND(AF19/AA19,4),"")) -> 0.4038 | AF19: =IF(AA19<>"",$P19,"") -> 49730.08
A20: - | B20: IX | C20: Licencia | D20: Quincena | E20: F2 | F20: Bls | G20: 2083 | H20: 3260 | I20: 66.7972 | J20: 67.3179 | N20: 737.78 | O20: =ROUND(G20*I20,2)+ROUND(H20*J20,2)-K20-L20-M20-N20 -> 357857.14 | P20: =ROUND(18.75%*O20,2) -> 67098.21 | Q20: =ROUND($O20*R20,2) -> 53678.57 | R20: 0.15 | S20: =ROUND($O20*T20,2) -> 13419.64 | T20: 0.0375 | U20: =IF($F20&"/Día"=W$9,SUM($G20:$H20),"") -> 5343 | V20: =IF(U20<>"",$O20,"") -> 357857.14 | W20: =IF($F20&"/Día"=W$9,ROUND(U20/$W$1,1),"") -> 172.4 | X20: =IF(U20=0,0,IF($F20&"/Día"=W$9,ROUND(V20/U20,4),"")) -> 66.9768 | Y20: =IF(U20=0,0,IF($F20&"/Día"=W$9,ROUND(Z20/U20,4),"")) -> 12.5582 | Z20: =IF(U20<>"",$P20,"") -> 67098.21 | AA20: =IF($F20&"/Día"=AC$9,SUM($G20:$H20),"") | AB20: =IF(AA20<>"",$O20,"") | AC20: =IF($F20&"/Día"=AC$9,ROUND(AA20/$W$1,1),"") | AD20: =IF(AA20=0,0,IF($F20&"/Día"=AC$9,ROUND(AB20/AA20,4),"")) | AE20: =IF(AA20=0,0,IF($F20&"/Día"=AC$9,ROUND(AF20/AA20,4),"")) | AF20: =IF(AA20<>"",$P20,"")
A21: - | B21: X | C21: Licencia | D21: Quincena | E21: F2 | F21: Bls | G21: 195037 | H21: 205982 | I21: 66.7972 | J21: 67.3179 | N21: 4334.18 | O21: =ROUND(G21*I21,2)+ROUND(H21*J21,2)-K21-L21-M21-N21 -> 26889867 | P21: =ROUND(18.75%*O21,2) -> 5041850.1 | Q21: =ROUND($O21*R21,2) -> 4033480 | R21: 0.15 | S21: =ROUND($O21*T21,2) -> 1008370 | T21: 0.0375 | U21: =IF($F21&"/Día"=W$9,SUM($G21:$H21),"") -> 401019 | V21: =IF(U21<>"",$O21,"") -> 26889867 | W21: =IF($F21&"/Día"=W$9,ROUND(U21/$W$1,1),"") -> 12936.1 | X21: =IF(U21=0,0,IF($F21&"/Día"=W$9,ROUND(V21/U21,4),"")) -> 67.0538 | Y21: =IF(U21=0,0,IF($F21&"/Día"=W$9,ROUND(Z21/U21,4),"")) -> 12.5726 | Z21: =IF(U21<>"",$P21,"") -> 5041850.1 | AA21: =IF($F21&"/Día"=AC$9,SUM($G21:$H21),"") | AB21: =IF(AA21<>"",$O21,"") | AC21: =IF($F21&"/Día"=AC$9,ROUND(AA21/$W$1,1),"") | AD21: =IF(AA21=0,0,IF($F21&"/Día"=AC$9,ROUND(AB21/AA21,4),"")) | AE21: =IF(AA21=0,0,IF($F21&"/Día"=AC$9,ROUND(AF21/AA21,4),"")) | AF21: =IF(AA21<>"",$P21,"")
A22: - | B22: X-GAS | C22: Licencia | D22: Mes | E22: F2 | F22: MM BTU | G22: 251980.16 | H22: 254840.6 | I22: 1.8012 | J22: 1.8012 | N22: 2235.16 | O22: =ROUND(G22*I22,2)+ROUND(H22*J22,2)-K22-L22-M22-N22 -> 910650.39 | P22: =ROUND(18.75%*O22,2) -> 170746.95 | Q22: =ROUND($O22*R22,2) -> 136597.56 | R22: 0.15 | S22: =ROUND($O22*T22,2) -> 34149.39 | T22: 0.0375 | U22: =IF($F22&"/Día"=W$9,SUM($G22:$H22),"") | V22: =IF(U22<>"",$O22,"") | W22: =IF($F22&"/Día"=W$9,ROUND(U22/$W$1,1),"") | X22: =IF(U22=0,0,IF($F22&"/Día"=W$9,ROUND(V22/U22,4),"")) | Y22: =IF(U22=0,0,IF($F22&"/Día"=W$9,ROUND(Z22/U22,4),"")) | Z22: =IF(U22<>"",$P22,"") | AA22: =IF($F22&"/Día"=AC$9,SUM($G22:$H22),"") -> 506820.76 | AB22: =IF(AA22<>"",$O22,"") -> 910650.39 | AC22: =IF($F22&"/Día"=AC$9,ROUND(AA22/$W$1,1),"") -> 16349.1 | AD22: =IF(AA22=0,0,IF($F22&"/Día"=AC$9,ROUND(AB22/AA22,4),"")) -> 1.7968 | AE22: =IF(AA22=0,0,IF($F22&"/Día"=AC$9,ROUND(AF22/AA22,4),"")) -> 0.3369 | AF22: =IF(AA22<>"",$P22,"") -> 170746.95
A23: - | B23: XIV | C23: Licencia | D23: Mes | E23: F2 | F23: Bls | O23: =ROUND(G23*I23,2)+ROUND(H23*J23,2)-K23-L23-M23-N23 -> 0 | P23: =ROUND(18.75%*O23,2) -> 0 | Q23: =ROUND($O23*R23,2) -> 0 | R23: 0.15 | S23: =ROUND($O23*T23,2) -> 0 | T23: 0.0375 | U23: =IF($F23&"/Día"=W$9,SUM($G23:$H23),"") -> 0 | V23: =IF(U23<>"",$O23,"") -> 0 | W23: =IF($F23&"/Día"=W$9,ROUND(U23/$W$1,1),"") -> 0 | X23: =IF(U23=0,0,IF($F23&"/Día"=W$9,ROUND(V23/U23,4),"")) -> 0 | Y23: =IF(U23=0,0,IF($F23&"/Día"=W$9,ROUND(Z23/U23,4),"")) -> 0 | Z23: =IF(U23<>"",$P23,"") -> 0 | AA23: =IF($F23&"/Día"=AC$9,SUM($G23:$H23),"") | AB23: =IF(AA23<>"",$O23,"") | AC23: =IF($F23&"/Día"=AC$9,ROUND(AA23/$W$1,1),"") | AD23: =IF(AA23=0,0,IF($F23&"/Día"=AC$9,ROUND(AB23/AA23,4),"")) | AE23: =IF(AA23=0,0,IF($F23&"/Día"=AC$9,ROUND(AF23/AA23,4),"")) | AF23: =IF(AA23<>"",$P23,"")
A24: - | B24: XV | C24: Licencia | D24: Quincena | E24: F2 | F24: Bls | G24: 564 | H24: 535 | I24: 66.5365 | J24: 67.7014 | N24: 802.26 | O24: =ROUND(G24*I24,2)+ROUND(H24*J24,2)-K24-L24-M24-N24 -> 72944.58 | P24: =ROUND(18.75%*O24,2) -> 13677.11 | Q24: =ROUND($O24*R24,2) -> 10941.69 | R24: 0.15 | S24: =ROUND($O24*T24,2) -> 2735.42 | T24: 0.0375 | U24: =IF($F24&"/Día"=W$9,SUM($G24:$H24),"") -> 1099 | V24: =IF(U24<>"",$O24,"") -> 72944.58 | W24: =IF($F24&"/Día"=W$9,ROUND(U24/$W$1,1),"") -> 35.5 | X24: =IF(U24=0,0,IF($F24&"/Día"=W$9,ROUND(V24/U24,4),"")) -> 66.3736 | Y24: =IF(U24=0,0,IF($F24&"/Día"=W$9,ROUND(Z24/U24,4),"")) -> 12.4451 | Z24: =IF(U24<>"",$P24,"") -> 13677.11 | AA24: =IF($F24&"/Día"=AC$9,SUM($G24:$H24),"") | AB24: =IF(AA24<>"",$O24,"") | AC24: =IF($F24&"/Día"=AC$9,ROUND(AA24/$W$1,1),"") | AD24: =IF(AA24=0,0,IF($F24&"/Día"=AC$9,ROUND(AB24/AA24,4),"")) | AE24: =IF(AA24=0,0,IF($F24&"/Día"=AC$9,ROUND(AF24/AA24,4),"")) | AF24: =IF(AA24<>"",$P24,"")
A25: - | B25: XIII Crudo | C25: Licencia | D25: Quincena | E25: F2 | F25: Bls | G25: 28828 | H25: 36208 | I25: 66.7972 | J25: 67.3179 | N25: 1530.48 | O25: =ROUND(G25*I25,2)+ROUND(H25*J25,2)-K25-L25-M25-N25 -> 4361545.7 | P25: =ROUND(18.75%*O25,2) -> 817789.82 | Q25: =ROUND($O25*R25,2) -> 654231.86 | R25: 0.15 | S25: =ROUND($O25*T25,2) -> 163557.96 | T25: 0.0375 | U25: =IF($F25&"/Día"=W$9,SUM($G25:$H25),"") -> 65036 | V25: =IF(U25<>"",$O25,"") -> 4361545.7 | W25: =IF($F25&"/Día"=W$9,ROUND(U25/$W$1,1),"") -> 2097.9 | X25: =IF(U25=0,0,IF($F25&"/Día"=W$9,ROUND(V25/U25,4),"")) -> 67.0636 | Y25: =IF(U25=0,0,IF($F25&"/Día"=W$9,ROUND(Z25/U25,4),"")) -> 12.5744 | Z25: =IF(U25<>"",$P25,"") -> 817789.82 | AA25: =IF($F25&"/Día"=AC$9,SUM($G25:$H25),"") | AB25: =IF(AA25<>"",$O25,"") | AC25: =IF($F25&"/Día"=AC$9,ROUND(AA25/$W$1,1),"") | AD25: =IF(AA25=0,0,IF($F25&"/Día"=AC$9,ROUND(AB25/AA25,4),"")) | AE25: =IF(AA25=0,0,IF($F25&"/Día"=AC$9,ROUND(AF25/AA25,4),"")) | AF25: =IF(AA25<>"",$P25,"")
A26: - | B26: XIII COND | C26: Licencia | D26: Quincena | E26: F2 | F26: Bls | O26: =ROUND(G26*I26,2)+ROUND(H26*J26,2)-K26-L26-M26-N26 -> 0 | P26: =ROUND(18.75%*O26,2) -> 0 | Q26: =ROUND($O26*R26,2) -> 0 | R26: 0.15 | S26: =ROUND($O26*T26,2) -> 0 | T26: 0.0375 | U26: =IF($F26&"/Día"=W$9,SUM($G26:$H26),"") -> 0 | V26: =IF(U26<>"",$O26,"") -> 0 | W26: =IF($F26&"/Día"=W$9,ROUND(U26/$W$1,1),"") -> 0 | X26: =IF(U26=0,0,IF($F26&"/Día"=W$9,ROUND(V26/U26,4),"")) -> 0 | Y26: =IF(U26=0,0,IF($F26&"/Día"=W$9,ROUND(Z26/U26,4),"")) -> 0 | Z26: =IF(U26<>"",$P26,"") -> 0 | AA26: =IF($F26&"/Día"=AC$9,SUM($G26:$H26),"") | AB26: =IF(AA26<>"",$O26,"") | AC26: =IF($F26&"/Día"=AC$9,ROUND(AA26/$W$1,1),"") | AD26: =IF(AA26=0,0,IF($F26&"/Día"=AC$9,ROUND(AB26/AA26,4),"")) | AE26: =IF(AA26=0,0,IF($F26&"/Día"=AC$9,ROUND(AF26/AA26,4),"")) | AF26: =IF(AA26<>"",$P26,"")
A27: - | B27: XIII Gas | C27: Licencia | D27: Quincena | E27: F2 | F27: MM BTU | G27: =109679.9639+69454.7114 -> 179134.68 | H27: =115352.29+94462.85 -> 209815.14 | I27: 2.4759775 | J27: 2.6336074 | N27: 3163.29 | O27: =ROUND(G27*I27,2)+ROUND(H27*J27,2)-K27-L27-M27-N27 -> 992940.84 | P27: =ROUND(18.75%*O27,2) -> 186176.41 | Q27: =ROUND($O27*R27,2) -> 148941.13 | R27: 0.15 | S27: =ROUND($O27*T27,2) -> 37235.28 | T27: 0.0375 | U27: =IF($F27&"/Día"=W$9,SUM($G27:$H27),"") | V27: =IF(U27<>"",$O27,"") | W27: =IF($F27&"/Día"=W$9,ROUND(U27/$W$1,1),"") | X27: =IF(U27=0,0,IF($F27&"/Día"=W$9,ROUND(V27/U27,4),"")) | Y27: =IF(U27=0,0,IF($F27&"/Día"=W$9,ROUND(Z27/U27,4),"")) | Z27: =IF(U27<>"",$P27,"") | AA27: =IF($F27&"/Día"=AC$9,SUM($G27:$H27),"") -> 388949.82 | AB27: =IF(AA27<>"",$O27,"") -> 992940.84 | AC27: =IF($F27&"/Día"=AC$9,ROUND(AA27/$W$1,1),"") -> 12546.8 | AD27: =IF(AA27=0,0,IF($F27&"/Día"=AC$9,ROUND(AB27/AA27,4),"")) -> 2.5529 | AE27: =IF(AA27=0,0,IF($F27&"/Día"=AC$9,ROUND(AF27/AA27,4),"")) -> 0.4787 | AF27: =IF(AA27<>"",$P27,"") -> 186176.41
A28: - | B28: Z-2B | C28: Servicios | D28: Mes | E28: F1 | F28: Bls | H28: =39453+207131 -> 246584 | J28: 64.0398 | N28: 2445.75 | O28: =ROUND(G28*I28,2)+ROUND(H28*J28,2)-K28-L28-M28-N28 -> 15788744 | P28: =ROUND(18.75%*O28,2) -> 2960389.5 | Q28: =ROUND($O28*R28,2) -> 2368311.6 | R28: 0.15 | S28: =ROUND($O28*T28,2) -> 592077.91 | T28: 0.0375 | U28: =IF($F28&"/Día"=W$9,SUM($G28:$H28),"") -> 246584 | V28: =IF(U28<>"",$O28,"") -> 15788744 | W28: =IF($F28&"/Día"=W$9,ROUND(U28/$W$1,1),"") -> 7954.3 | X28: =IF(U28=0,0,IF($F28&"/Día"=W$9,ROUND(V28/U28,4),"")) -> 64.0299 | Y28: =IF(U28=0,0,IF($F28&"/Día"=W$9,ROUND(Z28/U28,4),"")) -> 12.0056 | Z28: =IF(U28<>"",$P28,"") -> 2960389.5 | AA28: =IF($F28&"/Día"=AC$9,SUM($G28:$H28),"") | AB28: =IF(AA28<>"",$O28,"") | AC28: =IF($F28&"/Día"=AC$9,ROUND(AA28/$W$1,1),"") | AD28: =IF(AA28=0,0,IF($F28&"/Día"=AC$9,ROUND(AB28/AA28,4),"")) | AE28: =IF(AA28=0,0,IF($F28&"/Día"=AC$9,ROUND(AF28/AA28,4),"")) | AF28: =IF(AA28<>"",$P28,"")
A29: - | B29: Z-2B GAS | C29: Servicios | D29: Mes | E29: F1 | F29: MM BTU | H29: =28128.11+153471.87+1104.62 -> 182704.6 | J29: 5.4650451 | N29: 2156.75 | O29: =ROUND(G29*I29,2)+ROUND(H29*J29,2)-K29-L29-M29-N29 -> 996332.12 | P29: =ROUND(18.75%*O29,2) -> 186812.27 | Q29: =ROUND($O29*R29,2) -> 149449.82 | R29: 0.15 | S29: =ROUND($O29*T29,2) -> 37362.45 | T29: 0.0375 | U29: =IF($F29&"/Día"=W$9,SUM($G29:$H29),"") | V29: =IF(U29<>"",$O29,"") | W29: =IF($F29&"/Día"=W$9,ROUND(U29/$W$1,1),"") | X29: =IF(U29=0,0,IF($F29&"/Día"=W$9,ROUND(V29/U29,4),"")) | Y29: =IF(U29=0,0,IF($F29&"/Día"=W$9,ROUND(Z29/U29,4),"")) | Z29: =IF(U29<>"",$P29,"") | AA29: =IF($F29&"/Día"=AC$9,SUM($G29:$H29),"") -> 182704.6 | AB29: =IF(AA29<>"",$O29,"") -> 996332.12 | AC29: =IF($F29&"/Día"=AC$9,ROUND(AA29/$W$1,1),"") -> 5893.7 | AD29: =IF(AA29=0,0,IF($F29&"/Día"=AC$9,ROUND(AB29/AA29,4),"")) -> 5.4532 | AE29: =IF(AA29=0,0,IF($F29&"/Día"=AC$9,ROUND(AF29/AA29,4),"")) -> 1.0225 | AF29: =IF(AA29<>"",$P29,"") -> 186812.27
A30: - | B30: XX | C30: Licencia | D30: Quincena | E30: F2 | F30: Bls | G30: 480 | H30: 368 | I30: 66.7972 | J30: 67.3179 | N30: 471.2 | O30: =ROUND(G30*I30,2)+ROUND(H30*J30,2)-K30-L30-M30-N30 -> 56364.45 | P30: =ROUND(18.75%*O30,2) -> 10568.33 | Q30: =ROUND($O30*R30,2) -> 2113.67 | R30: 0.0375 | S30: =ROUND($O30*T30,2) -> 8454.67 | T30: 0.15 | U30: =IF($F30&"/Día"=W$9,SUM($G30:$H30),"") -> 848 | V30: =IF(U30<>"",$O30,"") -> 56364.45 | W30: =IF($F30&"/Día"=W$9,ROUND(U30/$W$1,1),"") -> 27.4 | X30: =IF(U30=0,0,IF($F30&"/Día"=W$9,ROUND(V30/U30,4),"")) -> 66.4675 | Y30: =IF(U30=0,0,IF($F30&"/Día"=W$9,ROUND(Z30/U30,4),"")) -> 12.4627 | Z30: =IF(U30<>"",$P30,"") -> 10568.33 | AA30: =IF($F30&"/Día"=AC$9,SUM($G30:$H30),"") | AB30: =IF(AA30<>"",$O30,"") | AC30: =IF($F30&"/Día"=AC$9,ROUND(AA30/$W$1,1),"") | AD30: =IF(AA30=0,0,IF($F30&"/Día"=AC$9,ROUND(AB30/AA30,4),"")) | AE30: =IF(AA30=0,0,IF($F30&"/Día"=AC$9,ROUND(AF30/AA30,4),"")) | AF30: =IF(AA30<>"",$P30,"")
A31: - | B31: Z1 Crudo | C31: Licencia | D31: Quincena | E31: F2 | F31: Bls | N31: 1450.98 | O31: =ROUND(G31*I31,2)+ROUND(H31*J31,2)-K31-L31-M31-N31 -> -1450.98 | P31: =ROUND(18.75%*O31,2) -> -272.06 | Q31: =ROUND($O31*R31,2) -> -54.41 | R31: 0.0375 | S31: =ROUND($O31*T31,2) -> -217.65 | T31: 0.15 | U31: =IF($F31&"/Día"=W$9,SUM($G31:$H31),"") -> 0 | V31: =IF(U31<>"",$O31,"") -> -1450.98 | W31: =IF($F31&"/Día"=W$9,ROUND(U31/$W$1,1),"") -> 0 | X31: =IF(U31=0,0,IF($F31&"/Día"=W$9,ROUND(V31/U31,4),"")) -> 0 | Y31: =IF(U31=0,0,IF($F31&"/Día"=W$9,ROUND(Z31/U31,4),"")) -> 0 | Z31: =IF(U31<>"",$P31,"") -> -272.06 | AA31: =IF($F31&"/Día"=AC$9,SUM($G31:$H31),"") | AB31: =IF(AA31<>"",$O31,"") | AC31: =IF($F31&"/Día"=AC$9,ROUND(AA31/$W$1,1),"") | AD31: =IF(AA31=0,0,IF($F31&"/Día"=AC$9,ROUND(AB31/AA31,4),"")) | AE31: =IF(AA31=0,0,IF($F31&"/Día"=AC$9,ROUND(AF31/AA31,4),"")) | AF31: =IF(AA31<>"",$P31,"")
A32: - | B32: Z1 Gas | C32: Licencia | D32: Quincena | E32: F2 | F32: MM BTU | O32: =ROUND(G32*I32,2)+ROUND(H32*J32,2)-K32-L32-M32-N32 -> 0 | P32: =ROUND(18.75%*O32,2) -> 0 | Q32: =ROUND($O32*R32,2) -> 0 | R32: 0.0375 | S32: =ROUND($O32*T32,2) -> 0 | T32: 0.15 | U32: =IF($F32&"/Día"=W$9,SUM($G32:$H32),"") | V32: =IF(U32<>"",$O32,"") | W32: =IF($F32&"/Día"=W$9,ROUND(U32/$W$1,1),"") | X32: =IF(U32=0,0,IF($F32&"/Día"=W$9,ROUND(V32/U32,4),"")) | Y32: =IF(U32=0,0,IF($F32&"/Día"=W$9,ROUND(Z32/U32,4),"")) | Z32: =IF(U32<>"",$P32,"") | AA32: =IF($F32&"/Día"=AC$9,SUM($G32:$H32),"") -> 0 | AB32: =IF(AA32<>"",$O32,"") -> 0 | AC32: =IF($F32&"/Día"=AC$9,ROUND(AA32/$W$1,1),"") -> 0 | AD32: =IF(AA32=0,0,IF($F32&"/Día"=AC$9,ROUND(AB32/AA32,4),"")) -> 0 | AE32: =IF(AA32=0,0,IF($F32&"/Día"=AC$9,ROUND(AF32/AA32,4),"")) -> 0 | AF32: =IF(AA32<>"",$P32,"") -> 0
A33: - | B33: Z-2B - LGN | C33: Servicios | D33: Mes | E33: F1 | F33: Bls | H33: =5522+28988 -> 34510 | J33: 59.0561 | N33: 2349.32 | O33: =ROUND(G33*I33,2)+ROUND(H33*J33,2)-K33-L33-M33-N33 -> 2035676.7 | P33: =ROUND(18.75%*O33,2) -> 381689.38 | Q33: =ROUND($O33*R33,2) -> 305351.5 | R33: 0.15 | S33: =ROUND($O33*T33,2) -> 76337.88 | T33: 0.0375 | U33: =IF($F33&"/Día"=W$9,SUM($G33:$H33),"") -> 34510 | V33: =IF(U33<>"",$O33,"") -> 2035676.7 | W33: =IF($F33&"/Día"=W$9,ROUND(U33/$W$1,1),"") -> 1113.2 | X33: =IF(U33=0,0,IF($F33&"/Día"=W$9,ROUND(V33/U33,4),"")) -> 58.988 | Y33: =IF(U33=0,0,IF($F33&"/Día"=W$9,ROUND(Z33/U33,4),"")) -> 11.0603 | Z33: =IF(U33<>"",$P33,"") -> 381689.38 | AA33: =IF($F33&"/Día"=AC$9,SUM($G33:$H33),"") | AB33: =IF(AA33<>"",$O33,"") | AC33: =IF($F33&"/Día"=AC$9,ROUND(AA33/$W$1,1),"") | AD33: =IF(AA33=0,0,IF($F33&"/Día"=AC$9,ROUND(AB33/AA33,4),"")) | AE33: =IF(AA33=0,0,IF($F33&"/Día"=AC$9,ROUND(AF33/AA33,4),"")) | AF33: =IF(AA33<>"",$P33,"")
A34: - | B34: Z-6 | C34: Licencia | D34: Quincena | E34: F2 | F34: MM BTU | O34: =ROUND(G34*I34,2)+ROUND(H34*J34,2)-K34-L34-M34-N34 -> 0 | P34: =ROUND(18.75%*O34,2) -> 0 | Q34: =ROUND($O34*R34,2) -> 0 | R34: 0.15 | S34: =ROUND($O34*T34,2) -> 0 | T34: 0.0375
A35: - | B35: Ajustes meses anteriores (1) | O35: =+O149 -> -23595.17 | P35: =ROUND(18.75%*O35,2) -> -4424.09 | Q35: =+Q149 -> -3539.28 | S35: =+S149 -> -884.82 | U35: =IF($F35&"/Día"=W$9,SUM($G35:$H35),"") | V35: =IF(U35<>"",$O35,"") | W35: =IF($F35&"/Día"=W$9,ROUND(U35/$W$1,1),"") | X35: =IF(U35=0,0,IF($F35&"/Día"=W$9,ROUND(V35/U35,4),"")) | Y35: =IF(U35=0,0,IF($F35&"/Día"=W$9,ROUND(Z35/U35,4),"")) | Z35: =IF(U35<>"",$P35,"") | AA35: =IF($F35&"/Día"=AC$9,SUM($G35:$H35),"") | AB35: =IF(AA35<>"",$O35,"") | AC35: =IF($F35&"/Día"=AC$9,ROUND(AA35/$W$1,1),"") | AD35: =IF(AA35=0,0,IF($F35&"/Día"=AC$9,ROUND(AB35/AA35,4),"")) | AE35: =IF(AA35=0,0,IF($F35&"/Día"=AC$9,ROUND(AF35/AA35,4),"")) | AF35: =IF(AA35<>"",$P35,"")
B36: Subtotal | C36: =TEXT(A$9,)&" US$" -> Piura / Tumbes US$ | O36: =SUM(O10:O35) -> 67371407 | P36: =SUM(P10:P35) -> 12632139 | Q36: =SUM(Q10:Q35) -> 10099533 | S36: =SUM(S10:S35) -> 2532605.5 | U36: =SUM(U10:U35) -> 960035 | V36: =SUM(V10:V35) -> 63261917 | W36: =SUM(W10:W35) -> 30969.1 | X36: =ROUND(V36/U36,4) -> 65.8954 | Y36: =ROUND(Z36/U36,4) -> 12.3554 | Z36: =SUM(Z10:Z35) -> 11861609 | AA36: =SUM(AA10:AA35) -> 1539785.8 | AB36: =SUM(AB10:AB35) -> 4133085.2 | AC36: =SUM(AC10:AC35) -> 49670.5 | AD36: =ROUND(AB36/AA36,4) -> 2.6842 | AE36: =ROUND(AF36/AA36,4) -> 0.5033 | AF36: =SUM(AF10:AF35) -> 774953.48 | AG36: =P36-Z36-AF36 -> -4424.09
C37: =TEXT(A$9,)&" S/." -> Piura / Tumbes S/. | P37: =ROUND($F$1*P36,2) -> 0 | Q37: =ROUND($F$1*Q36,2) -> 0 | S37: =ROUND($F$1*S36,2) -> 0
A38: Provincia Puerto Inca Huanuco | Q38: Puerto Inca
A39: - | B39: 31-D | C39: Licencia | D39: Quincena | E39: F2 | F39: Bls | H39: 2156 | J39: 68.2014 | N39: 1112.44 | O39: =ROUND(G39*I39,2)+ROUND(H39*J39,2)-K39-L39-M39-N39 -> 145929.78 | P39: =ROUND(15%*O39,2) -> 21889.47 | Q39: =ROUND($O39*R39,2) -> 21889.47 | R39: 0.15 | U39: =IF($F39&"/Día"=W$9,SUM($G39:$H39),"") -> 2156 | V39: =IF(U39<>"",$O39,"") -> 145929.78 | W39: =IF($F39&"/Día"=W$9,ROUND(U39/$W$1,1),"") -> 69.5 | X39: =IF(U39=0,0,IF($F39&"/Día"=W$9,ROUND(V39/U39,4),"")) -> 67.6854 | Y39: =IF(U39=0,0,IF($F39&"/Día"=W$9,ROUND(Z39/U39,4),"")) -> 10.1528 | Z39: =IF(U39<>"",$P39,"") -> 21889.47 | AA39: =IF($F39&"/Día"=AC$9,SUM($G39:$H39),"") | AB39: =IF(AA39<>"",$O39,"") | AC39: =IF($F39&"/Día"=AC$9,ROUND(AA39/$W$1,1),"") | AD39: =IF(AA39=0,0,IF($F39&"/Día"=AC$9,ROUND(AB39/AA39,4),"")) | AE39: =IF(AA39=0,0,IF($F39&"/Día"=AC$9,ROUND(AF39/AA39,4),"")) | AF39: =IF(AA39<>"",$P39,"")
A40: - | B40: 131 | C40: Licencia | D40: Quincena | E40: F2 | F40: Bls | G40: 41943 | H40: 45761 | I40: 64.135 | J40: 64.8264 | N40: 9444.89 | O40: =ROUND(G40*I40,2)+ROUND(H40*J40,2)-K40-L40-M40-N40 -> 5647090.3 | P40: =ROUND(15%*O40,2) -> 847063.55 | Q40: =ROUND($O40*R40,2) -> 847063.55 | R40: 0.15 | U40: =IF($F40&"/Día"=W$9,SUM($G40:$H40),"") -> 87704 | V40: =IF(U40<>"",$O40,"") -> 5647090.3 | W40: =IF($F40&"/Día"=W$9,ROUND(U40/$W$1,1),"") -> 2829.2 | X40: =IF(U40=0,0,IF($F40&"/Día"=W$9,ROUND(V40/U40,4),"")) -> 64.3881 | Y40: =IF(U40=0,0,IF($F40&"/Día"=W$9,ROUND(Z40/U40,4),"")) -> 9.6582 | Z40: =IF(U40<>"",$P40,"") -> 847063.55 | AA40: =IF($F40&"/Día"=AC$9,SUM($G40:$H40),"") | AB40: =IF(AA40<>"",$O40,"") | AC40: =IF($F40&"/Día"=AC$9,ROUND(AA40/$W$1,1),"") | AD40: =IF(AA40=0,0,IF($F40&"/Día"=AC$9,ROUND(AB40/AA40,4),"")) | AE40: =IF(AA40=0,0,IF($F40&"/Día"=AC$9,ROUND(AF40/AA40,4),"")) | AF40: =IF(AA40<>"",$P40,"")
A41: - | B41: Ajustes meses anteriores (2) | U41: =IF($F41&"/Día"=W$9,SUM($G41:$H41),"") | V41: =IF(U41<>"",$O41,"") | W41: =IF($F41&"/Día"=W$9,ROUND(U41/$W$1,1),"") | X41: =IF(U41=0,0,IF($F41&"/Día"=W$9,ROUND(V41/U41,4),"")) | Y41: =IF(U41=0,0,IF($F41&"/Día"=W$9,ROUND(Z41/U41,4),"")) | Z41: =IF(U41<>"",$P41,"") | AA41: =IF($F41&"/Día"=AC$9,SUM($G41:$H41),"") | AB41: =IF(AA41<>"",$O41,"") | AC41: =IF($F41&"/Día"=AC$9,ROUND(AA41/$W$1,1),"") | AD41: =IF(AA41=0,0,IF($F41&"/Día"=AC$9,ROUND(AB41/AA41,4),"")) | AE41: =IF(AA41=0,0,IF($F41&"/Día"=AC$9,ROUND(AF41/AA41,4),"")) | AF41: =IF(AA41<>"",$P41,"")
B42: Subtotal | C42: =TEXT(A$38,)&" US$" -> Provincia Puerto Inca Huanuco US$ | O42: =SUM(O39:O41) -> 5793020.1 | P42: =SUM(P39:P41) -> 868953.02 | Q42: =SUM(Q39:Q41) -> 868953.02 | S42: =SUM(S39:S41) -> 0 | U42: =SUM(U39:U41) -> 89860 | V42: =SUM(V39:V41) -> 5793020.1 | W42: =SUM(W39:W41) -> 2898.7 | X42: =ROUND(V42/U42,4) -> 64.4672 | Y42: =ROUND(Z42/U42,4) -> 9.6701 | Z42: =SUM(Z39:Z41) -> 868953.02 | AA42: =SUM(AA39:AA41) -> 0 | AB42: =SUM(AB39:AB41) -> 0 | AC42: =SUM(AC39:AC41) -> 0 | AD42: =IF(AA42=0,0,ROUND(AB42/AA42,4)) -> 0 | AE42: =IF(AA42=0,0,ROUND(AF42/AA42,4)) -> 0 | AF42: =SUM(AF39:AF41) -> 0 | AG42: =P42-Z42-AF42 -> 0
C43: =TEXT(A$38,)&" S/." -> Provincia Puerto Inca Huanuco S/. | P43: =ROUND($F$1*P42,2) -> 0 | Q43: =ROUND($F$1*Q42,2) -> 0 | S43: =ROUND($F$1*S42,2) -> 0
A44: Loreto / Ucayali | Q44: Loreto | S44: Ucayali
A45: - | B45: 31-E | C45: Licencia | D45: Mes | E45: F2 | F45: Bls | H45: 1460 | J45: 57.5825 | N45: 513.71 | O45: =ROUND(G45*I45,2)+ROUND(H45*J45,2)-K45-L45-M45-N45 -> 83556.74 | P45: =ROUND(18.75%*O45,2) -> 15666.89 | Q45: =ROUND($O45*R45,2) -> 12533.51 | R45: 0.15 | S45: =ROUND($O45*T45,2) -> 3133.38 | T45: 0.0375 | U45: =IF($F45&"/Día"=W$9,SUM($G45:$H45),"") -> 1460 | V45: =IF(U45<>"",$O45,"") -> 83556.74 | W45: =IF($F45&"/Día"=W$9,ROUND(U45/$W$1,1),"") -> 47.1 | X45: =IF(U45=0,0,IF($F45&"/Día"=W$9,ROUND(V45/U45,4),"")) -> 57.2306 | Y45: =IF(U45=0,0,IF($F45&"/Día"=W$9,ROUND(Z45/U45,4),"")) -> 10.7307 | Z45: =IF(U45<>"",$P45,"") -> 15666.89 | AA45: =IF($F45&"/Día"=AC$9,SUM($G45:$H45),"") | AB45: =IF(AA45<>"",$O45,"") | AC45: =IF($F45&"/Día"=AC$9,ROUND(AA45/$W$1,1),"") | AD45: =IF(AA45=0,0,IF($F45&"/Día"=AC$9,ROUND(AB45/AA45,4),"")) | AE45: =IF(AA45=0,0,IF($F45&"/Día"=AC$9,ROUND(AF45/AA45,4),"")) | AF45: =IF(AA45<>"",$P45,"")
A46: - | B46: 192 | C46: Servicios | D46: Mes | E46: F1 | F46: Bls | G46: 56090 | H46: =253581 -> 253581 | I46: =62.879+0.55 -> 63.429 | J46: 50.7749 | M46: 488728.87 | N46: 10608.43 | O46: =ROUND(G46*I46,2)+ROUND(H46*J46,2)-K46-L46-M46-N46 -> 15933945 | P46: =ROUND(18.75%*O46,2) -> 2987614.7 | Q46: =ROUND($O46*R46,2) -> 2390091.8 | R46: 0.15 | S46: =ROUND($O46*T46,2) -> 597522.95 | T46: 0.0375 | U46: =IF($F46&"/Día"=W$9,SUM($G46:$H46),"") -> 309671 | V46: =IF(U46<>"",$O46,"") -> 15933945 | W46: =IF($F46&"/Día"=W$9,ROUND(U46/$W$1,1),"") -> 9989.4 | X46: =IF(U46=0,0,IF($F46&"/Día"=W$9,ROUND(V46/U46,4),"")) -> 51.4544 | Y46: =IF(U46=0,0,IF($F46&"/Día"=W$9,ROUND(Z46/U46,4),"")) -> 9.6477 | Z46: =IF(U46<>"",$P46,"") -> 2987614.7 | AA46: =IF($F46&"/Día"=AC$9,SUM($G46:$H46),"") | AB46: =IF(AA46<>"",$O46,"") | AC46: =IF($F46&"/Día"=AC$9,ROUND(AA46/$W$1,1),"") | AD46: =IF(AA46=0,0,IF($F46&"/Día"=AC$9,ROUND(AB46/AA46,4),"")) | AE46: =IF(AA46=0,0,IF($F46&"/Día"=AC$9,ROUND(AF46/AA46,4),"")) | AF46: =IF(AA46<>"",$P46,"")
A47: - | B47: 8 | C47: Licencia | D47: Quincena | E47: F2 | F47: Bls | G47: 83109 | H47: 105805 | I47: 50.7307 | J47: 52.1566 | N47: 12654.24 | O47: =ROUND(G47*I47,2)+ROUND(H47*J47,2)-K47-L47-M47-N47 -> 9721952.6 | P47: =ROUND(18.75%*O47,2) -> 1822866.1 | Q47: =ROUND($O47*R47,2) -> 1458292.9 | R47: 0.15 | S47: =ROUND($O47*T47,2) -> 364573.22 | T47: 0.0375 | U47: =IF($F47&"/Día"=W$9,SUM($G47:$H47),"") -> 188914 | V47: =IF(U47<>"",$O47,"") -> 9721952.6 | W47: =IF($F47&"/Día"=W$9,ROUND(U47/$W$1,1),"") -> 6094 | X47: =IF(U47=0,0,IF($F47&"/Día"=W$9,ROUND(V47/U47,4),"")) -> 51.4623 | Y47: =IF(U47=0,0,IF($F47&"/Día"=W$9,ROUND(Z47/U47,4),"")) -> 9.6492 | Z47: =IF(U47<>"",$P47,"") -> 1822866.1 | AA47: =IF($F47&"/Día"=AC$9,SUM($G47:$H47),"") | AB47: =IF(AA47<>"",$O47,"") | AC47: =IF($F47&"/Día"=AC$9,ROUND(AA47/$W$1,1),"") | AD47: =IF(AA47=0,0,IF($F47&"/Día"=AC$9,ROUND(AB47/AA47,4),"")) | AE47: =IF(AA47=0,0,IF($F47&"/Día"=AC$9,ROUND(AF47/AA47,4),"")) | AF47: =IF(AA47<>"",$P47,"")
A48: - | B48: 31-B | C48: Licencia | D48: Quincena | E48: F2 | F48: Bls | H48: 1293 | J48: 68.2014 | N48: 657.07 | O48: =ROUND(G48*I48,2)+ROUND(H48*J48,2)-K48-L48-M48-N48 -> 87527.34 | P48: =ROUND(18.75%*O48,2) -> 16411.38 | Q48: =ROUND($O48*R48,2) -> 13129.1 | R48: 0.15 | S48: =ROUND($O48*T48,2) -> 3282.28 | T48: 0.0375 | U48: =IF($F48&"/Día"=W$9,SUM($G48:$H48),"") -> 1293 | V48: =IF(U48<>"",$O48,"") -> 87527.34 | W48: =IF($F48&"/Día"=W$9,ROUND(U48/$W$1,1),"") -> 41.7 | X48: =IF(U48=0,0,IF($F48&"/Día"=W$9,ROUND(V48/U48,4),"")) -> 67.6932 | Y48: =IF(U48=0,0,IF($F48&"/Día"=W$9,ROUND(Z48/U48,4),"")) -> 12.6925 | Z48: =IF(U48<>"",$P48,"") -> 16411.38 | AA48: =IF($F48&"/Día"=AC$9,SUM($G48:$H48),"") | AB48: =IF(AA48<>"",$O48,"") | AC48: =IF($F48&"/Día"=AC$9,ROUND(AA48/$W$1,1),"") | AD48: =IF(AA48=0,0,IF($F48&"/Día"=AC$9,ROUND(AB48/AA48,4),"")) | AE48: =IF(AA48=0,0,IF($F48&"/Día"=AC$9,ROUND(AF48/AA48,4),"")) | AF48: =IF(AA48<>"",$P48,"")
A49: - | B49: 31-C GAS | C49: Licencia | D49: Quincena | E49: F2 | F49: MM BTU | G49: 997.6446 | H49: 112703.94 | I49: 3.7465 | J49: 3.7467 | N49: 1184.26 | O49: =ROUND(G49*I49,2)+ROUND(H49*J49,2)-K49-L49-M49-N49 -> 424821.27 | P49: =ROUND(18.75%*O49,2) -> 79653.99 | Q49: =ROUND($O49*R49,2) -> 15930.8 | R49: 0.0375 | S49: =ROUND($O49*T49,2) -> 63723.19 | T49: 0.15 | U49: =IF($F49&"/Día"=W$9,SUM($G49:$H49),"") | V49: =IF(U49<>"",$O49,"") | W49: =IF($F49&"/Día"=W$9,ROUND(U49/$W$1,1),"") | X49: =IF(U49=0,0,IF($F49&"/Día"=W$9,ROUND(V49/U49,4),"")) | Y49: =IF(U49=0,0,IF($F49&"/Día"=W$9,ROUND(Z49/U49,4),"")) | Z49: =IF(U49<>"",$P49,"") | AA49: =IF($F49&"/Día"=AC$9,SUM($G49:$H49),"") -> 113701.58 | AB49: =IF(AA49<>"",$O49,"") -> 424821.27 | AC49: =IF($F49&"/Día"=AC$9,ROUND(AA49/$W$1,1),"") -> 3667.8 | AD49: =IF(AA49=0,0,IF($F49&"/Día"=AC$9,ROUND(AB49/AA49,4),"")) -> 3.7363 | AE49: =IF(AA49=0,0,IF($F49&"/Día"=AC$9,ROUND(AF49/AA49,4),"")) -> 0.7006 | AF49: =IF(AA49<>"",$P49,"") -> 79653.99
A50: - | B50: 31-C LGN (*) | C50: Licencia | D50: Quincena | E50: F3 | F50: Bls | G50: 17616 | H50: 18887 | I50: 57.3734 | J50: 57.3205 | N50: 5359.58 | O50: =ROUND(G50*I50,2)+ROUND(H50*J50,2)-K50-L50-M50-N50 -> 2087942.5 | P50: =ROUND(18.75%*O50,2) -> 391489.22 | Q50: =ROUND($O50*R50,2) -> 78297.84 | R50: 0.0375 | S50: =ROUND($O50*T50,2) -> 313191.38 | T50: 0.15 | U50: =IF($F50&"/Día"=W$9,SUM($G50:$H50),"") -> 36503 | V50: =IF(U50<>"",$O50,"") -> 2087942.5 | W50: =IF($F50&"/Día"=W$9,ROUND(U50/$W$1,1),"") -> 1177.5 | X50: =IF(U50=0,0,IF($F50&"/Día"=W$9,ROUND(V50/U50,4),"")) -> 57.1992 | Y50: =IF(U50=0,0,IF($F50&"/Día"=W$9,ROUND(Z50/U50,4),"")) -> 10.7249 | Z50: =IF(U50<>"",$P50,"") -> 391489.22 | AA50: =IF($F50&"/Día"=AC$9,SUM($G50:$H50),"") | AB50: =IF(AA50<>"",$O50,"") | AC50: =IF($F50&"/Día"=AC$9,ROUND(AA50/$W$1,1),"") | AD50: =IF(AA50=0,0,IF($F50&"/Día"=AC$9,ROUND(AB50/AA50,4),"")) | AE50: =IF(AA50=0,0,IF($F50&"/Día"=AC$9,ROUND(AF50/AA50,4),"")) | AF50: =IF(AA50<>"",$P50,"")
A51: - | B51: 31-C COND | C51: Licencia | D51: Quincena | E51: F2 | F51: Bls | O51: =ROUND(G51*I51,2)+ROUND(H51*J51,2)-K51-L51-M51-N51 -> 0 | P51: =ROUND(18.75%*O51,2) -> 0 | Q51: =ROUND($O51*R51,2) -> 0 | R51: 0.0375 | S51: =ROUND($O51*T51,2) -> 0 | T51: 0.15 | U51: =IF($F51&"/Día"=W$9,SUM($G51:$H51),"") -> 0 | V51: =IF(U51<>"",$O51,"") -> 0 | W51: =IF($F51&"/Día"=W$9,ROUND(U51/$W$1,1),"") -> 0 | X51: =IF(U51=0,0,IF($F51&"/Día"=W$9,ROUND(V51/U51,4),"")) -> 0 | Y51: =IF(U51=0,0,IF($F51&"/Día"=W$9,ROUND(Z51/U51,4),"")) -> 0 | Z51: =IF(U51<>"",$P51,"") -> 0 | AA51: =IF($F51&"/Día"=AC$9,SUM($G51:$H51),"") | AB51: =IF(AA51<>"",$O51,"") | AC51: =IF($F51&"/Día"=AC$9,ROUND(AA51/$W$1,1),"") | AD51: =IF(AA51=0,0,IF($F51&"/Día"=AC$9,ROUND(AB51/AA51,4),"")) | AE51: =IF(AA51=0,0,IF($F51&"/Día"=AC$9,ROUND(AF51/AA51,4),"")) | AF51: =IF(AA51<>"",$P51,"")
A52: - | B52: 102 | C52: Licencia | D52: Quincena | E52: F2 | F52: Bls | O52: =ROUND(G52*I52,2)+ROUND(H52*J52,2)-K52-L52-M52-N52 -> 0 | P52: =ROUND(18.75%*O52,2) -> 0 | Q52: =P52-S52 -> 0 | R52: 0.15 | S52: =ROUND($O52*T52,2) -> 0 | T52: 0.0375 | U52: =IF($F52&"/Día"=W$9,SUM($G52:$H52),"") -> 0 | V52: =IF(U52<>"",$O52,"") -> 0 | W52: =IF($F52&"/Día"=W$9,ROUND(U52/$W$1,1),"") -> 0 | X52: =IF(U52=0,0,IF($F52&"/Día"=W$9,ROUND(V52/U52,4),"")) -> 0 | Y52: =IF(U52=0,0,IF($F52&"/Día"=W$9,ROUND(Z52/U52,4),"")) -> 0 | Z52: =IF(U52<>"",$P52,"") -> 0 | AA52: =IF($F52&"/Día"=AC$9,SUM($G52:$H52),"") | AB52: =IF(AA52<>"",$O52,"") | AC52: =IF($F52&"/Día"=AC$9,ROUND(AA52/$W$1,1),"") | AD52: =IF(AA52=0,0,IF($F52&"/Día"=AC$9,ROUND(AB52/AA52,4),"")) | AE52: =IF(AA52=0,0,IF($F52&"/Día"=AC$9,ROUND(AF52/AA52,4),"")) | AF52: =IF(AA52<>"",$P52,"")
A53: - | B53: 95 | C53: Licencia | D53: Quincena | E53: F2 | F53: Bls | O53: =ROUND(G53*I53,2)+ROUND(H53*J53,2)-K53-L53-M53-N53 -> 0 | P53: =ROUND(18.75%*O53,2) -> 0 | Q53: =P53-S53 -> 0 | R53: 0.15 | S53: =ROUND($O53*T53,2) -> 0 | T53: 0.0375 | U53: =IF($F53&"/Día"=W$9,SUM($G53:$H53),"") -> 0 | V53: =IF(U53<>"",$O53,"") -> 0 | W53: =IF($F53&"/Día"=W$9,ROUND(U53/$W$1,1),"") -> 0 | X53: =IF(U53=0,0,IF($F53&"/Día"=W$9,ROUND(V53/U53,4),"")) -> 0 | Y53: =IF(U53=0,0,IF($F53&"/Día"=W$9,ROUND(Z53/U53,4),"")) -> 0 | Z53: =IF(U53<>"",$P53,"") -> 0 | AA53: =IF($F53&"/Día"=AC$9,SUM($G53:$H53),"") | AB53: =IF(AA53<>"",$O53,"") | AC53: =IF($F53&"/Día"=AC$9,ROUND(AA53/$W$1,1),"") | AD53: =IF(AA53=0,0,IF($F53&"/Día"=AC$9,ROUND(AB53/AA53,4),"")) | AE53: =IF(AA53=0,0,IF($F53&"/Día"=AC$9,ROUND(AF53/AA53,4),"")) | AF53: =IF(AA53<>"",$P53,"")
A54: - | B54: 67 | C54: Licencia | D54: Quincena | E54: F2 | F54: Bls | O54: =ROUND(G54*I54,2)+ROUND(H54*J54,2)-K54-L54-M54-N54 -> 0 | P54: =ROUND(18.75%*O54,2) -> 0 | Q54: =P54-S54 -> 0 | R54: 0.15 | S54: =ROUND($O54*T54,2) -> 0 | T54: 0.0375 | U54: =IF($F54&"/Día"=W$9,SUM($G54:$H54),"") -> 0 | V54: =IF(U54<>"",$O54,"") -> 0 | W54: =IF($F54&"/Día"=W$9,ROUND(U54/$W$1,1),"") -> 0 | X54: =IF(U54=0,0,IF($F54&"/Día"=W$9,ROUND(V54/U54,4),"")) -> 0 | Y54: =IF(U54=0,0,IF($F54&"/Día"=W$9,ROUND(Z54/U54,4),"")) -> 0 | Z54: =IF(U54<>"",$P54,"") -> 0 | AA54: =IF($F54&"/Día"=AC$9,SUM($G54:$H54),"") | AB54: =IF(AA54<>"",$O54,"") | AC54: =IF($F54&"/Día"=AC$9,ROUND(AA54/$W$1,1),"") | AD54: =IF(AA54=0,0,IF($F54&"/Día"=AC$9,ROUND(AB54/AA54,4),"")) | AE54: =IF(AA54=0,0,IF($F54&"/Día"=AC$9,ROUND(AF54/AA54,4),"")) | AF54: =IF(AA54<>"",$P54,"")
A55: - | B55: Ajustes meses anteriores (3) | O55: =+O152 -> 1253.64 | P55: =ROUND(18.75%*O55,2) -> 235.06 | Q55: =+Q152 -> 188.05 | S55: =+S152 -> 47.01 | U55: =IF($F55&"/Día"=W$9,SUM($G55:$H55),"") | V55: =IF(U55<>"",$O55,"") | W55: =IF($F55&"/Día"=W$9,ROUND(U55/$W$1,1),"") | X55: =IF(U55=0,0,IF($F55&"/Día"=W$9,ROUND(V55/U55,4),"")) | Y55: =IF(U55=0,0,IF($F55&"/Día"=W$9,ROUND(Z55/U55,4),"")) | Z55: =IF(U55<>"",$P55,"") | AA55: =IF($F55&"/Día"=AC$9,SUM($G55:$H55),"") | AB55: =IF(AA55<>"",$O55,"") | AC55: =IF($F55&"/Día"=AC$9,ROUND(AA55/$W$1,1),"") | AD55: =IF(AA55=0,0,IF($F55&"/Día"=AC$9,ROUND(AB55/AA55,4),"")) | AE55: =IF(AA55=0,0,IF($F55&"/Día"=AC$9,ROUND(AF55/AA55,4),"")) | AF55: =IF(AA55<>"",$P55,"")
B56: Subtotal | C56: =TEXT(A$44,)&" US$" -> Loreto / Ucayali US$ | O56: =SUM(O45:O55) -> 28340999 | P56: =SUM(P45:P55) -> 5313937.4 | Q56: =SUM(Q45:Q55) -> 3968464 | S56: =SUM(S45:S55) -> 1345473.4 | U56: =SUM(U45:U55) -> 537841 | V56: =SUM(V45:V55) -> 27914924 | W56: =SUM(W45:W55) -> 17349.7 | X56: =ROUND(V56/U56,4) -> 51.9018 | Y56: =ROUND(Z56/U56,4) -> 9.7316 | Z56: =SUM(Z45:Z55) -> 5234048.3 | AA56: =SUM(AA45:AA55) -> 113701.58 | AB56: =SUM(AB45:AB55) -> 424821.27 | AC56: =SUM(AC45:AC55) -> 3667.8 | AD56: =ROUND(AB56/AA56,4) -> 3.7363 | AE56: =ROUND(AF56/AA56,4) -> 0.7006 | AF56: =SUM(AF45:AF55) -> 79653.99 | AG56: =P56-Z56-AF56 -> 235.06
C57: =TEXT(A$44,)&" S/." -> Loreto / Ucayali S/. | P57: =ROUND($F$1*P56,2) -> 0 | Q57: =ROUND($F$1*Q56,2) -> 0 | S57: =ROUND($F$1*S56,2) -> 0
A58: Cusco | P58: V. Regalías | Q58: Cusco
A59: - | B59: 88 LGN | C59: Licencia | D59: Quincena | E59: F4 | F59: Bls | G59: 755338 | H59: 820304 | I59: 43.1163 | J59: 42.2687 | O59: =G59*I59+H59*J59 -> 67240563 | P59: =ROUND(37.24%*(G59*I59+H59*J59),2) -> 25040386 | Q59: =ROUND(R59*P59,2) -> 12520193 | R59: 0.5 | U59: =IF($F59&"/Día"=W$9,SUM($G59:$H59),"") -> 1575642 | V59: =IF(U59<>"",$O59,"") -> 67240563 | W59: =IF($F59&"/Día"=W$9,ROUND(U59/$W$1,1),"") -> 50827.2 | X59: =IF(U59=0,0,IF($F59&"/Día"=W$9,ROUND(V59/U59,4),"")) -> 42.675 | Y59: =IF(U59=0,0,IF($F59&"/Día"=W$9,ROUND(Z59/U59,4),"")) -> 7.9461 | Z59: =IF(U59<>"",$Q59,"") -> 12520193 | AA59: =IF($F59&"/Día"=AC$9,SUM($G59:$H59),"") | AB59: =IF(AA59<>"",$O59,"") | AC59: =IF($F59&"/Día"=AC$9,ROUND(AA59/$W$1,1),"") | AD59: =IF(AA59=0,0,IF($F59&"/Día"=AC$9,ROUND(AB59/AA59,4),"")) | AE59: =IF(AA59=0,0,IF($F59&"/Día"=AC$9,ROUND(AF59/AA59,4),"")) | AF59: =IF(AA59<>"",$Q59,"")
A60: - | B60: 88 GAS | C60: Licencia | D60: Quincena | E60: F4 | F60: MM BTU | G60: 7816183.7 | H60: 8555912.2 | I60: 1.9641 | J60: 1.9641 | O60: =G60*I60+H60*J60 -> 32156434 | P60: =ROUND(37.24%*(G60*I60+H60*J60),2) -> 11975056 | Q60: =ROUND(R60*P60,2) -> 5987527.9 | R60: 0.5 | U60: =IF($F60&"/Día"=W$9,SUM($G60:$H60),"") | V60: =IF(U60<>"",$O60,"") | W60: =IF($F60&"/Día"=W$9,ROUND(U60/$W$1,1),"") | X60: =IF(U60=0,0,IF($F60&"/Día"=W$9,ROUND(V60/U60,4),"")) | Y60: =IF(U60=0,0,IF($F60&"/Día"=W$9,ROUND(Z60/U60,4),"")) | Z60: =IF(U60<>"",$Q60,"") | AA60: =IF($F60&"/Día"=AC$9,SUM($G60:$H60),"") -> 16372096 | AB60: =IF(AA60<>"",$O60,"") -> 32156434 | AC60: =IF($F60&"/Día"=AC$9,ROUND(AA60/$W$1,1),"") -> 528132.1 | AD60: =IF(AA60=0,0,IF($F60&"/Día"=AC$9,ROUND(AB60/AA60,4),"")) -> 1.9641 | AE60: =IF(AA60=0,0,IF($F60&"/Día"=AC$9,ROUND(AF60/AA60,4),"")) -> 0.3657 | AF60: =IF(AA60<>"",$Q60,"") -> 5987527.9
A61: - | B61: 88 GAS -Mlocal | C61: Licencia | D61: Quincena | E61: F4 | F61: MM BTU | G61: 21481.44 | H61: 31441.16 | I61: 2.7628 | J61: 2.7628 | O61: =G61*I61+H61*J61 -> 146214.56 | P61: =ROUND(37.24%*O61,2) -> 54450.3 | Q61: =ROUND(R61*P61,2) -> 27225.15 | R61: 0.5 | U61: =IF($F61&"/Día"=W$9,SUM($G61:$H61),"") | V61: =IF(U61<>"",$O61,"") | W61: =IF($F61&"/Día"=W$9,ROUND(U61/$W$1,1),"") | X61: =IF(U61=0,0,IF($F61&"/Día"=W$9,ROUND(V61/U61,4),"")) | Y61: =IF(U61=0,0,IF($F61&"/Día"=W$9,ROUND(Z61/U61,4),"")) | Z61: =IF(U61<>"",$Q61,"") | AA61: =IF($F61&"/Día"=AC$9,SUM($G61:$H61),"") -> 52922.6 | AB61: =IF(AA61<>"",$O61,"") -> 146214.56 | AC61: =IF($F61&"/Día"=AC$9,ROUND(AA61/$W$1,1),"") -> 1707.2 | AD61: =IF(AA61=0,0,IF($F61&"/Día"=AC$9,ROUND(AB61/AA61,4),"")) -> 2.7628 | AE61: =IF(AA61=0,0,IF($F61&"/Día"=AC$9,ROUND(AF61/AA61,4),"")) -> 0.5144 | AF61: =IF(AA61<>"",$Q61,"") -> 27225.15
A62: - | B62: 88 GAS -PM | C62: Licencia | D62: Quincena | E62: F4 | F62: MM BTU | G62: 736346.49 | H62: 923857.55 | I62: 1.798 | J62: 3.309 | O62: =G62*I62+H62*J62 -> 4380995.6 | P62: =ROUND(38%*G62*I62,2)+ROUND(38%*H62*J62,2) -> 1664778.3 | Q62: =ROUND(R62*P62,2) -> 832389.17 | R62: 0.5 | U62: =IF($F62&"/Día"=W$9,SUM($G62:$H62),"") | V62: =IF(U62<>"",$O62,"") | W62: =IF($F62&"/Día"=W$9,ROUND(U62/$W$1,1),"") | X62: =IF(U62=0,0,IF($F62&"/Día"=W$9,ROUND(V62/U62,4),"")) | Y62: =IF(U62=0,0,IF($F62&"/Día"=W$9,ROUND(Z62/U62,4),"")) | Z62: =IF(U62<>"",$Q62,"") | AA62: =IF($F62&"/Día"=AC$9,SUM($G62:$H62),"") -> 1660204 | AB62: =IF(AA62<>"",$O62,"") -> 4380995.6 | AC62: =IF($F62&"/Día"=AC$9,ROUND(AA62/$W$1,1),"") -> 53555 | AD62: =IF(AA62=0,0,IF($F62&"/Día"=AC$9,ROUND(AB62/AA62,4),"")) -> 2.6388 | AE62: =IF(AA62=0,0,IF($F62&"/Día"=AC$9,ROUND(AF62/AA62,4),"")) -> 0.5014 | AF62: =IF(AA62<>"",$Q62,"") -> 832389.17
A63: - | B63: 56 LGN | C63: Licencia | D63: Quincena | E63: F4 | F63: Bls | G63: 304982 | H63: 452645 | I63: 43.0691 | J63: 42.269 | O63: =G63*I63+H63*J63 -> 32268152 | P63: =ROUND(40%*G63*I63,2)+ROUND(40%*H63*J63,2) -> 12907261 | Q63: =ROUND(R63*P63,2) -> 6453630.3 | R63: 0.5 | U63: =IF($F63&"/Día"=W$9,SUM($G63:$H63),"") -> 757627 | V63: =IF(U63<>"",$O63,"") -> 32268152 | W63: =IF($F63&"/Día"=W$9,ROUND(U63/$W$1,1),"") -> 24439.6 | X63: =IF(U63=0,0,IF($F63&"/Día"=W$9,ROUND(V63/U63,4),"")) -> 42.5911 | Y63: =IF(U63=0,0,IF($F63&"/Día"=W$9,ROUND(Z63/U63,4),"")) -> 8.5182 | Z63: =IF(U63<>"",$Q63,"") -> 6453630.3 | AA63: =IF($F63&"/Día"=AC$9,SUM($G63:$H63),"") | AB63: =IF(AA63<>"",$O63,"") | AC63: =IF($F63&"/Día"=AC$9,ROUND(AA63/$W$1,1),"") | AD63: =IF(AA63=0,0,IF($F63&"/Día"=AC$9,ROUND(AB63/AA63,4),"")) | AE63: =IF(AA63=0,0,IF($F63&"/Día"=AC$9,ROUND(AF63/AA63,4),"")) | AF63: =IF(AA63<>"",$Q63,"")
A64: - | B64: 56 GAS | C64: Licencia | D64: Quincena | E64: F4 | F64: MM BTU | G64: 4773948.5 | H64: 6910967.5 | I64: 1.798 | J64: 3.309 | O64: =G64*I64+H64*J64 -> 31451951 | P64: =ROUND(38%*G64*I64,2)+ROUND(38%*H64*J64,2) -> 11951741 | Q64: =ROUND(R64*P64,2) -> 5975870.7 | R64: 0.5 | U64: =IF($F64&"/Día"=W$9,SUM($G64:$H64),"") | V64: =IF(U64<>"",$O64,"") | W64: =IF($F64&"/Día"=W$9,ROUND(U64/$W$1,1),"") | X64: =IF(U64=0,0,IF($F64&"/Día"=W$9,ROUND(V64/U64,4),"")) | Y64: =IF(U64=0,0,IF($F64&"/Día"=W$9,ROUND(Z64/U64,4),"")) | Z64: =IF(U64<>"",$Q64,"") | AA64: =IF($F64&"/Día"=AC$9,SUM($G64:$H64),"") -> 11684916 | AB64: =IF(AA64<>"",$O64,"") -> 31451951 | AC64: =IF($F64&"/Día"=AC$9,ROUND(AA64/$W$1,1),"") -> 376932.8 | AD64: =IF(AA64=0,0,IF($F64&"/Día"=AC$9,ROUND(AB64/AA64,4),"")) -> 2.6917 | AE64: =IF(AA64=0,0,IF($F64&"/Día"=AC$9,ROUND(AF64/AA64,4),"")) -> 0.5114 | AF64: =IF(AA64<>"",$Q64,"") -> 5975870.7
A65: - | B65: 56 GAS-Mlocal | C65: Licencia | D65: Quincena | E65: F4 | F65: MM BTU | G65: 191112.54 | H65: 282162.15 | I65: 1.8266 | J65: 1.8266 | O65: =G65*I65+H65*J65 -> 864483.55 | P65: =ROUND(37.24%*(G65*I65+H65*J65),2) -> 321933.67 | Q65: =ROUND(R65*P65,2) -> 160966.84 | R65: 0.5 | U65: =IF($F65&"/Día"=W$9,SUM($G65:$H65),"") | V65: =IF(U65<>"",$O65,"") | W65: =IF($F65&"/Día"=W$9,ROUND(U65/$W$1,1),"") | X65: =IF(U65=0,0,IF($F65&"/Día"=W$9,ROUND(V65/U65,4),"")) | Y65: =IF(U65=0,0,IF($F65&"/Día"=W$9,ROUND(Z65/U65,4),"")) | Z65: =IF(U65<>"",$Q65,"") | AA65: =IF($F65&"/Día"=AC$9,SUM($G65:$H65),"") -> 473274.69 | AB65: =IF(AA65<>"",$O65,"") -> 864483.55 | AC65: =IF($F65&"/Día"=AC$9,ROUND(AA65/$W$1,1),"") -> 15266.9 | AD65: =IF(AA65=0,0,IF($F65&"/Día"=AC$9,ROUND(AB65/AA65,4),"")) -> 1.8266 | AE65: =IF(AA65=0,0,IF($F65&"/Día"=AC$9,ROUND(AF65/AA65,4),"")) -> 0.3401 | AF65: =IF(AA65<>"",$Q65,"") -> 160966.84
A66: - | B66: 57 LGN | C66: Licencia | D66: Quincena | E66: F4 | F66: Bls | G66: 152939 | H66: 223448 | I66: 38.9845 | J66: 38.1868 | O66: =G66*I66+H66*J66 -> 14495015 | P66: =ROUND(G66*I66,2)*6.22%+ROUND(H66*J66,2)*6.42% -> 918655.43 | Q66: =ROUND(R66*P66,2) -> 459327.72 | R66: 0.5 | U66: =IF($F66&"/Día"=W$9,SUM($G66:$H66),"") -> 376387 | V66: =IF(U66<>"",$O66,"") -> 14495015 | W66: =IF($F66&"/Día"=W$9,ROUND(U66/$W$1,1),"") -> 12141.5 | X66: =IF(U66=0,0,IF($F66&"/Día"=W$9,ROUND(V66/U66,4),"")) -> 38.5109 | Y66: =IF(U66=0,0,IF($F66&"/Día"=W$9,ROUND(Z66/U66,4),"")) -> 1.2204 | Z66: =IF(U66<>"",$Q66,"") -> 459327.72 | AA66: =IF($F66&"/Día"=AC$9,SUM($G66:$H66),"") | AB66: =IF(AA66<>"",$O66,"") | AC66: =IF($F66&"/Día"=AC$9,ROUND(AA66/$W$1,1),"") | AD66: =IF(AA66=0,0,IF($F66&"/Día"=AC$9,ROUND(AB66/AA66,4),"")) | AE66: =IF(AA66=0,0,IF($F66&"/Día"=AC$9,ROUND(AF66/AA66,4),"")) | AF66: =IF(AA66<>"",$Q66,"")
A67: - | B67: 57 GAS | C67: Licencia | D67: Quincena | E67: F4 | F67: MM BTU | G67: 2377392.5 | H67: 3455909.8 | I67: 3.118 | J67: 3.118 | O67: =G67*I67+H67*J67 -> 18188237 | P67: =ROUND(G67*I67,2)*9.42%+ROUND(H67*J67,2)*9.89% -> 1763976.9 | Q67: =ROUND(R67*P67,2) -> 881988.44 | R67: 0.5 | U67: =IF($F67&"/Día"=W$9,SUM($G67:$H67),"") | V67: =IF(U67<>"",$O67,"") | W67: =IF($F67&"/Día"=W$9,ROUND(U67/$W$1,1),"") | X67: =IF(U67=0,0,IF($F67&"/Día"=W$9,ROUND(V67/U67,4),"")) | Y67: =IF(U67=0,0,IF($F67&"/Día"=W$9,ROUND(Z67/U67,4),"")) | Z67: =IF(U67<>"",$Q67,"") | AA67: =IF($F67&"/Día"=AC$9,SUM($G67:$H67),"") -> 5833302.4 | AB67: =IF(AA67<>"",$O67,"") -> 18188237 | AC67: =IF($F67&"/Día"=AC$9,ROUND(AA67/$W$1,1),"") -> 188171 | AD67: =IF(AA67=0,0,IF($F67&"/Día"=AC$9,ROUND(AB67/AA67,4),"")) -> 3.118 | AE67: =IF(AA67=0,0,IF($F67&"/Día"=AC$9,ROUND(AF67/AA67,4),"")) -> 0.1512 | AF67: =IF(AA67<>"",$Q67,"") -> 881988.44
A68: - | B68: Ajustes meses anteriores (4) | O68: =+O159 -> 7563365.7 | P68: =+P159 -> 990126.66 | Q68: =+Q159 -> 495063.34 | U68: =IF($F68&"/Día"=W$9,SUM($G68:$H68),"") | V68: =IF(U68<>"",$O68,"") | W68: =IF($F68&"/Día"=W$9,ROUND(U68/$W$1,1),"") | X68: =IF(U68=0,0,IF($F68&"/Día"=W$9,ROUND(V68/U68,4),"")) | Y68: =IF(U68=0,0,IF($F68&"/Día"=W$9,ROUND(Z68/U68,4),"")) | Z68: =IF(U68<>"",$Q68,"") | AA68: =IF($F68&"/Día"=AC$9,SUM($G68:$H68),"") | AB68: =IF(AA68<>"",$O68,"") | AC68: =IF($F68&"/Día"=AC$9,ROUND(AA68/$W$1,1),"") | AD68: =IF(AA68=0,0,IF($F68&"/Día"=AC$9,ROUND(AB68/AA68,4),"")) | AE68: =IF(AA68=0,0,IF($F68&"/Día"=AC$9,ROUND(AF68/AA68,4),"")) | AF68: =IF(AA68<>"",$Q68,"")
B69: Subtotal | C69: =TEXT(A$58,)&" US$" -> Cusco US$ | G69: =SUM(G64:G65) -> 4965061 | H69: =SUM(H64:H65) -> 7193129.7 | O69: =SUM(O59:O68) -> 2.0875541e+08 | P69: =SUM(P59:P68) -> 67588365 | Q69: =SUM(Q59:Q68) -> 33794183 | U69: =SUM(U59:U68) -> 2709656 | V69: =SUM(V59:V68) -> 1.1400373e+08 | W69: =SUM(W59:W68) -> 87408.3 | X69: =ROUND(V69/U69,4) -> 42.0731 | Y69: =ROUND(Z69/U69,4) -> 7.1718 | Z69: =SUM(Z59:Z68) -> 19433151 | AA69: =SUM(AA59:AA68) -> 36076716 | AB69: =SUM(AB59:AB68) -> 87188315 | AC69: =SUM(AC59:AC68) -> 1163765 | AD69: =ROUND(AB69/AA69,4) -> 2.4167 | AE69: =ROUND(AF69/AA69,4) -> 0.3843 | AF69: =SUM(AF59:AF68) -> 13865968 | AG69: =Q69-Z69-AF69 -> 495063.34
C70: =TEXT(A$58,)&" S/." -> Cusco S/. | G70: =SUMPRODUCT(I64:I65,G64:G65)/SUM(G64:G65) -> 1.7991009 | H70: =SUMPRODUCT(J64:J65,H64:H65)/SUM(H64:H65) -> 3.2508505 | Q70: =Q69*F1 -> 0
A71: Total General | G71: =G69*G70 -> 8932645.5 | H71: =H69*H70 -> 23383789 | I71: =H71+G71 -> 32316434 | J71: =O64+O65 -> 32316434 | K71: =I71-J71 -> 0 | M71: =SUM(M10:M67) -> 488728.87 | N71: =SUM(N10:N67) -> 79794.42 | O71: =O36+O42+O56+O69 -> 3.1026084e+08 | P71: =Q69+P56+P42+P36 -> 52609212 | Q71: =Q70+P57+P43+P37 -> 0 | U71: =U36+U42+U56+U69 -> 4297392 | V71: =V36+V42+V56+V69 -> 2.1097359e+08 | W71: =W36+W42+W56+W69 -> 138625.8 | X71: =ROUND(V71/U71,4) -> 49.0934 | Y71: =ROUND(Z71/U71,4) -> 8.7024 | Z71: =Z36+Z42+Z56+Z69 -> 37397762 | AA71: =AA36+AA42+AA56+AA69 -> 37730203 | AB71: =AB36+AB42+AB56+AB69 -> 91746222 | AC71: =AC36+AC42+AC56+AC69 -> 1217103.3 | AD71: =ROUND(AB71/AA71,4) -> 2.4316 | AE71: =ROUND(AF71/AA71,4) -> 0.3902 | AF71: =AF36+AF42+AF56+AF69 -> 14720576 | AG71: =P71-Z71-AF71 -> 490874.31
A73: (*) | B73: Determinación de Canasta de los Líquidos de Gas Natural (VLGNF) | H73: = ( VC * %P + (PB - TF - TT) * (1 - %P)) | O73: =114343802.37+0.82-0.01+151152570.31+0.2+0.01+0.01+0.01-152.04-42861.83+7541024.21-488728.87-79794.42+37804126.66+30849.5 -> 3.1026084e+08 | U73: Regalía 1Q | V73: 5444409.8 | W73: =P36 -> 12632139 | X73: Piura / Tumbes
B74: Simbolo | C74: Descripcion | E74: 1ra. Q | F74: 2da. Q | H74: 1ra. Q | O74: =+O73-O71 -> 0.019931436 | U74: Regalía 2Q | V74: =7125040.18-V82 -> 6318288.6 | W74: =P56 -> 5313937.4 | X74: Loreto / Ucayali
B75: VC | C75: Canasta de Petróleo | H75: ="= ("&TEXT(E75,"0.0000")&" * "&TEXT(E78,"0.00%")&" + ("&TEXT(E76,"0.0000")&" - "&TEXT(E77,"0.0000")&" - "&TEXT(E80,"0.0000")&") * (1 - "&TEXT(E78,"0.00%")&"))" -> = (0.0000 * 0.00% + (0.0000 - 0.0000 - 0.0000) * (1 - 0.00%)) | M75: =370851.98/5962250.45 -> 0.0622 | N75: =547803.45/8532764.09 -> 0.064199999 | U75: Servicios | V75: 6998362.8 | W75: =P42 -> 868953.02 | X75: Huanuco
B76: PB | C76: Precio del GLP | H76: =((85.98%*E75+4.4221)*E78+(E76-E77-E80)*(1-E78)) -> 0 | M76: =698277.28/7412709.99 -> 0.0942 | N76: =1065699.61/10775526.87 -> 0.0989 | V76: =SUM(V73:V75) -> 18761061 | W76: =SUM(W73:W75) -> 18815029 | X76: =V76-W76 -> -53967.912 | Y76: 16411.38
B77: TF | C77: Tarifa de Fraccionam. | M77: =5254120.1/13135300.26 -> 0.4 | N77: =7653140.6/19132851.51 -> 0.4 | U77: Lote 56 1Q | V77: 4324077.9 | Y77: 21889.47
B78: %P | C78: % Contenido Pentanos | H78: 2da. Q | M78: =503101.38/1323950.99 -> 0.38 | U78: Lote 88 1Q | V78: 9393842.5 | Y78: 15666.89
B79: QLGNF | C79: Volumen de LGN | H79: ="= ("&TEXT(F75,"0.0000")&" * "&TEXT(F78,"0.00%")&" + ("&TEXT(F76,"0.0000")&" - "&TEXT(F77,"0.0000")&" - "&TEXT(F80,"0.0000")&") * (1 - "&TEXT(F78,"0.00%")&"))" -> = (0.0000 * 0.00% + (0.0000 - 0.0000 - 0.0000) * (1 - 0.00%)) | U79: Lote 57 1Q | V79: 819790.22 | Y79: =SUM(Y76:Y78) -> 53967.74 | Z79: Regalias dejadas de pagar Lote 31-B-31-D-31-E
B80: TT | C80: Tarifa de Transporte | H80: =((85.98%*F75+4.4221)*F78+(F76-F77-F80)*(1-F78)) -> 0 | U80: Lote 56 2Q | V80: 8267531.7 | Y80: volumen x can | Z80: g.f
U81: Lote 88 2Q | V81: 10182189 | Y81: 88184.41 | Z81: -657.06
U82: Lote 57 2Q | V82: 806751.54 | Y82: 147042.22 | Z82: -1112.44
A83: ="AJUSTES PARA "&UPPER(TEXT(E1,"MMMMMMM YYYY")) -> AJUSTES PARA ENERO 2018 | O83: 37804127 | P83: facturas | V83: =SUM(V77:V82) -> 33794183 | W83: =Q69 -> 33794183 | X83: =V83-W83 -> 0.0099999979 | Y83: 84070.45 | Z83: -513.71
Y84: =SUM(Y81:Y83) -> 319297.08 | Z84: =SUM(Z81:Z83) -> -2283.21 | AA84: =+Z84+Y84 -> 317013.87
A85: (4) | B85: Ajuste correspondiente de Julio 2017 (Reporte de Regalía 1ra. Quincena de Enero 2018) - Liq. 1190 | V85: =+V73+V77+V78+V79 -> 19982120
A86: Cusco | D86: Período | E86: Fórmula | F86: Unidades | G86: 1ra. Q | H86: 2da. Q / Mes | I86: 1ra. Q | J86: 2da. Q / Mes | K86: Flete Marítimo | L86: Comercialización | M86: Oleoducto | N86: Fiscalización | O86: Valor Producción | P86: V. Regalías | Q86: Cuzco | V86: =+V74+V80+V81+V82 -> 25574761
A87: - | B87: 56 GAS-Mlocal | C87: Licencia | D87: Calculo Efectuado | F87: MM BTU | G87: 178674.45 | H87: 212775.22 | I87: 1.8094 | J87: 1.8094 | O87: =G87*I87+H87*J87 -> 708289.03 | P87: =ROUND(37.24%*(G87*I87+H87*J87),2) -> 263766.84 | Q87: =ROUND(R87*P87,2) -> 131883.42 | R87: 0.5 | V87: =+V75 -> 6998362.8
A88: - | B88: 56 GAS-Mlocal | C88: Licencia | D88: Modificación | F88: =F87 -> MM BTU | G88: =+G87 -> 178674.45 | H88: =+H87 -> 212775.22 | I88: 1.8102 | J88: 1.8102 | O88: =G88*I88+H88*J88 -> 708602.19 | P88: =ROUND(37.24%*(G88*I88+H88*J88),2) -> 263883.46 | Q88: =ROUND(R88*P88,2) -> 131941.73 | R88: 0.5 | V88: =SUM(V85:V87) -> 52555244 | X88: =+V88-P71 -> -53967.902
B89: Ajuste | G89: =G88-G87 -> 0 | H89: =H88-H87 -> 0 | I89: =I88-I87 -> 0.0008 | J89: =J88-J87 -> 0.0008 | K89: =K88-K87 -> 0 | L89: =L88-L87 -> 0 | M89: =M88-M87 -> 0 | N89: =N88-N87 -> 0 | ... Q89: =Q88-Q87 -> 58.31 | S89: ok
B91: Ajuste correspondiente de Agosto 2017 (Reporte de Regalía 1ra. Quincena de Enero 2018) - Liq. 1190
A92: Cusco | D92: Período | E92: Fórmula | F92: Unidades | G92: 1ra. Q | H92: 2da. Q / Mes | I92: 1ra. Q | J92: 2da. Q / Mes | K92: Flete Marítimo | L92: Comercialización | M92: Oleoducto | N92: Fiscalización | O92: Valor Producción | P92: V. Regalías | Q92: Cuzco
A93: - | B93: 56 GAS-Mlocal | C93: Licencia | D93: Calculo Efectuado | F93: MM BTU | G93: 264856.53 | H93: 282980.91 | I93: 1.8103 | J93: 1.8103 | O93: =G93*I93+H93*J93 -> 991750.12 | P93: =ROUND(37.24%*(G93*I93+H93*J93),2) -> 369327.74 | Q93: =ROUND(R93*P93,2) -> 184663.87 | R93: 0.5
A94: - | B94: =B93 -> 56 GAS-Mlocal | C94: Licencia | D94: Modificación | F94: =F93 -> MM BTU | G94: =+G93 -> 264856.53 | H94: =+H93 -> 282980.91 | I94: 1.8121 | J94: 1.8121 | O94: =G94*I94+H94*J94 -> 992736.23 | P94: =ROUND(37.24%*(G94*I94+H94*J94),2) -> 369694.97 | Q94: =ROUND(R94*P94,2) -> 184847.49 | R94: 0.5
B95: Ajuste | G95: =G94-G93 -> 0 | H95: =H94-H93 -> 0 | I95: =I94-I93 -> 0.0018 | J95: =J94-J93 -> 0.0018 | K95: =K94-K93 -> 0 | L95: =L94-L93 -> 0 | M95: =M94-M93 -> 0 | N95: =N94-N93 -> 0 | ... Q95: =Q94-Q93 -> 183.62 | S95: ok
B97: Ajuste correspondiente de Setiembre 2017 (Reporte de Regalía 1ra. Quincena de Enero 2018) - Liq. 1190
A98: Cusco | D98: Período | E98: Fórmula | F98: Unidades | G98: 1ra. Q | H98: 2da. Q / Mes | I98: 1ra. Q | J98: 2da. Q / Mes | K98: Flete Marítimo | L98: Comercialización | M98: Oleoducto | N98: Fiscalización | O98: Valor Producción | P98: V. Regalías | Q98: Cuzco
A99: - | B99: 56 GAS-Mlocal | C99: Licencia | D99: Calculo Efectuado | F99: MM BTU | G99: 229509.74 | H99: 282759.39 | I99: 1.8121 | J99: 1.8121 | O99: =G99*I99+H99*J99 -> 928282.89 | P99: =ROUND(37.24%*(G99*I99+H99*J99),2) -> 345692.55 | Q99: =ROUND(R99*P99,2) -> 172846.28 | R99: 0.5
A100: - | B100: =B99 -> 56 GAS-Mlocal | C100: Licencia | D100: Modificación | F100: =F99 -> MM BTU | G100: =+G99 -> 229509.74 | H100: =+H99 -> 282759.39 | I100: 1.8149 | J100: 1.8149 | O100: =G100*I100+H100*J100 -> 929717.24 | P100: =ROUND(37.24%*(G100*I100+H100*J100),2) -> 346226.7 | Q100: =ROUND(R100*P100,2) -> 173113.35 | R100: 0.5
B101: Ajuste | G101: =G100-G99 -> 0 | H101: =H100-H99 -> 0 | I101: =I100-I99 -> 0.0028 | J101: =J100-J99 -> 0.0028 | K101: =K100-K99 -> 0 | L101: =L100-L99 -> 0 | M101: =M100-M99 -> 0 | N101: =N100-N99 -> 0 | ... Q101: =Q100-Q99 -> 267.07 | S101: ok
B103: Ajuste correspondiente de Diciembre 2017 (Reporte de Regalía 1ra. Quincena de Enero 2018) - Liq. 1190
A104: Cusco | D104: Período | E104: Fórmula | F104: Unidades | G104: 1ra. Q | H104: 2da. Q / Mes | I104: 1ra. Q | J104: 2da. Q / Mes | K104: Flete Marítimo | L104: Comercialización | M104: Oleoducto | N104: Fiscalización | O104: Valor Producción | P104: V. Regalías | Q104: Cuzco
A105: - | B105: 56 GAS-Mlocal | C105: Licencia | D105: Calculo Efectuado | F105: MM BTU | G105: 275481.21 | H105: 272627.36 | I105: 1.8204 | J105: 1.8204 | O105: =G105*I105+H105*J105 -> 997776.84 | P105: =ROUND(37.24%*(G105*I105+H105*J105),2) -> 371572.1 | Q105: =ROUND(R105*P105,2) -> 185786.05 | R105: 0.5
...

Sheet Feb
A1: Período de Cálculo: | E1: 45689 | F1: 3.626 | S1: ,
A2: PERUPETRO S.A.
A3: DETERMINACION DEL CANON, SOBRECANON y PARTICIPACION (US$)
A4: Correspondiente a Febrero 2025
A5: Tipo de Cambio= 3.626
A7: Localidad | C7: Modalidad de Contrato | D7: Calculo del Canon | F7: Volumen Producción / Venta | I7: Canasta o Valor Venta (US$/Unidad) | K7: Deducción de Gastos para determinación de valor de producción en Punto de Fiscalización (US$) | O7: Valor de la Producción (US$) | P7: Canon y Sobrecanon / Participación (US$)
A8: - Lote | D8: Período | E8: Fórmula | F8: Unidades | G8: 1ra. Q | H8: 2da. Q / Mes | I8: 1ra. Q | J8: 2da. Q / Mes | K8: Flete Marítimo | L8: Comercialización | M8: Oleoducto | N8: Fiscalización | P8: Total | Q8: Localidad 1 | S8: Localidad 2
A9: Piura / Tumbes | Q9: Piura | S9: Tumbes
A10: - | B10: I | C10: Licencia | D10: Quincena | E10: F2 | F10: Bls | G10: 8517 | H10: 7379 | I10: 76.8955 | J10: 76.1323 | N10: 77.18 | O10: 1216622 | P10: 228116.63 | Q10: 182493.3 | R10: 0.15 | S10: 45623.33 | T10: 0.0375
A11: - | B11: I GAS | C11: Licencia | D11: Quincena | E11: F2 | F11: MM BTU | G11: 47099.05 | H11: 40893.95 | I11: 3.8743 | J11: 3.8743 | N11: 216.11 | O11: 340695.17 | P11: 63880.34 | Q11: 51104.28 | R11: 0.15 | S11: 12776.07 | T11: 0.0375
A12: - | B12: II | C12: Licencia | D12: Quincena | E12: F2 | F12: Bls | G12: 5065 | H12: 4040 | I12: 75.7478 | J12: 74.8391 | N12: 620.55 | O12: 685392.02 | P12: 128511 | Q12: 102808.8 | R12: 0.15 | S12: 25702.2 | T12: 0.0375
A13: - | B13: II-GAS | C13: Licencia | D13: Quincena | E13: F2 | F13: MM BTU | G13: 17210.966 | H13: 13902.47 | I13: 2.8114 | J13: 2.8114 | N13: 663.77 | O13: 86808.54 | P13: 16276.6 | Q13: 13021.28 | R13: 0.15 | S13: 3255.32 | T13: 0.0375
A14: - | B14: III | C14: Licencia | D14: Quincena | E14: F2 | F14: Bls | G14: 26790 | H14: 26756 | I14: 76.8955 | J14: 76.1323 | N14: 1043.18 | O14: 4095983.1 | P14: 767996.83 | Q14: 614397.46 | R14: 0.15 | S14: 153599.37 | T14: 0.0375
A15: - | B15: III-GAS | C15: Licencia | D15: Quincena | E15: F2 | F15: MM BTU | G15: 18574.126 | H15: 20553.1 | I15: 3.2 | J15: 3.2 | O15: 125207.12 | P15: 23476.34 | Q15: 18781.07 | R15: 0.15 | S15: 4695.27 | T15: 0.0375
A16: - | B16: IV | C16: Licencia | D16: Quincena | E16: F2 | F16: Bls | G16: 38808 | H16: 34352 | I16: 76.8955 | J16: 76.1323 | N16: 1743.99 | O16: 5597713.3 | P16: 1049571.2 | Q16: 839657 | R16: 0.15 | S16: 209914.25 | T16: 0.0375
A17: - | B17: IV-GAS | C17: Licencia | D17: Quincena | E17: F2 | F17: Bls | G17: 55693.476 | H17: 34431.22 | I17: 3.6855 | J17: 3.6855 | N17: 601.69 | O17: 331552.88 | P17: 62166.17 | Q17: 49732.93 | R17: 0.15 | S17: 12433.23 | T17: 0.0375
A18: - | B18: V | C18: Licencia | D18: Quincena | E18: F2 | F18: Bls | G18: 3363 | H18: 3195 | I18: 75.802 | J18: 74.8394 | N18: 404.44 | O18: 493629.57 | P18: 92555.54 | Q18: 74044.44 | R18: 0.15 | S18: 18511.11 | T18: 0.0375
A19: - | B19: VI (T) | C19: Licencia | D19: Quincena | E19: F2 | F19: Bls | G19: 21067 | H19: 22528 | I19: 76.8955 | J19: 76.1323 | N19: 487.79 | O19: 3334578.2 | P19: 625233.41 | Q19: 500186.72 | R19: 0.15 | S19: 125046.68 | T19: 0.0375
A20: - | B20: VI - GAS | C20: Licencia | D20: Quincena | E20: F2 | F20: MM BTU | G20: 53493.596 | H20: 48445.58 | I20: 3.9039 | J20: 3.9039 | N20: 209.93 | O20: 397750.42 | P20: 74578.2 | Q20: 59662.56 | R20: 0.15 | S20: 14915.64 | T20: 0.0375
A21: - | B21: VII (T) | C21: Licencia | D21: Quincena | E21: F2 | F21: Bls | G21: 13403 | H21: 12376 | I21: 75.802 | J21: 74.8394 | N21: 240.81 | O21: 1941945.8 | P21: 364114.84 | Q21: 291291.87 | R21: 0.15 | S21: 72822.97 | T21: 0.0375
A22: - | B22: IX | C22: Licencia | D22: Quincena | E22: F2 | F22: Bls | G22: 1723 | H22: 1746 | I22: 76.8955 | J22: 76.1323 | N22: 259.33 | O22: 265158.62 | P22: 49717.24 | Q22: 39773.79 | R22: 0.15 | S22: 9943.45 | T22: 0.0375
A23: - | B23: X | C23: Licencia | D23: Quincena | E23: F2 | F23: Bls | G23: 118603 | H23: 100877 | I23: 76.5332 | J23: 75.5657 | N23: 1201.19 | O23: 16698707 | P23: 3131007.6 | Q23: 2504806.1 | R23: 0.15 | S23: 626201.51 | T23: 0.0375
A24: - | B24: X-GAS | C24: Licencia | D24: Quincena | E24: F2 | F24: MM BTU | G24: 203371.05 | H24: 177675.49 | I24: 2.9 | J24: 2.9 | N24: 917.16 | O24: 1104117.8 | P24: 207022.09 | Q24: 165617.67 | R24: 0.15 | S24: 41404.42 | T24: 0.0375
A25: - | B25: XV | C25: Licencia | D25: Quincena | E25: F2 | F25: Bls | G25: 289 | H25: 215 | I25: 75.802 | J25: 74.8394 | N25: 280.94 | O25: 37716.31 | P25: 7071.81 | Q25: 5657.45 | R25: 0.15 | S25: 1414.36 | T25: 0.0375
A26: - | B26: XIII Crudo | C26: Licencia | D26: Quincena | E26: F2 | F26: Bls | G26: 14009 | H26: 11945 | I26: 74.1555 | J26: 76.1323 | N26: 2676.69 | O26: 1945568 | P26: 364794.01 | Q26: 291835.2 | R26: 0.15 | S26: 72958.8 | T26: 0.0375
A27: - | B27: XIII Gas | C27: Licencia | D27: Quincena | E27: F2 | F27: MM BTU | G27: 427489.26 | H27: 336512.31 | I27: 3.2529123 | J27: 3.3837231 | N27: 1114.52 | O27: 2529249.6 | P27: 474234.29 | Q27: 379387.43 | R27: 0.15 | S27: 94846.86 | T27: 0.0375
A28: - | B28: XX | C28: Licencia | D28: Quincena | E28: F2 | F28: Bls | G28: 175 | H28: 148 | I28: 76.8955 | J28: 76.1323 | N28: 166.71 | O28: 24557.58 | P28: 4604.55 | Q28: 920.91 | R28: 0.0375 | S28: 3683.64 | T28: 0.15
A29: - | B29: Z1 Crudo | C29: Licencia | D29: Quincena | E29: F2 | F29: Bls | N29: 842.83 | O29: -842.83 | P29: -158.03 | Q29: -31.61 | R29: 0.0375 | S29: -126.42 | T29: 0.15
A30: - | B30: Z-69 Crudo | C30: Licencia | D30: Quincena | E30: F2 | F30: Bls | G30: 49693 | H30: 56963 | I30: 75.353 | J30: 74.556 | N30: 429.13 | O30: 7991020.9 | P30: 1498316.4 | Q30: 1198653.1 | R30: 0.15 | S30: 299663.28 | T30: 0.0375
A31: - | B31: Z-69 Gas | C31: Licencia | D31: Quincena | E31: F2 | F31: MM BTU | G31: 114976.54 | H31: 98293.75 | I31: 2.754975 | J31: 2.7559206 | N31: 379.74 | O31: 587647.26 | P31: 110183.86 | Q31: 88147.08 | R31: 0.15 | S31: 22036.78 | T31: 0.0375
A32: - | B32: Z-69 Lgn | C32: Licencia | D32: Quincena | E32: F2 | F32: Bls | G32: 10821 | H32: 9439 | I32: 46.9719 | J32: 45.6759 | N32: 413.7 | O32: 939004.05 | P32: 176063.26 | Q32: 140850.61 | R32: 0.15 | S32: 35212.65 | T32: 0.0375
A33: - | B33: Ajustes meses anteriores (1) | O33: -3818010 | P33: -715876.85 | Q33: -572701.52 | S33: -143175.4
B34: Subtotal | C34: Piura / Tumbes US$ | O34: 46951773 | P34: 8803457.4 | Q34: 7040097.9 | S34: 1763359.4 | T34: 0
C35: Piura / Tumbes S/. | P35: 31921336 | Q35: 25527395 | S35: 6393941.1
A36: Provincia Puerto Inca Huanuco | Q36: Puerto Inca
A37: - | B37: 131 | C37: Licencia | D37: Quincena | E37: F2 | F37: Bls | G37: 9672 | H37: 7205 | I37: 64.5485 | J37: 63.5235 | N37: 3321.93 | O37: 1078678 | P37: 161801.7 | Q37: 161801.7 | R37: 0.15
A38: - | B38: Ajustes meses anteriores (2)
B39: Subtotal | C39: Provincia Puerto Inca Huanuco US$ | O39: 1078678 | P39: 161801.7 | Q39: 161801.7 | S39: 0
C40: Provincia Puerto Inca Huanuco S/. | P40: 586692.96 | Q40: 586692.96 | S40: 0
A41: Loreto / Ucayali | Q41: Loreto | S41: Ucayali
A42: - | B42: 8 | C42: Licencia | D42: Quincena | E42: F2 | F42: Bls | G42: 17286 | H42: 48141 | I42: 63.1428 | J42: 62.3128 | N42: 4451.89 | O42: 4086835 | P42: 766281.57 | Q42: 613025.26 | R42: 0.15 | S42: 153256.31 | T42: 0.0375
A43: - | B43: 31-C GAS | C43: Licencia | D43: Quincena | E43: F2 | F43: MM BTU | G43: 103451.02 | H43: 81227.6 | I43: 3.6065 | J43: 3.6069 | N43: 1620.17 | O43: 664455.76 | P43: 124585.46 | Q43: 24917.09 | R43: 0.0375 | S43: 99668.36 | T43: 0.15
A44: - | B44: 31-C LGN (*) | C44: Licencia | D44: Quincena | E44: F3 | F44: Bls | G44: 4377 | I44: 60.8869 | N44: 3092.81 | O44: 263409.15 | P44: 49389.22 | Q44: 9877.84 | R44: 0.0375 | S44: 39511.37 | T44: 0.15
A45: - | B45: 95 | C45: Licencia | D45: Quincena | E45: F2 | F45: Bls | G45: 318763 | H45: 297826 | I45: 56.4451 | J45: 55.3214 | N45: 4454.97 | O45: 34464306 | P45: 6462057.3 | Q45: 5169645.9 | R45: 0.15 | S45: 1292411.5 | T45: 0.0375
A46: - | B46: 67 | C46: Licencia | D46: Quincena | E46: F2 | F46: Bls | O46: 0 | P46: 0 | Q46: 0 | R46: 0.15 | S46: 0 | T46: 0.0375
A47: - | B47: Ajustes meses anteriores (3)
B48: Subtotal | C48: Loreto / Ucayali US$ | O48: 39479006 | P48: 7402313.6 | Q48: 5817466.1 | S48: 1584847.5
C49: Loreto / Ucayali S/. | P49: 26840789 | Q49: 21094132 | S49: 5746657
A50: Cusco | P50: V. Regalías | Q50: Cusco
A51: - | B51: 88 LGN | C51: Licencia | D51: Quincena | E51: F4 | F51: Bls | G51: 772938 | H51: 648129 | I51: 46.0098 | J51: 45.0525 | O51: 64762555 | P51: 24117575 | Q51: 12058788 | R51: 0.5
A52: - | B52: 88 GAS | C52: Licencia | D52: Quincena | E52: F4 | F52: MM BTU | G52: 11741591 | H52: 10448137 | I52: 3.1031 | J52: 3.0191 | O52: 67979354 | P52: 25395438 | Q52: 12697719 | R52: 0.5
A53: - | B53: 56 LGN | C53: Licencia | D53: Quincena | E53: F4 | F53: Bls | G53: 159575 | H53: 132328 | I53: 46.0039 | J53: 45.0551 | O53: 13303124 | P53: 5321249.4 | Q53: 2660624.7 | R53: 0.5
A54: - | B54: 56 GAS | C54: Licencia | D54: Quincena | E54: F4 | F54: MM BTU | G54: 4205107.5 | H54: 3550506.6 | I54: 7.178 | J54: 6.116 | O54: 51899160 | P54: 19721681 | Q54: 9860840.5 | R54: 0.5
A55: - | B55: 57 LGN | C55: Licencia | D55: Quincena | E55: F4 | F55: Bls | G55: 245521 | H55: 209000 | I55: 41.5143 | J55: 40.4528 | O55: 18647268 | P55: 1262767.6 | Q55: 631383.81 | R55: 0.5
A56: - | B56: 57 GAS | C56: Licencia | D56: Quincena | E56: F4 | F56: MM BTU | G56: 4222998.9 | H56: 3582765.5 | I56: 6.175 | J56: 6.175 | O56: 48200595 | P56: 5560691.4 | Q56: 2780345.7 | R56: 0.5
A57: - | B57: Ajustes meses anteriores (4) | O57: 2210110.1 | P57: 380897.28 | Q57: 190448.65
B58: Subtotal | C58: Cusco US$ | O58: 2.6700217e+08 | P58: 81760300 | Q58: 40880150
C59: Cusco S/. | G59: 7.178 | H59: 6.116 | Q59: 1.4823142e+08
A60: Total General | G60: 0 | H60: 0 | I60: 0 | J60: #REF! | K60: #REF! | M60: 0 | N60: 31933.15 | O60: 3.5451162e+08 | P60: 57247723 | Q60: 2.0758024e+08
A62: (*) | B62: Determinación de Canasta de los Líquidos de Gas Natural (VLGNF) | H62: = ( VC * %P + (PB - TF - TT) * (1 - %P))
B63: Simbolo | C63: Descripcion | E63: 1ra. Q | F63: 2da. Q | H63: 1ra. Q
B64: VC | C64: Canasta de Petróleo | H64: = (0.0000 * 0.00% + (0.0000 - 0.0000 - 0.0000) * (1 - 0.00%)) | N64: 0.064199999
B65: PB | C65: Precio del GLP | H65: 0 | M65: 0.0942 | N65: 0.0989
B66: TF | C66: Tarifa de Fraccionam. | M66: 0.4 | N66: 0.4
B67: %P | C67: % Contenido Pentanos | H67: 2da. Q | M67: 0.38
B68: QLGNF | C68: Volumen de LGN | H68: = (0.0000 * 0.00% + (0.0000 - 0.0000 - 0.0000) * (1 - 0.00%))
B69: TT | C69: Tarifa de Transporte | H69: 0

Sheet Mar
A1: Período de Cálculo: | E1: 45717 | F1: 3.715 | S1: , | U1: Días en el mes | W1: 31
A2: PERUPETRO S.A.
A3: DETERMINACION DEL CANON, SOBRECANON y PARTICIPACION (US$)
A4: Correspondiente a Marzo 2025
A5: Tipo de Cambio= 3.715
A7: Localidad | C7: Modalidad de Contrato | D7: Calculo del Canon | F7: Volumen Producción / Venta | I7: Canasta o Valor Venta (US$/Unidad) | K7: Deducción de Gastos para determinación de valor de producción en Punto de Fiscalización (US$) | O7: Valor de la Producción (US$) | P7: Canon y Sobrecanon / Participación (US$) | U7: RESUMEN POR PETROLERO Y CONDENSADOS | AA7: RESUMEN POR GAS NATURAL | AG7: Control
A8: - Lote | D8: Período | E8: Fórmula | F8: Unidades | G8: 1ra. Q | H8: 2da. Q / Mes | I8: 1ra. Q | J8: 2da. Q / Mes | K8: Flete Marítimo | L8: Comercialización | M8: Oleoducto | N8: Fiscalización | P8: Total | Q8: Localidad 1 | S8: Localidad 2 | U8: Producción / Venta | X8: Valor Prod | Y8: Valor Canon | AA8: Producción / Venta | AD8: Valor Prod | AE8: Valor Canon | AG8: Total
A9: Piura / Tumbes | Q9: Piura | S9: Tumbes | U9: Bls/Mes | V9: V P (US$) | W9: Bls/Día | X9: US$/Bl | Y9: US$/Bl | Z9: US$ | AA9: MM BTU/Mes | AB9: V P (US$) | AC9: MM BTU/Día | AD9: US$/MM BTU | AE9: US$/MM BTU | AF9: US$ | AG9: Canon
A10: - | B10: I | C10: Licencia | D10: Quincena | E10: F2 | F10: Bls | G10: 7979 | H10: 8524 | I10: 71.594 | J10: 73.591 | N10: 87.86 | O10: 1198450.3 | P10: 224709.44 | Q10: 179767.55 | R10: 0.15 | S10: 44941.89 | T10: 0.0375 | U10: 16503 | V10: 1198450.3 | W10: 532.4 | X10: 72.6202 | Y10: 13.6163 | Z10: 224709.44
A11: - | B11: I GAS | C11: Licencia | D11: Quincena | E11: F2 | F11: MM BTU | G11: 39581.406 | H11: 49146.48 | I11: 4.1325 | J11: 4.1325 | N11: 246.02 | O11: 366421.97 | P11: 68704.12 | Q11: 54963.3 | R11: 0.15 | S11: 13740.82 | T11: 0.0375 | AA11: 88727.886 | AB11: 366421.97 | AC11: 2862.2 | AD11: 4.1297 | AE11: 0.7743 | AF11: 68704.12
A12: - | B12: II | C12: Licencia | D12: Quincena | E12: F2 | F12: Bls | G12: 4754 | H12: 5310 | I12: 71.2533 | J12: 73.0151 | N12: 706.44 | O12: 725741.93 | P12: 136076.61 | Q12: 108861.29 | R12: 0.15 | S12: 27215.32 | T12: 0.0375 | U12: 10064 | V12: 725741.93 | W12: 324.6 | X12: 72.1127 | Y12: 13.5211 | Z12: 136076.61
A13: - | B13: II - GAS | C13: Licencia | D13: Quincena | E13: F2 | F13: MM BTU | G13: 20909.32 | H13: 21900.22 | I13: 2.95 | J13: 2.95 | N13: 755.64 | O13: 125532.5 | P13: 23537.34 | Q13: 18829.88 | R13: 0.15 | S13: 4707.47 | T13: 0.0375 | AA13: 42809.54 | AB13: 125532.5 | AC13: 1381 | AD13: 2.9323 | AE13: 0.5498 | AF13: 23537.34
A14: - | B14: III | C14: Licencia | D14: Quincena | E14: F2 | F14: Bls | G14: 27973 | H14: 31030 | I14: 71.594 | J14: 73.591 | N14: 1104.28 | O14: 4285123.4 | P14: 803460.64 | Q14: 642768.51 | R14: 0.15 | S14: 160692.13 | T14: 0.0375 | U14: 59003 | V14: 4285123.4 | W14: 1903.3 | X14: 72.6255 | Y14: 13.6173 | Z14: 803460.64
A15: - | B15: III - GAS | C15: Licencia | D15: Quincena | E15: F2 | F15: MM BTU | G15: 17174.839 | H15: 24776.65 | I15: 3.2 | J15: 2.9365 | O15: 127716.12 | P15: 23946.77 | Q15: 19157.42 | R15: 0.15 | S15: 4789.35 | T15: 0.0375 | AA15: 41951.489 | AB15: 127716.12 | AC15: 1353.3 | AD15: 3.0444 | AE15: 0.5708 | AF15: 23946.77
A16: - | B16: IV | C16: Licencia | D16: Quincena | E16: F2 | F16: Bls | G16: 40714 | H16: 46912 | I16: 71.594 | J16: 73.591 | N16: 1902.1 | O16: 6365277 | P16: 1193489.4 | Q16: 954791.55 | R16: 0.15 | S16: 238697.89 | T16: 0.0375 | U16: 87626 | V16: 6365277 | W16: 2826.6 | X16: 72.6414 | Y16: 13.6203 | Z16: 1193489.4
A17: - | B17: IV - GAS | C17: Licencia | D17: Quincena | E17: F2 | F17: Bls | G17: 47443.946 | H17: 33841.23 | I17: 3.4108 | J17: 3.4108 | N17: 601.69 | O17: 276645.79 | P17: 51871.09 | Q17: 41496.87 | R17: 0.15 | S17: 10374.22 | T17: 0.0375 | U17: 81285.176 | V17: 276645.79 | W17: 2622.1 | X17: 3.4034 | Y17: 0.6381 | Z17: 51871.09
A18: - | B18: V | C18: Licencia | D18: Quincena | E18: F2 | F18: Bls | G18: 2924 | H18: 2927 | I18: 71.2867 | J18: 73.0159 | N18: 460.41 | O18: 421699.44 | P18: 79068.65 | Q18: 63254.92 | R18: 0.15 | S18: 15813.73 | T18: 0.0375 | U18: 5851 | V18: 421699.44 | W18: 188.7 | X18: 72.0731 | Y18: 13.5137 | Z18: 79068.65
A19: - | B19: VI (T) | C19: Licencia | D19: Quincena | E19: F2 | F19: Bls | G19: 21784 | H19: 27320 | I19: 71.594 | J19: 73.591 | N19: 555.31 | O19: 3569554.5 | P19: 669291.47 | Q19: 535433.18 | R19: 0.15 | S19: 133858.29 | T19: 0.0375 | U19: 49104 | V19: 3569554.5 | W19: 1584 | X19: 72.6938 | Y19: 13.6301 | Z19: 669291.47
A20: - | B20: VI - GAS | C20: Licencia | D20: Quincena | E20: F2 | F20: MM BTU | G20: 49863.982 | H20: 47841.75 | I20: 4.0417 | J20: 4.0417 | N20: 239 | O20: 394658.26 | P20: 73998.42 | Q20: 59198.74 | R20: 0.15 | S20: 14799.68 | T20: 0.0375 | AA20: 97705.732 | AB20: 394658.26 | AC20: 3151.8 | AD20: 4.0393 | AE20: 0.7574 | AF20: 73998.42
A21: - | B21: VII (T) | C21: Licencia | D21: Quincena | E21: F2 | F21: Bls | G21: 17528 | H21: 17935 | I21: 71.2867 | J21: 73.0159 | N21: 274.14 | O21: 2558779.3 | P21: 479771.12 | Q21: 383816.9 | R21: 0.15 | S21: 95954.22 | T21: 0.0375 | U21: 35463 | V21: 2558779.3 | W21: 1144 | X21: 72.1535 | Y21: 13.5288 | Z21: 479771.12
A22: - | B22: IX | C22: Licencia | D22: Quincena | E22: F2 | F22: Bls | G22: 1863 | H22: 2611 | I22: 71.594 | J22: 73.591 | N22: 295.23 | O22: 325230.49 | P22: 60980.72 | Q22: 48784.57 | R22: 0.15 | S22: 12196.14 | T22: 0.0375 | U22: 4474 | V22: 325230.49 | W22: 144.3 | X22: 72.6934 | Y22: 13.63 | Z22: 60980.72
A23: - | B23: X | C23: Licencia | D23: Quincena | E23: F2 | F23: Bls | G23: 118420 | H23: 126446 | I23: 71.884 | J23: 73.9738 | N23: 1286.15 | O23: 17864908 | P23: 3349670.3 | Q23: 2679736.2 | R23: 0.15 | S23: 669934.06 | T23: 0.0375 | U23: 244866 | V23: 17864908 | W23: 7898.9 | X23: 72.9579 | Y23: 13.6796 | Z23: 3349670.3
A24: - | B24: X - GAS | C24: Licencia | D24: Quincena | E24: F2 | F24: MM BTU | G24: 200721.02 | H24: 218807.76 | I24: 2.9 | J24: 2.9 | N24: 962.81 | O24: 1215670.6 | P24: 227938.25 | Q24: 182350.6 | R24: 0.15 | S24: 45587.65 | T24: 0.0375 | AA24: 419528.78 | AB24: 1215670.6 | AC24: 13533.2 | AD24: 2.8977 | AE24: 0.5433 | AF24: 227938.25
A25: - | B25: XV | C25: Licencia | D25: Quincena | E25: F2 | F25: Bls | G25: 282 | H25: 297 | I25: 71.2867 | J25: 73.0159 | N25: 319.83 | O25: 41468.74 | P25: 7775.39 | Q25: 6220.31 | R25: 0.15 | S25: 1555.08 | T25: 0.0375 | U25: 579 | V25: 41468.74 | W25: 18.7 | X25: 71.6213 | Y25: 13.429 | Z25: 7775.39
A26: - | B26: XIII Crudo | C26: Licencia | D26: Quincena | E26: F2 | F26: Bls | G26: 13825 | H26: 15599 | I26: 68.694 | J26: 73.521 | N26: 3047.18 | O26: 2093501.5 | P26: 392531.52 | Q26: 314025.22 | R26: 0.15 | S26: 78506.3 | T26: 0.0375 | U26: 29424 | V26: 2093501.5 | W26: 949.2 | X26: 71.1495 | Y26: 13.3405 | Z26: 392531.52
A27: - | B27: XIII Gas | C27: Licencia | D27: Quincena | E27: F2 | F27: MM BTU | G27: 403187.77 | H27: 371306.11 | I27: 3.3121129 | J27: 3.4717601 | N27: 1268.78 | O27: 2624489.2 | P27: 492091.73 | Q27: 393673.38 | R27: 0.15 | S27: 98418.35 | T27: 0.0375 | AA27: 774493.88 | AB27: 2624489.2 | AC27: 24983.7 | AD27: 3.3887 | AE27: 0.6354 | AF27: 492091.73
A28: - | B28: XX | C28: Licencia | D28: Quincena | E28: F2 | F28: Bls | G28: 122 | H28: 143 | I28: 71.594 | J28: 73.591 | N28: 189.79 | O28: 19068.19 | P28: 3575.29 | Q28: 715.06 | R28: 0.0375 | S28: 2860.23 | T28: 0.15 | U28: 265 | V28: 19068.19 | W28: 8.5 | X28: 71.9554 | Y28: 13.4917 | Z28: 3575.29
A29: - | B29: Z-1 Crudo | C29: Licencia | D29: Quincena | E29: F2 | F29: Bls | N29: 959.49 | O29: -959.49 | P29: -179.9 | Q29: -35.98 | R29: 0.0375 | S29: -143.92 | T29: 0.15
A30: - | B30: Z-69 Crudo | C30: Licencia | D30: Quincena | E30: F2 | F30: Bls | G30: 38828 | H30: 72647 | I30: 70.203 | J30: 72.6164 | N30: 432.3 | O30: 8000773.4 | P30: 1500145 | Q30: 1200116 | R30: 0.15 | S30: 300029 | T30: 0.0375
A31: - | B31: Z-69 Gas | C31: Licencia | D31: Quincena | E31: F2 | F31: MM BTU | G31: 116545.33 | H31: 168267.94 | I31: 2.8160073 | J31: 2.7611696 | N31: 488.53 | O31: 792808.82 | P31: 148651.66 | Q31: 118921.32 | R31: 0.15 | S31: 29730.34 | T31: 0.0375
A32: - | B32: Z-69 Lgn | C32: Licencia | D32: Quincena | E32: F2 | F32: Bls | G32: 10529 | H32: 11310 | I32: 42.6612 | J32: 44.2344 | N32: 470.96 | O32: 948999.87 | P32: 177937.48 | Q32: 142349.98 | R32: 0.15 | S32: 35587.5 | T32: 0.0375
A33: - | B33: Ajustes meses anteriores (1) | O33: -6754.2 | P33: -1266.42 | Q33: -1013.13 | S33: -253.29
B34: Subtotal | C34: Piura / Tumbes US$ | O34: 54334806 | P34: 10187776 | Q34: 8148183.7 | S34: 2039592.5 | T34: 0 | U34: 624507.18 | V34: 39745449 | W34: 20145.3 | X34: 63.6429 | Y34: 11.933 | Z34: 7452271.7 | AA34: 1465217.3 | AB34: 4854488.7 | AC34: 47265.2 | AD34: 3.3132 | AE34: 0.6212 | AF34: 910216.63 | AG34: 1825287.8
C35: Piura / Tumbes S/. | P35: 37847588 | Q35: 30270502 | S35: 7577086
A36: Provincia Puerto Inca Huanuco | Q36: Puerto Inca
A37: - | B37: 131 | C37: Licencia | D37: Quincena | E37: F2 | F37: Bls | G37: 8072 | H37: 9119 | I37: 69.8332 | J37: 60.064 | N37: 3781.73 | O37: 1107635.5 | P37: 166145.32 | Q37: 166145.32 | R37: 0.15 | U37: 17191 | V37: 1107635.5 | W37: 554.5 | X37: 64.4311 | Y37: 9.6647 | Z37: 166145.32
A38: - | B38: Ajustes meses anteriores (2)
B39: Subtotal | C39: Provincia Puerto Inca Huanuco US$ | O39: 1107635.5 | P39: 166145.32 | Q39: 166145.32 | S39: 0 | U39: 17191 | V39: 1107635.5 | W39: 554.5 | X39: 64.4311 | Y39: 9.6647 | Z39: 166145.32 | AA39: 0 | AB39: 0 | AC39: 0 | AD39: 0 | AE39: 0 | AF39: 0 | AG39: 0
C40: Provincia Puerto Inca Huanuco S/. | P40: 617229.86 | Q40: 617229.86 | S40: 0
A41: Loreto / Ucayali | Q41: Loreto | S41: Ucayali
A42: - | B42: 8 | C42: Licencia | D42: Quincena | E42: F2 | F42: Bls | G42: 37875 | H42: 56105 | I42: 58.3905 | J42: 60.4117 | N42: 5068.08 | O42: 5595870.5 | P42: 1049225.7 | Q42: 839380.58 | R42: 0.15 | S42: 209845.15 | T42: 0.0375 | U42: 93980 | V42: 5595870.5 | W42: 3031.6 | X42: 59.5432 | Y42: 11.1644 | Z42: 1049225.7
A43: - | B43: 31-C GAS | C43: Licencia | D43: Quincena | E43: F2 | F43: MM BTU | G43: 90108.12 | H43: 12288.69 | I43: 3.6073 | J43: 3.6074 | N43: 1677.86 | O43: 367699.38 | P43: 68943.63 | Q43: 13788.73 | R43: 0.0375 | S43: 55154.91 | T43: 0.15 | AA43: 102396.81 | AB43: 367699.38 | AC43: 3303.1 | AD43: 3.5909 | AE43: 0.6733 | AF43: 68943.63
A44: - | B44: 31-C LGN (*) | C44: Licencia | D44: Quincena | E44: F3 | F44: Bls | N44: 3354.34 | O44: -3354.34 | P44: -628.94 | Q44: -125.79 | R44: 0.0375 | S44: -503.15 | T44: 0.15 | U44: 0 | V44: -3354.34 | W44: 0 | X44: 0 | Y44: 0 | Z44: -628.94
A45: - | B45: 95 | C45: Licencia | D45: Quincena | E45: F2 | F45: Bls | G45: 346326 | H45: 366318 | I45: 51.5079 | J45: 53.4069 | N45: 5071.59 | O45: 37397362 | P45: 7012005.4 | Q45: 5609604.3 | R45: 0.15 | S45: 1402401.1 | T45: 0.0375 | U45: 712644 | V45: 37397362 | W45: 22988.5 | X45: 52.4769 | Y45: 9.8394 | Z45: 7012005.4
A46: - | B46: 67 | C46: Licencia | D46: Quincena | E46: F2 | F46: Bls | O46: 0 | P46: 0 | Q46: 0 | R46: 0.15 | S46: 0 | T46: 0.0375 | U46: 0 | V46: 0 | W46: 0 | X46: 0 | Y46: 0 | Z46: 0
A47: - | B47: Ajustes meses anteriores (3)
B48: Subtotal | C48: Loreto / Ucayali US$ | O48: 43357578 | P48: 8129545.8 | Q48: 6462647.8 | S48: 1666898 | U48: 806624 | V48: 42989878 | W48: 26020.1 | X48: 53.2961 | Y48: 9.993 | Z48: 8060602.2 | AA48: 102396.81 | AB48: 367699.38 | AC48: 3303.1 | AD48: 3.5909 | AE48: 0.6733 | AF48: 68943.63 | AG48: -1.1641532e-10
C49: Loreto / Ucayali S/. | P49: 30201263 | Q49: 24008737 | S49: 6192526
A50: Cusco | P50: V. Regalías | Q50: Cusco
A51: - | B51: 88 LGN | C51: Licencia | D51: Quincena | E51: F4 | F51: Bls | G51: 757184 | H51: 808842 | I51: 41.6651 | J51: 43.1301 | O51: 66433583 | P51: 24739866 | Q51: 12369933 | R51: 0.5 | U51: 1566026 | V51: 66433583 | W51: 50517 | X51: 42.4218 | Y51: 7.8989 | Z51: 12369933
A52: - | B52: 88 GAS | C52: Licencia | D52: Quincena | E52: F4 | F52: MM BTU | G52: 13188927 | H52: 12463819 | I52: 2.9161 | J52: 2.9474 | O52: 75195981 | P52: 28077761 | Q52: 14038881 | R52: 0.5 | AA52: 25652746 | AB52: 75195981 | AC52: 827507.9 | AD52: 2.9313 | AE52: 0.5473 | AF52: 14038881
A53: - | B53: 56 LGN | C53: Licencia | D53: Quincena | E53: F4 | F53: Bls | G53: 156041 | H53: 174545 | I53: 41.6653 | J53: 43.1304 | O53: 14029691 | P53: 5611876.3 | Q53: 2805938.1 | R53: 0.5 | U53: 330586 | V53: 14029691 | W53: 10664.1 | X53: 42.4389 | Y53: 8.4878 | Z53: 2805938.1
A54: - | B54: 56 GAS | C54: Licencia | D54: Quincena | E54: F4 | F54: MM BTU | G54: 4238367.7 | H54: 4696684.8 | I54: 5.529 | J54: 5.585 | O54: 49664919 | P54: 18872669 | Q54: 9436334.7 | R54: 0.5 | AA54: 8935052.5 | AB54: 49664919 | AC54: 288227.5 | AD54: 5.5584 | AE54: 1.0561 | AF54: 9436334.7
A55: - | B55: 57 LGN | C55: Licencia | D55: Quincena | E55: F4 | F55: Bls | G55: 243298 | H55: 261839 | I55: 37.937 | J55: 39.4585 | O55: 19561770 | P55: 1326398.2 | Q55: 663199.11 | R55: 0.5 | U55: 505137 | V55: 19561770 | W55: 16294.7 | X55: 38.7257 | Y55: 1.3129 | Z55: 663199.11
A56: - | B56: 57 GAS | C56: Licencia | D56: Quincena | E56: F4 | F56: MM BTU | G56: 4232723.3 | H56: 4526505.9 | I56: 6.684 | J56: 6.684 | O56: 58546688 | P56: 6809176.2 | Q56: 3404588.1 | R56: 0.5 | AA56: 8759229.2 | AB56: 58546688 | AC56: 282555.8 | AD56: 6.684 | AE56: 0.3887 | AF56: 3404588.1
A57: - | B57: Ajustes meses anteriores (4) | O57: 3214945 | P57: 92977.677 | Q57: 46488.85
B58: Subtotal | C58: Cusco US$ | G58: 4238367.7 | H58: 4696684.8 | O58: 2.8664758e+08 | P58: 85530726 | Q58: 42765363 | U58: 2401749 | V58: 1.0002504e+08 | W58: 77475.8 | X58: 41.6468 | Y58: 6.5948 | Z58: 15839070 | AA58: 43347027 | AB58: 1.8340759e+08 | AC58: 1398291.2 | AD58: 4.2311 | AE58: 0.6201 | AF58: 26879804 | AG58: 46488.85
C59: Cusco S/. | G59: 5.529 | H59: 5.585 | Q59: 1.5887332e+08
A60: Total General | G60: 23433935 | H60: 26230984 | I60: 49664919 | J60: #REF! | K60: #REF! | M60: 0 | N60: 35607.54 | O60: 3.854476e+08 | P60: 61248830 | Q60: 2.275394e+08 | U60: 3850071.2 | V60: 1.8386801e+08 | W60: 124195.7 | X60: 47.757 | Y60: 8.1864 | Z60: 31518090 | AA60: 44914642 | AB60: 1.8862978e+08 | AC60: 1448859.5 | AD60: 4.1997 | AE60: 0.6203 | AF60: 27858964 | AG60: 1871776.7 | AI60: 57
AI61: 56
A62: (*) | B62: Determinación de Canasta de los Líquidos de Gas Natural (VLGNF) | H62: = ( VC * %P + (PB - TF - TT) * (1 - %P)) | AI62: 88
B63: Simbolo | C63: Descripcion | E63: 1ra. Q | F63: 2da. Q | H63: 1ra. Q
B64: VC | C64: Canasta de Petróleo | H64: = (0.0000 * 0.00% + (0.0000 - 0.0000 - 0.0000) * (1 - 0.00%)) | N64: 0.064199999
B65: PB | C65: Precio del GLP | H65: 0 | M65: 0.0942 | N65: 0.0989
B66: TF | C66: Tarifa de Fraccionam. | M66: 0.4 | N66: 0.4
B67: %P | C67: % Contenido Pentanos | H67: 2da. Q | M67: 0.38
B68: QLGNF | C68: Volumen de LGN | H68: = (0.0000 * 0.00% + (0.0000 - 0.0000 - 0.0000) * (1 - 0.00%))
B69: TT | C69: Tarifa de Transporte | H69: 0

Sheet Abr
A1: Período de Cálculo: | E1: 45748 | F1: 3.697 | S1: , | U1: Días en el mes | W1: 30
A2: PERUPETRO S.A.
A3: DETERMINACION DEL CANON, SOBRECANON y PARTICIPACION (US$)
A4: Correspondiente a Abril 2025
A5: Tipo de Cambio= 3.697
A7: Localidad | C7: Modalidad de Contrato | D7: Calculo del Canon | F7: Volumen Producción / Venta | I7: Canasta o Valor Venta (US$/Unidad) | K7: Deducción de Gastos para determinación de valor de producción en Punto de Fiscalización (US$) | O7: Valor de la Producción (US$) | P7: Canon y Sobrecanon / Participación (US$) | U7: RESUMEN POR PETROLERO Y CONDENSADOS | AA7: RESUMEN POR GAS NATURAL | AG7: Control
A8: - Lote | D8: Período | E8: Fórmula | F8: Unidades | G8: 1ra. Q | H8: 2da. Q / Mes | I8: 1ra. Q | J8: 2da. Q / Mes | K8: Flete Marítimo | L8: Comercialización | M8: Oleoducto | N8: Fiscalización | P8: Total | Q8: Localidad 1 | S8: Localidad 2 | U8: Producción / Venta | X8: Valor Prod | Y8: Valor Canon | AA8: Producción / Venta | AD8: Valor Prod | AE8: Valor Canon | AG8: Total
A9: Piura / Tumbes | Q9: Piura | S9: Tumbes | U9: Bls/Mes | V9: V P (US$) | W9: Bls/Día | X9: US$/Bl | Y9: US$/Bl | Z9: US$ | AA9: MM BTU/Mes | AB9: V P (US$) | AC9: MM BTU/Día | AD9: US$/MM BTU | AE9: US$/MM BTU | AF9: US$ | AG9: Canon
A10: - | B10: I | C10: Licencia | D10: Quincena | E10: F2 | F10: Bls | G10: 5563 | H10: 9025 | I10: 68.515 | J10: 66.7176 | N10: 81.33 | O10: 983193.96 | P10: 184348.87 | Q10: 147479.09 | R10: 0.15 | S10: 36869.77 | T10: 0.0375 | U10: 14588 | V10: 983193.96 | W10: 486.3 | X10: 67.3974 | Y10: 12.637 | Z10: 184348.87
A11: - | B11: I GAS | C11: Licencia | D11: Quincena | E11: F2 | F11: MM BTU | G11: 45273.332 | H11: 44032.59 | I11: 4.1713 | J11: 4.1713 | N11: 227.72 | O11: 372294.07 | P11: 69805.14 | Q11: 55844.11 | R11: 0.15 | S11: 13961.03 | T11: 0.0375 | AA11: 89305.922 | AB11: 372294.07 | AC11: 2976.9 | AD11: 4.1688 | AE11: 0.7816 | AF11: 69805.14
A12: - | B12: II | C12: Licencia | D12: Quincena | E12: F2 | F12: Bls | G12: 4721 | H12: 4896 | I12: 67.4965 | J12: 65.8513 | N12: 653.87 | O12: 640405.07 | P12: 120075.95 | Q12: 96060.76 | R12: 0.15 | S12: 24015.19 | T12: 0.0375 | U12: 9617 | V12: 640405.07 | W12: 320.6 | X12: 66.5909 | Y12: 12.4858 | Z12: 120075.95
A13: - | B13: II - GAS | C13: Licencia | D13: Quincena | E13: F2 | F13: MM BTU | G13: 20922.086 | H13: 17309.28 | I13: 2.95 | J13: 2.95 | N13: 699.42 | O13: 112083.11 | P13: 21015.58 | Q13: 16812.47 | R13: 0.15 | S13: 4203.12 | T13: 0.0375 | AA13: 38231.366 | AB13: 112083.11 | AC13: 1274.4 | AD13: 2.9317 | AE13: 0.5497 | AF13: 21015.58
A14: - | B14: III | C14: Licencia | D14: Quincena | E14: F2 | F14: Bls | G14: 29139 | H14: 33912 | I14: 68.515 | J14: 66.7176 | N14: 1066.88 | O14: 4257919 | P14: 798359.81 | Q14: 638687.84 | R14: 0.15 | S14: 159671.96 | T14: 0.0375 | U14: 63051 | V14: 4257919 | W14: 2101.7 | X14: 67.5313 | Y14: 12.6621 | Z14: 798359.81
A15: - | B15: III - GAS | C15: Licencia | D15: Quincena | E15: F2 | F15: MM BTU | G15: 43870.619 | H15: 47175.65 | I15: 2.9365 | J15: 2.9365 | O15: 267357.37 | P15: 50129.51 | Q15: 40103.61 | R15: 0.15 | S15: 10025.9 | T15: 0.0375 | AA15: 91046.269 | AB15: 267357.37 | AC15: 3034.9 | AD15: 2.9365 | AE15: 0.5506 | AF15: 50129.51
A16: - | B16: IV | C16: Licencia | D16: Quincena | E16: F2 | F16: Bls | G16: 44202 | H16: 48867 | I16: 68.515 | J16: 66.7176 | N16: 1805.34 | O16: 6286983.7 | P16: 1178809.4 | Q16: 943047.55 | R16: 0.15 | S16: 235761.89 | T16: 0.0375 | U16: 93069 | V16: 6286983.7 | W16: 3102.3 | X16: 67.5519 | Y16: 12.666 | Z16: 1178809.4
A17: - | B17: IV - GAS | C17: Licencia | D17: Quincena | E17: F2 | F17: Bls | G17: 45337.798 | H17: 46196.43 | I17: 3.7597 | J17: 3.7597 | N17: 601.69 | O17: 343539.55 | P17: 64413.67 | Q17: 51530.93 | R17: 0.15 | S17: 12882.73 | T17: 0.0375 | U17: 91534.228 | V17: 343539.55 | W17: 3051.1 | X17: 3.7531 | Y17: 0.7037 | Z17: 64413.67
A18: - | B18: V | C18: Licencia | D18: Quincena | E18: F2 | F18: Bls | G18: 2442 | H18: 2540 | I18: 67.5526 | J18: 65.982 | N18: 426.16 | O18: 332131.57 | P18: 62274.67 | Q18: 49819.74 | R18: 0.15 | S18: 12454.93 | T18: 0.0375 | U18: 4982 | V18: 332131.57 | W18: 166.1 | X18: 66.6663 | Y18: 12.4999 | Z18: 62274.67
A19: - | B19: VI (T) | C19: Licencia | D19: Quincena | E19: F2 | F19: Bls | G19: 22295 | H19: 25594 | I19: 68.515 | J19: 66.7176 | N19: 513.99 | O19: 3234598.2 | P19: 606487.16 | Q19: 485189.73 | R19: 0.15 | S19: 121297.43 | T19: 0.0375 | U19: 47889 | V19: 3234598.2 | W19: 1596.3 | X19: 67.5437 | Y19: 12.6644 | Z19: 606487.16
A20: - | B20: VI - GAS | C20: Licencia | D20: Quincena | E20: F2 | F20: MM BTU | G20: 52233.643 | H20: 55360.76 | I20: 4.0132 | J20: 4.0132 | N20: 221.21 | O20: 431576.65 | P20: 80920.62 | Q20: 64736.5 | R20: 0.15 | S20: 16184.12 | T20: 0.0375 | AA20: 107594.4 | AB20: 431576.65 | AC20: 3586.5 | AD20: 4.0111 | AE20: 0.7521 | AF20: 80920.62
A21: - | B21: VII (T) | C21: Licencia | D21: Quincena | E21: F2 | F21: Bls | G21: 14737 | H21: 15767 | I21: 67.5526 | J21: 65.982 | N21: 253.74 | O21: 2035607.1 | P21: 381676.34 | Q21: 305341.07 | R21: 0.15 | S21: 76335.27 | T21: 0.0375 | U21: 30504 | V21: 2035607.1 | W21: 1016.8 | X21: 66.7325 | Y21: 12.5123 | Z21: 381676.34
A22: - | B22: IX | C22: Licencia | D22: Quincena | E22: F2 | F22: Bls | G22: 1794 | H22: 3684 | I22: 68.515 | J22: 66.7176 | N22: 273.26 | O22: 368430.29 | P22: 69080.68 | Q22: 55264.54 | R22: 0.15 | S22: 13816.14 | T22: 0.0375 | U22: 5478 | V22: 368430.29 | W22: 182.6 | X22: 67.2564 | Y22: 12.6106 | Z22: 69080.68
A23: - | B23: X | C23: Licencia | D23: Quincena | E23: F2 | F23: Bls | G23: 117643 | H23: 119655 | I23: 68.6365 | J23: 66.943 | N23: 1233.03 | O23: 16083435 | P23: 3015644.1 | Q23: 2412515.3 | R23: 0.15 | S23: 603128.83 | T23: 0.0375 | U23: 237298 | V23: 16083435 | W23: 7909.9 | X23: 67.7774 | Y23: 12.7083 | Z23: 3015644.1
A24: - | B24: X - GAS | C24: Licencia | D24: Quincena | E24: F2 | F24: MM BTU | G24: 206654.01 | H24: 202457.03 | I24: 2.9 | J24: 2.9 | N24: 933.74 | O24: 1185488.3 | P24: 222279.05 | Q24: 177823.24 | R24: 0.15 | S24: 44455.81 | T24: 0.0375 | AA24: 409111.04 | AB24: 1185488.3 | AC24: 13637 | AD24: 2.8977 | AE24: 0.5433 | AF24: 222279.05
A25: - | B25: XV | C25: Licencia | D25: Quincena | E25: F2 | F25: Bls | G25: 268 | H25: 279 | I25: 67.5526 | J25: 65.982 | N25: 296.03 | O25: 36217.05 | P25: 6790.7 | Q25: 5432.56 | R25: 0.15 | S25: 1358.14 | T25: 0.0375 | U25: 547 | V25: 36217.05 | W25: 18.2 | X25: 66.2103 | Y25: 12.4144 | Z25: 6790.7
A26: - | B26: XIII Crudo | C26: Licencia | D26: Quincena | E26: F2 | F26: Bls | G26: 14456 | H26: 14301 | I26: 65.755 | J26: 66.6476 | N26: 2820.44 | O26: 1900861.2 | P26: 356411.47 | Q26: 285129.18 | R26: 0.15 | S26: 71282.29 | T26: 0.0375 | U26: 28757 | V26: 1900861.2 | W26: 958.6 | X26: 66.1008 | Y26: 12.3939 | Z26: 356411.47
A27: - | B27: XIII Gas | C27: Licencia | D27: Quincena | E27: F2 | F27: MM BTU | G27: 308894.56 | H27: 351713.84 | I27: 3.5083906 | J27: 3.4282966 | N27: 1174.37 | O27: 2289502.1 | P27: 429281.65 | Q27: 343425.33 | R27: 0.15 | S27: 85856.34 | T27: 0.0375 | AA27: 660608.4 | AB27: 2289502.1 | AC27: 22020.3 | AD27: 3.4657 | AE27: 0.6498 | AF27: 429281.65
A28: - | B28: XX | C28: Licencia | D28: Quincena | E28: F2 | F28: Bls | G28: 115 | H28: 104 | I28: 68.515 | J28: 66.7176 | N28: 175.67 | O28: 14642.19 | P28: 2745.41 | Q28: 549.08 | R28: 0.0375 | S28: 2196.33 | T28: 0.15 | U28: 219 | V28: 14642.19 | W28: 7.3 | X28: 66.8593 | Y28: 12.5361 | Z28: 2745.41
A29: - | B29: Z-1 Crudo | C29: Licencia | D29: Quincena | E29: F2 | F29: Bls | G29: 59999 | I29: 65.765 | N29: 888.1 | O29: 3944946.1 | P29: 739677.4 | Q29: 147935.48 | R29: 0.0375 | S29: 591741.92 | T29: 0.15
A30: - | B30: Z-69 Crudo | C30: Licencia | D30: Quincena | E30: F2 | F30: Bls | G30: 33455 | H30: 70626 | I30: 66.8464 | J30: 66.028 | N30: 400.13 | O30: 6899239.7 | P30: 1293607.4 | Q30: 1034886 | R30: 0.15 | S30: 258721.49 | T30: 0.0375
A31: - | B31: Z-69 Gas | C31: Licencia | D31: Quincena | E31: F2 | F31: MM BTU | G31: 147644 | H31: 151458.35 | I31: 2.7743683 | J31: 2.7779597 | N31: 452.18 | O31: 830364.03 | P31: 155693.26 | Q31: 124554.61 | R31: 0.15 | S31: 31138.65 | T31: 0.0375
A32: - | B32: Z-69 Lgn | C32: Licencia | D32: Quincena | E32: F2 | F32: Bls | G32: 10552 | H32: 9971 | I32: 38.5216 | J32: 38.6101 | N32: 435.91 | O32: 791025.32 | P32: 148317.25 | Q32: 118653.8 | R32: 0.15 | S32: 29663.45 | T32: 0.0375
A33: - | B33: Ajustes meses anteriores (1) | O33: 9531.13 | P33: 1787.08 | Q33: 1429.67 | S33: 357.42
B34: Subtotal | C34: Piura / Tumbes US$ | O34: 53651372 | P34: 10059632 | Q34: 7602252.2 | S34: 2457380.1 | U34: 627533.23 | V34: 36517964 | W34: 20917.8 | X34: 58.1929 | Y34: 10.9112 | Z34: 6847118.3 | AA34: 1395897.4 | AB34: 4658301.6 | AC34: 46530 | AD34: 3.3371 | AE34: 0.6257 | AF34: 873431.55 | AG34: 2339082.4
C35: Piura / Tumbes S/. | P35: 37190461 | Q35: 28105526 | S35: 9084934.4
A36: Provincia Puerto Inca Huanuco | Q36: Puerto Inca
A37: - | B37: 131 | C37: Licencia | D37: Quincena | E37: F2 | F37: Bls | G37: 7831 | H37: 9637 | I37: 54.2325 | J37: 52.8025 | N37: 3500.34 | O37: 930052.06 | P37: 139507.81 | Q37: 139507.81 | R37: 0.15 | U37: 17468 | V37: 930052.06 | W37: 582.3 | X37: 53.2432 | Y37: 7.9865 | Z37: 139507.81
A38: - | B38: Ajustes meses anteriores (2)
B39: Subtotal | C39: Provincia Puerto Inca Huanuco US$ | O39: 930052.06 | P39: 139507.81 | Q39: 139507.81 | S39: 0 | U39: 17468 | V39: 930052.06 | W39: 582.3 | X39: 53.2432 | Y39: 7.9865 | Z39: 139507.81 | AA39: 0 | AB39: 0 | AC39: 0 | AD39: 0 | AE39: 0 | AF39: 0 | AG39: 0
C40: Provincia Puerto Inca Huanuco S/. | P40: 515760.37 | Q40: 515760.37 | S40: 0
A41: Loreto / Ucayali | Q41: Loreto | S41: Ucayali
A42: - | B42: 8 | C42: Licencia | D42: Quincena | E42: F2 | F42: Bls | G42: 129075 | H42: 33717 | I42: 57.432218 | J42: 54.852998 | N42: 4694.23 | O42: 9262542 | P42: 1736726.6 | Q42: 1389381.3 | R42: 0.15 | S42: 347345.33 | T42: 0.0375 | U42: 162792 | V42: 9262542 | W42: 5426.4 | X42: 56.898 | Y42: 10.6684 | Z42: 1736726.6
A43: - | B43: 31-C GAS | C43: Licencia | D43: Quincena | E43: F2 | F43: MM BTU | G43: 59615.79 | H43: 12386.03 | I43: 3.6075 | J43: 3.6076 | N43: 1642.56 | O43: 258105.24 | P43: 48394.73 | Q43: 9678.95 | R43: 0.0375 | S43: 38715.79 | T43: 0.15 | AA43: 72001.82 | AB43: 258105.24 | AC43: 2400.1 | AD43: 3.5847 | AE43: 0.6721 | AF43: 48394.73
A44: - | B44: 31-C LGN (*) | C44: Licencia | D44: Quincena | E44: F3 | F44: Bls | N44: 3191.04 | O44: -3191.04 | P44: -598.32 | Q44: -119.66 | R44: 0.0375 | S44: -478.66 | T44: 0.15 | U44: 0 | V44: -3191.04 | W44: 0 | X44: 0 | Y44: 0 | Z44: -598.32
A45: - | B45: 95 | C45: Licencia | D45: Quincena | E45: F2 | F45: Bls | G45: 329058 | H45: 335099 | I45: 47.9625 | J45: 46.8244 | N45: 4694.23 | O45: 31468560 | P45: 5900355 | Q45: 4720284 | R45: 0.15 | S45: 1180071 | T45: 0.0375 | U45: 664157 | V45: 31468560 | W45: 22138.6 | X45: 47.3812 | Y45: 8.884 | Z45: 5900355
A46: - | B46: 67 | C46: Licencia | D46: Quincena | E46: F2 | F46: Bls | O46: 0 | P46: 0 | Q46: 0 | R46: 0.15 | S46: 0 | T46: 0.0375 | U46: 0 | V46: 0 | W46: 0 | X46: 0 | Y46: 0 | Z46: 0
A47: - | B47: Ajustes meses anteriores (3)
B48: Subtotal | C48: Loreto / Ucayali US$ | O48: 40986016 | P48: 7684878 | Q48: 6119224.6 | S48: 1565653.4 | U48: 826949 | V48: 40727911 | W48: 27565 | X48: 49.2508 | Y48: 9.2345 | Z48: 7636483.3 | AA48: 72001.82 | AB48: 258105.24 | AC48: 2400.1 | AD48: 3.5847 | AE48: 0.6721 | AF48: 48394.73 | AG48: 4.4383341e-10
C49: Loreto / Ucayali S/. | P49: 28410994 | Q49: 22622773 | S49: 5788220.8
A50: Cusco | P50: V. Regalías | Q50: Cusco
A51: - | B51: 88 LGN | C51: Licencia | D51: Quincena | E51: F4 | F51: Bls | G51: 743558 | H51: 547576 | I51: 38.5223 | J51: 40.0428 | O51: 50570041 | P51: 18832283 | Q51: 9416141.6 | R51: 0.5 | U51: 1291134 | V51: 50570041 | W51: 43037.8 | X51: 39.1672 | Y51: 7.2929 | Z51: 9416141.6
A52: - | B52: 88 GAS | C52: Licencia | D52: Quincena | E52: F4 | F52: MM BTU | G52: 10992790 | H52: 10330141 | I52: 2.8894 | J52: 2.867 | O52: 61378795 | P52: 22913820 | Q52: 11456910 | R52: 0.5 | AA52: 21322932 | AB52: 61378795 | AC52: 710764.4 | AD52: 2.8785 | AE52: 0.5373 | AF52: 11456910
A53: - | B53: 56 LGN | C53: Licencia | D53: Quincena | E53: F4 | F53: Bls | G53: 161393 | H53: 123347 | I53: 38.508 | J53: 40.1207 | O53: 11163690 | P53: 4465475.8 | Q53: 2232737.9 | R53: 0.5 | U53: 284740 | V53: 11163690 | W53: 9491.3 | X53: 39.2066 | Y53: 7.8413 | Z53: 2232737.9
A54: - | B54: 56 GAS | C54: Licencia | D54: Quincena | E54: F4 | F54: MM BTU | G54: 4282579.2 | H54: 1803261.9 | I54: 4.651 | J54: 4.455 | O54: 27951807 | P54: 10621687 | Q54: 5310843.4 | R54: 0.5 | AA54: 6085841 | AB54: 27951807 | AC54: 202861.4 | AD54: 4.5929 | AE54: 0.8727 | AF54: 5310843.4
A55: - | B55: 57 LGN | C55: Licencia | D55: Quincena | E55: F4 | F55: Bls | G55: 248524 | H55: 108673 | I55: 34.8697 | J55: 35.2656 | O55: 12498376 | P55: 835626.7 | Q55: 417813.35 | R55: 0.5 | U55: 357197 | V55: 12498376 | W55: 11906.6 | X55: 34.9901 | Y55: 1.1697 | Z55: 417813.35
A56: - | B56: 57 GAS | C56: Licencia | D56: Quincena | E56: F4 | F56: MM BTU | G56: 4280022.4 | H56: 1945386.1 | I56: 5.53 | J56: 5.53 | O56: 34426509 | P56: 3910854.8 | Q56: 1955427.4 | R56: 0.5 | AA56: 6225408.5 | AB56: 34426509 | AC56: 207513.6 | AD56: 5.53 | AE56: 0.3141 | AF56: 1955427.4
A57: - | B57: Ajustes meses anteriores (4) | O57: -9748222.4 | P57: -1226112 | Q57: -613056
B58: Subtotal | C58: Cusco US$ | G58: 4282579.2 | H58: 1803261.9 | O58: 1.8824099e+08 | P58: 60353636 | Q58: 30176818 | U58: 1933071 | V58: 74232106 | W58: 64435.7 | X58: 38.4011 | Y58: 6.2422 | Z58: 12066693 | AA58: 33634181 | AB58: 1.2375711e+08 | AC58: 1121139.4 | AD58: 3.6795 | AE58: 0.5567 | AF58: 18723181 | AG58: -613056
C59: Cusco S/. | G59: 4.651 | H59: 4.455 | Q59: 1.115637e+08
A60: Total General | G60: 19918276 | H60: 8033531.5 | I60: 27951807 | J60: #REF! | K60: #REF! | M60: 0 | N60: 33356.61 | O60: 2.8380844e+08 | P60: 48060836 | Q60: 1.7768091e+08 | U60: 3405021.2 | V60: 1.5240803e+08 | W60: 113500.8 | X60: 44.7598 | Y60: 7.8384 | Z60: 26689802 | AA60: 35102080 | AB60: 1.2867352e+08 | AC60: 1170069.5 | AD60: 3.6657 | AE60: 0.5597 | AF60: 19645007 | AG60: 1726026.4
A62: (*) | B62: Determinación de Canasta de los Líquidos de Gas Natural (VLGNF) | H62: = ( VC * %P + (PB - TF - TT) * (1 - %P))
B63: Simbolo | C63: Descripcion | E63: 1ra. Q | F63: 2da. Q | H63: 1ra. Q
B64: VC | C64: Canasta de Petróleo | H64: = (0.0000 * 0.00% + (0.0000 - 0.0000 - 0.0000) * (1 - 0.00%)) | N64: 36728.48
B65: PB | C65: Precio del GLP | H65: 0 | M65: 0.0942 | N65: 0.0989
B66: TF | C66: Tarifa de Fraccionam. | M66: 0.4 | N66: 0.4
B67: %P | C67: % Contenido Pentanos | H67: 2da. Q | M67: 0.38
B68: QLGNF | C68: Volumen de LGN | H68: = (0.0000 * 0.00% + (0.0000 - 0.0000 - 0.0000) * (1 - 0.00%))
B69: TT | C69: Tarifa de Transporte | H69: 0

Sheet May
A1: Período de Cálculo: | E1: 45778 | F1: 3.604 | S1: ,
A2: PERUPETRO S.A.
A3: DETERMINACION DEL CANON, SOBRECANON y PARTICIPACION (US$)
A4: Correspondiente a Mayo 2025
A5: Tipo de Cambio= 3.604
A7: Localidad | C7: Modalidad de Contrato | D7: Calculo del Canon | F7: Volumen Producción / Venta | I7: Canasta o Valor Venta (US$/Unidad) | K7: Deducción de Gastos para determinación de valor de producción en Punto de Fiscalización (US$) | O7: Valor de la Producción (US$) | P7: Canon y Sobrecanon / Participación (US$)
A8: - Lote | D8: Período | E8: Fórmula | F8: Unidades | G8: 1ra. Q | H8: 2da. Q / Mes | I8: 1ra. Q | J8: 2da. Q / Mes | K8: Flete Marítimo | L8: Comercialización | M8: Oleoducto | N8: Fiscalización | P8: Total | Q8: Localidad 1 | S8: Localidad 2
A9: Piura / Tumbes | Q9: Piura | S9: Tumbes
A10: - | B10: I | C10: Licencia | D10: Quincena | E10: F2 | F10: Bls | G10: 4239 | H10: 10098 | I10: 63.7942 | J10: 65.0262 | N10: 85.11 | O10: 926973.07 | P10: 173807.45 | Q10: 139045.96 | R10: 0.15 | S10: 34761.49 | T10: 0.0375
A11: - | B11: I GAS | C11: Licencia | D11: Quincena | E11: F2 | F11: MM BTU | G11: 36056.804 | H11: 47224.107 | I11: 3.947 | J11: 3.947 | N11: 238.3 | O11: 328471.45 | P11: 61588.4 | Q11: 49270.72 | R11: 0.15 | S11: 12317.68 | T11: 0.0375
A12: - | B12: II | C12: Licencia | D12: Quincena | E12: F2 | F12: Bls | G12: 4864 | H12: 4986 | I12: 63.4053 | J12: 64.597 | N12: 684.26 | O12: 629799.76 | P12: 118087.46 | Q12: 94469.96 | R12: 0.15 | S12: 23617.49 | T12: 0.0375
A13: - | B13: II - GAS | C13: Licencia | D13: Quincena | E13: F2 | F13: MM BTU | G13: 18011.858 | H13: 17660.249 | I13: 2.95 | J13: 2.95 | N13: 731.92 | O13: 104500.79 | P13: 19593.9 | Q13: 15675.12 | R13: 0.15 | S13: 3918.78 | T13: 0.0375
A14: - | B14: III | C14: Licencia | D14: Quincena | E14: F2 | F14: Bls | G14: 34967 | H14: 35549 | I14: 63.7942 | J14: 65.0262 | N14: 1088.5 | O14: 4541219.7 | P14: 851478.69 | Q14: 681182.95 | R14: 0.15 | S14: 170295.74 | T14: 0.0375
A15: - | B15: III - GAS | C15: Licencia | D15: Quincena | E15: F2 | F15: MM BTU | G15: 18882.184 | H15: 68401.688 | I15: 2.8207 | J15: 2.8207 | O15: 246201.62 | P15: 46162.8 | Q15: 36930.24 | R15: 0.15 | S15: 9232.56 | T15: 0.0375
A16: - | B16: IV | C16: Licencia | D16: Quincena | E16: F2 | F16: Bls | G16: 48478 | H16: 57197 | I16: 63.7942 | J16: 65.0262 | N16: 1861.28 | O16: 6810057.5 | P16: 1276885.8 | Q16: 1021508.6 | R16: 0.15 | S16: 255377.16 | T16: 0.0375
A17: - | B17: IV - GAS | C17: Licencia | D17: Quincena | E17: F2 | F17: MM BTU | G17: 58619.96 | H17: 85565.027 | I17: 3.6743 | J17: 3.6743 | N17: 601.69 | O17: 529177.21 | P17: 99220.73 | Q17: 79376.58 | R17: 0.15 | S17: 19844.15 | T17: 0.0375
A18: - | B18: V | C18: Licencia | D18: Quincena | E18: F2 | F18: Bls | G18: 3281 | H18: 3239 | I18: 63.4822 | J18: 64.628 | N18: 445.96 | O18: 417169.23 | P18: 78219.23 | Q18: 62575.38 | R18: 0.15 | S18: 15643.85 | T18: 0.0375
A19: - | B19: VI (T) | C19: Licencia | D19: Quincena | E19: F2 | F19: Bls | G19: 22783 | H19: 27039 | I19: 63.7942 | J19: 65.0262 | N19: 537.88 | O19: 3211128.8 | P19: 602086.65 | Q19: 481669.32 | R19: 0.15 | S19: 120417.33 | T19: 0.0375
A20: - | B20: VI - GAS | C20: Licencia | D20: Quincena | E20: F2 | F20: MM BTU | G20: 52277.512 | H20: 58835.083 | I20: 3.8883 | J20: 3.8883 | N20: 231.49 | O20: 431807.61 | P20: 80963.93 | Q20: 64771.14 | R20: 0.15 | S20: 16192.79 | T20: 0.0375
A21: - | B21: VII (T) | C21: Licencia | D21: Quincena | E21: F2 | F21: Bls | G21: 14960 | H21: 16473 | I21: 63.4822 | J21: 64.628 | N21: 265.53 | O21: 2014045.2 | P21: 377633.48 | Q21: 302106.78 | R21: 0.15 | S21: 75526.7 | T21: 0.0375
A22: - | B22: IX | C22: Licencia | D22: Quincena | E22: F2 | F22: Bls | G22: 1571 | H22: 3493 | I22: 63.7942 | J22: 65.0262 | N22: 285.96 | O22: 327071.25 | P22: 61325.86 | Q22: 49060.69 | R22: 0.15 | S22: 12265.17 | T22: 0.0375
A23: - | B23: X | C23: Licencia | D23: Quincena | E23: F2 | F23: Bls | G23: 120264 | H23: 128398 | I23: 64.5147 | J23: 65.9355 | N23: 1268.81 | O23: 16223513 | P23: 3041908.8 | Q23: 2433527 | R23: 0.15 | S23: 608381.75 | T23: 0.0375
A24: - | B24: X - GAS | C24: Licencia | D24: Quincena | E24: F2 | F24: MM BTU | G24: 203977.86 | H24: 214188.41 | I24: 2.9 | J24: 3.0477 | N24: 955.61 | O24: 1243362.2 | P24: 233130.41 | Q24: 186504.33 | R24: 0.15 | S24: 46626.08 | T24: 0.0375
A25: - | B25: XV | C25: Licencia | D25: Quincena | E25: F2 | F25: Bls | G25: 266 | H25: 263 | I25: 63.4822 | J25: 64.628 | N25: 309.79 | O25: 33573.64 | P25: 6295.06 | Q25: 5036.05 | R25: 0.15 | S25: 1259.01 | T25: 0.0375
A26: - | B26: XIII Crudo | C26: Licencia | D26: Quincena | E26: F2 | F26: Bls | G26: 13819 | H26: 14223 | I26: 61.0142 | J26: 64.9562 | N26: 2951.52 | O26: 1764075.7 | P26: 330764.2 | Q26: 264611.36 | R26: 0.15 | S26: 66152.84 | T26: 0.0375
A27: - | B27: XIII Gas | C27: Licencia | D27: Quincena | E27: F2 | F27: MM BTU | G27: 306602.66 | H27: 489045.79 | I27: 3.4141104 | J27: 3.0155305 | N27: 1228.95 | O27: 2521507.8 | P27: 472782.72 | Q27: 378226.17 | R27: 0.15 | S27: 94556.54 | T27: 0.0375
A28: - | B28: XX | C28: Licencia | D28: Quincena | E28: F2 | F28: Bls | G28: 145 | H28: 130 | I28: 63.7942 | J28: 65.0262 | N28: 183.83 | O28: 17519.74 | P28: 3284.95 | Q28: 656.99 | R28: 0.0375 | S28: 2627.96 | T28: 0.15
A29: - | B29: Z-1 Crudo | C29: Licencia | D29: Quincena | E29: F2 | F29: Bls | N29: 929.37 | O29: -929.37 | P29: -174.26 | Q29: -34.85 | R29: 0.0375 | S29: -139.41 | T29: 0.15
A30: - | B30: Z-69 Crudo | C30: Licencia | D30: Quincena | E30: F2 | F30: Bls | G30: 26779 | H30: 74785 | I30: 63.2618 | J30: 64.7491 | N30: 473.2 | O30: 6535876 | P30: 1225476.8 | Q30: 980381.4 | R30: 0.15 | S30: 245095.35 | T30: 0.0375
A31: - | B31: Z-69 Gas | C31: Licencia | D31: Quincena | E31: F2 | F31: MM BTU | G31: 92072.49 | H31: 158544.66 | I31: 2.7340169 | J31: 2.744897 | N31: 418.73 | O31: 686916.5 | P31: 128796.84 | Q31: 103037.48 | R31: 0.15 | S31: 25759.37 | T31: 0.0375
A32: - | B32: Z-69 Lgn | C32: Licencia | D32: Quincena | E32: F2 | F32: Bls | G32: 10457 | H32: 10688 | I32: 37.5968 | J32: 36.9593 | N32: 456.18 | O32: 787714.56 | P32: 147696.48 | Q32: 118157.18 | R32: 0.15 | S32: 29539.3 | T32: 0.0375
A33: - | B33: Ajustes meses anteriores (1) | O33: -60569.49 | P33: -11356.79 | Q33: -9085.45 | S33: -2271.36
B34: Subtotal | C34: Piura / Tumbes US$ | O34: 50270184 | P34: 9425659.5 | Q34: 7538661.1 | S34: 1886998.3
C35: Piura / Tumbes S/. | P35: 33970077 | Q35: 27169335 | S35: 6800742
A36: Provincia Puerto Inca Huanuco | Q36: Puerto Inca
A37: - | B37: 131 | C37: Licencia | D37: Quincena | E37: F2 | F37: Bls | G37: 6347 | H37: 8371 | I37: 51.0185 | J37: 52.1568 | N37: 3666.42 | O37: 756752.57 | P37: 113512.89 | Q37: 113512.89 | R37: 0.15
A38: - | B38: Ajustes meses anteriores (2)
B39: Subtotal | C39: Provincia Puerto Inca Huanuco US$ | O39: 756752.57 | P39: 113512.89 | Q39: 113512.89 | S39: 0
C40: Provincia Puerto Inca Huanuco S/. | P40: 409100.46 | Q40: 409100.46 | S40: 0
A41: Loreto / Ucayali | Q41: Loreto | S41: Ucayali
A42: - | B42: 8 | C42: Licencia | D42: Quincena | E42: F2 | F42: Bls | G42: 30107 | H42: 43447 | I42: 51.4315 | J42: 51.9333 | N42: 4908.99 | O42: 3799885.3 | P42: 712478.49 | Q42: 569982.79 | R42: 0.15 | S42: 142495.7 | T42: 0.0375
A43: - | B43: 31-C GAS | C43: Licencia | D43: Quincena | E43: F2 | F43: MM BTU | G43: 6086.299 | I43: 3.6076 | N43: 1662.97 | O43: 20293.96 | P43: 3805.12 | Q43: 761.02 | R43: 0.0375 | S43: 3044.09 | T43: 0.15
A44: - | B44: 31-C LGN (*) | C44: Licencia | D44: Quincena | E44: F3 | F44: Bls | N44: 3283.41 | O44: -3283.41 | P44: -615.64 | Q44: -123.13 | R44: 0.0375 | S44: -492.51 | T44: 0.15
A45: - | B45: 95 | C45: Licencia | D45: Quincena | E45: F2 | F45: Bls | G45: 275543 | H45: 334582 | I45: 44.8737 | J45: 45.8441 | N45: 4912.4 | O45: 27698332 | P45: 5193437.3 | Q45: 4154749.8 | R45: 0.15 | S45: 1038687.5 | T45: 0.0375
A46: - | B46: 67 | C46: Licencia | D46: Quincena | E46: F2 | F46: Bls | O46: 0 | P46: 0 | Q46: 0 | R46: 0.15 | S46: 0 | T46: 0.0375
A47: - | B47: Ajustes meses anteriores (3)
B48: Subtotal | C48: Loreto / Ucayali US$ | O48: 31515228 | P48: 5909105.3 | Q48: 4725370.5 | S48: 1183734.7
C49: Loreto / Ucayali S/. | P49: 21296415 | Q49: 17030235 | S49: 4266180
A50: Cusco | P50: V. Regalías | Q50: Cusco
A51: - | B51: 88 LGN | C51: Licencia | D51: Quincena | E51: F4 | F51: Bls | G51: 500687 | H51: 796299 | I51: 37.0442 | J51: 36.3278 | O51: 47475340 | P51: 17679817 | Q51: 8839908.3 | R51: 0.5
A52: - | B52: 88 GAS | C52: Licencia | D52: Quincena | E52: F4 | F52: MM BTU | G52: 10696133 | H52: 13421910 | I52: 2.943 | J52: 2.9336 | O52: 70853586 | P52: 26442900 | Q52: 13221450 | R52: 0.5
A53: - | B53: 56 LGN | C53: Licencia | D53: Quincena | E53: F4 | F53: Bls | G53: 157744 | H53: 168508 | I53: 37.0802 | J53: 36.329 | O53: 11970906 | P53: 4788362.5 | Q53: 2394181.2 | R53: 0.5
A54: - | B54: 56 GAS | C54: Licencia | D54: Quincena | E54: F4 | F54: MM BTU | G54: 4330703.1 | H54: 4573558.5 | I54: 4.449 | J54: 4.605 | O54: 40328535 | P54: 15324843 | Q54: 7662421.6 | R54: 0.5
A55: - | B55: 57 LGN | C55: Licencia | D55: Quincena | E55: F4 | F55: Bls | G55: 239378 | H55: 228102 | I55: 33.1486 | J55: 32.4475 | O55: 15336385 | P55: 1023257.1 | Q55: 511628.56 | R55: 0.5
A56: - | B56: 57 GAS | C56: Licencia | D56: Quincena | E56: F4 | F56: MM BTU | G56: 4157554.2 | H56: 3964274.6 | I56: 4.416 | J56: 4.416 | O56: 35865996 | P56: 4059645.7 | Q56: 2029822.9 | R56: 0.5
A57: - | B57: Ajustes meses anteriores (4) | O57: -6993440.2 | P57: -666906.54 | Q57: -333453.28
B58: Subtotal | C58: Cusco US$ | G58: 4330703.1 | H58: 4573558.5 | O58: 2.1483731e+08 | P58: 68651919 | Q58: 34325959
C59: Cusco S/. | G59: 4.449 | H59: 4.605 | Q59: 1.2371076e+08
A60: Total General | G60: 19267298 | H60: 21061237 | I60: 40328535 | J60: #REF! | K60: #REF! | M60: 0 | N60: 34668.06 | O60: 2.9737947e+08 | P60: 49774237 | Q60: 1.7938635e+08
A62: (*) | B62: Determinación de Canasta de los Líquidos de Gas Natural (VLGNF) | H62: = ( VC * %P + (PB - TF - TT) * (1 - %P))
B63: Simbolo | C63: Descripcion | E63: 1ra. Q | F63: 2da. Q | H63: 1ra. Q
B64: VC | C64: Canasta de Petróleo | H64: = (0.0000 * 0.00% + (0.0000 - 0.0000 - 0.0000) * (1 - 0.00%)) | N64: 0.064199999
B65: PB | C65: Precio del GLP | H65: 0 | M65: 0.0942 | N65: 0.0989
B66: TF | C66: Tarifa de Fraccionam. | M66: 0.4 | N66: 0.4
B67: %P | C67: % Contenido Pentanos | H67: 2da. Q | M67: 0.38
B68: QLGNF | C68: Volumen de LGN | H68: = (0.0000 * 0.00% + (0.0000 - 0.0000 - 0.0000) * (1 - 0.00%))
B69: TT | C69: Tarifa de Transporte | H69: 0

Sheet Jun
A1: Período de Cálculo: | E1: 45444 | F1: 3.5560 | S1: ,
A2: PERUPETRO S.A.
A3: DETERMINACION DEL CANON, SOBRECANON y PARTICIPACION (US$)
A4: Correspondiente a Junio 2024
A5: Tipo de Cambio= 3.556
A7: Localidad | C7: Modalidad de Contrato | D7: Calculo del Canon | F7: Volumen Producción / Venta | I7: Canasta o Valor Venta (US$/Unidad) | K7: Deducción de Gastos para determinación de valor de producción en Punto de Fiscalización (US$) | O7: Valor de la Producción (US$) | P7: Canon y Sobrecanon / Participación (US$)
A8: - Lote | D8: Período | E8: Fórmula | F8: Unidades | G8: 1ra. Q | H8: 2da. Q / Mes | I8: 1ra. Q | J8: 2da. Q / Mes | K8: Flete Marítimo | L8: Comercialización | M8: Oleoducto | N8: Fiscalización | P8: Total | Q8: Localidad 1 | S8: Localidad 2
A9: Piura / Tumbes | Q9: Piura | S9: Tumbes
A10: - | B10: I | C10: Licencia | D10: Quincena | E10: F2 | F10: Bls | G10: 3827 | H10: 10340 | I10: 68.2985 | J10: 73.2594 | N10: 72.95 | O10: 1018807.6 | P10: 191026.43 | Q10: 152821.14 | R10: 0.15 | S10: 38205.29 | T10: 0.0375
A11: - | B11: I GAS | C11: Licencia | D11: Quincena | E11: F2 | F11: MM BTU | G11: 43888.609 | H11: 43795.698 | I11: 3.7884 | J11: 3.7884 | N11: 204.27 | O11: 331978.96 | P11: 62246.06 | Q11: 49796.84 | R11: 0.15 | S11: 12449.21 | T11: 0.0375
A12: - | B12: II | C12: Licencia | D12: Quincena | E12: F2 | F12: Bls | G12: 4572 | H12: 4495 | I12: 68.3528 | J12: 72.2297 | N12: 586.55 | O12: 636594.95 | P12: 119361.55 | Q12: 95489.24 | R12: 0.15 | S12: 23872.31 | T12: 0.0375
A13: - | B13: II - GAS | C13: Licencia | D13: Quincena | E13: F2 | F13: MM BTU | G13: 21113.802 | H13: 21457.217 | I13: 2.95 | J13: 2.95 | N13: 627.4 | O13: 124957.11 | P13: 23429.46 | Q13: 18743.57 | R13: 0.15 | S13: 4685.89 | T13: 0.0375
A14: - | B14: III | C14: Licencia | D14: Quincena | E14: F2 | F14: Bls | G14: 32537 | H14: 32943 | I14: 68.2985 | J14: 73.2594 | N14: 1018.99 | O14: 4634593.7 | P14: 868986.32 | Q14: 695189.06 | R14: 0.15 | S14: 173797.26 | T14: 0.0375
A15: - | B15: III - GAS | C15: Licencia | D15: Quincena | E15: F2 | F15: MM BTU | G15: 74613.026 | H15: 87916.833 | I15: 2.6482 | J15: 2.6482 | O15: 430411.58 | P15: 80702.17 | Q15: 64561.74 | R15: 0.15 | S15: 16140.43 | T15: 0.0375
A16: - | B16: IV | C16: Licencia | D16: Quincena | E16: F2 | F16: Bls | G16: 49822 | H16: 55700 | I16: 68.2985 | J16: 73.2594 | N16: 1681.41 | O16: 7481635 | P16: 1402806.6 | Q16: 1122245.3 | R16: 0.15 | S16: 280561.31 | T16: 0.0375
A17: - | B17: IV - GAS | C17: Licencia | D17: Quincena | E17: F2 | F17: Bls | G17: 74561.993 | H17: 82778.781 | I17: 3.2204 | J17: 3.2204 | N17: 601.69 | O17: 506098.54 | P17: 94893.48 | Q17: 75914.78 | R17: 0.15 | S17: 18978.7 | T17: 0.0375
A18: - | B18: V | C18: Licencia | D18: Quincena | E18: F2 | F18: Bls | G18: 2809 | H18: 2736 | I18: 68.4018 | J18: 72.2478 | N18: 382.28 | O18: 389428.36 | P18: 73017.82 | Q18: 58414.25 | R18: 0.15 | S18: 14603.56 | T18: 0.0375
A19: - | B19: VI (T) | C19: Licencia | D19: Quincena | E19: F2 | F19: Bls | G19: 22919 | H19: 25451 | I19: 68.2985 | J19: 73.2594 | N19: 461.07 | O19: 3429397.2 | P19: 643011.98 | Q19: 514409.59 | R19: 0.15 | S19: 128602.4 | T19: 0.0375
A20: - | B20: VI - GAS | C20: Licencia | D20: Quincena | E20: F2 | F20: MM BTU | G20: 60565.077 | H20: 57404.753 | I20: 3.7414 | J20: 3.7414 | N20: 198.43 | O20: 441173.89 | P20: 82720.1 | Q20: 66176.08 | R20: 0.15 | S20: 16544.02 | T20: 0.0375
A21: - | B21: VII (T) | C21: Licencia | D21: Quincena | E21: F2 | F21: Bls | G21: 15003 | H21: 15067 | I21: 68.4018 | J21: 72.2478 | N21: 227.62 | O21: 2114562.2 | P21: 396480.41 | Q21: 317184.33 | R21: 0.15 | S21: 79296.08 | T21: 0.0375
A22: - | B22: IX | C22: Licencia | D22: Quincena | E22: F2 | F22: Bls | G22: 1897 | H22: 2891 | I22: 68.2985 | J22: 73.2594 | N22: 245.13 | O22: 341110.05 | P22: 63958.13 | Q22: 51166.51 | R22: 0.15 | S22: 12791.63 | T22: 0.0375
A23: - | B23: X | C23: Licencia | D23: Quincena | E23: F2 | F23: Bls | G23: 121932 | H23: 124105 | I23: 69.7227 | J23: 74.358 | N23: 1159.06 | O23: 17728469 | P23: 3324087.9 | Q23: 2659270.3 | R23: 0.15 | S23: 664817.58 | T23: 0.0375
A24: - | B24: X - GAS | C24: Licencia | D24: Quincena | E24: F2 | F24: MM BTU | G24: 204852.25 | H24: 203819.33 | I24: 3.1 | J24: 3.1 | N24: 890.59 | O24: 1265991.3 | P24: 237373.37 | Q24: 189898.7 | R24: 0.15 | S24: 47474.67 | T24: 0.0375
A25: - | B25: XV | C25: Licencia | D25: Quincena | E25: F2 | F25: Bls | G25: 269 | H25: 249 | I25: 68.4018 | J25: 72.2478 | N25: 265.55 | O25: 36124.23 | P25: 6773.29 | Q25: 5418.63 | R25: 0.15 | S25: 1354.66 | T25: 0.0375
A26: - | B26: XIII Crudo | C26: Licencia | D26: Quincena | E26: F2 | F26: Bls | G26: 13089 | H26: 13167 | I26: 68.2285 | J26: 73.1794 | N26: 2530.05 | O26: 1854065.9 | P26: 347637.37 | Q26: 278109.89 | R26: 0.15 | S26: 69527.47 | T26: 0.0375
A27: - | B27: XIII Gas | C27: Licencia | D27: Quincena | E27: F2 | F27: MM BTU | G27: 445963.87 | H27: 474898.98 | I27: 3.0524003 | J27: 2.9997658 | N27: 1053.46 | O27: 2785846 | P27: 522346.12 | Q27: 417876.91 | R27: 0.15 | S27: 104469.22 | T27: 0.0375
A28: - | B28: XX | C28: Licencia | D28: Quincena | E28: F2 | F28: Bls | G28: 132 | H28: 149 | I28: 68.2985 | J28: 73.2594 | N28: 157.58 | O28: 19773.47 | P28: 3707.53 | Q28: 741.51 | R28: 0.0375 | S28: 2966.02 | T28: 0.15
A29: - | B29: Z-1 Crudo | C29: Licencia | D29: Quincena | E29: F2 | F29: Bls | N29: 796.66 | O29: -796.66 | P29: -149.37 | Q29: -29.87 | R29: 0.0375 | S29: -119.5 | T29: 0.15
A30: - | B30: Z-69 Crudo | C30: Licencia | D30: Quincena | E30: F2 | F30: Bls | G30: 42954 | H30: 61701 | I30: 67.42 | J30: 71.9682 | N30: 405.63 | O30: 7336063 | P30: 1375511.8 | Q30: 1100409.4 | R30: 0.15 | S30: 275104.75 | T30: 0.0375
A31: - | B31: Z-69 Gas | C31: Licencia | D31: Quincena | E31: F2 | F31: MM BTU | G31: 139076.77 | I31: 2.7472379 | N31: 358.94 | O31: 792022.65 | P31: 148504.25 | Q31: 118803.41 | R31: 0.15 | S31: 29700.85 | T31: 0.0375
A32: - | B32: Z-69 Lgn | C32: Licencia | D32: Quincena | E32: F2 | F32: Bls | G32: 9893 | H32: 9747 | I32: 36.8591 | J32: 38.6444 | N32: 391.04 | O32: 740923.01 | P32: 138923.06 | Q32: 111138.45 | R32: 0.15 | S32: 27784.61 | T32: 0.0375
A33: - | B33: Ajustes meses anteriores (1) | O33: -144239.3 | P33: -27044.84 | Q33: -21635.89 | S33: -5408.98
B34: Subtotal | C34: Piura / Tumbes US$ | O34: 54294992 | P34: 10180311 | Q34: 8142113.9 | S34: 2038199.4
C35: Piura / Tumbes S/. | P35: 36201186 | Q35: 28953357 | S35: 7247837.2
A36: Provincia Puerto Inca Huanuco | Q36: Puerto Inca
A37: - | B37: 131 | C37: Licencia | D37: Quincena | E37: F2 | F37: Bls | G37: 7143 | H37: 4651 | I37: 55.6958 | J37: 60.3319 | N37: 3142.87 | O37: 675295.9 | P37: 101294.39 | Q37: 101294.39 | R37: 0.15
A38: - | B38: Ajustes meses anteriores (2)
B39: Subtotal | C39: Provincia Puerto Inca Huanuco US$ | O39: 675295.9 | P39: 101294.39 | Q39: 101294.39 | S39: 0
C40: Provincia Puerto Inca Huanuco S/. | P40: 360202.85 | Q40: 360202.85 | S40: 0
A41: Loreto / Ucayali | Q41: Loreto | S41: Ucayali
A42: - | B42: 8 | C42: Licencia | D42: Quincena | E42: F2 | F42: Bls | G42: 50610 | H42: 25361 | I42: 54.8798 | J42: 58.7897 | N42: 4207.99 | O42: 4264224.3 | P42: 799542.05 | Q42: 639633.64 | R42: 0.15 | S42: 159908.41 | T42: 0.0375
A43: - | B43: 31-C GAS | C43: Licencia | D43: Quincena | E43: F2 | F43: MM BTU | G43: 72831.452 | H43: 39766.571 | I43: 3.6079 | J43: 3.6081 | N43: 1597.34 | O43: 404653.02 | P43: 75872.44 | Q43: 15174.49 | R43: 0.0375 | S43: 60697.95 | T43: 0.15
A44: - | B44: 31-C LGN (*) | C44: Licencia | D44: Quincena | E44: F3 | F44: Bls | N44: 2986.39 | O44: -2986.39 | P44: -559.95 | Q44: -111.99 | R44: 0.0375 | S44: -447.96 | T44: 0.15
A45: - | B45: 95 | C45: Licencia | D45: Quincena | E45: F2 | F45: Bls | G45: 259919 | H45: 284856 | I45: 48.5338 | J45: 51.6672 | N45: 4210.92 | O45: 27328358 | P45: 5124067.1 | Q45: 4099253.7 | R45: 0.15 | S45: 1024813.4 | T45: 0.0375
A46: - | B46: 67 | C46: Licencia | D46: Quincena | E46: F2 | F46: Bls | O46: 0 | P46: 0 | Q46: 0 | R46: 0.15 | S46: 0 | T46: 0.0375
A47: - | B47: Ajustes meses anteriores (3) | U47: =Q37+May!Q37+Abr!Q37+Mar!Q37+Feb!Q37+Ene!Q37 -> 864878.74
B48: Subtotal | C48: Loreto / Ucayali US$ | O48: 31994249 | P48: 5998921.6 | Q48: 4753949.8 | S48: 1244971.8
C49: Loreto / Ucayali S/. | P49: 21332165 | Q49: 16905045 | S49: 4427119.8
A50: Cusco | P50: V. Regalías | Q50: Cusco
A51: - | B51: 88 LGN | C51: Licencia | D51: Quincena | E51: F4 | F51: Bls | G51: 735305 | H51: 753118 | I51: 36.7381 | J51: 38.376 | O51: 55915365 | P51: 20822882 | Q51: 10411441 | R51: 0.5
A52: - | B52: 88 GAS | C52: Licencia | D52: Quincena | E52: F4 | F52: MM BTU | G52: 13285924 | H52: 13642692 | I52: 2.8936 | J52: 2.9629 | O52: 78866123 | P52: 29434464 | Q52: 14717232 | R52: 0.5
A53: - | B53: 56 LGN | C53: Licencia | D53: Quincena | E53: F4 | F53: Bls | G53: 106705 | H53: 157825 | I53: 36.5892 | J53: 38.3809 | O53: 9961716.1 | P53: 3984686.5 | Q53: 1992343.2 | R53: 0.5
A54: - | B54: 56 GAS | C54: Licencia | D54: Quincena | E54: F4 | F54: MM BTU | G54: 4352047.2 | H54: 4344863.9 | I54: 4.642 | J54: 5.557 | O54: 44346612 | P54: 16851713 | Q54: 8425856.3 | R54: 0.5
A55: - | B55: 57 LGN | C55: Licencia | D55: Quincena | E55: F4 | F55: Bls | G55: 146693 | H55: 244060 | I55: 33.671 | J55: 35.0888 | O55: 13503073 | P55: 903160.07 | Q55: 451580.03 | R55: 0.5
A56: - | B56: 57 GAS | C56: Licencia | D56: Quincena | E56: F4 | F56: MM BTU | G56: 2662414.2 | H56: 4255124.8 | I56: 4.495 | J56: 4.495 | O56: 31094338 | P56: 3571745.8 | Q56: 1785872.9 | R56: 0.5
A57: - | B57: Ajustes meses anteriores (4) | O57: -377182.98 | P57: -410923.32 | Q57: -205461.66
B58: Subtotal | C58: Cusco US$ | G58: 4352047.2 | H58: 4344863.9 | O58: 2.3331004e+08 | P58: 75157728 | Q58: 37578864
C59: Cusco S/. | G59: 4.642 | H59: 5.557 | Q59: 1.3363044e+08
A60: Total General | G60: 20202203 | H60: 24144409 | I60: 44346612 | J60: #REF! | K60: #REF! | M60: 0 | N60: 30461.86 | O60: 3.2027458e+08 | P60: 53859391 | Q60: 1.91524e+08
A62: (*) | B62: Determinación de Canasta de los Líquidos de Gas Natural (VLGNF) | H62: = ( VC * %P + (PB - TF - TT) * (1 - %P))
B63: Simbolo | C63: Descripcion | E63: 1ra. Q | F63: 2da. Q | H63: 1ra. Q
B64: VC | C64: Canasta de Petróleo | H64: ="= ("&TEXT(E64,"0.0000")&" * "&TEXT(E67,"0.00%")&" + ("&TEXT(E65,"0.0000")&" - "&TEXT(E66,"0.0000")&" - "&TEXT(E69,"0.0000")&") * (1 - "&TEXT(E67,"0.00%")&"))" -> = (0.0000 * 0.00% + (0.0000 - 0.0000 - 0.0000) * (1 - 0.00%))
B65: PB | C65: Precio del GLP | H65: =((85.98%*E64+4.4221)*E67+(E65-E66-E69)*(1-E67)) -> 0 | M65: 0.0942
B66: TF | C66: Tarifa de Fraccionam. | M66: 0.4
B67: %P | C67: % Contenido Pentanos | H67: 2da. Q | M67: 0.38
B68: QLGNF | C68: Volumen de LGN | H68: ="= ("&TEXT(F64,"0.0000")&" * "&TEXT(F67,"0.00%")&" + ("&TEXT(F65,"0.0000")&" - "&TEXT(F66,"0.0000")&" - "&TEXT(F69,"0.0000")&") * (1 - "&TEXT(F67,"0.00%")&"))" -> = (0.0000 * 0.00% + (0.0000 - 0.0000 - 0.0000) * (1 - 0.00%))
B69: TT | C69: Tarifa de Transporte | H69: =((85.98%*F64+4.4221)*F67+(F65-F66-F69)*(1-F67)) -> 0

Sheet Jul
A1: Período de Cálculo: | E1: 45839 | F1: 3.539 | S1: , | U1: Días en el mes | W1: 31
A2: PERUPETRO S.A.
A3: DETERMINACION DEL CANON, SOBRECANON y PARTICIPACION (US$)
A4: Correspondiente a Julio 2025
A5: Tipo de Cambio= 3.539
A7: Localidad | C7: Modalidad de Contrato | D7: Calculo del Canon | F7: Volumen Producción / Venta | I7: Canasta o Valor Venta (US$/Unidad) | K7: Deducción de Gastos para determinación de valor de producción en Punto de Fiscalización (US$) | O7: Valor de la Producción (US$) | P7: Canon y Sobrecanon / Participación (US$) | U7: RESUMEN POR PETROLERO Y CONDENSADOS | AA7: RESUMEN POR GAS NATURAL | AG7: Control
A8: - Lote | D8: Período | E8: Fórmula | F8: Unidades | G8: 1ra. Q | H8: 2da. Q / Mes | I8: 1ra. Q | J8: 2da. Q / Mes | K8: Flete Marítimo | L8: Comercialización | M8: Oleoducto | N8: Fiscalización | P8: Total | Q8: Localidad 1 | S8: Localidad 2 | U8: Producción / Venta | X8: Valor Prod | Y8: Valor Canon | AA8: Producción / Venta | AD8: Valor Prod | AE8: Valor Canon | AG8: Total
A9: Piura / Tumbes | Q9: Piura | S9: Tumbes | U9: Bls/Mes | V9: V P (US$) | W9: Bls/Día | X9: US$/Bl | Y9: US$/Bl | Z9: US$ | AA9: MM BTU/Mes | AB9: V P (US$) | AC9: MM BTU/Día | AD9: US$/MM BTU | AE9: US$/MM BTU | AF9: US$ | AG9: Canon
A10: - | B10: I | C10: Servicios | D10: Quincena | E10: F2 | F10: Bls | G10: 4588 | H10: 9776 | I10: 71.1227 | J10: 71.3147 | N10: 77.04 | O10: 1023406.4 | P10: 191888.7 | Q10: 153510.96 | R10: 0.15 | S10: 38377.74 | T10: 0.0375 | U10: 14364 | V10: 1023406.4 | W10: 463.4 | X10: 71.248 | Y10: 13.359 | Z10: 191888.7
A11: - | B11: I GAS | C11: Servicios | D11: Quincena | E11: F2 | F11: MM BTU | G11: 42339.893 | H11: 45445.01 | I11: 3.8749 | J11: 3.8749 | N11: 215.71 | O11: 339942.01 | P11: 63739.13 | Q11: 50991.3 | R11: 0.15 | S11: 12747.83 | T11: 0.0375 | AA11: 87784.903 | AB11: 339942.01 | AC11: 2831.8 | AD11: 3.8724 | AE11: 0.7261 | AF11: 63739.13
A12: - | B12: II | C12: Licencia | D12: Quincena | E12: F2 | F12: Bls | G12: 4560 | H12: 4859 | I12: 70.516 | J12: 70.3479 | N12: 619.39 | O12: 662754.02 | P12: 124266.38 | Q12: 99413.1 | R12: 0.15 | S12: 24853.28 | T12: 0.0375 | U12: 9419 | V12: 662754.02 | W12: 303.8 | X12: 70.3635 | Y12: 13.1932 | Z12: 124266.38
A13: - | B13: II - GAS | C13: Servicios | D13: Quincena | E13: F2 | F13: MM BTU | G13: 21706.3 | H13: 23254.257 | I13: 2.95 | J13: 2.95 | N13: 662.53 | O13: 131971.11 | P13: 24744.58 | Q13: 19795.67 | R13: 0.15 | S13: 4948.92 | T13: 0.0375 | AA13: 44960.556 | AB13: 131971.11 | AC13: 1450.3 | AD13: 2.9353 | AE13: 0.5504 | AF13: 24744.58
A14: - | B14: III | C14: Licencia | D14: Quincena | E14: F2 | F14: Bls | G14: 29370 | H14: 34117 | I14: 71.1227 | J14: 71.3147 | N14: 1045.67 | O14: 4520871.7 | P14: 847663.43 | Q14: 678130.75 | R14: 0.15 | S14: 169532.69 | T14: 0.0375 | U14: 63487 | V14: 4520871.7 | W14: 2048 | X14: 71.2094 | Y14: 13.3518 | Z14: 847663.43
A15: - | B15: III - GAS | C15: Servicios | D15: Quincena | E15: F2 | F15: MM BTU | G15: 90668.638 | H15: 101884.64 | I15: 2.7347 | J15: 2.7347 | O15: 526575.44 | P15: 98732.9 | Q15: 78986.32 | R15: 0.15 | S15: 19746.58 | T15: 0.0375 | AA15: 192553.28 | AB15: 526575.44 | AC15: 6211.4 | AD15: 2.7347 | AE15: 0.5128 | AF15: 98732.9
A16: - | B16: IV | C16: Licencia | D16: Quincena | E16: F2 | F16: Bls | G16: 52121 | H16: 64437 | I16: 71.1227 | J16: 71.3147 | N16: 1745.18 | O16: 8300546.4 | P16: 1556352.4 | Q16: 1245082 | R16: 0.15 | S16: 311270.49 | T16: 0.0375 | U16: 116558 | V16: 8300546.4 | W16: 3759.9 | X16: 71.2139 | Y16: 13.3526 | Z16: 1556352.4
A17: - | B17: IV - GAS | C17: Licencia | D17: Quincena | E17: F2 | F17: Bls | G17: 88142.326 | H17: 91133.111 | I17: 3.2399 | J17: 3.2399 | N17: 605.01 | O17: 580229.48 | P17: 108793.03 | Q17: 87034.42 | R17: 0.15 | S17: 21758.61 | T17: 0.0375 | U17: 179275.44 | V17: 580229.48 | W17: 5783.1 | X17: 3.2365 | Y17: 0.6068 | Z17: 108793.03
A18: - | B18: V | C18: Servicios | D18: Quincena | E18: F2 | F18: Bls | G18: 2771 | H18: 2717 | I18: 70.6613 | J18: 70.5203 | N18: 403.68 | O18: 387002.44 | P18: 72562.96 | Q18: 58050.37 | R18: 0.15 | S18: 14512.59 | T18: 0.0375 | U18: 5488 | V18: 387002.44 | W18: 177 | X18: 70.5179 | Y18: 13.2221 | Z18: 72562.96
A19: - | B19: VI (T) | C19: Licencia | D19: Quincena | E19: F2 | F19: Bls | G19: 20739 | H19: 26867 | I19: 71.1227 | J19: 71.3147 | N19: 486.89 | O19: 3390538.8 | P19: 635726.03 | Q19: 508580.82 | R19: 0.15 | S19: 127145.21 | T19: 0.0375 | U19: 47606 | V19: 3390538.8 | W19: 1535.7 | X19: 71.2208 | Y19: 13.3539 | Z19: 635726.03
A20: - | B20: VI - GAS | C20: Licencia | D20: Quincena | E20: F2 | F20: MM BTU | G20: 58948.958 | H20: 60937.621 | I20: 3.8243 | J20: 3.8243 | N20: 209.54 | O20: 458272.71 | P20: 85926.13 | Q20: 68740.91 | R20: 0.15 | S20: 17185.23 | T20: 0.0375 | AA20: 119886.58 | AB20: 458272.71 | AC20: 3867.3 | AD20: 3.8226 | AE20: 0.7167 | AF20: 85926.13
A21: - | B21: VII (T) | C21: Licencia | D21: Quincena | E21: F2 | F21: Bls | G21: 14774 | H21: 16008 | I21: 70.6613 | J21: 70.5203 | N21: 240.36 | O21: 2172598.6 | P21: 407362.25 | Q21: 325889.8 | R21: 0.15 | S21: 81472.45 | T21: 0.0375 | U21: 30782 | V21: 2172598.6 | W21: 993 | X21: 70.5802 | Y21: 13.2338 | Z21: 407362.25
A22: - | B22: IX | C22: Licencia | D22: Quincena | E22: F2 | F22: Bls | G22: 1839 | H22: 2962 | I22: 71.1227 | J22: 71.3147 | N22: 258.85 | O22: 341769.94 | P22: 64081.86 | Q22: 51265.49 | R22: 0.15 | S22: 12816.37 | T22: 0.0375 | U22: 4801 | V22: 341769.94 | W22: 154.9 | X22: 71.1872 | Y22: 13.3476 | Z22: 64081.86
A23: - | B23: X | C23: Licencia | D23: Quincena | E23: F2 | F23: Bls | G23: 124506 | H23: 133753 | I23: 72.1005 | J23: 71.8649 | N23: 1193.59 | O23: 18587897 | P23: 3485230.7 | Q23: 2788184.6 | R23: 0.15 | S23: 697046.15 | T23: 0.0375 | U23: 258259 | V23: 18587897 | W23: 8330.9 | X23: 71.9739 | Y23: 13.4951 | Z23: 3485230.7
A24: - | B24: X - GAS | C24: Licencia | D24: Mes | E24: F2 | F24: MM BTU | G24: 203062.61 | H24: 213238.09 | I24: 3.1 | J24: 3.1 | N24: 910.08 | O24: 1289622.1 | P24: 241804.14 | Q24: 193443.31 | R24: 0.15 | S24: 48360.83 | T24: 0.0375 | AA24: 416300.7 | AB24: 1289622.1 | AC24: 13429.1 | AD24: 3.0978 | AE24: 0.5808 | AF24: 241804.14
A25: - | B25: XV | C25: Licencia | D25: Quincena | E25: F2 | F25: Bls | G25: 252 | H25: 254 | I25: 70.6613 | J25: 70.5203 | N25: 280.42 | O25: 35438.39 | P25: 6644.7 | Q25: 5315.76 | R25: 0.15 | S25: 1328.94 | T25: 0.0375 | U25: 506 | V25: 35438.39 | W25: 16.3 | X25: 70.0363 | Y25: 13.1318 | Z25: 6644.7
A26: - | B26: XIII Crudo | C26: Licencia | D26: Quincena | E26: F2 | F26: Bls | G26: 13304 | H26: 14251 | I26: 69.3427 | J26: 71.2447 | N26: 2671.7 | O26: 1935171.8 | P26: 362844.71 | Q26: 290275.77 | R26: 0.15 | S26: 72568.94 | T26: 0.0375 | U26: 27555 | V26: 1935171.8 | W26: 888.9 | X26: 70.2294 | Y26: 13.168 | Z26: 362844.71
A27: - | B27: XIII Gas | C27: Licencia | D27: Quincena | E27: F2 | F27: MM BTU | G27: 455459.39 | H27: 439401.19 | I27: 2.9858113 | J27: 2.88939 | N27: 1112.44 | O27: 2629517.2 | P27: 493034.48 | Q27: 394427.58 | R27: 0.15 | S27: 98606.89 | T27: 0.0375 | AA27: 894860.57 | AB27: 2629517.2 | AC27: 28866.5 | AD27: 2.9385 | AE27: 0.551 | AF27: 493034.48
A28: - | B28: XX | C28: Licencia | D28: Quincena | E28: F2 | F28: Bls | G28: 152 | H28: 131 | I28: 71.1227 | J28: 71.3147 | N28: 166.4 | O28: 19986.48 | P28: 3747.47 | Q28: 749.49 | R28: 0.0375 | S28: 2997.97 | T28: 0.15 | U28: 283 | V28: 19986.48 | W28: 9.1 | X28: 70.6236 | Y28: 13.2419 | Z28: 3747.47
A29: - | B29: Z-1 Crudo | C29: Licencia | D29: Quincena | E29: F2 | F29: Bls | G29: 60432 | I29: 64.0327 | N29: 841.26 | O29: 3868782.9 | P29: 725396.79 | Q29: 145079.36 | R29: 0.0375 | S29: 580317.43 | T29: 0.15
A30: - | B30: Z-69 Crudo | C30: Licencia | D30: Quincena | E30: F2 | F30: Bls | G30: 37428 | H30: 66707 | I30: 69.1055 | J30: 69.9642 | N30: 428.33 | O30: 7253154.2 | P30: 1359966.4 | Q30: 1087973.1 | R30: 0.15 | S30: 271993.28 | T30: 0.0375
A31: - | B31: Z-69 Gas | C31: Licencia | D31: Quincena | E31: F2 | F31: MM BTU | G31: 148468.74 | H31: 159502.08 | I31: 2.7444029 | J31: 2.7487626 | N31: 379.03 | O31: 845891.4 | P31: 158604.63 | Q31: 126883.71 | R31: 0.15 | S31: 31720.93 | T31: 0.0375
A32: - | B32: Z-69 Lgn | C32: Licencia | D32: Quincena | E32: F2 | F32: Bls | G32: 9525 | H32: 10268 | I32: 37.5276 | J32: 37.1171 | N32: 412.93 | O32: 738155.84 | P32: 138404.22 | Q32: 110723.38 | R32: 0.15 | S32: 27680.84 | T32: 0.0375
A33: - | B33: Ajustes meses anteriores (1) | O33: -1638409.7 | P33: -307201.84 | Q33: -61619.81 | S33: -245581.99
B34: Subtotal | C34: Piura / Tumbes US$ | O34: 58401687 | P34: 10950316 | Q34: 8506908.1 | S34: 2443408.2 | U34: 758383.44 | V34: 41958212 | W34: 24464 | X34: 55.3259 | Y34: 10.3736 | Z34: 7867164.7 | AA34: 1756346.6 | AB34: 5375900.5 | AC34: 56656.4 | AD34: 3.0608 | AE34: 0.5739 | AF34: 1007981.4 | AG34: 2075170.2
C35: Piura / Tumbes S/. | P35: 38753169 | Q35: 30105948 | S35: 8647221.6
A36: Provincia Puerto Inca Huanuco | Q36: Puerto Inca
A37: - | B37: 131 | C37: Licencia | D37: Quincena | E37: F2 | F37: Bls | G37: 7806 | H37: 11036 | I37: 58.2254 | J37: 57.9965 | N37: 3318.82 | O37: 1091238 | P37: 163685.7 | Q37: 163685.7 | R37: 0.15 | U37: 18842 | V37: 1091238 | W37: 607.8 | X37: 57.9152 | Y37: 8.6873 | Z37: 163685.7
A38: - | B38: Ajustes meses anteriores (2)
B39: Subtotal | C39: Provincia Puerto Inca Huanuco US$ | O39: 1091238 | P39: 163685.7 | Q39: 163685.7 | S39: 0 | U39: 18842 | V39: 1091238 | W39: 607.8 | X39: 57.9152 | Y39: 8.6873 | Z39: 163685.7 | AA39: 0 | AB39: 0 | AC39: 0 | AD39: 0 | AE39: 0 | AF39: 0 | AG39: 0
C40: Provincia Puerto Inca Huanuco S/. | P40: 579283.69 | Q40: 579283.69 | S40: 0
A41: Loreto / Ucayali | Q41: Loreto | S41: Ucayali
A42: - | B42: 8 | C42: Licencia | D42: Quincena | E42: F2 | F42: Bls | G42: 70432 | H42: 65431 | I42: 57.4752 | J42: 57.9028 | N42: 4443.59 | O42: 7832287.8 | P42: 1468554 | Q42: 1174843.2 | R42: 0.15 | S42: 293710.79 | T42: 0.0375 | U42: 135863 | V42: 7832287.8 | W42: 4382.7 | X42: 57.6484 | Y42: 10.8091 | Z42: 1468554
A43: - | B43: 31-C GAS | C43: Licencia | D43: Quincena | E43: F2 | F43: MM BTU | H43: 57839.068 | J43: 3.6084 | N43: 1626.04 | O43: 207080.45 | P43: 38827.58 | Q43: 7765.52 | R43: 0.0375 | S43: 31062.07 | T43: 0.15 | AA43: 57839.068 | AB43: 207080.45 | AC43: 1865.8 | AD43: 3.5803 | AE43: 0.6713 | AF43: 38827.58
A44: - | B44: 31-C LGN (*) | C44: Licencia | D44: Quincena | E44: F3 | F44: Bls | N44: 3092.85 | O44: -3092.85 | P44: -579.91 | Q44: -115.98 | R44: 0.0375 | S44: -463.93 | T44: 0.15 | U44: 0 | V44: -3092.85 | W44: 0 | X44: 0 | Y44: 0 | Z44: -579.91
A45: - | B45: 95 | C45: Licencia | D45: Quincena | E45: F2 | F45: Bls | G45: 284187 | H45: 319018 | I45: 50.3147 | J45: 51.1664 | N45: 4446.67 | O45: 30617340 | P45: 5740751.2 | Q45: 4592600.9 | R45: 0.15 | S45: 1148150.2 | T45: 0.0375 | U45: 603205 | V45: 30617340 | W45: 19458.2 | X45: 50.7578 | Y45: 9.5171 | Z45: 5740751.2
A46: - | B46: 67 | C46: Licencia | D46: Quincena | E46: F2 | F46: Bls | O46: 0 | P46: 0 | Q46: 0 | R46: 0.15 | S46: 0 | T46: 0.0375 | U46: 0 | V46: 0 | W46: 0 | X46: 0 | Y46: 0 | Z46: 0
A47: - | B47: Ajustes meses anteriores (3)
B48: Subtotal | C48: Loreto / Ucayali US$ | O48: 38653615 | P48: 7247552.8 | Q48: 5775093.6 | S48: 1472459.2 | U48: 739068 | V48: 38446535 | W48: 23840.9 | X48: 52.0203 | Y48: 9.7538 | Z48: 7208725.2 | AA48: 57839.068 | AB48: 207080.45 | AC48: 1865.8 | AD48: 3.5803 | AE48: 0.6713 | AF48: 38827.58 | AG48: 7.2759576e-11
C49: Loreto / Ucayali S/. | P49: 25649089 | Q49: 20438056 | S49: 5211033
A50: Cusco | P50: V. Regalías | Q50: Cusco
A51: - | B51: 88 LGN | C51: Licencia | D51: Quincena | E51: F4 | F51: Bls | G51: 718135 | H51: 760787 | I51: 37.0702 | J51: 36.6232 | O51: 54483863 | P51: 20289790 | Q51: 10144895 | R51: 0.5 | U51: 1478922 | V51: 54483863 | W51: 47707.2 | X51: 36.8403 | Y51: 6.8597 | Z51: 10144895
A52: - | B52: 88 GAS | C52: Licencia | D52: Quincena | E52: F4 | F52: MM BTU | G52: 14678757 | H52: 14844957 | I52: 2.8448 | J52: 2.8489 | O52: 84050774 | P52: 31359788 | Q52: 15679894 | R52: 0.5 | AA52: 29523714 | AB52: 84050774 | AC52: 952377.9 | AD52: 2.8469 | AE52: 0.5311 | AF52: 15679894
