Workbook
Name tc: Sep!$N$1
Name tc: Ago!$N$1

Sheet Recuperado_Hoja1
N6: Pagina : | P6: 1/1
A8: Gerencia de Supervisión de Contratos | N8: Fecha : | P8: 45238
A10: reporte_ajuste_regalia_quincenal.rpt | N10: Hora : | P10: 0.72101852
I13: AJUSTE DE REGALIA CORRESPONDIENTE A LA
I15: SEGUNDA QUINCENA DEL MES OCTUBRE DEL 2023
E20: VALOR PRODUCCION | F20: VALOR PRODUCCION | H20: CANASTA | I20: CANASTA | J20: MONTO REGALIA | K20: MONTO REGALIA
A21: LOTE | B21: PERIODO | C21: MES AFECTADO | D21: PERIODO | E21: ORIGINAL | F21: AJUSTADO | H21: ORIGINAL | I21: AJUSTADA | J21: ORIGINAL | K21: AJUSTADO | L21: MONTO AJUSTE | M21: FECHA PAGO | N21: OBSERVACION
J22: US$ | K22: US$ | L22: US$
A26: HIDROCARBURO : | C26: GAS
A28: 56 | B28: 2023 | C28: SETIEMBRE | D28: SEGUNDA QUINCENA | E28: 27963147 | F28: 25283022 | H28: 5.415 | I28: 4.896 | J28: 10625996 | K28: 9607548.5 | L28: -1018447.2 | M28: 45233 | N28: Ajuste que considera cambio de destino de los embarques # 737 de Francia a Holanda y # 738 de Japón a Francia.
A31: 56 | B31: 2023 | C31: OCTUBRE | D31: PRIMERA QUINCENA | E31: 24372651 | F31: 22855598 | H31: 4.884 | I31: 4.58 | J31: 9261607.4 | K31: 8685127.3 | L31: -576480.06 | M31: 45233 | N31: Ajuste que considera cambio de destino del embarque # 739 de España a Reino Unido.
J35: SUB TOTAL | L35: -1594927.3
A37: 57 | B37: 2023 | C37: SETIEMBRE | D37: PRIMERA QUINCENA | E37: 17874603 | F37: 16902455 | H37: 4.707 | I37: 4.451 | J37: 1942969.3 | K37: 1837296.9 | L37: -105672.43 | M37: 45233 | N37: AJUSTE QUE CONSIDERA EL PRECIO REALIZADO DEL MES DE SETIEMBRE 2023, SEGÚN FACTURA N°F057-00000839 EMITIDA EL 10.10.2023 Y LAS NOTAS ND 058, 059 Y NC 148
A40: 57 | B40: 2023 | C40: SETIEMBRE | D40: SEGUNDA QUINCENA | E40: 18534725 | F40: 17526676 | H40: 4.707 | I40: 4.451 | J40: 2061061.4 | K40: 1948966.3 | L40: -112095.12 | M40: 45233 | N40: AJUSTE QUE CONSIDERA EL PRECIO REALIZADO DEL MES DE SETIEMBRE 2023, SEGÚN FACTURA N°F057-00000839 EMITIDA EL 10.10.2023 Y LAS NOTAS ND 058, 059 Y NC 148.
A43: 57 | B43: 2023 | C43: OCTUBRE | D43: PRIMERA QUINCENA | E43: 18131148 | F43: 17145048 | H43: 4.707 | I43: 4.451 | J43: 1987173.9 | K43: 1879097.3 | L43: -108076.59 | M43: 45233 | N43: AJUSTE QUE CONSIDERA EL PRECIO REALIZADO DEL MES DE SETIEMBRE 2023, SEGÚN FACTURA N°F057-00000839 EMITIDA EL 10.10.2023 Y LAS NOTAS ND 058, 059 Y NC 148.
J47: SUB TOTAL | L47: -325844.14
A49: VII_VI | B49: 2023 | C49: OCTUBRE | D49: PRIMERA QUINCENA | E49: 158453.96 | F49: 160506.8 | H49: 3.0026 | I49: 3.0415 | J49: 31690.79 | K49: 32101.36 | L49: 410.57 | M49: 45223 | N49: CONSIDERA PRECIO REALIZADO DEL MES DE OCTUBRE DE 2023, DE ACUERDO A FACTURA Nº FS02- 00000112 REMITIDA POR SAPET A ENEL GENERACION PIURA S.A.
J53: SUB TOTAL | L53: 410.57
A55: X | B55: 2023 | C55: OCTUBRE | D55: PRIMERA QUINCENA | E55: 635801.16 | F55: 645979.21 | H55: 2.7236 | I55: 2.7672 | J55: 155771.28 | K55: 158264.91 | L55: 2493.63 | M55: 45233 | N55: CONSIDERA PRECIO REALIZADO DEL MES DE OCTUBRE DE 2023, DE ACUERDO A FACTURA Nº F001- 00000459 REMITIDA POR CNPC PERÚ S.A. A ENEL GENERACION PIURA S.A.
J59: SUB TOTAL | L59: 2493.63
A61: HIDROCARBURO : | C61: GAS PAITA 2
A63: XIII | B63: 2023 | C63: SETIEMBRE | D63: PRIMERA QUINCENA | E63: 75945.12 | F63: 80933.38 | H63: 3.59 | I63: 3.8258 | J63: 16707.93 | K63: 17805.34 | L63: 1097.41 | M63: 45233 | N63: CONSIDERA EL PRECIO REALIZADO SEGÚ FACTURA N°01-1562 A ENERGIGAS SAC. INCLUYE FACTURA N°1569 Y NC N°001-154
J67: SUB TOTAL | L67: 1097.41
A69: HIDROCARBURO : | C69: GAS PLT. MELCHORITA
A71: 88 | B71: 2023 | C71: SETIEMBRE | D71: SEGUNDA QUINCENA | E71: 5397558.3 | F71: 4880230 | H71: 5.415 | I71: 4.896 | J71: 2051072.1 | K71: 1854487.4 | L71: -196584.75 | M71: 45233 | N71: Ajuste que considera cambio de destino de los embarques # 737 de Francia a Holanda y # 738 de Japón a Francia.
A74: 88 | B74: 2023 | C74: OCTUBRE | D74: PRIMERA QUINCENA | E74: 4311923.1 | F74: 4043531.5 | H74: 4.884 | I74: 4.58 | J74: 1638530.8 | K74: 1536542 | L74: -101988.81 | M74: 45233 | N74: Ajuste que considera el cambio de destino del embarque # 739 de España a Reino Unido.
J78: SUB TOTAL | L78: -298573.56
A80: HIDROCARBURO : | C80: LIQUIDO GAS NATURAL
A82: 31-C | B82: 2021 | C82: JULIO | D82: PRIMERA QUINCENA | E82: 111201.63 | F82: 102573.26 | G82: =E82/H82 -> 2206.0007 | H82: 50.4087 | I82: 46.4974 | J82: 44814.26 | K82: 41337.02 | L82: -3477.24 | M82: 45233 | N82: APLICACIÓN DEL ACUERDO DE VALORIZACIÓN DE LOS LGN DEL LOTE 31-C SUSCRITO EL 12.10.2023
A83: 31-C | B83: 2021 | C83: JULIO | D83: SEGUNDA QUINCENA | E83: 104544.09 | F83: 95685.61 | G83: =E83/H83 -> 2145.9997 | H83: 48.7158 | I83: 44.5879 | J83: 41085.83 | K83: 37604.44 | L83: -3481.39 | M83: 45233 | N83: APLICACIÓN DEL ACUERDO DE VALORIZACIÓN DE LOS LGN DEL LOTE 31-C SUSCRITO EL 12.10.2023
A84: 31-C | B84: 2021 | C84: AGOSTO | D84: PRIMERA QUINCENA | E84: 94664.3 | F84: 86618.28 | G84: =E84/H84 -> 1979.0005 | H84: 47.8344 | I84: 43.7687 | J84: 36540.42 | K84: 33434.66 | L84: -3105.76 | M84: 45233 | N84: APLICACIÓN DEL ACUERDO DE VALORIZACIÓN DE LOS LGN DEL LOTE 31-C SUSCRITO EL 12.10.2023
A85: 31-C | B85: 2021 | C85: AGOSTO | D85: SEGUNDA QUINCENA | E85: 96722.09 | F85: 88418.38 | G85: =E85/H85 -> 2094.9983 | H85: 46.1681 | I85: 42.2045 | J85: 36657.67 | K85: 33510.57 | L85: -3147.1 | M85: 45233 | N85: APLICACIÓN DEL ACUERDO DE VALORIZACIÓN DE LOS LGN DEL LOTE 31-C SUSCRITO EL 12.10.2023
A86: 31-C | B86: 2021 | C86: SETIEMBRE | D86: PRIMERA QUINCENA | E86: 87956.11 | F86: 81133.94 | G86: =E86/H86 -> 1796.9994 | H86: 48.9461 | I86: 45.1497 | J86: 34390.84 | K86: 31723.37 | L86: -2667.47 | M86: 45233 | N86: APLICACIÓN DEL ACUERDO DE VALORIZACIÓN DE LOS LGN DEL LOTE 31-C SUSCRITO EL 12.10.2023
A87: 31-C | B87: 2021 | C87: SETIEMBRE | D87: SEGUNDA QUINCENA | E87: 102122.85 | F87: 94884.62 | G87: =E87/H87 -> 1841.9996 | H87: 55.4413 | I87: 51.5117 | J87: 41257.63 | K87: 38333.39 | L87: -2924.24 | M87: 45233 | N87: APLICACIÓN DEL ACUERDO DE VALORIZACIÓN DE LOS LGN DEL LOTE 31-C SUSCRITO EL 12.10.2023
A88: 31-C | B88: 2021 | C88: OCTUBRE | D88: PRIMERA QUINCENA | E88: 100169 | F88: 93212.41 | G88: =E88/H88 -> 1727.0011 | H88: 58.0017 | I88: 53.9736 | J88: 42772.16 | K88: 39801.7 | L88: -2970.46 | M88: 45233 | N88: APLICACIÓN DEL ACUERDO DE VALORIZACIÓN DE LOS LGN DEL LOTE 31-C SUSCRITO EL 12.10.2023
A89: 31-C | B89: 2021 | C89: OCTUBRE | D89: SEGUNDA QUINCENA | E89: 111006.61 | F89: 103461.81 | G89: =E89/H89 -> 1963.9992 | H89: 56.5207 | I89: 52.6791 | J89: 48398.88 | K89: 45109.35 | L89: -3289.53 | M89: 45233 | N89: APLICACIÓN DEL ACUERDO DE VALORIZACIÓN DE LOS LGN DEL LOTE 31-C SUSCRITO EL 12.10.2023
A90: 31-C | B90: 2021 | C90: DICIEMBRE | D90: PRIMERA QUINCENA | E90: 60324.24 | F90: 55620.24 | G90: =E90/H90 -> 1215.9988 | H90: 49.6088 | I90: 45.7403 | J90: 23767.75 | K90: 21914.37 | L90: -1853.38 | M90: 45233 | N90: APLICACIÓN DEL ACUERDO DE VALORIZACIÓN DE LOS LGN DEL LOTE 31-C SUSCRITO EL 12.10.2023
A91: 31-C | B91: 2021 | C91: DICIEMBRE | D91: SEGUNDA QUINCENA | E91: 59208.78 | F91: 52626.06 | G91: =E91/H91 -> 1304.0002 | H91: 45.4055 | I91: 40.3574 | J91: 23742.72 | K91: 21103.05 | L91: -2639.67 | M91: 45233 | N91: APLICACIÓN DEL ACUERDO DE VALORIZACIÓN DE LOS LGN DEL LOTE 31-C SUSCRITO EL 12.10.2023
A92: 31-C | B92: 2022 | C92: ENERO | D92: PRIMERA QUINCENA | E92: 79057.23 | F92: 70365.05 | G92: =E92/H92 -> 1640.9984 | H92: 48.1763 | I92: 42.8794 | J92: 34073.67 | K92: 30327.34 | L92: -3746.33 | M92: 45233 | N92: APLICACIÓN DEL ACUERDO DE VALORIZACIÓN DE LOS LGN DEL LOTE 31-C SUSCRITO EL 12.10.2023
A93: 31-C | B93: 2022 | C93: ENERO | D93: SEGUNDA QUINCENA | E93: 247402.75 | F93: 227016.2 | G93: =E93/H93 -> 4463.997 | H93: 55.4218 | I93: 50.8549 | J93: 112568.25 | K93: 103292.37 | L93: -9275.88 | M93: 45233 | N93: APLICACIÓN DEL ACUERDO DE VALORIZACIÓN DE LOS LGN DEL LOTE 31-C SUSCRITO EL 12.10.2023
... A133: 31-C | B133: 2023 | C133: OCTUBRE | D133: PRIMERA QUINCENA | E133: 129538.6 | F133: 120913.09 | G133: =E133/H133 -> 1953.9989 | H133: 66.2941 | I133: 61.8798 | J133: 59069.6 | K133: 55136.37 | L133: -3933.23 | M133: 45233 | N133: APLICACIÓN DEL ACUERDO DE VALORIZACIÓN DE LOS LGN DEL LOTE 31-C SUSCRITO EL 12.10.2023
E134: =E131/H131 -> 2375.0014 | F134: =F131/I131 -> 2375.001
J136: SUB TOTAL | L136: -324161.08
A138: HIDROCARBURO : | C138: PETROLEO
A140: VII_VI | B140: 2023 | C140: SETIEMBRE | D140: PRIMERA QUINCENA | E140: 4154497.4 | F140: 4136614.9 | H140: 91.3257 | I140: 90.9326 | J140: 1442129.1 | K140: 1435921.7 | L140: -6207.46 | M140: 45223 | N140: CONSIDERA LA TARIFA DE TRANSPORTE Y ALMACENAMIENTO CORRESPONDIENTE AL MES DE SETIEMBRE 2023, SEGUN FACTURA N° FE62-00012487 DE PETROPERU.
A143: VII_VI | B143: 2023 | C143: SETIEMBRE | D143: SEGUNDA QUINCENA | E143: 3865976.1 | F143: 3849859.8 | H143: 94.2967 | I143: 93.9036 | J143: 1359149.4 | K143: 1353483.5 | L143: -5665.96 | M143: 45223 | N143: CONSIDERA LA TARIFA DE TRANSPORTE Y ALMACENAMIENTO CORRESPONDIENTE AL MES DE SETIEMBRE 2023, SEGUN FACTURA N° FE62-00012487 DE PETROPERU.
A146: VII_VI | B146: 2023 | C146: OCTUBRE | D146: PRIMERA QUINCENA | E146: 3880312.7 | F146: 3863626.9 | H146: 88.9042 | I146: 88.5219 | J146: 1319841.2 | K146: 1314165.7 | L146: -5675.5 | M146: 45223 | N146: CONSIDERA LA TARIFA DE TRANSPORTE Y ALMACENAMIENTO CORRESPONDIENTE AL MES DE OCTUBRE 2023, SEGUN FACTURA N° FE62-00012516 DE PETROPERU.
J150: SUB TOTAL | L150: -17548.92
J153: TOTAL | L153: -2557053.4
A154: OBSERVACION :

Sheet Ene-2
A1: Período de Cálculo: | E1: 43101 | U1: Días en el mes | W1: =DATE(YEAR(E1),MONTH(E1)+1,1)-DATE(YEAR(E1),MONTH(E1),1) -> 31
A2: PERUPETRO S.A.
A3: DETERMINACION DEL CANON, SOBRECANON y PARTICIPACION (US$)
A4: ="Correspondiente a "&TEXT(E1,"MMMMMMM YYYY") -> Correspondiente a Enero 2018
A5: ="Tipo de Cambio= "&TEXT(F1,"0.000") -> Tipo de Cambio= 0.000
A7: Localidad | C7: Modalidad de Contrato | D7: Calculo del Canon | F7: Volumen Producción / Venta | I7: Canasta o Valor Venta (US$/Unidad) | K7: Deducción de Gastos para determinación de valor de producción en Punto de Fiscalización (US$) | O7: Valor de la Producción (US$) | P7: Canon y Sobrecanon / Participación (US$) | U7: Resumen por Petróleo y Condensados | AA7: Resumen por Gas Natural | AG7: Control
A8: - Lote | D8: Período | E8: Fórmula | F8: Unidades | G8: 1ra. Q | H8: 2da. Q / Mes | I8: 1ra. Q | J8: 2da. Q / Mes | K8: Flete Marítimo | L8: Comercialización | M8: Oleoducto | N8: Fiscalización | P8: Total | Q8: Localidad 1 | S8: Localidad 2 | U8: Producción / Venta | X8: Valor Prod | Y8: Valor Canon | AA8: Producción / Venta | AD8: Valor Prod | AE8: Valor Canon | AG8: Total
A9: Piura / Tumbes | Q9: Piura | S9: Tumbes | U9: Bls/Mes | V9: V P (US$) | W9: Bls/Día | X9: US$/Bl | Y9: US$/Bl | Z9: US$ | AA9: MM BTU/Mes | AB9: V P (US$) | AC9: MM BTU/Día | AD9: US$/MM BTU | AE9: US$/MM BTU | AF9: US$ | AG9: Canon
A10: - | B10: I | C10: Servicios | D10: Mes | E10: F1 | F10: Bls | H10: 24582 | J10: 67.0812 | N10: 683.58 | O10: =ROUND(G10*I10,2)+ROUND(H10*J10,2)-K10-L10-M10-N10 -> 1648306.5 | P10: =ROUND(18.75%*O10,2) -> 309057.47 | Q10: =ROUND($O10*R10,2) -> 247245.97 | R10: 0.15 | S10: =ROUND($O10*T10,2) -> 61811.49 | T10: 0.0375 | U10: =IF($F10&"/Día"=W$9,SUM($G10:$H10),"") -> 24582 | V10: =IF(U10<>"",$O10,"") -> 1648306.5 | W10: =IF($F10&"/Día"=W$9,ROUND(U10/$W$1,1),"") -> 793 | X10: =IF(U10=0,0,IF($F10&"/Día"=W$9,ROUND(V10/U10,4),"")) -> 67.0534 | Y10: =IF(U10=0,0,IF($F10&"/Día"=W$9,ROUND(Z10/U10,4),"")) -> 12.5725 | Z10: =IF(U10<>"",$P10,"") -> 309057.47 | AA10: =IF($F10&"/Día"=AC$9,SUM($G10:$H10),"") | AB10: =IF(AA10<>"",$O10,"") | AC10: =IF($F10&"/Día"=AC$9,ROUND(AA10/$W$1,1),"") | AD10: =IF(AA10=0,0,IF($F10&"/Día"=AC$9,ROUND(AB10/AA10,4),"")) | AE10: =IF(AA10=0,0,IF($F10&"/Día"=AC$9,ROUND(AF10/AA10,4),"")) | AF10: =IF(AA10<>"",$P10,"")
A11: - | B11: I GAS | C11: Servicios | D11: Mes | E11: F1 | F11: MM BTU | H11: 253218.78 | J11: 2.9822 | N11: 1914.05 | O11: =ROUND(G11*I11,2)+ROUND(H11*J11,2)-K11-L11-M11-N11 -> 753235 | P11: =ROUND(18.75%*O11,2) -> 141231.56 | Q11: =ROUND($O11*R11,2) -> 112985.25 | R11: 0.15 | S11: =ROUND($O11*T11,2) -> 28246.31 | T11: 0.0375 | U11: =IF($F11&"/Día"=W$9,SUM($G11:$H11),"") | V11: =IF(U11<>"",$O11,"") | W11: =IF($F11&"/Día"=W$9,ROUND(U11/$W$1,1),"") | X11: =IF(U11=0,0,IF($F11&"/Día"=W$9,ROUND(V11/U11,4),"")) | Y11: =IF(U11=0,0,IF($F11&"/Día"=W$9,ROUND(Z11/U11,4),"")) | Z11: =IF(U11<>"",$P11,"") | AA11: =IF($F11&"/Día"=AC$9,SUM($G11:$H11),"") -> 253218.78 | AB11: =IF(AA11<>"",$O11,"") -> 753235 | AC11: =IF($F11&"/Día"=AC$9,ROUND(AA11/$W$1,1),"") -> 8168.3 | AD11: =IF(AA11=0,0,IF($F11&"/Día"=AC$9,ROUND(AB11/AA11,4),"")) -> 2.9746 | AE11: =IF(AA11=0,0,IF($F11&"/Día"=AC$9,ROUND(AF11/AA11,4),"")) -> 0.5577 | AF11: =IF(AA11<>"",$P11,"") -> 141231.56
A12: - | B12: II | C12: Licencia | D12: Quincena | E12: F2 | F12: Bls | G12: 4562 | H12: 4721 | I12: 64.1613 | J12: 65.1575 | N12: 1764.83 | O12: =ROUND(G12*I12,2)+ROUND(H12*J12,2)-K12-L12-M12-N12 -> 598547.58 | P12: =ROUND(18.75%*O12,2) -> 112227.67 | Q12: =ROUND($O12*R12,2) -> 89782.14 | R12: 0.15 | S12: =ROUND($O12*T12,2) -> 22445.53 | T12: 0.0375 | U12: =IF($F12&"/Día"=W$9,SUM($G12:$H12),"") -> 9283 | V12: =IF(U12<>"",$O12,"") -> 598547.58 | W12: =IF($F12&"/Día"=W$9,ROUND(U12/$W$1,1),"") -> 299.5 | X12: =IF(U12=0,0,IF($F12&"/Día"=W$9,ROUND(V12/U12,4),"")) -> 64.4778 | Y12: =IF(U12=0,0,IF($F12&"/Día"=W$9,ROUND(Z12/U12,4),"")) -> 12.0896 | Z12: =IF(U12<>"",$P12,"") -> 112227.67 | AA12: =IF($F12&"/Día"=AC$9,SUM($G12:$H12),"") | AB12: =IF(AA12<>"",$O12,"") | AC12: =IF($F12&"/Día"=AC$9,ROUND(AA12/$W$1,1),"") | AD12: =IF(AA12=0,0,IF($F12&"/Día"=AC$9,ROUND(AB12/AA12,4),"")) | AE12: =IF(AA12=0,0,IF($F12&"/Día"=AC$9,ROUND(AF12/AA12,4),"")) | AF12: =IF(AA12<>"",$P12,"")
A13: - | B13: II-GAS | C13: Servicios | D13: Mes | E13: F1 | F13: MM BTU | G13: 40281.697 | H13: 44653.33 | I13: 2.55 | J13: 2.55 | N13: 1884.53 | O13: =ROUND(G13*I13,2)+ROUND(H13*J13,2)-K13-L13-M13-N13 -> 214699.79 | P13: =ROUND(18.75%*O13,2) -> 40256.21 | Q13: =ROUND($P13*R13/(R13+T13),2) -> 32204.97 | R13: 0.15 | S13: =P13-Q13 -> 8051.24 | T13: 0.0375 | U13: =IF($F13&"/Día"=W$9,SUM($G13:$H13),"") | V13: =IF(U13<>"",$O13,"") | W13: =IF($F13&"/Día"=W$9,ROUND(U13/$W$1,1),"") | X13: =IF(U13=0,0,IF($F13&"/Día"=W$9,ROUND(V13/U13,4),"")) | Y13: =IF(U13=0,0,IF($F13&"/Día"=W$9,ROUND(Z13/U13,4),"")) | Z13: =IF(U13<>"",$P13,"") | AA13: =IF($F13&"/Día"=AC$9,SUM($G13:$H13),"") -> 84935.027 | AB13: =IF(AA13<>"",$O13,"") -> 214699.79 | AC13: =IF($F13&"/Día"=AC$9,ROUND(AA13/$W$1,1),"") -> 2739.8 | AD13: =IF(AA13=0,0,IF($F13&"/Día"=AC$9,ROUND(AB13/AA13,4),"")) -> 2.5278 | AE13: =IF(AA13=0,0,IF($F13&"/Día"=AC$9,ROUND(AF13/AA13,4),"")) -> 0.474 | AF13: =IF(AA13<>"",$P13,"") -> 40256.21
A14: - | B14: III | C14: Licencia | D14: Quincena | E14: F2 | F14: Bls | G14: 11836 | H14: 12495 | I14: 66.7972 | J14: 67.3179 | N14: 1257.31 | O14: =ROUND(G14*I14,2)+ROUND(H14*J14,2)-K14-L14-M14-N14 -> 1630491.5 | P14: =ROUND(18.75%*O14,2) -> 305717.16 | Q14: =ROUND($O14*R14,2) -> 244573.73 | R14: 0.15 | S14: =ROUND($O14*T14,2) -> 61143.43 | T14: 0.0375 | U14: =IF($F14&"/Día"=W$9,SUM($G14:$H14),"") -> 24331 | V14: =IF(U14<>"",$O14,"") -> 1630491.5 | W14: =IF($F14&"/Día"=W$9,ROUND(U14/$W$1,1),"") -> 784.9 | X14: =IF(U14=0,0,IF($F14&"/Día"=W$9,ROUND(V14/U14,4),"")) -> 67.0129 | Y14: =IF(U14=0,0,IF($F14&"/Día"=W$9,ROUND(Z14/U14,4),"")) -> 12.5649 | Z14: =IF(U14<>"",$P14,"") -> 305717.16 | AA14: =IF($F14&"/Día"=AC$9,SUM($G14:$H14),"") | AB14: =IF(AA14<>"",$O14,"") | AC14: =IF($F14&"/Día"=AC$9,ROUND(AA14/$W$1,1),"") | AD14: =IF(AA14=0,0,IF($F14&"/Día"=AC$9,ROUND(AB14/AA14,4),"")) | AE14: =IF(AA14=0,0,IF($F14&"/Día"=AC$9,ROUND(AF14/AA14,4),"")) | AF14: =IF(AA14<>"",$P14,"")
A15: - | B15: IV | C15: Licencia | D15: Quincena | E15: F2 | F15: Bls | G15: 17378 | H15: 20845 | I15: 66.7972 | J15: 67.3179 | N15: 3247.24 | O15: =ROUND(G15*I15,2)+ROUND(H15*J15,2)-K15-L15-M15-N15 -> 2560796.1 | P15: =ROUND(18.75%*O15,2) -> 480149.27 | Q15: =ROUND($O15*R15,2) -> 384119.42 | R15: 0.15 | S15: =ROUND($O15*T15,2) -> 96029.85 | T15: 0.0375 | U15: =IF($F15&"/Día"=W$9,SUM($G15:$H15),"") -> 38223 | V15: =IF(U15<>"",$O15,"") -> 2560796.1 | W15: =IF($F15&"/Día"=W$9,ROUND(U15/$W$1,1),"") -> 1233 | X15: =IF(U15=0,0,IF($F15&"/Día"=W$9,ROUND(V15/U15,4),"")) -> 66.9962 | Y15: =IF(U15=0,0,IF($F15&"/Día"=W$9,ROUND(Z15/U15,4),"")) -> 12.5618 | Z15: =IF(U15<>"",$P15,"") -> 480149.27 | AA15: =IF($F15&"/Día"=AC$9,SUM($G15:$H15),"") | AB15: =IF(AA15<>"",$O15,"") | AC15: =IF($F15&"/Día"=AC$9,ROUND(AA15/$W$1,1),"") | AD15: =IF(AA15=0,0,IF($F15&"/Día"=AC$9,ROUND(AB15/AA15,4),"")) | AE15: =IF(AA15=0,0,IF($F15&"/Día"=AC$9,ROUND(AF15/AA15,4),"")) | AF15: =IF(AA15<>"",$P15,"")
A16: - | B16: V | C16: Servicios | D16: Mes | E16: F1 | F16: Bls | H16: 2532 | J16: 67.0812 | N16: 1487.58 | O16: =ROUND(G16*I16,2)+ROUND(H16*J16,2)-K16-L16-M16-N16 -> 168362.02 | P16: =ROUND(18.75%*O16,2) -> 31567.88 | Q16: =ROUND($O16*R16,2) -> 25254.3 | R16: 0.15 | S16: =ROUND($O16*T16,2) -> 6313.58 | T16: 0.0375 | U16: =IF($F16&"/Día"=W$9,SUM($G16:$H16),"") -> 2532 | V16: =IF(U16<>"",$O16,"") -> 168362.02 | W16: =IF($F16&"/Día"=W$9,ROUND(U16/$W$1,1),"") -> 81.7 | X16: =IF(U16=0,0,IF($F16&"/Día"=W$9,ROUND(V16/U16,4),"")) -> 66.4937 | Y16: =IF(U16=0,0,IF($F16&"/Día"=W$9,ROUND(Z16/U16,4),"")) -> 12.4676 | Z16: =IF(U16<>"",$P16,"") -> 31567.88 | AA16: =IF($F16&"/Día"=AC$9,SUM($G16:$H16),"") | AB16: =IF(AA16<>"",$O16,"") | AC16: =IF($F16&"/Día"=AC$9,ROUND(AA16/$W$1,1),"") | AD16: =IF(AA16=0,0,IF($F16&"/Día"=AC$9,ROUND(AB16/AA16,4),"")) | AE16: =IF(AA16=0,0,IF($F16&"/Día"=AC$9,ROUND(AF16/AA16,4),"")) | AF16: =IF(AA16<>"",$P16,"")
A17: - | B17: VII/VI | C17: Licencia | D17: Quincena | E17: F2 | F17: Bls | G17: 46815 | H17: 59830 | I17: 66.2472 | J17: 66.7679 | N17: 2221.88 | O17: =ROUND(G17*I17,2)+ROUND(H17*J17,2)-K17-L17-M17-N17 -> 7093864.2 | P17: =ROUND(18.75%*O17,2) -> 1330099.6 | Q17: =ROUND($O17*R17,2) -> 1064079.6 | R17: 0.15 | S17: =ROUND($O17*T17,2) -> 266019.91 | T17: 0.0375 | U17: =IF($F17&"/Día"=W$9,SUM($G17:$H17),"") -> 106645 | V17: =IF(U17<>"",$O17,"") -> 7093864.2 | W17: =IF($F17&"/Día"=W$9,ROUND(U17/$W$1,1),"") -> 3440.2 | X17: =IF(U17=0,0,IF($F17&"/Día"=W$9,ROUND(V17/U17,4),"")) -> 66.5185 | Y17: =IF(U17=0,0,IF($F17&"/Día"=W$9,ROUND(Z17/U17,4),"")) -> 12.4722 | Z17: =IF(U17<>"",$P17,"") -> 1330099.6 | AA17: =IF($F17&"/Día"=AC$9,SUM($G17:$H17),"") | AB17: =IF(AA17<>"",$O17,"") | AC17: =IF($F17&"/Día"=AC$9,ROUND(AA17/$W$1,1),"") | AD17: =IF(AA17=0,0,IF($F17&"/Día"=AC$9,ROUND(AB17/AA17,4),"")) | AE17: =IF(AA17=0,0,IF($F17&"/Día"=AC$9,ROUND(AF17/AA17,4),"")) | AF17: =IF(AA17<>"",$P17,"")
A18: - | B18: VII | C18: Servicios | D18: Mes | E18: F1 | F18: Bls | O18: =ROUND(G18*I18,2)+ROUND(H18*J18,2)-K18-L18-M18-N18 -> 0 | P18: =ROUND(18.75%*O18,2) -> 0 | Q18: =ROUND($O18*R18,2) -> 0 | R18: 0.15 | S18: =ROUND($O18*T18,2) -> 0 | T18: 0.0375 | U18: =IF($F18&"/Día"=W$9,SUM($G18:$H18),"") -> 0 | V18: =IF(U18<>"",$O18,"") -> 0 | W18: =IF($F18&"/Día"=W$9,ROUND(U18/$W$1,1),"") -> 0 | X18: =IF(U18=0,0,IF($F18&"/Día"=W$9,ROUND(V18/U18,4),"")) -> 0 | Y18: =IF(U18=0,0,IF($F18&"/Día"=W$9,ROUND(Z18/U18,4),"")) -> 0 | Z18: =IF(U18<>"",$P18,"") -> 0 | AA18: =IF($F18&"/Día"=AC$9,SUM($G18:$H18),"") | AB18: =IF(AA18<>"",$O18,"") | AC18: =IF($F18&"/Día"=AC$9,ROUND(AA18/$W$1,1),"") | AD18: =IF(AA18=0,0,IF($F18&"/Día"=AC$9,ROUND(AB18/AA18,4),"")) | AE18: =IF(AA18=0,0,IF($F18&"/Día"=AC$9,ROUND(AF18/AA18,4),"")) | AF18: =IF(AA18<>"",$P18,"")
A19: - | B19: VII/VI-GAS | C19: Licencia | D19: Quincena | E19: F2 | F19: MM BTU | G19: 58474.37 | H19: 64682.42 | I19: 2.1708 | J19: 2.1708 | N19: 2121.65 | O19: =ROUND(G19*I19,2)+ROUND(H19*J19,2)-K19-L19-M19-N19 -> 265227.11 | P19: =ROUND(18.75%*O19,2) -> 49730.08 | Q19: =ROUND($O19*R19,2) -> 39784.07 | R19: 0.15 | S19: =ROUND($O19*T19,2) -> 9946.02 | T19: 0.0375 | U19: =IF($F19&"/Día"=W$9,SUM($G19:$H19),"") | V19: =IF(U19<>"",$O19,"") | W19: =IF($F19&"/Día"=W$9,ROUND(U19/$W$1,1),"") | X19: =IF(U19=0,0,IF($F19&"/Día"=W$9,ROUND(V19/U19,4),"")) | Y19: =IF(U19=0,0,IF($F19&"/Día"=W$9,ROUND(Z19/U19,4),"")) | Z19: =IF(U19<>"",$P19,"") | AA19: =IF($F19&"/Día"=AC$9,SUM($G19:$H19),"") -> 123156.79 | AB19: =IF(AA19<>"",$O19,"") -> 265227.11 | AC19: =IF($F19&"/Día"=AC$9,ROUND(AA19/$W$1,1),"") -> 3972.8 | AD19: =IF(AA19=0,0,IF($F19&"/Día"=AC$9,ROUND(AB19/AA19,4),"")) -> 2.1536 | AE19: =IF(AA19=0,0,IF($F19&"/Día"=AC$9,ROUND(AF19/AA19,4),"")) -> 0.4038 | AF19: =IF(AA19<>"",$P19,"") -> 49730.08
A20: - | B20: IX | C20: Licencia | D20: Quincena | E20: F2 | F20: Bls | G20: 2083 | H20: 3260 | I20: 66.7972 | J20: 67.3179 | N20: 737.78 | O20: =ROUND(G20*I20,2)+ROUND(H20*J20,2)-K20-L20-M20-N20 -> 357857.14 | P20: =ROUND(18.75%*O20,2) -> 67098.21 | Q20: =ROUND($O20*R20,2) -> 53678.57 | R20: 0.15 | S20: =ROUND($O20*T20,2) -> 13419.64 | T20: 0.0375 | U20: =IF($F20&"/Día"=W$9,SUM($G20:$H20),"") -> 5343 | V20: =IF(U20<>"",$O20,"") -> 357857.14 | W20: =IF($F20&"/Día"=W$9,ROUND(U20/$W$1,1),"") -> 172.4 | X20: =IF(U20=0,0,IF($F20&"/Día"=W$9,ROUND(V20/U20,4),"")) -> 66.9768 | Y20: =IF(U20=0,0,IF($F20&"/Día"=W$9,ROUND(Z20/U20,4),"")) -> 12.5582 | Z20: =IF(U20<>"",$P20,"") -> 67098.21 | AA20: =IF($F20&"/Día"=AC$9,SUM($G20:$H20),"") | AB20: =IF(AA20<>"",$O20,"") | AC20: =IF($F20&"/Día"=AC$9,ROUND(AA20/$W$1,1),"") | AD20: =IF(AA20=0,0,IF($F20&"/Día"=AC$9,ROUND(AB20/AA20,4),"")) | AE20: =IF(AA20=0,0,IF($F20&"/Día"=AC$9,ROUND(AF20/AA20,4),"")) | AF20: =IF(AA20<>"",$P20,"")
A21: - | B21: X | C21: Licencia | D21: Quincena | E21: F2 | F21: Bls | G21: 195037 | H21: 205982 | I21: 66.7972 | J21: 67.3179 | N21: 4334.18 | O21: =ROUND(G21*I21,2)+ROUND(H21*J21,2)-K21-L21-M21-N21 -> 26889867 | P21: =ROUND(18.75%*O21,2) -> 5041850.1 | Q21: =ROUND($O21*R21,2) -> 4033480 | R21: 0.15 | S21: =ROUND($O21*T21,2) -> 1008370 | T21: 0.0375 | U21: =IF($F21&"/Día"=W$9,SUM($G21:$H21),"") -> 401019 | V21: =IF(U21<>"",$O21,"") -> 26889867 | W21: =IF($F21&"/Día"=W$9,ROUND(U21/$W$1,1),"") -> 12936.1 | X21: =IF(U21=0,0,IF($F21&"/Día"=W$9,ROUND(V21/U21,4),"")) -> 67.0538 | Y21: =IF(U21=0,0,IF($F21&"/Día"=W$9,ROUND(Z21/U21,4),"")) -> 12.5726 | Z21: =IF(U21<>"",$P21,"") -> 5041850.1 | AA21: =IF($F21&"/Día"=AC$9,SUM($G21:$H21),"") | AB21: =IF(AA21<>"",$O21,"") | AC21: =IF($F21&"/Día"=AC$9,ROUND(AA21/$W$1,1),"") | AD21: =IF(AA21=0,0,IF($F21&"/Día"=AC$9,ROUND(AB21/AA21,4),"")) | AE21: =IF(AA21=0,0,IF($F21&"/Día"=AC$9,ROUND(AF21/AA21,4),"")) | AF21: =IF(AA21<>"",$P21,"")
A22: - | B22: X-GAS | C22: Licencia | D22: Mes | E22: F2 | F22: MM BTU | G22: 251980.16 | H22: 254840.6 | I22: 1.8012 | J22: 1.8012 | N22: 2235.16 | O22: =ROUND(G22*I22,2)+ROUND(H22*J22,2)-K22-L22-M22-N22 -> 910650.39 | P22: =ROUND(18.75%*O22,2) -> 170746.95 | Q22: =ROUND($O22*R22,2) -> 136597.56 | R22: 0.15 | S22: =ROUND($O22*T22,2) -> 34149.39 | T22: 0.0375 | U22: =IF($F22&"/Día"=W$9,SUM($G22:$H22),"") | V22: =IF(U22<>"",$O22,"") | W22: =IF($F22&"/Día"=W$9,ROUND(U22/$W$1,1),"") | X22: =IF(U22=0,0,IF($F22&"/Día"=W$9,ROUND(V22/U22,4),"")) | Y22: =IF(U22=0,0,IF($F22&"/Día"=W$9,ROUND(Z22/U22,4),"")) | Z22: =IF(U22<>"",$P22,"") | AA22: =IF($F22&"/Día"=AC$9,SUM($G22:$H22),"") -> 506820.76 | AB22: =IF(AA22<>"",$O22,"") -> 910650.39 | AC22: =IF($F22&"/Día"=AC$9,ROUND(AA22/$W$1,1),"") -> 16349.1 | AD22: =IF(AA22=0,0,IF($F22&"/Día"=AC$9,ROUND(AB22/AA22,4),"")) -> 1.7968 | AE22: =IF(AA22=0,0,IF($F22&"/Día"=AC$9,ROUND(AF22/AA22,4),"")) -> 0.3369 | AF22: =IF(AA22<>"",$P22,"") -> 170746.95
A23: - | B23: XIV | C23: Licencia | D23: Mes | E23: F2 | F23: Bls | O23: =ROUND(G23*I23,2)+ROUND(H23*J23,2)-K23-L23-M23-N23 -> 0 | P23: =ROUND(18.75%*O23,2) -> 0 | Q23: =ROUND($O23*R23,2) -> 0 | R23: 0.15 | S23: =ROUND($O23*T23,2) -> 0 | T23: 0.0375 | U23: =IF($F23&"/Día"=W$9,SUM($G23:$H23),"") -> 0 | V23: =IF(U23<>"",$O23,"") -> 0 | W23: =IF($F23&"/Día"=W$9,ROUND(U23/$W$1,1),"") -> 0 | X23: =IF(U23=0,0,IF($F23&"/Día"=W$9,ROUND(V23/U23,4),"")) -> 0 | Y23: =IF(U23=0,0,IF($F23&"/Día"=W$9,ROUND(Z23/U23,4),"")) -> 0 | Z23: =IF(U23<>"",$P23,"") -> 0 | AA23: =IF($F23&"/Día"=AC$9,SUM($G23:$H23),"") | AB23: =IF(AA23<>"",$O23,"") | AC23: =IF($F23&"/Día"=AC$9,ROUND(AA23/$W$1,1),"") | AD23: =IF(AA23=0,0,IF($F23&"/Día"=AC$9,ROUND(AB23/AA23,4),"")) | AE23: =IF(AA23=0,0,IF($F23&"/Día"=AC$9,ROUND(AF23/AA23,4),"")) | AF23: =IF(AA23<>"",$P23,"")
A24: - | B24: XV | C24: Licencia | D24: Quincena | E24: F2 | F24: Bls | G24: 564 | H24: 535 | I24: 66.5365 | J24: 67.7014 | N24: 802.26 | O24: =ROUND(G24*I24,2)+ROUND(H24*J24,2)-K24-L24-M24-N24 -> 72944.58 | P24: =ROUND(18.75%*O24,2) -> 13677.11 | Q24: =ROUND($O24*R24,2) -> 10941.69 | R24: 0.15 | S24: =ROUND($O24*T24,2) -> 2735.42 | T24: 0.0375 | U24: =IF($F24&"/Día"=W$9,SUM($G24:$H24),"") -> 1099 | V24: =IF(U24<>"",$O24,"") -> 72944.58 | W24: =IF($F24&"/Día"=W$9,ROUND(U24/$W$1,1),"") -> 35.5 | X24: =IF(U24=0,0,IF($F24&"/Día"=W$9,ROUND(V24/U24,4),"")) -> 66.3736 | Y24: =IF(U24=0,0,IF($F24&"/Día"=W$9,ROUND(Z24/U24,4),"")) -> 12.4451 | Z24: =IF(U24<>"",$P24,"") -> 13677.11 | AA24: =IF($F24&"/Día"=AC$9,SUM($G24:$H24),"") | AB24: =IF(AA24<>"",$O24,"") | AC24: =IF($F24&"/Día"=AC$9,ROUND(AA24/$W$1,1),"") | AD24: =IF(AA24=0,0,IF($F24&"/Día"=AC$9,ROUND(AB24/AA24,4),"")) | AE24: =IF(AA24=0,0,IF($F24&"/Día"=AC$9,ROUND(AF24/AA24,4),"")) | AF24: =IF(AA24<>"",$P24,"")
A25: - | B25: XIII Crudo | C25: Licencia | D25: Quincena | E25: F2 | F25: Bls | G25: 28828 | H25: 36208 | I25: 66.7972 | J25: 67.3179 | N25: 1530.48 | O25: =ROUND(G25*I25,2)+ROUND(H25*J25,2)-K25-L25-M25-N25 -> 4361545.7 | P25: =ROUND(18.75%*O25,2) -> 817789.82 | Q25: =ROUND($O25*R25,2) -> 654231.86 | R25: 0.15 | S25: =ROUND($O25*T25,2) -> 163557.96 | T25: 0.0375 | U25: =IF($F25&"/Día"=W$9,SUM($G25:$H25),"") -> 65036 | V25: =IF(U25<>"",$O25,"") -> 4361545.7 | W25: =IF($F25&"/Día"=W$9,ROUND(U25/$W$1,1),"") -> 2097.9 | X25: =IF(U25=0,0,IF($F25&"/Día"=W$9,ROUND(V25/U25,4),"")) -> 67.0636 | Y25: =IF(U25=0,0,IF($F25&"/Día"=W$9,ROUND(Z25/U25,4),"")) -> 12.5744 | Z25: =IF(U25<>"",$P25,"") -> 817789.82 | AA25: =IF($F25&"/Día"=AC$9,SUM($G25:$H25),"") | AB25: =IF(AA25<>"",$O25,"") | AC25: =IF($F25&"/Día"=AC$9,ROUND(AA25/$W$1,1),"") | AD25: =IF(AA25=0,0,IF($F25&"/Día"=AC$9,ROUND(AB25/AA25,4),"")) | AE25: =IF(AA25=0,0,IF($F25&"/Día"=AC$9,ROUND(AF25/AA25,4),"")) | AF25: =IF(AA25<>"",$P25,"")
A26: - | B26: XIII COND | C26: Licencia | D26: Quincena | E26: F2 | F26: Bls | O26: =ROUND(G26*I26,2)+ROUND(H26*J26,2)-K26-L26-M26-N26 -> 0 | P26: =ROUND(18.75%*O26,2) -> 0 | Q26: =ROUND($O26*R26,2) -> 0 | R26: 0.15 | S26: =ROUND($O26*T26,2) -> 0 | T26: 0.0375 | U26: =IF($F26&"/Día"=W$9,SUM($G26:$H26),"") -> 0 | V26: =IF(U26<>"",$O26,"") -> 0 | W26: =IF($F26&"/Día"=W$9,ROUND(U26/$W$1,1),"") -> 0 | X26: =IF(U26=0,0,IF($F26&"/Día"=W$9,ROUND(V26/U26,4),"")) -> 0 | Y26: =IF(U26=0,0,IF($F26&"/Día"=W$9,ROUND(Z26/U26,4),"")) -> 0 | Z26: =IF(U26<>"",$P26,"") -> 0 | AA26: =IF($F26&"/Día"=AC$9,SUM($G26:$H26),"") | AB26: =IF(AA26<>"",$O26,"") | AC26: =IF($F26&"/Día"=AC$9,ROUND(AA26/$W$1,1),"") | AD26: =IF(AA26=0,0,IF($F26&"/Día"=AC$9,ROUND(AB26/AA26,4),"")) | AE26: =IF(AA26=0,0,IF($F26&"/Día"=AC$9,ROUND(AF26/AA26,4),"")) | AF26: =IF(AA26<>"",$P26,"")
A27: - | B27: XIII Gas | C27: Licencia | D27: Quincena | E27: F2 | F27: MM BTU | G27: =109679.9639+69454.7114 -> 179134.68 | H27: =115352.29+94462.85 -> 209815.14 | I27: 2.4759775 | J27: 2.6336074 | N27: 3163.29 | O27: =ROUND(G27*I27,2)+ROUND(H27*J27,2)-K27-L27-M27-N27 -> 992940.84 | P27: =ROUND(18.75%*O27,2) -> 186176.41 | Q27: =ROUND($O27*R27,2) -> 148941.13 | R27: 0.15 | S27: =ROUND($O27*T27,2) -> 37235.28 | T27: 0.0375 | U27: =IF($F27&"/Día"=W$9,SUM($G27:$H27),"") | V27: =IF(U27<>"",$O27,"") | W27: =IF($F27&"/Día"=W$9,ROUND(U27/$W$1,1),"") | X27: =IF(U27=0,0,IF($F27&"/Día"=W$9,ROUND(V27/U27,4),"")) | Y27: =IF(U27=0,0,IF($F27&"/Día"=W$9,ROUND(Z27/U27,4),"")) | Z27: =IF(U27<>"",$P27,"") | AA27: =IF($F27&"/Día"=AC$9,SUM($G27:$H27),"") -> 388949.82 | AB27: =IF(AA27<>"",$O27,"") -> 992940.84 | AC27: =IF($F27&"/Día"=AC$9,ROUND(AA27/$W$1,1),"") -> 12546.8 | AD27: =IF(AA27=0,0,IF($F27&"/Día"=AC$9,ROUND(AB27/AA27,4),"")) -> 2.5529 | AE27: =IF(AA27=0,0,IF($F27&"/Día"=AC$9,ROUND(AF27/AA27,4),"")) -> 0.4787 | AF27: =IF(AA27<>"",$P27,"") -> 186176.41
A28: - | B28: Z-2B | C28: Servicios | D28: Mes | E28: F1 | F28: Bls | H28: =39453+207131 -> 246584 | J28: 64.0398 | N28: 2445.75 | O28: =ROUND(G28*I28,2)+ROUND(H28*J28,2)-K28-L28-M28-N28 -> 15788744 | P28: =ROUND(18.75%*O28,2) -> 2960389.5 | Q28: =ROUND($O28*R28,2) -> 2368311.6 | R28: 0.15 | S28: =ROUND($O28*T28,2) -> 592077.91 | T28: 0.0375 | U28: =IF($F28&"/Día"=W$9,SUM($G28:$H28),"") -> 246584 | V28: =IF(U28<>"",$O28,"") -> 15788744 | W28: =IF($F28&"/Día"=W$9,ROUND(U28/$W$1,1),"") -> 7954.3 | X28: =IF(U28=0,0,IF($F28&"/Día"=W$9,ROUND(V28/U28,4),"")) -> 64.0299 | Y28: =IF(U28=0,0,IF($F28&"/Día"=W$9,ROUND(Z28/U28,4),"")) -> 12.0056 | Z28: =IF(U28<>"",$P28,"") -> 2960389.5 | AA28: =IF($F28&"/Día"=AC$9,SUM($G28:$H28),"") | AB28: =IF(AA28<>"",$O28,"") | AC28: =IF($F28&"/Día"=AC$9,ROUND(AA28/$W$1,1),"") | AD28: =IF(AA28=0,0,IF($F28&"/Día"=AC$9,ROUND(AB28/AA28,4),"")) | AE28: =IF(AA28=0,0,IF($F28&"/Día"=AC$9,ROUND(AF28/AA28,4),"")) | AF28: =IF(AA28<>"",$P28,"")
A29: - | B29: Z-2B GAS | C29: Servicios | D29: Mes | E29: F1 | F29: MM BTU | H29: =28128.11+153471.87+1104.62 -> 182704.6 | J29: 5.4650451 | N29: 2156.75 | O29: =ROUND(G29*I29,2)+ROUND(H29*J29,2)-K29-L29-M29-N29 -> 996332.12 | P29: =ROUND(18.75%*O29,2) -> 186812.27 | Q29: =ROUND($O29*R29,2) -> 149449.82 | R29: 0.15 | S29: =ROUND($O29*T29,2) -> 37362.45 | T29: 0.0375 | U29: =IF($F29&"/Día"=W$9,SUM($G29:$H29),"") | V29: =IF(U29<>"",$O29,"") | W29: =IF($F29&"/Día"=W$9,ROUND(U29/$W$1,1),"") | X29: =IF(U29=0,0,IF($F29&"/Día"=W$9,ROUND(V29/U29,4),"")) | Y29: =IF(U29=0,0,IF($F29&"/Día"=W$9,ROUND(Z29/U29,4),"")) | Z29: =IF(U29<>"",$P29,"") | AA29: =IF($F29&"/Día"=AC$9,SUM($G29:$H29),"") -> 182704.6 | AB29: =IF(AA29<>"",$O29,"") -> 996332.12 | AC29: =IF($F29&"/Día"=AC$9,ROUND(AA29/$W$1,1),"") -> 5893.7 | AD29: =IF(AA29=0,0,IF($F29&"/Día"=AC$9,ROUND(AB29/AA29,4),"")) -> 5.4532 | AE29: =IF(AA29=0,0,IF($F29&"/Día"=AC$9,ROUND(AF29/AA29,4),"")) -> 1.0225 | AF29: =IF(AA29<>"",$P29,"") -> 186812.27
A30: - | B30: XX | C30: Licencia | D30: Quincena | E30: F2 | F30: Bls | G30: 480 | H30: 368 | I30: 66.7972 | J30: 67.3179 | N30: 471.2 | O30: =ROUND(G30*I30,2)+ROUND(H30*J30,2)-K30-L30-M30-N30 -> 56364.45 | P30: =ROUND(18.75%*O30,2) -> 10568.33 | Q30: =ROUND($O30*R30,2) -> 2113.67 | R30: 0.0375 | S30: =ROUND($O30*T30,2) -> 8454.67 | T30: 0.15 | U30: =IF($F30&"/Día"=W$9,SUM($G30:$H30),"") -> 848 | V30: =IF(U30<>"",$O30,"") -> 56364.45 | W30: =IF($F30&"/Día"=W$9,ROUND(U30/$W$1,1),"") -> 27.4 | X30: =IF(U30=0,0,IF($F30&"/Día"=W$9,ROUND(V30/U30,4),"")) -> 66.4675 | Y30: =IF(U30=0,0,IF($F30&"/Día"=W$9,ROUND(Z30/U30,4),"")) -> 12.4627 | Z30: =IF(U30<>"",$P30,"") -> 10568.33 | AA30: =IF($F30&"/Día"=AC$9,SUM($G30:$H30),"") | AB30: =IF(AA30<>"",$O30,"") | AC30: =IF($F30&"/Día"=AC$9,ROUND(AA30/$W$1,1),"") | AD30: =IF(AA30=0,0,IF($F30&"/Día"=AC$9,ROUND(AB30/AA30,4),"")) | AE30: =IF(AA30=0,0,IF($F30&"/Día"=AC$9,ROUND(AF30/AA30,4),"")) | AF30: =IF(AA30<>"",$P30,"")
A31: - | B31: Z1 Crudo | C31: Licencia | D31: Quincena | E31: F2 | F31: Bls | N31: 1450.98 | O31: =ROUND(G31*I31,2)+ROUND(H31*J31,2)-K31-L31-M31-N31 -> -1450.98 | P31: =ROUND(18.75%*O31,2) -> -272.06 | Q31: =ROUND($O31*R31,2) -> -54.41 | R31: 0.0375 | S31: =ROUND($O31*T31,2) -> -217.65 | T31: 0.15 | U31: =IF($F31&"/Día"=W$9,SUM($G31:$H31),"") -> 0 | V31: =IF(U31<>"",$O31,"") -> -1450.98 | W31: =IF($F31&"/Día"=W$9,ROUND(U31/$W$1,1),"") -> 0 | X31: =IF(U31=0,0,IF($F31&"/Día"=W$9,ROUND(V31/U31,4),"")) -> 0 | Y31: =IF(U31=0,0,IF($F31&"/Día"=W$9,ROUND(Z31/U31,4),"")) -> 0 | Z31: =IF(U31<>"",$P31,"") -> -272.06 | AA31: =IF($F31&"/Día"=AC$9,SUM($G31:$H31),"") | AB31: =IF(AA31<>"",$O31,"") | AC31: =IF($F31&"/Día"=AC$9,ROUND(AA31/$W$1,1),"") | AD31: =IF(AA31=0,0,IF($F31&"/Día"=AC$9,ROUND(AB31/AA31,4),"")) | AE31: =IF(AA31=0,0,IF($F31&"/Día"=AC$9,ROUND(AF31/AA31,4),"")) | AF31: =IF(AA31<>"",$P31,"")
A32: - | B32: Z1 Gas | C32: Licencia | D32: Quincena | E32: F2 | F32: MM BTU | O32: =ROUND(G32*I32,2)+ROUND(H32*J32,2)-K32-L32-M32-N32 -> 0 | P32: =ROUND(18.75%*O32,2) -> 0 | Q32: =ROUND($O32*R32,2) -> 0 | R32: 0.0375 | S32: =ROUND($O32*T32,2) -> 0 | T32: 0.15 | U32: =IF($F32&"/Día"=W$9,SUM($G32:$H32),"") | V32: =IF(U32<>"",$O32,"") | W32: =IF($F32&"/Día"=W$9,ROUND(U32/$W$1,1),"") | X32: =IF(U32=0,0,IF($F32&"/Día"=W$9,ROUND(V32/U32,4),"")) | Y32: =IF(U32=0,0,IF($F32&"/Día"=W$9,ROUND(Z32/U32,4),"")) | Z32: =IF(U32<>"",$P32,"") | AA32: =IF($F32&"/Día"=AC$9,SUM($G32:$H32),"") -> 0 | AB32: =IF(AA32<>"",$O32,"") -> 0 | AC32: =IF($F32&"/Día"=AC$9,ROUND(AA32/$W$1,1),"") -> 0 | AD32: =IF(AA32=0,0,IF($F32&"/Día"=AC$9,ROUND(AB32/AA32,4),"")) -> 0 | AE32: =IF(AA32=0,0,IF($F32&"/Día"=AC$9,ROUND(AF32/AA32,4),"")) -> 0 | AF32: =IF(AA32<>"",$P32,"") -> 0
A33: - | B33: Z-2B - LGN | C33: Servicios | D33: Mes | E33: F1 | F33: Bls | H33: =5522+28988 -> 34510 | J33: 59.0561 | N33: 2349.32 | O33: =ROUND(G33*I33,2)+ROUND(H33*J33,2)-K33-L33-M33-N33 -> 2035676.7 | P33: =ROUND(18.75%*O33,2) -> 381689.38 | Q33: =ROUND($O33*R33,2) -> 305351.5 | R33: 0.15 | S33: =ROUND($O33*T33,2) -> 76337.88 | T33: 0.0375 | U33: =IF($F33&"/Día"=W$9,SUM($G33:$H33),"") -> 34510 | V33: =IF(U33<>"",$O33,"") -> 2035676.7 | W33: =IF($F33&"/Día"=W$9,ROUND(U33/$W$1,1),"") -> 1113.2 | X33: =IF(U33=0,0,IF($F33&"/Día"=W$9,ROUND(V33/U33,4),"")) -> 58.988 | Y33: =IF(U33=0,0,IF($F33&"/Día"=W$9,ROUND(Z33/U33,4),"")) -> 11.0603 | Z33: =IF(U33<>"",$P33,"") -> 381689.38 | AA33: =IF($F33&"/Día"=AC$9,SUM($G33:$H33),"") | AB33: =IF(AA33<>"",$O33,"") | AC33: =IF($F33&"/Día"=AC$9,ROUND(AA33/$W$1,1),"") | AD33: =IF(AA33=0,0,IF($F33&"/Día"=AC$9,ROUND(AB33/AA33,4),"")) | AE33: =IF(AA33=0,0,IF($F33&"/Día"=AC$9,ROUND(AF33/AA33,4),"")) | AF33: =IF(AA33<>"",$P33,"")
A34: - | B34: Z-6 | C34: Licencia | D34: Quincena | E34: F2 | F34: MM BTU | O34: =ROUND(G34*I34,2)+ROUND(H34*J34,2)-K34-L34-M34-N34 -> 0 | P34: =ROUND(18.75%*O34,2) -> 0 | Q34: =ROUND($O34*R34,2) -> 0 | R34: 0.15 | S34: =ROUND($O34*T34,2) -> 0 | T34: 0.0375
A35: - | B35: Ajustes meses anteriores (1) | O35: =+O149 -> -23595.17 | P35: =ROUND(18.75%*O35,2) -> -4424.09 | Q35: =+Q149 -> -3539.28 | S35: =+S149 -> -884.82 | U35: =IF($F35&"/Día"=W$9,SUM($G35:$H35),"") | V35: =IF(U35<>"",$O35,"") | W35: =IF($F35&"/Día"=W$9,ROUND(U35/$W$1,1),"") | X35: =IF(U35=0,0,IF($F35&"/Día"=W$9,ROUND(V35/U35,4),"")) | Y35: =IF(U35=0,0,IF($F35&"/Día"=W$9,ROUND(Z35/U35,4),"")) | Z35: =IF(U35<>"",$P35,"") | AA35: =IF($F35&"/Día"=AC$9,SUM($G35:$H35),"") | AB35: =IF(AA35<>"",$O35,"") | AC35: =IF($F35&"/Día"=AC$9,ROUND(AA35/$W$1,1),"") | AD35: =IF(AA35=0,0,IF($F35&"/Día"=AC$9,ROUND(AB35/AA35,4),"")) | AE35: =IF(AA35=0,0,IF($F35&"/Día"=AC$9,ROUND(AF35/AA35,4),"")) | AF35: =IF(AA35<>"",$P35,"")
B36: Subtotal | C36: =TEXT(A$9,)&" US$" -> Piura / Tumbes US$ | O36: =SUM(O10:O35) -> 67371407 | P36: =SUM(P10:P35) -> 12632139 | Q36: =SUM(Q10:Q35) -> 10099533 | S36: =SUM(S10:S35) -> 2532605.5 | U36: =SUM(U10:U35) -> 960035 | V36: =SUM(V10:V35) -> 63261917 | W36: =SUM(W10:W35) -> 30969.1 | X36: =ROUND(V36/U36,4) -> 65.8954 | Y36: =ROUND(Z36/U36,4) -> 12.3554 | Z36: =SUM(Z10:Z35) -> 11861609 | AA36: =SUM(AA10:AA35) -> 1539785.8 | AB36: =SUM(AB10:AB35) -> 4133085.2 | AC36: =SUM(AC10:AC35) -> 49670.5 | AD36: =ROUND(AB36/AA36,4) -> 2.6842 | AE36: =ROUND(AF36/AA36,4) -> 0.5033 | AF36: =SUM(AF10:AF35) -> 774953.48 | AG36: =P36-Z36-AF36 -> -4424.09
C37: =TEXT(A$9,)&" S/." -> Piura / Tumbes S/. | P37: =ROUND($F$1*P36,2) -> 0 | Q37: =ROUND($F$1*Q36,2) -> 0 | S37: =ROUND($F$1*S36,2) -> 0
A38: Provincia Puerto Inca Huanuco | Q38: Puerto Inca
A39: - | B39: 31-D | C39: Licencia | D39: Quincena | E39: F2 | F39: Bls | H39: 2156 | J39: 68.2014 | N39: 1112.44 | O39: =ROUND(G39*I39,2)+ROUND(H39*J39,2)-K39-L39-M39-N39 -> 145929.78 | P39: =ROUND(15%*O39,2) -> 21889.47 | Q39: =ROUND($O39*R39,2) -> 21889.47 | R39: 0.15 | U39: =IF($F39&"/Día"=W$9,SUM($G39:$H39),"") -> 2156 | V39: =IF(U39<>"",$O39,"") -> 145929.78 | W39: =IF($F39&"/Día"=W$9,ROUND(U39/$W$1,1),"") -> 69.5 | X39: =IF(U39=0,0,IF($F39&"/Día"=W$9,ROUND(V39/U39,4),"")) -> 67.6854 | Y39: =IF(U39=0,0,IF($F39&"/Día"=W$9,ROUND(Z39/U39,4),"")) -> 10.1528 | Z39: =IF(U39<>"",$P39,"") -> 21889.47 | AA39: =IF($F39&"/Día"=AC$9,SUM($G39:$H39),"") | AB39: =IF(AA39<>"",$O39,"") | AC39: =IF($F39&"/Día"=AC$9,ROUND(AA39/$W$1,1),"") | AD39: =IF(AA39=0,0,IF($F39&"/Día"=AC$9,ROUND(AB39/AA39,4),"")) | AE39: =IF(AA39=0,0,IF($F39&"/Día"=AC$9,ROUND(AF39/AA39,4),"")) | AF39: =IF(AA39<>"",$P39,"")
A40: - | B40: 131 | C40: Licencia | D40: Quincena | E40: F2 | F40: Bls | G40: 41943 | H40: 45761 | I40: 64.135 | J40: 64.8264 | N40: 9444.89 | O40: =ROUND(G40*I40,2)+ROUND(H40*J40,2)-K40-L40-M40-N40 -> 5647090.3 | P40: =ROUND(15%*O40,2) -> 847063.55 | Q40: =ROUND($O40*R40,2) -> 847063.55 | R40: 0.15 | U40: =IF($F40&"/Día"=W$9,SUM($G40:$H40),"") -> 87704 | V40: =IF(U40<>"",$O40,"") -> 5647090.3 | W40: =IF($F40&"/Día"=W$9,ROUND(U40/$W$1,1),"") -> 2829.2 | X40: =IF(U40=0,0,IF($F40&"/Día"=W$9,ROUND(V40/U40,4),"")) -> 64.3881 | Y40: =IF(U40=0,0,IF($F40&"/Día"=W$9,ROUND(Z40/U40,4),"")) -> 9.6582 | Z40: =IF(U40<>"",$P40,"") -> 847063.55 | AA40: =IF($F40&"/Día"=AC$9,SUM($G40:$H40),"") | AB40: =IF(AA40<>"",$O40,"") | AC40: =IF($F40&"/Día"=AC$9,ROUND(AA40/$W$1,1),"") | AD40: =IF(AA40=0,0,IF($F40&"/Día"=AC$9,ROUND(AB40/AA40,4),"")) | AE40: =IF(AA40=0,0,IF($F40&"/Día"=AC$9,ROUND(AF40/AA40,4),"")) | AF40: =IF(AA40<>"",$P40,"")
A41: - | B41: Ajustes meses anteriores (2) | U41: =IF($F41&"/Día"=W$9,SUM($G41:$H41),"") | V41: =IF(U41<>"",$O41,"") | W41: =IF($F41&"/Día"=W$9,ROUND(U41/$W$1,1),"") | X41: =IF(U41=0,0,IF($F41&"/Día"=W$9,ROUND(V41/U41,4),"")) | Y41: =IF(U41=0,0,IF($F41&"/Día"=W$9,ROUND(Z41/U41,4),"")) | Z41: =IF(U41<>"",$P41,"") | AA41: =IF($F41&"/Día"=AC$9,SUM($G41:$H41),"") | AB41: =IF(AA41<>"",$O41,"") | AC41: =IF($F41&"/Día"=AC$9,ROUND(AA41/$W$1,1),"") | AD41: =IF(AA41=0,0,IF($F41&"/Día"=AC$9,ROUND(AB41/AA41,4),"")) | AE41: =IF(AA41=0,0,IF($F41&"/Día"=AC$9,ROUND(AF41/AA41,4),"")) | AF41: =IF(AA41<>"",$P41,"")
B42: Subtotal | C42: =TEXT(A$38,)&" US$" -> Provincia Puerto Inca Huanuco US$ | O42: =SUM(O39:O41) -> 5793020.1 | P42: =SUM(P39:P41) -> 868953.02 | Q42: =SUM(Q39:Q41) -> 868953.02 | S42: =SUM(S39:S41) -> 0 | U42: =SUM(U39:U41) -> 89860 | V42: =SUM(V39:V41) -> 5793020.1 | W42: =SUM(W39:W41) -> 2898.7 | X42: =ROUND(V42/U42,4) -> 64.4672 | Y42: =ROUND(Z42/U42,4) -> 9.6701 | Z42: =SUM(Z39:Z41) -> 868953.02 | AA42: =SUM(AA39:AA41) -> 0 | AB42: =SUM(AB39:AB41) -> 0 | AC42: =SUM(AC39:AC41) -> 0 | AD42: =IF(AA42=0,0,ROUND(AB42/AA42,4)) -> 0 | AE42: =IF(AA42=0,0,ROUND(AF42/AA42,4)) -> 0 | AF42: =SUM(AF39:AF41) -> 0 | AG42: =P42-Z42-AF42 -> 0
C43: =TEXT(A$38,)&" S/." -> Provincia Puerto Inca Huanuco S/. | P43: =ROUND($F$1*P42,2) -> 0 | Q43: =ROUND($F$1*Q42,2) -> 0 | S43: =ROUND($F$1*S42,2) -> 0
A44: Loreto / Ucayali | Q44: Loreto | S44: Ucayali
A45: - | B45: 31-E | C45: Licencia | D45: Mes | E45: F2 | F45: Bls | H45: 1460 | J45: 57.5825 | N45: 513.71 | O45: =ROUND(G45*I45,2)+ROUND(H45*J45,2)-K45-L45-M45-N45 -> 83556.74 | P45: =ROUND(18.75%*O45,2) -> 15666.89 | Q45: =ROUND($O45*R45,2) -> 12533.51 | R45: 0.15 | S45: =ROUND($O45*T45,2) -> 3133.38 | T45: 0.0375 | U45: =IF($F45&"/Día"=W$9,SUM($G45:$H45),"") -> 1460 | V45: =IF(U45<>"",$O45,"") -> 83556.74 | W45: =IF($F45&"/Día"=W$9,ROUND(U45/$W$1,1),"") -> 47.1 | X45: =IF(U45=0,0,IF($F45&"/Día"=W$9,ROUND(V45/U45,4),"")) -> 57.2306 | Y45: =IF(U45=0,0,IF($F45&"/Día"=W$9,ROUND(Z45/U45,4),"")) -> 10.7307 | Z45: =IF(U45<>"",$P45,"") -> 15666.89 | AA45: =IF($F45&"/Día"=AC$9,SUM($G45:$H45),"") | AB45: =IF(AA45<>"",$O45,"") | AC45: =IF($F45&"/Día"=AC$9,ROUND(AA45/$W$1,1),"") | AD45: =IF(AA45=0,0,IF($F45&"/Día"=AC$9,ROUND(AB45/AA45,4),"")) | AE45: =IF(AA45=0,0,IF($F45&"/Día"=AC$9,ROUND(AF45/AA45,4),"")) | AF45: =IF(AA45<>"",$P45,"")
A46: - | B46: 192 | C46: Servicios | D46: Mes | E46: F1 | F46: Bls | G46: 56090 | H46: =253581 -> 253581 | I46: =62.879+0.55 -> 63.429 | J46: 50.7749 | M46: 488728.87 | N46: 10608.43 | O46: =ROUND(G46*I46,2)+ROUND(H46*J46,2)-K46-L46-M46-N46 -> 15933945 | P46: =ROUND(18.75%*O46,2) -> 2987614.7 | Q46: =ROUND($O46*R46,2) -> 2390091.8 | R46: 0.15 | S46: =ROUND($O46*T46,2) -> 597522.95 | T46: 0.0375 | U46: =IF($F46&"/Día"=W$9,SUM($G46:$H46),"") -> 309671 | V46: =IF(U46<>"",$O46,"") -> 15933945 | W46: =IF($F46&"/Día"=W$9,ROUND(U46/$W$1,1),"") -> 9989.4 | X46: =IF(U46=0,0,IF($F46&"/Día"=W$9,ROUND(V46/U46,4),"")) -> 51.4544 | Y46: =IF(U46=0,0,IF($F46&"/Día"=W$9,ROUND(Z46/U46,4),"")) -> 9.6477 | Z46: =IF(U46<>"",$P46,"") -> 2987614.7 | AA46: =IF($F46&"/Día"=AC$9,SUM($G46:$H46),"") | AB46: =IF(AA46<>"",$O46,"") | AC46: =IF($F46&"/Día"=AC$9,ROUND(AA46/$W$1,1),"") | AD46: =IF(AA46=0,0,IF($F46&"/Día"=AC$9,ROUND(AB46/AA46,4),"")) | AE46: =IF(AA46=0,0,IF($F46&"/Día"=AC$9,ROUND(AF46/AA46,4),"")) | AF46: =IF(AA46<>"",$P46,"")
A47: - | B47: 8 | C47: Licencia | D47: Quincena | E47: F2 | F47: Bls | G47: 83109 | H47: 105805 | I47: 50.7307 | J47: 52.1566 | N47: 12654.24 | O47: =ROUND(G47*I47,2)+ROUND(H47*J47,2)-K47-L47-M47-N47 -> 9721952.6 | P47: =ROUND(18.75%*O47,2) -> 1822866.1 | Q47: =ROUND($O47*R47,2) -> 1458292.9 | R47: 0.15 | S47: =ROUND($O47*T47,2) -> 364573.22 | T47: 0.0375 | U47: =IF($F47&"/Día"=W$9,SUM($G47:$H47),"") -> 188914 | V47: =IF(U47<>"",$O47,"") -> 9721952.6 | W47: =IF($F47&"/Día"=W$9,ROUND(U47/$W$1,1),"") -> 6094 | X47: =IF(U47=0,0,IF($F47&"/Día"=W$9,ROUND(V47/U47,4),"")) -> 51.4623 | Y47: =IF(U47=0,0,IF($F47&"/Día"=W$9,ROUND(Z47/U47,4),"")) -> 9.6492 | Z47: =IF(U47<>"",$P47,"") -> 1822866.1 | AA47: =IF($F47&"/Día"=AC$9,SUM($G47:$H47),"") | AB47: =IF(AA47<>"",$O47,"") | AC47: =IF($F47&"/Día"=AC$9,ROUND(AA47/$W$1,1),"") | AD47: =IF(AA47=0,0,IF($F47&"/Día"=AC$9,ROUND(AB47/AA47,4),"")) | AE47: =IF(AA47=0,0,IF($F47&"/Día"=AC$9,ROUND(AF47/AA47,4),"")) | AF47: =IF(AA47<>"",$P47,"")
A48: - | B48: 31-B | C48: Licencia | D48: Quincena | E48: F2 | F48: Bls | H48: 1293 | J48: 68.2014 | N48: 657.07 | O48: =ROUND(G48*I48,2)+ROUND(H48*J48,2)-K48-L48-M48-N48 -> 87527.34 | P48: =ROUND(18.75%*O48,2) -> 16411.38 | Q48: =ROUND($O48*R48,2) -> 13129.1 | R48: 0.15 | S48: =ROUND($O48*T48,2) -> 3282.28 | T48: 0.0375 | U48: =IF($F48&"/Día"=W$9,SUM($G48:$H48),"") -> 1293 | V48: =IF(U48<>"",$O48,"") -> 87527.34 | W48: =IF($F48&"/Día"=W$9,ROUND(U48/$W$1,1),"") -> 41.7 | X48: =IF(U48=0,0,IF($F48&"/Día"=W$9,ROUND(V48/U48,4),"")) -> 67.6932 | Y48: =IF(U48=0,0,IF($F48&"/Día"=W$9,ROUND(Z48/U48,4),"")) -> 12.6925 | Z48: =IF(U48<>"",$P48,"") -> 16411.38 | AA48: =IF($F48&"/Día"=AC$9,SUM($G48:$H48),"") | AB48: =IF(AA48<>"",$O48,"") | AC48: =IF($F48&"/Día"=AC$9,ROUND(AA48/$W$1,1),"") | AD48: =IF(AA48=0,0,IF($F48&"/Día"=AC$9,ROUND(AB48/AA48,4),"")) | AE48: =IF(AA48=0,0,IF($F48&"/Día"=AC$9,ROUND(AF48/AA48,4),"")) | AF48: =IF(AA48<>"",$P48,"")
A49: - | B49: 31-C GAS | C49: Licencia | D49: Quincena | E49: F2 | F49: MM BTU | G49: 997.6446 | H49: 112703.94 | I49: 3.7465 | J49: 3.7467 | N49: 1184.26 | O49: =ROUND(G49*I49,2)+ROUND(H49*J49,2)-K49-L49-M49-N49 -> 424821.27 | P49: =ROUND(18.75%*O49,2) -> 79653.99 | Q49: =ROUND($O49*R49,2) -> 15930.8 | R49: 0.0375 | S49: =ROUND($O49*T49,2) -> 63723.19 | T49: 0.15 | U49: =IF($F49&"/Día"=W$9,SUM($G49:$H49),"") | V49: =IF(U49<>"",$O49,"") | W49: =IF($F49&"/Día"=W$9,ROUND(U49/$W$1,1),"") | X49: =IF(U49=0,0,IF($F49&"/Día"=W$9,ROUND(V49/U49,4),"")) | Y49: =IF(U49=0,0,IF($F49&"/Día"=W$9,ROUND(Z49/U49,4),"")) | Z49: =IF(U49<>"",$P49,"") | AA49: =IF($F49&"/Día"=AC$9,SUM($G49:$H49),"") -> 113701.58 | AB49: =IF(AA49<>"",$O49,"") -> 424821.27 | AC49: =IF($F49&"/Día"=AC$9,ROUND(AA49/$W$1,1),"") -> 3667.8 | AD49: =IF(AA49=0,0,IF($F49&"/Día"=AC$9,ROUND(AB49/AA49,4),"")) -> 3.7363 | AE49: =IF(AA49=0,0,IF($F49&"/Día"=AC$9,ROUND(AF49/AA49,4),"")) -> 0.7006 | AF49: =IF(AA49<>"",$P49,"") -> 79653.99
A50: - | B50: 31-C LGN (*) | C50: Licencia | D50: Quincena | E50: F3 | F50: Bls | G50: 17616 | H50: 18887 | I50: 57.3734 | J50: 57.3205 | N50: 5359.58 | O50: =ROUND(G50*I50,2)+ROUND(H50*J50,2)-K50-L50-M50-N50 -> 2087942.5 | P50: =ROUND(18.75%*O50,2) -> 391489.22 | Q50: =ROUND($O50*R50,2) -> 78297.84 | R50: 0.0375 | S50: =ROUND($O50*T50,2) -> 313191.38 | T50: 0.15 | U50: =IF($F50&"/Día"=W$9,SUM($G50:$H50),"") -> 36503 | V50: =IF(U50<>"",$O50,"") -> 2087942.5 | W50: =IF($F50&"/Día"=W$9,ROUND(U50/$W$1,1),"") -> 1177.5 | X50: =IF(U50=0,0,IF($F50&"/Día"=W$9,ROUND(V50/U50,4),"")) -> 57.1992 | Y50: =IF(U50=0,0,IF($F50&"/Día"=W$9,ROUND(Z50/U50,4),"")) -> 10.7249 | Z50: =IF(U50<>"",$P50,"") -> 391489.22 | AA50: =IF($F50&"/Día"=AC$9,SUM($G50:$H50),"") | AB50: =IF(AA50<>"",$O50,"") | AC50: =IF($F50&"/Día"=AC$9,ROUND(AA50/$W$1,1),"") | AD50: =IF(AA50=0,0,IF($F50&"/Día"=AC$9,ROUND(AB50/AA50,4),"")) | AE50: =IF(AA50=0,0,IF($F50&"/Día"=AC$9,ROUND(AF50/AA50,4),"")) | AF50: =IF(AA50<>"",$P50,"")
A51: - | B51: 31-C COND | C51: Licencia | D51: Quincena | E51: F2 | F51: Bls | O51: =ROUND(G51*I51,2)+ROUND(H51*J51,2)-K51-L51-M51-N51 -> 0 | P51: =ROUND(18.75%*O51,2) -> 0 | Q51: =ROUND($O51*R51,2) -> 0 | R51: 0.0375 | S51: =ROUND($O51*T51,2) -> 0 | T51: 0.15 | U51: =IF($F51&"/Día"=W$9,SUM($G51:$H51),"") -> 0 | V51: =IF(U51<>"",$O51,"") -> 0 | W51: =IF($F51&"/Día"=W$9,ROUND(U51/$W$1,1),"") -> 0 | X51: =IF(U51=0,0,IF($F51&"/Día"=W$9,ROUND(V51/U51,4),"")) -> 0 | Y51: =IF(U51=0,0,IF($F51&"/Día"=W$9,ROUND(Z51/U51,4),"")) -> 0 | Z51: =IF(U51<>"",$P51,"") -> 0 | AA51: =IF($F51&"/Día"=AC$9,SUM($G51:$H51),"") | AB51: =IF(AA51<>"",$O51,"") | AC51: =IF($F51&"/Día"=AC$9,ROUND(AA51/$W$1,1),"") | AD51: =IF(AA51=0,0,IF($F51&"/Día"=AC$9,ROUND(AB51/AA51,4),"")) | AE51: =IF(AA51=0,0,IF($F51&"/Día"=AC$9,ROUND(AF51/AA51,4),"")) | AF51: =IF(AA51<>"",$P51,"")
A52: - | B52: 102 | C52: Licencia | D52: Quincena | E52: F2 | F52: Bls | O52: =ROUND(G52*I52,2)+ROUND(H52*J52,2)-K52-L52-M52-N52 -> 0 | P52: =ROUND(18.75%*O52,2) -> 0 | Q52: =P52-S52 -> 0 | R52: 0.15 | S52: =ROUND($O52*T52,2) -> 0 | T52: 0.0375 | U52: =IF($F52&"/Día"=W$9,SUM($G52:$H52),"") -> 0 | V52: =IF(U52<>"",$O52,"") -> 0 | W52: =IF($F52&"/Día"=W$9,ROUND(U52/$W$1,1),"") -> 0 | X52: =IF(U52=0,0,IF($F52&"/Día"=W$9,ROUND(V52/U52,4),"")) -> 0 | Y52: =IF(U52=0,0,IF($F52&"/Día"=W$9,ROUND(Z52/U52,4),"")) -> 0 | Z52: =IF(U52<>"",$P52,"") -> 0 | AA52: =IF($F52&"/Día"=AC$9,SUM($G52:$H52),"") | AB52: =IF(AA52<>"",$O52,"") | AC52: =IF($F52&"/Día"=AC$9,ROUND(AA52/$W$1,1),"") | AD52: =IF(AA52=0,0,IF($F52&"/Día"=AC$9,ROUND(AB52/AA52,4),"")) | AE52: =IF(AA52=0,0,IF($F52&"/Día"=AC$9,ROUND(AF52/AA52,4),"")) | AF52: =IF(AA52<>"",$P52,"")
A53: - | B53: 95 | C53: Licencia | D53: Quincena | E53: F2 | F53: Bls | O53: =ROUND(G53*I53,2)+ROUND(H53*J53,2)-K53-L53-M53-N53 -> 0 | P53: =ROUND(18.75%*O53,2) -> 0 | Q53: =P53-S53 -> 0 | R53: 0.15 | S53: =ROUND($O53*T53,2) -> 0 | T53: 0.0375 | U53: =IF($F53&"/Día"=W$9,SUM($G53:$H53),"") -> 0 | V53: =IF(U53<>"",$O53,"") -> 0 | W53: =IF($F53&"/Día"=W$9,ROUND(U53/$W$1,1),"") -> 0 | X53: =IF(U53=0,0,IF($F53&"/Día"=W$9,ROUND(V53/U53,4),"")) -> 0 | Y53: =IF(U53=0,0,IF($F53&"/Día"=W$9,ROUND(Z53/U53,4),"")) -> 0 | Z53: =IF(U53<>"",$P53,"") -> 0 | AA53: =IF($F53&"/Día"=AC$9,SUM($G53:$H53),"") | AB53: =IF(AA53<>"",$O53,"") | AC53: =IF($F53&"/Día"=AC$9,ROUND(AA53/$W$1,1),"") | AD53: =IF(AA53=0,0,IF($F53&"/Día"=AC$9,ROUND(AB53/AA53,4),"")) | AE53: =IF(AA53=0,0,IF($F53&"/Día"=AC$9,ROUND(AF53/AA53,4),"")) | AF53: =IF(AA53<>"",$P53,"")
A54: - | B54: 67 | C54: Licencia | D54: Quincena | E54: F2 | F54: Bls | O54: =ROUND(G54*I54,2)+ROUND(H54*J54,2)-K54-L54-M54-N54 -> 0 | P54: =ROUND(18.75%*O54,2) -> 0 | Q54: =P54-S54 -> 0 | R54: 0.15 | S54: =ROUND($O54*T54,2) -> 0 | T54: 0.0375 | U54: =IF($F54&"/Día"=W$9,SUM($G54:$H54),"") -> 0 | V54: =IF(U54<>"",$O54,"") -> 0 | W54: =IF($F54&"/Día"=W$9,ROUND(U54/$W$1,1),"") -> 0 | X54: =IF(U54=0,0,IF($F54&"/Día"=W$9,ROUND(V54/U54,4),"")) -> 0 | Y54: =IF(U54=0,0,IF($F54&"/Día"=W$9,ROUND(Z54/U54,4),"")) -> 0 | Z54: =IF(U54<>"",$P54,"") -> 0 | AA54: =IF($F54&"/Día"=AC$9,SUM($G54:$H54),"") | AB54: =IF(AA54<>"",$O54,"") | AC54: =IF($F54&"/Día"=AC$9,ROUND(AA54/$W$1,1),"") | AD54: =IF(AA54=0,0,IF($F54&"/Día"=AC$9,ROUND(AB54/AA54,4),"")) | AE54: =IF(AA54=0,0,IF($F54&"/Día"=AC$9,ROUND(AF54/AA54,4),"")) | AF54: =IF(AA54<>"",$P54,"")
A55: - | B55: Ajustes meses anteriores (3) | O55: =+O152 -> 1253.64 | P55: =ROUND(18.75%*O55,2) -> 235.06 | Q55: =+Q152 -> 188.05 | S55: =+S152 -> 47.01 | U55: =IF($F55&"/Día"=W$9,SUM($G55:$H55),"") | V55: =IF(U55<>"",$O55,"") | W55: =IF($F55&"/Día"=W$9,ROUND(U55/$W$1,1),"") | X55: =IF(U55=0,0,IF($F55&"/Día"=W$9,ROUND(V55/U55,4),"")) | Y55: =IF(U55=0,0,IF($F55&"/Día"=W$9,ROUND(Z55/U55,4),"")) | Z55: =IF(U55<>"",$P55,"") | AA55: =IF($F55&"/Día"=AC$9,SUM($G55:$H55),"") | AB55: =IF(AA55<>"",$O55,"") | AC55: =IF($F55&"/Día"=AC$9,ROUND(AA55/$W$1,1),"") | AD55: =IF(AA55=0,0,IF($F55&"/Día"=AC$9,ROUND(AB55/AA55,4),"")) | AE55: =IF(AA55=0,0,IF($F55&"/Día"=AC$9,ROUND(AF55/AA55,4),"")) | AF55: =IF(AA55<>"",$P55,"")
B56: Subtotal | C56: =TEXT(A$44,)&" US$" -> Loreto / Ucayali US$ | O56: =SUM(O45:O55) -> 28340999 | P56: =SUM(P45:P55) -> 5313937.4 | Q56: =SUM(Q45:Q55) -> 3968464 | S56: =SUM(S45:S55) -> 1345473.4 | U56: =SUM(U45:U55) -> 537841 | V56: =SUM(V45:V55) -> 27914924 | W56: =SUM(W45:W55) -> 17349.7 | X56: =ROUND(V56/U56,4) -> 51.9018 | Y56: =ROUND(Z56/U56,4) -> 9.7316 | Z56: =SUM(Z45:Z55) -> 5234048.3 | AA56: =SUM(AA45:AA55) -> 113701.58 | AB56: =SUM(AB45:AB55) -> 424821.27 | AC56: =SUM(AC45:AC55) -> 3667.8 | AD56: =ROUND(AB56/AA56,4) -> 3.7363 | AE56: =ROUND(AF56/AA56,4) -> 0.7006 | AF56: =SUM(AF45:AF55) -> 79653.99 | AG56: =P56-Z56-AF56 -> 235.06
C57: =TEXT(A$44,)&" S/." -> Loreto / Ucayali S/. | P57: =ROUND($F$1*P56,2) -> 0 | Q57: =ROUND($F$1*Q56,2) -> 0 | S57: =ROUND($F$1*S56,2) -> 0
A58: Cusco | P58: V. Regalías | Q58: Cusco
A59: - | B59: 88 LGN | C59: Licencia | D59: Quincena | E59: F4 | F59: Bls | G59: 755338 | H59: 820304 | I59: 43.1163 | J59: 42.2687 | O59: =G59*I59+H59*J59 -> 67240563 | P59: =ROUND(37.24%*(G59*I59+H59*J59),2) -> 25040386 | Q59: =ROUND(R59*P59,2) -> 12520193 | R59: 0.5 | U59: =IF($F59&"/Día"=W$9,SUM($G59:$H59),"") -> 1575642 | V59: =IF(U59<>"",$O59,"") -> 67240563 | W59: =IF($F59&"/Día"=W$9,ROUND(U59/$W$1,1),"") -> 50827.2 | X59: =IF(U59=0,0,IF($F59&"/Día"=W$9,ROUND(V59/U59,4),"")) -> 42.675 | Y59: =IF(U59=0,0,IF($F59&"/Día"=W$9,ROUND(Z59/U59,4),"")) -> 7.9461 | Z59: =IF(U59<>"",$Q59,"") -> 12520193 | AA59: =IF($F59&"/Día"=AC$9,SUM($G59:$H59),"") | AB59: =IF(AA59<>"",$O59,"") | AC59: =IF($F59&"/Día"=AC$9,ROUND(AA59/$W$1,1),"") | AD59: =IF(AA59=0,0,IF($F59&"/Día"=AC$9,ROUND(AB59/AA59,4),"")) | AE59: =IF(AA59=0,0,IF($F59&"/Día"=AC$9,ROUND(AF59/AA59,4),"")) | AF59: =IF(AA59<>"",$Q59,"")
A60: - | B60: 88 GAS | C60: Licencia | D60: Quincena | E60: F4 | F60: MM BTU | G60: 7816183.7 | H60: 8555912.2 | I60: 1.9641 | J60: 1.9641 | O60: =G60*I60+H60*J60 -> 32156434 | P60: =ROUND(37.24%*(G60*I60+H60*J60),2) -> 11975056 | Q60: =ROUND(R60*P60,2) -> 5987527.9 | R60: 0.5 | U60: =IF($F60&"/Día"=W$9,SUM($G60:$H60),"") | V60: =IF(U60<>"",$O60,"") | W60: =IF($F60&"/Día"=W$9,ROUND(U60/$W$1,1),"") | X60: =IF(U60=0,0,IF($F60&"/Día"=W$9,ROUND(V60/U60,4),"")) | Y60: =IF(U60=0,0,IF($F60&"/Día"=W$9,ROUND(Z60/U60,4),"")) | Z60: =IF(U60<>"",$Q60,"") | AA60: =IF($F60&"/Día"=AC$9,SUM($G60:$H60),"") -> 16372096 | AB60: =IF(AA60<>"",$O60,"") -> 32156434 | AC60: =IF($F60&"/Día"=AC$9,ROUND(AA60/$W$1,1),"") -> 528132.1 | AD60: =IF(AA60=0,0,IF($F60&"/Día"=AC$9,ROUND(AB60/AA60,4),"")) -> 1.9641 | AE60: =IF(AA60=0,0,IF($F60&"/Día"=AC$9,ROUND(AF60/AA60,4),"")) -> 0.3657 | AF60: =IF(AA60<>"",$Q60,"") -> 5987527.9
A61: - | B61: 88 GAS -Mlocal | C61: Licencia | D61: Quincena | E61: F4 | F61: MM BTU | G61: 21481.44 | H61: 31441.16 | I61: 2.7628 | J61: 2.7628 | O61: =G61*I61+H61*J61 -> 146214.56 | P61: =ROUND(37.24%*O61,2) -> 54450.3 | Q61: =ROUND(R61*P61,2) -> 27225.15 | R61: 0.5 | U61: =IF($F61&"/Día"=W$9,SUM($G61:$H61),"") | V61: =IF(U61<>"",$O61,"") | W61: =IF($F61&"/Día"=W$9,ROUND(U61/$W$1,1),"") | X61: =IF(U61=0,0,IF($F61&"/Día"=W$9,ROUND(V61/U61,4),"")) | Y61: =IF(U61=0,0,IF($F61&"/Día"=W$9,ROUND(Z61/U61,4),"")) | Z61: =IF(U61<>"",$Q61,"") | AA61: =IF($F61&"/Día"=AC$9,SUM($G61:$H61),"") -> 52922.6 | AB61: =IF(AA61<>"",$O61,"") -> 146214.56 | AC61: =IF($F61&"/Día"=AC$9,ROUND(AA61/$W$1,1),"") -> 1707.2 | AD61: =IF(AA61=0,0,IF($F61&"/Día"=AC$9,ROUND(AB61/AA61,4),"")) -> 2.7628 | AE61: =IF(AA61=0,0,IF($F61&"/Día"=AC$9,ROUND(AF61/AA61,4),"")) -> 0.5144 | AF61: =IF(AA61<>"",$Q61,"") -> 27225.15
A62: - | B62: 88 GAS -PM | C62: Licencia | D62: Quincena | E62: F4 | F62: MM BTU | G62: 736346.49 | H62: 923857.55 | I62: 1.798 | J62: 3.309 | O62: =G62*I62+H62*J62 -> 4380995.6 | P62: =ROUND(38%*G62*I62,2)+ROUND(38%*H62*J62,2) -> 1664778.3 | Q62: =ROUND(R62*P62,2) -> 832389.17 | R62: 0.5 | U62: =IF($F62&"/Día"=W$9,SUM($G62:$H62),"") | V62: =IF(U62<>"",$O62,"") | W62: =IF($F62&"/Día"=W$9,ROUND(U62/$W$1,1),"") | X62: =IF(U62=0,0,IF($F62&"/Día"=W$9,ROUND(V62/U62,4),"")) | Y62: =IF(U62=0,0,IF($F62&"/Día"=W$9,ROUND(Z62/U62,4),"")) | Z62: =IF(U62<>"",$Q62,"") | AA62: =IF($F62&"/Día"=AC$9,SUM($G62:$H62),"") -> 1660204 | AB62: =IF(AA62<>"",$O62,"") -> 4380995.6 | AC62: =IF($F62&"/Día"=AC$9,ROUND(AA62/$W$1,1),"") -> 53555 | AD62: =IF(AA62=0,0,IF($F62&"/Día"=AC$9,ROUND(AB62/AA62,4),"")) -> 2.6388 | AE62: =IF(AA62=0,0,IF($F62&"/Día"=AC$9,ROUND(AF62/AA62,4),"")) -> 0.5014 | AF62: =IF(AA62<>"",$Q62,"") -> 832389.17
A63: - | B63: 56 LGN | C63: Licencia | D63: Quincena | E63: F4 | F63: Bls | G63: 304982 | H63: 452645 | I63: 43.0691 | J63: 42.269 | O63: =G63*I63+H63*J63 -> 32268152 | P63: =ROUND(40%*G63*I63,2)+ROUND(40%*H63*J63,2) -> 12907261 | Q63: =ROUND(R63*P63,2) -> 6453630.3 | R63: 0.5 | U63: =IF($F63&"/Día"=W$9,SUM($G63:$H63),"") -> 757627 | V63: =IF(U63<>"",$O63,"") -> 32268152 | W63: =IF($F63&"/Día"=W$9,ROUND(U63/$W$1,1),"") -> 24439.6 | X63: =IF(U63=0,0,IF($F63&"/Día"=W$9,ROUND(V63/U63,4),"")) -> 42.5911 | Y63: =IF(U63=0,0,IF($F63&"/Día"=W$9,ROUND(Z63/U63,4),"")) -> 8.5182 | Z63: =IF(U63<>"",$Q63,"") -> 6453630.3 | AA63: =IF($F63&"/Día"=AC$9,SUM($G63:$H63),"") | AB63: =IF(AA63<>"",$O63,"") | AC63: =IF($F63&"/Día"=AC$9,ROUND(AA63/$W$1,1),"") | AD63: =IF(AA63=0,0,IF($F63&"/Día"=AC$9,ROUND(AB63/AA63,4),"")) | AE63: =IF(AA63=0,0,IF($F63&"/Día"=AC$9,ROUND(AF63/AA63,4),"")) | AF63: =IF(AA63<>"",$Q63,"")
A64: - | B64: 56 GAS | C64: Licencia | D64: Quincena | E64: F4 | F64: MM BTU | G64: 4773948.5 | H64: 6910967.5 | I64: 1.798 | J64: 3.309 | O64: =G64*I64+H64*J64 -> 31451951 | P64: =ROUND(38%*G64*I64,2)+ROUND(38%*H64*J64,2) -> 11951741 | Q64: =ROUND(R64*P64,2) -> 5975870.7 | R64: 0.5 | U64: =IF($F64&"/Día"=W$9,SUM($G64:$H64),"") | V64: =IF(U64<>"",$O64,"") | W64: =IF($F64&"/Día"=W$9,ROUND(U64/$W$1,1),"") | X64: =IF(U64=0,0,IF($F64&"/Día"=W$9,ROUND(V64/U64,4),"")) | Y64: =IF(U64=0,0,IF($F64&"/Día"=W$9,ROUND(Z64/U64,4),"")) | Z64: =IF(U64<>"",$Q64,"") | AA64: =IF($F64&"/Día"=AC$9,SUM($G64:$H64),"") -> 11684916 | AB64: =IF(AA64<>"",$O64,"") -> 31451951 | AC64: =IF($F64&"/Día"=AC$9,ROUND(AA64/$W$1,1),"") -> 376932.8 | AD64: =IF(AA64=0,0,IF($F64&"/Día"=AC$9,ROUND(AB64/AA64,4),"")) -> 2.6917 | AE64: =IF(AA64=0,0,IF($F64&"/Día"=AC$9,ROUND(AF64/AA64,4),"")) -> 0.5114 | AF64: =IF(AA64<>"",$Q64,"") -> 5975870.7
A65: - | B65: 56 GAS-Mlocal | C65: Licencia | D65: Quincena | E65: F4 | F65: MM BTU | G65: 191112.54 | H65: 282162.15 | I65: 1.8266 | J65: 1.8266 | O65: =G65*I65+H65*J65 -> 864483.55 | P65: =ROUND(37.24%*(G65*I65+H65*J65),2) -> 321933.67 | Q65: =ROUND(R65*P65,2) -> 160966.84 | R65: 0.5 | U65: =IF($F65&"/Día"=W$9,SUM($G65:$H65),"") | V65: =IF(U65<>"",$O65,"") | W65: =IF($F65&"/Día"=W$9,ROUND(U65/$W$1,1),"") | X65: =IF(U65=0,0,IF($F65&"/Día"=W$9,ROUND(V65/U65,4),"")) | Y65: =IF(U65=0,0,IF($F65&"/Día"=W$9,ROUND(Z65/U65,4),"")) | Z65: =IF(U65<>"",$Q65,"") | AA65: =IF($F65&"/Día"=AC$9,SUM($G65:$H65),"") -> 473274.69 | AB65: =IF(AA65<>"",$O65,"") -> 864483.55 | AC65: =IF($F65&"/Día"=AC$9,ROUND(AA65/$W$1,1),"") -> 15266.9 | AD65: =IF(AA65=0,0,IF($F65&"/Día"=AC$9,ROUND(AB65/AA65,4),"")) -> 1.8266 | AE65: =IF(AA65=0,0,IF($F65&"/Día"=AC$9,ROUND(AF65/AA65,4),"")) -> 0.3401 | AF65: =IF(AA65<>"",$Q65,"") -> 160966.84
A66: - | B66: 57 LGN | C66: Licencia | D66: Quincena | E66: F4 | F66: Bls | G66: 152939 | H66: 223448 | I66: 38.9845 | J66: 38.1868 | O66: =G66*I66+H66*J66 -> 14495015 | P66: =ROUND(G66*I66,2)*6.22%+ROUND(H66*J66,2)*6.42% -> 918655.43 | Q66: =ROUND(R66*P66,2) -> 459327.72 | R66: 0.5 | U66: =IF($F66&"/Día"=W$9,SUM($G66:$H66),"") -> 376387 | V66: =IF(U66<>"",$O66,"") -> 14495015 | W66: =IF($F66&"/Día"=W$9,ROUND(U66/$W$1,1),"") -> 12141.5 | X66: =IF(U66=0,0,IF($F66&"/Día"=W$9,ROUND(V66/U66,4),"")) -> 38.5109 | Y66: =IF(U66=0,0,IF($F66&"/Día"=W$9,ROUND(Z66/U66,4),"")) -> 1.2204 | Z66: =IF(U66<>"",$Q66,"") -> 459327.72 | AA66: =IF($F66&"/Día"=AC$9,SUM($G66:$H66),"") | AB66: =IF(AA66<>"",$O66,"") | AC66: =IF($F66&"/Día"=AC$9,ROUND(AA66/$W$1,1),"") | AD66: =IF(AA66=0,0,IF($F66&"/Día"=AC$9,ROUND(AB66/AA66,4),"")) | AE66: =IF(AA66=0,0,IF($F66&"/Día"=AC$9,ROUND(AF66/AA66,4),"")) | AF66: =IF(AA66<>"",$Q66,"")
A67: - | B67: 57 GAS | C67: Licencia | D67: Quincena | E67: F4 | F67: MM BTU | G67: 2377392.5 | H67: 3455909.8 | I67: 3.118 | J67: 3.118 | O67: =G67*I67+H67*J67 -> 18188237 | P67: =ROUND(G67*I67,2)*9.42%+ROUND(H67*J67,2)*9.89% -> 1763976.9 | Q67: =ROUND(R67*P67,2) -> 881988.44 | R67: 0.5 | U67: =IF($F67&"/Día"=W$9,SUM($G67:$H67),"") | V67: =IF(U67<>"",$O67,"") | W67: =IF($F67&"/Día"=W$9,ROUND(U67/$W$1,1),"") | X67: =IF(U67=0,0,IF($F67&"/Día"=W$9,ROUND(V67/U67,4),"")) | Y67: =IF(U67=0,0,IF($F67&"/Día"=W$9,ROUND(Z67/U67,4),"")) | Z67: =IF(U67<>"",$Q67,"") | AA67: =IF($F67&"/Día"=AC$9,SUM($G67:$H67),"") -> 5833302.4 | AB67: =IF(AA67<>"",$O67,"") -> 18188237 | AC67: =IF($F67&"/Día"=AC$9,ROUND(AA67/$W$1,1),"") -> 188171 | AD67: =IF(AA67=0,0,IF($F67&"/Día"=AC$9,ROUND(AB67/AA67,4),"")) -> 3.118 | AE67: =IF(AA67=0,0,IF($F67&"/Día"=AC$9,ROUND(AF67/AA67,4),"")) -> 0.1512 | AF67: =IF(AA67<>"",$Q67,"") -> 881988.44
A68: - | B68: Ajustes meses anteriores (4) | O68: =+O159 -> 7563365.7 | P68: =+P159 -> 990126.66 | Q68: =+Q159 -> 495063.34 | U68: =IF($F68&"/Día"=W$9,SUM($G68:$H68),"") | V68: =IF(U68<>"",$O68,"") | W68: =IF($F68&"/Día"=W$9,ROUND(U68/$W$1,1),"") | X68: =IF(U68=0,0,IF($F68&"/Día"=W$9,ROUND(V68/U68,4),"")) | Y68: =IF(U68=0,0,IF($F68&"/Día"=W$9,ROUND(Z68/U68,4),"")) | Z68: =IF(U68<>"",$Q68,"") | AA68: =IF($F68&"/Día"=AC$9,SUM($G68:$H68),"") | AB68: =IF(AA68<>"",$O68,"") | AC68: =IF($F68&"/Día"=AC$9,ROUND(AA68/$W$1,1),"") | AD68: =IF(AA68=0,0,IF($F68&"/Día"=AC$9,ROUND(AB68/AA68,4),"")) | AE68: =IF(AA68=0,0,IF($F68&"/Día"=AC$9,ROUND(AF68/AA68,4),"")) | AF68: =IF(AA68<>"",$Q68,"")
B69: Subtotal | C69: =TEXT(A$58,)&" US$" -> Cusco US$ | G69: =SUM(G64:G65) -> 4965061 | H69: =SUM(H64:H65) -> 7193129.7 | O69: =SUM(O59:O68) -> 2.0875541e+08 | P69: =SUM(P59:P68) -> 67588365 | Q69: =SUM(Q59:Q68) -> 33794183 | U69: =SUM(U59:U68) -> 2709656 | V69: =SUM(V59:V68) -> 1.1400373e+08 | W69: =SUM(W59:W68) -> 87408.3 | X69: =ROUND(V69/U69,4) -> 42.0731 | Y69: =ROUND(Z69/U69,4) -> 7.1718 | Z69: =SUM(Z59:Z68) -> 19433151 | AA69: =SUM(AA59:AA68) -> 36076716 | AB69: =SUM(AB59:AB68) -> 87188315 | AC69: =SUM(AC59:AC68) -> 1163765 | AD69: =ROUND(AB69/AA69,4) -> 2.4167 | AE69: =ROUND(AF69/AA69,4) -> 0.3843 | AF69: =SUM(AF59:AF68) -> 13865968 | AG69: =Q69-Z69-AF69 -> 495063.34
C70: =TEXT(A$58,)&" S/." -> Cusco S/. | G70: =SUMPRODUCT(I64:I65,G64:G65)/SUM(G64:G65) -> 1.7991009 | H70: =SUMPRODUCT(J64:J65,H64:H65)/SUM(H64:H65) -> 3.2508505 | Q70: =Q69*F1 -> 0
A71: Total General | G71: =G69*G70 -> 8932645.5 | H71: =H69*H70 -> 23383789 | I71: =H71+G71 -> 32316434 | J71: =O64+O65 -> 32316434 | K71: =I71-J71 -> 0 | M71: =SUM(M10:M67) -> 488728.87 | N71: =SUM(N10:N67) -> 79794.42 | O71: =O36+O42+O56+O69 -> 3.1026084e+08 | P71: =Q69+P56+P42+P36 -> 52609212 | Q71: =Q70+P57+P43+P37 -> 0 | U71: =U36+U42+U56+U69 -> 4297392 | V71: =V36+V42+V56+V69 -> 2.1097359e+08 | W71: =W36+W42+W56+W69 -> 138625.8 | X71: =ROUND(V71/U71,4) -> 49.0934 | Y71: =ROUND(Z71/U71,4) -> 8.7024 | Z71: =Z36+Z42+Z56+Z69 -> 37397762 | AA71: =AA36+AA42+AA56+AA69 -> 37730203 | AB71: =AB36+AB42+AB56+AB69 -> 91746222 | AC71: =AC36+AC42+AC56+AC69 -> 1217103.3 | AD71: =ROUND(AB71/AA71,4) -> 2.4316 | AE71: =ROUND(AF71/AA71,4) -> 0.3902 | AF71: =AF36+AF42+AF56+AF69 -> 14720576 | AG71: =P71-Z71-AF71 -> 490874.31
A73: (*) | B73: Determinación de Canasta de los Líquidos de Gas Natural (VLGNF) | H73: = ( VC * %P + (PB - TF - TT) * (1 - %P)) | O73: =114343802.37+0.82-0.01+151152570.31+0.2+0.01+0.01+0.01-152.04-42861.83+7541024.21-488728.87-79794.42+37804126.66+30849.5 -> 3.1026084e+08 | U73: Regalía 1Q | V73: 5444409.8 | W73: =P36 -> 12632139 | X73: Piura / Tumbes
B74: Simbolo | C74: Descripcion | E74: 1ra. Q | F74: 2da. Q | H74: 1ra. Q | O74: =+O73-O71 -> 0.019931436 | U74: Regalía 2Q | V74: =7125040.18-V82 -> 6318288.6 | W74: =P56 -> 5313937.4 | X74: Loreto / Ucayali
B75: VC | C75: Canasta de Petróleo | H75: ="= ("&TEXT(E75,"0.0000")&" * "&TEXT(E78,"0.00%")&" + ("&TEXT(E76,"0.0000")&" - "&TEXT(E77,"0.0000")&" - "&TEXT(E80,"0.0000")&") * (1 - "&TEXT(E78,"0.00%")&"))" -> = (0.0000 * 0.00% + (0.0000 - 0.0000 - 0.0000) * (1 - 0.00%)) | M75: =370851.98/5962250.45 -> 0.0622 | N75: =547803.45/8532764.09 -> 0.064199999 | U75: Servicios | V75: 6998362.8 | W75: =P42 -> 868953.02 | X75: Huanuco
B76: PB | C76: Precio del GLP | H76: =((85.98%*E75+4.4221)*E78+(E76-E77-E80)*(1-E78)) -> 0 | M76: =698277.28/7412709.99 -> 0.0942 | N76: =1065699.61/10775526.87 -> 0.0989 | V76: =SUM(V73:V75) -> 18761061 | W76: =SUM(W73:W75) -> 18815029 | X76: =V76-W76 -> -53967.912 | Y76: 16411.38
B77: TF | C77: Tarifa de Fraccionam. | M77: =5254120.1/13135300.26 -> 0.4 | N77: =7653140.6/19132851.51 -> 0.4 | U77: Lote 56 1Q | V77: 4324077.9 | Y77: 21889.47
B78: %P | C78: % Contenido Pentanos | H78: 2da. Q | M78: =503101.38/1323950.99 -> 0.38 | U78: Lote 88 1Q | V78: 9393842.5 | Y78: 15666.89
B79: QLGNF | C79: Volumen de LGN | H79: ="= ("&TEXT(F75,"0.0000")&" * "&TEXT(F78,"0.00%")&" + ("&TEXT(F76,"0.0000")&" - "&TEXT(F77,"0.0000")&" - "&TEXT(F80,"0.0000")&") * (1 - "&TEXT(F78,"0.00%")&"))" -> = (0.0000 * 0.00% + (0.0000 - 0.0000 - 0.0000) * (1 - 0.00%)) | U79: Lote 57 1Q | V79: 819790.22 | Y79: =SUM(Y76:Y78) -> 53967.74 | Z79: Regalias dejadas de pagar Lote 31-B-31-D-31-E
B80: TT | C80: Tarifa de Transporte | H80: =((85.98%*F75+4.4221)*F78+(F76-F77-F80)*(1-F78)) -> 0 | U80: Lote 56 2Q | V80: 8267531.7 | Y80: volumen x can | Z80: g.f
U81: Lote 88 2Q | V81: 10182189 | Y81: 88184.41 | Z81: -657.06
U82: Lote 57 2Q | V82: 806751.54 | Y82: 147042.22 | Z82: -1112.44
A83: ="AJUSTES PARA "&UPPER(TEXT(E1,"MMMMMMM YYYY")) -> AJUSTES PARA ENERO 2018 | O83: 37804127 | P83: facturas | V83: =SUM(V77:V82) -> 33794183 | W83: =Q69 -> 33794183 | X83: =V83-W83 -> 0.0099999979 | Y83: 84070.45 | Z83: -513.71
Y84: =SUM(Y81:Y83) -> 319297.08 | Z84: =SUM(Z81:Z83) -> -2283.21 | AA84: =+Z84+Y84 -> 317013.87
A85: (4) | B85: Ajuste correspondiente de Julio 2017 (Reporte de Regalía 1ra. Quincena de Enero 2018) - Liq. 1190 | V85: =+V73+V77+V78+V79 -> 19982120
A86: Cusco | D86: Período | E86: Fórmula | F86: Unidades | G86: 1ra. Q | H86: 2da. Q / Mes | I86: 1ra. Q | J86: 2da. Q / Mes | K86: Flete Marítimo | L86: Comercialización | M86: Oleoducto | N86: Fiscalización | O86: Valor Producción | P86: V. Regalías | Q86: Cuzco | V86: =+V74+V80+V81+V82 -> 25574761
A87: - | B87: 56 GAS-Mlocal | C87: Licencia | D87: Calculo Efectuado | F87: MM BTU | G87: 178674.45 | H87: 212775.22 | I87: 1.8094 | J87: 1.8094 | O87: =G87*I87+H87*J87 -> 708289.03 | P87: =ROUND(37.24%*(G87*I87+H87*J87),2) -> 263766.84 | Q87: =ROUND(R87*P87,2) -> 131883.42 | R87: 0.5 | V87: =+V75 -> 6998362.8
A88: - | B88: 56 GAS-Mlocal | C88: Licencia | D88: Modificación | F88: =F87 -> MM BTU | G88: =+G87 -> 178674.45 | H88: =+H87 -> 212775.22 | I88: 1.8102 | J88: 1.8102 | O88: =G88*I88+H88*J88 -> 708602.19 | P88: =ROUND(37.24%*(G88*I88+H88*J88),2) -> 263883.46 | Q88: =ROUND(R88*P88,2) -> 131941.73 | R88: 0.5 | V88: =SUM(V85:V87) -> 52555244 | X88: =+V88-P71 -> -53967.902
B89: Ajuste | G89: =G88-G87 -> 0 | H89: =H88-H87 -> 0 | I89: =I88-I87 -> 0.0008 | J89: =J88-J87 -> 0.0008 | K89: =K88-K87 -> 0 | L89: =L88-L87 -> 0 | M89: =M88-M87 -> 0 | N89: =N88-N87 -> 0 | ... Q89: =Q88-Q87 -> 58.31 | S89: ok
B91: Ajuste correspondiente de Agosto 2017 (Reporte de Regalía 1ra. Quincena de Enero 2018) - Liq. 1190
A92: Cusco | D92: Período | E92: Fórmula | F92: Unidades | G92: 1ra. Q | H92: 2da. Q / Mes | I92: 1ra. Q | J92: 2da. Q / Mes | K92: Flete Marítimo | L92: Comercialización | M92: Oleoducto | N92: Fiscalización | O92: Valor Producción | P92: V. Regalías | Q92: Cuzco
A93: - | B93: 56 GAS-Mlocal | C93: Licencia | D93: Calculo Efectuado | F93: MM BTU | G93: 264856.53 | H93: 282980.91 | I93: 1.8103 | J93: 1.8103 | O93: =G93*I93+H93*J93 -> 991750.12 | P93: =ROUND(37.24%*(G93*I93+H93*J93),2) -> 369327.74 | Q93: =ROUND(R93*P93,2) -> 184663.87 | R93: 0.5
A94: - | B94: =B93 -> 56 GAS-Mlocal | C94: Licencia | D94: Modificación | F94: =F93 -> MM BTU | G94: =+G93 -> 264856.53 | H94: =+H93 -> 282980.91 | I94: 1.8121 | J94: 1.8121 | O94: =G94*I94+H94*J94 -> 992736.23 | P94: =ROUND(37.24%*(G94*I94+H94*J94),2) -> 369694.97 | Q94: =ROUND(R94*P94,2) -> 184847.49 | R94: 0.5
B95: Ajuste | G95: =G94-G93 -> 0 | H95: =H94-H93 -> 0 | I95: =I94-I93 -> 0.0018 | J95: =J94-J93 -> 0.0018 | K95: =K94-K93 -> 0 | L95: =L94-L93 -> 0 | M95: =M94-M93 -> 0 | N95: =N94-N93 -> 0 | ... Q95: =Q94-Q93 -> 183.62 | S95: ok
B97: Ajuste correspondiente de Setiembre 2017 (Reporte de Regalía 1ra. Quincena de Enero 2018) - Liq. 1190
A98: Cusco | D98: Período | E98: Fórmula | F98: Unidades | G98: 1ra. Q | H98: 2da. Q / Mes | I98: 1ra. Q | J98: 2da. Q / Mes | K98: Flete Marítimo | L98: Comercialización | M98: Oleoducto | N98: Fiscalización | O98: Valor Producción | P98: V. Regalías | Q98: Cuzco
A99: - | B99: 56 GAS-Mlocal | C99: Licencia | D99: Calculo Efectuado | F99: MM BTU | G99: 229509.74 | H99: 282759.39 | I99: 1.8121 | J99: 1.8121 | O99: =G99*I99+H99*J99 -> 928282.89 | P99: =ROUND(37.24%*(G99*I99+H99*J99),2) -> 345692.55 | Q99: =ROUND(R99*P99,2) -> 172846.28 | R99: 0.5
A100: - | B100: =B99 -> 56 GAS-Mlocal | C100: Licencia | D100: Modificación | F100: =F99 -> MM BTU | G100: =+G99 -> 229509.74 | H100: =+H99 -> 282759.39 | I100: 1.8149 | J100: 1.8149 | O100: =G100*I100+H100*J100 -> 929717.24 | P100: =ROUND(37.24%*(G100*I100+H100*J100),2) -> 346226.7 | Q100: =ROUND(R100*P100,2) -> 173113.35 | R100: 0.5
B101: Ajuste | G101: =G100-G99 -> 0 | H101: =H100-H99 -> 0 | I101: =I100-I99 -> 0.0028 | J101: =J100-J99 -> 0.0028 | K101: =K100-K99 -> 0 | L101: =L100-L99 -> 0 | M101: =M100-M99 -> 0 | N101: =N100-N99 -> 0 | ... Q101: =Q100-Q99 -> 267.07 | S101: ok
B103: Ajuste correspondiente de Diciembre 2017 (Reporte de Regalía 1ra. Quincena de Enero 2018) - Liq. 1190
A104: Cusco | D104: Período | E104: Fórmula | F104: Unidades | G104: 1ra. Q | H104: 2da. Q / Mes | I104: 1ra. Q | J104: 2da. Q / Mes | K104: Flete Marítimo | L104: Comercialización | M104: Oleoducto | N104: Fiscalización | O104: Valor Producción | P104: V. Regalías | Q104: Cuzco
A105: - | B105: 56 GAS-Mlocal | C105: Licencia | D105: Calculo Efectuado | F105: MM BTU | G105: 275481.21 | H105: 272627.36 | I105: 1.8204 | J105: 1.8204 | O105: =G105*I105+H105*J105 -> 997776.84 | P105: =ROUND(37.24%*(G105*I105+H105*J105),2) -> 371572.1 | Q105: =ROUND(R105*P105,2) -> 185786.05 | R105: 0.5
...

Sheet cuadre
E1: 45597 | S1: , | U1: Días en el mes | W1: =DATE(YEAR(E1),MONTH(E1)+1,1)-DATE(YEAR(E1),MONTH(E1),1) -> 30
A2: PERUPETRO S.A.
A3: DETERMINACION DEL CANON, SOBRECANON y PARTICIPACION (US$)
A4: ="Correspondiente a "&TEXT(E1,"MMMMMMM YYYY") -> Correspondiente a Noviembre 2024
A5: ="Tipo de Cambio= "&TEXT(F1,"0.000") -> Tipo de Cambio= 0.000
A7: Localidad | C7: Modalidad de Contrato | D7: Calculo del Canon | F7: Volumen Producción / Venta | I7: Canasta o Valor Venta (US$/Unidad) | K7: Deducción de Gastos para determinación de valor de producción en Punto de Fiscalización (US$) | O7: Valor de la Producción (US$) | P7: Canon y Sobrecanon / Participación (US$) | U7: RESUMEN POR PETROLERO Y CONDENSADOS | AA7: RESUMEN POR GAS NATURAL | AG7: Control
A8: - Lote | D8: Período | E8: Fórmula | F8: Unidades | G8: 1ra. Q | H8: 2da. Q / Mes | I8: 1ra. Q | J8: 2da. Q / Mes | K8: Flete Marítimo | L8: Comercialización | M8: Oleoducto | N8: Fiscalización | P8: Total | Q8: Localidad 1 | S8: Localidad 2 | U8: Producción / Venta | X8: Valor Prod | Y8: Valor Canon | AA8: Producción / Venta | AD8: Valor Prod | AE8: Valor Canon | AG8: Total
A9: Piura / Tumbes | Q9: Piura | S9: Tumbes | U9: Bls/Mes | V9: V P (US$) | W9: Bls/Día | X9: US$/Bl | Y9: US$/Bl | Z9: US$ | AA9: MM BTU/Mes | AB9: V P (US$) | AC9: MM BTU/Día | AD9: US$/MM BTU | AE9: US$/MM BTU | AF9: US$ | AG9: Canon
A10: - | B10: I | C10: Servicios | D10: Mes | E10: F1 | F10: Bls | G10: 4624 | H10: 9359 | J10: 73.2977 | N10: 93.41 | O10: =ROUND(G10*I10,2)+ROUND(H10*J10,2)-K10-L10-M10-N10 -> 685899.76 | P10: =ROUND(18.75%*O10,2) -> 128606.21 | Q10: =ROUND($O10*R10,2) -> 102884.96 | R10: 0.15 | S10: =ROUND($O10*T10,2) -> 25721.24 | T10: 0.0375 | U10: =IF($F10&"/Día"=W$9,SUM($G10:$H10),"") -> 13983 | V10: =IF(U10<>"",$O10,"") -> 685899.76 | W10: =IF($F10&"/Día"=W$9,ROUND(U10/$W$1,1),"") -> 466.1 | X10: =IF(U10=0,0,IF($F10&"/Día"=W$9,ROUND(V10/U10,4),"")) -> 49.0524 | Y10: =IF(U10=0,0,IF($F10&"/Día"=W$9,ROUND(Z10/U10,4),"")) -> 9.1973 | Z10: =IF(U10<>"",$P10,"") -> 128606.21 | AA10: =IF($F10&"/Día"=AC$9,SUM($G10:$H10),"") | AB10: =IF(AA10<>"",$O10,"") | AC10: =IF($F10&"/Día"=AC$9,ROUND(AA10/$W$1,1),"") | AD10: =IF(AA10=0,0,IF($F10&"/Día"=AC$9,ROUND(AB10/AA10,4),"")) | AE10: =IF(AA10=0,0,IF($F10&"/Día"=AC$9,ROUND(AF10/AA10,4),"")) | AF10: =IF(AA10<>"",$P10,"")
A11: - | B11: I GAS | C11: Servicios | D11: Mes | E11: F1 | F11: MM BTU | G11: 43341.48 | H11: 44253.289 | J11: 3.932 | N11: 264.11 | O11: =ROUND(G11*I11,2)+ROUND(H11*J11,2)-K11-L11-M11-N11 -> 173739.82 | P11: =ROUND(18.75%*O11,2) -> 32576.22 | Q11: =ROUND($O11*R11,2) -> 26060.97 | R11: 0.15 | S11: =ROUND($O11*T11,2) -> 6515.24 | T11: 0.0375 | U11: =IF($F11&"/Día"=W$9,SUM($G11:$H11),"") | V11: =IF(U11<>"",$O11,"") | W11: =IF($F11&"/Día"=W$9,ROUND(U11/$W$1,1),"") | X11: =IF(U11=0,0,IF($F11&"/Día"=W$9,ROUND(V11/U11,4),"")) | Y11: =IF(U11=0,0,IF($F11&"/Día"=W$9,ROUND(Z11/U11,4),"")) | Z11: =IF(U11<>"",$P11,"") | AA11: =IF($F11&"/Día"=AC$9,SUM($G11:$H11),"") -> 87594.769 | AB11: =IF(AA11<>"",$O11,"") -> 173739.82 | AC11: =IF($F11&"/Día"=AC$9,ROUND(AA11/$W$1,1),"") -> 2919.8 | AD11: =IF(AA11=0,0,IF($F11&"/Día"=AC$9,ROUND(AB11/AA11,4),"")) -> 1.9834 | AE11: =IF(AA11=0,0,IF($F11&"/Día"=AC$9,ROUND(AF11/AA11,4),"")) -> 0.3719 | AF11: =IF(AA11<>"",$P11,"") -> 32576.22 | AJ11: =AK11-P11 -> -0.01 | AK11: 32576.21
A12: - | B12: II | C12: Licencia | D12: Quincena | E12: F2 | F12: Bls | G12: 5026 | H12: 5243 | J12: 73.0332 | N12: 756.92 | O12: =ROUND(G12*I12,2)+ROUND(H12*J12,2)-K12-L12-M12-N12 -> 382156.15 | P12: =ROUND(18.75%*O12,2) -> 71654.28 | Q12: =ROUND($O12*R12,2) -> 57323.42 | R12: 0.15 | S12: =ROUND($O12*T12,2) -> 14330.86 | T12: 0.0375 | U12: =IF($F12&"/Día"=W$9,SUM($G12:$I12),"") -> 10269 | V12: =IF(U12<>"",$O12,"") -> 382156.15 | W12: =IF($F12&"/Día"=W$9,ROUND(U12/$W$1,1),"") -> 342.3 | X12: =IF(U12=0,0,IF($F12&"/Día"=W$9,ROUND(V12/U12,4),"")) -> 37.2145 | Y12: =IF(U12=0,0,IF($F12&"/Día"=W$9,ROUND(Z12/U12,4),"")) -> 6.9777 | Z12: =IF(U12<>"",$P12,"") -> 71654.28 | AA12: =IF($F12&"/Día"=AC$9,SUM($G12:$I12),"") | AB12: =IF(AA12<>"",$O12,"") | AC12: =IF($F12&"/Día"=AC$9,ROUND(AA12/$W$1,1),"") | AD12: =IF(AA12=0,0,IF($F12&"/Día"=AC$9,ROUND(AB12/AA12,4),"")) | AE12: =IF(AA12=0,0,IF($F12&"/Día"=AC$9,ROUND(AF12/AA12,4),"")) | AF12: =IF(AA12<>"",$P12,"")
A13: - | B13: II-GAS | C13: Servicios | D13: Mes | E13: F1 | F13: MM BTU | G13: 18137.092 | H13: 9380.4372 | J13: 2.8114 | N13: 808.45 | O13: =ROUND(G13*I13,2)+ROUND(H13*J13,2)-K13-L13-M13-N13 -> 25563.71 | P13: =ROUND(18.75%*O13,2) -> 4793.2 | Q13: =ROUND($O13*R13,2) -> 3834.56 | R13: 0.15 | S13: =ROUND($O13*T13,2) -> 958.64 | T13: 0.0375 | U13: =IF($F13&"/Día"=W$9,SUM($G13:$H13),"") | V13: =IF(U13<>"",$O13,"") | W13: =IF($F13&"/Día"=W$9,ROUND(U13/$W$1,1),"") | X13: =IF(U13=0,0,IF($F13&"/Día"=W$9,ROUND(V13/U13,4),"")) | Y13: =IF(U13=0,0,IF($F13&"/Día"=W$9,ROUND(Z13/U13,4),"")) | Z13: =IF(U13<>"",$P13,"") | AA13: =IF($F13&"/Día"=AC$9,SUM($G13:$H13),"") -> 27517.529 | AB13: =IF(AA13<>"",$O13,"") -> 25563.71 | AC13: =IF($F13&"/Día"=AC$9,ROUND(AA13/$W$1,1),"") -> 917.3 | AD13: =IF(AA13=0,0,IF($F13&"/Día"=AC$9,ROUND(AB13/AA13,4),"")) -> 0.929 | AE13: =IF(AA13=0,0,IF($F13&"/Día"=AC$9,ROUND(AF13/AA13,4),"")) -> 0.1742 | AF13: =IF(AA13<>"",$P13,"") -> 4793.2
A14: - | B14: III | C14: Licencia | D14: Quincena | E14: F2 | F14: Bls | G14: 28111 | H14: 27624 | J14: 73.2977 | N14: 1139.59 | O14: =ROUND(G14*I14,2)+ROUND(H14*J14,2)-K14-L14-M14-N14 -> 2023636.1 | P14: =ROUND(18.75%*O14,2) -> 379431.76 | Q14: =ROUND($O14*R14,2) -> 303545.41 | R14: 0.15 | S14: =ROUND($O14*T14,2) -> 75886.35 | T14: 0.0375 | U14: =IF($F14&"/Día"=W$9,SUM($G14:$H14),"") -> 55735 | V14: =IF(U14<>"",$O14,"") -> 2023636.1 | W14: =IF($F14&"/Día"=W$9,ROUND(U14/$W$1,1),"") -> 1857.8 | X14: =IF(U14=0,0,IF($F14&"/Día"=W$9,ROUND(V14/U14,4),"")) -> 36.3082 | Y14: =IF(U14=0,0,IF($F14&"/Día"=W$9,ROUND(Z14/U14,4),"")) -> 6.8078 | Z14: =IF(U14<>"",$P14,"") -> 379431.76 | AA14: =IF($F14&"/Día"=AC$9,SUM($G14:$H14),"") | AB14: =IF(AA14<>"",$O14,"") | AC14: =IF($F14&"/Día"=AC$9,ROUND(AA14/$W$1,1),"") | AD14: =IF(AA14=0,0,IF($F14&"/Día"=AC$9,ROUND(AB14/AA14,4),"")) | AE14: =IF(AA14=0,0,IF($F14&"/Día"=AC$9,ROUND(AF14/AA14,4),"")) | AF14: =IF(AA14<>"",$P14,"")
A15: - | B15: III-GAS | C15: Servicios | D15: Mes | E15: F1 | F15: MM BTU | G15: 13798.961 | H15: 8492.0515 | J15: 3.2 | O15: =ROUND(G15*I15,2)+ROUND(H15*J15,2)-K15-L15-M15-N15 -> 27174.56 | P15: =ROUND(18.75%*O15,2) -> 5095.23 | Q15: =ROUND($O15*R15,2) -> 4076.18 | R15: 0.15 | S15: =ROUND($O15*T15,2) -> 1019.05 | T15: 0.0375 | U15: =IF($F15&"/Día"=W$9,SUM($G15:$H15),"") | V15: =IF(U15<>"",$O15,"") | W15: =IF($F15&"/Día"=W$9,ROUND(U15/$W$1,1),"") | X15: =IF(U15=0,0,IF($F15&"/Día"=W$9,ROUND(V15/U15,4),"")) | Y15: =IF(U15=0,0,IF($F15&"/Día"=W$9,ROUND(Z15/U15,4),"")) | Z15: =IF(U15<>"",$P15,"") | AA15: =IF($F15&"/Día"=AC$9,SUM($G15:$H15),"") -> 22291.013 | AB15: =IF(AA15<>"",$O15,"") -> 27174.56 | AC15: =IF($F15&"/Día"=AC$9,ROUND(AA15/$W$1,1),"") -> 743 | AD15: =IF(AA15=0,0,IF($F15&"/Día"=AC$9,ROUND(AB15/AA15,4),"")) -> 1.2191 | AE15: =IF(AA15=0,0,IF($F15&"/Día"=AC$9,ROUND(AF15/AA15,4),"")) -> 0.2286 | AF15: =IF(AA15<>"",$P15,"") -> 5095.23
A16: - | B16: IV | C16: Licencia | D16: Quincena | E16: F2 | F16: Bls | G16: 43248 | H16: 43588 | J16: 73.2977 | N16: 1993.13 | O16: =ROUND(G16*I16,2)+ROUND(H16*J16,2)-K16-L16-M16-N16 -> 3192907 | P16: =ROUND(18.75%*O16,2) -> 598670.07 | Q16: =ROUND($O16*R16,2) -> 478936.05 | R16: 0.15 | S16: =ROUND($O16*T16,2) -> 119734.01 | T16: 0.0375 | U16: =IF($F16&"/Día"=W$9,SUM($G16:$H16),"") -> 86836 | V16: =IF(U16<>"",$O16,"") -> 3192907 | W16: =IF($F16&"/Día"=W$9,ROUND(U16/$W$1,1),"") -> 2894.5 | X16: =IF(U16=0,0,IF($F16&"/Día"=W$9,ROUND(V16/U16,4),"")) -> 36.7694 | Y16: =IF(U16=0,0,IF($F16&"/Día"=W$9,ROUND(Z16/U16,4),"")) -> 6.8943 | Z16: =IF(U16<>"",$P16,"") -> 598670.07 | AA16: =IF($F16&"/Día"=AC$9,SUM($G16:$H16),"") | AB16: =IF(AA16<>"",$O16,"") | AC16: =IF($F16&"/Día"=AC$9,ROUND(AA16/$W$1,1),"") | AD16: =IF(AA16=0,0,IF($F16&"/Día"=AC$9,ROUND(AB16/AA16,4),"")) | AE16: =IF(AA16=0,0,IF($F16&"/Día"=AC$9,ROUND(AF16/AA16,4),"")) | AF16: =IF(AA16<>"",$P16,"")
A17: - | B17: IV-GAS | C17: Licencia | D17: Quincena | E17: F2 | F17: Bls | G17: 71572.007 | H17: 44180.073 | J17: 3.1332 | N17: 601.69 | O17: =ROUND(G17*I17,2)+ROUND(H17*J17,2)-K17-L17-M17-N17 -> 137823.32 | P17: =ROUND(18.75%*O17,2) -> 25841.87 | Q17: =ROUND($O17*R17,2) -> 20673.5 | R17: 0.15 | S17: =ROUND($O17*T17,2) -> 5168.37 | T17: 0.0375 | U17: =IF($F17&"/Día"=W$9,SUM($G17:$H17),"") -> 115752.08 | V17: =IF(U17<>"",$O17,"") -> 137823.32 | W17: =IF($F17&"/Día"=W$9,ROUND(U17/$W$1,1),"") -> 3858.4 | X17: =IF(U17=0,0,IF($F17&"/Día"=W$9,ROUND(V17/U17,4),"")) -> 1.1907 | Y17: =IF(U17=0,0,IF($F17&"/Día"=W$9,ROUND(Z17/U17,4),"")) -> 0.2233 | Z17: =IF(U17<>"",$P17,"") -> 25841.87 | AA17: =IF($F17&"/Día"=AC$9,SUM($G17:$H17),"") | AB17: =IF(AA17<>"",$O17,"") | AC17: =IF($F17&"/Día"=AC$9,ROUND(AA17/$W$1,1),"") | AD17: =IF(AA17=0,0,IF($F17&"/Día"=AC$9,ROUND(AB17/AA17,4),"")) | AE17: =IF(AA17=0,0,IF($F17&"/Día"=AC$9,ROUND(AF17/AA17,4),"")) | AF17: =IF(AA17<>"",$P17,"")
A18: - | B18: V | C18: Servicios | D18: Mes | E18: F1 | F18: Bls | G18: 3037 | H18: 5045 | J18: 73.0596 | N18: 492.8 | O18: =ROUND(G18*I18,2)+ROUND(H18*J18,2)-K18-L18-M18-N18 -> 368092.88 | P18: =ROUND(18.75%*O18,2) -> 69017.42 | Q18: =ROUND($O18*R18,2) -> 55213.93 | R18: 0.15 | S18: =ROUND($O18*T18,2) -> 13803.48 | T18: 0.0375 | U18: =IF($F18&"/Día"=W$9,SUM($G18:$H18),"") -> 8082 | V18: =IF(U18<>"",$O18,"") -> 368092.88 | W18: =IF($F18&"/Día"=W$9,ROUND(U18/$W$1,1),"") -> 269.4 | X18: =IF(U18=0,0,IF($F18&"/Día"=W$9,ROUND(V18/U18,4),"")) -> 45.5448 | Y18: =IF(U18=0,0,IF($F18&"/Día"=W$9,ROUND(Z18/U18,4),"")) -> 8.5396 | Z18: =IF(U18<>"",$P18,"") -> 69017.42 | AA18: =IF($F18&"/Día"=AC$9,SUM($G18:$H18),"") | AB18: =IF(AA18<>"",$O18,"") | AC18: =IF($F18&"/Día"=AC$9,ROUND(AA18/$W$1,1),"") | AD18: =IF(AA18=0,0,IF($F18&"/Día"=AC$9,ROUND(AB18/AA18,4),"")) | AE18: =IF(AA18=0,0,IF($F18&"/Día"=AC$9,ROUND(AF18/AA18,4),"")) | AF18: =IF(AA18<>"",$P18,"")
A19: - | B19: VI (T) | C19: Licencia | D19: Quincena | E19: F1 | F19: Bls | G19: 23227 | H19: 25415 | J19: 73.2977 | N19: 592.65 | O19: =ROUND(G19*I19,2)+ROUND(H19*J19,2)-K19-L19-M19-N19 -> 1862268.4 | P19: =ROUND(18.75%*O19,2) -> 349175.33 | Q19: =ROUND($O19*R19,2) -> 279340.26 | R19: 0.15 | S19: =ROUND($O19*T19,2) -> 69835.07 | T19: 0.0375 | U19: =IF($F19&"/Día"=W$9,SUM($G19:$H19),"") -> 48642 | V19: =IF(U19<>"",$O19,"") -> 1862268.4 | W19: =IF($F19&"/Día"=W$9,ROUND(U19/$W$1,1),"") -> 1621.4 | X19: =IF(U19=0,0,IF($F19&"/Día"=W$9,ROUND(V19/U19,4),"")) -> 38.2852 | Y19: =IF(U19=0,0,IF($F19&"/Día"=W$9,ROUND(Z19/U19,4),"")) -> 7.1785 | Z19: =IF(U19<>"",$P19,"") -> 349175.33 | AA19: =IF($F19&"/Día"=AC$9,SUM($G19:$H19),"") | AB19: =IF(AA19<>"",$O19,"") | AC19: =IF($F19&"/Día"=AC$9,ROUND(AA19/$W$1,1),"") | AD19: =IF(AA19=0,0,IF($F19&"/Día"=AC$9,ROUND(AB19/AA19,4),"")) | AE19: =IF(AA19=0,0,IF($F19&"/Día"=AC$9,ROUND(AF19/AA19,4),"")) | AF19: =IF(AA19<>"",$P19,"")
A20: - | B20: VI - GAS | C20: Licencia | D20: Quincena | E20: F1 | F20: MM BTU | G20: 59288.898 | H20: 62901.239 | J20: 3.8211 | N20: 254.45 | O20: =ROUND(G20*I20,2)+ROUND(H20*J20,2)-K20-L20-M20-N20 -> 240097.48 | P20: =ROUND(18.75%*O20,2) -> 45018.28 | Q20: =ROUND($O20*R20,2) -> 36014.62 | R20: 0.15 | S20: =ROUND($O20*T20,2) -> 9003.66 | T20: 0.0375 | U20: =IF($F20&"/Día"=W$9,SUM($G20:$H20),"") | V20: =IF(U20<>"",$O20,"") | W20: =IF($F20&"/Día"=W$9,ROUND(U20/$W$1,1),"") | X20: =IF(U20=0,0,IF($F20&"/Día"=W$9,ROUND(V20/U20,4),"")) | Y20: =IF(U20=0,0,IF($F20&"/Día"=W$9,ROUND(Z20/U20,4),"")) | Z20: =IF(U20<>"",$P20,"") | AA20: =IF($F20&"/Día"=AC$9,SUM($G20:$H20),"") -> 122190.14 | AB20: =IF(AA20<>"",$O20,"") -> 240097.48 | AC20: =IF($F20&"/Día"=AC$9,ROUND(AA20/$W$1,1),"") -> 4073 | AD20: =IF(AA20=0,0,IF($F20&"/Día"=AC$9,ROUND(AB20/AA20,4),"")) -> 1.9649 | AE20: =IF(AA20=0,0,IF($F20&"/Día"=AC$9,ROUND(AF20/AA20,4),"")) -> 0.3684 | AF20: =IF(AA20<>"",$P20,"") -> 45018.28
A21: - | B21: VII (T) | C21: Licencia | D21: Quincena | E21: F1 | F21: Bls | G21: 15639 | H21: 16938 | J21: 73.0596 | N21: 293.11 | O21: =ROUND(G21*I21,2)+ROUND(H21*J21,2)-K21-L21-M21-N21 -> 1237190.4 | P21: =ROUND(18.75%*O21,2) -> 231973.2 | Q21: =ROUND($O21*R21,2) -> 185578.56 | R21: 0.15 | S21: =ROUND($O21*T21,2) -> 46394.64 | T21: 0.0375 | U21: =IF($F21&"/Día"=W$9,SUM($G21:$H21),"") -> 32577 | V21: =IF(U21<>"",$O21,"") -> 1237190.4 | W21: =IF($F21&"/Día"=W$9,ROUND(U21/$W$1,1),"") -> 1085.9 | X21: =IF(U21=0,0,IF($F21&"/Día"=W$9,ROUND(V21/U21,4),"")) -> 37.9774 | Y21: =IF(U21=0,0,IF($F21&"/Día"=W$9,ROUND(Z21/U21,4),"")) -> 7.1208 | Z21: =IF(U21<>"",$P21,"") -> 231973.2 | AA21: =IF($F21&"/Día"=AC$9,SUM($G21:$H21),"") | AB21: =IF(AA21<>"",$O21,"") | AC21: =IF($F21&"/Día"=AC$9,ROUND(AA21/$W$1,1),"") | AD21: =IF(AA21=0,0,IF($F21&"/Día"=AC$9,ROUND(AB21/AA21,4),"")) | AE21: =IF(AA21=0,0,IF($F21&"/Día"=AC$9,ROUND(AF21/AA21,4),"")) | AF21: =IF(AA21<>"",$P21,"")
A22: - | B22: VII/VI | C22: Licencia | D22: Quincena | E22: F2 | F22: Bls | O22: =ROUND(G22*I22,2)+ROUND(H22*J22,2)-K22-L22-M22-N22 -> 0 | P22: =ROUND(18.75%*O22,2) -> 0 | Q22: =ROUND($O22*R22,2) -> 0 | R22: 0.15 | S22: =ROUND($O22*T22,2) -> 0 | T22: 0.0375
A23: - | B23: IX | C23: Licencia | D23: Quincena | E23: F2 | F23: Bls | G23: 1870 | H23: 2633 | J23: 73.2977 | N23: 315.65 | O23: =ROUND(G23*I23,2)+ROUND(H23*J23,2)-K23-L23-M23-N23 -> 192677.19 | P23: =ROUND(18.75%*O23,2) -> 36126.97 | Q23: =ROUND($O23*R23,2) -> 28901.58 | R23: 0.15 | S23: =ROUND($O23*T23,2) -> 7225.39 | T23: 0.0375 | U23: =IF($F23&"/Día"=W$9,SUM($G23:$H23),"") -> 4503 | V23: =IF(U23<>"",$O23,"") -> 192677.19 | W23: =IF($F23&"/Día"=W$9,ROUND(U23/$W$1,1),"") -> 150.1 | X23: =IF(U23=0,0,IF($F23&"/Día"=W$9,ROUND(V23/U23,4),"")) -> 42.7886 | Y23: =IF(U23=0,0,IF($F23&"/Día"=W$9,ROUND(Z23/U23,4),"")) -> 8.0229 | Z23: =IF(U23<>"",$P23,"") -> 36126.97 | AA23: =IF($F23&"/Día"=AC$9,SUM($G23:$H23),"") | AB23: =IF(AA23<>"",$O23,"") | AC23: =IF($F23&"/Día"=AC$9,ROUND(AA23/$W$1,1),"") | AD23: =IF(AA23=0,0,IF($F23&"/Día"=AC$9,ROUND(AB23/AA23,4),"")) | AE23: =IF(AA23=0,0,IF($F23&"/Día"=AC$9,ROUND(AF23/AA23,4),"")) | AF23: =IF(AA23<>"",$P23,"")
A24: - | B24: X | C24: Licencia | D24: Quincena | E24: F2 | F24: Bls | G24: 118972 | H24: 117901 | J24: 74.8523 | N24: 1318.19 | O24: =ROUND(G24*I24,2)+ROUND(H24*J24,2)-K24-L24-M24-N24 -> 8823842.8 | P24: =ROUND(18.75%*O24,2) -> 1654470.5 | Q24: =ROUND($O24*R24,2) -> 1323576.4 | R24: 0.15 | S24: =ROUND($O24*T24,2) -> 330894.11 | T24: 0.0375 | U24: =IF($F24&"/Día"=W$9,SUM($G24:$H24),"") -> 236873 | V24: =IF(U24<>"",$O24,"") -> 8823842.8 | W24: =IF($F24&"/Día"=W$9,ROUND(U24/$W$1,1),"") -> 7895.8 | X24: =IF(U24=0,0,IF($F24&"/Día"=W$9,ROUND(V24/U24,4),"")) -> 37.2514 | Y24: =IF(U24=0,0,IF($F24&"/Día"=W$9,ROUND(Z24/U24,4),"")) -> 6.9846 | Z24: =IF(U24<>"",$P24,"") -> 1654470.5 | AA24: =IF($F24&"/Día"=AC$9,SUM($G24:$H24),"") | AB24: =IF(AA24<>"",$O24,"") | AC24: =IF($F24&"/Día"=AC$9,ROUND(AA24/$W$1,1),"") | AD24: =IF(AA24=0,0,IF($F24&"/Día"=AC$9,ROUND(AB24/AA24,4),"")) | AE24: =IF(AA24=0,0,IF($F24&"/Día"=AC$9,ROUND(AF24/AA24,4),"")) | AF24: =IF(AA24<>"",$P24,"")
A25: - | B25: X-GAS | C25: Licencia | D25: Mes | E25: F2 | F25: MM BTU | G25: 193471.59 | H25: 195754.86 | J25: 2.8097 | N25: 970.33 | O25: =ROUND(G25*I25,2)+ROUND(H25*J25,2)-K25-L25-M25-N25 -> 549042.1 | P25: =ROUND(18.75%*O25,2) -> 102945.39 | Q25: =ROUND($O25*R25,2) -> 82356.32 | R25: 0.15 | S25: =ROUND($O25*T25,2) -> 20589.08 | T25: 0.0375 | U25: =IF($F25&"/Día"=W$9,SUM($G25:$H25),"") | V25: =IF(U25<>"",$O25,"") | W25: =IF($F25&"/Día"=W$9,ROUND(U25/$W$1,1),"") | X25: =IF(U25=0,0,IF($F25&"/Día"=W$9,ROUND(V25/U25,4),"")) | Y25: =IF(U25=0,0,IF($F25&"/Día"=W$9,ROUND(Z25/U25,4),"")) | Z25: =IF(U25<>"",$P25,"") | AA25: =IF($F25&"/Día"=AC$9,SUM($G25:$H25),"") -> 389226.45 | AB25: =IF(AA25<>"",$O25,"") -> 549042.1 | AC25: =IF($F25&"/Día"=AC$9,ROUND(AA25/$W$1,1),"") -> 12974.2 | AD25: =IF(AA25=0,0,IF($F25&"/Día"=AC$9,ROUND(AB25/AA25,4),"")) -> 1.4106 | AE25: =IF(AA25=0,0,IF($F25&"/Día"=AC$9,ROUND(AF25/AA25,4),"")) -> 0.2645 | AF25: =IF(AA25<>"",$P25,"") -> 102945.39
A26: - | B26: XV | C26: Licencia | D26: Quincena | E26: F2 | F26: Bls | G26: 284 | H26: 270 | J26: 73.0596 | N26: 344.64 | O26: =ROUND(G26*I26,2)+ROUND(H26*J26,2)-K26-L26-M26-N26 -> 19381.45 | P26: =ROUND(18.75%*O26,2) -> 3634.02 | Q26: =ROUND($O26*R26,2) -> 2907.22 | R26: 0.15 | S26: =ROUND($O26*T26,2) -> 726.8 | T26: 0.0375 | U26: =IF($F26&"/Día"=W$9,SUM($G26:$H26),"") -> 554 | V26: =IF(U26<>"",$O26,"") -> 19381.45 | W26: =IF($F26&"/Día"=W$9,ROUND(U26/$W$1,1),"") -> 18.5 | X26: =IF(U26=0,0,IF($F26&"/Día"=W$9,ROUND(V26/U26,4),"")) -> 34.9846 | Y26: =IF(U26=0,0,IF($F26&"/Día"=W$9,ROUND(Z26/U26,4),"")) -> 6.5596 | Z26: =IF(U26<>"",$P26,"") -> 3634.02 | AA26: =IF($F26&"/Día"=AC$9,SUM($G26:$H26),"") | AB26: =IF(AA26<>"",$O26,"") | AC26: =IF($F26&"/Día"=AC$9,ROUND(AA26/$W$1,1),"") | AD26: =IF(AA26=0,0,IF($F26&"/Día"=AC$9,ROUND(AB26/AA26,4),"")) | AE26: =IF(AA26=0,0,IF($F26&"/Día"=AC$9,ROUND(AF26/AA26,4),"")) | AF26: =IF(AA26<>"",$P26,"")
A27: - | B27: XIII Crudo | C27: Licencia | D27: Quincena | E27: F2 | F27: Bls | G27: 14931 | H27: 14937 | J27: 73.2377 | N27: 3262.8 | O27: =ROUND(G27*I27,2)+ROUND(H27*J27,2)-K27-L27-M27-N27 -> 1090688.7 | P27: =ROUND(18.75%*O27,2) -> 204504.14 | Q27: =ROUND($O27*R27,2) -> 163603.31 | R27: 0.15 | S27: =ROUND($O27*T27,2) -> 40900.83 | T27: 0.0375 | U27: =IF($F27&"/Día"=W$9,SUM($G27:$H27),"") -> 29868 | V27: =IF(U27<>"",$O27,"") -> 1090688.7 | W27: =IF($F27&"/Día"=W$9,ROUND(U27/$W$1,1),"") -> 995.6 | X27: =IF(U27=0,0,IF($F27&"/Día"=W$9,ROUND(V27/U27,4),"")) -> 36.517 | Y27: =IF(U27=0,0,IF($F27&"/Día"=W$9,ROUND(Z27/U27,4),"")) -> 6.8469 | Z27: =IF(U27<>"",$P27,"") -> 204504.14 | AA27: =IF($F27&"/Día"=AC$9,SUM($G27:$H27),"") | AB27: =IF(AA27<>"",$O27,"") | AC27: =IF($F27&"/Día"=AC$9,ROUND(AA27/$W$1,1),"") | AD27: =IF(AA27=0,0,IF($F27&"/Día"=AC$9,ROUND(AB27/AA27,4),"")) | AE27: =IF(AA27=0,0,IF($F27&"/Día"=AC$9,ROUND(AF27/AA27,4),"")) | AF27: =IF(AA27<>"",$P27,"")
A28: - | B28: XIII Gas | C28: Licencia | D28: Quincena | E28: F2 | F28: MM BTU | G28: =G448 -> 391300.81 | H28: =H459 -> 396292.73 | J28: =J459 -> 3.3340609 | N28: =N438 -> 1356.01 | O28: =O438 -> 2589083.2 | P28: =P438 -> 485453.1 | Q28: =Q438 -> 388362.48 | R28: 0.15 | S28: =S438 -> 97090.61 | T28: 0.0375 | U28: =IF($F28&"/Día"=W$9,SUM($G28:$H28),"") | V28: =IF(U28<>"",$O28,"") | W28: =IF($F28&"/Día"=W$9,ROUND(U28/$W$1,1),"") | X28: =IF(U28=0,0,IF($F28&"/Día"=W$9,ROUND(V28/U28,4),"")) | Y28: =IF(U28=0,0,IF($F28&"/Día"=W$9,ROUND(Z28/U28,4),"")) | Z28: =IF(U28<>"",$P28,"") | AA28: =IF($F28&"/Día"=AC$9,SUM($G28:$H28),"") -> 787593.54 | AB28: =IF(AA28<>"",$O28,"") -> 2589083.2 | AC28: =IF($F28&"/Día"=AC$9,ROUND(AA28/$W$1,1),"") -> 26253.1 | AD28: =IF(AA28=0,0,IF($F28&"/Día"=AC$9,ROUND(AB28/AA28,4),"")) -> 3.2873 | AE28: =IF(AA28=0,0,IF($F28&"/Día"=AC$9,ROUND(AF28/AA28,4),"")) -> 0.6164 | AF28: =IF(AA28<>"",$P28,"") -> 485453.1
A29: - | B29: XX | C29: Licencia | D29: Quincena | E29: F2 | F29: Bls | G29: 161 | H29: 180 | J29: 73.2977 | N29: 202.92 | O29: =ROUND(G29*I29,2)+ROUND(H29*J29,2)-K29-L29-M29-N29 -> 12990.67 | P29: =ROUND(18.75%*O29,2) -> 2435.75 | Q29: =ROUND($O29*R29,2) -> 487.15 | R29: 0.0375 | S29: =ROUND($O29*T29,2) -> 1948.6 | T29: 0.15 | U29: =IF($F29&"/Día"=W$9,SUM($G29:$H29),"") -> 341 | V29: =IF(U29<>"",$O29,"") -> 12990.67 | W29: =IF($F29&"/Día"=W$9,ROUND(U29/$W$1,1),"") -> 11.4 | X29: =IF(U29=0,0,IF($F29&"/Día"=W$9,ROUND(V29/U29,4),"")) -> 38.0958 | Y29: =IF(U29=0,0,IF($F29&"/Día"=W$9,ROUND(Z29/U29,4),"")) -> 7.143 | Z29: =IF(U29<>"",$P29,"") -> 2435.75 | AA29: =IF($F29&"/Día"=AC$9,SUM($G29:$H29),"") | AB29: =IF(AA29<>"",$O29,"") | AC29: =IF($F29&"/Día"=AC$9,ROUND(AA29/$W$1,1),"") | AD29: =IF(AA29=0,0,IF($F29&"/Día"=AC$9,ROUND(AB29/AA29,4),"")) | AE29: =IF(AA29=0,0,IF($F29&"/Día"=AC$9,ROUND(AF29/AA29,4),"")) | AF29: =IF(AA29<>"",$P29,"")
A30: - | B30: Z1 Crudo | C30: Licencia | D30: Quincena | E30: F2 | F30: Bls | G30: 59744 | N30: 1027.48 | O30: =ROUND(G30*I30,2)+ROUND(H30*J30,2)-K30-L30-M30-N30 -> -1027.48 | P30: =ROUND(18.75%*O30,2) -> -192.65 | Q30: =ROUND($O30*R30,2) -> -38.53 | R30: 0.0375 | S30: =ROUND($O30*T30,2) -> -154.12 | T30: 0.15
A31: - | B31: Z-69 Crudo | C31: Licencia | D31: Quincena | E31: F2 | F31: Bls | G31: 50058 | H31: 74952 | J31: 73.369 | N31: 525.01 | O31: =ROUND(G31*I31,2)+ROUND(H31*J31,2)-K31-L31-M31-N31 -> 5498628.3 | P31: =ROUND(18.75%*O31,2) -> 1030992.8 | Q31: =ROUND($O31*R31,2) -> 824794.24 | R31: 0.15 | S31: =ROUND($O31*T31,2) -> 206198.56 | T31: 0.0375
A32: - | B32: Z-69 Gas | C32: Licencia | D32: Quincena | E32: F2 | F32: MM BTU | G32: =G504 -> 146872.7 | H32: =H513 -> 140602.21 | J32: =J513 -> 2.8168665 | N32: 463.82 | O32: =ROUND(G32*I32,2)+ROUND(H32*J32,2)-K32-L32-M32-N32 -> 395593.84 | P32: =ROUND(18.75%*O32,2) -> 74173.85 | Q32: =ROUND($O32*R32,2) -> 59339.08 | R32: 0.15 | S32: =ROUND($O32*T32,2) -> 14834.77 | T32: 0.0375
A33: - | B33: Z-69 Lgn | C33: Licencia | D33: Quincena | E33: F2 | F33: Bls | G33: 9427 | H33: 9336 | J33: 61.4049 | N33: 502.46 | O33: =ROUND(G33*I33,2)+ROUND(H33*J33,2)-K33-L33-M33-N33 -> 572773.69 | P33: =ROUND(18.75%*O33,2) -> 107395.07 | Q33: =ROUND($O33*R33,2) -> 85916.05 | R33: 0.15 | S33: =ROUND($O33*T33,2) -> 21479.01 | T33: 0.0375
A34: - | B34: Ajustes meses anteriores (1) | O34: =O304 -> -2401688 | P34: =P304 -> -450316.52 | Q34: =Q304 -> -360253.19 | S34: =S304 -> -90063.27 | U34: =IF($F34&"/Día"=W$9,SUM($G34:$H34),"") | V34: =IF(U34<>"",$O34,"") | W34: =IF($F34&"/Día"=W$9,ROUND(U34/$W$1,1),"") | X34: =IF(U34=0,0,IF($F34&"/Día"=W$9,ROUND(V34/U34,4),"")) | Y34: =IF(U34=0,0,IF($F34&"/Día"=W$9,ROUND(Z34/U34,4),"")) | Z34: =IF(U34<>"",$P34,"") | AA34: =IF($F34&"/Día"=AC$9,SUM($G34:$H34),"") | AB34: =IF(AA34<>"",$O34,"") | AC34: =IF($F34&"/Día"=AC$9,ROUND(AA34/$W$1,1),"") | AD34: =IF(AA34=0,0,IF($F34&"/Día"=AC$9,ROUND(AB34/AA34,4),"")) | AE34: =IF(AA34=0,0,IF($F34&"/Día"=AC$9,ROUND(AF34/AA34,4),"")) | AF34: =IF(AA34<>"",$P34,"")
B35: Subtotal | C35: =TEXT(A$9,)&" US$" -> Piura / Tumbes US$ | O35: =SUM(O10:O34) -> 27698536 | P35: =SUM(P10:P34) -> 5193475.5 | Q35: =SUM(Q10:Q34) -> 4153434.6 | S35: =SUM(S10:S34) -> 1040041 | T35: 0 | U35: =SUM(U10:U34) -> 644015.08 | V35: =SUM(V10:V34) -> 20029555 | W35: =SUM(W10:W34) -> 21467.2 | X35: =ROUND(V35/U35,4) -> 31.1011 | Y35: =ROUND(Z35/U35,4) -> 5.8314 | Z35: =SUM(Z10:Z34) -> 3755541.5 | AA35: =SUM(AA10:AA34) -> 1436413.4 | AB35: =SUM(AB10:AB34) -> 3604700.8 | AC35: =SUM(AC10:AC34) -> 47880.4 | AD35: =ROUND(AB35/AA35,4) -> 2.5095 | AE35: =ROUND(AF35/AA35,4) -> 0.4705 | AF35: =SUM(AF10:AF34) -> 675881.42 | AG35: =P35-Z35-AF35 -> 762052.55
C36: =TEXT(A$9,)&" S/." -> Piura / Tumbes S/. | P36: =ROUND($F$1*P35,2) -> 0 | Q36: =ROUND($F$1*Q35,2) -> 0 | S36: =ROUND($F$1*S35,2) -> 0
A37: Provincia Puerto Inca Huanuco | Q37: Puerto Inca
A38: - | B38: 131 | C38: Licencia | D38: Quincena | E38: F2 | F38: Bls | G38: 8410 | H38: 9414 | J38: 62.317 | N38: 4055.16 | O38: =ROUND(G38*I38,2)+ROUND(H38*J38,2)-K38-L38-M38-N38 -> 582597.08 | P38: =ROUND(15%*O38,2) -> 87389.56 | Q38: =ROUND($O38*R38,2) -> 87389.56 | R38: 0.15 | U38: =IF($F38&"/Día"=W$9,SUM($G38:$H38),"") -> 17824 | V38: =IF(U38<>"",$O38,"") -> 582597.08 | W38: =IF($F38&"/Día"=W$9,ROUND(U38/$W$1,1),"") -> 594.1 | X38: =IF(U38=0,0,IF($F38&"/Día"=W$9,ROUND(V38/U38,4),"")) -> 32.6861 | Y38: =IF(U38=0,0,IF($F38&"/Día"=W$9,ROUND(Z38/U38,4),"")) -> 4.9029 | Z38: =IF(U38<>"",$P38,"") -> 87389.56 | AA38: =IF($F38&"/Día"=AC$9,SUM($G38:$H38),"") | AB38: =IF(AA38<>"",$O38,"") | AC38: =IF($F38&"/Día"=AC$9,ROUND(AA38/$W$1,1),"") | AD38: =IF(AA38=0,0,IF($F38&"/Día"=AC$9,ROUND(AB38/AA38,4),"")) | AE38: =IF(AA38=0,0,IF($F38&"/Día"=AC$9,ROUND(AF38/AA38,4),"")) | AF38: =IF(AA38<>"",$P38,"")
A39: - | B39: Ajustes meses anteriores (2) | U39: =IF($F39&"/Día"=W$9,SUM($G39:$H39),"") | V39: =IF(U39<>"",$O39,"") | W39: =IF($F39&"/Día"=W$9,ROUND(U39/$W$1,1),"") | X39: =IF(U39=0,0,IF($F39&"/Día"=W$9,ROUND(V39/U39,4),"")) | Y39: =IF(U39=0,0,IF($F39&"/Día"=W$9,ROUND(Z39/U39,4),"")) | Z39: =IF(U39<>"",$P39,"") | AA39: =IF($F39&"/Día"=AC$9,SUM($G39:$H39),"") | AB39: =IF(AA39<>"",$O39,"") | AC39: =IF($F39&"/Día"=AC$9,ROUND(AA39/$W$1,1),"") | AD39: =IF(AA39=0,0,IF($F39&"/Día"=AC$9,ROUND(AB39/AA39,4),"")) | AE39: =IF(AA39=0,0,IF($F39&"/Día"=AC$9,ROUND(AF39/AA39,4),"")) | AF39: =IF(AA39<>"",$P39,"")
B40: Subtotal | C40: =TEXT(A$37,)&" US$" -> Provincia Puerto Inca Huanuco US$ | O40: =SUM(O38:O39) -> 582597.08 | P40: =SUM(P38:P39) -> 87389.56 | Q40: =SUM(Q38:Q39) -> 87389.56 | S40: =SUM(S38:S39) -> 0 | U40: =SUM(U38:U39) -> 17824 | V40: =SUM(V38:V39) -> 582597.08 | W40: =SUM(W38:W39) -> 594.1 | X40: =ROUND(V40/U40,4) -> 32.6861 | Y40: =ROUND(Z40/U40,4) -> 4.9029 | Z40: =SUM(Z38:Z39) -> 87389.56 | AA40: =SUM(AA38:AA39) -> 0 | AB40: =SUM(AB38:AB39) -> 0 | AC40: =SUM(AC38:AC39) -> 0 | AD40: =IF(AA40=0,0,ROUND(AB40/AA40,4)) -> 0 | AE40: =IF(AA40=0,0,ROUND(AF40/AA40,4)) -> 0 | AF40: =SUM(AF38:AF39) -> 0 | AG40: =P40-Z40-AF40 -> 0
C41: =TEXT(A$37,)&" S/." -> Provincia Puerto Inca Huanuco S/. | P41: =ROUND($F$1*P40,2) -> 0 | Q41: =ROUND($F$1*Q40,2) -> 0 | S41: =ROUND($F$1*S40,2) -> 0
A42: Loreto / Ucayali | Q42: Loreto | S42: Ucayali
A43: - | B43: 192 | C43: Servicios | D43: Mes | E43: F1 | F43: Bls | O43: =ROUND(G43*I43,2)+ROUND(H43*J43,2)-K43-L43-M43-N43 -> 0 | P43: =ROUND(18.75%*O43,2) -> 0 | Q43: =ROUND($O43*R43,2) -> 0 | R43: 0.15 | S43: =ROUND($O43*T43,2) -> 0 | T43: 0.0375 | U43: =IF($F43&"/Día"=W$9,SUM($G43:$H43),"") -> 0 | V43: =IF(U43<>"",$O43,"") -> 0 | W43: =IF($F43&"/Día"=W$9,ROUND(U43/$W$1,1),"") -> 0 | X43: =IF(U43=0,0,IF($F43&"/Día"=W$9,ROUND(V43/U43,4),"")) -> 0 | Y43: =IF(U43=0,0,IF($F43&"/Día"=W$9,ROUND(Z43/U43,4),"")) -> 0 | Z43: =IF(U43<>"",$P43,"") -> 0 | AA43: =IF($F43&"/Día"=AC$9,SUM($G43:$H43),"") | AB43: =IF(AA43<>"",$O43,"") | AC43: =IF($F43&"/Día"=AC$9,ROUND(AA43/$W$1,1),"") | AD43: =IF(AA43=0,0,IF($F43&"/Día"=AC$9,ROUND(AB43/AA43,4),"")) | AE43: =IF(AA43=0,0,IF($F43&"/Día"=AC$9,ROUND(AF43/AA43,4),"")) | AF43: =IF(AA43<>"",$P43,"")
A44: - | B44: 8 | C44: Licencia | D44: Quincena | E44: F2 | F44: Bls | O44: =ROUND(G44*I44,2)+ROUND(H44*J44,2)-K44-L44-M44-N44 -> 0 | P44: =ROUND(18.75%*O44,2) -> 0 | Q44: =ROUND($O44*R44,2) -> 0 | R44: 0.15 | S44: =ROUND($O44*T44,2) -> 0 | T44: 0.0375 | U44: =IF($F44&"/Día"=W$9,SUM($G44:$H44),"") -> 0 | V44: =IF(U44<>"",$O44,"") -> 0 | W44: =IF($F44&"/Día"=W$9,ROUND(U44/$W$1,1),"") -> 0 | X44: =IF(U44=0,0,IF($F44&"/Día"=W$9,ROUND(V44/U44,4),"")) -> 0 | Y44: =IF(U44=0,0,IF($F44&"/Día"=W$9,ROUND(Z44/U44,4),"")) -> 0 | Z44: =IF(U44<>"",$P44,"") -> 0 | AA44: =IF($F44&"/Día"=AC$9,SUM($G44:$H44),"") | AB44: =IF(AA44<>"",$O44,"") | AC44: =IF($F44&"/Día"=AC$9,ROUND(AA44/$W$1,1),"") | AD44: =IF(AA44=0,0,IF($F44&"/Día"=AC$9,ROUND(AB44/AA44,4),"")) | AE44: =IF(AA44=0,0,IF($F44&"/Día"=AC$9,ROUND(AF44/AA44,4),"")) | AF44: =IF(AA44<>"",$P44,"")
A45: - | B45: 31-C GAS | C45: Licencia | D45: Quincena | E45: F2 | F45: MM BTU | G45: 159353.64 | H45: 8113.0945 | J45: 3.6054 | N45: 1712.3 | O45: =ROUND(G45*I45,2)+ROUND(H45*J45,2)-K45-L45-M45-N45 -> 27538.65 | P45: =ROUND(18.75%*O45,2) -> 5163.5 | Q45: =ROUND($O45*R45,2) -> 1032.7 | R45: 0.0375 | S45: =ROUND($O45*T45,2) -> 4130.8 | T45: 0.15 | U45: =IF($F45&"/Día"=W$9,SUM($G45:$H45),"") | V45: =IF(U45<>"",$O45,"") | W45: =IF($F45&"/Día"=W$9,ROUND(U45/$W$1,1),"") | X45: =IF(U45=0,0,IF($F45&"/Día"=W$9,ROUND(V45/U45,4),"")) | Y45: =IF(U45=0,0,IF($F45&"/Día"=W$9,ROUND(Z45/U45,4),"")) | Z45: =IF(U45<>"",$P45,"") | AA45: =IF($F45&"/Día"=AC$9,SUM($G45:$H45),"") -> 167466.73 | AB45: =IF(AA45<>"",$O45,"") -> 27538.65 | AC45: =IF($F45&"/Día"=AC$9,ROUND(AA45/$W$1,1),"") -> 5582.2 | AD45: =IF(AA45=0,0,IF($F45&"/Día"=AC$9,ROUND(AB45/AA45,4),"")) -> 0.1644 | AE45: =IF(AA45=0,0,IF($F45&"/Día"=AC$9,ROUND(AF45/AA45,4),"")) -> 0.0308 | AF45: =IF(AA45<>"",$P45,"") -> 5163.5
A46: - | B46: 31-C LGN (*) | C46: Licencia | D46: Quincena | E46: F3 | F46: Bls | G46: 1119 | H46: 82 | J46: 58.7112 | N46: 3506.36 | O46: =ROUND(G46*I46,2)+ROUND(H46*J46,2)-K46-L46-M46-N46 -> 1307.96 | P46: =ROUND(18.75%*O46,2) -> 245.24 | Q46: =ROUND($O46*R46,2) -> 49.05 | R46: 0.0375 | S46: =ROUND($O46*T46,2) -> 196.19 | T46: 0.15 | U46: =IF($F46&"/Día"=W$9,SUM($G46:$H46),"") -> 1201 | V46: =IF(U46<>"",$O46,"") -> 1307.96 | W46: =IF($F46&"/Día"=W$9,ROUND(U46/$W$1,1),"") -> 40 | X46: =IF(U46=0,0,IF($F46&"/Día"=W$9,ROUND(V46/U46,4),"")) -> 1.0891 | Y46: =IF(U46=0,0,IF($F46&"/Día"=W$9,ROUND(Z46/U46,4),"")) -> 0.2042 | Z46: =IF(U46<>"",$P46,"") -> 245.24 | AA46: =IF($F46&"/Día"=AC$9,SUM($G46:$H46),"") | AB46: =IF(AA46<>"",$O46,"") | AC46: =IF($F46&"/Día"=AC$9,ROUND(AA46/$W$1,1),"") | AD46: =IF(AA46=0,0,IF($F46&"/Día"=AC$9,ROUND(AB46/AA46,4),"")) | AE46: =IF(AA46=0,0,IF($F46&"/Día"=AC$9,ROUND(AF46/AA46,4),"")) | AF46: =IF(AA46<>"",$P46,"")
A47: - | B47: 31-C COND | C47: Licencia | D47: Quincena | E47: F2 | F47: Bls | O47: =ROUND(G47*I47,2)+ROUND(H47*J47,2)-K47-L47-M47-N47 -> 0 | P47: =ROUND(18.75%*O47,2) -> 0 | Q47: =ROUND($O47*R47,2) -> 0 | R47: 0.0375 | S47: =ROUND($O47*T47,2) -> 0 | T47: 0.15 | U47: =IF($F47&"/Día"=W$9,SUM($G47:$H47),"") -> 0 | V47: =IF(U47<>"",$O47,"") -> 0 | W47: =IF($F47&"/Día"=W$9,ROUND(U47/$W$1,1),"") -> 0 | X47: =IF(U47=0,0,IF($F47&"/Día"=W$9,ROUND(V47/U47,4),"")) -> 0 | Y47: =IF(U47=0,0,IF($F47&"/Día"=W$9,ROUND(Z47/U47,4),"")) -> 0 | Z47: =IF(U47<>"",$P47,"") -> 0 | AA47: =IF($F47&"/Día"=AC$9,SUM($G47:$H47),"") | AB47: =IF(AA47<>"",$O47,"") | AC47: =IF($F47&"/Día"=AC$9,ROUND(AA47/$W$1,1),"") | AD47: =IF(AA47=0,0,IF($F47&"/Día"=AC$9,ROUND(AB47/AA47,4),"")) | AE47: =IF(AA47=0,0,IF($F47&"/Día"=AC$9,ROUND(AF47/AA47,4),"")) | AF47: =IF(AA47<>"",$P47,"")
A48: - | B48: 102 | C48: Licencia | D48: Quincena | E48: F2 | F48: Bls | O48: =ROUND(G48*I48,2)+ROUND(H48*J48,2)-K48-L48-M48-N48 -> 0 | P48: =ROUND(18.75%*O48,2) -> 0 | Q48: =P48-S48 -> 0 | R48: 0.15 | S48: =ROUND($O48*T48,2) -> 0 | T48: 0.0375 | U48: =IF($F48&"/Día"=W$9,SUM($G48:$H48),"") -> 0 | V48: =IF(U48<>"",$O48,"") -> 0 | W48: =IF($F48&"/Día"=W$9,ROUND(U48/$W$1,1),"") -> 0 | X48: =IF(U48=0,0,IF($F48&"/Día"=W$9,ROUND(V48/U48,4),"")) -> 0 | Y48: =IF(U48=0,0,IF($F48&"/Día"=W$9,ROUND(Z48/U48,4),"")) -> 0 | Z48: =IF(U48<>"",$P48,"") -> 0 | AA48: =IF($F48&"/Día"=AC$9,SUM($G48:$H48),"") | AB48: =IF(AA48<>"",$O48,"") | AC48: =IF($F48&"/Día"=AC$9,ROUND(AA48/$W$1,1),"") | AD48: =IF(AA48=0,0,IF($F48&"/Día"=AC$9,ROUND(AB48/AA48,4),"")) | AE48: =IF(AA48=0,0,IF($F48&"/Día"=AC$9,ROUND(AF48/AA48,4),"")) | AF48: =IF(AA48<>"",$P48,"")
A49: - | B49: 95 | C49: Licencia | D49: Quincena | E49: F2 | F49: Bls | G49: 314179 | H49: 309598 | J49: 52.616 | N49: 5430.5 | O49: =ROUND(G49*I49,2)+ROUND(H49*J49,2)-K49-L49-M49-N49 -> 16284378 | P49: =ROUND(18.75%*O49,2) -> 3053320.9 | Q49: =P49-S49 -> 2442656.7 | R49: 0.15 | S49: =ROUND($O49*T49,2) -> 610664.17 | T49: 0.0375 | U49: =IF($F49&"/Día"=W$9,SUM($G49:$H49),"") -> 623777 | V49: =IF(U49<>"",$O49,"") -> 16284378 | W49: =IF($F49&"/Día"=W$9,ROUND(U49/$W$1,1),"") -> 20792.6 | X49: =IF(U49=0,0,IF($F49&"/Día"=W$9,ROUND(V49/U49,4),"")) -> 26.1061 | Y49: =IF(U49=0,0,IF($F49&"/Día"=W$9,ROUND(Z49/U49,4),"")) -> 4.8949 | Z49: =IF(U49<>"",$P49,"") -> 3053320.9 | AA49: =IF($F49&"/Día"=AC$9,SUM($G49:$H49),"") | AB49: =IF(AA49<>"",$O49,"") | AC49: =IF($F49&"/Día"=AC$9,ROUND(AA49/$W$1,1),"") | AD49: =IF(AA49=0,0,IF($F49&"/Día"=AC$9,ROUND(AB49/AA49,4),"")) | AE49: =IF(AA49=0,0,IF($F49&"/Día"=AC$9,ROUND(AF49/AA49,4),"")) | AF49: =IF(AA49<>"",$P49,"") | AJ49: =AK49-P49 -> -0.86 | AK49: 3053320
A50: - | B50: 67 | C50: Licencia | D50: Quincena | E50: F2 | F50: Bls | O50: =ROUND(G50*I50,2)+ROUND(H50*J50,2)-K50-L50-M50-N50 -> 0 | P50: =ROUND(18.75%*O50,2) -> 0 | Q50: =P50-S50 -> 0 | R50: 0.15 | S50: =ROUND($O50*T50,2) -> 0 | T50: 0.0375 | U50: =IF($F50&"/Día"=W$9,SUM($G50:$H50),"") -> 0 | V50: =IF(U50<>"",$O50,"") -> 0 | W50: =IF($F50&"/Día"=W$9,ROUND(U50/$W$1,1),"") -> 0 | X50: =IF(U50=0,0,IF($F50&"/Día"=W$9,ROUND(V50/U50,4),"")) -> 0 | Y50: =IF(U50=0,0,IF($F50&"/Día"=W$9,ROUND(Z50/U50,4),"")) -> 0 | Z50: =IF(U50<>"",$P50,"") -> 0 | AA50: =IF($F50&"/Día"=AC$9,SUM($G50:$H50),"") | AB50: =IF(AA50<>"",$O50,"") | AC50: =IF($F50&"/Día"=AC$9,ROUND(AA50/$W$1,1),"") | AD50: =IF(AA50=0,0,IF($F50&"/Día"=AC$9,ROUND(AB50/AA50,4),"")) | AE50: =IF(AA50=0,0,IF($F50&"/Día"=AC$9,ROUND(AF50/AA50,4),"")) | AF50: =IF(AA50<>"",$P50,"")
A51: - | B51: Ajustes meses anteriores (3) | U51: =IF($F51&"/Día"=W$9,SUM($G51:$H51),"") | V51: =IF(U51<>"",$O51,"") | W51: =IF($F51&"/Día"=W$9,ROUND(U51/$W$1,1),"") | X51: =IF(U51=0,0,IF($F51&"/Día"=W$9,ROUND(V51/U51,4),"")) | Y51: =IF(U51=0,0,IF($F51&"/Día"=W$9,ROUND(Z51/U51,4),"")) | Z51: =IF(U51<>"",$P51,"") | AA51: =IF($F51&"/Día"=AC$9,SUM($G51:$H51),"") | AB51: =IF(AA51<>"",$O51,"") | AC51: =IF($F51&"/Día"=AC$9,ROUND(AA51/$W$1,1),"") | AD51: =IF(AA51=0,0,IF($F51&"/Día"=AC$9,ROUND(AB51/AA51,4),"")) | AE51: =IF(AA51=0,0,IF($F51&"/Día"=AC$9,ROUND(AF51/AA51,4),"")) | AF51: =IF(AA51<>"",$P51,"")
B52: Subtotal | C52: =TEXT(A$42,)&" US$" -> Loreto / Ucayali US$ | O52: =SUM(O43:O51) -> 16313224 | P52: =SUM(P43:P51) -> 3058729.6 | Q52: =SUM(Q43:Q51) -> 2443738.4 | S52: =SUM(S43:S51) -> 614991.16 | U52: =SUM(U43:U51) -> 624978 | V52: =SUM(V43:V51) -> 16285686 | W52: =SUM(W43:W51) -> 20832.6 | X52: =ROUND(V52/U52,4) -> 26.058 | Y52: =ROUND(Z52/U52,4) -> 4.8859 | Z52: =SUM(Z43:Z51) -> 3053566.1 | AA52: =SUM(AA43:AA51) -> 167466.73 | AB52: =SUM(AB43:AB51) -> 27538.65 | AC52: =SUM(AC43:AC51) -> 5582.2 | AD52: =ROUND(AB52/AA52,4) -> 0.1644 | AE52: =ROUND(AF52/AA52,4) -> 0.0308 | AF52: =SUM(AF43:AF51) -> 5163.5 | AG52: =P52-Z52-AF52 -> 0
C53: =TEXT(A$42,)&" S/." -> Loreto / Ucayali S/. | P53: =ROUND($F$1*P52,2) -> 0 | Q53: =ROUND($F$1*Q52,2) -> 0 | S53: =ROUND($F$1*S52,2) -> 0
A54: Cusco | P54: V. Regalías | Q54: Cusco
A55: - | B55: 88 LGN | C55: Licencia | D55: Quincena | E55: F4 | F55: Bls | G55: 717572 | H55: 710328 | J55: 43.0508 | O55: =G55*I55+H55*J55 -> 30580189 | P55: =ROUND(37.24%*(G55*I55+H55*J55),2) -> 11388062 | Q55: =ROUND(R55*P55,2) -> 5694031.1 | R55: 0.5 | U55: =IF($F55&"/Día"=W$9,SUM($G55:$H55),"") -> 1427900 | V55: =IF(U55<>"",$O55,"") -> 30580189 | W55: =IF($F55&"/Día"=W$9,ROUND(U55/$W$1,1),"") -> 47596.7 | X55: =IF(U55=0,0,IF($F55&"/Día"=W$9,ROUND(V55/U55,4),"")) -> 21.4162 | Y55: =IF(U55=0,0,IF($F55&"/Día"=W$9,ROUND(Z55/U55,4),"")) -> 3.9877 | Z55: =IF(U55<>"",$Q55,"") -> 5694031.1 | AA55: =IF($F55&"/Día"=AC$9,SUM($G55:$H55),"") | AB55: =IF(AA55<>"",$O55,"") | AC55: =IF($F55&"/Día"=AC$9,ROUND(AA55/$W$1,1),"") | AD55: =IF(AA55=0,0,IF($F55&"/Día"=AC$9,ROUND(AB55/AA55,4),"")) | AE55: =IF(AA55=0,0,IF($F55&"/Día"=AC$9,ROUND(AF55/AA55,4),"")) | AF55: =IF(AA55<>"",$Q55,"")
A56: - | B56: 88 GAS | C56: Licencia | D56: Quincena | E56: F4 | F56: MM BTU | G56: =G413 -> 14403589 | H56: =H421 -> 12762904 | J56: =J421 -> 2.6289 | O56: =O405 -> 74052896 | P56: =P405 -> 27636037 | Q56: =Q405 -> 13818018 | R56: 0.5 | U56: =IF($F56&"/Día"=W$9,SUM($G56:$H56),"") | V56: =IF(U56<>"",$O56,"") | W56: =IF($F56&"/Día"=W$9,ROUND(U56/$W$1,1),"") | X56: =IF(U56=0,0,IF($F56&"/Día"=W$9,ROUND(V56/U56,4),"")) | Y56: =IF(U56=0,0,IF($F56&"/Día"=W$9,ROUND(Z56/U56,4),"")) | Z56: =IF(U56<>"",$Q56,"") | AA56: =IF($F56&"/Día"=AC$9,SUM($G56:$H56),"") -> 27166493 | AB56: =IF(AA56<>"",$O56,"") -> 74052896 | AC56: =IF($F56&"/Día"=AC$9,ROUND(AA56/$W$1,1),"") -> 905549.8 | AD56: =IF(AA56=0,0,IF($F56&"/Día"=AC$9,ROUND(AB56/AA56,4),"")) -> 2.7259 | AE56: =IF(AA56=0,0,IF($F56&"/Día"=AC$9,ROUND(AF56/AA56,4),"")) -> 0.5086 | AF56: =IF(AA56<>"",$Q56,"") -> 13818018
A57: - | B57: 56 LGN | C57: Licencia | D57: Quincena | E57: F4 | F57: Bls | G57: 178347 | H57: 177661 | J57: 43.0503 | O57: =G57*I57+H57*J57 -> 7648359.3 | P57: =ROUND(40%*G57*I57,2)+ROUND(40%*H57*J57,2) -> 3059343.7 | Q57: =ROUND(R57*P57,2) -> 1529671.9 | R57: 0.5 | U57: =IF($F57&"/Día"=W$9,SUM($G57:$H57),"") -> 356008 | V57: =IF(U57<>"",$O57,"") -> 7648359.3 | W57: =IF($F57&"/Día"=W$9,ROUND(U57/$W$1,1),"") -> 11866.9 | X57: =IF(U57=0,0,IF($F57&"/Día"=W$9,ROUND(V57/U57,4),"")) -> 21.4837 | Y57: =IF(U57=0,0,IF($F57&"/Día"=W$9,ROUND(Z57/U57,4),"")) -> 4.2967 | Z57: =IF(U57<>"",$Q57,"") -> 1529671.9 | AA57: =IF($F57&"/Día"=AC$9,SUM($G57:$H57),"") | AB57: =IF(AA57<>"",$O57,"") | AC57: =IF($F57&"/Día"=AC$9,ROUND(AA57/$W$1,1),"") | AD57: =IF(AA57=0,0,IF($F57&"/Día"=AC$9,ROUND(AB57/AA57,4),"")) | AE57: =IF(AA57=0,0,IF($F57&"/Día"=AC$9,ROUND(AF57/AA57,4),"")) | AF57: =IF(AA57<>"",$Q57,"")
A58: - | B58: 56 GAS | C58: Licencia | D58: Quincena | E58: F4 | F58: MM BTU | G58: 5247656.3 | H58: 5344313.7 | J58: 2.731 | O58: =G58*I58+H58*J58 -> 14595321 | P58: =ROUND(38%*G58*I58,2)+ROUND(38%*H58*J58,2) -> 5546221.8 | Q58: =ROUND(R58*P58,2) -> 2773110.9 | R58: 0.5 | U58: =IF($F58&"/Día"=W$9,SUM($G58:$H58),"") | V58: =IF(U58<>"",$O58,"") | W58: =IF($F58&"/Día"=W$9,ROUND(U58/$W$1,1),"") | X58: =IF(U58=0,0,IF($F58&"/Día"=W$9,ROUND(V58/U58,4),"")) | Y58: =IF(U58=0,0,IF($F58&"/Día"=W$9,ROUND(Z58/U58,4),"")) | Z58: =IF(U58<>"",$Q58,"") | AA58: =IF($F58&"/Día"=AC$9,SUM($G58:$H58),"") -> 10591970 | AB58: =IF(AA58<>"",$O58,"") -> 14595321 | AC58: =IF($F58&"/Día"=AC$9,ROUND(AA58/$W$1,1),"") -> 353065.7 | AD58: =IF(AA58=0,0,IF($F58&"/Día"=AC$9,ROUND(AB58/AA58,4),"")) -> 1.378 | AE58: =IF(AA58=0,0,IF($F58&"/Día"=AC$9,ROUND(AF58/AA58,4),"")) -> 0.2618 | AF58: =IF(AA58<>"",$Q58,"") -> 2773110.9
A59: - | B59: 57 LGN | C59: Licencia | D59: Quincena | E59: F4 | F59: Bls | G59: 249009 | H59: 239293 | J59: 41.4703 | O59: =G59*I59+H59*J59 -> 9923552.5 | P59: =ROUND(G59*I59,2)*6.83%+ROUND(H59*J59,2)*6.73% -> 667855.08 | Q59: =ROUND(R59*P59,2) -> 333927.54 | R59: 0.5 | U59: =IF($F59&"/Día"=W$9,SUM($G59:$H59),"") -> 488302 | V59: =IF(U59<>"",$O59,"") -> 9923552.5 | W59: =IF($F59&"/Día"=W$9,ROUND(U59/$W$1,1),"") -> 16276.7 | X59: =IF(U59=0,0,IF($F59&"/Día"=W$9,ROUND(V59/U59,4),"")) -> 20.3226 | Y59: =IF(U59=0,0,IF($F59&"/Día"=W$9,ROUND(Z59/U59,4),"")) -> 0.6839 | Z59: =IF(U59<>"",$Q59,"") -> 333927.54 | AA59: =IF($F59&"/Día"=AC$9,SUM($G59:$H59),"") | AB59: =IF(AA59<>"",$O59,"") | AC59: =IF($F59&"/Día"=AC$9,ROUND(AA59/$W$1,1),"") | AD59: =IF(AA59=0,0,IF($F59&"/Día"=AC$9,ROUND(AB59/AA59,4),"")) | AE59: =IF(AA59=0,0,IF($F59&"/Día"=AC$9,ROUND(AF59/AA59,4),"")) | AF59: =IF(AA59<>"",$Q59,"")
A60: - | B60: 57 GAS | C60: Licencia | D60: Quincena | E60: F4 | F60: MM BTU | G60: 4227519 | H60: 4064039.9 | J60: 5.244 | O60: =G60*I60+H60*J60 -> 21311825 | P60: =ROUND(G60*I60,2)*11.62%+ROUND(H60*J60,2)*11.33% -> 2414629.8 | Q60: =ROUND(R60*P60,2) -> 1207314.9 | R60: 0.5 | U60: =IF($F60&"/Día"=W$9,SUM($G60:$H60),"") | V60: =IF(U60<>"",$O60,"") | W60: =IF($F60&"/Día"=W$9,ROUND(U60/$W$1,1),"") | X60: =IF(U60=0,0,IF($F60&"/Día"=W$9,ROUND(V60/U60,4),"")) | Y60: =IF(U60=0,0,IF($F60&"/Día"=W$9,ROUND(Z60/U60,4),"")) | Z60: =IF(U60<>"",$Q60,"") | AA60: =IF($F60&"/Día"=AC$9,SUM($G60:$H60),"") -> 8291558.9 | AB60: =IF(AA60<>"",$O60,"") -> 21311825 | AC60: =IF($F60&"/Día"=AC$9,ROUND(AA60/$W$1,1),"") -> 276385.3 | AD60: =IF(AA60=0,0,IF($F60&"/Día"=AC$9,ROUND(AB60/AA60,4),"")) -> 2.5703 | AE60: =IF(AA60=0,0,IF($F60&"/Día"=AC$9,ROUND(AF60/AA60,4),"")) -> 0.1456 | AF60: =IF(AA60<>"",$Q60,"") -> 1207314.9
A61: - | B61: Ajustes meses anteriores (4) | O61: =O317 -> -1669118.1 | P61: =P317 -> -263808.19 | Q61: =Q317 -> -131904.08 | U61: =IF($F61&"/Día"=W$9,SUM($G61:$H61),"") | V61: =IF(U61<>"",$O61,"") | W61: =IF($F61&"/Día"=W$9,ROUND(U61/$W$1,1),"") | X61: =IF(U61=0,0,IF($F61&"/Día"=W$9,ROUND(V61/U61,4),"")) | Y61: =IF(U61=0,0,IF($F61&"/Día"=W$9,ROUND(Z61/U61,4),"")) | Z61: =IF(U61<>"",$Q61,"") | AA61: =IF($F61&"/Día"=AC$9,SUM($G61:$H61),"") | AB61: =IF(AA61<>"",$O61,"") | AC61: =IF($F61&"/Día"=AC$9,ROUND(AA61/$W$1,1),"") | AD61: =IF(AA61=0,0,IF($F61&"/Día"=AC$9,ROUND(AB61/AA61,4),"")) | AE61: =IF(AA61=0,0,IF($F61&"/Día"=AC$9,ROUND(AF61/AA61,4),"")) | AF61: =IF(AA61<>"",$Q61,"")
B62: Subtotal | C62: =TEXT(A$54,)&" US$" -> Cusco US$ | O62: =SUM(O55:O61) -> 1.5644302e+08 | P62: =SUM(P55:P61) -> 50448341 | Q62: =SUM(Q55:Q61) -> 25224171 | U62: =SUM(U55:U61) -> 2272210 | V62: =SUM(V55:V61) -> 48152101 | W62: =SUM(W55:W61) -> 75740.3 | X62: =ROUND(V62/U62,4) -> 21.1917 | Y62: =ROUND(Z62/U62,4) -> 3.3261 | Z62: =SUM(Z55:Z61) -> 7557630.5 | AA62: =SUM(AA55:AA61) -> 46050022 | AB62: =SUM(AB55:AB61) -> 1.0996004e+08 | AC62: =SUM(AC55:AC61) -> 1535000.8 | AD62: =ROUND(AB62/AA62,4) -> 2.3878 | AE62: =ROUND(AF62/AA62,4) -> 0.3865 | AF62: =SUM(AF55:AF61) -> 17798444 | AG62: =Q62-Z62-AF62 -> -131904.08
C63: =TEXT(A$54,)&" S/." -> Cusco S/. | G63: =SUMPRODUCT(I58:I58,G58:G58)/SUM(G58:G58) -> #VALUE! | H63: =SUMPRODUCT(J58:J58,H58:H58)/SUM(H58:H58) -> 2.731 | Q63: =Q62*F1 -> 0 | AJ63: Regalía 1Q | AK63: 8616391.9 | AL63: =P35 -> 5193475.5 | AM63: Piura / Tumbes
A64: Total General | G64: =G62*G63 -> #VALUE! | H64: =H62*H63 -> 0 | I64: =H64+G64 -> #VALUE! | J64: =O58+#REF! -> #REF! | K64: =I64-J64 -> #VALUE! | M64: =SUM(M10:M60) -> 0 | N64: =SUM(N10:N60) -> 32283.94 | O64: =O35+O40+O52+O62 -> 2.0103738e+08 | P64: =Q62+P52+P40+P35 -> 33563765 | Q64: =Q36+S36+Q41+Q53+S53+Q63 -> 0 | U64: =U35+U40+U52+U62 -> 3559027.1 | V64: =V35+V40+V52+V62 -> 85049938 | W64: =W35+W40+W52+W62 -> 118634.2 | X64: =ROUND(V64/U64,4) -> 23.897 | Y64: =ROUND(Z64/U64,4) -> 4.0613 | Z64: =Z35+Z40+Z52+Z62 -> 14454128 | AA64: =AA35+AA40+AA52+AA62 -> 47653903 | AB64: =AB35+AB40+AB52+AB62 -> 1.1359228e+08 | AC64: =AC35+AC40+AC52+AC62 -> 1588463.4 | AD64: =ROUND(AB64/AA64,4) -> 2.3837 | AE64: =ROUND(AF64/AA64,4) -> 0.3878 | AF64: =AF35+AF40+AF52+AF62 -> 18479489 | AG64: =P64-Z64-AF64 -> 630148.47 | AI64: 57 | AJ64: Regalía 2Q | AK64: 8552748.6 | AL64: =P52 -> 3058729.6 | AM64: Loreto / Ucayali
AI65: 56 | AL65: =P40 -> 87389.56 | AM65: Huanuco
A66: (*) | B66: Determinación de Canasta de los Líquidos de Gas Natural (VLGNF) | H66: = ( VC * %P + (PB - TF - TT) * (1 - %P)) | AI66: 88 | AK66: =SUM(AK63:AK65) -> 17169140 | AL66: =SUM(AL63:AL65) -> 8339594.7 | AM66: =+AK66-AL66 -> 8829545.8
B67: Simbolo | C67: Descripcion | E67: 1ra. Q | F67: 2da. Q | H67: 1ra. Q
B68: VC | C68: Canasta de Petróleo | H68: ="= ("&TEXT(E68,"0.0000")&" * "&TEXT(E71,"0.00%")&" + ("&TEXT(E69,"0.0000")&" - "&TEXT(E70,"0.0000")&" - "&TEXT(E73,"0.0000")&") * (1 - "&TEXT(E71,"0.00%")&"))" -> = (0.0000 * 0.00% + (0.0000 - 0.0000 - 0.0000) * (1 - 0.00%)) | N68: =547803.45/8532764.09 -> 0.064199999 | AJ68: Lote 57 1Q | AK68: 1620125.4
B69: PB | C69: Precio del GLP | H69: =((85.98%*E68+4.4221)*E71+(E69-E70-E73)*(1-E71)) -> 0 | M69: =698277.28/7412709.99 -> 0.0942 | N69: =1065699.61/10775526.87 -> 0.0989 | AJ69: Lote 56 1Q | AK69: 7235877
B70: TF | C70: Tarifa de Fraccionam. | M70: =5254120.1/13135300.26 -> 0.4 | N70: =7653140.6/19132851.51 -> 0.4 | AJ70: Lote 88 1Q | AK70: 13473139
B71: %P | C71: % Contenido Pentanos | H71: 2da. Q | M71: =503101.38/1323950.99 -> 0.38 | AJ71: Lote 57 2Q | AK71: 1512806.4
B72: QLGNF | C72: Volumen de LGN | H72: ="= ("&TEXT(F68,"0.0000")&" * "&TEXT(F71,"0.00%")&" + ("&TEXT(F69,"0.0000")&" - "&TEXT(F70,"0.0000")&" - "&TEXT(F73,"0.0000")&") * (1 - "&TEXT(F71,"0.00%")&"))" -> = (0.0000 * 0.00% + (0.0000 - 0.0000 - 0.0000) * (1 - 0.00%)) | AJ72: Lote 56 2Q | AK72: 4201246.7
B73: TT | C73: Tarifa de Transporte | H73: =((85.98%*F68+4.4221)*F71+(F69-F70-F73)*(1-F71)) -> 0 | AJ73: Lote 88 2Q | AK73: 11926716
AK74: =SUM(AK68:AK73) -> 39969910 | AL74: =Q62 -> 25224171 | AM74: =AK74-AL74 -> 14745739
AK75: =+AK63+AK68+AK69+AK70 -> 30945533
O76: =69441.84+67862.67 -> 137304.51 | AK76: =+AK64+AK71+AK72+AK73 -> 26193517
A77: ="AJUSTES PARA "&UPPER(TEXT(E1,"MMMMMMM YYYY")) -> AJUSTES PARA NOVIEMBRE 2024 | AK77: =SUM(AK75:AK76) -> 57139050
B79: Ajuste correspondiente de Oct-24 (Reporte de Regalía 1Q.Nov.24) - Liq. 1433
A80: Cusco | D80: Período | E80: Fórmula | F80: Unidades | G80: 1ra. Q | H80: 2da. Q / Mes | I80: 1ra. Q | J80: 2da. Q / Mes | K80: Flete Marítimo | L80: Comercialización | M80: Oleoducto | N80: Fiscalización | O80: Valor Producción | P80: V. Regalías | Q80: Cuzco
A81: - | B81: 57 Gas | C81: Licencia | D81: Quincena | E81: F4 | F81: MM BTU | G81: 3897088.3 | H81: 1923805.7 | I81: 5.422 | J81: 5.422 | O81: =G81*I81+H81*J81 -> 31560887 | P81: =ROUND(G81*I81,2)*11.53%+ROUND(H81*J81,2)*11.44% -> 3629582.5 | Q81: =ROUND(R81*P81,2) -> 1814791.2 | R81: 0.5
A82: - | B82: =B81 -> 57 Gas | C82: Licencia | D82: Modificación | F82: =F81 -> MM BTU | G82: =G81 -> 3897088.3 | H82: =H81 -> 1923805.7 | I82: 5.293 | J82: 5.293 | O82: =G82*I82+H82*J82 -> 30809992 | P82: =ROUND(G82*I82,2)*11.53%+ROUND(H82*J82,2)*11.44% -> 3543227.6 | Q82: =ROUND(R82*P82,2) -> 1771613.8 | R82: 0.5
B83: Ajuste | G83: =G82-G81 -> 0 | H83: =H82-H81 -> 0 | I83: =I82-I81 -> -0.129 | J83: =J82-J81 -> -0.129 | K83: =K82-K81 -> 0 | L83: =L82-L81 -> 0 | M83: =M82-M81 -> 0 | N83: =N82-N81 -> 0 | ... Q83: =Q82-Q81 -> -43177.44 | S83: ok
B85: Ajuste correspondiente a Set.24 (Reporte de Regalía 1Q.Nov.24) - Liq. 1433
A86: Cusco | D86: Período | E86: Fórmula | F86: Unidades | G86: 1ra. Q | H86: 2da. Q / Mes | I86: 1ra. Q | J86: 2da. Q / Mes | K86: Flete Marítimo | L86: Comercialización | M86: Oleoducto | N86: Fiscalización | O86: Valor Producción | P86: V. Regalías | Q86: Cuzco
A87: - | B87: 88 GAS | C87: Licencia | D87: Quincena | E87: F4 | F87: MM BTU | G87: 14234434 | H87: 13910733 | I87: 2.6154 | J87: 2.6154 | O87: =ROUND(G87*I87+H87*J87,2) -> 73610869 | P87: =ROUND(37.24%*(G87*I87+H87*J87),2) -> 27412688 | Q87: =ROUND(R87*P87,2) -> 13706344 | R87: 0.5
A88: - | B88: =B87 -> 88 GAS | C88: Licencia | D88: Modificación | F88: =F87 -> MM BTU | G88: =G87 -> 14234434 | H88: =H87 -> 13910733 | I88: 2.6285 | J88: 2.6285 | O88: =G88*I88+H88*J88 -> 73979571 | P88: =ROUND(37.24%*(G88*I88+H88*J88),2) -> 27549992 | Q88: =ROUND(R88*P88,2) -> 13774996 | R88: 0.5
B89: Ajuste | G89: =G88-G87 -> 0 | H89: =H88-H87 -> 0 | I89: =I88-I87 -> 0.0131 | J89: =J88-J87 -> 0.0131 | K89: =K88-K87 -> 0 | L89: =L88-L87 -> 0 | M89: =M88-M87 -> 0 | N89: =N88-N87 -> 0 | ... Q89: =Q88-Q87 -> 68652.25 | S89: ok
B91: Ajuste correspondiente a Oct.24 (Reporte de Regalía 1Q.Nov.24) - Liq. 1433
A92: Cusco | D92: Período | E92: Fórmula | F92: Unidades | G92: 1ra. Q | H92: 2da. Q / Mes | I92: 1ra. Q | J92: 2da. Q / Mes | K92: Flete Marítimo | L92: Comercialización | M92: Oleoducto | N92: Fiscalización | O92: Valor Producción | P92: V. Regalías | Q92: Cuzco
A93: - | B93: 88 GAS | C93: Licencia | D93: Quincena | E93: F4 | F93: MM BTU | G93: 13438808 | H93: 14272479 | I93: 2.6154 | J93: 2.6154 | O93: =ROUND(G93*I93+H93*J93,2) -> 72476099 | P93: =ROUND(37.24%*(G93*I93+H93*J93),2) -> 26990099 | Q93: =ROUND(R93*P93,2) -> 13495050 | R93: 0.5
A94: - | B94: =B93 -> 88 GAS | C94: Licencia | D94: Modificación | F94: =F93 -> MM BTU | G94: =G93 -> 13438808 | H94: =H93 -> 14272479 | I94: 2.6158 | J94: 2.6158 | O94: =G94*I94+H94*J94 -> 72487184 | P94: =ROUND(37.24%*(G94*I94+H94*J94),2) -> 26994227 | Q94: =ROUND(R94*P94,2) -> 13497114 | R94: 0.5
B95: Ajuste | G95: =G94-G93 -> 0 | H95: =H94-H93 -> 0 | I95: =I94-I93 -> 0.0004 | J95: =J94-J93 -> 0.0004 | K95: =K94-K93 -> 0 | L95: =L94-L93 -> 0 | M95: =M94-M93 -> 0 | N95: =N94-N93 -> 0 | ... Q95: =Q94-Q93 -> 2063.93 | S95: ok
B97: Ajuste correspondiente a Set.24 (Reporte de Regalía 1Q.Nov.24) - Liq. 1433
A98: Cusco | D98: Período | E98: Fórmula | F98: Unidades | G98: 1ra. Q | H98: 2da. Q / Mes | I98: 1ra. Q | J98: 2da. Q / Mes | K98: Flete Marítimo | L98: Comercialización | M98: Oleoducto | N98: Fiscalización | O98: Valor Producción | P98: V. Regalías | Q98: Cuzco
A99: - | B99: 88 Gas Planta Pisco | C99: Licencia | D99: Quincena | E99: F4 | F99: MM BTU | G99: 33040.906 | H99: 34294.392 | I99: 3.6209 | J99: 3.6209 | O99: =G99*I99+H99*J99 -> 243814.38 | P99: =ROUND(37.24%*O99,2) -> 90796.48 | Q99: =ROUND(R99*P99,2) -> 45398.24 | R99: 0.5
A100: - | B100: =B99 -> 88 Gas Planta Pisco | C100: Licencia | D100: Modificación | F100: =F99 -> MM BTU | G100: =G99 -> 33040.906 | H100: =H99 -> 34294.392 | I100: 3.619 | J100: 3.619 | O100: =G100*I100+H100*J100 -> 243686.44 | P100: =ROUND(37.24%*O100,2) -> 90748.83 | Q100: =ROUND(R100*P100,2) -> 45374.42 | R100: 0.5
B101: Ajuste | G101: =G100-G99 -> 0 | H101: =H100-H99 -> 0 | I101: =I100-I99 -> -0.0019 | J101: =J100-J99 -> -0.0019 | K101: =K100-K99 -> 0 | L101: =L100-L99 -> 0 | M101: =M100-M99 -> 0 | N101: =N100-N99 -> 0 | ... Q101: =Q100-Q99 -> -23.82 | S101: ok
B103: Ajuste correspondiente a Oct.24 (Reporte de Regalía 1Q.Nov.24) - Liq. 1433
A104: Cusco | D104: Período | E104: Fórmula | F104: Unidades | G104: 1ra. Q | H104: 2da. Q / Mes | I104: 1ra. Q | J104: 2da. Q / Mes | K104: Flete Marítimo | L104: Comercialización | M104: Oleoducto | N104: Fiscalización | O104: Valor Producción | P104: V. Regalías | Q104: Cuzco
A105: - | B105: 88 Gas Planta Pisco | C105: Licencia | D105: Quincena | E105: F4 | F105: MM BTU | G105: 31501.491 | H105: 15335.298 | I105: 3.6209 | J105: 3.6209 | O105: =G105*I105+H105*J105 -> 169591.33 | P105: =ROUND(37.24%*O105,2) -> 63155.81 | Q105: =ROUND(R105*P105,2) -> 31577.91 | R105: 0.5
A106: - | B106: =B105 -> 88 Gas Planta Pisco | C106: Licencia | D106: Modificación | F106: =F105 -> MM BTU | G106: =G105 -> 31501.491 | H106: =H105 -> 15335.298 | I106: 3.6248 | J106: 3.6248 | O106: =G106*I106+H106*J106 -> 169773.99 | P106: =ROUND(37.24%*O106,2) -> 63223.83 | Q106: =ROUND(R106*P106,2) -> 31611.92 | R106: 0.5
...

Sheet Ene
A1: Período de Cálculo: | E1: 46053 | F1: 3.353
A2: PERUPETRO S.A.
A3: DETERMINACION DEL CANON, SOBRECANON y PARTICIPACION (US$)
A4: Correspondiente a Enero 2026
A5: Tipo de Cambio= 3.353
A7: Localidad | C7: Modalidad de Contrato | D7: Calculo del Canon | F7: Volumen Producción / Venta | I7: Canasta o Valor Venta (US$/Unidad) | K7: Deducción de Gastos para determinación de valor de producción en Punto de Fiscalización (US$) | O7: Valor de la Producción (US$) | P7: Canon y Sobrecanon / Participación (US$)
A8: - Lote | D8: Período | E8: Fórmula | F8: Unidades | G8: 1ra. Q | H8: 2da. Q / Mes | I8: 1ra. Q | J8: 2da. Q / Mes | K8: Flete Marítimo | L8: Comercialización | M8: Oleoducto | N8: Fiscalización | P8: Total | Q8: Localidad 1 | S8: Localidad 2
A9: Piura / Tumbes | Q9: Piura | S9: Tumbes
A10: - | B10: I | C10: Licencia | D10: Quincena | E10: F2 | F10: Bls | G10: 6218 | H10: 0 | I10: 62.6248 | J10: 0 | N10: 78.54 | O10: 389322.47 | P10: 72997.96 | Q10: 58398.37 | R10: 0.15 | S10: 14599.59 | T10: 0.0375
A11: - | B11: I GAS | C11: Licencia | D11: Quincena | E11: F2 | F11: MM BTU | G11: 39722.936 | H11: 47753.756 | I11: 3 | J11: 3 | N11: 2455.11 | O11: 259974.97 | P11: 48745.31 | Q11: 38996.25 | R11: 0.15 | S11: 9749.06 | T11: 0.0375
A12: - | B12: II | C12: Licencia | D12: Quincena | E12: F2 | F12: Bls | N12: 638.52 | O12: -638.52 | P12: -119.72 | Q12: -95.78 | R12: 0.15 | S12: -23.94 | T12: 0.0375
A13: - | B13: II - GAS | C13: Licencia | D13: Quincena | E13: F2 | F13: MM BTU | G13: 2448.8715 | H13: 0 | I13: 2.95 | J13: 0 | N13: 980.66 | O13: 6243.51 | P13: 1170.66 | Q13: 936.53 | R13: 0.15 | S13: 234.13 | T13: 0.0375
A14: - | B14: III | C14: Licencia | D14: Quincena | E14: F2 | F14: Bls | G14: 0 | H14: 0 | I14: 0 | J14: 0 | O14: 0 | P14: 0 | Q14: 0 | R14: 0.15 | S14: 0 | T14: 0.0375
A15: - | B15: III - GAS | C15: Licencia | D15: Quincena | E15: F2 | F15: MM BTU | G15: 94823.849 | H15: 104245.97 | I15: 2.9336 | J15: 2.9336 | N15: 447.31 | O15: 583543.9 | P15: 109414.48 | Q15: 87531.59 | R15: 0.15 | S15: 21882.9 | T15: 0.0375
A16: - | B16: IV | C16: Licencia | D16: Quincena | E16: F2 | F16: Bls | G16: 0 | H16: 0 | I16: 0 | J16: 0 | O16: 0 | P16: 0 | Q16: 0 | R16: 0.15 | S16: 0 | T16: 0.0375
A17: - | B17: IV - GAS | C17: Licencia | D17: Quincena | E17: F2 | F17: Bls | G17: 44376.026 | H17: 72854.085 | I17: 2.5029 | J17: 2.5029 | N17: 823.63 | O17: 292591.62 | P17: 54860.93 | Q17: 43888.74 | R17: 0.15 | S17: 10972.19 | T17: 0.0375
A18: - | B18: V | C18: Licencia | D18: Quincena | E18: F2 | F18: Bls | H18: 3113 | J18: 66.1598 | N18: 416.58 | O18: 205538.88 | P18: 38538.54 | Q18: 30830.83 | R18: 0.15 | S18: 7707.71 | T18: 0.0375
A19: - | B19: VI (T) | C19: Licencia | D19: Quincena | E19: F2 | F19: Bls | O19: 0 | P19: 0 | Q19: 0 | R19: 0.15 | S19: 0 | T19: 0.0375
A20: - | B20: VI - GAS | C20: Licencia | D20: Quincena | E20: F2 | F20: MM BTU | O20: 0 | P20: 0 | Q20: 0 | R20: 0.15 | S20: 0 | T20: 0.0375
A21: - | B21: VII (T) | C21: Licencia | D21: Quincena | E21: F2 | F21: Bls | G21: 0 | H21: 18420 | I21: 0 | J21: 66.1598 | N21: 249.26 | O21: 1218414.3 | P21: 228452.67 | Q21: 182762.14 | R21: 0.15 | S21: 45690.53 | T21: 0.0375
A22: - | B22: IX | C22: Licencia | D22: Quincena | E22: F2 | F22: Bls | G22: 2495 | H22: 4091 | I22: 62.6248 | J22: 66.2547 | N22: 266.33 | O22: 427030.53 | P22: 80068.22 | Q22: 64054.58 | R22: 0.15 | S22: 16013.64 | T22: 0.0375
A23: - | B23: X | C23: Licencia | D23: Quincena | E23: F2 | F23: Bls | G23: 48898.4 | H23: 47937.6 | I23: 64.6988 | J23: 68.6241 | N23: 2172.38 | O23: 6451170.1 | P23: 1209594.4 | Q23: 967675.51 | R23: 0.15 | S23: 241918.88 | T23: 0.0375
A24: - | B24: X - GAS | C24: Licencia | D24: Quincena | E24: F2 | F24: MM BTU | G24: 78337.056 | H24: 83546.768 | I24: 2.9 | J24: 2.9 | N24: 1410.94 | O24: 468052.15 | P24: 87759.78 | Q24: 70207.82 | R24: 0.15 | S24: 17551.96 | T24: 0.0375
A25: - | B25: XV | C25: Licencia | D25: Quincena | E25: F2 | F25: Bls | O25: 0 | P25: 0 | Q25: 0 | R25: 0.15 | S25: 0 | T25: 0.0375
A26: - | B26: XIII Crudo | C26: Licencia | D26: Quincena | E26: F2 | F26: Bls | G26: 0 | H26: 111.92584 | I26: 0 | J26: 66.2547 | N26: 2755.54 | O26: 4660.07 | P26: 873.76 | Q26: 699.01 | R26: 0.15 | S26: 174.75 | T26: 0.0375
A27: - | B27: XIII Gas | C27: Licencia | D27: Quincena | E27: F2 | F27: MM BTU | G27: 0 | H27: 3139.3894 | I27: 0 | J27: 1.8760081 | N27: 3201.4 | O27: 5889.52 | P27: 1104.28 | Q27: 883.43 | R27: 0.15 | S27: 220.85 | T27: 0.0375
A28: - | B28: XX | C28: Licencia | D28: Quincena | E28: F2 | F28: Bls | N28: 170.73 | O28: -170.73 | P28: -32.01 | Q28: -6.4 | R28: 0.0375 | S28: -25.61 | T28: 0.15
A29: - | B29: Z-1 Crudo | C29: Licencia | D29: Quincena | E29: F2 | F29: Bls | G29: 0 | I29: 0 | N29: 867.29 | O29: -867.29 | P29: -162.62 | Q29: -32.52 | R29: 0.0375 | S29: -130.09 | T29: 0.15
A30: - | B30: Z-69 Crudo | C30: Licencia | D30: Quincena | E30: F2 | F30: Bls | G30: 35004 | H30: 16048 | I30: 62.812 | J30: 66.4664 | N30: 3101.84 | O30: 3262222.2 | P30: 611666.66 | Q30: 489333.33 | R30: 0.15 | S30: 122333.33 | T30: 0.0375
A31: - | B31: Z-69 Gas | C31: Licencia | D31: Quincena | E31: F2 | F31: MM BTU | G31: 62721.31 | H31: 91186.15 | I31: 2.7369 | J31: 2.7369 | N31: 781.93 | O31: 729414.16 | P31: 136765.16 | Q31: 109412.12 | R31: 0.15 | S31: 27353.04 | T31: 0.0375
A32: - | B32: Z-69 Lgn | C32: Licencia | D32: Quincena | E32: F2 | F32: Bls | G32: 9918 | H32: 11227 | I32: 33.4131 | J32: 35.2918 | N32: 850.22 | O32: 726761.95 | P32: 136267.87 | Q32: 109014.29 | R32: 0.15 | S32: 27253.57 | T32: 0.0375
A33: - | B33: Ajustes meses anteriores (1) | O33: -36780.79 | P33: -6896.4 | Q33: -5517.12 | R33: 0 | S33: -1379.27
B34: Subtotal | C34: Piura / Tumbes US$ | O34: 14992373 | P34: 2811069.9 | Q34: 2248972.7 | S34: 562097.22 | T34: 0
C35: Piura / Tumbes S/. | P35: 9425517.4 | Q35: 7540805.5 | S35: 1884712
A36: Provincia Puerto Inca Huanuco | Q36: Puerto Inca
A37: - | B37: 131 | C37: Licencia | D37: Quincena | E37: F2 | F37: Bls | G37: 5289 | H37: 7195 | I37: 51.1484 | J37: 54.3 | N37: 3421.37 | O37: 657791.02 | P37: 98668.65 | Q37: 98668.65 | R37: 0.15
A38: - | B38: Ajustes meses anteriores (2) | O38: -517265.96 | P38: -77589.91 | Q38: -77589.91
B39: Subtotal | C39: Provincia Puerto Inca Huanuco US$ | O39: 140525.06 | P39: 21078.74 | Q39: 21078.74 | S39: 0
C40: Provincia Puerto Inca Huanuco S/. | P40: 70677.02 | Q40: 70677.02 | S40: 0
A41: Loreto / Ucayali | Q41: Loreto | S41: Ucayali
A42: - | B42: 8 | C42: Licencia | D42: Quincena | E42: F2 | F42: Bls | G42: 0 | H42: 118663 | I42: 0 | J42: 62.2353 | N42: 4585.73 | O42: 7380441.7 | P42: 1383832.8 | Q42: 1107066.2 | R42: 0.15 | S42: 276766.56 | T42: 0.0375
A43: - | B43: 31-C GAS | C43: Licencia | D43: Quincena | E43: F2 | F43: MM BTU | G43: 8333.5197 | H43: 30054.462 | I43: 3.6037 | J43: 3.6037 | N43: 1633.62 | O43: 136705.14 | P43: 25632.21 | Q43: 5126.44 | R43: 0.0375 | S43: 20505.77 | T43: 0.15
A44: - | B44: 31-C LGN (*) | C44: Licencia | D44: Quincena | E44: F3 | F44: Bls | N44: 2140.03 | O44: -2140.03 | P44: -401.26 | Q44: -80.25 | R44: 0.0375 | S44: -321 | T44: 0.15
A45: - | B45: 95 | C45: Licencia | D45: Quincena | E45: F2 | F45: Bls | G45: 228697 | H45: 231097 | I45: 42.6309 | J45: 45.725 | N45: 4585.73 | O45: 20311884 | P45: 3808478.2 | Q45: 3046782.5 | R45: 0.15 | S45: 761695.63 | T45: 0.0375
A46: - | B46: 67 | C46: Licencia | D46: Quincena | E46: F2 | F46: Bls | O46: 0 | P46: 0 | Q46: 0 | R46: 0.15 | S46: 0 | T46: 0.0375
A47: - | B47: Ajustes meses anteriores (3) | O47: 0 | P47: 0 | Q47: 0 | R47: 0 | S47: 0
B48: Subtotal | C48: Loreto / Ucayali US$ | O48: 27826890 | P48: 5217541.9 | Q48: 4158895 | S48: 1058647
C49: Loreto / Ucayali S/. | P49: 17494418 | Q49: 13944775 | S49: 3549643.3
A50: Cusco | P50: V. Regalías | Q50: Cusco
A51: - | B51: 88 LGN | C51: Licencia | D51: Quincena | E51: F4 | F51: Bls | G51: 703340 | H51: 737730 | I51: 31.7541 | J51: 34.0323 | N51: 2455.79 | O51: 47440577 | P51: 17666871 | Q51: 8833435.5 | R51: 0.5
A52: - | B52: 88 GAS | C52: Licencia | D52: Quincena | E52: F4 | F52: MM BTU | G52: 12597398 | H52: 13156941 | I52: 2.6982 | J52: 2.7661 | N52: 4258.92 | O52: 70383582 | P52: 26260558 | Q52: 13130279 | R52: 0.5
A53: - | B53: 56 LGN | C53: Licencia | D53: Quincena | E53: F4 | F53: Bls | G53: 167909 | H53: 176861 | I53: 31.755 | J53: 34.032 | N53: 1731.9 | O53: 11350884 | P53: 4540353.5 | Q53: 2270176.8 | R53: 0.5
A54: - | B54: 56 GAS | C54: Licencia | D54: Quincena | E54: F4 | F54: MM BTU | G54: 3802325 | H54: 4019439.8 | I54: 3.354 | J54: 4.371 | N54: 2440.18 | O54: 30321969 | P54: 11522348 | Q54: 5761174.2 | R54: 0.5
A55: - | B55: 57 LGN | C55: Licencia | D55: Quincena | E55: F4 | F55: Bls | G55: 236810 | H55: 221079 | I55: 30.1358 | J55: 32.0801 | N55: 758.76 | O55: 14228695 | P55: 953322.58 | Q55: 476661.29 | R55: 0.5
A56: - | B56: 57 GAS | C56: Licencia | D56: Quincena | E56: F4 | F56: MM BTU | G56: 3955331.8 | H56: 3695931.6 | I56: 3.488 | J56: 3.488 | N56: 1876.78 | O56: 26687607 | P56: 2974288.5 | Q56: 1487144.2 | R56: 0.5
A57: - | B57: Ajustes meses anteriores (4) | O57: 2815379.7 | P57: -471512.7 | Q57: -235756.35
B58: Subtotal | C58: Cusco US$ | G58: 3802325 | H58: 4019439.8 | O58: 2.0322869e+08 | P58: 63446229 | Q58: 31723115
C59: Cusco S/. | G59: 3.354 | H59: 4.371 | Q59: 1.063676e+08
A60: Total General | G60: 12752998 | H60: 17568971 | I60: 30321969 | J60: #REF! | K60: #REF! | M60: 0 | N60: 51557.02 | O60: 2.4618848e+08 | P60: 39772805 | Q60: 1.3335822e+08
A62: (*) | B62: Determinación de Canasta de los Líquidos de Gas Natural (VLGNF) | H62: = ( VC * %P + (PB - TF - TT) * (1 - %P)) | I62: = ( VC * %P + (PB - TF - TT) * (1 - %P)) | O62: 0.067
B63: Simbolo | C63: Descripcion | E63: 1ra. Q | F63: 2da. Q | H63: 1ra. Q | I63: 1ra. Q
B64: VC | C64: Canasta de Petróleo | H64: = (0.0000 * 0.00% + (0.0000 - 0.0000 - 0.0000) * (1 - 0.00%)) | I64: = (0.0000 * 0.00% + (0.0000 - 0.0000 - 0.0000) * (1 - 0.00%)) | N64: 0.064199999 | O64: 0.067 | P64: 0.065400001
B65: PB | C65: Precio del GLP | H65: 0 | I65: 0 | N65: 0.0989 | O65: 0.113 | P65: 0.1072
B66: TF | C66: Tarifa de Fraccionam. | N66: 0.4
B67: %P | C67: % Contenido Pentanos | H67: 2da. Q | I67: 2da. Q
B68: QLGNF | C68: Volumen de LGN | H68: = (0.0000 * 0.00% + (0.0000 - 0.0000 - 0.0000) * (1 - 0.00%)) | I68: = (0.0000 * 0.00% + (0.0000 - 0.0000 - 0.0000) * (1 - 0.00%)) | P68: 0.1114
B69: TT | C69: Tarifa de Transporte | H69: 0 | I69: 0

Sheet Ene(2)
A1: Período de Cálculo: | E1: 45322 | F1: 1 | U1: Días en el mes | W1: =DATE(YEAR(E1),MONTH(E1)+1,1)-DATE(YEAR(E1),MONTH(E1),1) -> 31
A2: PERUPETRO S.A.
A3: DETERMINACION DEL CANON, SOBRECANON y PARTICIPACION (US$)
A4: ="Correspondiente a "&TEXT(E1,"MMMMMMM YYYY") -> Correspondiente a Enero 2024
A5: ="Tipo de Cambio= "&TEXT(F1,"0.000") -> Tipo de Cambio= 1.000
A7: Localidad | C7: Modalidad de Contrato | D7: Calculo del Canon | F7: Volumen Producción / Venta | I7: Canasta o Valor Venta (US$/Unidad) | K7: Deducción de Gastos para determinación de valor de producción en Punto de Fiscalización (US$) | O7: Valor de la Producción (US$) | P7: Canon y Sobrecanon / Participación (US$) | U7: RESUMEN POR PETROLERO Y CONDENSADOS | AA7: RESUMEN POR GAS NATURAL | AG7: Control
A8: - Lote | D8: Período | E8: Fórmula | F8: Unidades | G8: 1ra. Q | H8: 2da. Q / Mes | I8: 1ra. Q | J8: 2da. Q / Mes | K8: Flete Marítimo | L8: Comercialización | M8: Oleoducto | N8: Fiscalización | P8: Total | Q8: Localidad 1 | S8: Localidad 2 | U8: Producción / Venta | X8: Valor Prod | Y8: Valor Canon | AA8: Producción / Venta | AD8: Valor Prod | AE8: Valor Canon | AG8: Total
A9: Piura / Tumbes | Q9: Piura | S9: Tumbes | U9: Bls/Mes | V9: V P (US$) | W9: Bls/Día | X9: US$/Bl | Y9: US$/Bl | Z9: US$ | AA9: MM BTU/Mes | AB9: V P (US$) | AC9: MM BTU/Día | AD9: US$/MM BTU | AE9: US$/MM BTU | AF9: US$ | AG9: Canon
A10: - | B10: I | C10: Servicios | D10: Mes | E10: F1 | F10: Bls | G10: 5090 | H10: 9219 | I10: 77.8038 | J10: 80.8319 | N10: 90.97 | O10: =ROUND(G10*I10,2)+ROUND(H10*J10,2)-K10-L10-M10-N10 -> 1141119.7 | P10: =ROUND(18.75%*O10,2) -> 213959.94 | Q10: =ROUND($O10*R10,2) -> 171167.95 | R10: 0.15 | S10: =ROUND($O10*T10,2) -> 42791.99 | T10: 0.0375 | U10: =IF($F10&"/Día"=W$9,SUM($G10:$H10),"") -> 14309 | V10: =IF(U10<>"",$O10,"") -> 1141119.7 | W10: =IF($F10&"/Día"=W$9,ROUND(U10/$W$1,1),"") -> 461.6 | X10: =IF(U10=0,0,IF($F10&"/Día"=W$9,ROUND(V10/U10,4),"")) -> 79.7484 | Y10: =IF(U10=0,0,IF($F10&"/Día"=W$9,ROUND(Z10/U10,4),"")) -> 14.9528 | Z10: =IF(U10<>"",$P10,"") -> 213959.94 | AA10: =IF($F10&"/Día"=AC$9,SUM($G10:$H10),"") | AB10: =IF(AA10<>"",$O10,"") | AC10: =IF($F10&"/Día"=AC$9,ROUND(AA10/$W$1,1),"") | AD10: =IF(AA10=0,0,IF($F10&"/Día"=AC$9,ROUND(AB10/AA10,4),"")) | AE10: =IF(AA10=0,0,IF($F10&"/Día"=AC$9,ROUND(AF10/AA10,4),"")) | AF10: =IF(AA10<>"",$P10,"")
A11: - | B11: I GAS | C11: Servicios | D11: Mes | E11: F1 | F11: MM BTU | G11: 46748.626 | H11: 49502.049 | I11: 4 | J11: 4 | N11: 254.71 | O11: =ROUND(G11*I11,2)+ROUND(H11*J11,2)-K11-L11-M11-N11 -> 384748 | P11: =ROUND(18.75%*O11,2) -> 72140.25 | Q11: =ROUND($O11*R11,2) -> 57712.2 | R11: 0.15 | S11: =ROUND($O11*T11,2) -> 14428.05 | T11: 0.0375 | U11: =IF($F11&"/Día"=W$9,SUM($G11:$H11),"") | V11: =IF(U11<>"",$O11,"") | W11: =IF($F11&"/Día"=W$9,ROUND(U11/$W$1,1),"") | X11: =IF(U11=0,0,IF($F11&"/Día"=W$9,ROUND(V11/U11,4),"")) | Y11: =IF(U11=0,0,IF($F11&"/Día"=W$9,ROUND(Z11/U11,4),"")) | Z11: =IF(U11<>"",$P11,"") | AA11: =IF($F11&"/Día"=AC$9,SUM($G11:$H11),"") -> 96250.676 | AB11: =IF(AA11<>"",$O11,"") -> 384748 | AC11: =IF($F11&"/Día"=AC$9,ROUND(AA11/$W$1,1),"") -> 3104.9 | AD11: =IF(AA11=0,0,IF($F11&"/Día"=AC$9,ROUND(AB11/AA11,4),"")) -> 3.9974 | AE11: =IF(AA11=0,0,IF($F11&"/Día"=AC$9,ROUND(AF11/AA11,4),"")) -> 0.7495 | AF11: =IF(AA11<>"",$P11,"") -> 72140.25
A12: - | B12: II | C12: Licencia | D12: Quincena | E12: F2 | F12: Bls | G12: 7222 | H12: 8503 | I12: 78.3628 | J12: 80.8431 | N12: 731.38 | O12: =ROUND(G12*I12,2)+ROUND(H12*J12,2)-K12-L12-M12-N12 -> 1252613.6 | P12: =ROUND(18.75%*O12,2) -> 234865.06 | Q12: =ROUND($O12*R12,2) -> 187892.05 | R12: 0.15 | S12: =ROUND($O12*T12,2) -> 46973.01 | T12: 0.0375 | U12: =IF($F12&"/Día"=W$9,SUM($G12:$H12),"") -> 15725 | V12: =IF(U12<>"",$O12,"") -> 1252613.6 | W12: =IF($F12&"/Día"=W$9,ROUND(U12/$W$1,1),"") -> 507.3 | X12: =IF(U12=0,0,IF($F12&"/Día"=W$9,ROUND(V12/U12,4),"")) -> 79.6575 | Y12: =IF(U12=0,0,IF($F12&"/Día"=W$9,ROUND(Z12/U12,4),"")) -> 14.9358 | Z12: =IF(U12<>"",$P12,"") -> 234865.06 | AA12: =IF($F12&"/Día"=AC$9,SUM($G12:$H12),"") | AB12: =IF(AA12<>"",$O12,"") | AC12: =IF($F12&"/Día"=AC$9,ROUND(AA12/$W$1,1),"") | AD12: =IF(AA12=0,0,IF($F12&"/Día"=AC$9,ROUND(AB12/AA12,4),"")) | AE12: =IF(AA12=0,0,IF($F12&"/Día"=AC$9,ROUND(AF12/AA12,4),"")) | AF12: =IF(AA12<>"",$P12,"")
A13: - | B13: II-GAS | C13: Servicios | D13: Mes | E13: F1 | F13: MM BTU | G13: 19136.188 | H13: 14569.777 | I13: 2.8114 | J13: 2.8114 | N13: 782.32 | O13: =ROUND(G13*I13,2)+ROUND(H13*J13,2)-K13-L13-M13-N13 -> 93978.63 | P13: =ROUND(18.75%*O13,2) -> 17620.99 | Q13: =ROUND($O13*R13,2) -> 14096.79 | R13: 0.15 | S13: =ROUND($O13*T13,2) -> 3524.2 | T13: 0.0375 | U13: =IF($F13&"/Día"=W$9,SUM($G13:$H13),"") | V13: =IF(U13<>"",$O13,"") | W13: =IF($F13&"/Día"=W$9,ROUND(U13/$W$1,1),"") | X13: =IF(U13=0,0,IF($F13&"/Día"=W$9,ROUND(V13/U13,4),"")) | Y13: =IF(U13=0,0,IF($F13&"/Día"=W$9,ROUND(Z13/U13,4),"")) | Z13: =IF(U13<>"",$P13,"") | AA13: =IF($F13&"/Día"=AC$9,SUM($G13:$H13),"") -> 33705.965 | AB13: =IF(AA13<>"",$O13,"") -> 93978.63 | AC13: =IF($F13&"/Día"=AC$9,ROUND(AA13/$W$1,1),"") -> 1087.3 | AD13: =IF(AA13=0,0,IF($F13&"/Día"=AC$9,ROUND(AB13/AA13,4),"")) -> 2.7882 | AE13: =IF(AA13=0,0,IF($F13&"/Día"=AC$9,ROUND(AF13/AA13,4),"")) -> 0.5228 | AF13: =IF(AA13<>"",$P13,"") -> 17620.99
A14: - | B14: III | C14: Licencia | D14: Quincena | E14: F2 | F14: Bls | G14: 23259 | H14: 25725 | I14: 77.8038 | J14: 80.8319 | N14: 1022.61 | O14: =ROUND(G14*I14,2)+ROUND(H14*J14,2)-K14-L14-M14-N14 -> 3888016.6 | P14: =ROUND(18.75%*O14,2) -> 729003.11 | Q14: =ROUND($O14*R14,2) -> 583202.49 | R14: 0.15 | S14: =ROUND($O14*T14,2) -> 145800.62 | T14: 0.0375 | U14: =IF($F14&"/Día"=W$9,SUM($G14:$H14),"") -> 48984 | V14: =IF(U14<>"",$O14,"") -> 3888016.6 | W14: =IF($F14&"/Día"=W$9,ROUND(U14/$W$1,1),"") -> 1580.1 | X14: =IF(U14=0,0,IF($F14&"/Día"=W$9,ROUND(V14/U14,4),"")) -> 79.3732 | Y14: =IF(U14=0,0,IF($F14&"/Día"=W$9,ROUND(Z14/U14,4),"")) -> 14.8825 | Z14: =IF(U14<>"",$P14,"") -> 729003.11 | AA14: =IF($F14&"/Día"=AC$9,SUM($G14:$H14),"") | AB14: =IF(AA14<>"",$O14,"") | AC14: =IF($F14&"/Día"=AC$9,ROUND(AA14/$W$1,1),"") | AD14: =IF(AA14=0,0,IF($F14&"/Día"=AC$9,ROUND(AB14/AA14,4),"")) | AE14: =IF(AA14=0,0,IF($F14&"/Día"=AC$9,ROUND(AF14/AA14,4),"")) | AF14: =IF(AA14<>"",$P14,"")
A15: - | B15: III-GAS | C15: Servicios | D15: Mes | E15: F1 | F15: MM BTU | G15: 8348.9928 | H15: 1540.6733 | I15: 3.21 | J15: 3.2 | O15: =ROUND(G15*I15,2)+ROUND(H15*J15,2)-K15-L15-M15-N15 -> 31730.42 | P15: =ROUND(18.75%*O15,2) -> 5949.45 | Q15: =ROUND($O15*R15,2) -> 36489.98 | R15: 1.15 | S15: =ROUND($O15*T15,2) -> 1189.89 | T15: 0.0375
A16: - | B16: IV | C16: Licencia | D16: Quincena | E16: F2 | F16: Bls | G16: 32708 | H16: 34926 | I16: 77.8038 | J16: 80.8319 | N16: 1848.59 | O16: =ROUND(G16*I16,2)+ROUND(H16*J16,2)-K16-L16-M16-N16 -> 5366093 | P16: =ROUND(18.75%*O16,2) -> 1006142.4 | Q16: =ROUND($O16*R16,2) -> 804913.96 | R16: 0.15 | S16: =ROUND($O16*T16,2) -> 201228.49 | T16: 0.0375 | U16: =IF($F16&"/Día"=W$9,SUM($G16:$H16),"") -> 67634 | V16: =IF(U16<>"",$O16,"") -> 5366093 | W16: =IF($F16&"/Día"=W$9,ROUND(U16/$W$1,1),"") -> 2181.7 | X16: =IF(U16=0,0,IF($F16&"/Día"=W$9,ROUND(V16/U16,4),"")) -> 79.3402 | Y16: =IF(U16=0,0,IF($F16&"/Día"=W$9,ROUND(Z16/U16,4),"")) -> 14.8763 | Z16: =IF(U16<>"",$P16,"") -> 1006142.4 | AA16: =IF($F16&"/Día"=AC$9,SUM($G16:$H16),"") | AB16: =IF(AA16<>"",$O16,"") | AC16: =IF($F16&"/Día"=AC$9,ROUND(AA16/$W$1,1),"") | AD16: =IF(AA16=0,0,IF($F16&"/Día"=AC$9,ROUND(AB16/AA16,4),"")) | AE16: =IF(AA16=0,0,IF($F16&"/Día"=AC$9,ROUND(AF16/AA16,4),"")) | AF16: =IF(AA16<>"",$P16,"")
A17: - | B17: IV-GAS | C17: Licencia | D17: Quincena | E17: F2 | F17: Bls | G17: 31444.218 | H17: 46042.529 | I17: 3.8094 | J17: 3.8094 | N17: 502.28 | O17: =ROUND(G17*I17,2)+ROUND(H17*J17,2)-K17-L17-M17-N17 -> 294675.73 | P17: =ROUND(18.75%*O17,2) -> 55251.7 | Q17: =ROUND($O17*R17,2) -> 44201.36 | R17: 0.15 | S17: =ROUND($O17*T17,2) -> 11050.34 | T17: 0.0375 | U17: =IF($F17&"/Día"=W$9,SUM($G17:$H17),"") -> 77486.747 | V17: =IF(U17<>"",$O17,"") -> 294675.73 | W17: =IF($F17&"/Día"=W$9,ROUND(U17/$W$1,1),"") -> 2499.6 | X17: =IF(U17=0,0,IF($F17&"/Día"=W$9,ROUND(V17/U17,4),"")) -> 3.8029 | Y17: =IF(U17=0,0,IF($F17&"/Día"=W$9,ROUND(Z17/U17,4),"")) -> 0.713 | Z17: =IF(U17<>"",$P17,"") -> 55251.7 | AA17: =IF($F17&"/Día"=AC$9,SUM($G17:$H17),"") | AB17: =IF(AA17<>"",$O17,"") | AC17: =IF($F17&"/Día"=AC$9,ROUND(AA17/$W$1,1),"") | AD17: =IF(AA17=0,0,IF($F17&"/Día"=AC$9,ROUND(AB17/AA17,4),"")) | AE17: =IF(AA17=0,0,IF($F17&"/Día"=AC$9,ROUND(AF17/AA17,4),"")) | AF17: =IF(AA17<>"",$P17,"")
A18: - | B18: V | C18: Servicios | D18: Mes | E18: F1 | F18: Bls | G18: 395 | H18: 1778 | I18: 76.817 | J18: 80.1679 | N18: 476.67 | O18: =ROUND(G18*I18,2)+ROUND(H18*J18,2)-K18-L18-M18-N18 -> 172404.58 | P18: =ROUND(18.75%*O18,2) -> 32325.86 | Q18: =ROUND($O18*R18,2) -> 25860.69 | R18: 0.15 | S18: =ROUND($O18*T18,2) -> 6465.17 | T18: 0.0375 | U18: =IF($F18&"/Día"=W$9,SUM($G18:$H18),"") -> 2173 | V18: =IF(U18<>"",$O18,"") -> 172404.58 | W18: =IF($F18&"/Día"=W$9,ROUND(U18/$W$1,1),"") -> 70.1 | X18: =IF(U18=0,0,IF($F18&"/Día"=W$9,ROUND(V18/U18,4),"")) -> 79.3394 | Y18: =IF(U18=0,0,IF($F18&"/Día"=W$9,ROUND(Z18/U18,4),"")) -> 14.8761 | Z18: =IF(U18<>"",$P18,"") -> 32325.86 | AA18: =IF($F18&"/Día"=AC$9,SUM($G18:$H18),"") | AB18: =IF(AA18<>"",$O18,"") | AC18: =IF($F18&"/Día"=AC$9,ROUND(AA18/$W$1,1),"") | AD18: =IF(AA18=0,0,IF($F18&"/Día"=AC$9,ROUND(AB18/AA18,4),"")) | AE18: =IF(AA18=0,0,IF($F18&"/Día"=AC$9,ROUND(AF18/AA18,4),"")) | AF18: =IF(AA18<>"",$P18,"")
A19: - | B19: VI (T) | C19: Licencia | D19: Quincena | E19: F1 | F19: Bls | G19: 26354 | H19: 34223 | I19: 77.8038 | J19: 80.8319 | N19: 574.91 | O19: =ROUND(G19*I19,2)+ROUND(H19*J19,2)-K19-L19-M19-N19 -> 4816176.5 | P19: =ROUND(18.75%*O19,2) -> 903033.1 | Q19: =ROUND($O19*R19,2) -> 722426.48 | R19: 0.15 | S19: =ROUND($O19*T19,2) -> 180606.62 | T19: 0.0375 | U19: =IF($F19&"/Día"=W$9,SUM($G19:$H19),"") -> 60577 | V19: =IF(U19<>"",$O19,"") -> 4816176.5 | W19: =IF($F19&"/Día"=W$9,ROUND(U19/$W$1,1),"") -> 1954.1 | X19: =IF(U19=0,0,IF($F19&"/Día"=W$9,ROUND(V19/U19,4),"")) -> 79.505 | Y19: =IF(U19=0,0,IF($F19&"/Día"=W$9,ROUND(Z19/U19,4),"")) -> 14.9072 | Z19: =IF(U19<>"",$P19,"") -> 903033.1 | AA19: =IF($F19&"/Día"=AC$9,SUM($G19:$H19),"") | AB19: =IF(AA19<>"",$O19,"") | AC19: =IF($F19&"/Día"=AC$9,ROUND(AA19/$W$1,1),"") | AD19: =IF(AA19=0,0,IF($F19&"/Día"=AC$9,ROUND(AB19/AA19,4),"")) | AE19: =IF(AA19=0,0,IF($F19&"/Día"=AC$9,ROUND(AF19/AA19,4),"")) | AF19: =IF(AA19<>"",$P19,"")
A20: - | B20: VI - GAS | C20: Licencia | D20: Quincena | E20: F1 | F20: MM BTU | G20: 57353.288 | H20: 60657.671 | I20: 4 | J20: 4 | N20: 247.43 | O20: =ROUND(G20*I20,2)+ROUND(H20*J20,2)-K20-L20-M20-N20 -> 471796.4 | P20: =ROUND(18.75%*O20,2) -> 88461.83 | Q20: =ROUND($O20*R20,2) -> 70769.46 | R20: 0.15 | S20: =ROUND($O20*T20,2) -> 17692.37 | T20: 0.0375 | U20: =IF($F20&"/Día"=W$9,SUM($G20:$H20),"") | V20: =IF(U20<>"",$O20,"") | W20: =IF($F20&"/Día"=W$9,ROUND(U20/$W$1,1),"") | X20: =IF(U20=0,0,IF($F20&"/Día"=W$9,ROUND(V20/U20,4),"")) | Y20: =IF(U20=0,0,IF($F20&"/Día"=W$9,ROUND(Z20/U20,4),"")) | Z20: =IF(U20<>"",$P20,"") | AA20: =IF($F20&"/Día"=AC$9,SUM($G20:$H20),"") -> 118010.96 | AB20: =IF(AA20<>"",$O20,"") -> 471796.4 | AC20: =IF($F20&"/Día"=AC$9,ROUND(AA20/$W$1,1),"") -> 3806.8 | AD20: =IF(AA20=0,0,IF($F20&"/Día"=AC$9,ROUND(AB20/AA20,4),"")) -> 3.9979 | AE20: =IF(AA20=0,0,IF($F20&"/Día"=AC$9,ROUND(AF20/AA20,4),"")) -> 0.7496 | AF20: =IF(AA20<>"",$P20,"") -> 88461.83
A21: - | B21: VII (T) | C21: Licencia | D21: Quincena | E21: F1 | F21: Bls | G21: 12900 | H21: 14290 | I21: 76.817 | J21: 80.1679 | N21: 283.82 | O21: =ROUND(G21*I21,2)+ROUND(H21*J21,2)-K21-L21-M21-N21 -> 2136254.8 | P21: =ROUND(18.75%*O21,2) -> 400547.77 | Q21: =ROUND($O21*R21,2) -> 320438.22 | R21: 0.15 | S21: =ROUND($O21*T21,2) -> 80109.55 | T21: 0.0375 | U21: =IF($F21&"/Día"=W$9,SUM($G21:$H21),"") -> 27190 | V21: =IF(U21<>"",$O21,"") -> 2136254.8 | W21: =IF($F21&"/Día"=W$9,ROUND(U21/$W$1,1),"") -> 877.1 | X21: =IF(U21=0,0,IF($F21&"/Día"=W$9,ROUND(V21/U21,4),"")) -> 78.5677 | Y21: =IF(U21=0,0,IF($F21&"/Día"=W$9,ROUND(Z21/U21,4),"")) -> 14.7314 | Z21: =IF(U21<>"",$P21,"") -> 400547.77 | AA21: =IF($F21&"/Día"=AC$9,SUM($G21:$H21),"") | AB21: =IF(AA21<>"",$O21,"") | AC21: =IF($F21&"/Día"=AC$9,ROUND(AA21/$W$1,1),"") | AD21: =IF(AA21=0,0,IF($F21&"/Día"=AC$9,ROUND(AB21/AA21,4),"")) | AE21: =IF(AA21=0,0,IF($F21&"/Día"=AC$9,ROUND(AF21/AA21,4),"")) | AF21: =IF(AA21<>"",$P21,"")
A22: - | B22: VII/VI | C22: Licencia | D22: Quincena | E22: F2 | F22: Bls | O22: =ROUND(G22*I22,2)+ROUND(H22*J22,2)-K22-L22-M22-N22 -> 0 | P22: =ROUND(18.75%*O22,2) -> 0 | Q22: =ROUND($O22*R22,2) -> 0 | R22: 0.15 | S22: =ROUND($O22*T22,2) -> 0 | T22: 0.0375 | U22: =IF($F22&"/Día"=W$9,SUM($G22:$H22),"") -> 0 | V22: =IF(U22<>"",$O22,"") -> 0 | W22: =IF($F22&"/Día"=W$9,ROUND(U22/$W$1,1),"") -> 0 | X22: =IF(U22=0,0,IF($F22&"/Día"=W$9,ROUND(V22/U22,4),"")) -> 0 | Y22: =IF(U22=0,0,IF($F22&"/Día"=W$9,ROUND(Z22/U22,4),"")) -> 0 | Z22: =IF(U22<>"",$P22,"") -> 0 | AA22: =IF($F22&"/Día"=AC$9,SUM($G22:$H22),"") | AB22: =IF(AA22<>"",$O22,"") | AC22: =IF($F22&"/Día"=AC$9,ROUND(AA22/$W$1,1),"") | AD22: =IF(AA22=0,0,IF($F22&"/Día"=AC$9,ROUND(AB22/AA22,4),"")) | AE22: =IF(AA22=0,0,IF($F22&"/Día"=AC$9,ROUND(AF22/AA22,4),"")) | AF22: =IF(AA22<>"",$P22,"")
A23: - | B23: VII/VI-GAS | C23: Licencia | D23: Quincena | E23: F2 | F23: MM BTU | O23: =ROUND(G23*I23,2)+ROUND(H23*J23,2)-K23-L23-M23-N23 -> 0 | P23: =ROUND(18.75%*O23,2) -> 0 | Q23: =ROUND($O23*R23,2) -> 0 | R23: 0.15 | S23: =ROUND($O23*T23,2) -> 0 | T23: 0.0375 | U23: =IF($F23&"/Día"=W$9,SUM($G23:$H23),"") | V23: =IF(U23<>"",$O23,"") | W23: =IF($F23&"/Día"=W$9,ROUND(U23/$W$1,1),"") | X23: =IF(U23=0,0,IF($F23&"/Día"=W$9,ROUND(V23/U23,4),"")) | Y23: =IF(U23=0,0,IF($F23&"/Día"=W$9,ROUND(Z23/U23,4),"")) | Z23: =IF(U23<>"",$P23,"") | AA23: =IF($F23&"/Día"=AC$9,SUM($G23:$H23),"") -> 0 | AB23: =IF(AA23<>"",$O23,"") -> 0 | AC23: =IF($F23&"/Día"=AC$9,ROUND(AA23/$W$1,1),"") -> 0 | AD23: =IF(AA23=0,0,IF($F23&"/Día"=AC$9,ROUND(AB23/AA23,4),"")) -> 0 | AE23: =IF(AA23=0,0,IF($F23&"/Día"=AC$9,ROUND(AF23/AA23,4),"")) -> 0 | AF23: =IF(AA23<>"",$P23,"") -> 0
A24: - | B24: IX | C24: Licencia | D24: Quincena | E24: F2 | F24: Bls | G24: 2064 | H24: 2803 | I24: 77.8038 | J24: 80.8319 | N24: 305.65 | O24: =ROUND(G24*I24,2)+ROUND(H24*J24,2)-K24-L24-M24-N24 -> 386853.21 | P24: =ROUND(18.75%*O24,2) -> 72534.98 | Q24: =ROUND($O24*R24,2) -> 58027.98 | R24: 0.15 | S24: =ROUND($O24*T24,2) -> 14507 | T24: 0.0375 | U24: =IF($F24&"/Día"=W$9,SUM($G24:$H24),"") -> 4867 | V24: =IF(U24<>"",$O24,"") -> 386853.21 | W24: =IF($F24&"/Día"=W$9,ROUND(U24/$W$1,1),"") -> 157 | X24: =IF(U24=0,0,IF($F24&"/Día"=W$9,ROUND(V24/U24,4),"")) -> 79.4849 | Y24: =IF(U24=0,0,IF($F24&"/Día"=W$9,ROUND(Z24/U24,4),"")) -> 14.9034 | Z24: =IF(U24<>"",$P24,"") -> 72534.98 | AA24: =IF($F24&"/Día"=AC$9,SUM($G24:$H24),"") | AB24: =IF(AA24<>"",$O24,"") | AC24: =IF($F24&"/Día"=AC$9,ROUND(AA24/$W$1,1),"") | AD24: =IF(AA24=0,0,IF($F24&"/Día"=AC$9,ROUND(AB24/AA24,4),"")) | AE24: =IF(AA24=0,0,IF($F24&"/Día"=AC$9,ROUND(AF24/AA24,4),"")) | AF24: =IF(AA24<>"",$P24,"")
A25: - | B25: X | C25: Licencia | D25: Quincena | E25: F2 | F25: Bls | G25: 134323 | H25: 140232 | I25: 77.8038 | J25: 80.8319 | N25: 5203.47 | O25: =ROUND(G25*I25,2)+ROUND(H25*J25,2)-K25-L25-M25-N25 -> 21780855 | P25: =ROUND(18.75%*O25,2) -> 4083910.4 | Q25: =ROUND($O25*R25,2) -> 3267128.3 | R25: 0.15 | S25: =ROUND($O25*T25,2) -> 816782.08 | T25: 0.0375 | U25: =IF($F25&"/Día"=W$9,SUM($G25:$H25),"") -> 274555 | V25: =IF(U25<>"",$O25,"") -> 21780855 | W25: =IF($F25&"/Día"=W$9,ROUND(U25/$W$1,1),"") -> 8856.6 | X25: =IF(U25=0,0,IF($F25&"/Día"=W$9,ROUND(V25/U25,4),"")) -> 79.3315 | Y25: =IF(U25=0,0,IF($F25&"/Día"=W$9,ROUND(Z25/U25,4),"")) -> 14.8747 | Z25: =IF(U25<>"",$P25,"") -> 4083910.4 | AA25: =IF($F25&"/Día"=AC$9,SUM($G25:$H25),"") | AB25: =IF(AA25<>"",$O25,"") | AC25: =IF($F25&"/Día"=AC$9,ROUND(AA25/$W$1,1),"") | AD25: =IF(AA25=0,0,IF($F25&"/Día"=AC$9,ROUND(AB25/AA25,4),"")) | AE25: =IF(AA25=0,0,IF($F25&"/Día"=AC$9,ROUND(AF25/AA25,4),"")) | AF25: =IF(AA25<>"",$P25,"")
A26: - | B26: X-GAS | C26: Licencia | D26: Mes | E26: F2 | F26: MM BTU | G26: 216678.83 | H26: 229636.87 | I26: 2.7745 | J26: 2.5787 | N26: 1430.14 | O26: =ROUND(G26*I26,2)+ROUND(H26*J26,2)-K26-L26-M26-N26 -> 1191909.9 | P26: =ROUND(18.75%*O26,2) -> 223483.1 | Q26: =ROUND($O26*R26,2) -> 178786.48 | R26: 0.15 | S26: =ROUND($O26*T26,2) -> 44696.62 | T26: 0.0375 | U26: =IF($F26&"/Día"=W$9,SUM($G26:$H26),"") | V26: =IF(U26<>"",$O26,"") | W26: =IF($F26&"/Día"=W$9,ROUND(U26/$W$1,1),"") | X26: =IF(U26=0,0,IF($F26&"/Día"=W$9,ROUND(V26/U26,4),"")) | Y26: =IF(U26=0,0,IF($F26&"/Día"=W$9,ROUND(Z26/U26,4),"")) | Z26: =IF(U26<>"",$P26,"") | AA26: =IF($F26&"/Día"=AC$9,SUM($G26:$H26),"") -> 446315.7 | AB26: =IF(AA26<>"",$O26,"") -> 1191909.9 | AC26: =IF($F26&"/Día"=AC$9,ROUND(AA26/$W$1,1),"") -> 14397.3 | AD26: =IF(AA26=0,0,IF($F26&"/Día"=AC$9,ROUND(AB26/AA26,4),"")) -> 2.6706 | AE26: =IF(AA26=0,0,IF($F26&"/Día"=AC$9,ROUND(AF26/AA26,4),"")) -> 0.5007 | AF26: =IF(AA26<>"",$P26,"") -> 223483.1
A27: - | B27: XV | C27: Licencia | D27: Quincena | E27: F2 | F27: Bls | G27: 319 | H27: 406 | I27: 77.4687 | J27: 80.3056 | N27: 331.12 | O27: =ROUND(G27*I27,2)+ROUND(H27*J27,2)-K27-L27-M27-N27 -> 56985.47 | P27: =ROUND(18.75%*O27,2) -> 10684.78 | Q27: =ROUND($O27*R27,2) -> 8547.82 | R27: 0.15 | S27: =ROUND($O27*T27,2) -> 2136.96 | T27: 0.0375 | U27: =IF($F27&"/Día"=W$9,SUM($G27:$H27),"") -> 725 | V27: =IF(U27<>"",$O27,"") -> 56985.47 | W27: =IF($F27&"/Día"=W$9,ROUND(U27/$W$1,1),"") -> 23.4 | X27: =IF(U27=0,0,IF($F27&"/Día"=W$9,ROUND(V27/U27,4),"")) -> 78.6006 | Y27: =IF(U27=0,0,IF($F27&"/Día"=W$9,ROUND(Z27/U27,4),"")) -> 14.7376 | Z27: =IF(U27<>"",$P27,"") -> 10684.78 | AA27: =IF($F27&"/Día"=AC$9,SUM($G27:$H27),"") | AB27: =IF(AA27<>"",$O27,"") | AC27: =IF($F27&"/Día"=AC$9,ROUND(AA27/$W$1,1),"") | AD27: =IF(AA27=0,0,IF($F27&"/Día"=AC$9,ROUND(AB27/AA27,4),"")) | AE27: =IF(AA27=0,0,IF($F27&"/Día"=AC$9,ROUND(AF27/AA27,4),"")) | AF27: =IF(AA27<>"",$P27,"")
A28: - | B28: XIII Crudo | C28: Licencia | D28: Quincena | E28: F2 | F28: Bls | G28: 20465 | H28: 20994 | I28: 76.0938 | J28: 80.7919 | N28: 3154.75 | O28: =ROUND(G28*I28,2)+ROUND(H28*J28,2)-K28-L28-M28-N28 -> 3250250 | P28: =ROUND(18.75%*O28,2) -> 609421.88 | Q28: =ROUND($O28*R28,2) -> 487537.5 | R28: 0.15 | S28: =ROUND($O28*T28,2) -> 121884.38 | T28: 0.0375 | U28: =IF($F28&"/Día"=W$9,SUM($G28:$H28),"") -> 41459 | V28: =IF(U28<>"",$O28,"") -> 3250250 | W28: =IF($F28&"/Día"=W$9,ROUND(U28/$W$1,1),"") -> 1337.4 | X28: =IF(U28=0,0,IF($F28&"/Día"=W$9,ROUND(V28/U28,4),"")) -> 78.3967 | Y28: =IF(U28=0,0,IF($F28&"/Día"=W$9,ROUND(Z28/U28,4),"")) -> 14.6994 | Z28: =IF(U28<>"",$P28,"") -> 609421.88 | AA28: =IF($F28&"/Día"=AC$9,SUM($G28:$H28),"") | AB28: =IF(AA28<>"",$O28,"") | AC28: =IF($F28&"/Día"=AC$9,ROUND(AA28/$W$1,1),"") | AD28: =IF(AA28=0,0,IF($F28&"/Día"=AC$9,ROUND(AB28/AA28,4),"")) | AE28: =IF(AA28=0,0,IF($F28&"/Día"=AC$9,ROUND(AF28/AA28,4),"")) | AF28: =IF(AA28<>"",$P28,"")
A29: - | B29: XIII COND | C29: Licencia | D29: Quincena | E29: F2 | F29: Bls | O29: =ROUND(G29*I29,2)+ROUND(H29*J29,2)-K29-L29-M29-N29 -> 0 | P29: =ROUND(18.75%*O29,2) -> 0 | Q29: =ROUND($O29*R29,2) -> 0 | R29: 0.15 | S29: =ROUND($O29*T29,2) -> 0 | T29: 0.0375 | U29: =IF($F29&"/Día"=W$9,SUM($G29:$H29),"") -> 0 | V29: =IF(U29<>"",$O29,"") -> 0 | W29: =IF($F29&"/Día"=W$9,ROUND(U29/$W$1,1),"") -> 0 | X29: =IF(U29=0,0,IF($F29&"/Día"=W$9,ROUND(V29/U29,4),"")) -> 0 | Y29: =IF(U29=0,0,IF($F29&"/Día"=W$9,ROUND(Z29/U29,4),"")) -> 0 | Z29: =IF(U29<>"",$P29,"") -> 0 | AA29: =IF($F29&"/Día"=AC$9,SUM($G29:$H29),"") | AB29: =IF(AA29<>"",$O29,"") | AC29: =IF($F29&"/Día"=AC$9,ROUND(AA29/$W$1,1),"") | AD29: =IF(AA29=0,0,IF($F29&"/Día"=AC$9,ROUND(AB29/AA29,4),"")) | AE29: =IF(AA29=0,0,IF($F29&"/Día"=AC$9,ROUND(AF29/AA29,4),"")) | AF29: =IF(AA29<>"",$P29,"")
A30: - | B30: XIII Gas | C30: Licencia | D30: Quincena | E30: F2 | F30: MM BTU | G30: =G134 -> 390810.16 | H30: =H145 -> 462867.74 | I30: =I134 -> 2.7545969 | J30: =J145 -> 2.8300577 | N30: =N124 -> 1309.93 | O30: =O124 -> 2386466.9 | P30: =P124 -> 447462.53 | Q30: =Q124 -> 357970.02 | R30: 0.15 | S30: =S124 -> 89492.51 | T30: 0.0375 | U30: =IF($F30&"/Día"=W$9,SUM($G30:$H30),"") | V30: =IF(U30<>"",$O30,"") | W30: =IF($F30&"/Día"=W$9,ROUND(U30/$W$1,1),"") | X30: =IF(U30=0,0,IF($F30&"/Día"=W$9,ROUND(V30/U30,4),"")) | Y30: =IF(U30=0,0,IF($F30&"/Día"=W$9,ROUND(Z30/U30,4),"")) | Z30: =IF(U30<>"",$P30,"") | AA30: =IF($F30&"/Día"=AC$9,SUM($G30:$H30),"") -> 853677.89 | AB30: =IF(AA30<>"",$O30,"") -> 2386466.9 | AC30: =IF($F30&"/Día"=AC$9,ROUND(AA30/$W$1,1),"") -> 27538 | AD30: =IF(AA30=0,0,IF($F30&"/Día"=AC$9,ROUND(AB30/AA30,4),"")) -> 2.7955 | AE30: =IF(AA30=0,0,IF($F30&"/Día"=AC$9,ROUND(AF30/AA30,4),"")) -> 0.5242 | AF30: =IF(AA30<>"",$P30,"") -> 447462.53
A31: - | B31: Z-2B | C31: Servicios | D31: Mes | E31: F1 | F31: Bls | O31: =ROUND(G31*I31,2)+ROUND(H31*J31,2)-K31-L31-M31-N31 -> 0 | P31: =ROUND(18.75%*O31,2) -> 0 | Q31: =ROUND($O31*R31,2) -> 0 | R31: 0.15 | S31: =ROUND($O31*T31,2) -> 0 | T31: 0.0375 | U31: =IF($F31&"/Día"=W$9,SUM($G31:$H31),"") -> 0 | V31: =IF(U31<>"",$O31,"") -> 0 | W31: =IF($F31&"/Día"=W$9,ROUND(U31/$W$1,1),"") -> 0 | X31: =IF(U31=0,0,IF($F31&"/Día"=W$9,ROUND(V31/U31,4),"")) -> 0 | Y31: =IF(U31=0,0,IF($F31&"/Día"=W$9,ROUND(Z31/U31,4),"")) -> 0 | Z31: =IF(U31<>"",$P31,"") -> 0 | AA31: =IF($F31&"/Día"=AC$9,SUM($G31:$H31),"") | AB31: =IF(AA31<>"",$O31,"") | AC31: =IF($F31&"/Día"=AC$9,ROUND(AA31/$W$1,1),"") | AD31: =IF(AA31=0,0,IF($F31&"/Día"=AC$9,ROUND(AB31/AA31,4),"")) | AE31: =IF(AA31=0,0,IF($F31&"/Día"=AC$9,ROUND(AF31/AA31,4),"")) | AF31: =IF(AA31<>"",$P31,"")
A32: - | B32: Z-2B GAS | C32: Servicios | D32: Mes | E32: F1 | F32: MM BTU | O32: =ROUND(G32*I32,2)+ROUND(H32*J32,2)-K32-L32-M32-N32 -> 0 | P32: =ROUND(18.75%*O32,2) -> 0 | Q32: =ROUND($O32*R32,2) -> 0 | R32: 0.15 | S32: =ROUND($O32*T32,2) -> 0 | T32: 0.0375 | U32: =IF($F32&"/Día"=W$9,SUM($G32:$H32),"") | V32: =IF(U32<>"",$O32,"") | W32: =IF($F32&"/Día"=W$9,ROUND(U32/$W$1,1),"") | X32: =IF(U32=0,0,IF($F32&"/Día"=W$9,ROUND(V32/U32,4),"")) | Y32: =IF(U32=0,0,IF($F32&"/Día"=W$9,ROUND(Z32/U32,4),"")) | Z32: =IF(U32<>"",$P32,"") | AA32: =IF($F32&"/Día"=AC$9,SUM($G32:$H32),"") -> 0 | AB32: =IF(AA32<>"",$O32,"") -> 0 | AC32: =IF($F32&"/Día"=AC$9,ROUND(AA32/$W$1,1),"") -> 0 | AD32: =IF(AA32=0,0,IF($F32&"/Día"=AC$9,ROUND(AB32/AA32,4),"")) -> 0 | AE32: =IF(AA32=0,0,IF($F32&"/Día"=AC$9,ROUND(AF32/AA32,4),"")) -> 0 | AF32: =IF(AA32<>"",$P32,"") -> 0
A33: - | B33: XX | C33: Licencia | D33: Quincena | E33: F2 | F33: Bls | G33: 189 | H33: 212 | I33: 77.8038 | J33: 80.8319 | N33: 196.49 | O33: =ROUND(G33*I33,2)+ROUND(H33*J33,2)-K33-L33-M33-N33 -> 31644.79 | P33: =ROUND(18.75%*O33,2) -> 5933.4 | Q33: =ROUND($O33*R33,2) -> 1186.68 | R33: 0.0375 | S33: =ROUND($O33*T33,2) -> 4746.72 | T33: 0.15 | U33: =IF($F33&"/Día"=W$9,SUM($G33:$H33),"") -> 401 | V33: =IF(U33<>"",$O33,"") -> 31644.79 | W33: =IF($F33&"/Día"=W$9,ROUND(U33/$W$1,1),"") -> 12.9 | X33: =IF(U33=0,0,IF($F33&"/Día"=W$9,ROUND(V33/U33,4),"")) -> 78.9147 | Y33: =IF(U33=0,0,IF($F33&"/Día"=W$9,ROUND(Z33/U33,4),"")) -> 14.7965 | Z33: =IF(U33<>"",$P33,"") -> 5933.4 | AA33: =IF($F33&"/Día"=AC$9,SUM($G33:$H33),"") | AB33: =IF(AA33<>"",$O33,"") | AC33: =IF($F33&"/Día"=AC$9,ROUND(AA33/$W$1,1),"") | AD33: =IF(AA33=0,0,IF($F33&"/Día"=AC$9,ROUND(AB33/AA33,4),"")) | AE33: =IF(AA33=0,0,IF($F33&"/Día"=AC$9,ROUND(AF33/AA33,4),"")) | AF33: =IF(AA33<>"",$P33,"")
A34: - | B34: Z1 Crudo | C34: Licencia | D34: Quincena | E34: F2 | F34: Bls | O34: =ROUND(G34*I34,2)+ROUND(H34*J34,2)-K34-L34-M34-N34 -> 0 | P34: =ROUND(18.75%*O34,2) -> 0 | Q34: =ROUND($O34*R34,2) -> 0 | R34: 0.0375 | S34: =ROUND($O34*T34,2) -> 0 | T34: 0.15 | U34: =IF($F34&"/Día"=W$9,SUM($G34:$H34),"") -> 0 | V34: =IF(U34<>"",$O34,"") -> 0 | W34: =IF($F34&"/Día"=W$9,ROUND(U34/$W$1,1),"") -> 0 | X34: =IF(U34=0,0,IF($F34&"/Día"=W$9,ROUND(V34/U34,4),"")) -> 0 | Y34: =IF(U34=0,0,IF($F34&"/Día"=W$9,ROUND(Z34/U34,4),"")) -> 0 | Z34: =IF(U34<>"",$P34,"") -> 0 | AA34: =IF($F34&"/Día"=AC$9,SUM($G34:$H34),"") | AB34: =IF(AA34<>"",$O34,"") | AC34: =IF($F34&"/Día"=AC$9,ROUND(AA34/$W$1,1),"") | AD34: =IF(AA34=0,0,IF($F34&"/Día"=AC$9,ROUND(AB34/AA34,4),"")) | AE34: =IF(AA34=0,0,IF($F34&"/Día"=AC$9,ROUND(AF34/AA34,4),"")) | AF34: =IF(AA34<>"",$P34,"")
A35: - | B35: Z1 Gas | C35: Licencia | D35: Quincena | E35: F2 | F35: MM BTU | O35: =ROUND(G35*I35,2)+ROUND(H35*J35,2)-K35-L35-M35-N35 -> 0 | P35: =ROUND(18.75%*O35,2) -> 0 | Q35: =ROUND($O35*R35,2) -> 0 | R35: 0.0375 | S35: =ROUND($O35*T35,2) -> 0 | T35: 0.15 | U35: =IF($F35&"/Día"=W$9,SUM($G35:$H35),"") | V35: =IF(U35<>"",$O35,"") | W35: =IF($F35&"/Día"=W$9,ROUND(U35/$W$1,1),"") | X35: =IF(U35=0,0,IF($F35&"/Día"=W$9,ROUND(V35/U35,4),"")) | Y35: =IF(U35=0,0,IF($F35&"/Día"=W$9,ROUND(Z35/U35,4),"")) | Z35: =IF(U35<>"",$P35,"") | AA35: =IF($F35&"/Día"=AC$9,SUM($G35:$H35),"") -> 0 | AB35: =IF(AA35<>"",$O35,"") -> 0 | AC35: =IF($F35&"/Día"=AC$9,ROUND(AA35/$W$1,1),"") -> 0 | AD35: =IF(AA35=0,0,IF($F35&"/Día"=AC$9,ROUND(AB35/AA35,4),"")) -> 0 | AE35: =IF(AA35=0,0,IF($F35&"/Día"=AC$9,ROUND(AF35/AA35,4),"")) -> 0 | AF35: =IF(AA35<>"",$P35,"") -> 0
A36: - | B36: Z-2B - LGN | C36: Servicios | D36: Mes | E36: F1 | F36: Bls | O36: =ROUND(G36*I36,2)+ROUND(H36*J36,2)-K36-L36-M36-N36 -> 0 | P36: =ROUND(18.75%*O36,2) -> 0 | Q36: =ROUND($O36*R36,2) -> 0 | R36: 0.15 | S36: =ROUND($O36*T36,2) -> 0 | T36: 0.0375 | U36: =IF($F36&"/Día"=W$9,SUM($G36:$H36),"") -> 0 | V36: =IF(U36<>"",$O36,"") -> 0 | W36: =IF($F36&"/Día"=W$9,ROUND(U36/$W$1,1),"") -> 0 | X36: =IF(U36=0,0,IF($F36&"/Día"=W$9,ROUND(V36/U36,4),"")) -> 0 | Y36: =IF(U36=0,0,IF($F36&"/Día"=W$9,ROUND(Z36/U36,4),"")) -> 0 | Z36: =IF(U36<>"",$P36,"") -> 0 | AA36: =IF($F36&"/Día"=AC$9,SUM($G36:$H36),"") | AB36: =IF(AA36<>"",$O36,"") | AC36: =IF($F36&"/Día"=AC$9,ROUND(AA36/$W$1,1),"") | AD36: =IF(AA36=0,0,IF($F36&"/Día"=AC$9,ROUND(AB36/AA36,4),"")) | AE36: =IF(AA36=0,0,IF($F36&"/Día"=AC$9,ROUND(AF36/AA36,4),"")) | AF36: =IF(AA36<>"",$P36,"")
A37: - | B37: Z-6 | C37: Licencia | D37: Quincena | E37: F2 | F37: MM BTU | O37: =ROUND(G37*I37,2)+ROUND(H37*J37,2)-K37-L37-M37-N37 -> 0 | P37: =ROUND(18.75%*O37,2) -> 0 | Q37: =ROUND($O37*R37,2) -> 0 | R37: 0.15 | S37: =ROUND($O37*T37,2) -> 0 | T37: 0.0375
A38: - | B38: Z-69 Crudo | C38: Licencia | D38: Quincena | E38: F2 | F38: Bls | G38: 47317 | H38: 108419 | I38: 77.485 | J38: 80.5367 | N38: 505.78 | O38: =ROUND(G38*I38,2)+ROUND(H38*J38,2)-K38-L38-M38-N38 -> 12397560 | P38: =ROUND(18.75%*O38,2) -> 2324542.6 | Q38: =ROUND($O38*R38,2) -> 1859634.1 | R38: 0.15 | S38: =ROUND($O38*T38,2) -> 464908.52 | T38: 0.0375
A39: - | B39: Z-69 Gas | C39: Licencia | D39: Quincena | E39: F2 | F39: MM BTU | G39: =G189 -> 171265.73 | H39: =H198 -> 94046.87 | I39: =I189 -> 3.3952979 | J39: =J198 -> 2.7946698 | N39: 447.56 | O39: =O181 -> 844328.12 | P39: =P181 -> 158311.52 | Q39: =Q181 -> 126649.22 | R39: 0.15 | S39: =S181 -> 31662.31 | T39: 0.0375
A40: - | B40: Z-69 Lgn | C40: Licencia | D40: Quincena | E40: F2 | F40: Bls | G40: 9181 | H40: 9526 | I40: 50.6005 | J40: 55.0327 | N40: 487.58 | O40: =ROUND(G40*I40,2)+ROUND(H40*J40,2)-K40-L40-M40-N40 -> 988317.11 | P40: =ROUND(18.75%*O40,2) -> 185309.46 | Q40: =ROUND($O40*R40,2) -> 148247.57 | R40: 0.15 | S40: =ROUND($O40*T40,2) -> 37061.89 | T40: 0.0375
A41: - | B41: Ajustes meses anteriores (1) | U41: =IF($F41&"/Día"=W$9,SUM($G41:$H41),"") | V41: =IF(U41<>"",$O41,"") | W41: =IF($F41&"/Día"=W$9,ROUND(U41/$W$1,1),"") | X41: =IF(U41=0,0,IF($F41&"/Día"=W$9,ROUND(V41/U41,4),"")) | Y41: =IF(U41=0,0,IF($F41&"/Día"=W$9,ROUND(Z41/U41,4),"")) | Z41: =IF(U41<>"",$P41,"") | AA41: =IF($F41&"/Día"=AC$9,SUM($G41:$H41),"") | AB41: =IF(AA41<>"",$O41,"") | AC41: =IF($F41&"/Día"=AC$9,ROUND(AA41/$W$1,1),"") | AD41: =IF(AA41=0,0,IF($F41&"/Día"=AC$9,ROUND(AB41/AA41,4),"")) | AE41: =IF(AA41=0,0,IF($F41&"/Día"=AC$9,ROUND(AF41/AA41,4),"")) | AF41: =IF(AA41<>"",$P41,"")
B42: Subtotal | C42: =TEXT(A$9,)&" US$" -> Piura / Tumbes US$ | O42: =SUM(O10:O41) -> 63364779 | P42: =SUM(P10:P41) -> 11880896 | Q42: =SUM(Q10:Q41) -> 9532887.3 | S42: =SUM(S10:S41) -> 2379739.3 | T42: 0 | U42: =SUM(U10:U41) -> 636085.75 | V42: =SUM(V10:V41) -> 44573943 | W42: =SUM(W10:W41) -> 20518.9 | X42: =ROUND(V42/U42,4) -> 70.0754 | Y42: =ROUND(Z42/U42,4) -> 13.1391 | Z42: =SUM(Z10:Z41) -> 8357614.4 | AA42: =SUM(AA10:AA41) -> 1547961.2 | AB42: =SUM(AB10:AB41) -> 4528899.8 | AC42: =SUM(AC10:AC41) -> 49934.3 | AD42: =ROUND(AB42/AA42,4) -> 2.9257 | AE42: =ROUND(AF42/AA42,4) -> 0.5486 | AF42: =SUM(AF10:AF41) -> 849168.7 | AG42: =P42-Z42-AF42 -> 2674113
C43: =TEXT(A$9,)&" S/." -> Piura / Tumbes S/. | P43: =ROUND($F$1*P42,2) -> 11880896 | Q43: =ROUND($F$1*Q42,2) -> 9532887.3 | S43: =ROUND($F$1*S42,2) -> 2379739.3
A44: Provincia Puerto Inca Huanuco | Q44: Puerto Inca
A45: - | B45: 131 | C45: Licencia | D45: Quincena | E45: F2 | F45: Bls | G45: 13970 | H45: 17678 | I45: 65.6113 | J45: 68.4274 | N45: 3915.23 | O45: =ROUND(G45*I45,2)+ROUND(H45*J45,2)-K45-L45-M45-N45 -> 2122334.2 | P45: =ROUND(15%*O45,2) -> 318350.13 | Q45: =ROUND($O45*R45,2) -> 318350.13 | R45: 0.15 | U45: =IF($F45&"/Día"=W$9,SUM($G45:$H45),"") -> 31648 | V45: =IF(U45<>"",$O45,"") -> 2122334.2 | W45: =IF($F45&"/Día"=W$9,ROUND(U45/$W$1,1),"") -> 1020.9 | X45: =IF(U45=0,0,IF($F45&"/Día"=W$9,ROUND(V45/U45,4),"")) -> 67.0606 | Y45: =IF(U45=0,0,IF($F45&"/Día"=W$9,ROUND(Z45/U45,4),"")) -> 10.0591 | Z45: =IF(U45<>"",$P45,"") -> 318350.13 | AA45: =IF($F45&"/Día"=AC$9,SUM($G45:$H45),"") | AB45: =IF(AA45<>"",$O45,"") | AC45: =IF($F45&"/Día"=AC$9,ROUND(AA45/$W$1,1),"") | AD45: =IF(AA45=0,0,IF($F45&"/Día"=AC$9,ROUND(AB45/AA45,4),"")) | AE45: =IF(AA45=0,0,IF($F45&"/Día"=AC$9,ROUND(AF45/AA45,4),"")) | AF45: =IF(AA45<>"",$P45,"")
A46: - | B46: Ajustes meses anteriores (2) | U46: =IF($F46&"/Día"=W$9,SUM($G46:$H46),"") | V46: =IF(U46<>"",$O46,"") | W46: =IF($F46&"/Día"=W$9,ROUND(U46/$W$1,1),"") | X46: =IF(U46=0,0,IF($F46&"/Día"=W$9,ROUND(V46/U46,4),"")) | Y46: =IF(U46=0,0,IF($F46&"/Día"=W$9,ROUND(Z46/U46,4),"")) | Z46: =IF(U46<>"",$P46,"") | AA46: =IF($F46&"/Día"=AC$9,SUM($G46:$H46),"") | AB46: =IF(AA46<>"",$O46,"") | AC46: =IF($F46&"/Día"=AC$9,ROUND(AA46/$W$1,1),"") | AD46: =IF(AA46=0,0,IF($F46&"/Día"=AC$9,ROUND(AB46/AA46,4),"")) | AE46: =IF(AA46=0,0,IF($F46&"/Día"=AC$9,ROUND(AF46/AA46,4),"")) | AF46: =IF(AA46<>"",$P46,"")
B47: Subtotal | C47: =TEXT(A$44,)&" US$" -> Provincia Puerto Inca Huanuco US$ | O47: =SUM(O45:O46) -> 2122334.2 | P47: =SUM(P45:P46) -> 318350.13 | Q47: =SUM(Q45:Q46) -> 318350.13 | S47: =SUM(S45:S46) -> 0 | U47: =SUM(U45:U46) -> 31648 | V47: =SUM(V45:V46) -> 2122334.2 | W47: =SUM(W45:W46) -> 1020.9 | X47: =ROUND(V47/U47,4) -> 67.0606 | Y47: =ROUND(Z47/U47,4) -> 10.0591 | Z47: =SUM(Z45:Z46) -> 318350.13 | AA47: =SUM(AA45:AA46) -> 0 | AB47: =SUM(AB45:AB46) -> 0 | AC47: =SUM(AC45:AC46) -> 0 | AD47: =IF(AA47=0,0,ROUND(AB47/AA47,4)) -> 0 | AE47: =IF(AA47=0,0,ROUND(AF47/AA47,4)) -> 0 | AF47: =SUM(AF45:AF46) -> 0 | AG47: =P47-Z47-AF47 -> 0
C48: =TEXT(A$44,)&" S/." -> Provincia Puerto Inca Huanuco S/. | P48: =ROUND($F$1*P47,2) -> 318350.13 | Q48: =ROUND($F$1*Q47,2) -> 318350.13 | S48: =ROUND($F$1*S47,2) -> 0
A49: Loreto / Ucayali | Q49: Loreto | S49: Ucayali
A50: - | B50: 192 | C50: Servicios | D50: Mes | E50: F1 | F50: Bls | O50: =ROUND(G50*I50,2)+ROUND(H50*J50,2)-K50-L50-M50-N50 -> 0 | P50: =ROUND(18.75%*O50,2) -> 0 | Q50: =ROUND($O50*R50,2) -> 0 | R50: 0.15 | S50: =ROUND($O50*T50,2) -> 0 | T50: 0.0375 | U50: =IF($F50&"/Día"=W$9,SUM($G50:$H50),"") -> 0 | V50: =IF(U50<>"",$O50,"") -> 0 | W50: =IF($F50&"/Día"=W$9,ROUND(U50/$W$1,1),"") -> 0 | X50: =IF(U50=0,0,IF($F50&"/Día"=W$9,ROUND(V50/U50,4),"")) -> 0 | Y50: =IF(U50=0,0,IF($F50&"/Día"=W$9,ROUND(Z50/U50,4),"")) -> 0 | Z50: =IF(U50<>"",$P50,"") -> 0 | AA50: =IF($F50&"/Día"=AC$9,SUM($G50:$H50),"") | AB50: =IF(AA50<>"",$O50,"") | AC50: =IF($F50&"/Día"=AC$9,ROUND(AA50/$W$1,1),"") | AD50: =IF(AA50=0,0,IF($F50&"/Día"=AC$9,ROUND(AB50/AA50,4),"")) | AE50: =IF(AA50=0,0,IF($F50&"/Día"=AC$9,ROUND(AF50/AA50,4),"")) | AF50: =IF(AA50<>"",$P50,"")
A51: - | B51: 8 | C51: Licencia | D51: Quincena | E51: F2 | F51: Bls | O51: =ROUND(G51*I51,2)+ROUND(H51*J51,2)-K51-L51-M51-N51 -> 0 | P51: =ROUND(18.75%*O51,2) -> 0 | Q51: =ROUND($O51*R51,2) -> 0 | R51: 0.15 | S51: =ROUND($O51*T51,2) -> 0 | T51: 0.0375 | U51: =IF($F51&"/Día"=W$9,SUM($G51:$H51),"") -> 0 | V51: =IF(U51<>"",$O51,"") -> 0 | W51: =IF($F51&"/Día"=W$9,ROUND(U51/$W$1,1),"") -> 0 | X51: =IF(U51=0,0,IF($F51&"/Día"=W$9,ROUND(V51/U51,4),"")) -> 0 | Y51: =IF(U51=0,0,IF($F51&"/Día"=W$9,ROUND(Z51/U51,4),"")) -> 0 | Z51: =IF(U51<>"",$P51,"") -> 0 | AA51: =IF($F51&"/Día"=AC$9,SUM($G51:$H51),"") | AB51: =IF(AA51<>"",$O51,"") | AC51: =IF($F51&"/Día"=AC$9,ROUND(AA51/$W$1,1),"") | AD51: =IF(AA51=0,0,IF($F51&"/Día"=AC$9,ROUND(AB51/AA51,4),"")) | AE51: =IF(AA51=0,0,IF($F51&"/Día"=AC$9,ROUND(AF51/AA51,4),"")) | AF51: =IF(AA51<>"",$P51,"")
A52: - | B52: 31-C GAS | C52: Licencia | D52: Quincena | E52: F2 | F52: MM BTU | G52: 31203.768 | H52: 153281.12 | I52: 3.6562 | J52: 3.6515 | N52: 1495.79 | O52: =ROUND(G52*I52,2)+ROUND(H52*J52,2)-K52-L52-M52-N52 -> 672297.44 | P52: =ROUND(18.75%*O52,2) -> 126055.77 | Q52: =ROUND($O52*R52,2) -> 25211.15 | R52: 0.0375 | S52: =ROUND($O52*T52,2) -> 100844.62 | T52: 0.15 | U52: =IF($F52&"/Día"=W$9,SUM($G52:$H52),"") | V52: =IF(U52<>"",$O52,"") | W52: =IF($F52&"/Día"=W$9,ROUND(U52/$W$1,1),"") | X52: =IF(U52=0,0,IF($F52&"/Día"=W$9,ROUND(V52/U52,4),"")) | Y52: =IF(U52=0,0,IF($F52&"/Día"=W$9,ROUND(Z52/U52,4),"")) | Z52: =IF(U52<>"",$P52,"") | AA52: =IF($F52&"/Día"=AC$9,SUM($G52:$H52),"") -> 184484.89 | AB52: =IF(AA52<>"",$O52,"") -> 672297.44 | AC52: =IF($F52&"/Día"=AC$9,ROUND(AA52/$W$1,1),"") -> 5951.1 | AD52: =IF(AA52=0,0,IF($F52&"/Día"=AC$9,ROUND(AB52/AA52,4),"")) -> 3.6442 | AE52: =IF(AA52=0,0,IF($F52&"/Día"=AC$9,ROUND(AF52/AA52,4),"")) -> 0.6833 | AF52: =IF(AA52<>"",$P52,"") -> 126055.77
A53: - | B53: 31-C LGN (*) | C53: Licencia | D53: Quincena | E53: F3 | F53: Bls | G53: 1895 | H53: 812 | I53: 56.1137 | J53: 60.7846 | N53: 3227.8 | O53: =ROUND(G53*I53,2)+ROUND(H53*J53,2)-K53-L53-M53-N53 -> 152464.76 | P53: =ROUND(18.75%*O53,2) -> 28587.14 | Q53: =ROUND($O53*R53,2) -> 5717.43 | R53: 0.0375 | S53: =ROUND($O53*T53,2) -> 22869.71 | T53: 0.15 | U53: =IF($F53&"/Día"=W$9,SUM($G53:$H53),"") -> 2707 | V53: =IF(U53<>"",$O53,"") -> 152464.76 | W53: =IF($F53&"/Día"=W$9,ROUND(U53/$W$1,1),"") -> 87.3 | X53: =IF(U53=0,0,IF($F53&"/Día"=W$9,ROUND(V53/U53,4),"")) -> 56.3224 | Y53: =IF(U53=0,0,IF($F53&"/Día"=W$9,ROUND(Z53/U53,4),"")) -> 10.5605 | Z53: =IF(U53<>"",$P53,"") -> 28587.14 | AA53: =IF($F53&"/Día"=AC$9,SUM($G53:$H53),"") | AB53: =IF(AA53<>"",$O53,"") | AC53: =IF($F53&"/Día"=AC$9,ROUND(AA53/$W$1,1),"") | AD53: =IF(AA53=0,0,IF($F53&"/Día"=AC$9,ROUND(AB53/AA53,4),"")) | AE53: =IF(AA53=0,0,IF($F53&"/Día"=AC$9,ROUND(AF53/AA53,4),"")) | AF53: =IF(AA53<>"",$P53,"")
A54: - | B54: 31-C COND | C54: Licencia | D54: Quincena | E54: F2 | F54: Bls | O54: =ROUND(G54*I54,2)+ROUND(H54*J54,2)-K54-L54-M54-N54 -> 0 | P54: =ROUND(18.75%*O54,2) -> 0 | Q54: =ROUND($O54*R54,2) -> 0 | R54: 0.0375 | S54: =ROUND($O54*T54,2) -> 0 | T54: 0.15 | U54: =IF($F54&"/Día"=W$9,SUM($G54:$H54),"") -> 0 | V54: =IF(U54<>"",$O54,"") -> 0 | W54: =IF($F54&"/Día"=W$9,ROUND(U54/$W$1,1),"") -> 0 | X54: =IF(U54=0,0,IF($F54&"/Día"=W$9,ROUND(V54/U54,4),"")) -> 0 | Y54: =IF(U54=0,0,IF($F54&"/Día"=W$9,ROUND(Z54/U54,4),"")) -> 0 | Z54: =IF(U54<>"",$P54,"") -> 0 | AA54: =IF($F54&"/Día"=AC$9,SUM($G54:$H54),"") | AB54: =IF(AA54<>"",$O54,"") | AC54: =IF($F54&"/Día"=AC$9,ROUND(AA54/$W$1,1),"") | AD54: =IF(AA54=0,0,IF($F54&"/Día"=AC$9,ROUND(AB54/AA54,4),"")) | AE54: =IF(AA54=0,0,IF($F54&"/Día"=AC$9,ROUND(AF54/AA54,4),"")) | AF54: =IF(AA54<>"",$P54,"")
A55: - | B55: 102 | C55: Licencia | D55: Quincena | E55: F2 | F55: Bls | O55: =ROUND(G55*I55,2)+ROUND(H55*J55,2)-K55-L55-M55-N55 -> 0 | P55: =ROUND(18.75%*O55,2) -> 0 | Q55: =P55-S55 -> 0 | R55: 0.15 | S55: =ROUND($O55*T55,2) -> 0 | T55: 0.0375 | U55: =IF($F55&"/Día"=W$9,SUM($G55:$H55),"") -> 0 | V55: =IF(U55<>"",$O55,"") -> 0 | W55: =IF($F55&"/Día"=W$9,ROUND(U55/$W$1,1),"") -> 0 | X55: =IF(U55=0,0,IF($F55&"/Día"=W$9,ROUND(V55/U55,4),"")) -> 0 | Y55: =IF(U55=0,0,IF($F55&"/Día"=W$9,ROUND(Z55/U55,4),"")) -> 0 | Z55: =IF(U55<>"",$P55,"") -> 0 | AA55: =IF($F55&"/Día"=AC$9,SUM($G55:$H55),"") | AB55: =IF(AA55<>"",$O55,"") | AC55: =IF($F55&"/Día"=AC$9,ROUND(AA55/$W$1,1),"") | AD55: =IF(AA55=0,0,IF($F55&"/Día"=AC$9,ROUND(AB55/AA55,4),"")) | AE55: =IF(AA55=0,0,IF($F55&"/Día"=AC$9,ROUND(AF55/AA55,4),"")) | AF55: =IF(AA55<>"",$P55,"")
A56: - | B56: 95 | C56: Licencia | D56: Quincena | E56: F2 | F56: Bls | G56: 273072 | H56: 314659 | I56: 59.1987 | J56: 61.7993 | N56: 5239.72 | O56: =ROUND(G56*I56,2)+ROUND(H56*J56,2)-K56-L56-M56-N56 -> 35605974 | P56: =ROUND(18.75%*O56,2) -> 6676120.1 | Q56: =P56-S56 -> 5340896 | R56: 0.15 | S56: =ROUND($O56*T56,2) -> 1335224 | T56: 0.0375 | U56: =IF($F56&"/Día"=W$9,SUM($G56:$H56),"") -> 587731 | V56: =IF(U56<>"",$O56,"") -> 35605974 | W56: =IF($F56&"/Día"=W$9,ROUND(U56/$W$1,1),"") -> 18959.1 | X56: =IF(U56=0,0,IF($F56&"/Día"=W$9,ROUND(V56/U56,4),"")) -> 60.5821 | Y56: =IF(U56=0,0,IF($F56&"/Día"=W$9,ROUND(Z56/U56,4),"")) -> 11.3591 | Z56: =IF(U56<>"",$P56,"") -> 6676120.1 | AA56: =IF($F56&"/Día"=AC$9,SUM($G56:$H56),"") | AB56: =IF(AA56<>"",$O56,"") | AC56: =IF($F56&"/Día"=AC$9,ROUND(AA56/$W$1,1),"") | AD56: =IF(AA56=0,0,IF($F56&"/Día"=AC$9,ROUND(AB56/AA56,4),"")) | AE56: =IF(AA56=0,0,IF($F56&"/Día"=AC$9,ROUND(AF56/AA56,4),"")) | AF56: =IF(AA56<>"",$P56,"")
A57: - | B57: 67 | C57: Licencia | D57: Quincena | E57: F2 | F57: Bls | N57: 1684.72 | O57: =ROUND(G57*I57,2)+ROUND(H57*J57,2)-K57-L57-M57-N57 -> -1684.72 | P57: =ROUND(18.75%*O57,2) -> -315.89 | Q57: =P57-S57 -> -252.71 | R57: 0.15 | S57: =ROUND($O57*T57,2) -> -63.18 | T57: 0.0375 | U57: =IF($F57&"/Día"=W$9,SUM($G57:$H57),"") -> 0 | V57: =IF(U57<>"",$O57,"") -> -1684.72 | W57: =IF($F57&"/Día"=W$9,ROUND(U57/$W$1,1),"") -> 0 | X57: =IF(U57=0,0,IF($F57&"/Día"=W$9,ROUND(V57/U57,4),"")) -> 0 | Y57: =IF(U57=0,0,IF($F57&"/Día"=W$9,ROUND(Z57/U57,4),"")) -> 0 | Z57: =IF(U57<>"",$P57,"") -> -315.89 | AA57: =IF($F57&"/Día"=AC$9,SUM($G57:$H57),"") | AB57: =IF(AA57<>"",$O57,"") | AC57: =IF($F57&"/Día"=AC$9,ROUND(AA57/$W$1,1),"") | AD57: =IF(AA57=0,0,IF($F57&"/Día"=AC$9,ROUND(AB57/AA57,4),"")) | AE57: =IF(AA57=0,0,IF($F57&"/Día"=AC$9,ROUND(AF57/AA57,4),"")) | AF57: =IF(AA57<>"",$P57,"")
A58: - | B58: Ajustes meses anteriores (3) | U58: =IF($F58&"/Día"=W$9,SUM($G58:$H58),"") | V58: =IF(U58<>"",$O58,"") | W58: =IF($F58&"/Día"=W$9,ROUND(U58/$W$1,1),"") | X58: =IF(U58=0,0,IF($F58&"/Día"=W$9,ROUND(V58/U58,4),"")) | Y58: =IF(U58=0,0,IF($F58&"/Día"=W$9,ROUND(Z58/U58,4),"")) | Z58: =IF(U58<>"",$P58,"") | AA58: =IF($F58&"/Día"=AC$9,SUM($G58:$H58),"") | AB58: =IF(AA58<>"",$O58,"") | AC58: =IF($F58&"/Día"=AC$9,ROUND(AA58/$W$1,1),"") | AD58: =IF(AA58=0,0,IF($F58&"/Día"=AC$9,ROUND(AB58/AA58,4),"")) | AE58: =IF(AA58=0,0,IF($F58&"/Día"=AC$9,ROUND(AF58/AA58,4),"")) | AF58: =IF(AA58<>"",$P58,"")
B59: Subtotal | C59: =TEXT(A$49,)&" US$" -> Loreto / Ucayali US$ | O59: =SUM(O50:O58) -> 36429051 | P59: =SUM(P50:P58) -> 6830447.1 | Q59: =SUM(Q50:Q58) -> 5371571.9 | S59: =SUM(S50:S58) -> 1458875.2 | U59: =SUM(U50:U58) -> 590438 | V59: =SUM(V50:V58) -> 35756754 | W59: =SUM(W50:W58) -> 19046.4 | X59: =ROUND(V59/U59,4) -> 60.5597 | Y59: =ROUND(Z59/U59,4) -> 11.3549 | Z59: =SUM(Z50:Z58) -> 6704391.3 | AA59: =SUM(AA50:AA58) -> 184484.89 | AB59: =SUM(AB50:AB58) -> 672297.44 | AC59: =SUM(AC50:AC58) -> 5951.1 | AD59: =ROUND(AB59/AA59,4) -> 3.6442 | AE59: =ROUND(AF59/AA59,4) -> 0.6833 | AF59: =SUM(AF50:AF58) -> 126055.77 | AG59: =P59-Z59-AF59 -> 4.802132e-10
C60: =TEXT(A$49,)&" S/." -> Loreto / Ucayali S/. | P60: =ROUND($F$1*P59,2) -> 6830447.1 | Q60: =ROUND($F$1*Q59,2) -> 5371571.9 | S60: =ROUND($F$1*S59,2) -> 1458875.2
A61: Cusco | P61: V. Regalías | Q61: Cusco
A62: - | B62: 88 LGN | C62: Licencia | D62: Quincena | E62: F4 | F62: Bls | G62: 786979 | H62: 802294 | I62: 40.6674 | J62: 45.0146 | N62: 2627.28 | O62: =G62*I62+H62*J62 -> 68119333 | P62: =ROUND(37.24%*(G62*I62+H62*J62),2) -> 25367640 | Q62: =ROUND(R62*P62,2) -> 12683820 | R62: 0.5 | U62: =IF($F62&"/Día"=W$9,SUM($G62:$H62),"") -> 1589273 | V62: =IF(U62<>"",$O62,"") -> 68119333 | W62: =IF($F62&"/Día"=W$9,ROUND(U62/$W$1,1),"") -> 51266.9 | X62: =IF(U62=0,0,IF($F62&"/Día"=W$9,ROUND(V62/U62,4),"")) -> 42.8619 | Y62: =IF(U62=0,0,IF($F62&"/Día"=W$9,ROUND(Z62/U62,4),"")) -> 7.9809 | Z62: =IF(U62<>"",$Q62,"") -> 12683820 | AA62: =IF($F62&"/Día"=AC$9,SUM($G62:$H62),"") | AB62: =IF(AA62<>"",$O62,"") | AC62: =IF($F62&"/Día"=AC$9,ROUND(AA62/$W$1,1),"") | AD62: =IF(AA62=0,0,IF($F62&"/Día"=AC$9,ROUND(AB62/AA62,4),"")) | AE62: =IF(AA62=0,0,IF($F62&"/Día"=AC$9,ROUND(AF62/AA62,4),"")) | AF62: =IF(AA62<>"",$Q62,"")
A63: - | B63: 88 GAS | C63: Licencia | D63: Quincena | E63: F4 | F63: MM BTU | G63: =G100 -> 10439446 | H63: =H108 -> 11974700 | I63: =I100 -> 2.928 | J63: =J108 -> 2.8775 | N63: 3759.61 | O63: =O92 -> 65023973 | P63: =P92 -> 24443382 | Q63: =Q92 -> 12221691 | R63: 0.5 | U63: =IF($F63&"/Día"=W$9,SUM($G63:$H63),"") | V63: =IF(U63<>"",$O63,"") | W63: =IF($F63&"/Día"=W$9,ROUND(U63/$W$1,1),"") | X63: =IF(U63=0,0,IF($F63&"/Día"=W$9,ROUND(V63/U63,4),"")) | Y63: =IF(U63=0,0,IF($F63&"/Día"=W$9,ROUND(Z63/U63,4),"")) | Z63: =IF(U63<>"",$Q63,"") | AA63: =IF($F63&"/Día"=AC$9,SUM($G63:$H63),"") -> 22414146 | AB63: =IF(AA63<>"",$O63,"") -> 65023973 | AC63: =IF($F63&"/Día"=AC$9,ROUND(AA63/$W$1,1),"") -> 723037 | AD63: =IF(AA63=0,0,IF($F63&"/Día"=AC$9,ROUND(AB63/AA63,4),"")) -> 2.901 | AE63: =IF(AA63=0,0,IF($F63&"/Día"=AC$9,ROUND(AF63/AA63,4),"")) -> 0.5453 | AF63: =IF(AA63<>"",$Q63,"") -> 12221691
A64: - | B64: 56 LGN | C64: Licencia | D64: Quincena | E64: F4 | F64: Bls | G64: 201028 | H64: 224035 | I64: 40.6855 | J64: 45.0104 | N64: 1797.65 | O64: =G64*I64+H64*J64 -> 18262830 | P64: =ROUND(40%*G64*I64,2)+ROUND(40%*H64*J64,2) -> 7305131.9 | Q64: =ROUND(R64*P64,2) -> 3652565.9 | R64: 0.5 | U64: =IF($F64&"/Día"=W$9,SUM($G64:$H64),"") -> 425063 | V64: =IF(U64<>"",$O64,"") -> 18262830 | W64: =IF($F64&"/Día"=W$9,ROUND(U64/$W$1,1),"") -> 13711.7 | X64: =IF(U64=0,0,IF($F64&"/Día"=W$9,ROUND(V64/U64,4),"")) -> 42.965 | Y64: =IF(U64=0,0,IF($F64&"/Día"=W$9,ROUND(Z64/U64,4),"")) -> 8.593 | Z64: =IF(U64<>"",$Q64,"") -> 3652565.9 | AA64: =IF($F64&"/Día"=AC$9,SUM($G64:$H64),"") | AB64: =IF(AA64<>"",$O64,"") | AC64: =IF($F64&"/Día"=AC$9,ROUND(AA64/$W$1,1),"") | AD64: =IF(AA64=0,0,IF($F64&"/Día"=AC$9,ROUND(AB64/AA64,4),"")) | AE64: =IF(AA64=0,0,IF($F64&"/Día"=AC$9,ROUND(AF64/AA64,4),"")) | AF64: =IF(AA64<>"",$Q64,"")
A65: - | B65: 56 GAS | C65: Licencia | D65: Quincena | E65: F4 | F65: MM BTU | G65: =G164 -> 5146043.6 | H65: =H172 -> 5558408 | I65: =I164 -> 3.916 | J65: =J172 -> 3.218 | N65: 2234.58 | O65: =O151 -> 37493383 | P65: =P151 -> 14247486 | Q65: =Q151 -> 7123742.8 | R65: 0.5 | U65: =IF($F65&"/Día"=W$9,SUM($G65:$H65),"") | V65: =IF(U65<>"",$O65,"") | W65: =IF($F65&"/Día"=W$9,ROUND(U65/$W$1,1),"") | X65: =IF(U65=0,0,IF($F65&"/Día"=W$9,ROUND(V65/U65,4),"")) | Y65: =IF(U65=0,0,IF($F65&"/Día"=W$9,ROUND(Z65/U65,4),"")) | Z65: =IF(U65<>"",$Q65,"") | AA65: =IF($F65&"/Día"=AC$9,SUM($G65:$H65),"") -> 10704452 | AB65: =IF(AA65<>"",$O65,"") -> 37493383 | AC65: =IF($F65&"/Día"=AC$9,ROUND(AA65/$W$1,1),"") -> 345304.9 | AD65: =IF(AA65=0,0,IF($F65&"/Día"=AC$9,ROUND(AB65/AA65,4),"")) -> 3.5026 | AE65: =IF(AA65=0,0,IF($F65&"/Día"=AC$9,ROUND(AF65/AA65,4),"")) -> 0.6655 | AF65: =IF(AA65<>"",$Q65,"") -> 7123742.8
A66: - | B66: 57 LGN | C66: Licencia | D66: Quincena | E66: F4 | F66: Bls | G66: 217783 | I66: 36.4882 | N66: 680.57 | O66: =G66*I66+H66*J66 -> 7946509.7 | P66: =ROUND(G66*I66,2)*6.73%+ROUND(H66*J66,2)*6.9% -> 534800.1 | Q66: =ROUND(R66*P66,2) -> 267400.05 | R66: 0.5 | U66: =IF($F66&"/Día"=W$9,SUM($G66:$H66),"") -> 217783 | V66: =IF(U66<>"",$O66,"") -> 7946509.7 | W66: =IF($F66&"/Día"=W$9,ROUND(U66/$W$1,1),"") -> 7025.3 | X66: =IF(U66=0,0,IF($F66&"/Día"=W$9,ROUND(V66/U66,4),"")) -> 36.4882 | Y66: =IF(U66=0,0,IF($F66&"/Día"=W$9,ROUND(Z66/U66,4),"")) -> 1.2278 | Z66: =IF(U66<>"",$Q66,"") -> 267400.05 | AA66: =IF($F66&"/Día"=AC$9,SUM($G66:$H66),"") | AB66: =IF(AA66<>"",$O66,"") | AC66: =IF($F66&"/Día"=AC$9,ROUND(AA66/$W$1,1),"") | AD66: =IF(AA66=0,0,IF($F66&"/Día"=AC$9,ROUND(AB66/AA66,4),"")) | AE66: =IF(AA66=0,0,IF($F66&"/Día"=AC$9,ROUND(AF66/AA66,4),"")) | AF66: =IF(AA66<>"",$Q66,"")
A67: - | B67: 57 GAS | C67: Licencia | D67: Quincena | E67: F4 | F67: MM BTU | G67: 3383715 | I67: 2.523 | N67: 1590.53 | O67: =G67*I67+H67*J67 -> 8537112.8 | P67: =ROUND(G67*I67,2)*11.18%+ROUND(H67*J67,2)*11.47% -> 954449.21 | Q67: =ROUND(R67*P67,2) -> 477224.61 | R67: 0.5 | U67: =IF($F67&"/Día"=W$9,SUM($G67:$H67),"") | V67: =IF(U67<>"",$O67,"") | W67: =IF($F67&"/Día"=W$9,ROUND(U67/$W$1,1),"") | X67: =IF(U67=0,0,IF($F67&"/Día"=W$9,ROUND(V67/U67,4),"")) | Y67: =IF(U67=0,0,IF($F67&"/Día"=W$9,ROUND(Z67/U67,4),"")) | Z67: =IF(U67<>"",$Q67,"") | AA67: =IF($F67&"/Día"=AC$9,SUM($G67:$H67),"") -> 3383715 | AB67: =IF(AA67<>"",$O67,"") -> 8537112.8 | AC67: =IF($F67&"/Día"=AC$9,ROUND(AA67/$W$1,1),"") -> 109152.1 | AD67: =IF(AA67=0,0,IF($F67&"/Día"=AC$9,ROUND(AB67/AA67,4),"")) -> 2.523 | AE67: =IF(AA67=0,0,IF($F67&"/Día"=AC$9,ROUND(AF67/AA67,4),"")) -> 0.141 | AF67: =IF(AA67<>"",$Q67,"") -> 477224.61
A68: - | B68: Ajustes meses anteriores (4) | U68: =IF($F68&"/Día"=W$9,SUM($G68:$H68),"") | V68: =IF(U68<>"",$O68,"") | W68: =IF($F68&"/Día"=W$9,ROUND(U68/$W$1,1),"") | X68: =IF(U68=0,0,IF($F68&"/Día"=W$9,ROUND(V68/U68,4),"")) | Y68: =IF(U68=0,0,IF($F68&"/Día"=W$9,ROUND(Z68/U68,4),"")) | Z68: =IF(U68<>"",$Q68,"") | AA68: =IF($F68&"/Día"=AC$9,SUM($G68:$H68),"") | AB68: =IF(AA68<>"",$O68,"") | AC68: =IF($F68&"/Día"=AC$9,ROUND(AA68/$W$1,1),"") | AD68: =IF(AA68=0,0,IF($F68&"/Día"=AC$9,ROUND(AB68/AA68,4),"")) | AE68: =IF(AA68=0,0,IF($F68&"/Día"=AC$9,ROUND(AF68/AA68,4),"")) | AF68: =IF(AA68<>"",$Q68,"")
B69: Subtotal | C69: =TEXT(A$61,)&" US$" -> Cusco US$ | G69: =SUM(G65:G65) -> 5146043.6 | H69: =SUM(H65:H65) -> 5558408 | O69: =SUM(O62:O68) -> 2.0538314e+08 | P69: =SUM(P62:P68) -> 72852889 | Q69: =SUM(Q62:Q68) -> 36426444 | U69: =SUM(U62:U68) -> 2232119 | V69: =SUM(V62:V68) -> 94328673 | W69: =SUM(W62:W68) -> 72003.9 | X69: =ROUND(V69/U69,4) -> 42.2597 | Y69: =ROUND(Z69/U69,4) -> 7.4386 | Z69: =SUM(Z62:Z68) -> 16603786 | AA69: =SUM(AA62:AA68) -> 36502313 | AB69: =SUM(AB62:AB68) -> 1.1105447e+08 | AC69: =SUM(AC62:AC68) -> 1177494 | AD69: =ROUND(AB69/AA69,4) -> 3.0424 | AE69: =ROUND(AF69/AA69,4) -> 0.5431 | AF69: =SUM(AF62:AF68) -> 19822659 | AG69: =Q69-Z69-AF69 -> 0
C70: =TEXT(A$61,)&" S/." -> Cusco S/. | G70: =SUMPRODUCT(I65:I65,G65:G65)/SUM(G65:G65) -> 3.916 | H70: =SUMPRODUCT(J65:J65,H65:H65)/SUM(H65:H65) -> 3.218 | Q70: =Q69*F1 -> 36426444
A71: Total General | G71: =G69*G70 -> 20151907 | H71: =H69*H70 -> 17886957 | I71: =H71+G71 -> 38038864 | J71: =O65+#REF! -> #REF! | K71: =I71-J71 -> #REF! | M71: =SUM(M10:M67) -> 0 | N71: =SUM(N10:N67) -> 48441.64 | O71: =O42+O47+O59+O69 -> 3.0729931e+08 | P71: =Q69+P59+P47+P42 -> 55456138 | Q71: =Q43+S43+Q48+Q60+S60+Q70 -> 55487868 | U71: =U42+U47+U59+U69 -> 3490290.7 | V71: =V42+V47+V59+V69 -> 1.767817e+08 | W71: =W42+W47+W59+W69 -> 112590.1 | X71: =ROUND(V71/U71,4) -> 50.6496 | Y71: =ROUND(Z71/U71,4) -> 9.1637 | Z71: =Z42+Z47+Z59+Z69 -> 31984142 | AA71: =AA42+AA47+AA59+AA69 -> 38234759 | AB71: =AB42+AB47+AB59+AB69 -> 1.1625567e+08 | AC71: =AC42+AC47+AC59+AC69 -> 1233379.4 | AD71: =ROUND(AB71/AA71,4) -> 3.0406 | AE71: =ROUND(AF71/AA71,4) -> 0.544 | AF71: =AF42+AF47+AF59+AF69 -> 20797883 | AG71: =P71-Z71-AF71 -> 2674113
A73: (*) | B73: Determinación de Canasta de los Líquidos de Gas Natural (VLGNF) | H73: = ( VC * %P + (PB - TF - TT) * (1 - %P))
B74: Simbolo | C74: Descripcion | E74: 1ra. Q | F74: 2da. Q | H74: 1ra. Q
B75: VC | C75: Canasta de Petróleo | H75: ="= ("&TEXT(E75,"0.0000")&" * "&TEXT(E78,"0.00%")&" + ("&TEXT(E76,"0.0000")&" - "&TEXT(E77,"0.0000")&" - "&TEXT(E80,"0.0000")&") * (1 - "&TEXT(E78,"0.00%")&"))" -> = (0.0000 * 0.00% + (0.0000 - 0.0000 - 0.0000) * (1 - 0.00%)) | N75: =547803.45/8532764.09 -> 0.064199999
B76: PB | C76: Precio del GLP | H76: =((85.98%*E75+4.4221)*E78+(E76-E77-E80)*(1-E78)) -> 0 | M76: =698277.28/7412709.99 -> 0.0942 | N76: =1065699.61/10775526.87 -> 0.0989
B77: TF | C77: Tarifa de Fraccionam. | M77: =5254120.1/13135300.26 -> 0.4 | N77: =7653140.6/19132851.51 -> 0.4
B78: %P | C78: % Contenido Pentanos | H78: 2da. Q | M78: =503101.38/1323950.99 -> 0.38
B79: QLGNF | C79: Volumen de LGN | H79: ="= ("&TEXT(F75,"0.0000")&" * "&TEXT(F78,"0.00%")&" + ("&TEXT(F76,"0.0000")&" - "&TEXT(F77,"0.0000")&" - "&TEXT(F80,"0.0000")&") * (1 - "&TEXT(F78,"0.00%")&"))" -> = (0.0000 * 0.00% + (0.0000 - 0.0000 - 0.0000) * (1 - 0.00%))
B80: TT | C80: Tarifa de Transporte | H80: =((85.98%*F75+4.4221)*F78+(F76-F77-F80)*(1-F78)) -> 0
A82: (*) Crudo Garantia de Interoil
A84: ="AJUSTES PARA "&UPPER(TEXT(E1,"MMMMMMM YYYY")) -> AJUSTES PARA ENERO 2024
A86: DATOS PROMEDIOS:
A87: REAL
A88: - | B88: 88 GAS | C88: Licencia | D88: Quincena | E88: F4 | F88: MM BTU | G88: 28986.371 | H88: 10969128 | I88: 3.739 | J88: 2.8429 | O88: =ROUND(G88*I88+H88*J88,2) -> 31292514 | P88: =ROUND(37.24%*O88,2) -> 11653332 | Q88: =ROUND(R88*P88,2) -> 5826666.1 | R88: 0.5 | S88: =Q88 -> 5826666.1
A89: - | B89: 88 GAS -Mlocal | C89: Licencia | D89: Quincena | E89: F4 | F89: MM BTU | G89: 866323.03 | H89: 39937.228 | I89: 3.81 | J89: 3.739 | O89: =ROUND(G89*I89+H89*J89,2) -> 3450016 | P89: =ROUND(37.24%*O89,2) -> 1284786 | Q89: =ROUND(R89*P89,2) -> 642392.99 | R89: 0.5
A90: - | B90: 88 GAS -Mlocal (L56) | C90: Licencia | D90: Quincena | E90: F4 | F90: MM BTU | G90: 26991.31 | H90: 32276.91 | I90: 3.739 | J90: 3.739 | O90: =ROUND(G90*I90+H90*J90,2) -> 221603.87 | P90: =ROUND(37.24%*O90,2) -> 82525.28 | Q90: =ROUND(R90*P90,2) -> 41262.64 | R90: 0.5 | S90: =Q90+Q89 -> 683655.63
A91: - | B91: 88 GAS -PM | C91: Licencia | D91: Quincena | E91: F4 | F91: MM BTU | G91: 9517145.3 | H91: 933358.21 | I91: 2.8429 | J91: 3.218 | O91: =ROUND(G91*I91+H91*J91,2) -> 30059839 | P91: =ROUND(38%*G91*I91,2)+ROUND(38%*H91*J91,2) -> 11422739 | Q91: =ROUND(R91*P91,2) -> 5711369.5 | R91: 0.5 | S91: =Q91 -> 5711369.5
G92: =SUM(G88:G91) -> 10439446 | H92: =SUM(H88:H91) -> 11974700 | O92: =SUM(O88:O91) -> 65023973 | P92: =SUM(P88:P91) -> 24443382 | Q92: =SUM(Q88:Q91) -> 12221691
P93: =P92/O92 -> 0.37591339
A94: PROMEDIO 1Q
A96: - | B96: 88 GAS | C96: Licencia | D96: Quincena | E96: F4 | F96: MM BTU | G96: =G88 -> 28986.371 | I96: =I88 -> 3.739 | O96: =ROUND(G96*I96+H96*J96,2) -> 108380.04 | P96: =ROUND(37.24%*(G96*I96+H96*J96),2) -> 40360.73 | Q96: =ROUND(R96*P96,2) -> 20180.37 | R96: 0.5
A97: - | B97: 88 GAS -Mlocal | C97: Licencia | D97: Quincena | E97: F4 | F97: MM BTU | G97: =G89 -> 866323.03 | I97: =I89 -> 3.81 | O97: =ROUND(G97*I97+H97*J97,2) -> 3300690.8 | P97: =ROUND(37.24%*O97,2) -> 1229177.2 | Q97: =ROUND(R97*P97,2) -> 614588.62 | R97: 0.5
A98: - | B98: 88 GAS -Mlocal (L56) | C98: Licencia | D98: Quincena | E98: F4 | F98: MM BTU | G98: =G90 -> 26991.31 | I98: =I90 -> 3.739 | O98: =ROUND(G98*I98+H98*J98,2) -> 100920.51 | P98: =ROUND(37.24%*O98,2) -> 37582.8 | Q98: =ROUND(R98*P98,2) -> 18791.4 | R98: 0.5
A99: - | B99: 88 GAS -PM | C99: Licencia | D99: Quincena | E99: F4 | F99: MM BTU | G99: =G91 -> 9517145.3 | I99: =I91 -> 2.8429 | O99: =ROUND(G99*I99+H99*J99,2) -> 27056292 | P99: =ROUND(38%*G99*I99,2)+ROUND(38%*H99*J99,2) -> 10281391 | Q99: =ROUND(R99*P99,2) -> 5140695.6 | R99: 0.5
G100: =SUM(G96:G99) -> 10439446 | I100: =ROUND(O100/G100,4) -> 2.928 | O100: =SUM(O96:O99) -> 30566284 | P100: =SUM(P96:P99) -> 11588512 | Q100: =SUM(Q96:Q99) -> 5794256
A102: PROMEDIO 2Q
A104: - | B104: 88 GAS | C104: Licencia | D104: Quincena | E104: F4 | F104: MM BTU | H104: =H88 -> 10969128 | J104: =J88 -> 2.8429 | O104: =ROUND(G104*I104+H104*J104,2) -> 31184134 | P104: =ROUND(37.24%*(G104*I104+H104*J104),2) -> 11612972 | Q104: =ROUND(R104*P104,2) -> 5806485.8 | R104: 0.5
A105: - | B105: 88 GAS -Mlocal | C105: Licencia | D105: Quincena | E105: F4 | F105: MM BTU | H105: =H89 -> 39937.228 | J105: =J89 -> 3.739 | O105: =ROUND(G105*I105+H105*J105,2) -> 149325.3 | P105: =ROUND(37.24%*O105,2) -> 55608.74 | Q105: =ROUND(R105*P105,2) -> 27804.37 | R105: 0.5
A106: - | B106: 88 GAS -Mlocal (L56) | C106: Licencia | D106: Quincena | E106: F4 | F106: MM BTU | H106: =H90 -> 32276.91 | J106: =J90 -> 3.739 | O106: =ROUND(G106*I106+H106*J106,2) -> 120683.37 | P106: =ROUND(37.24%*O106,2) -> 44942.49 | Q106: =ROUND(R106*P106,2) -> 22471.25 | R106: 0.5
A107: - | B107: 88 GAS -PM | C107: Licencia | D107: Quincena | E107: F4 | F107: MM BTU | H107: =H91 -> 933358.21 | J107: =J91 -> 3.218 | O107: =ROUND(G107*I107+H107*J107,2) -> 3003546.7 | P107: =ROUND(38%*G107*I107,2)+ROUND(38%*H107*J107,2) -> 1141347.8 | Q107: =ROUND(R107*P107,2) -> 570673.88 | R107: 0.5
H108: =SUM(H104:H107) -> 11974700 | J108: =ROUND(O108/H108,4) -> 2.8775 | O108: =SUM(O104:O107) -> 34457689 | P108: =SUM(P104:P107) -> 12854870 | Q108: =SUM(Q104:Q107) -> 6427435.3
...

Sheet Feb
A1: Período de Cálculo: | E1: 46054 | F1: 3.454 | S1: ,
A2: PERUPETRO S.A.
A3: DETERMINACION DEL CANON, SOBRECANON y PARTICIPACION (US$)
A4: Correspondiente a Febrero 2026
A5: Tipo de Cambio= 3.454
A7: Localidad | C7: Modalidad de Contrato | D7: Calculo del Canon | F7: Volumen Producción / Venta | I7: Canasta o Valor Venta (US$/Unidad) | K7: Deducción de Gastos para determinación de valor de producción en Punto de Fiscalización (US$) | O7: Valor de la Producción (US$) | P7: Canon y Sobrecanon / Participación (US$)
A8: - Lote | D8: Período | E8: Fórmula | F8: Unidades | G8: 1ra. Q | H8: 2da. Q / Mes | I8: 1ra. Q | J8: 2da. Q / Mes | K8: Flete Marítimo | L8: Comercialización | M8: Oleoducto | N8: Fiscalización | P8: Total | Q8: Localidad 1 | S8: Localidad 2
A9: Piura / Tumbes | Q9: Piura | S9: Tumbes
A10: - | B10: I | C10: Licencia | D10: Quincena | E10: F2 | F10: Bls | G10: 6306 | H10: 5602 | I10: 68.7235 | J10: 70.6862 | N10: 86.89 | O10: 829267.59 | P10: 155487.67 | Q10: 124390.14 | R10: 0.15 | S10: 31097.53 | T10: 0.0375
A11: - | B11: I GAS | C11: Licencia | D11: Quincena | E11: F2 | F11: MM BTU | G11: 44983.374 | H11: 34344.505 | I11: 3 | J11: 3 | N11: 2479.35 | O11: 235504.29 | P11: 44157.05 | Q11: 35325.64 | R11: 0.15 | S11: 8831.41 | T11: 0.0375
A12: - | B12: II | C12: Licencia | D12: Quincena | E12: F2 | F12: Bls | O12: 0 | P12: 0 | Q12: 0 | R12: 0.15 | S12: 0 | T12: 0.0375
A13: - | B13: II - GAS | C13: Licencia | D13: Quincena | E13: F2 | F13: MM BTU | O13: 0 | P13: 0 | Q13: 0 | R13: 0.15 | S13: 0 | T13: 0.0375
A14: - | B14: III | C14: Licencia | D14: Quincena | E14: F2 | F14: Bls | G14: 0 | H14: 0 | I14: 0 | J14: 0 | O14: 0 | P14: 0 | Q14: 0 | R14: 0.15 | S14: 0 | T14: 0.0375
A15: - | B15: III - GAS | C15: Licencia | D15: Quincena | E15: F2 | F15: MM BTU | G15: 88294.495 | H15: 77796.325 | I15: 2.9305 | J15: 2.9305 | N15: 492.37 | O15: 486236.78 | P15: 91169.4 | Q15: 72935.52 | R15: 0.15 | S15: 18233.88 | T15: 0.0375
A16: - | B16: IV | C16: Licencia | D16: Quincena | E16: F2 | F16: Bls | G16: 0 | H16: 0 | I16: 0 | J16: 0 | O16: 0 | P16: 0 | Q16: 0 | R16: 0.15 | S16: 0 | T16: 0.0375
A17: - | B17: IV - GAS | C17: Licencia | D17: Quincena | E17: F2 | F17: Bls | G17: 71638.013 | H17: 62417.464 | I17: 2.718 | J17: 2.718 | N17: 847.87 | O17: 363514.92 | P17: 68159.05 | Q17: 54527.24 | R17: 0.15 | S17: 13631.81 | T17: 0.0375
A18: - | B18: V | C18: Licencia | D18: Quincena | E18: F2 | F18: Bls | G18: 2320 | H18: 252.6981 | I18: 67.7477 | J18: 69.6809 | N18: 459.78 | O18: 174323.11 | P18: 32685.58 | Q18: 26148.47 | R18: 0.15 | S18: 6537.12 | T18: 0.0375
A19: - | B19: VI (T) | C19: Licencia | D19: Quincena | E19: F2 | F19: Bls | O19: 0 | P19: 0 | Q19: 0 | R19: 0.15 | S19: 0 | T19: 0.0375
A20: - | B20: VI - GAS | C20: Licencia | D20: Quincena | E20: F2 | F20: MM BTU | O20: 0 | P20: 0 | Q20: 0 | R20: 0.15 | S20: 0 | T20: 0.0375
A21: - | B21: VII (T) | C21: Licencia | D21: Quincena | E21: F2 | F21: Bls | G21: 12941 | H21: 15190 | I21: 67.7477 | J21: 69.6809 | N21: 271.52 | O21: 1934904.3 | P21: 362794.56 | Q21: 290235.65 | R21: 0.15 | S21: 72558.91 | T21: 0.0375
A22: - | B22: IX | C22: Licencia | D22: Quincena | E22: F2 | F22: Bls | G22: 1478 | H22: 4096 | I22: 68.7235 | J22: 70.6862 | N22: 293.25 | O22: 390810.76 | P22: 73277.02 | Q22: 58621.61 | R22: 0.15 | S22: 14655.4 | T22: 0.0375
A23: - | B23: X | C23: Licencia | D23: Quincena | E23: F2 | F23: Bls | G23: 31725.2 | H23: 40887.6 | I23: 70.5277 | J23: 71.801 | N23: 2332.21 | O23: 5170943.8 | P23: 969551.95 | Q23: 775641.56 | R23: 0.15 | S23: 193910.39 | T23: 0.0375
A24: - | B24: X - GAS | C24: Licencia | D24: Quincena | E24: F2 | F24: MM BTU | G24: 78633.34 | H24: 66385.932 | I24: 2.9 | J24: 2.9 | N24: 1495.91 | O24: 419059.98 | P24: 78573.75 | Q24: 62859 | R24: 0.15 | S24: 15714.75 | T24: 0.0375
A25: - | B25: XV | C25: Licencia | D25: Quincena | E25: F2 | F25: Bls | O25: 0 | P25: 0 | Q25: 0 | R25: 0.15 | S25: 0 | T25: 0.0375
A26: - | B26: XIII Crudo | C26: Licencia | D26: Quincena | E26: F2 | F26: Bls | G26: 5017.0715 | H26: 1376.2829 | I26: 65.5835 | J26: 70.6862 | N26: 3037.46 | O26: 423283.85 | P26: 79365.72 | Q26: 63492.58 | R26: 0.15 | S26: 15873.14 | T26: 0.0375
A27: - | B27: XIII Gas | C27: Licencia | D27: Quincena | E27: F2 | F27: MM BTU | G27: 0 | H27: 57179.021 | I27: 0 | J27: 2.9627326 | N27: 3321.03 | O27: 169406.15 | P27: 31763.64 | Q27: 25410.93 | R27: 0.15 | S27: 6352.73 | T27: 0.0375
A28: - | B28: XX | C28: Licencia | D28: Quincena | E28: F2 | F28: Bls | N28: 188.26 | O28: -188.26 | P28: -35.3 | Q28: -7.06 | R28: 0.0375 | S28: -28.24 | T28: 0.15
A29: - | B29: Z-1 Crudo | C29: Licencia | D29: Quincena | E29: F2 | F29: Bls | N29: 955.77 | O29: -955.77 | P29: -179.21 | Q29: -35.84 | R29: 0.0375 | S29: -143.37 | T29: 0.15
A30: - | B30: Z-69 Crudo | C30: Licencia | D30: Quincena | E30: F2 | F30: Bls | G30: 55682 | H30: 33077 | I30: 68.12 | J30: 70.618 | N30: 3194.96 | O30: 6125694.5 | P30: 1148567.7 | Q30: 918854.17 | R30: 0.15 | S30: 229713.54 | T30: 0.0375
A31: - | B31: Z-69 Gas | C31: Licencia | D31: Quincena | E31: F2 | F31: MM BTU | G31: 125024.2 | H31: 111836.46 | I31: 2.7443704 | J31: 2.7455107 | N31: 861.64 | O31: 650160.91 | P31: 121905.17 | Q31: 97524.13 | R31: 0.15 | S31: 24381.04 | T31: 0.0375
A32: - | B32: Z-69 Lgn | C32: Licencia | D32: Quincena | E32: F2 | F32: Bls | G32: 10472 | H32: 9282 | I32: 35.677 | J32: 36.2948 | N32: 937.66 | O32: 709560.21 | P32: 133042.54 | Q32: 106434.03 | R32: 0.15 | S32: 26608.51 | T32: 0.0375
A33: - | B33: Ajustes meses anteriores (1) | O33: 87942.63 | P33: 16489.24 | Q33: 13191.39 | S33: 3297.84
B34: Subtotal | C34: Piura / Tumbes US$ | O34: 18169470 | P34: 3406775.5 | Q34: 2725549.2 | S34: 681226.39 | T34: 0
C35: Piura / Tumbes S/. | P35: 11767003 | Q35: 9414046.8 | S35: 2352956
A36: Provincia Puerto Inca Huanuco | Q36: Puerto Inca
A37: - | B37: 131 | C37: Licencia | D37: Quincena | E37: F2 | F37: Bls | H37: 10812 | J37: 57.1159 | N37: 3772.39 | O37: 613764.72 | P37: 92064.71 | Q37: 92064.71 | R37: 0.15
A38: - | B38: Ajustes meses anteriores (2)
B39: Subtotal | C39: Provincia Puerto Inca Huanuco US$ | O39: 613764.72 | P39: 92064.71 | Q39: 92064.71 | S39: 0
C40: Provincia Puerto Inca Huanuco S/. | P40: 317991.51 | Q40: 317991.51 | S40: 0
A41: Loreto / Ucayali | Q41: Loreto | S41: Ucayali
A42: - | B42: 8 | C42: Licencia | D42: Quincena | E42: F2 | F42: Bls | G42: 33026 | H42: 76714 | I42: 63.2397 | J42: 64.006122 | N42: 5053.98 | O42: 6993666 | P42: 1311312.4 | Q42: 1049049.9 | R42: 0.15 | S42: 262262.48 | T42: 0.0375
A43: - | B43: 31-C GAS | C43: Licencia | D43: Quincena | E43: F2 | F43: MM BTU | G43: 36589.816 | H43: 79149.989 | I43: 3.6039 | J43: 3.6041 | N43: 1677.65 | O43: 415452.86 | P43: 77897.41 | Q43: 15579.48 | R43: 0.0375 | S43: 62317.93 | T43: 0.15
A44: - | B44: 31-C LGN (*) | C44: Licencia | D44: Quincena | E44: F3 | F44: Bls | N44: 2139.61 | O44: -2139.61 | P44: -401.18 | Q44: -80.24 | R44: 0.0375 | S44: -320.94 | T44: 0.15
A45: - | B45: 95 | C45: Licencia | D45: Quincena | E45: F2 | F45: Bls | G45: 201738 | H45: 196782 | I45: 47.3006 | J45: 49.853 | N45: 5053.98 | O45: 19347448 | P45: 3627646.4 | Q45: 2902117.1 | R45: 0.15 | S45: 725529.28 | T45: 0.0375
A46: - | B46: 67 | C46: Licencia | D46: Quincena | E46: F2 | F46: Bls | O46: 0 | P46: 0 | Q46: 0 | R46: 0.15 | S46: 0 | T46: 0.0375
A47: - | B47: Ajustes meses anteriores (3) | P47: 0 | Q47: 0 | S47: 0
B48: Subtotal | C48: Loreto / Ucayali US$ | O48: 26754427 | P48: 5016455 | Q48: 3966666.3 | S48: 1049788.8
C49: Loreto / Ucayali S/. | P49: 17326836 | Q49: 13700865 | S49: 3625970.3
A50: Cusco | P50: V. Regalías | Q50: Cusco
A51: - | B51: 88 LGN | C51: Licencia | D51: Quincena | E51: F4 | F51: Bls | G51: 698189 | H51: 604305 | I51: 34.2622 | J51: 34.8313 | N51: 2647.18 | O51: 44970220 | P51: 16746910 | Q51: 8373455 | R51: 0.5
A52: - | B52: 88 GAS | C52: Licencia | D52: Quincena | E52: F4 | F52: MM BTU | G52: 12463191 | H52: 11097048 | I52: 2.8017 | J52: 2.7979 | N52: 4326.99 | O52: 65967391 | P52: 24613072 | Q52: 12306536 | R52: 0.5
A53: - | B53: 56 LGN | C53: Licencia | D53: Quincena | E53: F4 | F53: Bls | G53: 161903 | H53: 138169 | I53: 34.2636 | J53: 34.8387 | N53: 1850.7 | O53: 10361008 | P53: 4144403.2 | Q53: 2072201.6 | R53: 0.5
A54: - | B54: 56 GAS | C54: Licencia | D54: Quincena | E54: F4 | F54: MM BTU | G54: 3658054.4 | H54: 3186263.7 | I54: 3.986 | J54: 3.985 | N54: 2507.42 | O54: 27278266 | P54: 10365741 | Q54: 5182870.5 | R54: 0.5
A55: - | B55: 57 LGN | C55: Licencia | D55: Quincena | E55: F4 | F55: Bls | G55: 231742 | H55: 202637 | I55: 32.4945 | J55: 33.4457 | N55: 775.47 | O55: 14307677 | P55: 952815.97 | Q55: 476407.98 | R55: 0.5
A56: - | B56: 57 GAS | C56: Licencia | D56: Quincena | E56: F4 | F56: MM BTU | G56: 3835520.8 | H56: 3325250.1 | I56: 3.869 | J56: 3.869 | N56: 1884.72 | O56: 27705023 | P56: 3029445.5 | Q56: 1514722.8 | R56: 0.5
A57: - | B57: Ajustes meses anteriores (4) | O57: 4446609.5 | P57: 912982.49 | Q57: 456491.24
B58: Subtotal | C58: Cusco US$ | O58: 1.9503619e+08 | P58: 60765370 | Q58: 30382685
C59: Cusco S/. | G59: 3.986 | H59: 3.985 | Q59: 1.0494179e+08
A60: Total General | G60: 0 | H60: 0 | I60: 0 | J60: #REF! | K60: #REF! | M60: 0 | N60: 52946.02 | O60: 2.4057385e+08 | P60: 38897980 | Q60: 1.3435362e+08
A62: (*) | B62: Determinación de Canasta de los Líquidos de Gas Natural (VLGNF) | H62: = ( VC * %P + (PB - TF - TT) * (1 - %P))
B63: Simbolo | C63: Descripcion | E63: 1ra. Q | F63: 2da. Q | H63: 1ra. Q | O63: 7530340.4 | P63: 14839630
B64: VC | C64: Canasta de Petróleo | H64: = (0.0000 * 0.00% + (0.0000 - 0.0000 - 0.0000) * (1 - 0.00%)) | N64: 12865393 | O64: 500767.64 | P64: 1621971.6
B65: PB | C65: Precio del GLP | H65: 0 | M65: 0.0942 | N65: 0.0989 | O65: 0.0665 | P65: 0.1093
B66: TF | C66: Tarifa de Fraccionam. | M66: 0.4 | N66: 0.4 | O66: 452048.33
B67: %P | C67: % Contenido Pentanos | H67: 2da. Q | M67: 0.38 | O67: 6777336.3
B68: QLGNF | C68: Volumen de LGN | H68: = (0.0000 * 0.00% + (0.0000 - 0.0000 - 0.0000) * (1 - 0.00%)) | O68: 0.0667
B69: TT | C69: Tarifa de Transporte | H69: 0

Sheet Mar
A1: Período de Cálculo: | E1: 46082 | F1: 3.442 | S1: ,
A2: PERUPETRO S.A.
A3: DETERMINACION DEL CANON, SOBRECANON y PARTICIPACION (US$)
A4: Correspondiente a Marzo 2026
A5: Tipo de Cambio= 3.442
A7: Localidad | C7: Modalidad de Contrato | D7: Calculo del Canon | F7: Volumen Producción / Venta | I7: Canasta o Valor Venta (US$/Unidad) | K7: Deducción de Gastos para determinación de valor de producción en Punto de Fiscalización (US$) | O7: Valor de la Producción (US$) | P7: Canon y Sobrecanon / Participación (US$)
A8: - Lote | D8: Período | E8: Fórmula | F8: Unidades | G8: 1ra. Q | H8: 2da. Q / Mes | I8: 1ra. Q | J8: 2da. Q / Mes | K8: Flete Marítimo | L8: Comercialización | M8: Oleoducto | N8: Fiscalización | P8: Total | Q8: Localidad 1 | S8: Localidad 2
A9: Piura / Tumbes | Q9: Piura | S9: Tumbes
A10: - | B10: I | C10: Licencia | D10: Quincena | E10: F2 | F10: Bls | G10: 5446 | H10: 8723 | I10: 94.5525 | J10: 123.9661 | N10: 108.01 | O10: 1596181.2 | P10: 299283.98 | Q10: 239427.18 | R10: 0.15 | S10: 59856.8 | T10: 0.0375
A11: - | B11: I GAS | C11: Licencia | D11: Quincena | E11: F2 | F11: MM BTU | G11: 45326.457 | H11: 50147.147 | I11: 3 | J11: 3 | N11: 2539.2 | O11: 283881.61 | P11: 53227.8 | Q11: 42582.24 | R11: 0.15 | S11: 10645.56 | T11: 0.0375
A12: - | B12: II | C12: Licencia | D12: Quincena | E12: F2 | F12: Bls | O12: 0 | P12: 0 | Q12: 0 | R12: 0.15 | S12: 0 | T12: 0.0375
A13: - | B13: II - GAS | C13: Licencia | D13: Quincena | E13: F2 | F13: MM BTU | O13: 0 | P13: 0 | Q13: 0 | R13: 0.15 | S13: 0 | T13: 0.0375
A14: - | B14: III | C14: Licencia | D14: Quincena | E14: F2 | F14: Bls | G14: 0 | H14: 0 | I14: 96.9525 | J14: 123.9661 | N14: 0 | O14: 0 | P14: 0 | Q14: 0 | R14: 0.15 | S14: 0 | T14: 0.0375
A15: - | B15: III - GAS | C15: Licencia | D15: Quincena | E15: F2 | F15: MM BTU | G15: 84112.209 | H15: 99788.559 | I15: 2.9633 | J15: 2.9633 | N15: 612.05 | O15: 544341.1 | P15: 102063.96 | Q15: 81651.17 | R15: 0.15 | S15: 20412.79 | T15: 0.0375
A16: - | B16: IV | C16: Licencia | D16: Quincena | E16: F2 | F16: Bls | G16: 0 | H16: 0 | I16: 96.9525 | J16: 123.9661 | N16: 0 | O16: 0 | P16: 0 | Q16: 0 | R16: 0.15 | S16: 0 | T16: 0.0375
A17: - | B17: IV - GAS | C17: Licencia | D17: Quincena | E17: F2 | F17: Bls | G17: 74013.029 | H17: 73289.559 | I17: 2.4112 | J17: 2.4112 | N17: 907.72 | O17: 354268.27 | P17: 66425.3 | Q17: 53140.24 | R17: 0.15 | S17: 13285.06 | T17: 0.0375
A18: - | B18: V | C18: Licencia | D18: Quincena | E18: F2 | F18: Bls | G18: 2319 | H18: 1567 | I18: 89.5893 | J18: 107.8822 | N18: 571.54 | O18: 376237.46 | P18: 70544.52 | Q18: 56435.62 | R18: 0.15 | S18: 14108.9 | T18: 0.0375
A19: - | B19: VI (T) | C19: Licencia | D19: Quincena | E19: F2 | F19: Bls | O19: 0 | P19: 0 | Q19: 0 | R19: 0.15 | S19: 0 | T19: 0.0375
A20: - | B20: VI - GAS | C20: Licencia | D20: Quincena | E20: F2 | F20: MM BTU | O20: 0 | P20: 0 | Q20: 0 | R20: 0.15 | S20: 0 | T20: 0.0375
A21: - | B21: VII (T) | C21: Licencia | D21: Quincena | E21: F2 | F21: Bls | G21: 14330 | H21: 18731 | I21: 89.5893 | J21: 107.8822 | N21: 337.53 | O21: 3304218.6 | P21: 619540.99 | Q21: 495632.79 | R21: 0.15 | S21: 123908.2 | T21: 0.0375
A22: - | B22: IX | C22: Licencia | D22: Quincena | E22: F2 | F22: Bls | G22: 2255 | H22: 4286 | I22: 96.9525 | J22: 123.9661 | N22: 364.53 | O22: 749582.06 | P22: 140546.64 | Q22: 112437.31 | R22: 0.15 | S22: 28109.33 | T22: 0.0375
A23: - | B23: X | C23: Licencia | D23: Quincena | E23: F2 | F23: Bls | G23: 123883 | H23: 105520 | I23: 89.3045 | J23: 111.8943 | N23: 2752.86 | O23: 22867643 | P23: 4287683.1 | Q23: 3430146.5 | R23: 0.15 | S23: 857536.61 | T23: 0.0375
A24: - | B24: X - GAS | C24: Licencia | D24: Quincena | E24: F2 | F24: MM BTU | G24: 200133.88 | H24: 208679.97 | I24: 2.9 | J24: 2.9 | N24: 1713.28 | O24: 1183846.9 | P24: 221971.29 | Q24: 177577.03 | R24: 0.15 | S24: 44394.26 | T24: 0.0375
A25: - | B25: XV | C25: Licencia | D25: Quincena | E25: F2 | F25: Bls | O25: 0 | P25: 0 | Q25: 0 | R25: 0.15 | S25: 0 | T25: 0.0375
A26: - | B26: XIII Crudo | C26: Licencia | D26: Quincena | E26: F2 | F26: Bls | G26: 10050 | H26: 11020 | I26: 93.6325 | J26: 123.8661 | N26: 3775.79 | O26: 2302235.3 | P26: 431669.11 | Q26: 345335.29 | R26: 0.15 | S26: 86333.82 | T26: 0.0375
A27: - | B27: XIII Gas | C27: Licencia | D27: Quincena | E27: F2 | F27: MM BTU | G27: 401172.61 | H27: 385924.17 | I27: 2.9735956 | J27: 3.0248985 | N27: 3628.15 | O27: 2360306.5 | P27: 442557.47 | Q27: 354045.99 | R27: 0.15 | S27: 88511.49 | T27: 0.0375
A28: - | B28: XX | C28: Licencia | D28: Quincena | E28: F2 | F28: Bls | N28: 234.02 | O28: -234.02 | P28: -43.88 | Q28: -8.78 | R28: 0.0375 | S28: -35.1 | T28: 0.15
A29: - | B29: Z-1 Crudo | C29: Licencia | D29: Quincena | E29: F2 | F29: Bls | H29: 0 | J29: 116.8761 | N29: 0 | O29: 0 | P29: 0 | Q29: 0 | R29: 0.0375 | S29: 0 | T29: 0.15
A30: - | B30: Z-69 Crudo | C30: Licencia | D30: Quincena | E30: F2 | F30: Bls | G30: 63592 | H30: 62533 | I30: 90.098 | J30: 107.5175 | N30: 3432.57 | O30: 12449471 | P30: 2334275.9 | Q30: 1867420.7 | R30: 0.15 | S30: 466855.17 | T30: 0.0375
A31: - | B31: Z-69 Gas | C31: Licencia | D31: Quincena | E31: F2 | F31: MM BTU | G31: 127045.16 | H31: 129905.6 | I31: 2.7358789 | J31: 2.7461826 | N31: 1071.08 | O31: 704324.67 | P31: 132060.87 | Q31: 105648.7 | R31: 0.15 | S31: 26412.17 | T31: 0.0375
A32: - | B32: Z-69 Lgn | C32: Licencia | D32: Quincena | E32: F2 | F32: Bls | G32: 10656 | H32: 11220 | I32: 49.7446 | J32: 61.5652 | N32: 1165.59 | O32: 1219674.4 | P32: 228688.95 | Q32: 182951.16 | R32: 0.15 | S32: 45737.79 | T32: 0.0375
A33: - | B33: Ajustes meses anteriores (1) | O33: 46502201 | P33: 8719162.6 | Q33: 6975330.1 | S33: 1743832.5
B34: Subtotal | C34: Piura / Tumbes US$ | O34: 96798179 | P34: 18149659 | Q34: 14519753 | S34: 3629905.4 | T34: 0
C35: Piura / Tumbes S/. | P35: 62471125 | Q35: 49976991 | S35: 12494134
A36: Provincia Puerto Inca Huanuco | Q36: Puerto Inca
A37: - | B37: 131 | C37: Licencia | D37: Quincena | E37: F2 | F37: Bls | G37: 2361 | H37: 8749 | I37: 75.9972 | J37: 97.3319 | N37: 4689.36 | O37: 1026296.8 | P37: 153944.52 | Q37: 153944.52 | R37: 0.15
A38: - | B38: Ajustes meses anteriores (2)
B39: Subtotal | C39: Provincia Puerto Inca Huanuco US$ | O39: 1026296.8 | P39: 153944.52 | Q39: 153944.52 | S39: 0
C40: Provincia Puerto Inca Huanuco S/. | P40: 529877.04 | Q40: 529877.04 | S40: 0
A41: Loreto / Ucayali | Q41: Loreto | S41: Ucayali
A42: - | B42: 8 | C42: Licencia | D42: Quincena | E42: F2 | F42: Bls | G42: 80516 | H42: 0 | I42: 81.260289 | J42: 0 | N42: 459.04 | O42: 6542753.4 | P42: 1226766.3 | Q42: 981413.01 | R42: 0.15 | S42: 245353.25 | T42: 0.0375
A43: - | B43: 31-C GAS | C43: Licencia | D43: Quincena | E43: F2 | F43: MM BTU | G43: 166261.06 | H43: 112729.85 | I43: 3.6057 | J43: 3.6018 | N43: 1792.94 | O43: 1003724.9 | P43: 188198.42 | Q43: 37639.68 | R43: 0.0375 | S43: 150558.74 | T43: 0.15
A44: - | B44: 31-C LGN (*) | C44: Licencia | D44: Quincena | E44: F3 | F44: Bls | N44: 2659.7 | O44: -2659.7 | P44: -498.69 | Q44: -99.74 | R44: 0.0375 | S44: -398.96 | T44: 0.15
A45: - | B45: 95 | C45: Licencia | D45: Quincena | E45: F2 | F45: Bls | G45: 212377 | H45: 212013 | I45: 66.3191 | J45: 82.2024 | N45: 6286.99 | O45: 31506342 | P45: 5907439.1 | Q45: 4725951.3 | R45: 0.15 | S45: 1181487.8 | T45: 0.0375
A46: - | B46: 67 | C46: Licencia | D46: Quincena | E46: F2 | F46: Bls | O46: 0 | P46: 0 | Q46: 0 | R46: 0.15 | S46: 0 | T46: 0.0375
A47: - | B47: Ajustes meses anteriores (3) | O47: 570957.18 | P47: 107054.47 | Q47: 85643.58 | S47: 21410.89
B48: Subtotal | C48: Loreto / Ucayali US$ | O48: 39621118 | P48: 7428959.6 | Q48: 5830547.8 | S48: 1598411.7
C49: Loreto / Ucayali S/. | P49: 25570479 | Q49: 20068746 | S49: 5501733.2
A50: Cusco | P50: V. Regalías | Q50: Cusco
A51: - | B51: 88 LGN | C51: Licencia | D51: Quincena | E51: F4 | F51: Bls | G51: 134322 | H51: 723542 | I51: 45.7175 | J51: 55.8891 | O51: 46578977 | P51: 17346011 | Q51: 8673005.6 | R51: 0.5
A52: - | B52: 88 GAS | C52: Licencia | D52: Quincena | E52: F4 | F52: MM BTU | G52: 2759800.7 | H52: 14421569 | I52: 3.6943 | J52: 3.2939 | O52: 57699401 | P52: 21588519 | Q52: 10794259 | R52: 0.5
A53: - | B53: 56 LGN | C53: Licencia | D53: Quincena | E53: F4 | F53: Bls | G53: 10474 | H53: 184680 | I53: 45.5241 | J53: 55.8899 | O53: 10798566 | P53: 4319426.5 | Q53: 2159713.2 | R53: 0.5
A54: - | B54: 56 GAS | C54: Licencia | D54: Quincena | E54: F4 | F54: MM BTU | G54: 251353.37 | H54: 3717230.4 | I54: 10.125 | J54: 10.206 | O54: 40483007 | P54: 15383543 | Q54: 7691771.3 | R54: 0.5
A55: - | B55: 57 LGN | C55: Licencia | D55: Quincena | E55: F4 | F55: Bls | G55: 13053 | H55: 249048 | I55: 45.5289 | J55: 57.9107 | O55: 15016833 | P55: 1016200.5 | Q55: 508100.24 | R55: 0.5
A56: - | B56: 57 GAS | C56: Licencia | D56: Quincena | E56: F4 | F56: MM BTU | G56: 248415.04 | H56: 4091297.4 | I56: 3.986 | J56: 3.986 | O56: 17298094 | P56: 1929806.9 | Q56: 964903.47 | R56: 0.5
A57: - | B57: Ajustes meses anteriores (4) | O57: 2006535.9 | P57: 631015 | Q57: 315507.51
B58: Subtotal | C58: Cusco US$ | G58: 251353.37 | H58: 3717230.4 | O58: 1.8988141e+08 | P58: 62214521 | Q58: 31107261
C59: Cusco S/. | G59: 10.125 | H59: 10.206 | Q59: 1.0707119e+08
A60: Total General | G60: 2544952.9 | H60: 37938054 | I60: 40483007 | J60: #REF! | K60: #REF! | M60: 0 | N60: 39101.95 | O60: 3.2732701e+08 | P60: 56839823 | Q60: 1.9564267e+08
A62: (*) | B62: Determinación de Canasta de los Líquidos de Gas Natural (VLGNF) | H62: = ( VC * %P + (PB - TF - TT) * (1 - %P))
