Workbook
Name UCA.AGRO.DATE: '01.XLS'!$B$5:$FA$5
Name UCA.AGRO.NAME: '01.XLS'!$A$7:$A$55
Name UCA.AGRO.VAL: '01.XLS'!$B$7:$FA$55
Name UCA.AGROOTROS.DATE: '02.XLS'!$B$5:$FA$5
Name UCA.AGROOTROS.NAME: '02.XLS'!$A$7:$A$51
Name UCA.AGROOTROS.VAL: '02.XLS'!$B$7:$FA$51
Name UCA.ASERRADA.DATE: '09.XLS'!$B$5:$FA$5
Name UCA.ASERRADA.NAME: '09.XLS'!$A$7:$A$41
Name UCA.ASERRADA.VAL: '09.XLS'!$B$7:$FA$41
Name UCA.COSECHAS.DATE: '05.XLS'!$B$5:$FA$5
Name UCA.COSECHAS.NAME: '05.XLS'!$A$7:$A$34
Name UCA.COSECHAS.VAL: '05.XLS'!$B$7:$FA$34
Name UCA.COSECHASOTROS.DATE: '06.XLS'!$B$5:$FA$5
Name UCA.COSECHASOTROS.NAME: '06.XLS'!$A$7:$A$49
Name UCA.COSECHASOTROS.VAL: '06.XLS'!$B$7:$FA$49
Name UCA.GGL.DATE: 'GASTOS G.L.'!$B$5:$FA$5
Name UCA.GGL.NAME: 'GASTOS G.L.'!$A$7:$A$30
Name UCA.GGL.VAL: 'GASTOS G.L.'!$B$7:$FA$30
Name UCA.GGN.DATE: 'GASTOS G.N.'!$B$5:$FA$5
Name UCA.GGN.NAME: 'GASTOS G.N.'!$A$7:$A$30
Name UCA.GGN.VAL: 'GASTOS G.N.'!$B$7:$FA$30
Name UCA.GGR.DATE: 'GASTOS G.R.'!$B$5:$FA$5
Name UCA.GGR.NAME: 'GASTOS G.R.'!$A$7:$A$31
Name UCA.GGR.VAL: 'GASTOS G.R.'!$B$7:$FA$31
Name UCA.HIDROCARBURO.DATE: '10.XLS'!$B$5:$FA$5
Name UCA.HIDROCARBURO.NAME: '10.XLS'!$A$7:$A$14
Name UCA.HIDROCARBURO.VAL: '10.XLS'!$B$7:$FA$14
Name UCA.IGL.DATE: 'INVERSIÓN G.L.'!$B$5:$FA$5
Name UCA.IGL.NAME: 'INVERSIÓN G.L.'!$A$7:$A$32
Name UCA.IGL.VAL: 'INVERSIÓN G.L.'!$B$7:$FA$32
Name UCA.IGN.DATE: 'INVERSIÓN G.N.'!$B$5:$FA$5
Name UCA.IGN.NAME: 'INVERSIÓN G.N.'!$A$7:$A$34
Name UCA.IGN.VAL: 'INVERSIÓN G.N.'!$B$7:$FA$34
Name UCA.IGR.DATE: 'INVERSIÓN G.R.'!$B$5:$FA$5
Name UCA.IGR.NAME: 'INVERSIÓN G.R.'!$A$7:$A$34
Name UCA.IGR.VAL: 'INVERSIÓN G.R.'!$B$7:$FA$34
Name UCA.MANUFACTURA.DATE: '11.XLS-BASE 2007'!$B$5:$FA$5
Name UCA.MANUFACTURA.NAME: '11.XLS-BASE 2007'!$A$7:$A$17
Name UCA.MANUFACTURA.VAL: '11.XLS-BASE 2007'!$B$7:$FA$17
Name UCA.MANUFACTURAVAR.NAME: '11.XLS-BASE 2007'!$A$23:$A$33
Name UCA.MANUFACTURAVAR.VAL: '11.XLS-BASE 2007'!$B$23:$FA$33
Name UCA.PESCA.DATE: '07.XLS'!$B$5:$FA$5
Name UCA.PESCA.NAME: '07.XLS'!$A$7:$A$54
Name UCA.PESCA.VAL: '07.XLS'!$B$7:$FA$54
Name UCA.ROLLIZA.DATE: '08.XLS'!$B$5:$FA$5
Name UCA.ROLLIZA.NAME: '08.XLS'!$A$7:$A$41
Name UCA.ROLLIZA.VAL: '08.XLS'!$B$7:$FA$41
Name UCA.SIEMBRAS.DATE: '03.XLS'!$B$5:$FN$5
Name UCA.SIEMBRAS.NAME: '03.XLS'!$A$7:$A$34
Name UCA.SIEMBRAS.VAL: '03.XLS'!$B$7:$FN$34
Name UCA.SIEMBRASOTROS.DATE: '04.XLS'!$B$5:$FN$5
Name UCA.SIEMBRASOTROS.NAME: '04.XLS'!$A$7:$A$49
Name UCA.SIEMBRASOTROS.VAL: '04.XLS'!$B$7:$FN$49
Name UCA.X.DATE: '15.XLS'!$B$5:$FA$5
Name UCA.X.NAME: '15.XLS'!$A$7:$A$34
Name UCA.X.VAL: '15.XLS'!$B$7:$FA$34

Sheet 01.XLS
A1: Cuadro N° 01
A2: UCAYALI: PRODUCCIÓN DE PRINCIPALES PRODUCTOS AGROPECUARIOS 1/
A3: (VBP y toneladas métricas)
B4: 2015 | N4: Total | O4: 2016 | AA4: Total | AB4: 2017 | AN4: Total | AO4: 2018 | BA4: Total | BB4: 2019 | BN4: Total | BO4: 2020 | CA4: Total | CB4: 2021 | CN4: Total | CO4: 2022 | DA4: Total | DB4: 2023 | DN4: Total | DO4: 2024 | EA4: Total | EB4: 2025 | EN4: Total | EO4: 2026 | FA4: Total | FC4: =CONCATENATE("Var.% ",FF4,"/",FF4-1) -> Var.% 2025/2024 | FE4: =FF4-1 -> 2024 | FF4: =YEAR(FC5) -> 2025 | FH4: PARA COMPROBAR
B5: 42005 | C5: 42036 | D5: 42064 | E5: 42095 | F5: 42125 | G5: 42156 | H5: 42186 | I5: 42217 | J5: 42248 | K5: 42278 | L5: 42309 | M5: 42339 | N5: =YEAR(M5) -> 2015 | O5: 42370 | P5: 42401 | Q5: 42430 | R5: 42461 | S5: 42491 | T5: 42522 | U5: 42552 | V5: 42583 | W5: 42614 | X5: 42644 | Y5: 42675 | Z5: 42705 | AA5: =YEAR(Z5) -> 2016 | AB5: 42736 | AC5: 42767 | AD5: 42795 | AE5: 42826 | AF5: 42856 | AG5: 42887 | AH5: 42917 | AI5: 42948 | AJ5: 42979 | AK5: 43009 | AL5: 43040 | AM5: 43070 | AN5: =YEAR(AM5) -> 2017 | AO5: 43101 | AP5: 43132 | AQ5: 43160 | AR5: 43191 | AS5: 43221 | AT5: 43252 | AU5: 43282 | AV5: 43313 | AW5: 43344 | AX5: 43374 | AY5: 43405 | AZ5: 43435 | BA5: =YEAR(AZ5) -> 2018 | BB5: 43466 | BC5: 43497 | BD5: 43525 | BE5: 43556 | BF5: 43586 | BG5: 43617 | BH5: 43647 | BI5: 43678 | BJ5: 43709 | BK5: 43739 | BL5: 43770 | BM5: 43800 | BN5: =YEAR(BM5) -> 2019 | BO5: 43831 | BP5: 43862 | BQ5: 43891 | BR5: 43922 | BS5: 43952 | BT5: 43983 | BU5: 44013 | BV5: 44044 | BW5: 44075 | BX5: 44105 | BY5: 44136 | BZ5: 44166 | CA5: =YEAR(BZ5) -> 2020 | CB5: 44197 | CC5: 44228 | CD5: 44256 | CE5: 44287 | CF5: 44317 | CG5: 44348 | CH5: 44378 | CI5: 44409 | CJ5: 44440 | CK5: 44470 | CL5: 44501 | CM5: 44531 | CN5: =YEAR(CM5) -> 2021 | CO5: 44562 | CP5: 44593 | CQ5: 44621 | CR5: 44652 | CS5: 44682 | CT5: 44713 | CU5: 44743 | CV5: 44774 | CW5: 44805 | CX5: 44835 | CY5: 44866 | CZ5: 44896 | DA5: =YEAR(CZ5) -> 2022 | DB5: 44927 | DC5: 44958 | DD5: 44986 | DE5: 45017 | DF5: 45047 | DG5: 45078 | DH5: 45108 | DI5: 45139 | DJ5: 45170 | DK5: 45200 | DL5: 45231 | DM5: 45261 | DN5: =YEAR(DM5) -> 2023 | DO5: 45292 | DP5: 45323 | DQ5: 45352 | DR5: 45383 | DS5: 45413 | DT5: 45444 | DU5: 45474 | DV5: 45505 | DW5: 45536 | DX5: 45566 | DY5: 45597 | DZ5: 45627 | EA5: =YEAR(DZ5) -> 2024 | EB5: 45658 | EC5: 45689 | ED5: 45717 | EE5: 45748 | EF5: 45778 | EG5: 45809 | EH5: 45839 | EI5: 45870 | EJ5: 45901 | EK5: 45931 | EL5: 45962 | EM5: 45992 | EN5: =YEAR(EM5) -> 2025 | EO5: 46023 | EP5: 46054 | EQ5: 46082 | ER5: 46113 | ES5: 46143 | ET5: 46174 | EU5: 46204 | EV5: 46235 | EW5: 46266 | EX5: 46296 | EY5: 46327 | EZ5: 46357 | FA5: =YEAR(EZ5) -> 2026 | FC5: =EL5 -> 45962 | FD5: =CONCATENATE("Ene.-",TEXT(FC5,"MMM.")) -> Ene.-Nov. | FE5: =FD5 -> Ene.-Nov. | FF5: =FD5 -> Ene.-Nov. | FH5: NO BORRRAR
A7: AGROPECUARIO 2/ | B7: =SUM(B8,B9) -> 38760.828 | C7: =SUM(C8,C9) -> 38938.516 | D7: =SUM(D8,D9) -> 41960.989 | E7: =SUM(E8,E9) -> 42033.767 | F7: =SUM(F8,F9) -> 38668.799 | G7: =SUM(G8,G9) -> 38459.462 | H7: =SUM(H8,H9) -> 34407.461 | I7: =SUM(I8,I9) -> 34410.185 | ... M7: =SUM(M8,M9) -> 36358.656 | N7: =SUM(B7:M7) -> 461014.28 | O7: =SUM(O8,O9) -> 33536.73 | P7: =SUM(P8,P9) -> 34432.231 | Q7: =SUM(Q8,Q9) -> 36968.369 | R7: =SUM(R8,R9) -> 39065.915 | S7: =SUM(S8,S9) -> 38904.029 | T7: =SUM(T8,T9) -> 39241.798 | U7: =SUM(U8,U9) -> 33273.882 | V7: =SUM(V8,V9) -> 30653.481 | ... Z7: =SUM(Z8,Z9) -> 37771.783 | AA7: =SUM(O7:Z7) -> 432418.43 | AB7: =SUM(AB8,AB9) -> 32281.672 | AC7: =SUM(AC8,AC9) -> 36554.884 | AD7: =SUM(AD8,AD9) -> 43293.764 | AE7: =SUM(AE8,AE9) -> 39582.055 | AF7: =SUM(AF8,AF9) -> 43831.377 | AG7: =SUM(AG8,AG9) -> 44243.127 | AH7: =SUM(AH8,AH9) -> 42058.807 | AI7: =SUM(AI8,AI9) -> 36723.214 | ... AM7: =SUM(AM8,AM9) -> 43880.2 | AN7: =SUM(AB7:AM7) -> 511748.59 | AO7: =SUM(AO8,AO9) -> 38091.032 | AP7: =SUM(AP8,AP9) -> 37823.768 | AQ7: =SUM(AQ8,AQ9) -> 43249.204 | AR7: =SUM(AR8,AR9) -> 45238.725 | AS7: =SUM(AS8,AS9) -> 51642.304 | AT7: =SUM(AT8,AT9) -> 54312.281 | AU7: =SUM(AU8,AU9) -> 48791.589 | AV7: =SUM(AV8,AV9) -> 46436.351 | ... AZ7: =SUM(AZ8,AZ9) -> 47359.36 | BA7: =SUM(AO7:AZ7) -> 565980.89 | BB7: =SUM(BB8,BB9) -> 43439.109 | BC7: =SUM(BC8,BC9) -> 43156.495 | BD7: =SUM(BD8,BD9) -> 45637.677 | BE7: =SUM(BE8,BE9) -> 55712.548 | BF7: =SUM(BF8,BF9) -> 65538.257 | BG7: =SUM(BG8,BG9) -> 62316.623 | BH7: =SUM(BH8,BH9) -> 56605.858 | BI7: =SUM(BI8,BI9) -> 55149.705 | ... BM7: =SUM(BM8,BM9) -> 51605.006 | BN7: =SUM(BB7:BM7) -> 644679.63 | BO7: =SUM(BO8,BO9) -> 48895.218 | BP7: =SUM(BP8,BP9) -> 47475.876 | BQ7: =SUM(BQ8,BQ9) -> 50609.84 | BR7: =SUM(BR8,BR9) -> 57032.063 | BS7: =SUM(BS8,BS9) -> 61502.711 | BT7: =SUM(BT8,BT9) -> 63105.677 | BU7: =SUM(BU8,BU9) -> 57527.477 | BV7: =SUM(BV8,BV9) -> 64387.702 | ... BZ7: =SUM(BZ8,BZ9) -> 46990.257 | CA7: =SUM(BO7:BZ7) -> 649348.67 | CB7: =SUM(CB8,CB9) -> 47170.727 | CC7: =SUM(CC8,CC9) -> 50765.463 | CD7: =SUM(CD8,CD9) -> 57482.06 | CE7: =SUM(CE8,CE9) -> 65995.589 | CF7: =SUM(CF8,CF9) -> 75124.649 | CG7: =SUM(CG8,CG9) -> 72449.193 | CH7: =SUM(CH8,CH9) -> 70014.362 | CI7: =SUM(CI8,CI9) -> 64187.284 | ... CM7: =SUM(CM8,CM9) -> 59446.82 | CN7: =SUM(CB7:CM7) -> 748934.56 | CO7: =SUM(CO8,CO9) -> 59216.068 | CP7: =SUM(CP8,CP9) -> 53423.636 | CQ7: =SUM(CQ8,CQ9) -> 62239.816 | CR7: =SUM(CR8,CR9) -> 59727.853 | CS7: =SUM(CS8,CS9) -> 80912.127 | CT7: =SUM(CT8,CT9) -> 80897.88 | CU7: =SUM(CU8,CU9) -> 72996.447 | CV7: =SUM(CV8,CV9) -> 76511.922 | ... CZ7: =SUM(CZ8,CZ9) -> 63971.965 | DA7: =SUM(CO7:CZ7) -> 807608.06 | DB7: =SUM(DB8,DB9) -> 56178.83 | DC7: =SUM(DC8,DC9) -> 54121.879 | DD7: =SUM(DD8,DD9) -> 50776.446 | DE7: =SUM(DE8,DE9) -> 56283.124 | DF7: =SUM(DF8,DF9) -> 69655.139 | DG7: =SUM(DG8,DG9) -> 70236.774 | DH7: =SUM(DH8,DH9) -> 79554.611 | DI7: =SUM(DI8,DI9) -> 80042.525 | ... DM7: =SUM(DM8,DM9) -> 48723.482 | DN7: =SUM(DB7:DM7) -> 796977.84 | DO7: =SUM(DO8,DO9) -> 44596.747 | DP7: =SUM(DP8,DP9) -> 46193.9 | DQ7: =SUM(DQ8,DQ9) -> 53305.25 | DR7: =SUM(DR8,DR9) -> 47609.912 | DS7: =SUM(DS8,DS9) -> 43783.763 | DT7: =SUM(DT8,DT9) -> 43510.157 | DU7: =SUM(DU8,DU9) -> 52737.955 | DV7: =SUM(DV8,DV9) -> 76607.234 | ... DZ7: =SUM(DZ8,DZ9) -> 67738.083 | EA7: =SUM(DO7:DZ7) -> 712139.7 | EB7: =SUM(EB8,EB9) -> 59241.238 | EC7: =SUM(EC8,EC9) -> 57605.097 | ED7: =SUM(ED8,ED9) -> 53960.501 | EE7: =SUM(EE8,EE9) -> 39898.6 | EF7: =SUM(EF8,EF9) -> 59990.763 | EG7: =SUM(EG8,EG9) -> 75931.111 | EH7: =SUM(EH8,EH9) -> 64887.604 | EI7: =SUM(EI8,EI9) -> 64464.929 | ... EM7: =SUM(EM8,EM9) -> 65431.101 | EN7: =SUM(EB7:EM7) -> 768387.78 | EO7: =SUM(EO8,EO9) -> 64958.487 | EP7: =SUM(EP8,EP9) -> 60686.13 | EQ7: =SUM(EQ8,EQ9) -> 0 | ER7: =SUM(ER8,ER9) -> 0 | ES7: =SUM(ES8,ES9) -> 0 | ET7: =SUM(ET8,ET9) -> 0 | EU7: =SUM(EU8,EU9) -> 0 | EV7: =SUM(EV8,EV9) -> 0 | ... EZ7: =SUM(EZ8,EZ9) -> 0 | FA7: =SUM(EO7:EZ7) -> 125644.62 | FC7: =IFERROR((( _xlfn.XLOOKUP((DATE(YEAR($FC$5),MONTH($FC$5),1)),UCA.AGRO.DATE,$B7:$FA7) / _xlfn.XLOOKUP((DATE(YEAR($FC$5)-1,MONTH($FC$5),1)),UCA.AGRO.DATE,$B7:$FA7) )-1)*100,"") -> 7.5468804 | FD7: =IFERROR(((FF7/FE7)-1)*100,"") -> 9.0867344 | FE7: =SUMIFS($B7:$FA7,UCA.AGRO.DATE,">="&DATE(YEAR($FC$5)-1,1,1),UCA.AGRO.DATE,"<="&DATE(YEAR($FC$5)-1,MONTH($FC$5),1)) -> 644401.61 | FF7: =SUMIFS($B7:$FA7,UCA.AGRO.DATE,">="&DATE(YEAR($FC$5),1,1),UCA.AGRO.DATE,"<="&$FC$5) -> 702956.68
A8: A. AGRÍCOLA 2/ | B8: 29883.172 | C8: 28378.571 | D8: 31623.204 | E8: 31329.006 | F8: 30331.084 | G8: 30625.279 | H8: 26376.675 | I8: 27475.514 | J8: 34586.142 | K8: 33169.498 | L8: 29859.273 | M8: 29115.883 | N8: =SUM(B8:M8) -> 362753.3 | O8: 27924.724 | P8: 28974.418 | Q8: 32196.367 | R8: 33639.588 | S8: 32050.662 | T8: 32443.696 | U8: 27415.798 | V8: 24619.563 | W8: 28490.211 | X8: 35911.237 | Y8: 27759.485 | Z8: 31367.218 | AA8: =SUM(O8:Z8) -> 362792.97 | AB8: 28290.733 | AC8: 30780.946 | AD8: 36289.579 | AE8: 33061.038 | AF8: 35830.23 | AG8: 36596.366 | AH8: 35268.263 | AI8: 30574.373 | AJ8: 46503.493 | AK8: 50361.462 | AL8: 34738.759 | AM8: 37874.335 | AN8: =SUM(AB8:AM8) -> 436169.58 | AO8: 32923.047 | AP8: 33370.469 | AQ8: 37145.36 | AR8: 38405.828 | AS8: 45242.167 | AT8: 47323.275 | AU8: 42083.49 | AV8: 38094.056 | AW8: 42095.935 | AX8: 45544.921 | AY8: 42738.977 | AZ8: 38000.907 | BA8: =SUM(AO8:AZ8) -> 482968.43 | BB8: 36608.144 | BC8: 37535.891 | BD8: 37835.754 | BE8: 46557.349 | BF8: 56807.001 | BG8: 52978.063 | BH8: 47373.887 | BI8: 44112.879 | BJ8: 43031.247 | BK8: 46755.905 | BL8: 45275.854 | BM8: 39750.015 | BN8: =SUM(BB8:BM8) -> 534621.99 | BO8: 41944.238 | BP8: 41880.075 | BQ8: 42989.731 | BR8: 48147.788 | BS8: 53117.592 | BT8: 53793.559 | BU8: 48341.548 | BV8: 53906.186 | BW8: 48590.393 | BX8: 40383.35 | BY8: 33612.492 | BZ8: 35345.505 | CA8: 542052.46 | CB8: 40216.33 | CC8: 45181.169 | CD8: 50034.979 | CE8: 57152.685 | CF8: 66703.059 | CG8: 63023.896 | CH8: 60826.282 | CI8: 53471.99 | CJ8: 57925.838 | CK8: 51268.725 | CL8: 47203.876 | CM8: 47734.963 | CN8: 640743.79 | CO8: 51955.324 | CP8: 47721.453 | CQ8: 54653.092 | CR8: 50696.902 | CS8: 72398.17 | CT8: 71418.332 | CU8: 63795.708 | CV8: 66017.988 | CW8: 60014.725 | CX8: 57180.356 | CY8: 51685.986 | CZ8: 53133.422 | DA8: 700671.46 | DB8: 48748.373 | DC8: 48302.882 | DD8: 42877.327 | DE8: 47364.358 | DF8: 61117.641 | DG8: 61246.209 | DH8: 70473.413 | DI8: 69272.558 | DJ8: 74834.524 | DK8: 72704.227 | DL8: 53891.175 | DM8: 37433.82 | DN8: 688266.51 | DO8: 37356.337 | DP8: 40520.426 | DQ8: 45389.013 | DR8: 38740.559 | DS8: 35285.942 | DT8: 34541.443 | DU8: 43625.287 | DV8: 65978.968 | DW8: 77187.895 | DX8: 74765.488 | DY8: 53500.297 | DZ8: 56414.372 | EA8: 603306.03 | EB8: 51275.185 | EC8: 51631.624 | ED8: 46044.369 | EE8: 30983.069 | EF8: 51039.16 | EG8: 66133.595 | EH8: 55097.877 | EI8: 53984.891 | EJ8: 74090.531 | EK8: 64085.971 | EL8: 58045.967 | EM8: 54068.817 | EN8: 656481.06 | EO8: 57076.084 | EP8: 54772.647 | FA8: =SUM(EO8:EZ8) -> 111848.73 | FC8: =IFERROR((( _xlfn.XLOOKUP((DATE(YEAR($FC$5),MONTH($FC$5),1)),UCA.AGRO.DATE,$B8:$FA8) / _xlfn.XLOOKUP((DATE(YEAR($FC$5)-1,MONTH($FC$5),1)),UCA.AGRO.DATE,$B8:$FA8) )-1)*100,"") -> 8.4965333 | FD8: =IFERROR(((FF8/FE8)-1)*100,"") -> 10.152026 | FE8: =SUMIFS($B8:$FA8,UCA.AGRO.DATE,">="&DATE(YEAR($FC$5)-1,1,1),UCA.AGRO.DATE,"<="&DATE(YEAR($FC$5)-1,MONTH($FC$5),1)) -> 546891.66 | FF8: =SUMIFS($B8:$FA8,UCA.AGRO.DATE,">="&DATE(YEAR($FC$5),1,1),UCA.AGRO.DATE,"<="&$FC$5) -> 602412.24
A9: B. PECUARIO 2/ | B9: 8877.6564 | C9: 10559.944 | D9: 10337.785 | E9: 10704.762 | F9: 8337.7146 | G9: 7834.1825 | H9: 8030.7867 | I9: 6934.6704 | J9: 6184.3169 | K9: 6465.951 | L9: 6750.4362 | M9: 7242.7736 | N9: =SUM(B9:M9) -> 98260.98 | O9: 5612.0052 | P9: 5457.8123 | Q9: 4772.002 | R9: 5426.3275 | S9: 6853.3666 | T9: 6798.102 | U9: 5858.0832 | V9: 6033.9178 | W9: 5841.6866 | X9: 4971.7449 | Y9: 5595.844 | Z9: 6404.5654 | AA9: =SUM(O9:Z9) -> 69625.458 | AB9: 3990.9389 | AC9: 5773.9382 | AD9: 7004.1844 | AE9: 6521.0175 | AF9: 8001.1465 | AG9: 7646.7612 | AH9: 6790.5446 | AI9: 6148.8409 | AJ9: 6198.1402 | AK9: 5731.3665 | AL9: 5766.2716 | AM9: 6005.8655 | AN9: =SUM(AB9:AM9) -> 75579.016 | AO9: 5167.9856 | AP9: 4453.2985 | AQ9: 6103.8436 | AR9: 6832.8976 | AS9: 6400.1366 | AT9: 6989.0053 | AU9: 6708.0992 | AV9: 8342.2953 | AW9: 6695.9522 | AX9: 8923.3743 | AY9: 7037.1121 | AZ9: 9358.4535 | BA9: =SUM(AO9:AZ9) -> 83012.454 | BB9: 6830.9646 | BC9: 5620.6039 | BD9: 7801.9234 | BE9: 9155.199 | BF9: 8731.2561 | BG9: 9338.5603 | BH9: 9231.9709 | BI9: 11036.826 | BJ9: 9201.457 | BK9: 12157.196 | BL9: 9096.696 | BM9: 11854.991 | BN9: =SUM(BB9:BM9) -> 110057.64 | BO9: 6950.98 | BP9: 5595.8015 | BQ9: 7620.1095 | BR9: 8884.2748 | BS9: 8385.119 | BT9: 9312.1185 | BU9: 9185.9289 | BV9: 10481.515 | BW9: 8831.6796 | BX9: 11688.608 | BY9: 8715.3211 | BZ9: 11644.752 | CA9: 107296.21 | CB9: 6954.3974 | CC9: 5584.2946 | CD9: 7447.0815 | CE9: 8842.9046 | CF9: 8421.5902 | CG9: 9425.2962 | CH9: 9188.0806 | CI9: 10715.294 | CJ9: 9261.9786 | CK9: 11890.964 | CL9: 8747.0284 | CM9: 11711.858 | CN9: 108190.77 | CO9: 7260.7433 | CP9: 5702.1824 | CQ9: 7586.7238 | CR9: 9030.9511 | CS9: 8513.9572 | CT9: 9479.5473 | CU9: 9200.7392 | CV9: 10493.934 | CW9: 8950.958 | CX9: 11596.605 | CY9: 8281.7126 | CZ9: 10838.542 | DA9: 106936.6 | DB9: 7430.4569 | DC9: 5818.9961 | DD9: 7899.1191 | DE9: 8918.7654 | DF9: 8537.4979 | DG9: 8990.5659 | DH9: 9081.1985 | DI9: 10769.966 | DJ9: 9416.3988 | DK9: 11818.476 | DL9: 8740.2313 | DM9: 11289.662 | DN9: 108711.33 | DO9: 7240.4102 | DP9: 5673.4733 | DQ9: 7916.2369 | DR9: 8869.3528 | DS9: 8497.821 | DT9: 8968.7135 | DU9: 9112.6688 | DV9: 10628.267 | DW9: 9516.7815 | DX9: 12271.567 | DY9: 8814.6684 | DZ9: 11323.711 | EA9: 108833.67 | EB9: 7966.0536 | EC9: 5973.4739 | ED9: 7916.1321 | EE9: 8915.5308 | EF9: 8951.6026 | EG9: 9797.5165 | EH9: 9789.7266 | EI9: 10480.039 | EJ9: 9483.5309 | EK9: 12299 | EL9: 8971.8337 | EM9: 11362.285 | EN9: 111906.72 | EO9: 7882.4032 | EP9: 5913.4839 | FA9: =SUM(EO9:EZ9) -> 13795.887 | FC9: =IFERROR((( _xlfn.XLOOKUP((DATE(YEAR($FC$5),MONTH($FC$5),1)),UCA.AGRO.DATE,$B9:$FA9) / _xlfn.XLOOKUP((DATE(YEAR($FC$5)-1,MONTH($FC$5),1)),UCA.AGRO.DATE,$B9:$FA9) )-1)*100,"") -> 1.7829978 | FD9: =IFERROR(((FF9/FE9)-1)*100,"") -> 3.1119692 | FE9: =SUMIFS($B9:$FA9,UCA.AGRO.DATE,">="&DATE(YEAR($FC$5)-1,1,1),UCA.AGRO.DATE,"<="&DATE(YEAR($FC$5)-1,MONTH($FC$5),1)) -> 97509.96 | FF9: =SUMIFS($B9:$FA9,UCA.AGRO.DATE,">="&DATE(YEAR($FC$5),1,1),UCA.AGRO.DATE,"<="&$FC$5) -> 100544.44
A11: TOTAL AGRÍCOLA | B11: =SUM(B13:B37,B39) -> 80334 | C11: =SUM(C13:C37,C39) -> 76800 | D11: =SUM(D13:D37,D39) -> 72549 | E11: =SUM(E13:E37,E39) -> 69152 | F11: =SUM(F13:F37,F39) -> 65836 | G11: =SUM(G13:G37,G39) -> 64809 | H11: =SUM(H13:H37,H39) -> 56715 | I11: =SUM(I13:I37,I39) -> 65295 | ... M11: =SUM(M13:M37,M39) -> 77153 | N11: =SUM(B11:M11) -> 859583 | O11: =SUM(O13:O37,O39) -> 75698 | P11: =SUM(P13:P37,P39) -> 81263 | Q11: =SUM(Q13:Q37,Q39) -> 78146 | R11: =SUM(R13:R37,R39) -> 73764 | S11: =SUM(S13:S37,S39) -> 67317 | T11: =SUM(T13:T37,T39) -> 64535 | U11: =SUM(U13:U37,U39) -> 52501 | V11: =SUM(V13:V37,V39) -> 58615 | ... Z11: =SUM(Z13:Z37,Z39) -> 80276 | AA11: =SUM(O11:Z11) -> 849920 | AB11: =SUM(AB13:AB37,AB39) -> 76851 | AC11: =SUM(AC13:AC37,AC39) -> 83617 | AD11: =SUM(AD13:AD37,AD39) -> 88568 | AE11: =SUM(AE13:AE37,AE39) -> 73209 | AF11: =SUM(AF13:AF37,AF39) -> 73805 | AG11: =SUM(AG13:AG37,AG39) -> 68430 | AH11: =SUM(AH13:AH37,AH39) -> 63946 | AI11: =SUM(AI13:AI37,AI39) -> 69059 | ... AM11: =SUM(AM13:AM37,AM39) -> 82897 | AN11: =SUM(AB11:AM11) -> 947850 | AO11: =SUM(AO13:AO37,AO39) -> 82918 | AP11: =SUM(AP13:AP37,AP39) -> 85528 | AQ11: =SUM(AQ13:AQ37,AQ39) -> 89223 | AR11: =SUM(AR13:AR37,AR39) -> 85194 | AS11: =SUM(AS13:AS37,AS39) -> 76662 | AT11: =SUM(AT13:AT37,AT39) -> 71934 | AU11: =SUM(AU13:AU37,AU39) -> 72244 | AV11: =SUM(AV13:AV37,AV39) -> 82500 | ... AZ11: =SUM(AZ13:AZ37,AZ39) -> 86391 | BA11: =SUM(AO11:AZ11) -> 1005868 | BB11: =SUM(BB13:BB37,BB39) -> 87135 | BC11: =SUM(BC13:BC37,BC39) -> 90291 | BD11: =SUM(BD13:BD37,BD39) -> 90617 | BE11: =SUM(BE13:BE37,BE39) -> 87889 | BF11: =SUM(BF13:BF37,BF39) -> 89557 | BG11: =SUM(BG13:BG37,BG39) -> 78136 | BH11: =SUM(BH13:BH37,BH39) -> 74137 | BI11: =SUM(BI13:BI37,BI39) -> 76128 | ... BM11: =SUM(BM13:BM37,BM39) -> 88968 | BN11: =SUM(BB11:BM11) -> 1045646 | BO11: =SUM(BO13:BO37,BO39) -> 97164.962 | BP11: =SUM(BP13:BP37,BP39) -> 100093.17 | BQ11: =SUM(BQ13:BQ37,BQ39) -> 100404.42 | BR11: =SUM(BR13:BR37,BR39) -> 88074.423 | BS11: =SUM(BS13:BS37,BS39) -> 81644.33 | BT11: =SUM(BT13:BT37,BT39) -> 76574.021 | BU11: =SUM(BU13:BU37,BU39) -> 76409.869 | BV11: =SUM(BV13:BV37,BV39) -> 89392.072 | ... BZ11: =SUM(BZ13:BZ37,BZ39) -> 86754.404 | CA11: =SUM(BO11:BZ11) -> 1066289 | CB11: =SUM(CB13:CB37,CB39) -> 102106.48 | CC11: =SUM(CC13:CC37,CC39) -> 115151.82 | CD11: =SUM(CD13:CD37,CD39) -> 124556.01 | CE11: =SUM(CE13:CE37,CE39) -> 120500.24 | CF11: =SUM(CF13:CF37,CF39) -> 115840.37 | CG11: =SUM(CG13:CG37,CG39) -> 102427.78 | CH11: =SUM(CH13:CH37,CH39) -> 101129.93 | CI11: =SUM(CI13:CI37,CI39) -> 104405.33 | ... CM11: =SUM(CM13:CM37,CM39) -> 116348.22 | CN11: =SUM(CB11:CM11) -> 1380257.1 | CO11: =SUM(CO13:CO37,CO39) -> 122169.11 | CP11: =SUM(CP13:CP37,CP39) -> 119559.94 | CQ11: =SUM(CQ13:CQ37,CQ39) -> 133497.38 | CR11: =SUM(CR13:CR37,CR39) -> 116109.34 | CS11: =SUM(CS13:CS37,CS39) -> 125411.45 | CT11: =SUM(CT13:CT37,CT39) -> 113309.27 | CU11: =SUM(CU13:CU37,CU39) -> 100469.12 | CV11: =SUM(CV13:CV37,CV39) -> 128022.17 | ... CZ11: =SUM(CZ13:CZ37,CZ39) -> 138250.07 | DA11: =SUM(CO11:CZ11) -> 1489137.7 | DB11: =SUM(DB13:DB37,DB39) -> 125194.14 | DC11: =SUM(DC13:DC37,DC39) -> 125669.53 | DD11: =SUM(DD13:DD37,DD39) -> 112251.98 | DE11: =SUM(DE13:DE37,DE39) -> 108900.89 | DF11: =SUM(DF13:DF37,DF39) -> 117667.26 | DG11: =SUM(DG13:DG37,DG39) -> 109719.62 | DH11: =SUM(DH13:DH37,DH39) -> 115109.51 | DI11: =SUM(DI13:DI37,DI39) -> 120214.1 | ... DM11: =SUM(DM13:DM37,DM39) -> 105488.58 | DN11: =SUM(DB11:DM11) -> 1491728.1 | DO11: =SUM(DO13:DO37,DO39) -> 100343.56 | DP11: =SUM(DP13:DP37,DP39) -> 103578.87 | DQ11: =SUM(DQ13:DQ37,DQ39) -> 111402.71 | DR11: =SUM(DR13:DR37,DR39) -> 100322.95 | DS11: =SUM(DS13:DS37,DS39) -> 88667.193 | DT11: =SUM(DT13:DT37,DT39) -> 80964.668 | DU11: =SUM(DU13:DU37,DU39) -> 103704.46 | DV11: =SUM(DV13:DV37,DV39) -> 141854.63 | ... DZ11: =SUM(DZ13:DZ37,DZ39) -> 128679.6 | EA11: =SUM(DO11:DZ11) -> 1429919.8 | EB11: =SUM(EB13:EB37,EB39) -> 115155.7 | EC11: =SUM(EC13:EC37,EC39) -> 119135.65 | ED11: =SUM(ED13:ED37,ED39) -> 109168.43 | EE11: =SUM(EE13:EE37,EE39) -> 81000.748 | EF11: =SUM(EF13:EF37,EF39) -> 105208.94 | EG11: =SUM(EG13:EG37,EG39) -> 114925.36 | EH11: =SUM(EH13:EH37,EH39) -> 96222.423 | EI11: =SUM(EI13:EI37,EI39) -> 111212.84 | ... EM11: =SUM(EM13:EM37,EM39) -> 142342.11 | EN11: =SUM(EB11:EM11) -> 1444988.2 | EO11: =SUM(EO13:EO37,EO39) -> 136460.79 | EP11: =SUM(EP13:EP37,EP39) -> 137830.45 | EQ11: =SUM(EQ13:EQ37,EQ39) -> 0 | ER11: =SUM(ER13:ER37,ER39) -> 0 | ES11: =SUM(ES13:ES37,ES39) -> 0 | ET11: =SUM(ET13:ET37,ET39) -> 0 | EU11: =SUM(EU13:EU37,EU39) -> 0 | EV11: =SUM(EV13:EV37,EV39) -> 0 | ... EZ11: =SUM(EZ13:EZ37,EZ39) -> 0 | FA11: =SUM(EO11:EZ11) -> 274291.24 | FC11: =IFERROR((( _xlfn.XLOOKUP((DATE(YEAR($FC$5),MONTH($FC$5),1)),UCA.AGRO.DATE,$B11:$FA11) / _xlfn.XLOOKUP((DATE(YEAR($FC$5)-1,MONTH($FC$5),1)),UCA.AGRO.DATE,$B11:$FA11) )-1)*100,"") -> 9.0909624 | FD11: =IFERROR(((FF11/FE11)-1)*100,"") -> 0.10804592 | FE11: =SUMIFS($B11:$FA11,UCA.AGRO.DATE,">="&DATE(YEAR($FC$5)-1,1,1),UCA.AGRO.DATE,"<="&DATE(YEAR($FC$5)-1,MONTH($FC$5),1)) -> 1301240.2 | FF11: =SUMIFS($B11:$FA11,UCA.AGRO.DATE,">="&DATE(YEAR($FC$5),1,1),UCA.AGRO.DATE,"<="&$FC$5) -> 1302646.1
A13: Arroz Cáscara | B13: 1841 | C13: 1820 | D13: 1274 | E13: 1885 | F13: 1253 | G13: 2126 | H13: 658 | I13: 2994 | J13: 4141 | K13: 4247 | L13: 1767 | M13: 2723 | N13: =SUM(B13:M13) -> 26729 | O13: 2352 | P13: 1985 | Q13: 1895 | R13: 1590 | S13: 660 | T13: 1466 | U13: 1026 | V13: 2688 | W13: 3657 | X13: 4873 | Y13: 2403 | Z13: 2339 | AA13: =SUM(O13:Z13) -> 26934 | AB13: 2184 | AC13: 3217 | AD13: 2898 | AE13: 2489 | AF13: 2776 | AG13: 3713 | AH13: 5586 | AI13: 3797 | AJ13: 16239 | AK13: 14475 | AL13: 5286 | AM13: 3538 | AN13: =SUM(AB13:AM13) -> 66198 | AO13: 2324 | AP13: 2720 | AQ13: 2972 | AR13: 3544 | AS13: 4972 | AT13: 3660 | AU13: 4083 | AV13: 4839 | AW13: 9903 | AX13: 8252 | AY13: 8440 | AZ13: 3887 | BA13: =SUM(AO13:AZ13) -> 59596 | BB13: 3645 | BC13: 4868 | BD13: 2081 | BE13: 4076 | BF13: 11337 | BG13: 7788 | BH13: 9707 | BI13: 10133 | BJ13: 10945 | BK13: 7831 | BL13: 12098 | BM13: 4945 | BN13: =SUM(BB13:BM13) -> 89454 | BO13: 6286.438 | BP13: 4747.04 | BQ13: 5497.84 | BR13: 9327.969 | BS13: 4191.779 | BT13: 5715.925 | BU13: 2767.75 | BV13: 5303.86 | BW13: 7985.358 | BX13: 5190.058 | BY13: 4574.94 | BZ13: 4651.689 | CA13: 66240.646 | CB13: 6179.609 | CC13: 6740.98 | CD13: 9133.519 | CE13: 9075.02 | CF13: 2596.18 | CG13: 2351.12 | CH13: 5026.34 | CI13: 4626.689 | CJ13: 6958.6 | CK13: 4962.62 | CL13: 2954.47 | CM13: 6522.909 | CN13: 67128.056 | CO13: 15084.36 | CP13: 10863.09 | CQ13: 15999.81 | CR13: 2769.288 | CS13: 5591.67 | CT13: 3736.74 | CU13: 4141.94 | CV13: 7316.6 | CW13: 9645.13 | CX13: 11757.82 | CY13: 10080.44 | CZ13: 7555.42 | DA13: 104542.31 | DB13: 7154.52 | DC13: 10297.78 | DD13: 8796.61 | DE13: 10941.62 | DF13: 7708.53 | DG13: 2624.32 | DH13: 8922.98 | DI13: 7237.039 | DJ13: 13351.195 | DK13: 18811.938 | DL13: 11534.86 | DM13: 4503.759 | DN13: 111885.15 | DO13: 6373.139 | DP13: 9957.99 | DQ13: 16534.459 | DR13: 8751.649 | DS13: 7995.54 | DT13: 5028.879 | DU13: 5939.62 | DV13: 12793.679 | DW13: 21474.989 | DX13: 16753.479 | DY13: 9413.05 | DZ13: 18757.409 | EA13: 139773.88 | EB13: 17796.938 | EC13: 20937.582 | ED13: 18390.61 | EE13: 3016.85 | EF13: 1704.266 | EG13: 4875.639 | EH13: 3603.53 | EI13: 2651.054 | EJ13: 14715.625 | EK13: 11233.379 | EL13: 7978.438 | EM13: 6788.77 | EN13: 113692.68 | EO13: 10933.929 | EP13: 11590.195 | FA13: =SUM(EO13:EZ13) -> 22524.124 | FC13: =IFERROR((( _xlfn.XLOOKUP((DATE(YEAR($FC$5),MONTH($FC$5),1)),UCA.AGRO.DATE,$B13:$FA13) / _xlfn.XLOOKUP((DATE(YEAR($FC$5)-1,MONTH($FC$5),1)),UCA.AGRO.DATE,$B13:$FA13) )-1)*100,"") -> -15.240671 | FD13: =IFERROR(((FF13/FE13)-1)*100,"") -> -11.661687 | FE13: =SUMIFS($B13:$FA13,UCA.AGRO.DATE,">="&DATE(YEAR($FC$5)-1,1,1),UCA.AGRO.DATE,"<="&DATE(YEAR($FC$5)-1,MONTH($FC$5),1)) -> 121016.47 | FF13: =SUMIFS($B13:$FA13,UCA.AGRO.DATE,">="&DATE(YEAR($FC$5),1,1),UCA.AGRO.DATE,"<="&$FC$5) -> 106903.91 | FH13: =SUM(B13:FA13) -> 1789395.7 | FI13: Arroz Cáscara | FJ13: =IF(EXACT(A13,FI13)=TRUE,"OK","VER") -> OK
A14: Cacao | B14: 411 | C14: 491 | D14: 519 | E14: 539 | F14: 581 | G14: 633 | H14: 687 | I14: 736 | J14: 773 | K14: 588 | L14: 415 | M14: 332 | N14: =SUM(B14:M14) -> 6705 | O14: 214 | P14: 250 | Q14: 534 | R14: 1198 | S14: 1174 | T14: 1257 | U14: 966 | V14: 638 | W14: 587 | X14: 653 | Y14: 550 | Z14: 602 | AA14: =SUM(O14:Z14) -> 8623 | AB14: 286 | AC14: 320 | AD14: 891 | AE14: 1218 | AF14: 1366 | AG14: 1751 | AH14: 1365 | AI14: 1026 | AJ14: 1149 | AK14: 1042 | AL14: 1140 | AM14: 1690 | AN14: =SUM(AB14:AM14) -> 13244 | AO14: 828 | AP14: 800 | AQ14: 897 | AR14: 1250 | AS14: 1661 | AT14: 1752 | AU14: 1650 | AV14: 1676 | AW14: 1591 | AX14: 1658 | AY14: 1446 | AZ14: 1377 | BA14: =SUM(AO14:AZ14) -> 16586 | BB14: 1217 | BC14: 1193 | BD14: 1327 | BE14: 1383 | BF14: 1634 | BG14: 1785 | BH14: 1426 | BI14: 1306 | BJ14: 1518 | BK14: 1578 | BL14: 1211 | BM14: 1453 | BN14: =SUM(BB14:BM14) -> 17031 | BO14: 1283.544 | BP14: 1357.009 | BQ14: 1391.53 | BR14: 2395.879 | BS14: 3055.638 | BT14: 3058.83 | BU14: 2373.86 | BV14: 1997.128 | BW14: 1973.789 | BX14: 1374.058 | BY14: 648.049 | BZ14: 795.975 | CA14: 21705.289 | CB14: 552.937 | CC14: 787.479 | CD14: 818.099 | CE14: 1944.898 | CF14: 3101.21 | CG14: 3132.847 | CH14: 2643 | CI14: 1742.243 | CJ14: 1704.8 | CK14: 1389.239 | CL14: 1219.79 | CM14: 1009.889 | CN14: 20046.431 | CO14: 648.04 | CP14: 564.789 | CQ14: 433.919 | CR14: 1971.18 | CS14: 4015.63 | CT14: 4480.25 | CU14: 4125.838 | CV14: 2622.708 | CW14: 1784.84 | CX14: 1047.989 | CY14: 639.679 | CZ14: 389.159 | DA14: 22724.021 | DB14: 325.85 | DC14: 228.143 | DD14: 180.686 | DE14: 899.543 | DF14: 2864.789 | DG14: 3273.029 | DH14: 3776.82 | DI14: 3103.518 | DJ14: 2333.805 | DK14: 1291.666 | DL14: 450.78 | DM14: 157.99 | DN14: 18886.619 | DO14: 102.887 | DP14: 70.424 | DQ14: 39.182 | DR14: 26.613 | DS14: 128.487 | DT14: 545.629 | DU14: 944.228 | DV14: 2017.467 | DW14: 2079.959 | DX14: 1288.754 | DY14: 532.659 | DZ14: 275.19 | EA14: 8051.479 | EB14: 134.3 | EC14: 90.36 | ED14: 55.283 | EE14: 30.898 | EF14: 2420.294 | EG14: 3875.167 | EH14: 3298.529 | EI14: 2347.738 | EJ14: 1726.515 | EK14: 1379.355 | EL14: 974.475 | EM14: 714.816 | EN14: 17047.73 | EO14: 160.22 | EP14: 103.486 | FA14: =SUM(EO14:EZ14) -> 263.706 | FC14: =IFERROR((( _xlfn.XLOOKUP((DATE(YEAR($FC$5),MONTH($FC$5),1)),UCA.AGRO.DATE,$B14:$FA14) / _xlfn.XLOOKUP((DATE(YEAR($FC$5)-1,MONTH($FC$5),1)),UCA.AGRO.DATE,$B14:$FA14) )-1)*100,"") -> 82.945374 | FD14: =IFERROR(((FF14/FE14)-1)*100,"") -> 110.03481 | FE14: =SUMIFS($B14:$FA14,UCA.AGRO.DATE,">="&DATE(YEAR($FC$5)-1,1,1),UCA.AGRO.DATE,"<="&DATE(YEAR($FC$5)-1,MONTH($FC$5),1)) -> 7776.289 | FF14: =SUMIFS($B14:$FA14,UCA.AGRO.DATE,">="&DATE(YEAR($FC$5),1,1),UCA.AGRO.DATE,"<="&$FC$5) -> 16332.914 | FH14: =SUM(B14:FA14) -> 341828.55 | FI14: Cacao | FJ14: =IF(EXACT(A14,FI14)=TRUE,"OK","VER") -> OK
A15: Café | D15: 1054 | E15: 1150 | F15: 1205 | G15: 1155 | H15: 878 | N15: =SUM(B15:M15) -> 5442 | Q15: 713 | R15: 709 | S15: 932 | T15: 1017 | U15: 1158 | AA15: =SUM(O15:Z15) -> 4529 | AD15: 430 | AE15: 551 | AF15: 929 | AG15: 925 | AH15: 1169 | AN15: =SUM(AB15:AM15) -> 4004 | AQ15: 456 | AR15: 583 | AS15: 2256 | AT15: 3098 | AU15: 1933 | BA15: =SUM(AO15:AZ15) -> 8326 | BD15: 124 | BE15: 2010 | BF15: 3168 | BG15: 3423 | BH15: 2555 | BI15: 1724 | BJ15: 619 | BN15: =SUM(BB15:BM15) -> 13623 | BQ15: 35.77 | BR15: 577.91 | BS15: 2085.499 | BT15: 2523.475 | BU15: 2398.546 | BV15: 2540.08 | BW15: 806.4 | CA15: 10967.68 | CD15: 199.8 | CE15: 918.328 | CF15: 2941.363 | CG15: 3126.867 | CH15: 2899.791 | CI15: 1853.18 | CJ15: 719.5 | CN15: 12658.829 | CQ15: 86.5 | CR15: 507.38 | CS15: 2228.134 | CT15: 2576.233 | CU15: 2192.38 | CV15: 1886.319 | CW15: 1217.75 | CX15: 48.52 | DA15: 10743.216 | DE15: 288.86 | DF15: 1072.38 | DG15: 1867.68 | DH15: 2419.75 | DI15: 2627.75 | DJ15: 1718.63 | DN15: 9995.05 | DO15: 0 | DP15: 0 | DQ15: 0 | DR15: 340.24 | DS15: 385.45 | DT15: 550.34 | DU15: 575.1 | DV15: 943.09 | DW15: 542.88 | DX15: 0 | DY15: 0 | DZ15: 0 | EA15: 3337.1 | EB15: 0 | EC15: 0 | ED15: 0 | EE15: 621.16 | EF15: 949.05 | EG15: 1662.09 | EH15: 1429.56 | EI15: 1178.05 | EJ15: 891.11 | EK15: 0 | EL15: 0 | EM15: 0 | EN15: 6731.02 | EO15: 0 | EP15: 0 | FA15: =SUM(EO15:EZ15) -> 0 | FC15: =IFERROR((( _xlfn.XLOOKUP((DATE(YEAR($FC$5),MONTH($FC$5),1)),UCA.AGRO.DATE,$B15:$FA15) / _xlfn.XLOOKUP((DATE(YEAR($FC$5)-1,MONTH($FC$5),1)),UCA.AGRO.DATE,$B15:$FA15) )-1)*100,"") | FD15: =IFERROR(((FF15/FE15)-1)*100,"") -> 101.70268 | FE15: =SUMIFS($B15:$FA15,UCA.AGRO.DATE,">="&DATE(YEAR($FC$5)-1,1,1),UCA.AGRO.DATE,"<="&DATE(YEAR($FC$5)-1,MONTH($FC$5),1)) -> 3337.1 | FF15: =SUMIFS($B15:$FA15,UCA.AGRO.DATE,">="&DATE(YEAR($FC$5),1,1),UCA.AGRO.DATE,"<="&$FC$5) -> 6731.02 | FH15: =SUM(B15:FA15) -> 180713.79 | FI15: Café | FJ15: =IF(EXACT(A15,FI15)=TRUE,"OK","VER") -> OK
A16: Camu Camu | B16: 251 | C16: 253 | D16: 260 | E16: 137 | F16: 152 | G16: 89 | H16: 53 | I16: 24 | J16: 33 | K16: 36 | L16: 51 | M16: 61 | N16: =SUM(B16:M16) -> 1400 | O16: 162 | P16: 114 | Q16: 318 | R16: 216 | S16: 286 | T16: 171 | U16: 59 | V16: 11 | W16: 21 | X16: 29 | Y16: 47 | Z16: 59 | AA16: =SUM(O16:Z16) -> 1493 | AB16: 172 | AC16: 194 | AD16: 280 | AE16: 242 | AF16: 325 | AG16: 41 | AH16: 6 | AI16: 6 | AJ16: 33 | AK16: 34 | AL16: 59 | AM16: 90 | AN16: =SUM(AB16:AM16) -> 1482 | AO16: 197 | AP16: 241 | AQ16: 290 | AR16: 381 | AS16: 265 | AT16: 46 | AU16: 10 | AV16: 13 | AW16: 38 | AX16: 36 | AY16: 71 | AZ16: 1638 | BA16: =SUM(AO16:AZ16) -> 3226 | BB16: 81 | BC16: 106 | BD16: 483 | BE16: 338 | BF16: 98 | BG16: 19 | BH16: 5 | BI16: 11 | BJ16: 32 | BK16: 137 | BL16: 117 | BM16: 206 | BN16: =SUM(BB16:BM16) -> 1633 | BO16: 121 | BP16: 185 | BQ16: 515 | BR16: 410 | BS16: 228.809 | BT16: 96 | BU16: 20 | BV16: 60 | BW16: 44 | BX16: 87 | BY16: 7 | BZ16: 149 | CA16: 1922.809 | CB16: 74.51 | CC16: 86.439 | CD16: 157.999 | CE16: 435.59 | CF16: 363.16 | CG16: 176.67 | CH16: 71.718 | CI16: 92.5 | CJ16: 75.45 | CK16: 141.628 | CL16: 66.57 | CM16: 262.35 | CN16: 2004.584 | CO16: 205.229 | CP16: 126.339 | CQ16: 381.518 | CR16: 382.16 | CS16: 298.529 | CT16: 213.54 | CU16: 104.94 | CV16: 69.519 | CW16: 36.85 | CX16: 76.48 | CY16: 112.96 | CZ16: 414.15 | DA16: 2422.214 | DB16: 297.2 | DC16: 163.703 | DD16: 169.32 | DE16: 219.87 | DF16: 108.3 | DG16: 84.87 | DH16: 20.05 | DI16: 23.5 | DJ16: 15.74 | DK16: 51.59 | DL16: 76.269 | DM16: 60.318 | DN16: 1290.73 | DO16: 65.75 | DP16: 105.46 | DQ16: 138.269 | DR16: 183.17 | DS16: 192.18 | DT16: 80.17 | DU16: 27.63 | DV16: 29.34 | DW16: 19.47 | DX16: 37.279 | DY16: 106.51 | DZ16: 128.44 | EA16: 1113.668 | EB16: 117.319 | EC16: 68 | ED16: 19.159 | EE16: 17.802 | EF16: 119.279 | EG16: 104.19 | EH16: 57.34 | EI16: 44.22 | EJ16: 19.47 | EK16: 45.16 | EL16: 449.81 | EM16: 479.77 | EN16: 1541.519 | EO16: 267.569 | EP16: 158.187 | FA16: =SUM(EO16:EZ16) -> 425.756 | FC16: =IFERROR((( _xlfn.XLOOKUP((DATE(YEAR($FC$5),MONTH($FC$5),1)),UCA.AGRO.DATE,$B16:$FA16) / _xlfn.XLOOKUP((DATE(YEAR($FC$5)-1,MONTH($FC$5),1)),UCA.AGRO.DATE,$B16:$FA16) )-1)*100,"") -> 322.31715 | FD16: =IFERROR(((FF16/FE16)-1)*100,"") -> 7.7668316 | FE16: =SUMIFS($B16:$FA16,UCA.AGRO.DATE,">="&DATE(YEAR($FC$5)-1,1,1),UCA.AGRO.DATE,"<="&DATE(YEAR($FC$5)-1,MONTH($FC$5),1)) -> 985.228 | FF16: =SUMIFS($B16:$FA16,UCA.AGRO.DATE,">="&DATE(YEAR($FC$5),1,1),UCA.AGRO.DATE,"<="&$FC$5) -> 1061.749 | FH16: =SUM(B16:FA16) -> 39910.56 | FI16: Camu Camu | FJ16: =IF(EXACT(A16,FI16)=TRUE,"OK","VER") -> OK
A17: Caña de Azúcar | B17: 2264 | C17: 2353 | D17: 1959 | E17: 2284 | F17: 1808 | G17: 1805 | H17: 1785 | I17: 1951 | J17: 1913 | K17: 1919 | L17: 2058 | M17: 2114 | N17: =SUM(B17:M17) -> 24213 | O17: 1579 | P17: 1777 | Q17: 1728 | R17: 1575 | S17: 1544 | T17: 1535 | U17: 1372 | V17: 1229 | W17: 1215 | X17: 1323 | Y17: 1463 | Z17: 1622 | AA17: =SUM(O17:Z17) -> 17962 | AB17: 1533 | AC17: 1456 | AD17: 1326 | AE17: 1102 | AF17: 1030 | AG17: 1192 | AH17: 968 | AI17: 711 | AJ17: 733 | AK17: 772 | AL17: 895 | AM17: 1025 | AN17: =SUM(AB17:AM17) -> 12743 | AO17: 930 | AP17: 926 | AQ17: 1082 | AR17: 844 | AS17: 901 | AT17: 837 | AU17: 727 | AV17: 687 | AW17: 674 | AX17: 688 | AY17: 638 | AZ17: 726 | BA17: =SUM(AO17:AZ17) -> 9660 | BB17: 646 | BC17: 853 | BD17: 800 | BE17: 664 | BF17: 621 | BG17: 537 | BH17: 691 | BI17: 717 | BJ17: 627 | BK17: 652 | BL17: 545 | BM17: 782 | BN17: =SUM(BB17:BM17) -> 8135 | BO17: 772 | BP17: 1019 | BQ17: 970 | BR17: 1088 | BS17: 1295.67 | BT17: 1247 | BU17: 1193 | BV17: 1100 | BW17: 998 | BX17: 1095 | BY17: 1007 | BZ17: 1051 | CA17: 12835.67 | CB17: 902.256 | CC17: 972.949 | CD17: 1657.45 | CE17: 2057.827 | CF17: 2433.46 | CG17: 2364.729 | CH17: 1978.02 | CI17: 1716.739 | CJ17: 1954.329 | CK17: 1858.389 | CL17: 1909.266 | CM17: 1699.479 | CN17: 21504.893 | CO17: 1437.618 | CP17: 580.677 | CQ17: 645.009 | CR17: 1182.067 | CS17: 1688.549 | CT17: 2302.199 | CU17: 2409.73 | CV17: 1901.009 | CW17: 1714.226 | CX17: 1470.469 | CY17: 1255.28 | CZ17: 1367.303 | DA17: 17954.136 | DB17: 1194.55 | DC17: 380.249 | DD17: 292.9 | DE17: 470.549 | DF17: 664.089 | DG17: 1230.199 | DH17: 1636.709 | DI17: 1817.788 | DJ17: 1823.999 | DK17: 1589.688 | DL17: 1113.986 | DM17: 539.58 | DN17: 12754.286 | DO17: 361.469 | DP17: 256.667 | DQ17: 161.519 | DR17: 102.193 | DS17: 182.549 | DT17: 302.096 | DU17: 483.829 | DV17: 1134.717 | DW17: 1168.164 | DX17: 1161.219 | DY17: 733.6 | DZ17: 490.017 | EA17: 6538.039 | EB17: 335.069 | EC17: 227.178 | ED17: 128.387 | EE17: 81.034 | EF17: 225.807 | EG17: 336.857 | EH17: 392.7 | EI17: 398.568 | EJ17: 425.069 | EK17: 474.186 | EL17: 539.307 | EM17: 529.056 | EN17: 4093.218 | EO17: 447.624 | EP17: 323.507 | FA17: =SUM(EO17:EZ17) -> 771.131 | FC17: =IFERROR((( _xlfn.XLOOKUP((DATE(YEAR($FC$5),MONTH($FC$5),1)),UCA.AGRO.DATE,$B17:$FA17) / _xlfn.XLOOKUP((DATE(YEAR($FC$5)-1,MONTH($FC$5),1)),UCA.AGRO.DATE,$B17:$FA17) )-1)*100,"") -> -26.484869 | FD17: =IFERROR(((FF17/FE17)-1)*100,"") -> -41.068964 | FE17: =SUMIFS($B17:$FA17,UCA.AGRO.DATE,">="&DATE(YEAR($FC$5)-1,1,1),UCA.AGRO.DATE,"<="&DATE(YEAR($FC$5)-1,MONTH($FC$5),1)) -> 6048.022 | FF17: =SUMIFS($B17:$FA17,UCA.AGRO.DATE,">="&DATE(YEAR($FC$5),1,1),UCA.AGRO.DATE,"<="&$FC$5) -> 3564.162 | FH17: =SUM(B17:FA17) -> 298328.75 | FI17: Caña de Azúcar | FJ17: =IF(EXACT(A17,FI17)=TRUE,"OK","VER") -> OK
A18: Cocotero | B18: 385 | C18: 401 | D18: 401 | E18: 363 | F18: 410 | G18: 408 | H18: 428 | I18: 469 | J18: 484 | K18: 471 | L18: 478 | M18: 491 | N18: =SUM(B18:M18) -> 5189 | O18: 447 | P18: 435 | Q18: 460 | R18: 436 | S18: 453 | T18: 466 | U18: 450 | V18: 425 | W18: 418 | X18: 451 | Y18: 445 | Z18: 492 | AA18: =SUM(O18:Z18) -> 5378 | AB18: 450 | AC18: 480 | AD18: 506 | AE18: 525 | AF18: 549 | AG18: 557 | AH18: 554 | AI18: 546 | AJ18: 597 | AK18: 635 | AL18: 642 | AM18: 729 | AN18: =SUM(AB18:AM18) -> 6770 | AO18: 559 | AP18: 583 | AQ18: 611 | AR18: 656 | AS18: 683 | AT18: 728 | AU18: 745 | AV18: 764 | AW18: 799 | AX18: 816 | AY18: 826 | AZ18: 784 | BA18: =SUM(AO18:AZ18) -> 8554 | BB18: 840 | BC18: 862 | BD18: 875 | BE18: 867 | BF18: 864 | BG18: 887 | BH18: 893 | BI18: 896 | BJ18: 911 | BK18: 916 | BL18: 924 | BM18: 938 | BN18: =SUM(BB18:BM18) -> 10673 | BO18: 922 | BP18: 949 | BQ18: 931 | BR18: 950 | BS18: 952.029 | BT18: 955 | BU18: 946 | BV18: 974 | BW18: 994 | BX18: 1024 | BY18: 1020 | BZ18: 1066 | CA18: 11683.029 | CB18: 926.57 | CC18: 964.229 | CD18: 970.88 | CE18: 986.248 | CF18: 1029.958 | CG18: 1019.43 | CH18: 1012.629 | CI18: 989.259 | CJ18: 1028.089 | CK18: 1046.519 | CL18: 1020.049 | CM18: 1062.15 | CN18: 12056.01 | CO18: 930.75 | CP18: 981.7 | CQ18: 926.978 | CR18: 936.809 | CS18: 991.778 | CT18: 1020.579 | CU18: 1041.589 | CV18: 1123.63 | CW18: 1102.881 | CX18: 1106.65 | CY18: 1080.28 | CZ18: 1092.429 | DA18: 12336.053 | DB18: 1042.61 | DC18: 1017.64 | DD18: 988.84 | DE18: 998.489 | DF18: 1013.96 | DG18: 1057.145 | DH18: 1070.06 | DI18: 1079.367 | DJ18: 1084.42 | DK18: 1092.647 | DL18: 1098.978 | DM18: 1102.239 | DN18: 12646.395 | DO18: 1098.705 | DP18: 1081.979 | DQ18: 1080.699 | DR18: 1027.299 | DS18: 1043.609 | DT18: 1043.154 | DU18: 1048.25 | DV18: 1052.497 | DW18: 1051.409 | DX18: 1053.451 | DY18: 1055.829 | DZ18: 1041.796 | EA18: 12678.677 | EB18: 1025.468 | EC18: 976.248 | ED18: 852.568 | EE18: 685.021 | EF18: 688.178 | EG18: 692.148 | EH18: 696.109 | EI18: 695.887 | EJ18: 698.295 | EK18: 701.526 | EL18: 592.578 | EM18: 560.47 | EN18: 8864.496 | EO18: 519.438 | EP18: 522.689 | FA18: =SUM(EO18:EZ18) -> 1042.127 | FC18: =IFERROR((( _xlfn.XLOOKUP((DATE(YEAR($FC$5),MONTH($FC$5),1)),UCA.AGRO.DATE,$B18:$FA18) / _xlfn.XLOOKUP((DATE(YEAR($FC$5)-1,MONTH($FC$5),1)),UCA.AGRO.DATE,$B18:$FA18) )-1)*100,"") -> -43.875571 | FD18: =IFERROR(((FF18/FE18)-1)*100,"") -> -28.640449 | FE18: =SUMIFS($B18:$FA18,UCA.AGRO.DATE,">="&DATE(YEAR($FC$5)-1,1,1),UCA.AGRO.DATE,"<="&DATE(YEAR($FC$5)-1,MONTH($FC$5),1)) -> 11636.881 | FF18: =SUMIFS($B18:$FA18,UCA.AGRO.DATE,">="&DATE(YEAR($FC$5),1,1),UCA.AGRO.DATE,"<="&$FC$5) -> 8304.026 | FH18: =SUM(B18:FA18) -> 215741.57 | FI18: Cocotero | FJ18: =IF(EXACT(A18,FI18)=TRUE,"OK","VER") -> OK
A19: Frijol Caupí Chiclayo | I19: 183 | J19: 560 | K19: 275 | L19: 4 | M19: 23 | N19: =SUM(B19:M19) -> 1045 | O19: 15 | P19: 1 | V19: 97 | W19: 260 | X19: 89 | AA19: =SUM(O19:Z19) -> 462 | AH19: 24 | AI19: 102 | AJ19: 175 | AK19: 319 | AL19: 32 | AN19: =SUM(AB19:AM19) -> 652 | AU19: 28 | AV19: 188 | AW19: 103 | AX19: 106 | BA19: =SUM(AO19:AZ19) -> 425 | BH19: 12 | BI19: 76 | BJ19: 176 | BK19: 286 | BL19: 80 | BM19: 3 | BN19: =SUM(BB19:BM19) -> 633 | BO19: 2.95 | BU19: 61.069 | BV19: 174.15 | BW19: 310.14 | BX19: 104.01 | BZ19: 65.1 | CA19: 717.419 | CB19: 50.874 | CC19: 73.7 | CG19: 60.83 | CH19: 88.16 | CI19: 261.143 | CJ19: 205.146 | CK19: 27.69 | CL19: 4.74 | CM19: 35.069 | CN19: 807.352 | CO19: 8.45 | CT19: 30.65 | CU19: 49.76 | CV19: 236.517 | CW19: 281.93 | CX19: 153.62 | CY19: 4.71 | DA19: 765.637 | DB19: 32.079 | DC19: 3.06 | DD19: 3.18 | DF19: 4.74 | DH19: 43.62 | DI19: 291.479 | DJ19: 684.887 | DK19: 349.989 | DL19: 40.18 | DM19: 23.01 | DN19: 1476.224 | DO19: 48.629 | DP19: 0 | DQ19: 0 | DR19: 0 | DS19: 0 | DT19: 0 | DU19: 12.21 | DV19: 217.765 | DW19: 332.649 | DX19: 172.74 | DY19: 32.49 | DZ19: 32.66 | EA19: 849.143 | EB19: 23.37 | EC19: 0 | ED19: 0 | EE19: 0 | EF19: 0 | EG19: 0 | EH19: 61.33 | EI19: 286.858 | EJ19: 253.68 | EK19: 171.078 | EL19: 25.749 | EM19: 186.548 | EN19: 1008.613 | EO19: 18.61 | EP19: 52.59 | FA19: =SUM(EO19:EZ19) -> 71.2 | FC19: =IFERROR((( _xlfn.XLOOKUP((DATE(YEAR($FC$5),MONTH($FC$5),1)),UCA.AGRO.DATE,$B19:$FA19) / _xlfn.XLOOKUP((DATE(YEAR($FC$5)-1,MONTH($FC$5),1)),UCA.AGRO.DATE,$B19:$FA19) )-1)*100,"") -> -20.747922 | FD19: =IFERROR(((FF19/FE19)-1)*100,"") -> 0.68366396 | FE19: =SUMIFS($B19:$FA19,UCA.AGRO.DATE,">="&DATE(YEAR($FC$5)-1,1,1),UCA.AGRO.DATE,"<="&DATE(YEAR($FC$5)-1,MONTH($FC$5),1)) -> 816.483 | FF19: =SUMIFS($B19:$FA19,UCA.AGRO.DATE,">="&DATE(YEAR($FC$5),1,1),UCA.AGRO.DATE,"<="&$FC$5) -> 822.065 | FH19: =SUM(B19:FA19) -> 17825.176 | FI19: Frijol Caupí Chiclayo | FJ19: =IF(EXACT(A19,FI19)=TRUE,"OK","VER") -> OK
A20: Frijol Grano Seco | B20: 40 | C20: 26 | H20: 170 | I20: 438 | J20: 992 | K20: 546 | L20: 590 | M20: 57 | N20: =SUM(B20:M20) -> 2859 | O20: 31 | P20: 9 | V20: 349 | W20: 716 | X20: 705 | Y20: 228 | Z20: 196 | AA20: =SUM(O20:Z20) -> 2234 | AI20: 356 | AJ20: 848 | AK20: 737 | AL20: 55 | AN20: =SUM(AB20:AM20) -> 1996 | AO20: 4 | AQ20: 9 | AU20: 36 | AV20: 175 | AW20: 260 | AX20: 382 | AY20: 181 | AZ20: 97 | BA20: =SUM(AO20:AZ20) -> 1144 | BH20: 42 | BI20: 69 | BJ20: 172 | BK20: 338 | BL20: 265 | BM20: 124 | BN20: =SUM(BB20:BM20) -> 1010 | BO20: 33.57 | BP20: 10.28 | BR20: 10.289 | BV20: 271.69 | BW20: 268.049 | BX20: 171.888 | BY20: 50.15 | BZ20: 77.17 | CA20: 893.086 | CB20: 103.969 | CC20: 67.19 | CD20: 35.34 | CH20: 142.31 | CI20: 171.679 | CJ20: 290.77 | CK20: 222.079 | CL20: 76.25 | CM20: 45.38 | CN20: 1154.967 | CO20: 36.15 | CP20: 54.4 | CQ20: 4.769 | CT20: 3.34 | CU20: 130.82 | CV20: 156.95 | CW20: 182.649 | CX20: 227.64 | CY20: 144.619 | CZ20: 71.83 | DA20: 1013.167 | DB20: 80.51 | DC20: 95.48 | DD20: 48.4 | DE20: 13.06 | DG20: 5.04 | DI20: 219.569 | DJ20: 221.765 | DK20: 345.388 | DL20: 152.819 | DN20: 1182.031 | DO20: 51.239 | DP20: 113.66 | DQ20: 0 | DR20: 0 | DS20: 0 | DT20: 0 | DU20: 0 | DV20: 14.22 | DW20: 350.228 | DX20: 444.829 | DY20: 153.547 | DZ20: 249.838 | EA20: 1377.561 | EB20: 213.539 | EC20: 48.739 | ED20: 23.47 | EE20: 0 | EF20: 0 | EG20: 0 | EH20: 0 | EI20: 12.48 | EJ20: 2293.24 | EK20: 381.498 | EL20: 254.428 | EM20: 91.8 | EN20: 3319.194 | EO20: 1046.228 | EP20: 220.575 | FA20: =SUM(EO20:EZ20) -> 1266.803 | FC20: =IFERROR((( _xlfn.XLOOKUP((DATE(YEAR($FC$5),MONTH($FC$5),1)),UCA.AGRO.DATE,$B20:$FA20) / _xlfn.XLOOKUP((DATE(YEAR($FC$5)-1,MONTH($FC$5),1)),UCA.AGRO.DATE,$B20:$FA20) )-1)*100,"") -> 65.700404 | FD20: =IFERROR(((FF20/FE20)-1)*100,"") -> 186.18677 | FE20: =SUMIFS($B20:$FA20,UCA.AGRO.DATE,">="&DATE(YEAR($FC$5)-1,1,1),UCA.AGRO.DATE,"<="&DATE(YEAR($FC$5)-1,MONTH($FC$5),1)) -> 1127.723 | FF20: =SUMIFS($B20:$FA20,UCA.AGRO.DATE,">="&DATE(YEAR($FC$5),1,1),UCA.AGRO.DATE,"<="&$FC$5) -> 3227.394 | FH20: =SUM(B20:FA20) -> 38899.618 | FI20: Frijol Grano Seco | FJ20: =IF(EXACT(A20,FI20)=TRUE,"OK","VER") -> OK
A21: Limón Sutil | B21: 1059 | C21: 1191 | D21: 1051 | E21: 772 | F21: 980 | G21: 1122 | H21: 800 | I21: 660 | J21: 536 | K21: 492 | L21: 385 | M21: 539 | N21: =SUM(B21:M21) -> 9587 | O21: 755 | P21: 1036 | Q21: 1087 | R21: 811 | S21: 948 | T21: 1022 | U21: 815 | V21: 525 | W21: 401 | X21: 455 | Y21: 467 | Z21: 627 | AA21: =SUM(O21:Z21) -> 8949 | AB21: 806 | AC21: 976 | AD21: 1105 | AE21: 934 | AF21: 924 | AG21: 1017 | AH21: 864 | AI21: 573 | AJ21: 526 | AK21: 618 | AL21: 602 | AM21: 731 | AN21: =SUM(AB21:AM21) -> 9676 | AO21: 751 | AP21: 1177 | AQ21: 1298 | AR21: 941 | AS21: 928 | AT21: 970 | AU21: 927 | AV21: 706 | AW21: 536 | AX21: 760 | AY21: 665 | AZ21: 921 | BA21: =SUM(AO21:AZ21) -> 10580 | BB21: 920 | BC21: 1227 | BD21: 1485 | BE21: 1045 | BF21: 1121 | BG21: 898 | BH21: 890 | BI21: 730 | BJ21: 490 | BK21: 876 | BL21: 770 | BM21: 866 | BN21: =SUM(BB21:BM21) -> 11318 | BO21: 1085.147 | BP21: 1467.189 | BQ21: 1727.738 | BR21: 1321.87 | BS21: 1349.84 | BT21: 1206.18 | BU21: 1213.95 | BV21: 963.38 | BW21: 843.34 | BX21: 932.219 | BY21: 1024.519 | BZ21: 1068.03 | CA21: 14203.402 | CB21: 1077.27 | CC21: 1490.5 | CD21: 1757.789 | CE21: 1462.859 | CF21: 1752.86 | CG21: 1407.579 | CH21: 1275.26 | CI21: 1093.38 | CJ21: 1020.388 | CK21: 1076.23 | CL21: 1194.56 | CM21: 1319.309 | CN21: 15927.984 | CO21: 1220.956 | CP21: 1550.43 | CQ21: 1684.231 | CR21: 1546.277 | CS21: 1710.7 | CT21: 1779.599 | CU21: 1506.61 | CV21: 1108.988 | CW21: 1040.31 | CX21: 809.359 | CY21: 579.33 | CZ21: 833.43 | DA21: 15370.22 | DB21: 1185.999 | DC21: 1421.41 | DD21: 1535.96 | DE21: 1381.999 | DF21: 1058.708 | DG21: 1140.68 | DH21: 1171.179 | DI21: 884.438 | DJ21: 817.999 | DK21: 767.959 | DL21: 654.394 | DM21: 716.089 | DN21: 12736.814 | DO21: 871.938 | DP21: 927.879 | DQ21: 998.94 | DR21: 1070.903 | DS21: 877.548 | DT21: 869.916 | DU21: 955.57 | DV21: 790.238 | DW21: 617.12 | DX21: 518.804 | DY21: 537.699 | DZ21: 593.279 | EA21: 9629.834 | EB21: 665.689 | EC21: 760.326 | ED21: 707.996 | EE21: 462.811 | EF21: 357.09 | EG21: 432.589 | EH21: 471.307 | EI21: 318.828 | EJ21: 249.398 | EK21: 276.516 | EL21: 339.592 | EM21: 389.046 | EN21: 5431.188 | EO21: 528.327 | EP21: 707.29 | FA21: =SUM(EO21:EZ21) -> 1235.617 | FC21: =IFERROR((( _xlfn.XLOOKUP((DATE(YEAR($FC$5),MONTH($FC$5),1)),UCA.AGRO.DATE,$B21:$FA21) / _xlfn.XLOOKUP((DATE(YEAR($FC$5)-1,MONTH($FC$5),1)),UCA.AGRO.DATE,$B21:$FA21) )-1)*100,"") -> -36.843476 | FD21: =IFERROR(((FF21/FE21)-1)*100,"") -> -44.20283 | FE21: =SUMIFS($B21:$FA21,UCA.AGRO.DATE,">="&DATE(YEAR($FC$5)-1,1,1),UCA.AGRO.DATE,"<="&DATE(YEAR($FC$5)-1,MONTH($FC$5),1)) -> 9036.555 | FF21: =SUMIFS($B21:$FA21,UCA.AGRO.DATE,">="&DATE(YEAR($FC$5),1,1),UCA.AGRO.DATE,"<="&$FC$5) -> 5042.142 | FH21: =SUM(B21:FA21) -> 249290.12 | FI21: Limón Sutil | FJ21: =IF(EXACT(A21,FI21)=TRUE,"OK","VER") -> OK
A22: Maíz Amarillo Duro | B22: 3537 | C22: 2596 | D22: 2248 | E22: 2239 | F22: 1317 | G22: 1036 | H22: 748 | I22: 1098 | J22: 2150 | K22: 3222 | L22: 4344 | M22: 3572 | N22: =SUM(B22:M22) -> 28107 | O22: 4278 | P22: 3047 | Q22: 2062 | R22: 1531 | S22: 1061 | T22: 837 | U22: 358 | V22: 1342 | W22: 1775 | X22: 4825 | Y22: 2146 | Z22: 2528 | AA22: =SUM(O22:Z22) -> 25790 | AB22: 3967 | AC22: 3347 | AD22: 1591 | AE22: 787 | AF22: 656 | AG22: 778 | AH22: 507 | AI22: 1960 | AJ22: 4487 | AK22: 9479 | AL22: 2664 | AM22: 3007 | AN22: =SUM(AB22:AM22) -> 33230 | AO22: 3634 | AP22: 2763 | AQ22: 1696 | AR22: 1246 | AS22: 742 | AT22: 586 | AU22: 561 | AV22: 1624 | AW22: 2542 | AX22: 4824 | AY22: 3604 | AZ22: 2730 | BA22: =SUM(AO22:AZ22) -> 26552 | BB22: 3848 | BC22: 2885 | BD22: 1974 | BE22: 1273 | BF22: 725 | BG22: 436 | BH22: 1116 | BI22: 1569 | BJ22: 2531 | BK22: 3000 | BL22: 2556 | BM22: 3599 | BN22: =SUM(BB22:BM22) -> 25512 | BO22: 3590.38 | BP22: 2227.45 | BQ22: 1527.099 | BR22: 1565.409 | BS22: 1495.439 | BT22: 905.24 | BU22: 501.769 | BV22: 2527.068 | BW22: 2072.077 | BX22: 2745.84 | BY22: 1741.988 | BZ22: 1936.23 | CA22: 22835.989 | CB22: 3463.858 | CC22: 2939.46 | CD22: 1592.2 | CE22: 919.42 | CF22: 478.068 | CG22: 262.96 | CH22: 300.939 | CI22: 1091.189 | CJ22: 2223.09 | CK22: 2978.83 | CL22: 950.289 | CM22: 4701.28 | CN22: 21901.583 | CO22: 5396.099 | CP22: 3255.06 | CQ22: 2828.529 | CR22: 522.35 | CS22: 475.01 | CT22: 295.119 | CU22: 313.668 | CV22: 1032.11 | CW22: 1900.32 | CX22: 3235.449 | CY22: 3218.409 | CZ22: 7827.15 | DA22: 30299.273 | DB22: 9210.66 | DC22: 5126.865 | DD22: 1702.86 | DE22: 3052.789 | DF22: 1368.379 | DG22: 1322.944 | DH22: 834.659 | DI22: 1274.949 | DJ22: 6354.656 | DK22: 5390.44 | DL22: 3453.728 | DM22: 1459.4 | DN22: 40552.329 | DO22: 3017.14 | DP22: 4346.639 | DQ22: 3519.24 | DR22: 1011.86 | DS22: 304 | DT22: 1051.61 | DU22: 853.77 | DV22: 1002.519 | DW22: 5705.909 | DX22: 9273.09 | DY22: 6577.91 | DZ22: 10705.809 | EA22: 47369.496 | EB22: 11962.28 | EC22: 6463.9 | ED22: 3541.45 | EE22: 649.545 | EF22: 320.518 | EG22: 548.35 | EH22: 506.04 | EI22: 1056.72 | EJ22: 6359.849 | EK22: 4741.488 | EL22: 3679.37 | EM22: 2359.099 | EN22: 42188.609 | EO22: 13762.456 | EP22: 9917.788 | FA22: =SUM(EO22:EZ22) -> 23680.244 | FC22: =IFERROR((( _xlfn.XLOOKUP((DATE(YEAR($FC$5),MONTH($FC$5),1)),UCA.AGRO.DATE,$B22:$FA22) / _xlfn.XLOOKUP((DATE(YEAR($FC$5)-1,MONTH($FC$5),1)),UCA.AGRO.DATE,$B22:$FA22) )-1)*100,"") -> -44.064756 | FD22: =IFERROR(((FF22/FE22)-1)*100,"") -> 8.6347644 | FE22: =SUMIFS($B22:$FA22,UCA.AGRO.DATE,">="&DATE(YEAR($FC$5)-1,1,1),UCA.AGRO.DATE,"<="&DATE(YEAR($FC$5)-1,MONTH($FC$5),1)) -> 36663.687 | FF22: =SUMIFS($B22:$FA22,UCA.AGRO.DATE,">="&DATE(YEAR($FC$5),1,1),UCA.AGRO.DATE,"<="&$FC$5) -> 39829.51 | FH22: =SUM(B22:FA22) -> 736037.05 | FI22: Maíz Amarillo Duro | FJ22: =IF(EXACT(A22,FI22)=TRUE,"OK","VER") -> OK
A23: Mandarina | B23: 438 | C23: 548 | D23: 652 | E23: 462 | F23: 662 | G23: 813 | H23: 352 | I23: 164 | J23: 88 | K23: 99 | L23: 158 | M23: 265 | N23: =SUM(B23:M23) -> 4701 | O23: 357 | P23: 481 | Q23: 647 | R23: 487 | S23: 635 | T23: 710 | U23: 380 | V23: 174 | W23: 87 | X23: 99 | Y23: 179 | Z23: 326 | AA23: =SUM(O23:Z23) -> 4562 | AB23: 432 | AC23: 537 | AD23: 692 | AE23: 627 | AF23: 683 | AG23: 718 | AH23: 415 | AI23: 204 | AJ23: 103 | AK23: 100 | AL23: 216 | AM23: 443 | AN23: =SUM(AB23:AM23) -> 5170 | AO23: 416 | AP23: 622 | AQ23: 888 | AR23: 685 | AS23: 656 | AT23: 558 | AU23: 360 | AV23: 178 | AW23: 72 | AX23: 76 | AY23: 168 | AZ23: 259 | BA23: =SUM(AO23:AZ23) -> 4938 | BB23: 265 | BC23: 310 | BD23: 839 | BE23: 744 | BF23: 977 | BG23: 646 | BH23: 486 | BI23: 395 | BJ23: 16 | BM23: 155 | BN23: =SUM(BB23:BM23) -> 4833 | BO23: 407.039 | BP23: 563.469 | BQ23: 948.359 | BR23: 919.008 | BS23: 1071.188 | BT23: 671.949 | BU23: 599.423 | BV23: 291.5 | BZ23: 279.729 | CA23: 5751.664 | CB23: 486.5 | CC23: 577.89 | CD23: 893.08 | CE23: 1261.309 | CF23: 1259.2 | CG23: 927.629 | CH23: 700.618 | CI23: 377.88 | CM23: 342.699 | CN23: 6826.805 | CO23: 530.56 | CP23: 700.438 | CQ23: 975.2 | CR23: 1089.739 | CS23: 1239.21 | CT23: 1195.237 | CU23: 745.34 | CV23: 444.039 | CW23: 45.82 | CZ23: 419.499 | DA23: 7385.082 | DB23: 548.793 | DC23: 572.819 | DD23: 789.258 | DE23: 824.75 | DF23: 1153.259 | DG23: 1163.824 | DH23: 800.709 | DI23: 327.439 | DM23: 267.508 | DN23: 6448.359 | DO23: 353.679 | DP23: 358.819 | DQ23: 415.909 | DR23: 542.847 | DS23: 1059.169 | DT23: 1129.448 | DU23: 870.547 | DV23: 457.55 | DW23: 0 | DX23: 0 | DY23: 0 | DZ23: 238.268 | EA23: 5426.236 | EB23: 334.17 | EC23: 329.478 | ED23: 378.899 | EE23: 451.449 | EF23: 573.368 | EG23: 719.768 | EH23: 628.15 | EI23: 377.179 | EJ23: 0 | EK23: 0 | EL23: 0 | EM23: 199.66 | EN23: 3992.121 | EO23: 234.339 | EP23: 271.968 | FA23: =SUM(EO23:EZ23) -> 506.307 | FC23: =IFERROR((( _xlfn.XLOOKUP((DATE(YEAR($FC$5),MONTH($FC$5),1)),UCA.AGRO.DATE,$B23:$FA23) / _xlfn.XLOOKUP((DATE(YEAR($FC$5)-1,MONTH($FC$5),1)),UCA.AGRO.DATE,$B23:$FA23) )-1)*100,"") | FD23: =IFERROR(((FF23/FE23)-1)*100,"") -> -26.898913 | FE23: =SUMIFS($B23:$FA23,UCA.AGRO.DATE,">="&DATE(YEAR($FC$5)-1,1,1),UCA.AGRO.DATE,"<="&DATE(YEAR($FC$5)-1,MONTH($FC$5),1)) -> 5187.968 | FF23: =SUMIFS($B23:$FA23,UCA.AGRO.DATE,">="&DATE(YEAR($FC$5),1,1),UCA.AGRO.DATE,"<="&$FC$5) -> 3792.461 | FH23: =SUM(B23:FA23) -> 121081.15 | FI23: Mandarina | FJ23: =IF(EXACT(A23,FI23)=TRUE,"OK","VER") -> OK
A24: Mango | B24: 972 | J24: 987 | K24: 1371 | L24: 1537 | M24: 1453 | N24: =SUM(B24:M24) -> 6320 | O24: 798 | V24: 10 | W24: 1156 | X24: 1454 | Y24: 1510 | Z24: 1482 | AA24: =SUM(O24:Z24) -> 6410 | AB24: 813 | AI24: 15 | AJ24: 934 | AK24: 1476 | AL24: 1753 | AM24: 1663 | AN24: =SUM(AB24:AM24) -> 6654 | AO24: 733 | AU24: 11 | AV24: 32 | AW24: 678 | AX24: 1177 | AY24: 1416 | AZ24: 440 | BA24: =SUM(AO24:AZ24) -> 4487 | BB24: 151 | BJ24: 168 | BK24: 1014 | BL24: 1364 | BM24: 970 | BN24: =SUM(BB24:BM24) -> 3667 | BO24: 403.68 | BW24: 709.599 | BX24: 1821.618 | BY24: 1932.22 | BZ24: 1257.27 | CA24: 6124.387 | CB24: 580.54 | CJ24: 720.666 | CK24: 1978.42 | CL24: 1952.498 | CM24: 1256.72 | CN24: 6488.844 | CO24: 560.35 | CV24: 39.85 | CW24: 550.97 | CX24: 2181.71 | CY24: 1571.34 | CZ24: 1181.089 | DA24: 6085.309 | DB24: 633.92 | DJ24: 490.587 | DK24: 1763.359 | DL24: 1116.579 | DM24: 447.099 | DN24: 4451.544 | DO24: 230.849 | DP24: 0 | DQ24: 0 | DR24: 0 | DS24: 0 | DT24: 0 | DU24: 0 | DV24: 0 | DW24: 641.908 | DX24: 1445.355 | DY24: 998.198 | DZ24: 426.63 | EA24: 3742.94 | EB24: 233.254 | EC24: 0 | ED24: 0 | EE24: 0 | EF24: 0 | EG24: 0 | EH24: 0 | EI24: 0 | EJ24: 329.379 | EK24: 1395.105 | EL24: 1085.669 | EM24: 677.516 | EN24: 3720.923 | EO24: 315.795 | EP24: 0 | FA24: =SUM(EO24:EZ24) -> 315.795 | FC24: =IFERROR((( _xlfn.XLOOKUP((DATE(YEAR($FC$5),MONTH($FC$5),1)),UCA.AGRO.DATE,$B24:$FA24) / _xlfn.XLOOKUP((DATE(YEAR($FC$5)-1,MONTH($FC$5),1)),UCA.AGRO.DATE,$B24:$FA24) )-1)*100,"") -> 8.7628907 | FD24: =IFERROR(((FF24/FE24)-1)*100,"") -> -8.2291161 | FE24: =SUMIFS($B24:$FA24,UCA.AGRO.DATE,">="&DATE(YEAR($FC$5)-1,1,1),UCA.AGRO.DATE,"<="&DATE(YEAR($FC$5)-1,MONTH($FC$5),1)) -> 3316.31 | FF24: =SUMIFS($B24:$FA24,UCA.AGRO.DATE,">="&DATE(YEAR($FC$5),1,1),UCA.AGRO.DATE,"<="&$FC$5) -> 3043.407 | FH24: =SUM(B24:FA24) -> 116935.48 | FI24: Mango | FJ24: =IF(EXACT(A24,FI24)=TRUE,"OK","VER") -> OK
A25: Maní | B25: 34 | I25: 8 | J25: 61 | K25: 95 | L25: 93 | M25: 13 | N25: =SUM(B25:M25) -> 304 | O25: 29 | P25: 15 | W25: 67 | X25: 124 | Y25: 100 | Z25: 127 | AA25: =SUM(O25:Z25) -> 462 | AI25: 41 | AJ25: 110 | AK25: 152 | AL25: 28 | AM25: 69 | AN25: =SUM(AB25:AM25) -> 400 | AU25: 24 | AV25: 55 | AW25: 57 | AX25: 129 | AY25: 99 | AZ25: 20 | BA25: =SUM(AO25:AZ25) -> 384 | BB25: 18 | BC25: 18 | BD25: 3 | BI25: 3 | BJ25: 22 | BK25: 80 | BL25: 105 | BM25: 38 | BN25: =SUM(BB25:BM25) -> 287 | BO25: 38 | BP25: 29 | BQ25: 25 | BV25: 24 | BW25: 75 | BX25: 81 | BY25: 32 | CA25: 304 | CB25: 32.639 | CC25: 16.519 | CD25: 35.21 | CE25: 1.48 | CH25: 16.169 | CI25: 61.28 | CJ25: 143.18 | CK25: 38.909 | CL25: 12.96 | CM25: 37.93 | CN25: 396.276 | CO25: 35.9 | CP25: 14.67 | CQ25: 25.308 | CV25: 40.32 | CW25: 136.82 | CX25: 159.559 | CY25: 93.998 | CZ25: 5.04 | DA25: 511.615 | DB25: 50.33 | DC25: 32.76 | DD25: 37.96 | DE25: 12.937 | DF25: 39.31 | DG25: 3.259 | DI25: 41.674 | DJ25: 127.499 | DK25: 203.849 | DL25: 134.429 | DM25: 14.9 | DN25: 698.907 | DO25: 27.22 | DP25: 89.56 | DQ25: 0 | DR25: 0 | DS25: 15.3 | DT25: 0 | DU25: 0 | DV25: 0 | DW25: 72.246 | DX25: 107.906 | DY25: 72.878 | DZ25: 4.769 | EA25: 389.879 | EB25: 0 | EC25: 6.379 | ED25: 21.56 | EE25: 0 | EF25: 0 | EG25: 0 | EH25: 0 | EI25: 15.9 | EJ25: 58.18 | EK25: 144.888 | EL25: 101.13 | EM25: 20.31 | EN25: 368.347 | EO25: 88.13 | EP25: 50.34 | FA25: =SUM(EO25:EZ25) -> 138.47 | FC25: =IFERROR((( _xlfn.XLOOKUP((DATE(YEAR($FC$5),MONTH($FC$5),1)),UCA.AGRO.DATE,$B25:$FA25) / _xlfn.XLOOKUP((DATE(YEAR($FC$5)-1,MONTH($FC$5),1)),UCA.AGRO.DATE,$B25:$FA25) )-1)*100,"") -> 38.766157 | FD25: =IFERROR(((FF25/FE25)-1)*100,"") -> -9.6266002 | FE25: =SUMIFS($B25:$FA25,UCA.AGRO.DATE,">="&DATE(YEAR($FC$5)-1,1,1),UCA.AGRO.DATE,"<="&DATE(YEAR($FC$5)-1,MONTH($FC$5),1)) -> 385.11 | FF25: =SUMIFS($B25:$FA25,UCA.AGRO.DATE,">="&DATE(YEAR($FC$5),1,1),UCA.AGRO.DATE,"<="&$FC$5) -> 348.037 | FH25: =SUM(B25:FA25) -> 9288.988 | FI25: Maní | FJ25: =IF(EXACT(A25,FI25)=TRUE,"OK","VER") -> OK
A26: Naranja | B26: 874 | C26: 1137 | D26: 1151 | E26: 795 | F26: 1037 | G26: 1060 | H26: 634 | I26: 306 | J26: 256 | K26: 234 | L26: 284 | M26: 476 | N26: =SUM(B26:M26) -> 8244 | O26: 717 | P26: 962 | Q26: 1145 | R26: 848 | S26: 1028 | T26: 1079 | U26: 701 | V26: 290 | W26: 167 | X26: 246 | Y26: 321 | Z26: 637 | AA26: =SUM(O26:Z26) -> 8141 | AB26: 863 | AC26: 1021 | AD26: 1273 | AE26: 1028 | AF26: 1172 | AG26: 1246 | AH26: 234 | AI26: 99 | AJ26: 94 | AK26: 136 | AL26: 315 | AM26: 830 | AN26: =SUM(AB26:AM26) -> 8311 | AO26: 879 | AP26: 1162 | AQ26: 1333 | AR26: 1219 | AS26: 1134 | AT26: 1083 | AU26: 474 | AV26: 94 | AW26: 102 | AX26: 131 | AY26: 192 | AZ26: 244 | BA26: =SUM(AO26:AZ26) -> 8047 | BB26: 620 | BC26: 1239 | BD26: 1699 | BE26: 1419 | BF26: 1212 | BG26: 1134 | BH26: 899 | BI26: 564 | BJ26: 46 | BM26: 480 | BN26: =SUM(BB26:BM26) -> 9312 | BO26: 1064.609 | BP26: 1625.919 | BQ26: 1929.48 | BR26: 1812.309 | BS26: 1814.199 | BT26: 1402.259 | BU26: 1170.022 | BV26: 635.079 | BZ26: 603.179 | CA26: 12057.055 | CB26: 1117.84 | CC26: 1299.859 | CD26: 1837.237 | CE26: 2206.2 | CF26: 2344.85 | CG26: 1708.04 | CH26: 1213.51 | CI26: 650.509 | CM26: 821.129 | CN26: 13199.174 | CO26: 1281.618 | CP26: 1619.658 | CQ26: 2010.816 | CR26: 2156.379 | CS26: 2425.268 | CT26: 2090.658 | CU26: 1543.928 | CV26: 768.82 | CW26: 74.519 | CY26: 26.48 | CZ26: 806.999 | DA26: 14805.143 | DB26: 1132.13 | DC26: 1486.318 | DD26: 1724.43 | DE26: 1776.43 | DF26: 2166.84 | DG26: 2043.47 | DH26: 1683.607 | DI26: 720.064 | DM26: 372.488 | DN26: 13105.777 | DO26: 598.65 | DP26: 815.209 | DQ26: 985.369 | DR26: 1207.4 | DS26: 1737.23 | DT26: 2034.719 | DU26: 1693.349 | DV26: 897.61 | DW26: 0 | DX26: 0 | DY26: 0 | DZ26: 336.358 | EA26: 10305.894 | EB26: 477.598 | EC26: 581.058 | ED26: 641.288 | EE26: 632.63 | EF26: 914.042 | EG26: 1231.866 | EH26: 1105.087 | EI26: 660.158 | EJ26: 0 | EK26: 0 | EL26: 0 | EM26: 258.129 | EN26: 6501.856 | EO26: 307.426 | EP26: 433.79 | FA26: =SUM(EO26:EZ26) -> 741.216 | FC26: =IFERROR((( _xlfn.XLOOKUP((DATE(YEAR($FC$5),MONTH($FC$5),1)),UCA.AGRO.DATE,$B26:$FA26) / _xlfn.XLOOKUP((DATE(YEAR($FC$5)-1,MONTH($FC$5),1)),UCA.AGRO.DATE,$B26:$FA26) )-1)*100,"") | FD26: =IFERROR(((FF26/FE26)-1)*100,"") -> -37.37194 | FE26: =SUMIFS($B26:$FA26,UCA.AGRO.DATE,">="&DATE(YEAR($FC$5)-1,1,1),UCA.AGRO.DATE,"<="&DATE(YEAR($FC$5)-1,MONTH($FC$5),1)) -> 9969.536 | FF26: =SUMIFS($B26:$FA26,UCA.AGRO.DATE,">="&DATE(YEAR($FC$5),1,1),UCA.AGRO.DATE,"<="&$FC$5) -> 6243.727 | FH26: =SUM(B26:FA26) -> 225542.23 | FI26: Naranja | FJ26: =IF(EXACT(A26,FI26)=TRUE,"OK","VER") -> OK
A27: Palma Aceitera | B27: 11839 | C27: 12007 | D27: 14204 | E27: 15811 | F27: 15211 | G27: 15018 | H27: 11604 | I27: 15227 | J27: 19909 | K27: 21436 | L27: 17600 | M27: 18268 | N27: =SUM(B27:M27) -> 188134 | O27: 15626 | P27: 16693 | Q27: 17245 | R27: 17281 | S27: 15831 | T27: 16854 | U27: 11589 | V27: 16496 | W27: 23055 | X27: 28644 | Y27: 19927 | Z27: 24005 | AA27: =SUM(O27:Z27) -> 223246 | AB27: 20010 | AC27: 21745 | AD27: 28991 | AE27: 23880 | AF27: 26242 | AG27: 23796 | AH27: 20770 | AI27: 25995 | AJ27: 28183 | AK27: 30605 | AL27: 24312 | AM27: 24123 | AN27: =SUM(AB27:AM27) -> 298652 | AO27: 24987 | AP27: 24714 | AQ27: 28010 | AR27: 28526 | AS27: 24204 | AT27: 20735 | AU27: 26005 | AV27: 34548 | AW27: 34740 | AX27: 37355 | AY27: 34999 | AZ27: 31423 | BA27: =SUM(AO27:AZ27) -> 350246 | BB27: 30558 | BC27: 26858 | BD27: 30364 | BE27: 28454 | BF27: 26938 | BG27: 23702 | BH27: 20394 | BI27: 25820 | BJ27: 29139 | BK27: 44587 | BL27: 37401 | BM27: 30350 | BN27: =SUM(BB27:BM27) -> 354565 | BO27: 31622.03 | BP27: 28427.2 | BQ27: 30252.65 | BR27: 17589.005 | BS27: 18405.61 | BT27: 17319.82 | BU27: 22283.79 | BV27: 30907.08 | BW27: 35604.859 | BX27: 34512.85 | BY27: 28125.77 | BZ27: 23914.22 | CA27: 318964.88 | CB27: 32916.05 | CC27: 37419.039 | CD27: 46225.54 | CE27: 44857.729 | CF27: 43882.819 | CG27: 37544.688 | CH27: 35909.57 | CI27: 43786.51 | CJ27: 69355.12 | CK27: 67555.049 | CL27: 63822.95 | CM27: 42163.72 | CN27: 565438.78 | CO27: 42302.17 | CP27: 42628.869 | CQ27: 52684.5 | CR27: 52076.03 | CS27: 49485.3 | CT27: 35201.239 | CU27: 35155.76 | CV27: 63038.91 | CW27: 62399.27 | CX27: 77887.03 | CY27: 75922.85 | CZ27: 75649.36 | DA27: 664431.29 | DB27: 59285.49 | DC27: 58925.3 | DD27: 47495.921 | DE27: 40575.055 | DF27: 37990.087 | DG27: 35956.799 | DH27: 32128.449 | DI27: 58279.92 | DJ27: 72459.85 | DK27: 93999.218 | DL27: 78274.539 | DM27: 51431.489 | DN27: 666802.12 | DO27: 41044.58 | DP27: 37102.98 | DQ27: 39880.11 | DR27: 39869.68 | DS27: 37321.65 | DT27: 28872.97 | DU27: 51905.22 | DV27: 79590.4 | DW27: 83373.009 | DX27: 105716.91 | DY27: 77739.77 | DZ27: 51809.999 | EA27: 674227.28 | EB27: 43094.739 | EC27: 45460.49 | ED27: 41760.44 | EE27: 38554.139 | EF27: 38566.25 | EG27: 31868.518 | EH27: 43945.358 | EI27: 65102.929 | EJ27: 95634.759 | EK27: 105328.07 | EL27: 102901.28 | EM27: 102582.76 | EN27: 754799.73 | EO27: 79930.95 | EP27: 79757.809 | FA27: =SUM(EO27:EZ27) -> 159688.76 | FC27: =IFERROR((( _xlfn.XLOOKUP((DATE(YEAR($FC$5),MONTH($FC$5),1)),UCA.AGRO.DATE,$B27:$FA27) / _xlfn.XLOOKUP((DATE(YEAR($FC$5)-1,MONTH($FC$5),1)),UCA.AGRO.DATE,$B27:$FA27) )-1)*100,"") -> 32.366328 | FD27: =IFERROR(((FF27/FE27)-1)*100,"") -> 4.7877353 | FE27: =SUMIFS($B27:$FA27,UCA.AGRO.DATE,">="&DATE(YEAR($FC$5)-1,1,1),UCA.AGRO.DATE,"<="&DATE(YEAR($FC$5)-1,MONTH($FC$5),1)) -> 622417.28 | FF27: =SUMIFS($B27:$FA27,UCA.AGRO.DATE,">="&DATE(YEAR($FC$5),1,1),UCA.AGRO.DATE,"<="&$FC$5) -> 652216.97 | FH27: =SUM(B27:FA27) -> 10438392 | FI27: Palma Aceitera | FJ27: =IF(EXACT(A27,FI27)=TRUE,"OK","VER") -> OK
A28: Papaya | B28: 4478 | C28: 4450 | D28: 4008 | E28: 4133 | F28: 3735 | G28: 3872 | H28: 3464 | I28: 3831 | J28: 3705 | K28: 3612 | L28: 3758 | M28: 3849 | N28: =SUM(B28:M28) -> 46895 | O28: 4349 | P28: 4388 | Q28: 4231 | R28: 4333 | S28: 3487 | T28: 3617 | U28: 3220 | V28: 2918 | W28: 3021 | X28: 3484 | Y28: 3794 | Z28: 4191 | AA28: =SUM(O28:Z28) -> 45033 | AB28: 4296 | AC28: 4340 | AD28: 3932 | AE28: 3695 | AF28: 4074 | AG28: 3972 | AH28: 3697 | AI28: 3572 | AJ28: 3477 | AK28: 3779 | AL28: 3932 | AM28: 3955 | AN28: =SUM(AB28:AM28) -> 46721 | AO28: 3900 | AP28: 4620 | AQ28: 4624 | AR28: 3907 | AS28: 4097 | AT28: 3783 | AU28: 3605 | AV28: 3712 | AW28: 3782 | AX28: 4045 | AY28: 3578 | AZ28: 3584 | BA28: =SUM(AO28:AZ28) -> 47237 | BB28: 3269 | BC28: 3375 | BD28: 3475 | BE28: 3061 | BF28: 2939 | BG28: 2840 | BH28: 3203 | BI28: 2919 | BJ28: 2719 | BK28: 3600 | BL28: 3872 | BM28: 3864 | BN28: =SUM(BB28:BM28) -> 39136 | BO28: 4722 | BP28: 5254.3 | BQ28: 4889.619 | BR28: 4455.68 | BS28: 4188.55 | BT28: 3750.069 | BU28: 3505.07 | BV28: 3537.238 | BW28: 3844.2 | BX28: 4458.989 | BY28: 4591.53 | BZ28: 4889.39 | CA28: 52086.635 | CB28: 5258.28 | CC28: 5273.609 | CD28: 5256.36 | CE28: 5598.119 | CF28: 5456.42 | CG28: 5234.1 | CH28: 4963.446 | CI28: 4613.429 | CJ28: 4571.88 | CK28: 4828.668 | CL28: 5021.25 | CM28: 5800.878 | CN28: 61876.439 | CO28: 5931.38 | CP28: 5659.579 | CQ28: 5714.44 | CR28: 5879.33 | CS28: 5643.75 | CT28: 5423.57 | CU28: 5226.65 | CV28: 5033.859 | CW28: 4672.709 | CX28: 4259.01 | CY28: 3814.448 | CZ28: 4369.799 | DA28: 61628.524 | DB28: 5331.34 | DC28: 5166.928 | DD28: 5316.3 | DE28: 4937.76 | DF28: 4693.17 | DG28: 5076.41 | DH28: 5139.49 | DI28: 4890.975 | DJ28: 4823.709 | DK28: 4675.489 | DL28: 4615.67 | DM28: 4290.74 | DN28: 58957.981 | DO28: 4306.056 | DP28: 4177.909 | DQ28: 4073.748 | DR28: 3686.989 | DS28: 3420.308 | DT28: 3471.719 | DU28: 3815.757 | DV28: 3997.678 | DW28: 4015.238 | DX28: 3973.78 | DY28: 3923.79 | DZ28: 3652.979 | EA28: 46515.951 | EB28: 3260.839 | EC28: 2648.128 | ED28: 1959.539 | EE28: 1322.447 | EF28: 858.929 | EG28: 1033.832 | EH28: 903.701 | EI28: 836.069 | EJ28: 798.529 | EK28: 785.147 | EL28: 896.35 | EM28: 915.534 | EN28: 16219.044 | EO28: 1062.548 | EP28: 1175.646 | FA28: =SUM(EO28:EZ28) -> 2238.194 | FC28: =IFERROR((( _xlfn.XLOOKUP((DATE(YEAR($FC$5),MONTH($FC$5),1)),UCA.AGRO.DATE,$B28:$FA28) / _xlfn.XLOOKUP((DATE(YEAR($FC$5)-1,MONTH($FC$5),1)),UCA.AGRO.DATE,$B28:$FA28) )-1)*100,"") -> -77.156015 | FD28: =IFERROR(((FF28/FE28)-1)*100,"") -> -64.296666 | FE28: =SUMIFS($B28:$FA28,UCA.AGRO.DATE,">="&DATE(YEAR($FC$5)-1,1,1),UCA.AGRO.DATE,"<="&DATE(YEAR($FC$5)-1,MONTH($FC$5),1)) -> 42862.972 | FF28: =SUMIFS($B28:$FA28,UCA.AGRO.DATE,">="&DATE(YEAR($FC$5),1,1),UCA.AGRO.DATE,"<="&$FC$5) -> 15303.51 | FH28: =SUM(B28:FA28) -> 1049089.5 | FI28: Papaya | FJ28: =IF(EXACT(A28,FI28)=TRUE,"OK","VER") -> OK
A29: Pijuayo Fruto | B29: 1783 | C29: 2194 | D29: 1742 | E29: 600 | F29: 180 | J29: 15 | K29: 300 | L29: 453 | M29: 456 | N29: =SUM(B29:M29) -> 7723 | O29: 1303 | P29: 1871 | Q29: 1924 | R29: 1105 | S29: 350 | W29: 9 | X29: 232 | Y29: 257 | Z29: 358 | AA29: =SUM(O29:Z29) -> 7409 | AB29: 1117 | AC29: 1683 | AD29: 1837 | AE29: 1234 | AF29: 450 | AJ29: 42 | AK29: 317 | AL29: 420 | AM29: 494 | AN29: =SUM(AB29:AM29) -> 7594 | AO29: 1044 | AP29: 1756 | AQ29: 1597 | AR29: 878 | AS29: 374 | AW29: 16 | AX29: 157 | AY29: 195 | AZ29: 463 | BA29: =SUM(AO29:AZ29) -> 6480 | BB29: 1058 | BC29: 1917 | BD29: 1382 | BE29: 819 | BF29: 279 | BJ29: 76 | BK29: 393 | BL29: 427 | BM29: 159 | BN29: =SUM(BB29:BM29) -> 6510 | BO29: 1228 | BP29: 2219 | BQ29: 1879 | BR29: 1276 | BS29: 449.97 | BY29: 634 | BZ29: 910 | CA29: 8595.97 | CB29: 1358.614 | CC29: 2208.979 | CD29: 2109.79 | CE29: 1525.417 | CF29: 634.9 | CL29: 829.69 | CM29: 1170.26 | CN29: 9837.65 | CO29: 1538.61 | CP29: 2204.84 | CQ29: 2166.5 | CR29: 1667.56 | CS29: 840.5 | CY29: 142.38 | CZ29: 725.4 | DA29: 9285.79 | DB29: 1239.06 | DC29: 1810.92 | DD29: 1776.02 | DE29: 1070.418 | DF29: 523.159 | DK29: 23.78 | DL29: 204.939 | DM29: 371.175 | DN29: 7019.471 | DO29: 641.539 | DP29: 986.483 | DQ29: 1159.649 | DR29: 814.669 | DS29: 356.668 | DT29: 0 | DU29: 0 | DV29: 0 | DW29: 0 | DX29: 37.32 | DY29: 237.06 | DZ29: 385.418 | EA29: 4618.806 | EB29: 509.339 | EC29: 582.819 | ED29: 525.508 | EE29: 356.428 | EF29: 208.64 | EG29: 0 | EH29: 0 | EI29: 0 | EJ29: 0 | EK29: 14.63 | EL29: 331.276 | EM29: 456.866 | EN29: 2985.506 | EO29: 522.279 | EP29: 572.477 | FA29: =SUM(EO29:EZ29) -> 1094.756 | FC29: =IFERROR((( _xlfn.XLOOKUP((DATE(YEAR($FC$5),MONTH($FC$5),1)),UCA.AGRO.DATE,$B29:$FA29) / _xlfn.XLOOKUP((DATE(YEAR($FC$5)-1,MONTH($FC$5),1)),UCA.AGRO.DATE,$B29:$FA29) )-1)*100,"") -> 39.743525 | FD29: =IFERROR(((FF29/FE29)-1)*100,"") -> -40.269118 | FE29: =SUMIFS($B29:$FA29,UCA.AGRO.DATE,">="&DATE(YEAR($FC$5)-1,1,1),UCA.AGRO.DATE,"<="&DATE(YEAR($FC$5)-1,MONTH($FC$5),1)) -> 4233.388 | FF29: =SUMIFS($B29:$FA29,UCA.AGRO.DATE,">="&DATE(YEAR($FC$5),1,1),UCA.AGRO.DATE,"<="&$FC$5) -> 2528.64 | FH29: =SUM(B29:FA29) -> 158307.9 | FI29: Pijuayo Fruto | FJ29: =IF(EXACT(A29,FI29)=TRUE,"OK","VER") -> OK
A30: Pijuayo Palmito | B30: 56 | C30: 58 | D30: 56 | E30: 52 | F30: 58 | G30: 60 | H30: 59 | I30: 60 | J30: 65 | K30: 70 | L30: 66 | M30: 64 | N30: =SUM(B30:M30) -> 724 | O30: 62 | P30: 62 | Q30: 61 | R30: 59 | S30: 58 | T30: 65 | U30: 59 | V30: 52 | W30: 51 | X30: 58 | Y30: 63 | Z30: 75 | AA30: =SUM(O30:Z30) -> 725 | AB30: 70 | AC30: 71 | AD30: 84 | AE30: 76 | AF30: 77 | AG30: 75 | AH30: 76 | AI30: 70 | AJ30: 74 | AK30: 78 | AL30: 85 | AM30: 100 | AN30: =SUM(AB30:AM30) -> 936 | AO30: 82 | AP30: 93 | AQ30: 97 | AR30: 95 | AS30: 90 | AT30: 100 | AU30: 93 | AV30: 95 | AW30: 86 | AX30: 100 | AY30: 91 | AZ30: 94 | BA30: =SUM(AO30:AZ30) -> 1116 | BB30: 88 | BC30: 91 | BD30: 96 | BE30: 94 | BF30: 94 | BG30: 89 | BH30: 88 | BI30: 85 | BJ30: 88 | BK30: 85 | BL30: 86 | BM30: 92 | BN30: =SUM(BB30:BM30) -> 1076 | BO30: 92 | BP30: 91 | BQ30: 91 | BR30: 90 | BS30: 92.93 | BT30: 92 | BU30: 91 | BV30: 79 | BW30: 84 | BX30: 79 | BY30: 84 | BZ30: 95 | CA30: 1060.93 | CB30: 93.52 | CC30: 99.02 | CD30: 97.609 | CE30: 106.594 | CF30: 96.65 | CG30: 96.028 | CH30: 84.659 | CI30: 72.889 | CJ30: 83.25 | CK30: 81.67 | CL30: 86.23 | CM30: 104.6 | CN30: 1102.719 | CO30: 82.12 | CP30: 92.21 | CQ30: 77.759 | CR30: 95.03 | CS30: 94.43 | CT30: 87.068 | CU30: 82.32 | CV30: 55.689 | CW30: 70.3 | CX30: 62.91 | CY30: 51.277 | CZ30: 42.9 | DA30: 894.013 | DB30: 30.24 | DC30: 22.13 | DD30: 18.75 | DN30: 71.12 | DO30: 0 | DP30: 0 | DQ30: 0 | DR30: 0 | DS30: 0 | DT30: 0 | DU30: 0 | DV30: 0 | DW30: 0 | DX30: 0 | DY30: 0 | DZ30: 0 | EA30: 0 | EB30: 0 | EC30: 0 | ED30: 0 | EE30: 0 | EF30: 0 | EG30: 0 | EH30: 0 | EI30: 0 | EJ30: 0 | EK30: 0 | EL30: 0 | EM30: 0 | EN30: 0 | EO30: 0 | EP30: 0 | FA30: =SUM(EO30:EZ30) -> 0 | FC30: =IFERROR((( _xlfn.XLOOKUP((DATE(YEAR($FC$5),MONTH($FC$5),1)),UCA.AGRO.DATE,$B30:$FA30) / _xlfn.XLOOKUP((DATE(YEAR($FC$5)-1,MONTH($FC$5),1)),UCA.AGRO.DATE,$B30:$FA30) )-1)*100,"") | FD30: =IFERROR(((FF30/FE30)-1)*100,"") | FE30: =SUMIFS($B30:$FA30,UCA.AGRO.DATE,">="&DATE(YEAR($FC$5)-1,1,1),UCA.AGRO.DATE,"<="&DATE(YEAR($FC$5)-1,MONTH($FC$5),1)) -> 0 | FF30: =SUMIFS($B30:$FA30,UCA.AGRO.DATE,">="&DATE(YEAR($FC$5),1,1),UCA.AGRO.DATE,"<="&$FC$5) -> 0 | FH30: =SUM(B30:FA30) -> 15411.564 | FI30: Pijuayo Palmito | FJ30: =IF(EXACT(A30,FI30)=TRUE,"OK","VER") -> OK
A31: Piña | B31: 815 | C31: 819 | D31: 648 | E31: 470 | F31: 525 | G31: 610 | H31: 637 | I31: 572 | J31: 988 | K31: 1093 | L31: 1279 | M31: 1459 | N31: =SUM(B31:M31) -> 9915 | O31: 734 | P31: 824 | Q31: 713 | R31: 506 | S31: 537 | T31: 612 | U31: 545 | V31: 473 | W31: 778 | X31: 1049 | Y31: 1244 | Z31: 1484 | AA31: =SUM(O31:Z31) -> 9499 | AB31: 956 | AC31: 892 | AD31: 783 | AE31: 564 | AF31: 608 | AG31: 666 | AH31: 552 | AI31: 501 | AJ31: 829 | AK31: 1284 | AL31: 1466 | AM31: 1885 | AN31: =SUM(AB31:AM31) -> 10986 | AO31: 739 | AP31: 792 | AQ31: 695 | AR31: 485 | AS31: 555 | AT31: 532 | AU31: 466 | AV31: 428 | AW31: 775 | AX31: 1206 | AY31: 1209 | AZ31: 1493 | BA31: =SUM(AO31:AZ31) -> 9375 | BB31: 896 | BC31: 779 | BD31: 695 | BE31: 539 | BF31: 506 | BG31: 496 | BH31: 497 | BI31: 530 | BJ31: 831 | BK31: 1204 | BL31: 1288 | BM31: 1543 | BN31: =SUM(BB31:BM31) -> 9804 | BO31: 993.869 | BP31: 858.58 | BQ31: 693.8 | BR31: 549.57 | BS31: 514.45 | BT31: 519.81 | BU31: 598.61 | BV31: 671.64 | BW31: 1351.53 | BX31: 1601.9 | BY31: 1568.11 | BZ31: 1686.519 | CA31: 11608.388 | CB31: 1181.19 | CC31: 919.69 | CD31: 1026.583 | CE31: 1138.919 | CF31: 877.88 | CG31: 783.57 | CH31: 693.72 | CI31: 620.04 | CJ31: 1068.68 | CK31: 1566.99 | CL31: 1841.57 | CM31: 1811.46 | CN31: 13530.292 | CO31: 1119.499 | CP31: 878.289 | CQ31: 879.72 | CR31: 881.869 | CS31: 914.09 | CT31: 932.99 | CU31: 870.349 | CV31: 735.428 | CW31: 1064.49 | CX31: 1391.33 | CY31: 1164.2 | CZ31: 1399.39 | DA31: 12231.644 | DB31: 1048.46 | DC31: 829.029 | DD31: 734.62 | DE31: 766.579 | DF31: 886.51 | DG31: 921.409 | DH31: 885.94 | DI31: 824.174 | DJ31: 999.178 | DK31: 1016.139 | DL31: 890.15 | DM31: 565.825 | DN31: 10368.013 | DO31: 513.029 | DP31: 456.209 | DQ31: 403.009 | DR31: 331.069 | DS31: 253.1 | DT31: 315.789 | DU31: 474.288 | DV31: 465.29 | DW31: 825.807 | DX31: 784.188 | DY31: 693.81 | DZ31: 479.696 | EA31: 5995.284 | EB31: 297.269 | EC31: 305.236 | ED31: 227.314 | EE31: 174.17 | EF31: 140.36 | EG31: 185.369 | EH31: 299.349 | EI31: 277.389 | EJ31: 473.516 | EK31: 601.478 | EL31: 678.03 | EM31: 693.932 | EN31: 4353.412 | EO31: 278.129 | EP31: 289.589 | FA31: =SUM(EO31:EZ31) -> 567.718 | FC31: =IFERROR((( _xlfn.XLOOKUP((DATE(YEAR($FC$5),MONTH($FC$5),1)),UCA.AGRO.DATE,$B31:$FA31) / _xlfn.XLOOKUP((DATE(YEAR($FC$5)-1,MONTH($FC$5),1)),UCA.AGRO.DATE,$B31:$FA31) )-1)*100,"") -> -2.2743979 | FD31: =IFERROR(((FF31/FE31)-1)*100,"") -> -33.652042 | FE31: =SUMIFS($B31:$FA31,UCA.AGRO.DATE,">="&DATE(YEAR($FC$5)-1,1,1),UCA.AGRO.DATE,"<="&DATE(YEAR($FC$5)-1,MONTH($FC$5),1)) -> 5515.588 | FF31: =SUMIFS($B31:$FA31,UCA.AGRO.DATE,">="&DATE(YEAR($FC$5),1,1),UCA.AGRO.DATE,"<="&$FC$5) -> 3659.48 | FH31: =SUM(B31:FA31) -> 216467.5 | FI31: Piña | FJ31: =IF(EXACT(A31,FI31)=TRUE,"OK","VER") -> OK
A32: Plátano | B32: 24878 | C32: 24624 | D32: 23274 | E32: 21375 | F32: 19764 | G32: 19135 | H32: 19695 | I32: 20664 | J32: 23104 | K32: 24882 | L32: 25948 | M32: 27038 | N32: =SUM(B32:M32) -> 274381 | O32: 25853 | P32: 25011 | Q32: 23065 | R32: 21509 | S32: 19239 | T32: 18942 | U32: 18485 | V32: 18347 | W32: 19581 | X32: 22223 | Y32: 24106 | Z32: 26007 | AA32: =SUM(O32:Z32) -> 262368 | AB32: 24855 | AC32: 24078 | AD32: 22997 | AE32: 21175 | AF32: 20289 | AG32: 19646 | AH32: 19316 | AI32: 19018 | AJ32: 20200 | AK32: 21409 | AL32: 23130 | AM32: 24841 | AN32: =SUM(AB32:AM32) -> 260954 | AO32: 25370 | AP32: 26319 | AQ32: 25039 | AR32: 22985 | AS32: 21954 | AT32: 20722 | AU32: 20429 | AV32: 21028 | AW32: 20977 | AX32: 22349 | AY32: 24061 | AZ32: 25541 | BA32: =SUM(AO32:AZ32) -> 276774 | BB32: 26320 | BC32: 26702 | BD32: 25658 | BE32: 23443 | BF32: 22912 | BG32: 21363 | BH32: 21804 | BI32: 20591 | BJ32: 21551 | BK32: 23439 | BL32: 24454 | BM32: 25929 | BN32: =SUM(BB32:BM32) -> 284166 | BO32: 27814.67 | BP32: 28140 | BQ32: 26608.12 | BR32: 25080.27 | BS32: 22820.5 | BT32: 21725.88 | BU32: 21713.48 | BV32: 21858.34 | BW32: 23199.99 | BX32: 24177.78 | BY32: 26200.03 | BZ32: 27297.4 | CA32: 296636.46 | CB32: 29573.1 | CC32: 28881.5 | CD32: 28688.948 | CE32: 28648.825 | CF32: 27251.858 | CG32: 26453.28 | CH32: 25892.76 | CI32: 24662.299 | CJ32: 24712.3 | CK32: 25035.29 | CL32: 27079.5 | CM32: 29317.88 | CN32: 326197.54 | CO32: 27438.5 | CP32: 27395.2 | CQ32: 26173.2 | CR32: 24636.639 | CS32: 23495.839 | CT32: 23097.509 | CU32: 23073.269 | CV32: 25398.06 | CW32: 25023.96 | CX32: 23638.759 | CY32: 22147.259 | CZ32: 21748.309 | DA32: 293266.5 | DB32: 21747.3 | DC32: 21221.45 | DD32: 22662.27 | DE32: 22860.47 | DF32: 23918.01 | DG32: 24787.069 | DH32: 25149.56 | DI32: 25300.01 | DJ32: 25726.32 | DK32: 26332.949 | DL32: 26512.49 | DM32: 26595.5 | DN32: 292813.4 | DO32: 27256.348 | DP32: 26673.96 | DQ32: 26382.68 | DR32: 25154.51 | DS32: 24722.709 | DT32: 24585.239 | DU32: 24690.49 | DV32: 24544.419 | DW32: 24427.77 | DX32: 24292.699 | DY32: 24163.739 | DZ32: 24324.49 | EA32: 301219.05 | EB32: 23963.65 | EC32: 23994.689 | ED32: 23033.46 | EE32: 22143.989 | EF32: 19133.88 | EG32: 18338.628 | EH32: 17360.148 | EI32: 16913.749 | EJ32: 16821.088 | EK32: 16774.716 | EL32: 16438.997 | EM32: 16301.939 | EN32: 231218.93 | EO32: 15927.689 | EP32: 15700.079 | FA32: =SUM(EO32:EZ32) -> 31627.768 | FC32: =IFERROR((( _xlfn.XLOOKUP((DATE(YEAR($FC$5),MONTH($FC$5),1)),UCA.AGRO.DATE,$B32:$FA32) / _xlfn.XLOOKUP((DATE(YEAR($FC$5)-1,MONTH($FC$5),1)),UCA.AGRO.DATE,$B32:$FA32) )-1)*100,"") -> -31.968322 | FD32: =IFERROR(((FF32/FE32)-1)*100,"") -> -22.383094 | FE32: =SUMIFS($B32:$FA32,UCA.AGRO.DATE,">="&DATE(YEAR($FC$5)-1,1,1),UCA.AGRO.DATE,"<="&DATE(YEAR($FC$5)-1,MONTH($FC$5),1)) -> 276894.56 | FF32: =SUMIFS($B32:$FA32,UCA.AGRO.DATE,">="&DATE(YEAR($FC$5),1,1),UCA.AGRO.DATE,"<="&$FC$5) -> 214916.99 | FH32: =SUM(B32:FA32) -> 6263245.3 | FI32: Plátano | FJ32: =IF(EXACT(A32,FI32)=TRUE,"OK","VER") -> OK
A33: Sacha Inchi | N33: =SUM(B33:M33) -> 0 | AA33: =SUM(O33:Z33) -> 0 | AN33: =SUM(AB33:AM33) -> 0 | BA33: =SUM(AO33:AZ33) -> 0 | BN33: =SUM(BB33:BM33) -> 0 | DO33: 0 | DP33: 0 | DQ33: 0 | DR33: 0 | DS33: 0 | DT33: 0 | DU33: 0 | DV33: 0 | DW33: 0 | DX33: 0 | DY33: 0 | DZ33: 0 | EA33: 0 | EB33: 0 | EC33: 0 | ED33: 0 | EE33: 0 | EF33: 0 | EG33: 0 | EH33: 0 | EI33: 0 | EJ33: 0 | EK33: 0 | EL33: 0 | EM33: 0 | EN33: 0 | EO33: 0 | EP33: 0 | FA33: =SUM(EO33:EZ33) -> 0 | FC33: =IFERROR((( _xlfn.XLOOKUP((DATE(YEAR($FC$5),MONTH($FC$5),1)),UCA.AGRO.DATE,$B33:$FA33) / _xlfn.XLOOKUP((DATE(YEAR($FC$5)-1,MONTH($FC$5),1)),UCA.AGRO.DATE,$B33:$FA33) )-1)*100,"") | FD33: =IFERROR(((FF33/FE33)-1)*100,"") | FE33: =SUMIFS($B33:$FA33,UCA.AGRO.DATE,">="&DATE(YEAR($FC$5)-1,1,1),UCA.AGRO.DATE,"<="&DATE(YEAR($FC$5)-1,MONTH($FC$5),1)) -> 0 | FF33: =SUMIFS($B33:$FA33,UCA.AGRO.DATE,">="&DATE(YEAR($FC$5),1,1),UCA.AGRO.DATE,"<="&$FC$5) -> 0 | FH33: =SUM(B33:FA33) -> 0 | FI33: Sacha Inchi | FJ33: =IF(EXACT(A33,FI33)=TRUE,"OK","VER") -> OK
A34: Sandía | H34: 217 | I34: 1021 | J34: 1399 | K34: 1122 | L34: 263 | M34: 135 | N34: =SUM(B34:M34) -> 4157 | O34: 34 | P34: 46 | U34: 108 | V34: 860 | W34: 693 | X34: 436 | Y34: 180 | Z34: 41 | AA34: =SUM(O34:Z34) -> 2398 | AH34: 482 | AI34: 1451 | AJ34: 843 | AK34: 476 | AL34: 39 | AN34: =SUM(AB34:AM34) -> 3291 | AO34: 34 | AP34: 18 | AQ34: 35 | AU34: 526 | AV34: 2241 | AW34: 1073 | AX34: 762 | AY34: 148 | AZ34: 138 | BA34: =SUM(AO34:AZ34) -> 4975 | BH34: 169 | BI34: 672 | BJ34: 2058 | BK34: 2715 | BL34: 397 | BM34: 162 | BN34: =SUM(BB34:BM34) -> 6173 | BO34: 25.4 | BP34: 30.6 | BU34: 754.2 | BV34: 3862.149 | BW34: 2223.52 | BX34: 648.67 | BY34: 18.7 | BZ34: 269.5 | CA34: 7832.739 | CB34: 177.95 | CC34: 99 | CH34: 460.8 | CI34: 4147.45 | CJ34: 2298.45 | CK34: 1271.94 | CL34: 980.85 | CM34: 283.1 | CN34: 9719.54 | CP34: 118.25 | CU34: 83.4 | CV34: 2272.5 | CW34: 1606.31 | CX34: 853.15 | CY34: 231.92 | CZ34: 530.87 | DA34: 5696.4 | DB34: 346.88 | DC34: 157.99 | DI34: 1085.35 | DJ34: 1798.59 | DK34: 1210.429 | DL34: 12.58 | DM34: 124.25 | DN34: 4736.069 | DO34: 528.37 | DP34: 0 | DQ34: 0 | DR34: 0 | DS34: 0 | DT34: 0 | DU34: 70.1 | DV34: 3733.53 | DW34: 3631.53 | DX34: 1030.509 | DY34: 1039.174 | DZ34: 702.761 | EA34: 10735.974 | EB34: 156.309 | EC34: 0 | ED34: 0 | EE34: 0 | EF34: 0 | EG34: 0 | EH34: 25.47 | EI34: 2057.878 | EJ34: 1953.839 | EK34: 1391.629 | EL34: 302.889 | EM34: 1364.422 | EN34: 7252.436 | EO34: 0 | EP34: 0 | FA34: =SUM(EO34:EZ34) -> 0 | FC34: =IFERROR((( _xlfn.XLOOKUP((DATE(YEAR($FC$5),MONTH($FC$5),1)),UCA.AGRO.DATE,$B34:$FA34) / _xlfn.XLOOKUP((DATE(YEAR($FC$5)-1,MONTH($FC$5),1)),UCA.AGRO.DATE,$B34:$FA34) )-1)*100,"") -> -70.852908 | FD34: =IFERROR(((FF34/FE34)-1)*100,"") -> -41.314771 | FE34: =SUMIFS($B34:$FA34,UCA.AGRO.DATE,">="&DATE(YEAR($FC$5)-1,1,1),UCA.AGRO.DATE,"<="&DATE(YEAR($FC$5)-1,MONTH($FC$5),1)) -> 10033.213 | FF34: =SUMIFS($B34:$FA34,UCA.AGRO.DATE,">="&DATE(YEAR($FC$5),1,1),UCA.AGRO.DATE,"<="&$FC$5) -> 5888.014 | FH34: =SUM(B34:FA34) -> 133934.32 | FI34: Sandía | FJ34: =IF(EXACT(A34,FI34)=TRUE,"OK","VER") -> OK
A35: Tomate | B35: 32 | C35: 10 | D35: 25 | I35: 6 | J35: 33 | K35: 37 | L35: 43 | M35: 48 | N35: =SUM(B35:M35) -> 234 | O35: 45 | P35: 45 | Q35: 26 | R35: 26 | S35: 13 | W35: 9 | X35: 57 | Y35: 104 | Z35: 23 | AA35: =SUM(O35:Z35) -> 348 | AK35: 34 | AL35: 106 | AM35: 22 | AN35: =SUM(AB35:AM35) -> 162 | AW35: 7 | AX35: 67 | AY35: 61 | AZ35: 35 | BA35: =SUM(AO35:AZ35) -> 170 | BB35: 6 | BH35: 5 | BJ35: 8 | BK35: 6 | BL35: 49 | BM35: 65 | BN35: =SUM(BB35:BM35) -> 139 | BO35: 24.98 | BP35: 14.3 | BQ35: 8.56 | BR35: 8.72 | BS35: 4.75 | BW35: 27.65 | BX35: 187.47 | BY35: 62.47 | BZ35: 98.27 | CA35: 437.17 | CB35: 12.18 | CC35: 60.77 | CD35: 11.61 | CE35: 24.11 | CI35: 11.54 | CJ35: 33.67 | CK35: 103.55 | CL35: 88.06 | CM35: 108.278 | CN35: 453.768 | CO35: 52.409 | CP35: 28.18 | CQ35: 7.15 | CR35: 48.24 | CW35: 8.519 | CX35: 53.52 | CY35: 118.389 | CZ35: 55.889 | DA35: 372.296 | DB35: 73.61 | DC35: 50.37 | DD35: 36.02 | DE35: 51.468 | DH35: 12.57 | DJ35: 24.75 | DK35: 64.6 | DL35: 167.16 | DM35: 43.039 | DN35: 523.587 | DO35: 26.45 | DP35: 5.84 | DQ35: 51.51 | DR35: 0 | DS35: 0 | DT35: 0 | DU35: 0 | DV35: 0 | DW35: 4.95 | DX35: 322.159 | DY35: 267.379 | DZ35: 251.399 | EA35: 929.687 | EB35: 220.28 | EC35: 162.441 | ED35: 87.09 | EE35: 0 | EF35: 6.57 | EG35: 0 | EH35: 20.129 | EI35: 0 | EJ35: 421.68 | EK35: 316.43 | EL35: 305.929 | EM35: 149.45 | EN35: 1689.999 | EO35: 316.627 | EP35: 161.38 | FA35: =SUM(EO35:EZ35) -> 478.007 | FC35: =IFERROR((( _xlfn.XLOOKUP((DATE(YEAR($FC$5),MONTH($FC$5),1)),UCA.AGRO.DATE,$B35:$FA35) / _xlfn.XLOOKUP((DATE(YEAR($FC$5)-1,MONTH($FC$5),1)),UCA.AGRO.DATE,$B35:$FA35) )-1)*100,"") -> 14.417737 | FD35: =IFERROR(((FF35/FE35)-1)*100,"") -> 127.12314 | FE35: =SUMIFS($B35:$FA35,UCA.AGRO.DATE,">="&DATE(YEAR($FC$5)-1,1,1),UCA.AGRO.DATE,"<="&DATE(YEAR($FC$5)-1,MONTH($FC$5),1)) -> 678.288 | FF35: =SUMIFS($B35:$FA35,UCA.AGRO.DATE,">="&DATE(YEAR($FC$5),1,1),UCA.AGRO.DATE,"<="&$FC$5) -> 1540.549 | FH35: =SUM(B35:FA35) -> 11875.028 | FI35: Tomate | FJ35: =IF(EXACT(A35,FI35)=TRUE,"OK","VER") -> OK
A36: Yuca | B36: 15946 | C36: 12745 | D36: 10618 | E36: 12103 | F36: 12944 | G36: 12610 | H36: 11894 | I36: 12482 | J36: 12507 | K36: 8149 | L36: 7900 | M36: 7539 | N36: =SUM(B36:M36) -> 137437 | O36: 9367 | P36: 13605 | Q36: 11967 | R36: 14196 | S36: 14697 | T36: 11875 | U36: 9438 | V36: 9757 | W36: 5708 | X36: 8342 | Y36: 4993 | Z36: 6814 | AA36: =SUM(O36:Z36) -> 120759 | AB36: 7239 | AC36: 10967 | AD36: 10125 | AE36: 6432 | AF36: 6493 | AG36: 4785 | AH36: 5318 | AI36: 6977 | AJ36: 6966 | AK36: 8078 | AL36: 5358 | AM36: 6355 | AN36: =SUM(AB36:AM36) -> 85093 | AO36: 8429 | AP36: 6992 | AQ36: 9206 | AR36: 11076 | AS36: 5990 | AT36: 8809 | AU36: 6787 | AV36: 6961 | AW36: 5188 | AX36: 6994 | AY36: 5090 | AZ36: 5229 | BA36: =SUM(AO36:AZ36) -> 86751 | BB36: 6759 | BC36: 8237 | BD36: 9381 | BE36: 11516 | BF36: 8991 | BG36: 8816 | BH36: 7105 | BI36: 5775 | BJ36: 5121 | BK36: 7274 | BL36: 6290 | BM36: 7637 | BN36: =SUM(BB36:BM36) -> 92902 | BO36: 6897.019 | BP36: 9366.72 | BQ36: 8939.59 | BR36: 9649.829 | BS36: 10395.36 | BT36: 11136.828 | BU36: 10626.39 | BV36: 8570.03 | BW36: 6427.99 | BX36: 8038.37 | BY36: 5772.408 | BZ36: 7126.289 | CA36: 102946.82 | CB36: 6790.819 | CC36: 12011.959 | CD36: 10036.799 | CE36: 6251.119 | CF36: 11015.87 | CG36: 10320.239 | CH36: 12645.284 | CI36: 8760.928 | CJ36: 6986.419 | CK36: 5179.74 | CL36: 3443.079 | CM36: 7099.51 | CN36: 100541.76 | CO36: 6956.12 | CP36: 8403.57 | CQ36: 7960.329 | CR36: 7081.289 | CS36: 15628.128 | CT36: 22866.45 | CU36: 14201.81 | CV36: 9460.699 | CW36: 6351.719 | CX36: 2692.76 | CY36: 3849.32 | CZ36: 3409.14 | DA36: 108861.33 | DB36: 4219.879 | DC36: 6826.94 | DD36: 7790.33 | DE36: 9418.525 | DF36: 23244.439 | DG36: 21273.148 | DH36: 25876.217 | DI36: 7296.319 | DJ36: 5377.322 | DK36: 6338.86 | DL36: 3554.029 | DM36: 7404.448 | DN36: 128620.46 | DO36: 6764.15 | DP36: 9298.169 | DQ36: 9139.63 | DR36: 10259.619 | DS36: 2893.309 | DT36: 6370.93 | DU36: 6058.159 | DV36: 4898.72 | DW36: 5283.219 | DX36: 3826.66 | DY36: 2892.048 | DZ36: 8644.208 | EA36: 76328.821 | EB36: 4669.519 | EC36: 10113.118 | ED36: 11887.917 | EE36: 7978.95 | EF36: 34064.497 | EG36: 45801.146 | EH36: 19210.5 | EI36: 13832.23 | EJ36: 2801.459 | EK36: 3325.359 | EL36: 5758.889 | EM36: 2592.938 | EN36: 162036.52 | EO36: 5863.18 | EP36: 12230.945 | FA36: =SUM(EO36:EZ36) -> 18094.125 | FC36: =IFERROR((( _xlfn.XLOOKUP((DATE(YEAR($FC$5),MONTH($FC$5),1)),UCA.AGRO.DATE,$B36:$FA36) / _xlfn.XLOOKUP((DATE(YEAR($FC$5)-1,MONTH($FC$5),1)),UCA.AGRO.DATE,$B36:$FA36) )-1)*100,"") -> 99.128403 | FD36: =IFERROR(((FF36/FE36)-1)*100,"") -> 135.56844 | FE36: =SUMIFS($B36:$FA36,UCA.AGRO.DATE,">="&DATE(YEAR($FC$5)-1,1,1),UCA.AGRO.DATE,"<="&DATE(YEAR($FC$5)-1,MONTH($FC$5),1)) -> 67684.613 | FF36: =SUMIFS($B36:$FA36,UCA.AGRO.DATE,">="&DATE(YEAR($FC$5),1,1),UCA.AGRO.DATE,"<="&$FC$5) -> 159443.58 | FH36: =SUM(B36:FA36) -> 2440743.7 | FI36: Yuca | FJ36: =IF(EXACT(A36,FI36)=TRUE,"OK","VER") -> OK
A37: Aguaje | B37: 1674 | C37: 1783 | D37: 1334 | E37: 667 | F37: 757 | G37: 656 | H37: 441 | I37: 521 | J37: 757 | K37: 1066 | L37: 1181 | M37: 1372 | N37: =SUM(B37:M37) -> 12209 | O37: 1578 | P37: 1776 | Q37: 1481 | R37: 993 | S37: 845 | T37: 750 | U37: 548 | V37: 447 | W37: 548 | X37: 875 | Y37: 1052 | Z37: 1241 | AA37: =SUM(O37:Z37) -> 12134 | AB37: 1576 | AC37: 1775 | AD37: 1576 | AE37: 1208 | AF37: 990 | AG37: 868 | AH37: 692 | AI37: 585 | AJ37: 610 | AK37: 906 | AL37: 1175 | AM37: 1350 | AN37: =SUM(AB37:AM37) -> 13311 | AO37: 1495 | AP37: 1831 | AQ37: 803 | AR37: 205 | AS37: 791 | AT37: 967 | AU37: 833 | AV37: 772 | AW37: 748 | AX37: 1054 | AY37: 1259 | AZ37: 1261 | BA37: =SUM(AO37:AZ37) -> 12019 | BB37: 1529 | BC37: 2004 | BD37: 1249 | BE37: 760 | BF37: 915 | BG37: 779 | BH37: 739 | BI37: 629 | BJ37: 552 | BK37: 985 | BL37: 1048 | BM37: 956 | BN37: =SUM(BB37:BM37) -> 12145 | BO37: 1400 | BP37: 1784 | BQ37: 1365 | BR37: 934 | BS37: 922 | BT37: 754 | BU37: 710 | BV37: 682 | BW37: 843 | BX37: 1013 | BY37: 1150 | BZ37: 1197 | CA37: 12754 | CB37: 1417.66 | CC37: 1936.71 | CD37: 1672.89 | CE37: 1233.75 | CF37: 1091.228 | CG37: 982.537 | CH37: 794.769 | CI37: 682.23 | CJ37: 792.37 | CK37: 1024.49 | CL37: 1214.09 | CM37: 1259.94 | CN37: 14102.664 | CO37: 1248.517 | CP37: 1667.057 | CQ37: 1517.969 | CR37: 1285.038 | CS37: 1132.859 | CT37: 1134.33 | CU37: 973.35 | CV37: 1138.809 | CW37: 1131.51 | CX37: 1180.19 | CY37: 1240.7 | CZ37: 1225.93 | DA37: 14876.259 | DB37: 1210.309 | DC37: 1519.03 | DD37: 1531.22 | DE37: 1419.33 | DF37: 1205.165 | DG37: 1244.69 | DH37: 1083.897 | DI37: 924.75 | DJ37: 911.249 | DK37: 1068.996 | DL37: 1110.077 | DM37: 929.188 | DN37: 14157.901 | DO37: 1084.084 | DP37: 1258.949 | DQ37: 1292.89 | DR37: 1208.948 | DS37: 1014.96 | DT37: 977.04 | DU37: 884.896 | DV37: 760.289 | DW37: 688.338 | DX37: 634.317 | DY37: 741.301 | DZ37: 633.31 | EA37: 11179.322 | EB37: 699.567 | EC37: 777.31 | ED37: 654.568 | EE37: 426.047 | EF37: 473.297 | EG37: 468.497 | EH37: 422.767 | EI37: 398.267 | EJ37: 405.628 | EK37: 431.216 | EL37: 506.434 | EN37: 5663.598 | FA37: =SUM(EO37:EZ37) -> 0 | FC37: =IFERROR((( _xlfn.XLOOKUP((DATE(YEAR($FC$5),MONTH($FC$5),1)),UCA.AGRO.DATE,$B37:$FA37) / _xlfn.XLOOKUP((DATE(YEAR($FC$5)-1,MONTH($FC$5),1)),UCA.AGRO.DATE,$B37:$FA37) )-1)*100,"") -> -31.683082 | FD37: =IFERROR(((FF37/FE37)-1)*100,"") -> -46.296306 | FE37: =SUMIFS($B37:$FA37,UCA.AGRO.DATE,">="&DATE(YEAR($FC$5)-1,1,1),UCA.AGRO.DATE,"<="&DATE(YEAR($FC$5)-1,MONTH($FC$5),1)) -> 10546.012 | FF37: =SUMIFS($B37:$FA37,UCA.AGRO.DATE,">="&DATE(YEAR($FC$5),1,1),UCA.AGRO.DATE,"<="&$FC$5) -> 5663.598 | FH37: =SUM(B37:FA37) -> 269103.49 | FI37: ZZ Aguaje | FJ37: =IF(EXACT(A37,FI37)=TRUE,"OK","VER") -> VER
A39: Otros agrícolas | B39: {=SUMPRODUCT((UCA.AGROOTROS.NAME=$A39)*(UCA.AGROOTROS.DATE=B$5)*(UCA.AGROOTROS.VAL))} -> 6727 | C39: {=SUMPRODUCT((UCA.AGROOTROS.NAME=$A39)*(UCA.AGROOTROS.DATE=C$5)*(UCA.AGROOTROS.VAL))} -> 7294 | D39: {=SUMPRODUCT((UCA.AGROOTROS.NAME=$A39)*(UCA.AGROOTROS.DATE=D$5)*(UCA.AGROOTROS.VAL))} -> 6071 | E39: {=SUMPRODUCT((UCA.AGROOTROS.NAME=$A39)*(UCA.AGROOTROS.DATE=E$5)*(UCA.AGROOTROS.VAL))} -> 3315 | F39: {=SUMPRODUCT((UCA.AGROOTROS.NAME=$A39)*(UCA.AGROOTROS.DATE=F$5)*(UCA.AGROOTROS.VAL))} -> 3257 | G39: {=SUMPRODUCT((UCA.AGROOTROS.NAME=$A39)*(UCA.AGROOTROS.DATE=G$5)*(UCA.AGROOTROS.VAL))} -> 2601 | H39: {=SUMPRODUCT((UCA.AGROOTROS.NAME=$A39)*(UCA.AGROOTROS.DATE=H$5)*(UCA.AGROOTROS.VAL))} -> 1511 | I39: {=SUMPRODUCT((UCA.AGROOTROS.NAME=$A39)*(UCA.AGROOTROS.DATE=I$5)*(UCA.AGROOTROS.VAL))} -> 1880 | ... M39: {=SUMPRODUCT((UCA.AGROOTROS.NAME=$A39)*(UCA.AGROOTROS.DATE=M$5)*(UCA.AGROOTROS.VAL))} -> 4806 | N39: =SUM(B39:M39) -> 46929 | O39: {=SUMPRODUCT((UCA.AGROOTROS.NAME=$A39)*(UCA.AGROOTROS.DATE=O$5)*(UCA.AGROOTROS.VAL))} -> 5013 | P39: {=SUMPRODUCT((UCA.AGROOTROS.NAME=$A39)*(UCA.AGROOTROS.DATE=P$5)*(UCA.AGROOTROS.VAL))} -> 6830 | Q39: {=SUMPRODUCT((UCA.AGROOTROS.NAME=$A39)*(UCA.AGROOTROS.DATE=Q$5)*(UCA.AGROOTROS.VAL))} -> 6844 | R39: {=SUMPRODUCT((UCA.AGROOTROS.NAME=$A39)*(UCA.AGROOTROS.DATE=R$5)*(UCA.AGROOTROS.VAL))} -> 4355 | S39: {=SUMPRODUCT((UCA.AGROOTROS.NAME=$A39)*(UCA.AGROOTROS.DATE=S$5)*(UCA.AGROOTROS.VAL))} -> 3539 | T39: {=SUMPRODUCT((UCA.AGROOTROS.NAME=$A39)*(UCA.AGROOTROS.DATE=T$5)*(UCA.AGROOTROS.VAL))} -> 2260 | U39: {=SUMPRODUCT((UCA.AGROOTROS.NAME=$A39)*(UCA.AGROOTROS.DATE=U$5)*(UCA.AGROOTROS.VAL))} -> 1224 | V39: {=SUMPRODUCT((UCA.AGROOTROS.NAME=$A39)*(UCA.AGROOTROS.DATE=V$5)*(UCA.AGROOTROS.VAL))} -> 1487 | ... Z39: {=SUMPRODUCT((UCA.AGROOTROS.NAME=$A39)*(UCA.AGROOTROS.DATE=Z$5)*(UCA.AGROOTROS.VAL))} -> 5000 | AA39: =SUM(O39:Z39) -> 44072 | AB39: {=SUMPRODUCT((UCA.AGROOTROS.NAME=$A39)*(UCA.AGROOTROS.DATE=AB$5)*(UCA.AGROOTROS.VAL))} -> 5226 | AC39: {=SUMPRODUCT((UCA.AGROOTROS.NAME=$A39)*(UCA.AGROOTROS.DATE=AC$5)*(UCA.AGROOTROS.VAL))} -> 6518 | AD39: {=SUMPRODUCT((UCA.AGROOTROS.NAME=$A39)*(UCA.AGROOTROS.DATE=AD$5)*(UCA.AGROOTROS.VAL))} -> 7251 | AE39: {=SUMPRODUCT((UCA.AGROOTROS.NAME=$A39)*(UCA.AGROOTROS.DATE=AE$5)*(UCA.AGROOTROS.VAL))} -> 5442 | AF39: {=SUMPRODUCT((UCA.AGROOTROS.NAME=$A39)*(UCA.AGROOTROS.DATE=AF$5)*(UCA.AGROOTROS.VAL))} -> 4172 | AG39: {=SUMPRODUCT((UCA.AGROOTROS.NAME=$A39)*(UCA.AGROOTROS.DATE=AG$5)*(UCA.AGROOTROS.VAL))} -> 2684 | AH39: {=SUMPRODUCT((UCA.AGROOTROS.NAME=$A39)*(UCA.AGROOTROS.DATE=AH$5)*(UCA.AGROOTROS.VAL))} -> 1351 | AI39: {=SUMPRODUCT((UCA.AGROOTROS.NAME=$A39)*(UCA.AGROOTROS.DATE=AI$5)*(UCA.AGROOTROS.VAL))} -> 1454 | ... AM39: {=SUMPRODUCT((UCA.AGROOTROS.NAME=$A39)*(UCA.AGROOTROS.DATE=AM$5)*(UCA.AGROOTROS.VAL))} -> 5957 | AN39: =SUM(AB39:AM39) -> 49620 | AO39: {=SUMPRODUCT((UCA.AGROOTROS.NAME=$A39)*(UCA.AGROOTROS.DATE=AO$5)*(UCA.AGROOTROS.VAL))} -> 5583 | AP39: {=SUMPRODUCT((UCA.AGROOTROS.NAME=$A39)*(UCA.AGROOTROS.DATE=AP$5)*(UCA.AGROOTROS.VAL))} -> 7399 | AQ39: {=SUMPRODUCT((UCA.AGROOTROS.NAME=$A39)*(UCA.AGROOTROS.DATE=AQ$5)*(UCA.AGROOTROS.VAL))} -> 7585 | AR39: {=SUMPRODUCT((UCA.AGROOTROS.NAME=$A39)*(UCA.AGROOTROS.DATE=AR$5)*(UCA.AGROOTROS.VAL))} -> 5688 | AS39: {=SUMPRODUCT((UCA.AGROOTROS.NAME=$A39)*(UCA.AGROOTROS.DATE=AS$5)*(UCA.AGROOTROS.VAL))} -> 4409 | AT39: {=SUMPRODUCT((UCA.AGROOTROS.NAME=$A39)*(UCA.AGROOTROS.DATE=AT$5)*(UCA.AGROOTROS.VAL))} -> 2968 | AU39: {=SUMPRODUCT((UCA.AGROOTROS.NAME=$A39)*(UCA.AGROOTROS.DATE=AU$5)*(UCA.AGROOTROS.VAL))} -> 1931 | AV39: {=SUMPRODUCT((UCA.AGROOTROS.NAME=$A39)*(UCA.AGROOTROS.DATE=AV$5)*(UCA.AGROOTROS.VAL))} -> 1684 | ... AZ39: {=SUMPRODUCT((UCA.AGROOTROS.NAME=$A39)*(UCA.AGROOTROS.DATE=AZ$5)*(UCA.AGROOTROS.VAL))} -> 4007 | BA39: =SUM(AO39:AZ39) -> 48220 | BB39: {=SUMPRODUCT((UCA.AGROOTROS.NAME=$A39)*(UCA.AGROOTROS.DATE=BB$5)*(UCA.AGROOTROS.VAL))} -> 4401 | BC39: {=SUMPRODUCT((UCA.AGROOTROS.NAME=$A39)*(UCA.AGROOTROS.DATE=BC$5)*(UCA.AGROOTROS.VAL))} -> 6767 | BD39: {=SUMPRODUCT((UCA.AGROOTROS.NAME=$A39)*(UCA.AGROOTROS.DATE=BD$5)*(UCA.AGROOTROS.VAL))} -> 6627 | BE39: {=SUMPRODUCT((UCA.AGROOTROS.NAME=$A39)*(UCA.AGROOTROS.DATE=BE$5)*(UCA.AGROOTROS.VAL))} -> 5384 | BF39: {=SUMPRODUCT((UCA.AGROOTROS.NAME=$A39)*(UCA.AGROOTROS.DATE=BF$5)*(UCA.AGROOTROS.VAL))} -> 4226 | BG39: {=SUMPRODUCT((UCA.AGROOTROS.NAME=$A39)*(UCA.AGROOTROS.DATE=BG$5)*(UCA.AGROOTROS.VAL))} -> 2498 | BH39: {=SUMPRODUCT((UCA.AGROOTROS.NAME=$A39)*(UCA.AGROOTROS.DATE=BH$5)*(UCA.AGROOTROS.VAL))} -> 1411 | BI39: {=SUMPRODUCT((UCA.AGROOTROS.NAME=$A39)*(UCA.AGROOTROS.DATE=BI$5)*(UCA.AGROOTROS.VAL))} -> 914 | ... BM39: {=SUMPRODUCT((UCA.AGROOTROS.NAME=$A39)*(UCA.AGROOTROS.DATE=BM$5)*(UCA.AGROOTROS.VAL))} -> 3652 | BN39: =SUM(BB39:BM39) -> 41909 | BO39: {=SUMPRODUCT((UCA.AGROOTROS.NAME=$A39)*(UCA.AGROOTROS.DATE=BO$5)*(UCA.AGROOTROS.VAL))} -> 6334.637 | BP39: {=SUMPRODUCT((UCA.AGROOTROS.NAME=$A39)*(UCA.AGROOTROS.DATE=BP$5)*(UCA.AGROOTROS.VAL))} -> 9727.113 | BQ39: {=SUMPRODUCT((UCA.AGROOTROS.NAME=$A39)*(UCA.AGROOTROS.DATE=BQ$5)*(UCA.AGROOTROS.VAL))} -> 10178.267 | BR39: {=SUMPRODUCT((UCA.AGROOTROS.NAME=$A39)*(UCA.AGROOTROS.DATE=BR$5)*(UCA.AGROOTROS.VAL))} -> 8062.706 | BS39: {=SUMPRODUCT((UCA.AGROOTROS.NAME=$A39)*(UCA.AGROOTROS.DATE=BS$5)*(UCA.AGROOTROS.VAL))} -> 6310.12 | BT39: {=SUMPRODUCT((UCA.AGROOTROS.NAME=$A39)*(UCA.AGROOTROS.DATE=BT$5)*(UCA.AGROOTROS.VAL))} -> 3493.756 | BU39: {=SUMPRODUCT((UCA.AGROOTROS.NAME=$A39)*(UCA.AGROOTROS.DATE=BU$5)*(UCA.AGROOTROS.VAL))} -> 2881.94 | BV39: {=SUMPRODUCT((UCA.AGROOTROS.NAME=$A39)*(UCA.AGROOTROS.DATE=BV$5)*(UCA.AGROOTROS.VAL))} -> 2362.66 | ... BZ39: {=SUMPRODUCT((UCA.AGROOTROS.NAME=$A39)*(UCA.AGROOTROS.DATE=BZ$5)*(UCA.AGROOTROS.VAL))} -> 6270.444 | CA39: =SUM(BO39:BZ39) -> 65122.886 | CB39: {=SUMPRODUCT((UCA.AGROOTROS.NAME=$A39)*(UCA.AGROOTROS.DATE=CB$5)*(UCA.AGROOTROS.VAL))} -> 7777.742 | CC39: {=SUMPRODUCT((UCA.AGROOTROS.NAME=$A39)*(UCA.AGROOTROS.DATE=CC$5)*(UCA.AGROOTROS.VAL))} -> 10224.347 | CD39: {=SUMPRODUCT((UCA.AGROOTROS.NAME=$A39)*(UCA.AGROOTROS.DATE=CD$5)*(UCA.AGROOTROS.VAL))} -> 10341.28 | CE39: {=SUMPRODUCT((UCA.AGROOTROS.NAME=$A39)*(UCA.AGROOTROS.DATE=CE$5)*(UCA.AGROOTROS.VAL))} -> 9846.476 | CF39: {=SUMPRODUCT((UCA.AGROOTROS.NAME=$A39)*(UCA.AGROOTROS.DATE=CF$5)*(UCA.AGROOTROS.VAL))} -> 7232.435 | CG39: {=SUMPRODUCT((UCA.AGROOTROS.NAME=$A39)*(UCA.AGROOTROS.DATE=CG$5)*(UCA.AGROOTROS.VAL))} -> 4474.635 | CH39: {=SUMPRODUCT((UCA.AGROOTROS.NAME=$A39)*(UCA.AGROOTROS.DATE=CH$5)*(UCA.AGROOTROS.VAL))} -> 2316.455 | CI39: {=SUMPRODUCT((UCA.AGROOTROS.NAME=$A39)*(UCA.AGROOTROS.DATE=CI$5)*(UCA.AGROOTROS.VAL))} -> 2320.344 | ... CM39: {=SUMPRODUCT((UCA.AGROOTROS.NAME=$A39)*(UCA.AGROOTROS.DATE=CM$5)*(UCA.AGROOTROS.VAL))} -> 8112.305 | CN39: =SUM(CB39:CM39) -> 75354.112 | CO39: {=SUMPRODUCT((UCA.AGROOTROS.NAME=$A39)*(UCA.AGROOTROS.DATE=CO$5)*(UCA.AGROOTROS.VAL))} -> 8123.709 | CP39: {=SUMPRODUCT((UCA.AGROOTROS.NAME=$A39)*(UCA.AGROOTROS.DATE=CP$5)*(UCA.AGROOTROS.VAL))} -> 10172.645 | CQ39: {=SUMPRODUCT((UCA.AGROOTROS.NAME=$A39)*(UCA.AGROOTROS.DATE=CQ$5)*(UCA.AGROOTROS.VAL))} -> 10313.227 | CR39: {=SUMPRODUCT((UCA.AGROOTROS.NAME=$A39)*(UCA.AGROOTROS.DATE=CR$5)*(UCA.AGROOTROS.VAL))} -> 9394.681 | CS39: {=SUMPRODUCT((UCA.AGROOTROS.NAME=$A39)*(UCA.AGROOTROS.DATE=CS$5)*(UCA.AGROOTROS.VAL))} -> 7512.08 | CT39: {=SUMPRODUCT((UCA.AGROOTROS.NAME=$A39)*(UCA.AGROOTROS.DATE=CT$5)*(UCA.AGROOTROS.VAL))} -> 4841.966 | CU39: {=SUMPRODUCT((UCA.AGROOTROS.NAME=$A39)*(UCA.AGROOTROS.DATE=CU$5)*(UCA.AGROOTROS.VAL))} -> 2495.67 | CV39: {=SUMPRODUCT((UCA.AGROOTROS.NAME=$A39)*(UCA.AGROOTROS.DATE=CV$5)*(UCA.AGROOTROS.VAL))} -> 2140.835 | ... CZ39: {=SUMPRODUCT((UCA.AGROOTROS.NAME=$A39)*(UCA.AGROOTROS.DATE=CZ$5)*(UCA.AGROOTROS.VAL))} -> 7129.588 | DA39: =SUM(CO39:CZ39) -> 70636.303 | DB39: {=SUMPRODUCT((UCA.AGROOTROS.NAME=$A39)*(UCA.AGROOTROS.DATE=DB$5)*(UCA.AGROOTROS.VAL))} -> 7772.424 | DC39: {=SUMPRODUCT((UCA.AGROOTROS.NAME=$A39)*(UCA.AGROOTROS.DATE=DC$5)*(UCA.AGROOTROS.VAL))} -> 8313.219 | DD39: {=SUMPRODUCT((UCA.AGROOTROS.NAME=$A39)*(UCA.AGROOTROS.DATE=DD$5)*(UCA.AGROOTROS.VAL))} -> 8620.12 | DE39: {=SUMPRODUCT((UCA.AGROOTROS.NAME=$A39)*(UCA.AGROOTROS.DATE=DE$5)*(UCA.AGROOTROS.VAL))} -> 6920.39 | DF39: {=SUMPRODUCT((UCA.AGROOTROS.NAME=$A39)*(UCA.AGROOTROS.DATE=DF$5)*(UCA.AGROOTROS.VAL))} -> 5983.436 | DG39: {=SUMPRODUCT((UCA.AGROOTROS.NAME=$A39)*(UCA.AGROOTROS.DATE=DG$5)*(UCA.AGROOTROS.VAL))} -> 4643.635 | DH39: {=SUMPRODUCT((UCA.AGROOTROS.NAME=$A39)*(UCA.AGROOTROS.DATE=DH$5)*(UCA.AGROOTROS.VAL))} -> 2453.241 | DI39: {=SUMPRODUCT((UCA.AGROOTROS.NAME=$A39)*(UCA.AGROOTROS.DATE=DI$5)*(UCA.AGROOTROS.VAL))} -> 1964.03 | ... DM39: {=SUMPRODUCT((UCA.AGROOTROS.NAME=$A39)*(UCA.AGROOTROS.DATE=DM$5)*(UCA.AGROOTROS.VAL))} -> 4068.549 | DN39: =SUM(DB39:DM39) -> 59547.784 | DO39: {=SUMPRODUCT((UCA.AGROOTROS.NAME=$A39)*(UCA.AGROOTROS.DATE=DO$5)*(UCA.AGROOTROS.VAL))} -> 4977.662 | DP39: {=SUMPRODUCT((UCA.AGROOTROS.NAME=$A39)*(UCA.AGROOTROS.DATE=DP$5)*(UCA.AGROOTROS.VAL))} -> 5494.089 | DQ39: {=SUMPRODUCT((UCA.AGROOTROS.NAME=$A39)*(UCA.AGROOTROS.DATE=DQ$5)*(UCA.AGROOTROS.VAL))} -> 5145.899 | DR39: {=SUMPRODUCT((UCA.AGROOTROS.NAME=$A39)*(UCA.AGROOTROS.DATE=DR$5)*(UCA.AGROOTROS.VAL))} -> 4733.296 | DS39: {=SUMPRODUCT((UCA.AGROOTROS.NAME=$A39)*(UCA.AGROOTROS.DATE=DS$5)*(UCA.AGROOTROS.VAL))} -> 4763.427 | DT39: {=SUMPRODUCT((UCA.AGROOTROS.NAME=$A39)*(UCA.AGROOTROS.DATE=DT$5)*(UCA.AGROOTROS.VAL))} -> 3735.02 | DU39: {=SUMPRODUCT((UCA.AGROOTROS.NAME=$A39)*(UCA.AGROOTROS.DATE=DU$5)*(UCA.AGROOTROS.VAL))} -> 2401.446 | DV39: {=SUMPRODUCT((UCA.AGROOTROS.NAME=$A39)*(UCA.AGROOTROS.DATE=DV$5)*(UCA.AGROOTROS.VAL))} -> 2513.61 | ... DZ39: {=SUMPRODUCT((UCA.AGROOTROS.NAME=$A39)*(UCA.AGROOTROS.DATE=DZ$5)*(UCA.AGROOTROS.VAL))} -> 4514.874 | EA39: =SUM(DO39:DZ39) -> 47585.792 | EB39: {=SUMPRODUCT((UCA.AGROOTROS.NAME=$A39)*(UCA.AGROOTROS.DATE=EB$5)*(UCA.AGROOTROS.VAL))} -> 4965.194 | EC39: {=SUMPRODUCT((UCA.AGROOTROS.NAME=$A39)*(UCA.AGROOTROS.DATE=EC$5)*(UCA.AGROOTROS.VAL))} -> 4602.174 | ED39: {=SUMPRODUCT((UCA.AGROOTROS.NAME=$A39)*(UCA.AGROOTROS.DATE=ED$5)*(UCA.AGROOTROS.VAL))} -> 4271.92 | EE39: {=SUMPRODUCT((UCA.AGROOTROS.NAME=$A39)*(UCA.AGROOTROS.DATE=EE$5)*(UCA.AGROOTROS.VAL))} -> 3395.378 | EF39: {=SUMPRODUCT((UCA.AGROOTROS.NAME=$A39)*(UCA.AGROOTROS.DATE=EF$5)*(UCA.AGROOTROS.VAL))} -> 3484.624 | EG39: {=SUMPRODUCT((UCA.AGROOTROS.NAME=$A39)*(UCA.AGROOTROS.DATE=EG$5)*(UCA.AGROOTROS.VAL))} -> 2750.705 | EH39: {=SUMPRODUCT((UCA.AGROOTROS.NAME=$A39)*(UCA.AGROOTROS.DATE=EH$5)*(UCA.AGROOTROS.VAL))} -> 1785.319 | EI39: {=SUMPRODUCT((UCA.AGROOTROS.NAME=$A39)*(UCA.AGROOTROS.DATE=EI$5)*(UCA.AGROOTROS.VAL))} -> 1750.687 | ... EM39: {=SUMPRODUCT((UCA.AGROOTROS.NAME=$A39)*(UCA.AGROOTROS.DATE=EM$5)*(UCA.AGROOTROS.VAL))} -> 4029.274 | EN39: =SUM(EB39:EM39) -> 40267.545 | EO39: {=SUMPRODUCT((UCA.AGROOTROS.NAME=$A39)*(UCA.AGROOTROS.DATE=EO$5)*(UCA.AGROOTROS.VAL))} -> 3929.302 | EP39: {=SUMPRODUCT((UCA.AGROOTROS.NAME=$A39)*(UCA.AGROOTROS.DATE=EP$5)*(UCA.AGROOTROS.VAL))} -> 3590.119 | EQ39: {=SUMPRODUCT((UCA.AGROOTROS.NAME=$A39)*(UCA.AGROOTROS.DATE=EQ$5)*(UCA.AGROOTROS.VAL))} -> 0 | ER39: {=SUMPRODUCT((UCA.AGROOTROS.NAME=$A39)*(UCA.AGROOTROS.DATE=ER$5)*(UCA.AGROOTROS.VAL))} -> 0 | ES39: {=SUMPRODUCT((UCA.AGROOTROS.NAME=$A39)*(UCA.AGROOTROS.DATE=ES$5)*(UCA.AGROOTROS.VAL))} -> 0 | ET39: {=SUMPRODUCT((UCA.AGROOTROS.NAME=$A39)*(UCA.AGROOTROS.DATE=ET$5)*(UCA.AGROOTROS.VAL))} -> 0 | EU39: {=SUMPRODUCT((UCA.AGROOTROS.NAME=$A39)*(UCA.AGROOTROS.DATE=EU$5)*(UCA.AGROOTROS.VAL))} -> 0 | EV39: {=SUMPRODUCT((UCA.AGROOTROS.NAME=$A39)*(UCA.AGROOTROS.DATE=EV$5)*(UCA.AGROOTROS.VAL))} -> 0 | ... EZ39: {=SUMPRODUCT((UCA.AGROOTROS.NAME=$A39)*(UCA.AGROOTROS.DATE=EZ$5)*(UCA.AGROOTROS.VAL))} -> 0 | FA39: =SUM(EO39:EZ39) -> 7519.421 | FC39: =IFERROR((( _xlfn.XLOOKUP((DATE(YEAR($FC$5),MONTH($FC$5),1)),UCA.AGRO.DATE,$B39:$FA39) / _xlfn.XLOOKUP((DATE(YEAR($FC$5)-1,MONTH($FC$5),1)),UCA.AGRO.DATE,$B39:$FA39) )-1)*100,"") -> 2.6580105 | FD39: =IFERROR(((FF39/FE39)-1)*100,"") -> -15.863713 | FE39: =SUMIFS($B39:$FA39,UCA.AGRO.DATE,">="&DATE(YEAR($FC$5)-1,1,1),UCA.AGRO.DATE,"<="&DATE(YEAR($FC$5)-1,MONTH($FC$5),1)) -> 43070.918 | FF39: =SUMIFS($B39:$FA39,UCA.AGRO.DATE,">="&DATE(YEAR($FC$5),1,1),UCA.AGRO.DATE,"<="&$FC$5) -> 36238.271 | FH39: =SUM(B39:FA39) -> 1193567.7 | FJ39: =IF(EXACT(A39,FI39)=TRUE,"OK","VER") -> VER
A40: Algodón | B40: {=SUMPRODUCT((UCA.AGROOTROS.NAME=$A40)*(UCA.AGROOTROS.DATE=B$5)*(UCA.AGROOTROS.VAL))} -> 0 | C40: {=SUMPRODUCT((UCA.AGROOTROS.NAME=$A40)*(UCA.AGROOTROS.DATE=C$5)*(UCA.AGROOTROS.VAL))} -> 0 | D40: {=SUMPRODUCT((UCA.AGROOTROS.NAME=$A40)*(UCA.AGROOTROS.DATE=D$5)*(UCA.AGROOTROS.VAL))} -> 0 | E40: {=SUMPRODUCT((UCA.AGROOTROS.NAME=$A40)*(UCA.AGROOTROS.DATE=E$5)*(UCA.AGROOTROS.VAL))} -> 0 | F40: {=SUMPRODUCT((UCA.AGROOTROS.NAME=$A40)*(UCA.AGROOTROS.DATE=F$5)*(UCA.AGROOTROS.VAL))} -> 0 | G40: {=SUMPRODUCT((UCA.AGROOTROS.NAME=$A40)*(UCA.AGROOTROS.DATE=G$5)*(UCA.AGROOTROS.VAL))} -> 0 | H40: {=SUMPRODUCT((UCA.AGROOTROS.NAME=$A40)*(UCA.AGROOTROS.DATE=H$5)*(UCA.AGROOTROS.VAL))} -> 0 | I40: {=SUMPRODUCT((UCA.AGROOTROS.NAME=$A40)*(UCA.AGROOTROS.DATE=I$5)*(UCA.AGROOTROS.VAL))} -> 6 | ... M40: {=SUMPRODUCT((UCA.AGROOTROS.NAME=$A40)*(UCA.AGROOTROS.DATE=M$5)*(UCA.AGROOTROS.VAL))} -> 0 | N40: =SUM(B40:M40) -> 101 | O40: {=SUMPRODUCT((UCA.AGROOTROS.NAME=$A40)*(UCA.AGROOTROS.DATE=O$5)*(UCA.AGROOTROS.VAL))} -> 0 | P40: {=SUMPRODUCT((UCA.AGROOTROS.NAME=$A40)*(UCA.AGROOTROS.DATE=P$5)*(UCA.AGROOTROS.VAL))} -> 0 | Q40: {=SUMPRODUCT((UCA.AGROOTROS.NAME=$A40)*(UCA.AGROOTROS.DATE=Q$5)*(UCA.AGROOTROS.VAL))} -> 0 | R40: {=SUMPRODUCT((UCA.AGROOTROS.NAME=$A40)*(UCA.AGROOTROS.DATE=R$5)*(UCA.AGROOTROS.VAL))} -> 0 | S40: {=SUMPRODUCT((UCA.AGROOTROS.NAME=$A40)*(UCA.AGROOTROS.DATE=S$5)*(UCA.AGROOTROS.VAL))} -> 0 | T40: {=SUMPRODUCT((UCA.AGROOTROS.NAME=$A40)*(UCA.AGROOTROS.DATE=T$5)*(UCA.AGROOTROS.VAL))} -> 0 | U40: {=SUMPRODUCT((UCA.AGROOTROS.NAME=$A40)*(UCA.AGROOTROS.DATE=U$5)*(UCA.AGROOTROS.VAL))} -> 0 | V40: {=SUMPRODUCT((UCA.AGROOTROS.NAME=$A40)*(UCA.AGROOTROS.DATE=V$5)*(UCA.AGROOTROS.VAL))} -> 0 | ... Z40: {=SUMPRODUCT((UCA.AGROOTROS.NAME=$A40)*(UCA.AGROOTROS.DATE=Z$5)*(UCA.AGROOTROS.VAL))} -> 0 | AA40: =SUM(O40:Z40) -> 128 | AB40: {=SUMPRODUCT((UCA.AGROOTROS.NAME=$A40)*(UCA.AGROOTROS.DATE=AB$5)*(UCA.AGROOTROS.VAL))} -> 0 | AC40: {=SUMPRODUCT((UCA.AGROOTROS.NAME=$A40)*(UCA.AGROOTROS.DATE=AC$5)*(UCA.AGROOTROS.VAL))} -> 0 | AD40: {=SUMPRODUCT((UCA.AGROOTROS.NAME=$A40)*(UCA.AGROOTROS.DATE=AD$5)*(UCA.AGROOTROS.VAL))} -> 0 | AE40: {=SUMPRODUCT((UCA.AGROOTROS.NAME=$A40)*(UCA.AGROOTROS.DATE=AE$5)*(UCA.AGROOTROS.VAL))} -> 0 | AF40: {=SUMPRODUCT((UCA.AGROOTROS.NAME=$A40)*(UCA.AGROOTROS.DATE=AF$5)*(UCA.AGROOTROS.VAL))} -> 0 | AG40: {=SUMPRODUCT((UCA.AGROOTROS.NAME=$A40)*(UCA.AGROOTROS.DATE=AG$5)*(UCA.AGROOTROS.VAL))} -> 0 | AH40: {=SUMPRODUCT((UCA.AGROOTROS.NAME=$A40)*(UCA.AGROOTROS.DATE=AH$5)*(UCA.AGROOTROS.VAL))} -> 0 | AI40: {=SUMPRODUCT((UCA.AGROOTROS.NAME=$A40)*(UCA.AGROOTROS.DATE=AI$5)*(UCA.AGROOTROS.VAL))} -> 0 | ... AM40: {=SUMPRODUCT((UCA.AGROOTROS.NAME=$A40)*(UCA.AGROOTROS.DATE=AM$5)*(UCA.AGROOTROS.VAL))} -> 0 | AN40: =SUM(AB40:AM40) -> 145 | AO40: {=SUMPRODUCT((UCA.AGROOTROS.NAME=$A40)*(UCA.AGROOTROS.DATE=AO$5)*(UCA.AGROOTROS.VAL))} -> 0 | AP40: {=SUMPRODUCT((UCA.AGROOTROS.NAME=$A40)*(UCA.AGROOTROS.DATE=AP$5)*(UCA.AGROOTROS.VAL))} -> 0 | AQ40: {=SUMPRODUCT((UCA.AGROOTROS.NAME=$A40)*(UCA.AGROOTROS.DATE=AQ$5)*(UCA.AGROOTROS.VAL))} -> 0 | AR40: {=SUMPRODUCT((UCA.AGROOTROS.NAME=$A40)*(UCA.AGROOTROS.DATE=AR$5)*(UCA.AGROOTROS.VAL))} -> 0 | AS40: {=SUMPRODUCT((UCA.AGROOTROS.NAME=$A40)*(UCA.AGROOTROS.DATE=AS$5)*(UCA.AGROOTROS.VAL))} -> 0 | AT40: {=SUMPRODUCT((UCA.AGROOTROS.NAME=$A40)*(UCA.AGROOTROS.DATE=AT$5)*(UCA.AGROOTROS.VAL))} -> 0 | AU40: {=SUMPRODUCT((UCA.AGROOTROS.NAME=$A40)*(UCA.AGROOTROS.DATE=AU$5)*(UCA.AGROOTROS.VAL))} -> 0 | AV40: {=SUMPRODUCT((UCA.AGROOTROS.NAME=$A40)*(UCA.AGROOTROS.DATE=AV$5)*(UCA.AGROOTROS.VAL))} -> 0 | ... AZ40: {=SUMPRODUCT((UCA.AGROOTROS.NAME=$A40)*(UCA.AGROOTROS.DATE=AZ$5)*(UCA.AGROOTROS.VAL))} -> 0 | BA40: =SUM(AO40:AZ40) -> 234 | BB40: {=SUMPRODUCT((UCA.AGROOTROS.NAME=$A40)*(UCA.AGROOTROS.DATE=BB$5)*(UCA.AGROOTROS.VAL))} -> 0 | BC40: {=SUMPRODUCT((UCA.AGROOTROS.NAME=$A40)*(UCA.AGROOTROS.DATE=BC$5)*(UCA.AGROOTROS.VAL))} -> 0 | BD40: {=SUMPRODUCT((UCA.AGROOTROS.NAME=$A40)*(UCA.AGROOTROS.DATE=BD$5)*(UCA.AGROOTROS.VAL))} -> 0 | BE40: {=SUMPRODUCT((UCA.AGROOTROS.NAME=$A40)*(UCA.AGROOTROS.DATE=BE$5)*(UCA.AGROOTROS.VAL))} -> 0 | BF40: {=SUMPRODUCT((UCA.AGROOTROS.NAME=$A40)*(UCA.AGROOTROS.DATE=BF$5)*(UCA.AGROOTROS.VAL))} -> 0 | BG40: {=SUMPRODUCT((UCA.AGROOTROS.NAME=$A40)*(UCA.AGROOTROS.DATE=BG$5)*(UCA.AGROOTROS.VAL))} -> 0 | BH40: {=SUMPRODUCT((UCA.AGROOTROS.NAME=$A40)*(UCA.AGROOTROS.DATE=BH$5)*(UCA.AGROOTROS.VAL))} -> 0 | BI40: {=SUMPRODUCT((UCA.AGROOTROS.NAME=$A40)*(UCA.AGROOTROS.DATE=BI$5)*(UCA.AGROOTROS.VAL))} -> 0 | ... BM40: {=SUMPRODUCT((UCA.AGROOTROS.NAME=$A40)*(UCA.AGROOTROS.DATE=BM$5)*(UCA.AGROOTROS.VAL))} -> 0 | BN40: =SUM(BB40:BM40) -> 213 | BO40: {=SUMPRODUCT((UCA.AGROOTROS.NAME=$A40)*(UCA.AGROOTROS.DATE=BO$5)*(UCA.AGROOTROS.VAL))} -> 0 | BP40: {=SUMPRODUCT((UCA.AGROOTROS.NAME=$A40)*(UCA.AGROOTROS.DATE=BP$5)*(UCA.AGROOTROS.VAL))} -> 0 | BQ40: {=SUMPRODUCT((UCA.AGROOTROS.NAME=$A40)*(UCA.AGROOTROS.DATE=BQ$5)*(UCA.AGROOTROS.VAL))} -> 0 | BR40: {=SUMPRODUCT((UCA.AGROOTROS.NAME=$A40)*(UCA.AGROOTROS.DATE=BR$5)*(UCA.AGROOTROS.VAL))} -> 0 | BS40: {=SUMPRODUCT((UCA.AGROOTROS.NAME=$A40)*(UCA.AGROOTROS.DATE=BS$5)*(UCA.AGROOTROS.VAL))} -> 0 | BT40: {=SUMPRODUCT((UCA.AGROOTROS.NAME=$A40)*(UCA.AGROOTROS.DATE=BT$5)*(UCA.AGROOTROS.VAL))} -> 0 | BU40: {=SUMPRODUCT((UCA.AGROOTROS.NAME=$A40)*(UCA.AGROOTROS.DATE=BU$5)*(UCA.AGROOTROS.VAL))} -> 0 | BV40: {=SUMPRODUCT((UCA.AGROOTROS.NAME=$A40)*(UCA.AGROOTROS.DATE=BV$5)*(UCA.AGROOTROS.VAL))} -> 0 | ... BZ40: {=SUMPRODUCT((UCA.AGROOTROS.NAME=$A40)*(UCA.AGROOTROS.DATE=BZ$5)*(UCA.AGROOTROS.VAL))} -> 0 | CA40: =SUM(BO40:BZ40) -> 183.655 | CB40: {=SUMPRODUCT((UCA.AGROOTROS.NAME=$A40)*(UCA.AGROOTROS.DATE=CB$5)*(UCA.AGROOTROS.VAL))} -> 0 | CC40: {=SUMPRODUCT((UCA.AGROOTROS.NAME=$A40)*(UCA.AGROOTROS.DATE=CC$5)*(UCA.AGROOTROS.VAL))} -> 0 | CD40: {=SUMPRODUCT((UCA.AGROOTROS.NAME=$A40)*(UCA.AGROOTROS.DATE=CD$5)*(UCA.AGROOTROS.VAL))} -> 0 | CE40: {=SUMPRODUCT((UCA.AGROOTROS.NAME=$A40)*(UCA.AGROOTROS.DATE=CE$5)*(UCA.AGROOTROS.VAL))} -> 0 | CF40: {=SUMPRODUCT((UCA.AGROOTROS.NAME=$A40)*(UCA.AGROOTROS.DATE=CF$5)*(UCA.AGROOTROS.VAL))} -> 0 | CG40: {=SUMPRODUCT((UCA.AGROOTROS.NAME=$A40)*(UCA.AGROOTROS.DATE=CG$5)*(UCA.AGROOTROS.VAL))} -> 0 | CH40: {=SUMPRODUCT((UCA.AGROOTROS.NAME=$A40)*(UCA.AGROOTROS.DATE=CH$5)*(UCA.AGROOTROS.VAL))} -> 0 | CI40: {=SUMPRODUCT((UCA.AGROOTROS.NAME=$A40)*(UCA.AGROOTROS.DATE=CI$5)*(UCA.AGROOTROS.VAL))} -> 0 | ... CM40: {=SUMPRODUCT((UCA.AGROOTROS.NAME=$A40)*(UCA.AGROOTROS.DATE=CM$5)*(UCA.AGROOTROS.VAL))} -> 0 | CN40: =SUM(CB40:CM40) -> 408.909 | CO40: {=SUMPRODUCT((UCA.AGROOTROS.NAME=$A40)*(UCA.AGROOTROS.DATE=CO$5)*(UCA.AGROOTROS.VAL))} -> 0 | CP40: {=SUMPRODUCT((UCA.AGROOTROS.NAME=$A40)*(UCA.AGROOTROS.DATE=CP$5)*(UCA.AGROOTROS.VAL))} -> 0 | CQ40: {=SUMPRODUCT((UCA.AGROOTROS.NAME=$A40)*(UCA.AGROOTROS.DATE=CQ$5)*(UCA.AGROOTROS.VAL))} -> 0 | CR40: {=SUMPRODUCT((UCA.AGROOTROS.NAME=$A40)*(UCA.AGROOTROS.DATE=CR$5)*(UCA.AGROOTROS.VAL))} -> 0 | CS40: {=SUMPRODUCT((UCA.AGROOTROS.NAME=$A40)*(UCA.AGROOTROS.DATE=CS$5)*(UCA.AGROOTROS.VAL))} -> 0 | CT40: {=SUMPRODUCT((UCA.AGROOTROS.NAME=$A40)*(UCA.AGROOTROS.DATE=CT$5)*(UCA.AGROOTROS.VAL))} -> 0 | CU40: {=SUMPRODUCT((UCA.AGROOTROS.NAME=$A40)*(UCA.AGROOTROS.DATE=CU$5)*(UCA.AGROOTROS.VAL))} -> 0 | CV40: {=SUMPRODUCT((UCA.AGROOTROS.NAME=$A40)*(UCA.AGROOTROS.DATE=CV$5)*(UCA.AGROOTROS.VAL))} -> 0 | ... CZ40: {=SUMPRODUCT((UCA.AGROOTROS.NAME=$A40)*(UCA.AGROOTROS.DATE=CZ$5)*(UCA.AGROOTROS.VAL))} -> 2.104 | DA40: =SUM(CO40:CZ40) -> 355.263 | DB40: {=SUMPRODUCT((UCA.AGROOTROS.NAME=$A40)*(UCA.AGROOTROS.DATE=DB$5)*(UCA.AGROOTROS.VAL))} -> 0 | DC40: {=SUMPRODUCT((UCA.AGROOTROS.NAME=$A40)*(UCA.AGROOTROS.DATE=DC$5)*(UCA.AGROOTROS.VAL))} -> 0 | DD40: {=SUMPRODUCT((UCA.AGROOTROS.NAME=$A40)*(UCA.AGROOTROS.DATE=DD$5)*(UCA.AGROOTROS.VAL))} -> 0 | DE40: {=SUMPRODUCT((UCA.AGROOTROS.NAME=$A40)*(UCA.AGROOTROS.DATE=DE$5)*(UCA.AGROOTROS.VAL))} -> 0 | DF40: {=SUMPRODUCT((UCA.AGROOTROS.NAME=$A40)*(UCA.AGROOTROS.DATE=DF$5)*(UCA.AGROOTROS.VAL))} -> 0 | DG40: {=SUMPRODUCT((UCA.AGROOTROS.NAME=$A40)*(UCA.AGROOTROS.DATE=DG$5)*(UCA.AGROOTROS.VAL))} -> 0 | DH40: {=SUMPRODUCT((UCA.AGROOTROS.NAME=$A40)*(UCA.AGROOTROS.DATE=DH$5)*(UCA.AGROOTROS.VAL))} -> 0 | DI40: {=SUMPRODUCT((UCA.AGROOTROS.NAME=$A40)*(UCA.AGROOTROS.DATE=DI$5)*(UCA.AGROOTROS.VAL))} -> 0 | ... DM40: {=SUMPRODUCT((UCA.AGROOTROS.NAME=$A40)*(UCA.AGROOTROS.DATE=DM$5)*(UCA.AGROOTROS.VAL))} -> 0 | DN40: =SUM(DB40:DM40) -> 366.253 | DO40: {=SUMPRODUCT((UCA.AGROOTROS.NAME=$A40)*(UCA.AGROOTROS.DATE=DO$5)*(UCA.AGROOTROS.VAL))} -> 0 | DP40: {=SUMPRODUCT((UCA.AGROOTROS.NAME=$A40)*(UCA.AGROOTROS.DATE=DP$5)*(UCA.AGROOTROS.VAL))} -> 0 | DQ40: {=SUMPRODUCT((UCA.AGROOTROS.NAME=$A40)*(UCA.AGROOTROS.DATE=DQ$5)*(UCA.AGROOTROS.VAL))} -> 0 | DR40: {=SUMPRODUCT((UCA.AGROOTROS.NAME=$A40)*(UCA.AGROOTROS.DATE=DR$5)*(UCA.AGROOTROS.VAL))} -> 0 | DS40: {=SUMPRODUCT((UCA.AGROOTROS.NAME=$A40)*(UCA.AGROOTROS.DATE=DS$5)*(UCA.AGROOTROS.VAL))} -> 0 | DT40: {=SUMPRODUCT((UCA.AGROOTROS.NAME=$A40)*(UCA.AGROOTROS.DATE=DT$5)*(UCA.AGROOTROS.VAL))} -> 0 | DU40: {=SUMPRODUCT((UCA.AGROOTROS.NAME=$A40)*(UCA.AGROOTROS.DATE=DU$5)*(UCA.AGROOTROS.VAL))} -> 0 | DV40: {=SUMPRODUCT((UCA.AGROOTROS.NAME=$A40)*(UCA.AGROOTROS.DATE=DV$5)*(UCA.AGROOTROS.VAL))} -> 0 | ... DZ40: {=SUMPRODUCT((UCA.AGROOTROS.NAME=$A40)*(UCA.AGROOTROS.DATE=DZ$5)*(UCA.AGROOTROS.VAL))} -> 0 | EA40: =SUM(DO40:DZ40) -> 362.517 | EB40: {=SUMPRODUCT((UCA.AGROOTROS.NAME=$A40)*(UCA.AGROOTROS.DATE=EB$5)*(UCA.AGROOTROS.VAL))} -> 0 | EC40: {=SUMPRODUCT((UCA.AGROOTROS.NAME=$A40)*(UCA.AGROOTROS.DATE=EC$5)*(UCA.AGROOTROS.VAL))} -> 0 | ED40: {=SUMPRODUCT((UCA.AGROOTROS.NAME=$A40)*(UCA.AGROOTROS.DATE=ED$5)*(UCA.AGROOTROS.VAL))} -> 0 | EE40: {=SUMPRODUCT((UCA.AGROOTROS.NAME=$A40)*(UCA.AGROOTROS.DATE=EE$5)*(UCA.AGROOTROS.VAL))} -> 0 | EF40: {=SUMPRODUCT((UCA.AGROOTROS.NAME=$A40)*(UCA.AGROOTROS.DATE=EF$5)*(UCA.AGROOTROS.VAL))} -> 0 | EG40: {=SUMPRODUCT((UCA.AGROOTROS.NAME=$A40)*(UCA.AGROOTROS.DATE=EG$5)*(UCA.AGROOTROS.VAL))} -> 0 | EH40: {=SUMPRODUCT((UCA.AGROOTROS.NAME=$A40)*(UCA.AGROOTROS.DATE=EH$5)*(UCA.AGROOTROS.VAL))} -> 0 | EI40: {=SUMPRODUCT((UCA.AGROOTROS.NAME=$A40)*(UCA.AGROOTROS.DATE=EI$5)*(UCA.AGROOTROS.VAL))} -> 0 | ... EM40: {=SUMPRODUCT((UCA.AGROOTROS.NAME=$A40)*(UCA.AGROOTROS.DATE=EM$5)*(UCA.AGROOTROS.VAL))} -> 0 | EN40: =SUM(EB40:EM40) -> 500.901 | EO40: {=SUMPRODUCT((UCA.AGROOTROS.NAME=$A40)*(UCA.AGROOTROS.DATE=EO$5)*(UCA.AGROOTROS.VAL))} -> 0 | EP40: {=SUMPRODUCT((UCA.AGROOTROS.NAME=$A40)*(UCA.AGROOTROS.DATE=EP$5)*(UCA.AGROOTROS.VAL))} -> 0 | EQ40: {=SUMPRODUCT((UCA.AGROOTROS.NAME=$A40)*(UCA.AGROOTROS.DATE=EQ$5)*(UCA.AGROOTROS.VAL))} -> 0 | ER40: {=SUMPRODUCT((UCA.AGROOTROS.NAME=$A40)*(UCA.AGROOTROS.DATE=ER$5)*(UCA.AGROOTROS.VAL))} -> 0 | ES40: {=SUMPRODUCT((UCA.AGROOTROS.NAME=$A40)*(UCA.AGROOTROS.DATE=ES$5)*(UCA.AGROOTROS.VAL))} -> 0 | ET40: {=SUMPRODUCT((UCA.AGROOTROS.NAME=$A40)*(UCA.AGROOTROS.DATE=ET$5)*(UCA.AGROOTROS.VAL))} -> 0 | EU40: {=SUMPRODUCT((UCA.AGROOTROS.NAME=$A40)*(UCA.AGROOTROS.DATE=EU$5)*(UCA.AGROOTROS.VAL))} -> 0 | EV40: {=SUMPRODUCT((UCA.AGROOTROS.NAME=$A40)*(UCA.AGROOTROS.DATE=EV$5)*(UCA.AGROOTROS.VAL))} -> 0 | ... EZ40: {=SUMPRODUCT((UCA.AGROOTROS.NAME=$A40)*(UCA.AGROOTROS.DATE=EZ$5)*(UCA.AGROOTROS.VAL))} -> 0 | FA40: =SUM(EO40:EZ40) -> 0 | FC40: =IFERROR((( _xlfn.XLOOKUP((DATE(YEAR($FC$5),MONTH($FC$5),1)),UCA.AGRO.DATE,$B40:$FA40) / _xlfn.XLOOKUP((DATE(YEAR($FC$5)-1,MONTH($FC$5),1)),UCA.AGRO.DATE,$B40:$FA40) )-1)*100,"") -> 1.7637618 | FD40: =IFERROR(((FF40/FE40)-1)*100,"") -> 38.173106 | FE40: =SUMIFS($B40:$FA40,UCA.AGRO.DATE,">="&DATE(YEAR($FC$5)-1,1,1),UCA.AGRO.DATE,"<="&DATE(YEAR($FC$5)-1,MONTH($FC$5),1)) -> 362.517 | FF40: =SUMIFS($B40:$FA40,UCA.AGRO.DATE,">="&DATE(YEAR($FC$5),1,1),UCA.AGRO.DATE,"<="&$FC$5) -> 500.901 | FH40: =SUM(B40:FA40) -> 5996.996 | FJ40: =IF(EXACT(A40,FI40)=TRUE,"OK","VER") -> VER
A41: Cocona | B41: {=SUMPRODUCT((UCA.AGROOTROS.NAME=$A41)*(UCA.AGROOTROS.DATE=B$5)*(UCA.AGROOTROS.VAL))} -> 229 | C41: {=SUMPRODUCT((UCA.AGROOTROS.NAME=$A41)*(UCA.AGROOTROS.DATE=C$5)*(UCA.AGROOTROS.VAL))} -> 242 | D41: {=SUMPRODUCT((UCA.AGROOTROS.NAME=$A41)*(UCA.AGROOTROS.DATE=D$5)*(UCA.AGROOTROS.VAL))} -> 185 | E41: {=SUMPRODUCT((UCA.AGROOTROS.NAME=$A41)*(UCA.AGROOTROS.DATE=E$5)*(UCA.AGROOTROS.VAL))} -> 131 | F41: {=SUMPRODUCT((UCA.AGROOTROS.NAME=$A41)*(UCA.AGROOTROS.DATE=F$5)*(UCA.AGROOTROS.VAL))} -> 131 | G41: {=SUMPRODUCT((UCA.AGROOTROS.NAME=$A41)*(UCA.AGROOTROS.DATE=G$5)*(UCA.AGROOTROS.VAL))} -> 120 | H41: {=SUMPRODUCT((UCA.AGROOTROS.NAME=$A41)*(UCA.AGROOTROS.DATE=H$5)*(UCA.AGROOTROS.VAL))} -> 97 | I41: {=SUMPRODUCT((UCA.AGROOTROS.NAME=$A41)*(UCA.AGROOTROS.DATE=I$5)*(UCA.AGROOTROS.VAL))} -> 121 | ... M41: {=SUMPRODUCT((UCA.AGROOTROS.NAME=$A41)*(UCA.AGROOTROS.DATE=M$5)*(UCA.AGROOTROS.VAL))} -> 153 | N41: =SUM(B41:M41) -> 1824 | O41: {=SUMPRODUCT((UCA.AGROOTROS.NAME=$A41)*(UCA.AGROOTROS.DATE=O$5)*(UCA.AGROOTROS.VAL))} -> 143 | P41: {=SUMPRODUCT((UCA.AGROOTROS.NAME=$A41)*(UCA.AGROOTROS.DATE=P$5)*(UCA.AGROOTROS.VAL))} -> 178 | Q41: {=SUMPRODUCT((UCA.AGROOTROS.NAME=$A41)*(UCA.AGROOTROS.DATE=Q$5)*(UCA.AGROOTROS.VAL))} -> 153 | R41: {=SUMPRODUCT((UCA.AGROOTROS.NAME=$A41)*(UCA.AGROOTROS.DATE=R$5)*(UCA.AGROOTROS.VAL))} -> 97 | S41: {=SUMPRODUCT((UCA.AGROOTROS.NAME=$A41)*(UCA.AGROOTROS.DATE=S$5)*(UCA.AGROOTROS.VAL))} -> 83 | T41: {=SUMPRODUCT((UCA.AGROOTROS.NAME=$A41)*(UCA.AGROOTROS.DATE=T$5)*(UCA.AGROOTROS.VAL))} -> 92 | U41: {=SUMPRODUCT((UCA.AGROOTROS.NAME=$A41)*(UCA.AGROOTROS.DATE=U$5)*(UCA.AGROOTROS.VAL))} -> 65 | V41: {=SUMPRODUCT((UCA.AGROOTROS.NAME=$A41)*(UCA.AGROOTROS.DATE=V$5)*(UCA.AGROOTROS.VAL))} -> 55 | ... Z41: {=SUMPRODUCT((UCA.AGROOTROS.NAME=$A41)*(UCA.AGROOTROS.DATE=Z$5)*(UCA.AGROOTROS.VAL))} -> 127 | AA41: =SUM(O41:Z41) -> 1260 | AB41: {=SUMPRODUCT((UCA.AGROOTROS.NAME=$A41)*(UCA.AGROOTROS.DATE=AB$5)*(UCA.AGROOTROS.VAL))} -> 123 | AC41: {=SUMPRODUCT((UCA.AGROOTROS.NAME=$A41)*(UCA.AGROOTROS.DATE=AC$5)*(UCA.AGROOTROS.VAL))} -> 144 | AD41: {=SUMPRODUCT((UCA.AGROOTROS.NAME=$A41)*(UCA.AGROOTROS.DATE=AD$5)*(UCA.AGROOTROS.VAL))} -> 134 | AE41: {=SUMPRODUCT((UCA.AGROOTROS.NAME=$A41)*(UCA.AGROOTROS.DATE=AE$5)*(UCA.AGROOTROS.VAL))} -> 91 | AF41: {=SUMPRODUCT((UCA.AGROOTROS.NAME=$A41)*(UCA.AGROOTROS.DATE=AF$5)*(UCA.AGROOTROS.VAL))} -> 87 | AG41: {=SUMPRODUCT((UCA.AGROOTROS.NAME=$A41)*(UCA.AGROOTROS.DATE=AG$5)*(UCA.AGROOTROS.VAL))} -> 88 | AH41: {=SUMPRODUCT((UCA.AGROOTROS.NAME=$A41)*(UCA.AGROOTROS.DATE=AH$5)*(UCA.AGROOTROS.VAL))} -> 66 | AI41: {=SUMPRODUCT((UCA.AGROOTROS.NAME=$A41)*(UCA.AGROOTROS.DATE=AI$5)*(UCA.AGROOTROS.VAL))} -> 51 | ... AM41: {=SUMPRODUCT((UCA.AGROOTROS.NAME=$A41)*(UCA.AGROOTROS.DATE=AM$5)*(UCA.AGROOTROS.VAL))} -> 123 | AN41: =SUM(AB41:AM41) -> 1111 | AO41: {=SUMPRODUCT((UCA.AGROOTROS.NAME=$A41)*(UCA.AGROOTROS.DATE=AO$5)*(UCA.AGROOTROS.VAL))} -> 104 | AP41: {=SUMPRODUCT((UCA.AGROOTROS.NAME=$A41)*(UCA.AGROOTROS.DATE=AP$5)*(UCA.AGROOTROS.VAL))} -> 97 | AQ41: {=SUMPRODUCT((UCA.AGROOTROS.NAME=$A41)*(UCA.AGROOTROS.DATE=AQ$5)*(UCA.AGROOTROS.VAL))} -> 119 | AR41: {=SUMPRODUCT((UCA.AGROOTROS.NAME=$A41)*(UCA.AGROOTROS.DATE=AR$5)*(UCA.AGROOTROS.VAL))} -> 101 | AS41: {=SUMPRODUCT((UCA.AGROOTROS.NAME=$A41)*(UCA.AGROOTROS.DATE=AS$5)*(UCA.AGROOTROS.VAL))} -> 77 | AT41: {=SUMPRODUCT((UCA.AGROOTROS.NAME=$A41)*(UCA.AGROOTROS.DATE=AT$5)*(UCA.AGROOTROS.VAL))} -> 75 | AU41: {=SUMPRODUCT((UCA.AGROOTROS.NAME=$A41)*(UCA.AGROOTROS.DATE=AU$5)*(UCA.AGROOTROS.VAL))} -> 72 | AV41: {=SUMPRODUCT((UCA.AGROOTROS.NAME=$A41)*(UCA.AGROOTROS.DATE=AV$5)*(UCA.AGROOTROS.VAL))} -> 56 | ... AZ41: {=SUMPRODUCT((UCA.AGROOTROS.NAME=$A41)*(UCA.AGROOTROS.DATE=AZ$5)*(UCA.AGROOTROS.VAL))} -> 61 | BA41: =SUM(AO41:AZ41) -> 929 | BB41: {=SUMPRODUCT((UCA.AGROOTROS.NAME=$A41)*(UCA.AGROOTROS.DATE=BB$5)*(UCA.AGROOTROS.VAL))} -> 54 | BC41: {=SUMPRODUCT((UCA.AGROOTROS.NAME=$A41)*(UCA.AGROOTROS.DATE=BC$5)*(UCA.AGROOTROS.VAL))} -> 43 | BD41: {=SUMPRODUCT((UCA.AGROOTROS.NAME=$A41)*(UCA.AGROOTROS.DATE=BD$5)*(UCA.AGROOTROS.VAL))} -> 45 | BE41: {=SUMPRODUCT((UCA.AGROOTROS.NAME=$A41)*(UCA.AGROOTROS.DATE=BE$5)*(UCA.AGROOTROS.VAL))} -> 36 | BF41: {=SUMPRODUCT((UCA.AGROOTROS.NAME=$A41)*(UCA.AGROOTROS.DATE=BF$5)*(UCA.AGROOTROS.VAL))} -> 33 | BG41: {=SUMPRODUCT((UCA.AGROOTROS.NAME=$A41)*(UCA.AGROOTROS.DATE=BG$5)*(UCA.AGROOTROS.VAL))} -> 46 | BH41: {=SUMPRODUCT((UCA.AGROOTROS.NAME=$A41)*(UCA.AGROOTROS.DATE=BH$5)*(UCA.AGROOTROS.VAL))} -> 57 | BI41: {=SUMPRODUCT((UCA.AGROOTROS.NAME=$A41)*(UCA.AGROOTROS.DATE=BI$5)*(UCA.AGROOTROS.VAL))} -> 56 | ... BM41: {=SUMPRODUCT((UCA.AGROOTROS.NAME=$A41)*(UCA.AGROOTROS.DATE=BM$5)*(UCA.AGROOTROS.VAL))} -> 68 | BN41: =SUM(BB41:BM41) -> 578 | BO41: {=SUMPRODUCT((UCA.AGROOTROS.NAME=$A41)*(UCA.AGROOTROS.DATE=BO$5)*(UCA.AGROOTROS.VAL))} -> 186 | BP41: {=SUMPRODUCT((UCA.AGROOTROS.NAME=$A41)*(UCA.AGROOTROS.DATE=BP$5)*(UCA.AGROOTROS.VAL))} -> 223 | BQ41: {=SUMPRODUCT((UCA.AGROOTROS.NAME=$A41)*(UCA.AGROOTROS.DATE=BQ$5)*(UCA.AGROOTROS.VAL))} -> 211 | BR41: {=SUMPRODUCT((UCA.AGROOTROS.NAME=$A41)*(UCA.AGROOTROS.DATE=BR$5)*(UCA.AGROOTROS.VAL))} -> 285 | BS41: {=SUMPRODUCT((UCA.AGROOTROS.NAME=$A41)*(UCA.AGROOTROS.DATE=BS$5)*(UCA.AGROOTROS.VAL))} -> 345.228 | BT41: {=SUMPRODUCT((UCA.AGROOTROS.NAME=$A41)*(UCA.AGROOTROS.DATE=BT$5)*(UCA.AGROOTROS.VAL))} -> 339 | BU41: {=SUMPRODUCT((UCA.AGROOTROS.NAME=$A41)*(UCA.AGROOTROS.DATE=BU$5)*(UCA.AGROOTROS.VAL))} -> 382 | BV41: {=SUMPRODUCT((UCA.AGROOTROS.NAME=$A41)*(UCA.AGROOTROS.DATE=BV$5)*(UCA.AGROOTROS.VAL))} -> 472 | ... BZ41: {=SUMPRODUCT((UCA.AGROOTROS.NAME=$A41)*(UCA.AGROOTROS.DATE=BZ$5)*(UCA.AGROOTROS.VAL))} -> 389 | CA41: =SUM(BO41:BZ41) -> 3997.228 | CB41: {=SUMPRODUCT((UCA.AGROOTROS.NAME=$A41)*(UCA.AGROOTROS.DATE=CB$5)*(UCA.AGROOTROS.VAL))} -> 356.008 | CC41: {=SUMPRODUCT((UCA.AGROOTROS.NAME=$A41)*(UCA.AGROOTROS.DATE=CC$5)*(UCA.AGROOTROS.VAL))} -> 251.448 | CD41: {=SUMPRODUCT((UCA.AGROOTROS.NAME=$A41)*(UCA.AGROOTROS.DATE=CD$5)*(UCA.AGROOTROS.VAL))} -> 202.649 | CE41: {=SUMPRODUCT((UCA.AGROOTROS.NAME=$A41)*(UCA.AGROOTROS.DATE=CE$5)*(UCA.AGROOTROS.VAL))} -> 286.65 | CF41: {=SUMPRODUCT((UCA.AGROOTROS.NAME=$A41)*(UCA.AGROOTROS.DATE=CF$5)*(UCA.AGROOTROS.VAL))} -> 376.139 | CG41: {=SUMPRODUCT((UCA.AGROOTROS.NAME=$A41)*(UCA.AGROOTROS.DATE=CG$5)*(UCA.AGROOTROS.VAL))} -> 345.38 | CH41: {=SUMPRODUCT((UCA.AGROOTROS.NAME=$A41)*(UCA.AGROOTROS.DATE=CH$5)*(UCA.AGROOTROS.VAL))} -> 328.776 | CI41: {=SUMPRODUCT((UCA.AGROOTROS.NAME=$A41)*(UCA.AGROOTROS.DATE=CI$5)*(UCA.AGROOTROS.VAL))} -> 292.218 | ... CM41: {=SUMPRODUCT((UCA.AGROOTROS.NAME=$A41)*(UCA.AGROOTROS.DATE=CM$5)*(UCA.AGROOTROS.VAL))} -> 404.01 | CN41: =SUM(CB41:CM41) -> 3872.225 | CO41: {=SUMPRODUCT((UCA.AGROOTROS.NAME=$A41)*(UCA.AGROOTROS.DATE=CO$5)*(UCA.AGROOTROS.VAL))} -> 311.558 | CP41: {=SUMPRODUCT((UCA.AGROOTROS.NAME=$A41)*(UCA.AGROOTROS.DATE=CP$5)*(UCA.AGROOTROS.VAL))} -> 241.303 | CQ41: {=SUMPRODUCT((UCA.AGROOTROS.NAME=$A41)*(UCA.AGROOTROS.DATE=CQ$5)*(UCA.AGROOTROS.VAL))} -> 166.117 | CR41: {=SUMPRODUCT((UCA.AGROOTROS.NAME=$A41)*(UCA.AGROOTROS.DATE=CR$5)*(UCA.AGROOTROS.VAL))} -> 246.728 | CS41: {=SUMPRODUCT((UCA.AGROOTROS.NAME=$A41)*(UCA.AGROOTROS.DATE=CS$5)*(UCA.AGROOTROS.VAL))} -> 261.614 | CT41: {=SUMPRODUCT((UCA.AGROOTROS.NAME=$A41)*(UCA.AGROOTROS.DATE=CT$5)*(UCA.AGROOTROS.VAL))} -> 277.06 | CU41: {=SUMPRODUCT((UCA.AGROOTROS.NAME=$A41)*(UCA.AGROOTROS.DATE=CU$5)*(UCA.AGROOTROS.VAL))} -> 276.227 | CV41: {=SUMPRODUCT((UCA.AGROOTROS.NAME=$A41)*(UCA.AGROOTROS.DATE=CV$5)*(UCA.AGROOTROS.VAL))} -> 372.917 | ... CZ41: {=SUMPRODUCT((UCA.AGROOTROS.NAME=$A41)*(UCA.AGROOTROS.DATE=CZ$5)*(UCA.AGROOTROS.VAL))} -> 220.588 | DA41: =SUM(CO41:CZ41) -> 3255.815 | DB41: {=SUMPRODUCT((UCA.AGROOTROS.NAME=$A41)*(UCA.AGROOTROS.DATE=DB$5)*(UCA.AGROOTROS.VAL))} -> 260.465 | DC41: {=SUMPRODUCT((UCA.AGROOTROS.NAME=$A41)*(UCA.AGROOTROS.DATE=DC$5)*(UCA.AGROOTROS.VAL))} -> 215.905 | DD41: {=SUMPRODUCT((UCA.AGROOTROS.NAME=$A41)*(UCA.AGROOTROS.DATE=DD$5)*(UCA.AGROOTROS.VAL))} -> 169.57 | DE41: {=SUMPRODUCT((UCA.AGROOTROS.NAME=$A41)*(UCA.AGROOTROS.DATE=DE$5)*(UCA.AGROOTROS.VAL))} -> 214.341 | DF41: {=SUMPRODUCT((UCA.AGROOTROS.NAME=$A41)*(UCA.AGROOTROS.DATE=DF$5)*(UCA.AGROOTROS.VAL))} -> 317.568 | DG41: {=SUMPRODUCT((UCA.AGROOTROS.NAME=$A41)*(UCA.AGROOTROS.DATE=DG$5)*(UCA.AGROOTROS.VAL))} -> 393.637 | DH41: {=SUMPRODUCT((UCA.AGROOTROS.NAME=$A41)*(UCA.AGROOTROS.DATE=DH$5)*(UCA.AGROOTROS.VAL))} -> 384.305 | DI41: {=SUMPRODUCT((UCA.AGROOTROS.NAME=$A41)*(UCA.AGROOTROS.DATE=DI$5)*(UCA.AGROOTROS.VAL))} -> 360.34 | ... DM41: {=SUMPRODUCT((UCA.AGROOTROS.NAME=$A41)*(UCA.AGROOTROS.DATE=DM$5)*(UCA.AGROOTROS.VAL))} -> 217.015 | DN41: =SUM(DB41:DM41) -> 3531.68 | DO41: {=SUMPRODUCT((UCA.AGROOTROS.NAME=$A41)*(UCA.AGROOTROS.DATE=DO$5)*(UCA.AGROOTROS.VAL))} -> 176.279 | DP41: {=SUMPRODUCT((UCA.AGROOTROS.NAME=$A41)*(UCA.AGROOTROS.DATE=DP$5)*(UCA.AGROOTROS.VAL))} -> 141.909 | DQ41: {=SUMPRODUCT((UCA.AGROOTROS.NAME=$A41)*(UCA.AGROOTROS.DATE=DQ$5)*(UCA.AGROOTROS.VAL))} -> 106.678 | DR41: {=SUMPRODUCT((UCA.AGROOTROS.NAME=$A41)*(UCA.AGROOTROS.DATE=DR$5)*(UCA.AGROOTROS.VAL))} -> 72.258 | DS41: {=SUMPRODUCT((UCA.AGROOTROS.NAME=$A41)*(UCA.AGROOTROS.DATE=DS$5)*(UCA.AGROOTROS.VAL))} -> 104.79 | DT41: {=SUMPRODUCT((UCA.AGROOTROS.NAME=$A41)*(UCA.AGROOTROS.DATE=DT$5)*(UCA.AGROOTROS.VAL))} -> 172.749 | DU41: {=SUMPRODUCT((UCA.AGROOTROS.NAME=$A41)*(UCA.AGROOTROS.DATE=DU$5)*(UCA.AGROOTROS.VAL))} -> 257.499 | DV41: {=SUMPRODUCT((UCA.AGROOTROS.NAME=$A41)*(UCA.AGROOTROS.DATE=DV$5)*(UCA.AGROOTROS.VAL))} -> 348.538 | ... DZ41: {=SUMPRODUCT((UCA.AGROOTROS.NAME=$A41)*(UCA.AGROOTROS.DATE=DZ$5)*(UCA.AGROOTROS.VAL))} -> 173.64 | EA41: =SUM(DO41:DZ41) -> 2465.938 | EB41: {=SUMPRODUCT((UCA.AGROOTROS.NAME=$A41)*(UCA.AGROOTROS.DATE=EB$5)*(UCA.AGROOTROS.VAL))} -> 134.31 | EC41: {=SUMPRODUCT((UCA.AGROOTROS.NAME=$A41)*(UCA.AGROOTROS.DATE=EC$5)*(UCA.AGROOTROS.VAL))} -> 104.574 | ED41: {=SUMPRODUCT((UCA.AGROOTROS.NAME=$A41)*(UCA.AGROOTROS.DATE=ED$5)*(UCA.AGROOTROS.VAL))} -> 73.1 | EE41: {=SUMPRODUCT((UCA.AGROOTROS.NAME=$A41)*(UCA.AGROOTROS.DATE=EE$5)*(UCA.AGROOTROS.VAL))} -> 42.83 | EF41: {=SUMPRODUCT((UCA.AGROOTROS.NAME=$A41)*(UCA.AGROOTROS.DATE=EF$5)*(UCA.AGROOTROS.VAL))} -> 98.619 | EG41: {=SUMPRODUCT((UCA.AGROOTROS.NAME=$A41)*(UCA.AGROOTROS.DATE=EG$5)*(UCA.AGROOTROS.VAL))} -> 156.273 | EH41: {=SUMPRODUCT((UCA.AGROOTROS.NAME=$A41)*(UCA.AGROOTROS.DATE=EH$5)*(UCA.AGROOTROS.VAL))} -> 294.869 | EI41: {=SUMPRODUCT((UCA.AGROOTROS.NAME=$A41)*(UCA.AGROOTROS.DATE=EI$5)*(UCA.AGROOTROS.VAL))} -> 302.042 | ... EM41: {=SUMPRODUCT((UCA.AGROOTROS.NAME=$A41)*(UCA.AGROOTROS.DATE=EM$5)*(UCA.AGROOTROS.VAL))} -> 383.16 | EN41: =SUM(EB41:EM41) -> 2577.35 | EO41: {=SUMPRODUCT((UCA.AGROOTROS.NAME=$A41)*(UCA.AGROOTROS.DATE=EO$5)*(UCA.AGROOTROS.VAL))} -> 320.138 | EP41: {=SUMPRODUCT((UCA.AGROOTROS.NAME=$A41)*(UCA.AGROOTROS.DATE=EP$5)*(UCA.AGROOTROS.VAL))} -> 264.227 | EQ41: {=SUMPRODUCT((UCA.AGROOTROS.NAME=$A41)*(UCA.AGROOTROS.DATE=EQ$5)*(UCA.AGROOTROS.VAL))} -> 0 | ER41: {=SUMPRODUCT((UCA.AGROOTROS.NAME=$A41)*(UCA.AGROOTROS.DATE=ER$5)*(UCA.AGROOTROS.VAL))} -> 0 | ES41: {=SUMPRODUCT((UCA.AGROOTROS.NAME=$A41)*(UCA.AGROOTROS.DATE=ES$5)*(UCA.AGROOTROS.VAL))} -> 0 | ET41: {=SUMPRODUCT((UCA.AGROOTROS.NAME=$A41)*(UCA.AGROOTROS.DATE=ET$5)*(UCA.AGROOTROS.VAL))} -> 0 | EU41: {=SUMPRODUCT((UCA.AGROOTROS.NAME=$A41)*(UCA.AGROOTROS.DATE=EU$5)*(UCA.AGROOTROS.VAL))} -> 0 | EV41: {=SUMPRODUCT((UCA.AGROOTROS.NAME=$A41)*(UCA.AGROOTROS.DATE=EV$5)*(UCA.AGROOTROS.VAL))} -> 0 | ... EZ41: {=SUMPRODUCT((UCA.AGROOTROS.NAME=$A41)*(UCA.AGROOTROS.DATE=EZ$5)*(UCA.AGROOTROS.VAL))} -> 0 | FA41: =SUM(EO41:EZ41) -> 584.365 | FC41: =IFERROR((( _xlfn.XLOOKUP((DATE(YEAR($FC$5),MONTH($FC$5),1)),UCA.AGRO.DATE,$B41:$FA41) / _xlfn.XLOOKUP((DATE(YEAR($FC$5)-1,MONTH($FC$5),1)),UCA.AGRO.DATE,$B41:$FA41) )-1)*100,"") -> 47.263005 | FD41: =IFERROR(((FF41/FE41)-1)*100,"") -> -4.2798973 | FE41: =SUMIFS($B41:$FA41,UCA.AGRO.DATE,">="&DATE(YEAR($FC$5)-1,1,1),UCA.AGRO.DATE,"<="&DATE(YEAR($FC$5)-1,MONTH($FC$5),1)) -> 2292.298 | FF41: =SUMIFS($B41:$FA41,UCA.AGRO.DATE,">="&DATE(YEAR($FC$5),1,1),UCA.AGRO.DATE,"<="&$FC$5) -> 2194.19 | FH41: =SUM(B41:FA41) -> 51973.202 | FJ41: =IF(EXACT(A41,FI41)=TRUE,"OK","VER") -> VER
A42: Melón | B42: {=SUMPRODUCT((UCA.AGROOTROS.NAME=$A42)*(UCA.AGROOTROS.DATE=B$5)*(UCA.AGROOTROS.VAL))} -> 0 | C42: {=SUMPRODUCT((UCA.AGROOTROS.NAME=$A42)*(UCA.AGROOTROS.DATE=C$5)*(UCA.AGROOTROS.VAL))} -> 0 | D42: {=SUMPRODUCT((UCA.AGROOTROS.NAME=$A42)*(UCA.AGROOTROS.DATE=D$5)*(UCA.AGROOTROS.VAL))} -> 0 | E42: {=SUMPRODUCT((UCA.AGROOTROS.NAME=$A42)*(UCA.AGROOTROS.DATE=E$5)*(UCA.AGROOTROS.VAL))} -> 0 | F42: {=SUMPRODUCT((UCA.AGROOTROS.NAME=$A42)*(UCA.AGROOTROS.DATE=F$5)*(UCA.AGROOTROS.VAL))} -> 0 | G42: {=SUMPRODUCT((UCA.AGROOTROS.NAME=$A42)*(UCA.AGROOTROS.DATE=G$5)*(UCA.AGROOTROS.VAL))} -> 0 | H42: {=SUMPRODUCT((UCA.AGROOTROS.NAME=$A42)*(UCA.AGROOTROS.DATE=H$5)*(UCA.AGROOTROS.VAL))} -> 0 | I42: {=SUMPRODUCT((UCA.AGROOTROS.NAME=$A42)*(UCA.AGROOTROS.DATE=I$5)*(UCA.AGROOTROS.VAL))} -> 508 | ... M42: {=SUMPRODUCT((UCA.AGROOTROS.NAME=$A42)*(UCA.AGROOTROS.DATE=M$5)*(UCA.AGROOTROS.VAL))} -> 35 | N42: =SUM(B42:M42) -> 1932 | O42: {=SUMPRODUCT((UCA.AGROOTROS.NAME=$A42)*(UCA.AGROOTROS.DATE=O$5)*(UCA.AGROOTROS.VAL))} -> 39 | P42: {=SUMPRODUCT((UCA.AGROOTROS.NAME=$A42)*(UCA.AGROOTROS.DATE=P$5)*(UCA.AGROOTROS.VAL))} -> 35 | Q42: {=SUMPRODUCT((UCA.AGROOTROS.NAME=$A42)*(UCA.AGROOTROS.DATE=Q$5)*(UCA.AGROOTROS.VAL))} -> 0 | R42: {=SUMPRODUCT((UCA.AGROOTROS.NAME=$A42)*(UCA.AGROOTROS.DATE=R$5)*(UCA.AGROOTROS.VAL))} -> 0 | S42: {=SUMPRODUCT((UCA.AGROOTROS.NAME=$A42)*(UCA.AGROOTROS.DATE=S$5)*(UCA.AGROOTROS.VAL))} -> 0 | T42: {=SUMPRODUCT((UCA.AGROOTROS.NAME=$A42)*(UCA.AGROOTROS.DATE=T$5)*(UCA.AGROOTROS.VAL))} -> 0 | U42: {=SUMPRODUCT((UCA.AGROOTROS.NAME=$A42)*(UCA.AGROOTROS.DATE=U$5)*(UCA.AGROOTROS.VAL))} -> 0 | V42: {=SUMPRODUCT((UCA.AGROOTROS.NAME=$A42)*(UCA.AGROOTROS.DATE=V$5)*(UCA.AGROOTROS.VAL))} -> 532 | ... Z42: {=SUMPRODUCT((UCA.AGROOTROS.NAME=$A42)*(UCA.AGROOTROS.DATE=Z$5)*(UCA.AGROOTROS.VAL))} -> 65 | AA42: =SUM(O42:Z42) -> 1670 | AB42: {=SUMPRODUCT((UCA.AGROOTROS.NAME=$A42)*(UCA.AGROOTROS.DATE=AB$5)*(UCA.AGROOTROS.VAL))} -> 0 | AC42: {=SUMPRODUCT((UCA.AGROOTROS.NAME=$A42)*(UCA.AGROOTROS.DATE=AC$5)*(UCA.AGROOTROS.VAL))} -> 0 | AD42: {=SUMPRODUCT((UCA.AGROOTROS.NAME=$A42)*(UCA.AGROOTROS.DATE=AD$5)*(UCA.AGROOTROS.VAL))} -> 0 | AE42: {=SUMPRODUCT((UCA.AGROOTROS.NAME=$A42)*(UCA.AGROOTROS.DATE=AE$5)*(UCA.AGROOTROS.VAL))} -> 0 | AF42: {=SUMPRODUCT((UCA.AGROOTROS.NAME=$A42)*(UCA.AGROOTROS.DATE=AF$5)*(UCA.AGROOTROS.VAL))} -> 0 | AG42: {=SUMPRODUCT((UCA.AGROOTROS.NAME=$A42)*(UCA.AGROOTROS.DATE=AG$5)*(UCA.AGROOTROS.VAL))} -> 0 | AH42: {=SUMPRODUCT((UCA.AGROOTROS.NAME=$A42)*(UCA.AGROOTROS.DATE=AH$5)*(UCA.AGROOTROS.VAL))} -> 22 | AI42: {=SUMPRODUCT((UCA.AGROOTROS.NAME=$A42)*(UCA.AGROOTROS.DATE=AI$5)*(UCA.AGROOTROS.VAL))} -> 338 | ... AM42: {=SUMPRODUCT((UCA.AGROOTROS.NAME=$A42)*(UCA.AGROOTROS.DATE=AM$5)*(UCA.AGROOTROS.VAL))} -> 0 | AN42: =SUM(AB42:AM42) -> 1218 | AO42: {=SUMPRODUCT((UCA.AGROOTROS.NAME=$A42)*(UCA.AGROOTROS.DATE=AO$5)*(UCA.AGROOTROS.VAL))} -> 0 | AP42: {=SUMPRODUCT((UCA.AGROOTROS.NAME=$A42)*(UCA.AGROOTROS.DATE=AP$5)*(UCA.AGROOTROS.VAL))} -> 0 | AQ42: {=SUMPRODUCT((UCA.AGROOTROS.NAME=$A42)*(UCA.AGROOTROS.DATE=AQ$5)*(UCA.AGROOTROS.VAL))} -> 0 | AR42: {=SUMPRODUCT((UCA.AGROOTROS.NAME=$A42)*(UCA.AGROOTROS.DATE=AR$5)*(UCA.AGROOTROS.VAL))} -> 0 | AS42: {=SUMPRODUCT((UCA.AGROOTROS.NAME=$A42)*(UCA.AGROOTROS.DATE=AS$5)*(UCA.AGROOTROS.VAL))} -> 0 | AT42: {=SUMPRODUCT((UCA.AGROOTROS.NAME=$A42)*(UCA.AGROOTROS.DATE=AT$5)*(UCA.AGROOTROS.VAL))} -> 77 | AU42: {=SUMPRODUCT((UCA.AGROOTROS.NAME=$A42)*(UCA.AGROOTROS.DATE=AU$5)*(UCA.AGROOTROS.VAL))} -> 257 | AV42: {=SUMPRODUCT((UCA.AGROOTROS.NAME=$A42)*(UCA.AGROOTROS.DATE=AV$5)*(UCA.AGROOTROS.VAL))} -> 598 | ... AZ42: {=SUMPRODUCT((UCA.AGROOTROS.NAME=$A42)*(UCA.AGROOTROS.DATE=AZ$5)*(UCA.AGROOTROS.VAL))} -> 0 | BA42: =SUM(AO42:AZ42) -> 1566 | BB42: {=SUMPRODUCT((UCA.AGROOTROS.NAME=$A42)*(UCA.AGROOTROS.DATE=BB$5)*(UCA.AGROOTROS.VAL))} -> 0 | BC42: {=SUMPRODUCT((UCA.AGROOTROS.NAME=$A42)*(UCA.AGROOTROS.DATE=BC$5)*(UCA.AGROOTROS.VAL))} -> 0 | BD42: {=SUMPRODUCT((UCA.AGROOTROS.NAME=$A42)*(UCA.AGROOTROS.DATE=BD$5)*(UCA.AGROOTROS.VAL))} -> 0 | BE42: {=SUMPRODUCT((UCA.AGROOTROS.NAME=$A42)*(UCA.AGROOTROS.DATE=BE$5)*(UCA.AGROOTROS.VAL))} -> 0 | BF42: {=SUMPRODUCT((UCA.AGROOTROS.NAME=$A42)*(UCA.AGROOTROS.DATE=BF$5)*(UCA.AGROOTROS.VAL))} -> 0 | BG42: {=SUMPRODUCT((UCA.AGROOTROS.NAME=$A42)*(UCA.AGROOTROS.DATE=BG$5)*(UCA.AGROOTROS.VAL))} -> 0 | BH42: {=SUMPRODUCT((UCA.AGROOTROS.NAME=$A42)*(UCA.AGROOTROS.DATE=BH$5)*(UCA.AGROOTROS.VAL))} -> 30 | BI42: {=SUMPRODUCT((UCA.AGROOTROS.NAME=$A42)*(UCA.AGROOTROS.DATE=BI$5)*(UCA.AGROOTROS.VAL))} -> 37 | ... BM42: {=SUMPRODUCT((UCA.AGROOTROS.NAME=$A42)*(UCA.AGROOTROS.DATE=BM$5)*(UCA.AGROOTROS.VAL))} -> 17 | BN42: =SUM(BB42:BM42) -> 574 | BO42: {=SUMPRODUCT((UCA.AGROOTROS.NAME=$A42)*(UCA.AGROOTROS.DATE=BO$5)*(UCA.AGROOTROS.VAL))} -> 0 | BP42: {=SUMPRODUCT((UCA.AGROOTROS.NAME=$A42)*(UCA.AGROOTROS.DATE=BP$5)*(UCA.AGROOTROS.VAL))} -> 0 | BQ42: {=SUMPRODUCT((UCA.AGROOTROS.NAME=$A42)*(UCA.AGROOTROS.DATE=BQ$5)*(UCA.AGROOTROS.VAL))} -> 0 | BR42: {=SUMPRODUCT((UCA.AGROOTROS.NAME=$A42)*(UCA.AGROOTROS.DATE=BR$5)*(UCA.AGROOTROS.VAL))} -> 0 | BS42: {=SUMPRODUCT((UCA.AGROOTROS.NAME=$A42)*(UCA.AGROOTROS.DATE=BS$5)*(UCA.AGROOTROS.VAL))} -> 0 | BT42: {=SUMPRODUCT((UCA.AGROOTROS.NAME=$A42)*(UCA.AGROOTROS.DATE=BT$5)*(UCA.AGROOTROS.VAL))} -> 0 | BU42: {=SUMPRODUCT((UCA.AGROOTROS.NAME=$A42)*(UCA.AGROOTROS.DATE=BU$5)*(UCA.AGROOTROS.VAL))} -> 590.14 | BV42: {=SUMPRODUCT((UCA.AGROOTROS.NAME=$A42)*(UCA.AGROOTROS.DATE=BV$5)*(UCA.AGROOTROS.VAL))} -> 996.31 | ... BZ42: {=SUMPRODUCT((UCA.AGROOTROS.NAME=$A42)*(UCA.AGROOTROS.DATE=BZ$5)*(UCA.AGROOTROS.VAL))} -> 0 | CA42: =SUM(BO42:BZ42) -> 1987.7 | CB42: {=SUMPRODUCT((UCA.AGROOTROS.NAME=$A42)*(UCA.AGROOTROS.DATE=CB$5)*(UCA.AGROOTROS.VAL))} -> 0 | CC42: {=SUMPRODUCT((UCA.AGROOTROS.NAME=$A42)*(UCA.AGROOTROS.DATE=CC$5)*(UCA.AGROOTROS.VAL))} -> 0 | CD42: {=SUMPRODUCT((UCA.AGROOTROS.NAME=$A42)*(UCA.AGROOTROS.DATE=CD$5)*(UCA.AGROOTROS.VAL))} -> 0 | CE42: {=SUMPRODUCT((UCA.AGROOTROS.NAME=$A42)*(UCA.AGROOTROS.DATE=CE$5)*(UCA.AGROOTROS.VAL))} -> 0 | CF42: {=SUMPRODUCT((UCA.AGROOTROS.NAME=$A42)*(UCA.AGROOTROS.DATE=CF$5)*(UCA.AGROOTROS.VAL))} -> 0 | CG42: {=SUMPRODUCT((UCA.AGROOTROS.NAME=$A42)*(UCA.AGROOTROS.DATE=CG$5)*(UCA.AGROOTROS.VAL))} -> 0 | CH42: {=SUMPRODUCT((UCA.AGROOTROS.NAME=$A42)*(UCA.AGROOTROS.DATE=CH$5)*(UCA.AGROOTROS.VAL))} -> 77.4 | CI42: {=SUMPRODUCT((UCA.AGROOTROS.NAME=$A42)*(UCA.AGROOTROS.DATE=CI$5)*(UCA.AGROOTROS.VAL))} -> 755.88 | ... CM42: {=SUMPRODUCT((UCA.AGROOTROS.NAME=$A42)*(UCA.AGROOTROS.DATE=CM$5)*(UCA.AGROOTROS.VAL))} -> 52.63 | CN42: =SUM(CB42:CM42) -> 1427.41 | CO42: {=SUMPRODUCT((UCA.AGROOTROS.NAME=$A42)*(UCA.AGROOTROS.DATE=CO$5)*(UCA.AGROOTROS.VAL))} -> 0 | CP42: {=SUMPRODUCT((UCA.AGROOTROS.NAME=$A42)*(UCA.AGROOTROS.DATE=CP$5)*(UCA.AGROOTROS.VAL))} -> 0 | CQ42: {=SUMPRODUCT((UCA.AGROOTROS.NAME=$A42)*(UCA.AGROOTROS.DATE=CQ$5)*(UCA.AGROOTROS.VAL))} -> 0 | CR42: {=SUMPRODUCT((UCA.AGROOTROS.NAME=$A42)*(UCA.AGROOTROS.DATE=CR$5)*(UCA.AGROOTROS.VAL))} -> 0 | CS42: {=SUMPRODUCT((UCA.AGROOTROS.NAME=$A42)*(UCA.AGROOTROS.DATE=CS$5)*(UCA.AGROOTROS.VAL))} -> 0 | CT42: {=SUMPRODUCT((UCA.AGROOTROS.NAME=$A42)*(UCA.AGROOTROS.DATE=CT$5)*(UCA.AGROOTROS.VAL))} -> 0 | CU42: {=SUMPRODUCT((UCA.AGROOTROS.NAME=$A42)*(UCA.AGROOTROS.DATE=CU$5)*(UCA.AGROOTROS.VAL))} -> 0 | CV42: {=SUMPRODUCT((UCA.AGROOTROS.NAME=$A42)*(UCA.AGROOTROS.DATE=CV$5)*(UCA.AGROOTROS.VAL))} -> 544.16 | ... CZ42: {=SUMPRODUCT((UCA.AGROOTROS.NAME=$A42)*(UCA.AGROOTROS.DATE=CZ$5)*(UCA.AGROOTROS.VAL))} -> 0 | DA42: =SUM(CO42:CZ42) -> 1098.43 | DB42: {=SUMPRODUCT((UCA.AGROOTROS.NAME=$A42)*(UCA.AGROOTROS.DATE=DB$5)*(UCA.AGROOTROS.VAL))} -> 0 | DC42: {=SUMPRODUCT((UCA.AGROOTROS.NAME=$A42)*(UCA.AGROOTROS.DATE=DC$5)*(UCA.AGROOTROS.VAL))} -> 0 | DD42: {=SUMPRODUCT((UCA.AGROOTROS.NAME=$A42)*(UCA.AGROOTROS.DATE=DD$5)*(UCA.AGROOTROS.VAL))} -> 0 | DE42: {=SUMPRODUCT((UCA.AGROOTROS.NAME=$A42)*(UCA.AGROOTROS.DATE=DE$5)*(UCA.AGROOTROS.VAL))} -> 0 | DF42: {=SUMPRODUCT((UCA.AGROOTROS.NAME=$A42)*(UCA.AGROOTROS.DATE=DF$5)*(UCA.AGROOTROS.VAL))} -> 0 | DG42: {=SUMPRODUCT((UCA.AGROOTROS.NAME=$A42)*(UCA.AGROOTROS.DATE=DG$5)*(UCA.AGROOTROS.VAL))} -> 0 | DH42: {=SUMPRODUCT((UCA.AGROOTROS.NAME=$A42)*(UCA.AGROOTROS.DATE=DH$5)*(UCA.AGROOTROS.VAL))} -> 0 | DI42: {=SUMPRODUCT((UCA.AGROOTROS.NAME=$A42)*(UCA.AGROOTROS.DATE=DI$5)*(UCA.AGROOTROS.VAL))} -> 643.55 | ... DM42: {=SUMPRODUCT((UCA.AGROOTROS.NAME=$A42)*(UCA.AGROOTROS.DATE=DM$5)*(UCA.AGROOTROS.VAL))} -> 0 | DN42: =SUM(DB42:DM42) -> 2096.69 | DO42: {=SUMPRODUCT((UCA.AGROOTROS.NAME=$A42)*(UCA.AGROOTROS.DATE=DO$5)*(UCA.AGROOTROS.VAL))} -> 0 | DP42: {=SUMPRODUCT((UCA.AGROOTROS.NAME=$A42)*(UCA.AGROOTROS.DATE=DP$5)*(UCA.AGROOTROS.VAL))} -> 0 | DQ42: {=SUMPRODUCT((UCA.AGROOTROS.NAME=$A42)*(UCA.AGROOTROS.DATE=DQ$5)*(UCA.AGROOTROS.VAL))} -> 0 | DR42: {=SUMPRODUCT((UCA.AGROOTROS.NAME=$A42)*(UCA.AGROOTROS.DATE=DR$5)*(UCA.AGROOTROS.VAL))} -> 0 | DS42: {=SUMPRODUCT((UCA.AGROOTROS.NAME=$A42)*(UCA.AGROOTROS.DATE=DS$5)*(UCA.AGROOTROS.VAL))} -> 0 | DT42: {=SUMPRODUCT((UCA.AGROOTROS.NAME=$A42)*(UCA.AGROOTROS.DATE=DT$5)*(UCA.AGROOTROS.VAL))} -> 0 | DU42: {=SUMPRODUCT((UCA.AGROOTROS.NAME=$A42)*(UCA.AGROOTROS.DATE=DU$5)*(UCA.AGROOTROS.VAL))} -> 0 | DV42: {=SUMPRODUCT((UCA.AGROOTROS.NAME=$A42)*(UCA.AGROOTROS.DATE=DV$5)*(UCA.AGROOTROS.VAL))} -> 950.66 | ... DZ42: {=SUMPRODUCT((UCA.AGROOTROS.NAME=$A42)*(UCA.AGROOTROS.DATE=DZ$5)*(UCA.AGROOTROS.VAL))} -> 0 | EA42: =SUM(DO42:DZ42) -> 2956.909 | EB42: {=SUMPRODUCT((UCA.AGROOTROS.NAME=$A42)*(UCA.AGROOTROS.DATE=EB$5)*(UCA.AGROOTROS.VAL))} -> 46.94 | EC42: {=SUMPRODUCT((UCA.AGROOTROS.NAME=$A42)*(UCA.AGROOTROS.DATE=EC$5)*(UCA.AGROOTROS.VAL))} -> 0 | ED42: {=SUMPRODUCT((UCA.AGROOTROS.NAME=$A42)*(UCA.AGROOTROS.DATE=ED$5)*(UCA.AGROOTROS.VAL))} -> 0 | EE42: {=SUMPRODUCT((UCA.AGROOTROS.NAME=$A42)*(UCA.AGROOTROS.DATE=EE$5)*(UCA.AGROOTROS.VAL))} -> 0 | EF42: {=SUMPRODUCT((UCA.AGROOTROS.NAME=$A42)*(UCA.AGROOTROS.DATE=EF$5)*(UCA.AGROOTROS.VAL))} -> 0 | EG42: {=SUMPRODUCT((UCA.AGROOTROS.NAME=$A42)*(UCA.AGROOTROS.DATE=EG$5)*(UCA.AGROOTROS.VAL))} -> 0 | EH42: {=SUMPRODUCT((UCA.AGROOTROS.NAME=$A42)*(UCA.AGROOTROS.DATE=EH$5)*(UCA.AGROOTROS.VAL))} -> 0 | EI42: {=SUMPRODUCT((UCA.AGROOTROS.NAME=$A42)*(UCA.AGROOTROS.DATE=EI$5)*(UCA.AGROOTROS.VAL))} -> 246.77 | ... EM42: {=SUMPRODUCT((UCA.AGROOTROS.NAME=$A42)*(UCA.AGROOTROS.DATE=EM$5)*(UCA.AGROOTROS.VAL))} -> 224.84 | EN42: =SUM(EB42:EM42) -> 1822.618 | EO42: {=SUMPRODUCT((UCA.AGROOTROS.NAME=$A42)*(UCA.AGROOTROS.DATE=EO$5)*(UCA.AGROOTROS.VAL))} -> 18.75 | EP42: {=SUMPRODUCT((UCA.AGROOTROS.NAME=$A42)*(UCA.AGROOTROS.DATE=EP$5)*(UCA.AGROOTROS.VAL))} -> 0 | EQ42: {=SUMPRODUCT((UCA.AGROOTROS.NAME=$A42)*(UCA.AGROOTROS.DATE=EQ$5)*(UCA.AGROOTROS.VAL))} -> 0 | ER42: {=SUMPRODUCT((UCA.AGROOTROS.NAME=$A42)*(UCA.AGROOTROS.DATE=ER$5)*(UCA.AGROOTROS.VAL))} -> 0 | ES42: {=SUMPRODUCT((UCA.AGROOTROS.NAME=$A42)*(UCA.AGROOTROS.DATE=ES$5)*(UCA.AGROOTROS.VAL))} -> 0 | ET42: {=SUMPRODUCT((UCA.AGROOTROS.NAME=$A42)*(UCA.AGROOTROS.DATE=ET$5)*(UCA.AGROOTROS.VAL))} -> 0 | EU42: {=SUMPRODUCT((UCA.AGROOTROS.NAME=$A42)*(UCA.AGROOTROS.DATE=EU$5)*(UCA.AGROOTROS.VAL))} -> 0 | EV42: {=SUMPRODUCT((UCA.AGROOTROS.NAME=$A42)*(UCA.AGROOTROS.DATE=EV$5)*(UCA.AGROOTROS.VAL))} -> 0 | ... EZ42: {=SUMPRODUCT((UCA.AGROOTROS.NAME=$A42)*(UCA.AGROOTROS.DATE=EZ$5)*(UCA.AGROOTROS.VAL))} -> 0 | FA42: =SUM(EO42:EZ42) -> 18.75 | FC42: =IFERROR((( _xlfn.XLOOKUP((DATE(YEAR($FC$5),MONTH($FC$5),1)),UCA.AGRO.DATE,$B42:$FA42) / _xlfn.XLOOKUP((DATE(YEAR($FC$5)-1,MONTH($FC$5),1)),UCA.AGRO.DATE,$B42:$FA42) )-1)*100,"") -> -62.906291 | FD42: =IFERROR(((FF42/FE42)-1)*100,"") -> -45.964587 | FE42: =SUMIFS($B42:$FA42,UCA.AGRO.DATE,">="&DATE(YEAR($FC$5)-1,1,1),UCA.AGRO.DATE,"<="&DATE(YEAR($FC$5)-1,MONTH($FC$5),1)) -> 2956.909 | FF42: =SUMIFS($B42:$FA42,UCA.AGRO.DATE,">="&DATE(YEAR($FC$5),1,1),UCA.AGRO.DATE,"<="&$FC$5) -> 1597.778 | FH42: =SUM(B42:FA42) -> 36737.014 | FJ42: =IF(EXACT(A42,FI42)=TRUE,"OK","VER") -> VER
A43: Pepino | B43: {=SUMPRODUCT((UCA.AGROOTROS.NAME=$A43)*(UCA.AGROOTROS.DATE=B$5)*(UCA.AGROOTROS.VAL))} -> 23 | C43: {=SUMPRODUCT((UCA.AGROOTROS.NAME=$A43)*(UCA.AGROOTROS.DATE=C$5)*(UCA.AGROOTROS.VAL))} -> 11 | D43: {=SUMPRODUCT((UCA.AGROOTROS.NAME=$A43)*(UCA.AGROOTROS.DATE=D$5)*(UCA.AGROOTROS.VAL))} -> 11 | E43: {=SUMPRODUCT((UCA.AGROOTROS.NAME=$A43)*(UCA.AGROOTROS.DATE=E$5)*(UCA.AGROOTROS.VAL))} -> 31 | F43: {=SUMPRODUCT((UCA.AGROOTROS.NAME=$A43)*(UCA.AGROOTROS.DATE=F$5)*(UCA.AGROOTROS.VAL))} -> 16 | G43: {=SUMPRODUCT((UCA.AGROOTROS.NAME=$A43)*(UCA.AGROOTROS.DATE=G$5)*(UCA.AGROOTROS.VAL))} -> 0 | H43: {=SUMPRODUCT((UCA.AGROOTROS.NAME=$A43)*(UCA.AGROOTROS.DATE=H$5)*(UCA.AGROOTROS.VAL))} -> 29 | I43: {=SUMPRODUCT((UCA.AGROOTROS.NAME=$A43)*(UCA.AGROOTROS.DATE=I$5)*(UCA.AGROOTROS.VAL))} -> 76 | ... M43: {=SUMPRODUCT((UCA.AGROOTROS.NAME=$A43)*(UCA.AGROOTROS.DATE=M$5)*(UCA.AGROOTROS.VAL))} -> 33 | N43: =SUM(B43:M43) -> 569 | O43: {=SUMPRODUCT((UCA.AGROOTROS.NAME=$A43)*(UCA.AGROOTROS.DATE=O$5)*(UCA.AGROOTROS.VAL))} -> 36 | P43: {=SUMPRODUCT((UCA.AGROOTROS.NAME=$A43)*(UCA.AGROOTROS.DATE=P$5)*(UCA.AGROOTROS.VAL))} -> 22 | Q43: {=SUMPRODUCT((UCA.AGROOTROS.NAME=$A43)*(UCA.AGROOTROS.DATE=Q$5)*(UCA.AGROOTROS.VAL))} -> 0 | R43: {=SUMPRODUCT((UCA.AGROOTROS.NAME=$A43)*(UCA.AGROOTROS.DATE=R$5)*(UCA.AGROOTROS.VAL))} -> 0 | S43: {=SUMPRODUCT((UCA.AGROOTROS.NAME=$A43)*(UCA.AGROOTROS.DATE=S$5)*(UCA.AGROOTROS.VAL))} -> 0 | T43: {=SUMPRODUCT((UCA.AGROOTROS.NAME=$A43)*(UCA.AGROOTROS.DATE=T$5)*(UCA.AGROOTROS.VAL))} -> 11 | U43: {=SUMPRODUCT((UCA.AGROOTROS.NAME=$A43)*(UCA.AGROOTROS.DATE=U$5)*(UCA.AGROOTROS.VAL))} -> 12 | V43: {=SUMPRODUCT((UCA.AGROOTROS.NAME=$A43)*(UCA.AGROOTROS.DATE=V$5)*(UCA.AGROOTROS.VAL))} -> 70 | ... Z43: {=SUMPRODUCT((UCA.AGROOTROS.NAME=$A43)*(UCA.AGROOTROS.DATE=Z$5)*(UCA.AGROOTROS.VAL))} -> 0 | AA43: =SUM(O43:Z43) -> 316 | AB43: {=SUMPRODUCT((UCA.AGROOTROS.NAME=$A43)*(UCA.AGROOTROS.DATE=AB$5)*(UCA.AGROOTROS.VAL))} -> 0 | AC43: {=SUMPRODUCT((UCA.AGROOTROS.NAME=$A43)*(UCA.AGROOTROS.DATE=AC$5)*(UCA.AGROOTROS.VAL))} -> 0 | AD43: {=SUMPRODUCT((UCA.AGROOTROS.NAME=$A43)*(UCA.AGROOTROS.DATE=AD$5)*(UCA.AGROOTROS.VAL))} -> 0 | AE43: {=SUMPRODUCT((UCA.AGROOTROS.NAME=$A43)*(UCA.AGROOTROS.DATE=AE$5)*(UCA.AGROOTROS.VAL))} -> 0 | AF43: {=SUMPRODUCT((UCA.AGROOTROS.NAME=$A43)*(UCA.AGROOTROS.DATE=AF$5)*(UCA.AGROOTROS.VAL))} -> 0 | AG43: {=SUMPRODUCT((UCA.AGROOTROS.NAME=$A43)*(UCA.AGROOTROS.DATE=AG$5)*(UCA.AGROOTROS.VAL))} -> 0 | AH43: {=SUMPRODUCT((UCA.AGROOTROS.NAME=$A43)*(UCA.AGROOTROS.DATE=AH$5)*(UCA.AGROOTROS.VAL))} -> 6 | AI43: {=SUMPRODUCT((UCA.AGROOTROS.NAME=$A43)*(UCA.AGROOTROS.DATE=AI$5)*(UCA.AGROOTROS.VAL))} -> 96 | ... AM43: {=SUMPRODUCT((UCA.AGROOTROS.NAME=$A43)*(UCA.AGROOTROS.DATE=AM$5)*(UCA.AGROOTROS.VAL))} -> 0 | AN43: =SUM(AB43:AM43) -> 341 | AO43: {=SUMPRODUCT((UCA.AGROOTROS.NAME=$A43)*(UCA.AGROOTROS.DATE=AO$5)*(UCA.AGROOTROS.VAL))} -> 0 | AP43: {=SUMPRODUCT((UCA.AGROOTROS.NAME=$A43)*(UCA.AGROOTROS.DATE=AP$5)*(UCA.AGROOTROS.VAL))} -> 0 | AQ43: {=SUMPRODUCT((UCA.AGROOTROS.NAME=$A43)*(UCA.AGROOTROS.DATE=AQ$5)*(UCA.AGROOTROS.VAL))} -> 0 | AR43: {=SUMPRODUCT((UCA.AGROOTROS.NAME=$A43)*(UCA.AGROOTROS.DATE=AR$5)*(UCA.AGROOTROS.VAL))} -> 0 | AS43: {=SUMPRODUCT((UCA.AGROOTROS.NAME=$A43)*(UCA.AGROOTROS.DATE=AS$5)*(UCA.AGROOTROS.VAL))} -> 0 | AT43: {=SUMPRODUCT((UCA.AGROOTROS.NAME=$A43)*(UCA.AGROOTROS.DATE=AT$5)*(UCA.AGROOTROS.VAL))} -> 80 | AU43: {=SUMPRODUCT((UCA.AGROOTROS.NAME=$A43)*(UCA.AGROOTROS.DATE=AU$5)*(UCA.AGROOTROS.VAL))} -> 133 | AV43: {=SUMPRODUCT((UCA.AGROOTROS.NAME=$A43)*(UCA.AGROOTROS.DATE=AV$5)*(UCA.AGROOTROS.VAL))} -> 153 | ... AZ43: {=SUMPRODUCT((UCA.AGROOTROS.NAME=$A43)*(UCA.AGROOTROS.DATE=AZ$5)*(UCA.AGROOTROS.VAL))} -> 21 | BA43: =SUM(AO43:AZ43) -> 594 | BB43: {=SUMPRODUCT((UCA.AGROOTROS.NAME=$A43)*(UCA.AGROOTROS.DATE=BB$5)*(UCA.AGROOTROS.VAL))} -> 21 | BC43: {=SUMPRODUCT((UCA.AGROOTROS.NAME=$A43)*(UCA.AGROOTROS.DATE=BC$5)*(UCA.AGROOTROS.VAL))} -> 21 | BD43: {=SUMPRODUCT((UCA.AGROOTROS.NAME=$A43)*(UCA.AGROOTROS.DATE=BD$5)*(UCA.AGROOTROS.VAL))} -> 0 | BE43: {=SUMPRODUCT((UCA.AGROOTROS.NAME=$A43)*(UCA.AGROOTROS.DATE=BE$5)*(UCA.AGROOTROS.VAL))} -> 0 | BF43: {=SUMPRODUCT((UCA.AGROOTROS.NAME=$A43)*(UCA.AGROOTROS.DATE=BF$5)*(UCA.AGROOTROS.VAL))} -> 13 | BG43: {=SUMPRODUCT((UCA.AGROOTROS.NAME=$A43)*(UCA.AGROOTROS.DATE=BG$5)*(UCA.AGROOTROS.VAL))} -> 9 | BH43: {=SUMPRODUCT((UCA.AGROOTROS.NAME=$A43)*(UCA.AGROOTROS.DATE=BH$5)*(UCA.AGROOTROS.VAL))} -> 21 | BI43: {=SUMPRODUCT((UCA.AGROOTROS.NAME=$A43)*(UCA.AGROOTROS.DATE=BI$5)*(UCA.AGROOTROS.VAL))} -> 42 | ... BM43: {=SUMPRODUCT((UCA.AGROOTROS.NAME=$A43)*(UCA.AGROOTROS.DATE=BM$5)*(UCA.AGROOTROS.VAL))} -> 10 | BN43: =SUM(BB43:BM43) -> 301 | BO43: {=SUMPRODUCT((UCA.AGROOTROS.NAME=$A43)*(UCA.AGROOTROS.DATE=BO$5)*(UCA.AGROOTROS.VAL))} -> 5 | BP43: {=SUMPRODUCT((UCA.AGROOTROS.NAME=$A43)*(UCA.AGROOTROS.DATE=BP$5)*(UCA.AGROOTROS.VAL))} -> 0 | BQ43: {=SUMPRODUCT((UCA.AGROOTROS.NAME=$A43)*(UCA.AGROOTROS.DATE=BQ$5)*(UCA.AGROOTROS.VAL))} -> 0 | BR43: {=SUMPRODUCT((UCA.AGROOTROS.NAME=$A43)*(UCA.AGROOTROS.DATE=BR$5)*(UCA.AGROOTROS.VAL))} -> 6 | BS43: {=SUMPRODUCT((UCA.AGROOTROS.NAME=$A43)*(UCA.AGROOTROS.DATE=BS$5)*(UCA.AGROOTROS.VAL))} -> 0 | BT43: {=SUMPRODUCT((UCA.AGROOTROS.NAME=$A43)*(UCA.AGROOTROS.DATE=BT$5)*(UCA.AGROOTROS.VAL))} -> 0 | BU43: {=SUMPRODUCT((UCA.AGROOTROS.NAME=$A43)*(UCA.AGROOTROS.DATE=BU$5)*(UCA.AGROOTROS.VAL))} -> 79 | BV43: {=SUMPRODUCT((UCA.AGROOTROS.NAME=$A43)*(UCA.AGROOTROS.DATE=BV$5)*(UCA.AGROOTROS.VAL))} -> 168 | ... BZ43: {=SUMPRODUCT((UCA.AGROOTROS.NAME=$A43)*(UCA.AGROOTROS.DATE=BZ$5)*(UCA.AGROOTROS.VAL))} -> 31 | CA43: =SUM(BO43:BZ43) -> 485 | CB43: {=SUMPRODUCT((UCA.AGROOTROS.NAME=$A43)*(UCA.AGROOTROS.DATE=CB$5)*(UCA.AGROOTROS.VAL))} -> 24.49 | CC43: {=SUMPRODUCT((UCA.AGROOTROS.NAME=$A43)*(UCA.AGROOTROS.DATE=CC$5)*(UCA.AGROOTROS.VAL))} -> 23.83 | CD43: {=SUMPRODUCT((UCA.AGROOTROS.NAME=$A43)*(UCA.AGROOTROS.DATE=CD$5)*(UCA.AGROOTROS.VAL))} -> 6.25 | CE43: {=SUMPRODUCT((UCA.AGROOTROS.NAME=$A43)*(UCA.AGROOTROS.DATE=CE$5)*(UCA.AGROOTROS.VAL))} -> 0 | CF43: {=SUMPRODUCT((UCA.AGROOTROS.NAME=$A43)*(UCA.AGROOTROS.DATE=CF$5)*(UCA.AGROOTROS.VAL))} -> 0 | CG43: {=SUMPRODUCT((UCA.AGROOTROS.NAME=$A43)*(UCA.AGROOTROS.DATE=CG$5)*(UCA.AGROOTROS.VAL))} -> 50.488 | CH43: {=SUMPRODUCT((UCA.AGROOTROS.NAME=$A43)*(UCA.AGROOTROS.DATE=CH$5)*(UCA.AGROOTROS.VAL))} -> 50.45 | CI43: {=SUMPRODUCT((UCA.AGROOTROS.NAME=$A43)*(UCA.AGROOTROS.DATE=CI$5)*(UCA.AGROOTROS.VAL))} -> 240.759 | ... CM43: {=SUMPRODUCT((UCA.AGROOTROS.NAME=$A43)*(UCA.AGROOTROS.DATE=CM$5)*(UCA.AGROOTROS.VAL))} -> 0 | CN43: =SUM(CB43:CM43) -> 786.657 | CO43: {=SUMPRODUCT((UCA.AGROOTROS.NAME=$A43)*(UCA.AGROOTROS.DATE=CO$5)*(UCA.AGROOTROS.VAL))} -> 19.92 | CP43: {=SUMPRODUCT((UCA.AGROOTROS.NAME=$A43)*(UCA.AGROOTROS.DATE=CP$5)*(UCA.AGROOTROS.VAL))} -> 73.76 | CQ43: {=SUMPRODUCT((UCA.AGROOTROS.NAME=$A43)*(UCA.AGROOTROS.DATE=CQ$5)*(UCA.AGROOTROS.VAL))} -> 0 | CR43: {=SUMPRODUCT((UCA.AGROOTROS.NAME=$A43)*(UCA.AGROOTROS.DATE=CR$5)*(UCA.AGROOTROS.VAL))} -> 0 | CS43: {=SUMPRODUCT((UCA.AGROOTROS.NAME=$A43)*(UCA.AGROOTROS.DATE=CS$5)*(UCA.AGROOTROS.VAL))} -> 6.75 | CT43: {=SUMPRODUCT((UCA.AGROOTROS.NAME=$A43)*(UCA.AGROOTROS.DATE=CT$5)*(UCA.AGROOTROS.VAL))} -> 38.22 | CU43: {=SUMPRODUCT((UCA.AGROOTROS.NAME=$A43)*(UCA.AGROOTROS.DATE=CU$5)*(UCA.AGROOTROS.VAL))} -> 95.86 | CV43: {=SUMPRODUCT((UCA.AGROOTROS.NAME=$A43)*(UCA.AGROOTROS.DATE=CV$5)*(UCA.AGROOTROS.VAL))} -> 184.36 | ... CZ43: {=SUMPRODUCT((UCA.AGROOTROS.NAME=$A43)*(UCA.AGROOTROS.DATE=CZ$5)*(UCA.AGROOTROS.VAL))} -> 151.81 | DA43: =SUM(CO43:CZ43) -> 1112.75 | DB43: {=SUMPRODUCT((UCA.AGROOTROS.NAME=$A43)*(UCA.AGROOTROS.DATE=DB$5)*(UCA.AGROOTROS.VAL))} -> 107.54 | DC43: {=SUMPRODUCT((UCA.AGROOTROS.NAME=$A43)*(UCA.AGROOTROS.DATE=DC$5)*(UCA.AGROOTROS.VAL))} -> 74.739 | DD43: {=SUMPRODUCT((UCA.AGROOTROS.NAME=$A43)*(UCA.AGROOTROS.DATE=DD$5)*(UCA.AGROOTROS.VAL))} -> 40.44 | DE43: {=SUMPRODUCT((UCA.AGROOTROS.NAME=$A43)*(UCA.AGROOTROS.DATE=DE$5)*(UCA.AGROOTROS.VAL))} -> 6.59 | DF43: {=SUMPRODUCT((UCA.AGROOTROS.NAME=$A43)*(UCA.AGROOTROS.DATE=DF$5)*(UCA.AGROOTROS.VAL))} -> 20.55 | DG43: {=SUMPRODUCT((UCA.AGROOTROS.NAME=$A43)*(UCA.AGROOTROS.DATE=DG$5)*(UCA.AGROOTROS.VAL))} -> 12.78 | DH43: {=SUMPRODUCT((UCA.AGROOTROS.NAME=$A43)*(UCA.AGROOTROS.DATE=DH$5)*(UCA.AGROOTROS.VAL))} -> 44.84 | DI43: {=SUMPRODUCT((UCA.AGROOTROS.NAME=$A43)*(UCA.AGROOTROS.DATE=DI$5)*(UCA.AGROOTROS.VAL))} -> 212.12 | ... DM43: {=SUMPRODUCT((UCA.AGROOTROS.NAME=$A43)*(UCA.AGROOTROS.DATE=DM$5)*(UCA.AGROOTROS.VAL))} -> 154.058 | DN43: =SUM(DB43:DM43) -> 1307.464 | DO43: {=SUMPRODUCT((UCA.AGROOTROS.NAME=$A43)*(UCA.AGROOTROS.DATE=DO$5)*(UCA.AGROOTROS.VAL))} -> 177.59 | DP43: {=SUMPRODUCT((UCA.AGROOTROS.NAME=$A43)*(UCA.AGROOTROS.DATE=DP$5)*(UCA.AGROOTROS.VAL))} -> 0 | DQ43: {=SUMPRODUCT((UCA.AGROOTROS.NAME=$A43)*(UCA.AGROOTROS.DATE=DQ$5)*(UCA.AGROOTROS.VAL))} -> 11.52 | DR43: {=SUMPRODUCT((UCA.AGROOTROS.NAME=$A43)*(UCA.AGROOTROS.DATE=DR$5)*(UCA.AGROOTROS.VAL))} -> 19.44 | DS43: {=SUMPRODUCT((UCA.AGROOTROS.NAME=$A43)*(UCA.AGROOTROS.DATE=DS$5)*(UCA.AGROOTROS.VAL))} -> 27.32 | DT43: {=SUMPRODUCT((UCA.AGROOTROS.NAME=$A43)*(UCA.AGROOTROS.DATE=DT$5)*(UCA.AGROOTROS.VAL))} -> 30.151 | DU43: {=SUMPRODUCT((UCA.AGROOTROS.NAME=$A43)*(UCA.AGROOTROS.DATE=DU$5)*(UCA.AGROOTROS.VAL))} -> 144.97 | DV43: {=SUMPRODUCT((UCA.AGROOTROS.NAME=$A43)*(UCA.AGROOTROS.DATE=DV$5)*(UCA.AGROOTROS.VAL))} -> 408.019 | ... DZ43: {=SUMPRODUCT((UCA.AGROOTROS.NAME=$A43)*(UCA.AGROOTROS.DATE=DZ$5)*(UCA.AGROOTROS.VAL))} -> 195.419 | EA43: =SUM(DO43:DZ43) -> 2310.934 | EB43: {=SUMPRODUCT((UCA.AGROOTROS.NAME=$A43)*(UCA.AGROOTROS.DATE=EB$5)*(UCA.AGROOTROS.VAL))} -> 170.919 | EC43: {=SUMPRODUCT((UCA.AGROOTROS.NAME=$A43)*(UCA.AGROOTROS.DATE=EC$5)*(UCA.AGROOTROS.VAL))} -> 5.38 | ED43: {=SUMPRODUCT((UCA.AGROOTROS.NAME=$A43)*(UCA.AGROOTROS.DATE=ED$5)*(UCA.AGROOTROS.VAL))} -> 0 | EE43: {=SUMPRODUCT((UCA.AGROOTROS.NAME=$A43)*(UCA.AGROOTROS.DATE=EE$5)*(UCA.AGROOTROS.VAL))} -> 0 | EF43: {=SUMPRODUCT((UCA.AGROOTROS.NAME=$A43)*(UCA.AGROOTROS.DATE=EF$5)*(UCA.AGROOTROS.VAL))} -> 32.81 | EG43: {=SUMPRODUCT((UCA.AGROOTROS.NAME=$A43)*(UCA.AGROOTROS.DATE=EG$5)*(UCA.AGROOTROS.VAL))} -> 34.47 | EH43: {=SUMPRODUCT((UCA.AGROOTROS.NAME=$A43)*(UCA.AGROOTROS.DATE=EH$5)*(UCA.AGROOTROS.VAL))} -> 46.005 | EI43: {=SUMPRODUCT((UCA.AGROOTROS.NAME=$A43)*(UCA.AGROOTROS.DATE=EI$5)*(UCA.AGROOTROS.VAL))} -> 340.91 | ... EM43: {=SUMPRODUCT((UCA.AGROOTROS.NAME=$A43)*(UCA.AGROOTROS.DATE=EM$5)*(UCA.AGROOTROS.VAL))} -> 269.17 | EN43: =SUM(EB43:EM43) -> 1738.852 | EO43: {=SUMPRODUCT((UCA.AGROOTROS.NAME=$A43)*(UCA.AGROOTROS.DATE=EO$5)*(UCA.AGROOTROS.VAL))} -> 186.23 | EP43: {=SUMPRODUCT((UCA.AGROOTROS.NAME=$A43)*(UCA.AGROOTROS.DATE=EP$5)*(UCA.AGROOTROS.VAL))} -> 6.73 | EQ43: {=SUMPRODUCT((UCA.AGROOTROS.NAME=$A43)*(UCA.AGROOTROS.DATE=EQ$5)*(UCA.AGROOTROS.VAL))} -> 0 | ER43: {=SUMPRODUCT((UCA.AGROOTROS.NAME=$A43)*(UCA.AGROOTROS.DATE=ER$5)*(UCA.AGROOTROS.VAL))} -> 0 | ES43: {=SUMPRODUCT((UCA.AGROOTROS.NAME=$A43)*(UCA.AGROOTROS.DATE=ES$5)*(UCA.AGROOTROS.VAL))} -> 0 | ET43: {=SUMPRODUCT((UCA.AGROOTROS.NAME=$A43)*(UCA.AGROOTROS.DATE=ET$5)*(UCA.AGROOTROS.VAL))} -> 0 | EU43: {=SUMPRODUCT((UCA.AGROOTROS.NAME=$A43)*(UCA.AGROOTROS.DATE=EU$5)*(UCA.AGROOTROS.VAL))} -> 0 | EV43: {=SUMPRODUCT((UCA.AGROOTROS.NAME=$A43)*(UCA.AGROOTROS.DATE=EV$5)*(UCA.AGROOTROS.VAL))} -> 0 | ... EZ43: {=SUMPRODUCT((UCA.AGROOTROS.NAME=$A43)*(UCA.AGROOTROS.DATE=EZ$5)*(UCA.AGROOTROS.VAL))} -> 0 | FA43: =SUM(EO43:EZ43) -> 192.96 | FC43: =IFERROR((( _xlfn.XLOOKUP((DATE(YEAR($FC$5),MONTH($FC$5),1)),UCA.AGRO.DATE,$B43:$FA43) / _xlfn.XLOOKUP((DATE(YEAR($FC$5)-1,MONTH($FC$5),1)),UCA.AGRO.DATE,$B43:$FA43) )-1)*100,"") -> -4.4787544 | FD43: =IFERROR(((FF43/FE43)-1)*100,"") -> -30.528406 | FE43: =SUMIFS($B43:$FA43,UCA.AGRO.DATE,">="&DATE(YEAR($FC$5)-1,1,1),UCA.AGRO.DATE,"<="&DATE(YEAR($FC$5)-1,MONTH($FC$5),1)) -> 2115.515 | FF43: =SUMIFS($B43:$FA43,UCA.AGRO.DATE,">="&DATE(YEAR($FC$5),1,1),UCA.AGRO.DATE,"<="&$FC$5) -> 1469.682 | FH43: =SUM(B43:FA43) -> 20111.234 | FJ43: =IF(EXACT(A43,FI43)=TRUE,"OK","VER") -> VER
A44: Soya | B44: {=SUMPRODUCT((UCA.AGROOTROS.NAME=$A44)*(UCA.AGROOTROS.DATE=B$5)*(UCA.AGROOTROS.VAL))} -> 0 | C44: {=SUMPRODUCT((UCA.AGROOTROS.NAME=$A44)*(UCA.AGROOTROS.DATE=C$5)*(UCA.AGROOTROS.VAL))} -> 0 | D44: {=SUMPRODUCT((UCA.AGROOTROS.NAME=$A44)*(UCA.AGROOTROS.DATE=D$5)*(UCA.AGROOTROS.VAL))} -> 0 | E44: {=SUMPRODUCT((UCA.AGROOTROS.NAME=$A44)*(UCA.AGROOTROS.DATE=E$5)*(UCA.AGROOTROS.VAL))} -> 0 | F44: {=SUMPRODUCT((UCA.AGROOTROS.NAME=$A44)*(UCA.AGROOTROS.DATE=F$5)*(UCA.AGROOTROS.VAL))} -> 0 | G44: {=SUMPRODUCT((UCA.AGROOTROS.NAME=$A44)*(UCA.AGROOTROS.DATE=G$5)*(UCA.AGROOTROS.VAL))} -> 0 | H44: {=SUMPRODUCT((UCA.AGROOTROS.NAME=$A44)*(UCA.AGROOTROS.DATE=H$5)*(UCA.AGROOTROS.VAL))} -> 0 | I44: {=SUMPRODUCT((UCA.AGROOTROS.NAME=$A44)*(UCA.AGROOTROS.DATE=I$5)*(UCA.AGROOTROS.VAL))} -> 0 | ... M44: {=SUMPRODUCT((UCA.AGROOTROS.NAME=$A44)*(UCA.AGROOTROS.DATE=M$5)*(UCA.AGROOTROS.VAL))} -> 3 | N44: =SUM(B44:M44) -> 39 | O44: {=SUMPRODUCT((UCA.AGROOTROS.NAME=$A44)*(UCA.AGROOTROS.DATE=O$5)*(UCA.AGROOTROS.VAL))} -> 0 | P44: {=SUMPRODUCT((UCA.AGROOTROS.NAME=$A44)*(UCA.AGROOTROS.DATE=P$5)*(UCA.AGROOTROS.VAL))} -> 7 | Q44: {=SUMPRODUCT((UCA.AGROOTROS.NAME=$A44)*(UCA.AGROOTROS.DATE=Q$5)*(UCA.AGROOTROS.VAL))} -> 7 | R44: {=SUMPRODUCT((UCA.AGROOTROS.NAME=$A44)*(UCA.AGROOTROS.DATE=R$5)*(UCA.AGROOTROS.VAL))} -> 0 | S44: {=SUMPRODUCT((UCA.AGROOTROS.NAME=$A44)*(UCA.AGROOTROS.DATE=S$5)*(UCA.AGROOTROS.VAL))} -> 0 | T44: {=SUMPRODUCT((UCA.AGROOTROS.NAME=$A44)*(UCA.AGROOTROS.DATE=T$5)*(UCA.AGROOTROS.VAL))} -> 0 | U44: {=SUMPRODUCT((UCA.AGROOTROS.NAME=$A44)*(UCA.AGROOTROS.DATE=U$5)*(UCA.AGROOTROS.VAL))} -> 0 | V44: {=SUMPRODUCT((UCA.AGROOTROS.NAME=$A44)*(UCA.AGROOTROS.DATE=V$5)*(UCA.AGROOTROS.VAL))} -> 0 | ... Z44: {=SUMPRODUCT((UCA.AGROOTROS.NAME=$A44)*(UCA.AGROOTROS.DATE=Z$5)*(UCA.AGROOTROS.VAL))} -> 0 | AA44: =SUM(O44:Z44) -> 20 | AB44: {=SUMPRODUCT((UCA.AGROOTROS.NAME=$A44)*(UCA.AGROOTROS.DATE=AB$5)*(UCA.AGROOTROS.VAL))} -> 0 | AC44: {=SUMPRODUCT((UCA.AGROOTROS.NAME=$A44)*(UCA.AGROOTROS.DATE=AC$5)*(UCA.AGROOTROS.VAL))} -> 0 | AD44: {=SUMPRODUCT((UCA.AGROOTROS.NAME=$A44)*(UCA.AGROOTROS.DATE=AD$5)*(UCA.AGROOTROS.VAL))} -> 0 | AE44: {=SUMPRODUCT((UCA.AGROOTROS.NAME=$A44)*(UCA.AGROOTROS.DATE=AE$5)*(UCA.AGROOTROS.VAL))} -> 0 | AF44: {=SUMPRODUCT((UCA.AGROOTROS.NAME=$A44)*(UCA.AGROOTROS.DATE=AF$5)*(UCA.AGROOTROS.VAL))} -> 0 | AG44: {=SUMPRODUCT((UCA.AGROOTROS.NAME=$A44)*(UCA.AGROOTROS.DATE=AG$5)*(UCA.AGROOTROS.VAL))} -> 0 | AH44: {=SUMPRODUCT((UCA.AGROOTROS.NAME=$A44)*(UCA.AGROOTROS.DATE=AH$5)*(UCA.AGROOTROS.VAL))} -> 0 | AI44: {=SUMPRODUCT((UCA.AGROOTROS.NAME=$A44)*(UCA.AGROOTROS.DATE=AI$5)*(UCA.AGROOTROS.VAL))} -> 0 | ... AM44: {=SUMPRODUCT((UCA.AGROOTROS.NAME=$A44)*(UCA.AGROOTROS.DATE=AM$5)*(UCA.AGROOTROS.VAL))} -> 0 | AN44: =SUM(AB44:AM44) -> 413 | AO44: {=SUMPRODUCT((UCA.AGROOTROS.NAME=$A44)*(UCA.AGROOTROS.DATE=AO$5)*(UCA.AGROOTROS.VAL))} -> 0 | AP44: {=SUMPRODUCT((UCA.AGROOTROS.NAME=$A44)*(UCA.AGROOTROS.DATE=AP$5)*(UCA.AGROOTROS.VAL))} -> 0 | AQ44: {=SUMPRODUCT((UCA.AGROOTROS.NAME=$A44)*(UCA.AGROOTROS.DATE=AQ$5)*(UCA.AGROOTROS.VAL))} -> 0 | AR44: {=SUMPRODUCT((UCA.AGROOTROS.NAME=$A44)*(UCA.AGROOTROS.DATE=AR$5)*(UCA.AGROOTROS.VAL))} -> 0 | AS44: {=SUMPRODUCT((UCA.AGROOTROS.NAME=$A44)*(UCA.AGROOTROS.DATE=AS$5)*(UCA.AGROOTROS.VAL))} -> 0 | AT44: {=SUMPRODUCT((UCA.AGROOTROS.NAME=$A44)*(UCA.AGROOTROS.DATE=AT$5)*(UCA.AGROOTROS.VAL))} -> 0 | AU44: {=SUMPRODUCT((UCA.AGROOTROS.NAME=$A44)*(UCA.AGROOTROS.DATE=AU$5)*(UCA.AGROOTROS.VAL))} -> 0 | AV44: {=SUMPRODUCT((UCA.AGROOTROS.NAME=$A44)*(UCA.AGROOTROS.DATE=AV$5)*(UCA.AGROOTROS.VAL))} -> 10 | ... AZ44: {=SUMPRODUCT((UCA.AGROOTROS.NAME=$A44)*(UCA.AGROOTROS.DATE=AZ$5)*(UCA.AGROOTROS.VAL))} -> 0 | BA44: =SUM(AO44:AZ44) -> 44 | BB44: {=SUMPRODUCT((UCA.AGROOTROS.NAME=$A44)*(UCA.AGROOTROS.DATE=BB$5)*(UCA.AGROOTROS.VAL))} -> 0 | BC44: {=SUMPRODUCT((UCA.AGROOTROS.NAME=$A44)*(UCA.AGROOTROS.DATE=BC$5)*(UCA.AGROOTROS.VAL))} -> 0 | BD44: {=SUMPRODUCT((UCA.AGROOTROS.NAME=$A44)*(UCA.AGROOTROS.DATE=BD$5)*(UCA.AGROOTROS.VAL))} -> 0 | BE44: {=SUMPRODUCT((UCA.AGROOTROS.NAME=$A44)*(UCA.AGROOTROS.DATE=BE$5)*(UCA.AGROOTROS.VAL))} -> 0 | BF44: {=SUMPRODUCT((UCA.AGROOTROS.NAME=$A44)*(UCA.AGROOTROS.DATE=BF$5)*(UCA.AGROOTROS.VAL))} -> 0 | BG44: {=SUMPRODUCT((UCA.AGROOTROS.NAME=$A44)*(UCA.AGROOTROS.DATE=BG$5)*(UCA.AGROOTROS.VAL))} -> 0 | BH44: {=SUMPRODUCT((UCA.AGROOTROS.NAME=$A44)*(UCA.AGROOTROS.DATE=BH$5)*(UCA.AGROOTROS.VAL))} -> 0 | BI44: {=SUMPRODUCT((UCA.AGROOTROS.NAME=$A44)*(UCA.AGROOTROS.DATE=BI$5)*(UCA.AGROOTROS.VAL))} -> 3 | ... BM44: {=SUMPRODUCT((UCA.AGROOTROS.NAME=$A44)*(UCA.AGROOTROS.DATE=BM$5)*(UCA.AGROOTROS.VAL))} -> 19 | BN44: =SUM(BB44:BM44) -> 85 | BO44: {=SUMPRODUCT((UCA.AGROOTROS.NAME=$A44)*(UCA.AGROOTROS.DATE=BO$5)*(UCA.AGROOTROS.VAL))} -> 12 | BP44: {=SUMPRODUCT((UCA.AGROOTROS.NAME=$A44)*(UCA.AGROOTROS.DATE=BP$5)*(UCA.AGROOTROS.VAL))} -> 0 | BQ44: {=SUMPRODUCT((UCA.AGROOTROS.NAME=$A44)*(UCA.AGROOTROS.DATE=BQ$5)*(UCA.AGROOTROS.VAL))} -> 3 | BR44: {=SUMPRODUCT((UCA.AGROOTROS.NAME=$A44)*(UCA.AGROOTROS.DATE=BR$5)*(UCA.AGROOTROS.VAL))} -> 0 | BS44: {=SUMPRODUCT((UCA.AGROOTROS.NAME=$A44)*(UCA.AGROOTROS.DATE=BS$5)*(UCA.AGROOTROS.VAL))} -> 2.98 | BT44: {=SUMPRODUCT((UCA.AGROOTROS.NAME=$A44)*(UCA.AGROOTROS.DATE=BT$5)*(UCA.AGROOTROS.VAL))} -> 0 | BU44: {=SUMPRODUCT((UCA.AGROOTROS.NAME=$A44)*(UCA.AGROOTROS.DATE=BU$5)*(UCA.AGROOTROS.VAL))} -> 0 | BV44: {=SUMPRODUCT((UCA.AGROOTROS.NAME=$A44)*(UCA.AGROOTROS.DATE=BV$5)*(UCA.AGROOTROS.VAL))} -> 5 | ... BZ44: {=SUMPRODUCT((UCA.AGROOTROS.NAME=$A44)*(UCA.AGROOTROS.DATE=BZ$5)*(UCA.AGROOTROS.VAL))} -> 0 | CA44: =SUM(BO44:BZ44) -> 61.98 | CB44: {=SUMPRODUCT((UCA.AGROOTROS.NAME=$A44)*(UCA.AGROOTROS.DATE=CB$5)*(UCA.AGROOTROS.VAL))} -> 9.81 | CC44: {=SUMPRODUCT((UCA.AGROOTROS.NAME=$A44)*(UCA.AGROOTROS.DATE=CC$5)*(UCA.AGROOTROS.VAL))} -> 1.57 | CD44: {=SUMPRODUCT((UCA.AGROOTROS.NAME=$A44)*(UCA.AGROOTROS.DATE=CD$5)*(UCA.AGROOTROS.VAL))} -> 9.27 | CE44: {=SUMPRODUCT((UCA.AGROOTROS.NAME=$A44)*(UCA.AGROOTROS.DATE=CE$5)*(UCA.AGROOTROS.VAL))} -> 9.099 | CF44: {=SUMPRODUCT((UCA.AGROOTROS.NAME=$A44)*(UCA.AGROOTROS.DATE=CF$5)*(UCA.AGROOTROS.VAL))} -> 9.389 | CG44: {=SUMPRODUCT((UCA.AGROOTROS.NAME=$A44)*(UCA.AGROOTROS.DATE=CG$5)*(UCA.AGROOTROS.VAL))} -> 1.52 | CH44: {=SUMPRODUCT((UCA.AGROOTROS.NAME=$A44)*(UCA.AGROOTROS.DATE=CH$5)*(UCA.AGROOTROS.VAL))} -> 13.529 | CI44: {=SUMPRODUCT((UCA.AGROOTROS.NAME=$A44)*(UCA.AGROOTROS.DATE=CI$5)*(UCA.AGROOTROS.VAL))} -> 54.78 | ... CM44: {=SUMPRODUCT((UCA.AGROOTROS.NAME=$A44)*(UCA.AGROOTROS.DATE=CM$5)*(UCA.AGROOTROS.VAL))} -> 13.1 | CN44: =SUM(CB44:CM44) -> 216.747 | CO44: {=SUMPRODUCT((UCA.AGROOTROS.NAME=$A44)*(UCA.AGROOTROS.DATE=CO$5)*(UCA.AGROOTROS.VAL))} -> 15.69 | CP44: {=SUMPRODUCT((UCA.AGROOTROS.NAME=$A44)*(UCA.AGROOTROS.DATE=CP$5)*(UCA.AGROOTROS.VAL))} -> 0 | CQ44: {=SUMPRODUCT((UCA.AGROOTROS.NAME=$A44)*(UCA.AGROOTROS.DATE=CQ$5)*(UCA.AGROOTROS.VAL))} -> 12.019 | CR44: {=SUMPRODUCT((UCA.AGROOTROS.NAME=$A44)*(UCA.AGROOTROS.DATE=CR$5)*(UCA.AGROOTROS.VAL))} -> 0 | CS44: {=SUMPRODUCT((UCA.AGROOTROS.NAME=$A44)*(UCA.AGROOTROS.DATE=CS$5)*(UCA.AGROOTROS.VAL))} -> 0 | CT44: {=SUMPRODUCT((UCA.AGROOTROS.NAME=$A44)*(UCA.AGROOTROS.DATE=CT$5)*(UCA.AGROOTROS.VAL))} -> 0 | CU44: {=SUMPRODUCT((UCA.AGROOTROS.NAME=$A44)*(UCA.AGROOTROS.DATE=CU$5)*(UCA.AGROOTROS.VAL))} -> 0 | CV44: {=SUMPRODUCT((UCA.AGROOTROS.NAME=$A44)*(UCA.AGROOTROS.DATE=CV$5)*(UCA.AGROOTROS.VAL))} -> 4.86 | ... CZ44: {=SUMPRODUCT((UCA.AGROOTROS.NAME=$A44)*(UCA.AGROOTROS.DATE=CZ$5)*(UCA.AGROOTROS.VAL))} -> 32.47 | DA44: =SUM(CO44:CZ44) -> 129.988 | DB44: {=SUMPRODUCT((UCA.AGROOTROS.NAME=$A44)*(UCA.AGROOTROS.DATE=DB$5)*(UCA.AGROOTROS.VAL))} -> 42.1 | DC44: {=SUMPRODUCT((UCA.AGROOTROS.NAME=$A44)*(UCA.AGROOTROS.DATE=DC$5)*(UCA.AGROOTROS.VAL))} -> 19.33 | DD44: {=SUMPRODUCT((UCA.AGROOTROS.NAME=$A44)*(UCA.AGROOTROS.DATE=DD$5)*(UCA.AGROOTROS.VAL))} -> 792.54 | DE44: {=SUMPRODUCT((UCA.AGROOTROS.NAME=$A44)*(UCA.AGROOTROS.DATE=DE$5)*(UCA.AGROOTROS.VAL))} -> 0 | DF44: {=SUMPRODUCT((UCA.AGROOTROS.NAME=$A44)*(UCA.AGROOTROS.DATE=DF$5)*(UCA.AGROOTROS.VAL))} -> 0 | DG44: {=SUMPRODUCT((UCA.AGROOTROS.NAME=$A44)*(UCA.AGROOTROS.DATE=DG$5)*(UCA.AGROOTROS.VAL))} -> 0 | DH44: {=SUMPRODUCT((UCA.AGROOTROS.NAME=$A44)*(UCA.AGROOTROS.DATE=DH$5)*(UCA.AGROOTROS.VAL))} -> 0 | DI44: {=SUMPRODUCT((UCA.AGROOTROS.NAME=$A44)*(UCA.AGROOTROS.DATE=DI$5)*(UCA.AGROOTROS.VAL))} -> 34.36 | ... DM44: {=SUMPRODUCT((UCA.AGROOTROS.NAME=$A44)*(UCA.AGROOTROS.DATE=DM$5)*(UCA.AGROOTROS.VAL))} -> 0 | DN44: =SUM(DB44:DM44) -> 1239.15 | DO44: {=SUMPRODUCT((UCA.AGROOTROS.NAME=$A44)*(UCA.AGROOTROS.DATE=DO$5)*(UCA.AGROOTROS.VAL))} -> 0 | DP44: {=SUMPRODUCT((UCA.AGROOTROS.NAME=$A44)*(UCA.AGROOTROS.DATE=DP$5)*(UCA.AGROOTROS.VAL))} -> 0 | DQ44: {=SUMPRODUCT((UCA.AGROOTROS.NAME=$A44)*(UCA.AGROOTROS.DATE=DQ$5)*(UCA.AGROOTROS.VAL))} -> 0 | DR44: {=SUMPRODUCT((UCA.AGROOTROS.NAME=$A44)*(UCA.AGROOTROS.DATE=DR$5)*(UCA.AGROOTROS.VAL))} -> 0 | DS44: {=SUMPRODUCT((UCA.AGROOTROS.NAME=$A44)*(UCA.AGROOTROS.DATE=DS$5)*(UCA.AGROOTROS.VAL))} -> 0 | DT44: {=SUMPRODUCT((UCA.AGROOTROS.NAME=$A44)*(UCA.AGROOTROS.DATE=DT$5)*(UCA.AGROOTROS.VAL))} -> 0 | DU44: {=SUMPRODUCT((UCA.AGROOTROS.NAME=$A44)*(UCA.AGROOTROS.DATE=DU$5)*(UCA.AGROOTROS.VAL))} -> 0 | DV44: {=SUMPRODUCT((UCA.AGROOTROS.NAME=$A44)*(UCA.AGROOTROS.DATE=DV$5)*(UCA.AGROOTROS.VAL))} -> 114.42 | ... DZ44: {=SUMPRODUCT((UCA.AGROOTROS.NAME=$A44)*(UCA.AGROOTROS.DATE=DZ$5)*(UCA.AGROOTROS.VAL))} -> 28.858 | EA44: =SUM(DO44:DZ44) -> 436.496 | EB44: {=SUMPRODUCT((UCA.AGROOTROS.NAME=$A44)*(UCA.AGROOTROS.DATE=EB$5)*(UCA.AGROOTROS.VAL))} -> 28.169 | EC44: {=SUMPRODUCT((UCA.AGROOTROS.NAME=$A44)*(UCA.AGROOTROS.DATE=EC$5)*(UCA.AGROOTROS.VAL))} -> 3.14 | ED44: {=SUMPRODUCT((UCA.AGROOTROS.NAME=$A44)*(UCA.AGROOTROS.DATE=ED$5)*(UCA.AGROOTROS.VAL))} -> 0 | EE44: {=SUMPRODUCT((UCA.AGROOTROS.NAME=$A44)*(UCA.AGROOTROS.DATE=EE$5)*(UCA.AGROOTROS.VAL))} -> 0 | EF44: {=SUMPRODUCT((UCA.AGROOTROS.NAME=$A44)*(UCA.AGROOTROS.DATE=EF$5)*(UCA.AGROOTROS.VAL))} -> 0 | EG44: {=SUMPRODUCT((UCA.AGROOTROS.NAME=$A44)*(UCA.AGROOTROS.DATE=EG$5)*(UCA.AGROOTROS.VAL))} -> 0 | EH44: {=SUMPRODUCT((UCA.AGROOTROS.NAME=$A44)*(UCA.AGROOTROS.DATE=EH$5)*(UCA.AGROOTROS.VAL))} -> 0 | EI44: {=SUMPRODUCT((UCA.AGROOTROS.NAME=$A44)*(UCA.AGROOTROS.DATE=EI$5)*(UCA.AGROOTROS.VAL))} -> 0 | ... EM44: {=SUMPRODUCT((UCA.AGROOTROS.NAME=$A44)*(UCA.AGROOTROS.DATE=EM$5)*(UCA.AGROOTROS.VAL))} -> 14.42 | EN44: =SUM(EB44:EM44) -> 254.958 | EO44: {=SUMPRODUCT((UCA.AGROOTROS.NAME=$A44)*(UCA.AGROOTROS.DATE=EO$5)*(UCA.AGROOTROS.VAL))} -> 23.18 | EP44: {=SUMPRODUCT((UCA.AGROOTROS.NAME=$A44)*(UCA.AGROOTROS.DATE=EP$5)*(UCA.AGROOTROS.VAL))} -> 23.18 | EQ44: {=SUMPRODUCT((UCA.AGROOTROS.NAME=$A44)*(UCA.AGROOTROS.DATE=EQ$5)*(UCA.AGROOTROS.VAL))} -> 0 | ER44: {=SUMPRODUCT((UCA.AGROOTROS.NAME=$A44)*(UCA.AGROOTROS.DATE=ER$5)*(UCA.AGROOTROS.VAL))} -> 0 | ES44: {=SUMPRODUCT((UCA.AGROOTROS.NAME=$A44)*(UCA.AGROOTROS.DATE=ES$5)*(UCA.AGROOTROS.VAL))} -> 0 | ET44: {=SUMPRODUCT((UCA.AGROOTROS.NAME=$A44)*(UCA.AGROOTROS.DATE=ET$5)*(UCA.AGROOTROS.VAL))} -> 0 | EU44: {=SUMPRODUCT((UCA.AGROOTROS.NAME=$A44)*(UCA.AGROOTROS.DATE=EU$5)*(UCA.AGROOTROS.VAL))} -> 0 | EV44: {=SUMPRODUCT((UCA.AGROOTROS.NAME=$A44)*(UCA.AGROOTROS.DATE=EV$5)*(UCA.AGROOTROS.VAL))} -> 0 | ... EZ44: {=SUMPRODUCT((UCA.AGROOTROS.NAME=$A44)*(UCA.AGROOTROS.DATE=EZ$5)*(UCA.AGROOTROS.VAL))} -> 0 | FA44: =SUM(EO44:EZ44) -> 46.36 | FC44: =IFERROR((( _xlfn.XLOOKUP((DATE(YEAR($FC$5),MONTH($FC$5),1)),UCA.AGRO.DATE,$B44:$FA44) / _xlfn.XLOOKUP((DATE(YEAR($FC$5)-1,MONTH($FC$5),1)),UCA.AGRO.DATE,$B44:$FA44) )-1)*100,"") -> -49.583796 | FD44: =IFERROR(((FF44/FE44)-1)*100,"") -> -40.992253 | FE44: =SUMIFS($B44:$FA44,UCA.AGRO.DATE,">="&DATE(YEAR($FC$5)-1,1,1),UCA.AGRO.DATE,"<="&DATE(YEAR($FC$5)-1,MONTH($FC$5),1)) -> 407.638 | FF44: =SUMIFS($B44:$FA44,UCA.AGRO.DATE,">="&DATE(YEAR($FC$5),1,1),UCA.AGRO.DATE,"<="&$FC$5) -> 240.538 | FH44: =SUM(B44:FA44) -> 5973.358 | FJ44: =IF(EXACT(A44,FI44)=TRUE,"OK","VER") -> VER
A45: Ungurahui | B45: {=SUMPRODUCT((UCA.AGROOTROS.NAME=$A45)*(UCA.AGROOTROS.DATE=B$5)*(UCA.AGROOTROS.VAL))} -> 577 | C45: {=SUMPRODUCT((UCA.AGROOTROS.NAME=$A45)*(UCA.AGROOTROS.DATE=C$5)*(UCA.AGROOTROS.VAL))} -> 645 | D45: {=SUMPRODUCT((UCA.AGROOTROS.NAME=$A45)*(UCA.AGROOTROS.DATE=D$5)*(UCA.AGROOTROS.VAL))} -> 544 | E45: {=SUMPRODUCT((UCA.AGROOTROS.NAME=$A45)*(UCA.AGROOTROS.DATE=E$5)*(UCA.AGROOTROS.VAL))} -> 324 | F45: {=SUMPRODUCT((UCA.AGROOTROS.NAME=$A45)*(UCA.AGROOTROS.DATE=F$5)*(UCA.AGROOTROS.VAL))} -> 306 | G45: {=SUMPRODUCT((UCA.AGROOTROS.NAME=$A45)*(UCA.AGROOTROS.DATE=G$5)*(UCA.AGROOTROS.VAL))} -> 203 | H45: {=SUMPRODUCT((UCA.AGROOTROS.NAME=$A45)*(UCA.AGROOTROS.DATE=H$5)*(UCA.AGROOTROS.VAL))} -> 198 | I45: {=SUMPRODUCT((UCA.AGROOTROS.NAME=$A45)*(UCA.AGROOTROS.DATE=I$5)*(UCA.AGROOTROS.VAL))} -> 150 | ... M45: {=SUMPRODUCT((UCA.AGROOTROS.NAME=$A45)*(UCA.AGROOTROS.DATE=M$5)*(UCA.AGROOTROS.VAL))} -> 302 | N45: =SUM(B45:M45) -> 3498 | O45: {=SUMPRODUCT((UCA.AGROOTROS.NAME=$A45)*(UCA.AGROOTROS.DATE=O$5)*(UCA.AGROOTROS.VAL))} -> 509 | P45: {=SUMPRODUCT((UCA.AGROOTROS.NAME=$A45)*(UCA.AGROOTROS.DATE=P$5)*(UCA.AGROOTROS.VAL))} -> 641 | Q45: {=SUMPRODUCT((UCA.AGROOTROS.NAME=$A45)*(UCA.AGROOTROS.DATE=Q$5)*(UCA.AGROOTROS.VAL))} -> 633 | R45: {=SUMPRODUCT((UCA.AGROOTROS.NAME=$A45)*(UCA.AGROOTROS.DATE=R$5)*(UCA.AGROOTROS.VAL))} -> 428 | S45: {=SUMPRODUCT((UCA.AGROOTROS.NAME=$A45)*(UCA.AGROOTROS.DATE=S$5)*(UCA.AGROOTROS.VAL))} -> 341 | T45: {=SUMPRODUCT((UCA.AGROOTROS.NAME=$A45)*(UCA.AGROOTROS.DATE=T$5)*(UCA.AGROOTROS.VAL))} -> 211 | U45: {=SUMPRODUCT((UCA.AGROOTROS.NAME=$A45)*(UCA.AGROOTROS.DATE=U$5)*(UCA.AGROOTROS.VAL))} -> 176 | V45: {=SUMPRODUCT((UCA.AGROOTROS.NAME=$A45)*(UCA.AGROOTROS.DATE=V$5)*(UCA.AGROOTROS.VAL))} -> 122 | ... Z45: {=SUMPRODUCT((UCA.AGROOTROS.NAME=$A45)*(UCA.AGROOTROS.DATE=Z$5)*(UCA.AGROOTROS.VAL))} -> 358 | AA45: =SUM(O45:Z45) -> 3707 | AB45: {=SUMPRODUCT((UCA.AGROOTROS.NAME=$A45)*(UCA.AGROOTROS.DATE=AB$5)*(UCA.AGROOTROS.VAL))} -> 516 | AC45: {=SUMPRODUCT((UCA.AGROOTROS.NAME=$A45)*(UCA.AGROOTROS.DATE=AC$5)*(UCA.AGROOTROS.VAL))} -> 572 | AD45: {=SUMPRODUCT((UCA.AGROOTROS.NAME=$A45)*(UCA.AGROOTROS.DATE=AD$5)*(UCA.AGROOTROS.VAL))} -> 606 | AE45: {=SUMPRODUCT((UCA.AGROOTROS.NAME=$A45)*(UCA.AGROOTROS.DATE=AE$5)*(UCA.AGROOTROS.VAL))} -> 499 | AF45: {=SUMPRODUCT((UCA.AGROOTROS.NAME=$A45)*(UCA.AGROOTROS.DATE=AF$5)*(UCA.AGROOTROS.VAL))} -> 419 | AG45: {=SUMPRODUCT((UCA.AGROOTROS.NAME=$A45)*(UCA.AGROOTROS.DATE=AG$5)*(UCA.AGROOTROS.VAL))} -> 238 | AH45: {=SUMPRODUCT((UCA.AGROOTROS.NAME=$A45)*(UCA.AGROOTROS.DATE=AH$5)*(UCA.AGROOTROS.VAL))} -> 203 | AI45: {=SUMPRODUCT((UCA.AGROOTROS.NAME=$A45)*(UCA.AGROOTROS.DATE=AI$5)*(UCA.AGROOTROS.VAL))} -> 138 | ... AM45: {=SUMPRODUCT((UCA.AGROOTROS.NAME=$A45)*(UCA.AGROOTROS.DATE=AM$5)*(UCA.AGROOTROS.VAL))} -> 419 | AN45: =SUM(AB45:AM45) -> 3971 | AO45: {=SUMPRODUCT((UCA.AGROOTROS.NAME=$A45)*(UCA.AGROOTROS.DATE=AO$5)*(UCA.AGROOTROS.VAL))} -> 473 | AP45: {=SUMPRODUCT((UCA.AGROOTROS.NAME=$A45)*(UCA.AGROOTROS.DATE=AP$5)*(UCA.AGROOTROS.VAL))} -> 619 | AQ45: {=SUMPRODUCT((UCA.AGROOTROS.NAME=$A45)*(UCA.AGROOTROS.DATE=AQ$5)*(UCA.AGROOTROS.VAL))} -> 676 | AR45: {=SUMPRODUCT((UCA.AGROOTROS.NAME=$A45)*(UCA.AGROOTROS.DATE=AR$5)*(UCA.AGROOTROS.VAL))} -> 548 | AS45: {=SUMPRODUCT((UCA.AGROOTROS.NAME=$A45)*(UCA.AGROOTROS.DATE=AS$5)*(UCA.AGROOTROS.VAL))} -> 456 | AT45: {=SUMPRODUCT((UCA.AGROOTROS.NAME=$A45)*(UCA.AGROOTROS.DATE=AT$5)*(UCA.AGROOTROS.VAL))} -> 276 | AU45: {=SUMPRODUCT((UCA.AGROOTROS.NAME=$A45)*(UCA.AGROOTROS.DATE=AU$5)*(UCA.AGROOTROS.VAL))} -> 219 | AV45: {=SUMPRODUCT((UCA.AGROOTROS.NAME=$A45)*(UCA.AGROOTROS.DATE=AV$5)*(UCA.AGROOTROS.VAL))} -> 114 | ... AZ45: {=SUMPRODUCT((UCA.AGROOTROS.NAME=$A45)*(UCA.AGROOTROS.DATE=AZ$5)*(UCA.AGROOTROS.VAL))} -> 324 | BA45: =SUM(AO45:AZ45) -> 3955 | BB45: {=SUMPRODUCT((UCA.AGROOTROS.NAME=$A45)*(UCA.AGROOTROS.DATE=BB$5)*(UCA.AGROOTROS.VAL))} -> 439 | BC45: {=SUMPRODUCT((UCA.AGROOTROS.NAME=$A45)*(UCA.AGROOTROS.DATE=BC$5)*(UCA.AGROOTROS.VAL))} -> 625 | BD45: {=SUMPRODUCT((UCA.AGROOTROS.NAME=$A45)*(UCA.AGROOTROS.DATE=BD$5)*(UCA.AGROOTROS.VAL))} -> 660 | BE45: {=SUMPRODUCT((UCA.AGROOTROS.NAME=$A45)*(UCA.AGROOTROS.DATE=BE$5)*(UCA.AGROOTROS.VAL))} -> 552 | BF45: {=SUMPRODUCT((UCA.AGROOTROS.NAME=$A45)*(UCA.AGROOTROS.DATE=BF$5)*(UCA.AGROOTROS.VAL))} -> 465 | BG45: {=SUMPRODUCT((UCA.AGROOTROS.NAME=$A45)*(UCA.AGROOTROS.DATE=BG$5)*(UCA.AGROOTROS.VAL))} -> 300 | BH45: {=SUMPRODUCT((UCA.AGROOTROS.NAME=$A45)*(UCA.AGROOTROS.DATE=BH$5)*(UCA.AGROOTROS.VAL))} -> 254 | BI45: {=SUMPRODUCT((UCA.AGROOTROS.NAME=$A45)*(UCA.AGROOTROS.DATE=BI$5)*(UCA.AGROOTROS.VAL))} -> 128 | ... BM45: {=SUMPRODUCT((UCA.AGROOTROS.NAME=$A45)*(UCA.AGROOTROS.DATE=BM$5)*(UCA.AGROOTROS.VAL))} -> 312 | BN45: =SUM(BB45:BM45) -> 3913 | BO45: {=SUMPRODUCT((UCA.AGROOTROS.NAME=$A45)*(UCA.AGROOTROS.DATE=BO$5)*(UCA.AGROOTROS.VAL))} -> 450 | BP45: {=SUMPRODUCT((UCA.AGROOTROS.NAME=$A45)*(UCA.AGROOTROS.DATE=BP$5)*(UCA.AGROOTROS.VAL))} -> 669 | BQ45: {=SUMPRODUCT((UCA.AGROOTROS.NAME=$A45)*(UCA.AGROOTROS.DATE=BQ$5)*(UCA.AGROOTROS.VAL))} -> 671 | BR45: {=SUMPRODUCT((UCA.AGROOTROS.NAME=$A45)*(UCA.AGROOTROS.DATE=BR$5)*(UCA.AGROOTROS.VAL))} -> 584 | BS45: {=SUMPRODUCT((UCA.AGROOTROS.NAME=$A45)*(UCA.AGROOTROS.DATE=BS$5)*(UCA.AGROOTROS.VAL))} -> 511 | BT45: {=SUMPRODUCT((UCA.AGROOTROS.NAME=$A45)*(UCA.AGROOTROS.DATE=BT$5)*(UCA.AGROOTROS.VAL))} -> 323 | BU45: {=SUMPRODUCT((UCA.AGROOTROS.NAME=$A45)*(UCA.AGROOTROS.DATE=BU$5)*(UCA.AGROOTROS.VAL))} -> 293 | BV45: {=SUMPRODUCT((UCA.AGROOTROS.NAME=$A45)*(UCA.AGROOTROS.DATE=BV$5)*(UCA.AGROOTROS.VAL))} -> 122 | ... BZ45: {=SUMPRODUCT((UCA.AGROOTROS.NAME=$A45)*(UCA.AGROOTROS.DATE=BZ$5)*(UCA.AGROOTROS.VAL))} -> 380 | CA45: =SUM(BO45:BZ45) -> 4186 | CB45: {=SUMPRODUCT((UCA.AGROOTROS.NAME=$A45)*(UCA.AGROOTROS.DATE=CB$5)*(UCA.AGROOTROS.VAL))} -> 477.39 | CC45: {=SUMPRODUCT((UCA.AGROOTROS.NAME=$A45)*(UCA.AGROOTROS.DATE=CC$5)*(UCA.AGROOTROS.VAL))} -> 693.948 | CD45: {=SUMPRODUCT((UCA.AGROOTROS.NAME=$A45)*(UCA.AGROOTROS.DATE=CD$5)*(UCA.AGROOTROS.VAL))} -> 720.049 | CE45: {=SUMPRODUCT((UCA.AGROOTROS.NAME=$A45)*(UCA.AGROOTROS.DATE=CE$5)*(UCA.AGROOTROS.VAL))} -> 703.169 | CF45: {=SUMPRODUCT((UCA.AGROOTROS.NAME=$A45)*(UCA.AGROOTROS.DATE=CF$5)*(UCA.AGROOTROS.VAL))} -> 607.429 | CG45: {=SUMPRODUCT((UCA.AGROOTROS.NAME=$A45)*(UCA.AGROOTROS.DATE=CG$5)*(UCA.AGROOTROS.VAL))} -> 371.56 | CH45: {=SUMPRODUCT((UCA.AGROOTROS.NAME=$A45)*(UCA.AGROOTROS.DATE=CH$5)*(UCA.AGROOTROS.VAL))} -> 348.879 | CI45: {=SUMPRODUCT((UCA.AGROOTROS.NAME=$A45)*(UCA.AGROOTROS.DATE=CI$5)*(UCA.AGROOTROS.VAL))} -> 167.19 | ... CM45: {=SUMPRODUCT((UCA.AGROOTROS.NAME=$A45)*(UCA.AGROOTROS.DATE=CM$5)*(UCA.AGROOTROS.VAL))} -> 459.13 | CN45: =SUM(CB45:CM45) -> 4825.014 | CO45: {=SUMPRODUCT((UCA.AGROOTROS.NAME=$A45)*(UCA.AGROOTROS.DATE=CO$5)*(UCA.AGROOTROS.VAL))} -> 511.56 | CP45: {=SUMPRODUCT((UCA.AGROOTROS.NAME=$A45)*(UCA.AGROOTROS.DATE=CP$5)*(UCA.AGROOTROS.VAL))} -> 679.809 | CQ45: {=SUMPRODUCT((UCA.AGROOTROS.NAME=$A45)*(UCA.AGROOTROS.DATE=CQ$5)*(UCA.AGROOTROS.VAL))} -> 659.649 | CR45: {=SUMPRODUCT((UCA.AGROOTROS.NAME=$A45)*(UCA.AGROOTROS.DATE=CR$5)*(UCA.AGROOTROS.VAL))} -> 600.69 | CS45: {=SUMPRODUCT((UCA.AGROOTROS.NAME=$A45)*(UCA.AGROOTROS.DATE=CS$5)*(UCA.AGROOTROS.VAL))} -> 545.648 | CT45: {=SUMPRODUCT((UCA.AGROOTROS.NAME=$A45)*(UCA.AGROOTROS.DATE=CT$5)*(UCA.AGROOTROS.VAL))} -> 356.75 | CU45: {=SUMPRODUCT((UCA.AGROOTROS.NAME=$A45)*(UCA.AGROOTROS.DATE=CU$5)*(UCA.AGROOTROS.VAL))} -> 367.61 | CV45: {=SUMPRODUCT((UCA.AGROOTROS.NAME=$A45)*(UCA.AGROOTROS.DATE=CV$5)*(UCA.AGROOTROS.VAL))} -> 206.82 | ... CZ45: {=SUMPRODUCT((UCA.AGROOTROS.NAME=$A45)*(UCA.AGROOTROS.DATE=CZ$5)*(UCA.AGROOTROS.VAL))} -> 436.57 | DA45: =SUM(CO45:CZ45) -> 4590.976 | DB45: {=SUMPRODUCT((UCA.AGROOTROS.NAME=$A45)*(UCA.AGROOTROS.DATE=DB$5)*(UCA.AGROOTROS.VAL))} -> 520.277 | DC45: {=SUMPRODUCT((UCA.AGROOTROS.NAME=$A45)*(UCA.AGROOTROS.DATE=DC$5)*(UCA.AGROOTROS.VAL))} -> 461.87 | DD45: {=SUMPRODUCT((UCA.AGROOTROS.NAME=$A45)*(UCA.AGROOTROS.DATE=DD$5)*(UCA.AGROOTROS.VAL))} -> 433.64 | DE45: {=SUMPRODUCT((UCA.AGROOTROS.NAME=$A45)*(UCA.AGROOTROS.DATE=DE$5)*(UCA.AGROOTROS.VAL))} -> 283.179 | DF45: {=SUMPRODUCT((UCA.AGROOTROS.NAME=$A45)*(UCA.AGROOTROS.DATE=DF$5)*(UCA.AGROOTROS.VAL))} -> 221.409 | DG45: {=SUMPRODUCT((UCA.AGROOTROS.NAME=$A45)*(UCA.AGROOTROS.DATE=DG$5)*(UCA.AGROOTROS.VAL))} -> 202.888 | DH45: {=SUMPRODUCT((UCA.AGROOTROS.NAME=$A45)*(UCA.AGROOTROS.DATE=DH$5)*(UCA.AGROOTROS.VAL))} -> 190.79 | DI45: {=SUMPRODUCT((UCA.AGROOTROS.NAME=$A45)*(UCA.AGROOTROS.DATE=DI$5)*(UCA.AGROOTROS.VAL))} -> 57.3 | ... DM45: {=SUMPRODUCT((UCA.AGROOTROS.NAME=$A45)*(UCA.AGROOTROS.DATE=DM$5)*(UCA.AGROOTROS.VAL))} -> 193.439 | DN45: =SUM(DB45:DM45) -> 2681.872 | DO45: {=SUMPRODUCT((UCA.AGROOTROS.NAME=$A45)*(UCA.AGROOTROS.DATE=DO$5)*(UCA.AGROOTROS.VAL))} -> 242.669 | DP45: {=SUMPRODUCT((UCA.AGROOTROS.NAME=$A45)*(UCA.AGROOTROS.DATE=DP$5)*(UCA.AGROOTROS.VAL))} -> 223.019 | DQ45: {=SUMPRODUCT((UCA.AGROOTROS.NAME=$A45)*(UCA.AGROOTROS.DATE=DQ$5)*(UCA.AGROOTROS.VAL))} -> 183.218 | DR45: {=SUMPRODUCT((UCA.AGROOTROS.NAME=$A45)*(UCA.AGROOTROS.DATE=DR$5)*(UCA.AGROOTROS.VAL))} -> 168.839 | DS45: {=SUMPRODUCT((UCA.AGROOTROS.NAME=$A45)*(UCA.AGROOTROS.DATE=DS$5)*(UCA.AGROOTROS.VAL))} -> 155.679 | DT45: {=SUMPRODUCT((UCA.AGROOTROS.NAME=$A45)*(UCA.AGROOTROS.DATE=DT$5)*(UCA.AGROOTROS.VAL))} -> 130.09 | DU45: {=SUMPRODUCT((UCA.AGROOTROS.NAME=$A45)*(UCA.AGROOTROS.DATE=DU$5)*(UCA.AGROOTROS.VAL))} -> 121.23 | DV45: {=SUMPRODUCT((UCA.AGROOTROS.NAME=$A45)*(UCA.AGROOTROS.DATE=DV$5)*(UCA.AGROOTROS.VAL))} -> 55.35 | ... DZ45: {=SUMPRODUCT((UCA.AGROOTROS.NAME=$A45)*(UCA.AGROOTROS.DATE=DZ$5)*(UCA.AGROOTROS.VAL))} -> 156.878 | EA45: =SUM(DO45:DZ45) -> 1523.322 | EB45: {=SUMPRODUCT((UCA.AGROOTROS.NAME=$A45)*(UCA.AGROOTROS.DATE=EB$5)*(UCA.AGROOTROS.VAL))} -> 191.079 | EC45: {=SUMPRODUCT((UCA.AGROOTROS.NAME=$A45)*(UCA.AGROOTROS.DATE=EC$5)*(UCA.AGROOTROS.VAL))} -> 195.34 | ED45: {=SUMPRODUCT((UCA.AGROOTROS.NAME=$A45)*(UCA.AGROOTROS.DATE=ED$5)*(UCA.AGROOTROS.VAL))} -> 179.587 | EE45: {=SUMPRODUCT((UCA.AGROOTROS.NAME=$A45)*(UCA.AGROOTROS.DATE=EE$5)*(UCA.AGROOTROS.VAL))} -> 142.073 | EF45: {=SUMPRODUCT((UCA.AGROOTROS.NAME=$A45)*(UCA.AGROOTROS.DATE=EF$5)*(UCA.AGROOTROS.VAL))} -> 126.659 | EG45: {=SUMPRODUCT((UCA.AGROOTROS.NAME=$A45)*(UCA.AGROOTROS.DATE=EG$5)*(UCA.AGROOTROS.VAL))} -> 89.779 | EH45: {=SUMPRODUCT((UCA.AGROOTROS.NAME=$A45)*(UCA.AGROOTROS.DATE=EH$5)*(UCA.AGROOTROS.VAL))} -> 82.8 | EI45: {=SUMPRODUCT((UCA.AGROOTROS.NAME=$A45)*(UCA.AGROOTROS.DATE=EI$5)*(UCA.AGROOTROS.VAL))} -> 37.38 | ... EM45: {=SUMPRODUCT((UCA.AGROOTROS.NAME=$A45)*(UCA.AGROOTROS.DATE=EM$5)*(UCA.AGROOTROS.VAL))} -> 0 | EN45: =SUM(EB45:EM45) -> 1133.826 | EO45: {=SUMPRODUCT((UCA.AGROOTROS.NAME=$A45)*(UCA.AGROOTROS.DATE=EO$5)*(UCA.AGROOTROS.VAL))} -> 0 | EP45: {=SUMPRODUCT((UCA.AGROOTROS.NAME=$A45)*(UCA.AGROOTROS.DATE=EP$5)*(UCA.AGROOTROS.VAL))} -> 0 | EQ45: {=SUMPRODUCT((UCA.AGROOTROS.NAME=$A45)*(UCA.AGROOTROS.DATE=EQ$5)*(UCA.AGROOTROS.VAL))} -> 0 | ER45: {=SUMPRODUCT((UCA.AGROOTROS.NAME=$A45)*(UCA.AGROOTROS.DATE=ER$5)*(UCA.AGROOTROS.VAL))} -> 0 | ES45: {=SUMPRODUCT((UCA.AGROOTROS.NAME=$A45)*(UCA.AGROOTROS.DATE=ES$5)*(UCA.AGROOTROS.VAL))} -> 0 | ET45: {=SUMPRODUCT((UCA.AGROOTROS.NAME=$A45)*(UCA.AGROOTROS.DATE=ET$5)*(UCA.AGROOTROS.VAL))} -> 0 | EU45: {=SUMPRODUCT((UCA.AGROOTROS.NAME=$A45)*(UCA.AGROOTROS.DATE=EU$5)*(UCA.AGROOTROS.VAL))} -> 0 | EV45: {=SUMPRODUCT((UCA.AGROOTROS.NAME=$A45)*(UCA.AGROOTROS.DATE=EV$5)*(UCA.AGROOTROS.VAL))} -> 0 | ... EZ45: {=SUMPRODUCT((UCA.AGROOTROS.NAME=$A45)*(UCA.AGROOTROS.DATE=EZ$5)*(UCA.AGROOTROS.VAL))} -> 0 | FA45: =SUM(EO45:EZ45) -> 0 | FC45: =IFERROR((( _xlfn.XLOOKUP((DATE(YEAR($FC$5),MONTH($FC$5),1)),UCA.AGRO.DATE,$B45:$FA45) / _xlfn.XLOOKUP((DATE(YEAR($FC$5)-1,MONTH($FC$5),1)),UCA.AGRO.DATE,$B45:$FA45) )-1)*100,"") -> 6.6033297 | FD45: =IFERROR(((FF45/FE45)-1)*100,"") -> -17.023603 | FE45: =SUMIFS($B45:$FA45,UCA.AGRO.DATE,">="&DATE(YEAR($FC$5)-1,1,1),UCA.AGRO.DATE,"<="&DATE(YEAR($FC$5)-1,MONTH($FC$5),1)) -> 1366.444 | FF45: =SUMIFS($B45:$FA45,UCA.AGRO.DATE,">="&DATE(YEAR($FC$5),1,1),UCA.AGRO.DATE,"<="&$FC$5) -> 1133.826 | FH45: =SUM(B45:FA45) -> 75970.02 | FJ45: =IF(EXACT(A45,FI45)=TRUE,"OK","VER") -> VER
A47: TOTAL PECUARIO | B47: =SUM(B49,B54,B55) -> 2702 | C47: =SUM(C49,C54,C55) -> 3166 | D47: =SUM(D49,D54,D55) -> 3117 | E47: =SUM(E49,E54,E55) -> 3222 | F47: =SUM(F49,F54,F55) -> 2594 | G47: =SUM(G49,G54,G55) -> 2455 | H47: =SUM(H49,H54,H55) -> 2514 | I47: =SUM(I49,I54,I55) -> 2215 | ... M47: =SUM(M49,M54,M55) -> 2337 | N47: =SUM(B47:M47) -> 30639 | O47: =SUM(O49,O54,O55) -> 1929 | P47: =SUM(P49,P54,P55) -> 1892 | Q47: =SUM(Q49,Q54,Q55) -> 1739 | R47: =SUM(R49,R54,R55) -> 1967 | S47: =SUM(S49,S54,S55) -> 2356 | T47: =SUM(T49,T54,T55) -> 2360 | U47: =SUM(U49,U54,U55) -> 2134 | V47: =SUM(V49,V54,V55) -> 2070 | ... Z47: =SUM(Z49,Z54,Z55) -> 2271 | AA47: =SUM(O47:Z47) -> 24714 | AB47: =SUM(AB49,AB54,AB55) -> 1645 | AC47: =SUM(AC49,AC54,AC55) -> 2069 | AD47: =SUM(AD49,AD54,AD55) -> 2445 | AE47: =SUM(AE49,AE54,AE55) -> 2298 | AF47: =SUM(AF49,AF54,AF55) -> 2697 | AG47: =SUM(AG49,AG54,AG55) -> 2572 | AH47: =SUM(AH49,AH54,AH55) -> 2352 | AI47: =SUM(AI49,AI54,AI55) -> 1993 | ... AM47: =SUM(AM49,AM54,AM55) -> 1888 | AN47: =SUM(AB47:AM47) -> 25540 | AO47: =SUM(AO49,AO54,AO55) -> 1842 | AP47: =SUM(AP49,AP54,AP55) -> 1650.4928 | AQ47: =SUM(AQ49,AQ54,AQ55) -> 2100.5319 | AR47: =SUM(AR49,AR54,AR55) -> 2283 | AS47: =SUM(AS49,AS54,AS55) -> 2164 | AT47: =SUM(AT49,AT54,AT55) -> 2322 | AU47: =SUM(AU49,AU54,AU55) -> 2229 | AV47: =SUM(AV49,AV54,AV55) -> 2634 | ... AZ47: =SUM(AZ49,AZ54,AZ55) -> 2791 | BA47: =SUM(AO47:AZ47) -> 26970.025 | BB47: =SUM(BB49,BB54,BB55) -> 2241 | BC47: =SUM(BC49,BC54,BC55) -> 1930 | BD47: =SUM(BD49,BD54,BD55) -> 2516 | BE47: =SUM(BE49,BE54,BE55) -> 2834 | BF47: =SUM(BF49,BF54,BF55) -> 2756 | BG47: =SUM(BG49,BG54,BG55) -> 2877 | BH47: =SUM(BH49,BH54,BH55) -> 2857 | BI47: =SUM(BI49,BI54,BI55) -> 3314 | ... BM47: =SUM(BM49,BM54,BM55) -> 3432 | BN47: =SUM(BB47:BM47) -> 33687 | BO47: =SUM(BO49,BO54,BO55) -> 2257.4733 | BP47: =SUM(BP49,BP54,BP55) -> 1900.9602 | BQ47: =SUM(BQ49,BQ54,BQ55) -> 2491.7653 | BR47: =SUM(BR49,BR54,BR55) -> 2758.1343 | BS47: =SUM(BS49,BS54,BS55) -> 2616.1246 | BT47: =SUM(BT49,BT54,BT55) -> 2816.5469 | BU47: =SUM(BU49,BU54,BU55) -> 2776.6521 | BV47: =SUM(BV49,BV54,BV55) -> 3096.491 | ... BZ47: =SUM(BZ49,BZ54,BZ55) -> 3346.3555 | CA47: =SUM(BO47:BZ47) -> 32589.663 | CB47: =SUM(CB49,CB54,CB55) -> 2210.536 | CC47: =SUM(CC49,CC54,CC55) -> 1843.2414 | CD47: =SUM(CD49,CD54,CD55) -> 2360.7469 | CE47: =SUM(CE49,CE54,CE55) -> 2663.8765 | CF47: =SUM(CF49,CF54,CF55) -> 2541.0994 | CG47: =SUM(CG49,CG54,CG55) -> 2780.8613 | CH47: =SUM(CH49,CH54,CH55) -> 2717.9048 | CI47: =SUM(CI49,CI54,CI55) -> 3108.6868 | ... CM47: =SUM(CM49,CM54,CM55) -> 3318.8718 | CN47: =SUM(CB47:CM47) -> 32185.011 | CO47: =SUM(CO49,CO54,CO55) -> 2237.9436 | CP47: =SUM(CP49,CP54,CP55) -> 1831.2785 | CQ47: =SUM(CQ49,CQ54,CQ55) -> 2328.6436 | CR47: =SUM(CR49,CR54,CR55) -> 2673.8737 | CS47: =SUM(CS49,CS54,CS55) -> 2539.1529 | CT47: =SUM(CT49,CT54,CT55) -> 2781.4091 | CU47: =SUM(CU49,CU54,CU55) -> 2710.1902 | CV47: =SUM(CV49,CV54,CV55) -> 3038.4832 | ... CZ47: =SUM(CZ49,CZ54,CZ55) -> 3082.9906 | DA47: =SUM(CO47:CZ47) -> 31518.657 | DB47: =SUM(DB49,DB54,DB55) -> 2235.4224 | DC47: =SUM(DC49,DC54,DC55) -> 1826.6873 | DD47: =SUM(DD49,DD54,DD55) -> 2369.6651 | DE47: =SUM(DE49,DE54,DE55) -> 2620.1132 | DF47: =SUM(DF49,DF54,DF55) -> 2525.0063 | DG47: =SUM(DG49,DG54,DG55) -> 2647.7579 | DH47: =SUM(DH49,DH54,DH55) -> 2672.8936 | DI47: =SUM(DI49,DI54,DI55) -> 3087.0029 | ... DM47: =SUM(DM49,DM54,DM55) -> 3146.2109 | DN47: =SUM(DB47:DM47) -> 31630.555 | DO47: =SUM(DO49,DO54,DO55) -> 2157.831 | DP47: =SUM(DP49,DP54,DP55) -> 1752.8866 | DQ47: =SUM(DQ49,DQ54,DQ55) -> 2353.1842 | DR47: =SUM(DR49,DR54,DR55) -> 2577.2485 | DS47: =SUM(DS49,DS54,DS55) -> 2485.0174 | DT47: =SUM(DT49,DT54,DT55) -> 2646.4294 | DU47: =SUM(DU49,DU54,DU55) -> 2674.1667 | DV47: =SUM(DV49,DV54,DV55) -> 3048.3806 | ... DZ47: =SUM(DZ49,DZ54,DZ55) -> 3152.719 | EA47: =SUM(DO47:DZ47) -> 31504.503 | EB47: =SUM(EB49,EB54,EB55) -> 2288.9528 | EC47: =SUM(EC49,EC54,EC55) -> 1768.7797 | ED47: =SUM(ED49,ED54,ED55) -> 2282.283 | EE47: =SUM(EE49,EE54,EE55) -> 2552.3806 | EF47: =SUM(EF49,EF54,EF55) -> 2557.8541 | EG47: =SUM(EG49,EG54,EG55) -> 2775.8249 | EH47: =SUM(EH49,EH54,EH55) -> 2777.1739 | EI47: =SUM(EI49,EI54,EI55) -> 2965.4686 | ... EM47: =SUM(EM49,EM54,EM55) -> 3180.0306 | EN47: =SUM(EB47:EM47) -> 31839.448 | EO47: =SUM(EO49,EO54,EO55) -> 2270.0993 | EP47: =SUM(EP49,EP54,EP55) -> 1761.9077 | EQ47: =SUM(EQ49,EQ54,EQ55) -> 0 | ER47: =SUM(ER49,ER54,ER55) -> 0 | ES47: =SUM(ES49,ES54,ES55) -> 0 | ET47: =SUM(ET49,ET54,ET55) -> 0 | EU47: =SUM(EU49,EU54,EU55) -> 0 | EV47: =SUM(EV49,EV54,EV55) -> 0 | ... EZ47: =SUM(EZ49,EZ54,EZ55) -> 0 | FA47: =SUM(EO47:EZ47) -> 4032.007 | FC47: =IFERROR((( _xlfn.XLOOKUP((DATE(YEAR($FC$5),MONTH($FC$5),1)),UCA.AGRO.DATE,$B47:$FA47) / _xlfn.XLOOKUP((DATE(YEAR($FC$5)-1,MONTH($FC$5),1)),UCA.AGRO.DATE,$B47:$FA47) )-1)*100,"") -> 2.1721201 | FD47: =IFERROR(((FF47/FE47)-1)*100,"") -> 1.0850603 | FE47: =SUMIFS($B47:$FA47,UCA.AGRO.DATE,">="&DATE(YEAR($FC$5)-1,1,1),UCA.AGRO.DATE,"<="&DATE(YEAR($FC$5)-1,MONTH($FC$5),1)) -> 28351.783 | FF47: =SUMIFS($B47:$FA47,UCA.AGRO.DATE,">="&DATE(YEAR($FC$5),1,1),UCA.AGRO.DATE,"<="&$FC$5) -> 28659.417 | FH47: =SUM(B47:FA47) -> 673699.74 | FJ47: =IF(EXACT(A47,FI47)=TRUE,"OK","VER") -> VER
A49: Carne | B49: =SUM(B50:B53) -> 1976 | C49: =SUM(C50:C53) -> 2415 | D49: =SUM(D50:D53) -> 2339 | E49: =SUM(E50:E53) -> 2437 | F49: =SUM(F50:F53) -> 1815 | G49: =SUM(G50:G53) -> 1691 | H49: =SUM(H50:H53) -> 1732 | I49: =SUM(I50:I53) -> 1437 | ... M49: =SUM(M50:M53) -> 1567 | N49: =SUM(B49:M49) -> 21434 | O49: =SUM(O50:O53) -> 1135 | P49: =SUM(P50:P53) -> 1086 | Q49: =SUM(Q50:Q53) -> 876 | R49: =SUM(R50:R53) -> 1043 | S49: =SUM(S50:S53) -> 1402 | T49: =SUM(T50:T53) -> 1385 | U49: =SUM(U50:U53) -> 1120 | V49: =SUM(V50:V53) -> 1182 | ... Z49: =SUM(Z50:Z53) -> 1218 | AA49: =SUM(O49:Z49) -> 13427 | AB49: =SUM(AB50:AB53) -> 553 | AC49: =SUM(AC50:AC53) -> 1041 | AD49: =SUM(AD50:AD53) -> 1384 | AE49: =SUM(AE50:AE53) -> 1249 | AF49: =SUM(AF50:AF53) -> 1665 | AG49: =SUM(AG50:AG53) -> 1609 | AH49: =SUM(AH50:AH53) -> 1392 | AI49: =SUM(AI50:AI53) -> 1256 | ... AM49: =SUM(AM50:AM53) -> 1232 | AN49: =SUM(AB49:AM49) -> 14964 | AO49: =SUM(AO50:AO53) -> 997 | AP49: =SUM(AP50:AP53) -> 795 | AQ49: =SUM(AQ50:AQ53) -> 1237 | AR49: =SUM(AR50:AR53) -> 1433 | AS49: =SUM(AS50:AS53) -> 1325 | AT49: =SUM(AT50:AT53) -> 1475 | AU49: =SUM(AU50:AU53) -> 1405 | AV49: =SUM(AV50:AV53) -> 1809 | ... AZ49: =SUM(AZ50:AZ53) -> 2147 | BA49: =SUM(AO49:AZ49) -> 17593 | BB49: =SUM(BB50:BB53) -> 1406 | BC49: =SUM(BC50:BC53) -> 1069 | BD49: =SUM(BD50:BD53) -> 1663 | BE49: =SUM(BE50:BE53) -> 2018 | BF49: =SUM(BF50:BF53) -> 1911 | BG49: =SUM(BG50:BG53) -> 2078 | BH49: =SUM(BH50:BH53) -> 2041 | BI49: =SUM(BI50:BI53) -> 2498 | ... BM49: =SUM(BM50:BM53) -> 2772 | BN49: =SUM(BB49:BM49) -> 24379 | BO49: =SUM(BO50:BO53) -> 1436.5865 | BP49: =SUM(BP50:BP53) -> 1064.0579 | BQ49: =SUM(BQ50:BQ53) -> 1598.7802 | BR49: =SUM(BR50:BR53) -> 1944.8722 | BS49: =SUM(BS50:BS53) -> 1835.7947 | BT49: =SUM(BT50:BT53) -> 2086.5316 | BU49: =SUM(BU50:BU53) -> 2039.2466 | BV49: =SUM(BV50:BV53) -> 2367.5462 | ... BZ49: =SUM(BZ50:BZ53) -> 2725.7667 | CA49: =SUM(BO49:BZ49) -> 23720.836 | CB49: =SUM(CB50:CB53) -> 1456.6486 | CC49: =SUM(CC50:CC53) -> 1091.8085 | CD49: =SUM(CD50:CD53) -> 1583.6423 | CE49: =SUM(CE50:CE53) -> 1955.8771 | CF49: =SUM(CF50:CF53) -> 1867.4281 | CG49: =SUM(CG50:CG53) -> 2127.6107 | CH49: =SUM(CH50:CH53) -> 2060.8968 | CI49: =SUM(CI50:CI53) -> 2465.7101 | ... CM49: =SUM(CM50:CM53) -> 2761.9027 | CN49: =SUM(CB49:CM49) -> 24206.792 | CO49: =SUM(CO50:CO53) -> 1555.1518 | CP49: =SUM(CP50:CP53) -> 1131.8673 | CQ49: =SUM(CQ50:CQ53) -> 1640.3416 | CR49: =SUM(CR50:CR53) -> 2023.6828 | CS49: =SUM(CS50:CS53) -> 1904.4973 | CT49: =SUM(CT50:CT53) -> 2149.3793 | CU49: =SUM(CU50:CU53) -> 2065.6984 | CV49: =SUM(CV50:CV53) -> 2414.1577 | ... CZ49: =SUM(CZ50:CZ53) -> 2545.8311 | DA49: =SUM(CO49:CZ49) -> 24008.862 | DB49: =SUM(DB50:DB53) -> 1599.0388 | DC49: =SUM(DC50:DC53) -> 1167.8423 | DD49: =SUM(DD50:DD53) -> 1721.6519 | DE49: =SUM(DE50:DE53) -> 1998.2701 | DF49: =SUM(DF50:DF53) -> 1918.1521 | DG49: =SUM(DG50:DG53) -> 2046.5458 | DH49: =SUM(DH50:DH53) -> 2051.641 | DI49: =SUM(DI50:DI53) -> 2487.893 | ... DM49: =SUM(DM50:DM53) -> 2650.9951 | DN49: =SUM(DB49:DM49) -> 24519.035 | DO49: =SUM(DO50:DO53) -> 1562.0089 | DP49: =SUM(DP50:DP53) -> 1147.3626 | DQ49: =SUM(DQ50:DQ53) -> 1740.4091 | DR49: =SUM(DR50:DR53) -> 2002.7815 | DS49: =SUM(DS50:DS53) -> 1922.8295 | DT49: =SUM(DT50:DT53) -> 2042.935 | DU49: =SUM(DU50:DU53) -> 2062.9872 | DV49: =SUM(DV50:DV53) -> 2454.2378 | ... DZ49: =SUM(DZ50:DZ53) -> 2664.1677 | EA49: =SUM(DO49:DZ49) -> 24648.826 | EB49: =SUM(EB50:EB53) -> 1754.37 | EC49: =SUM(EC50:EC53) -> 1240.491 | ED49: =SUM(ED50:ED53) -> 1766.456 | EE49: =SUM(EE50:EE53) -> 2035.1251 | EF49: =SUM(EF50:EF53) -> 2052.6347 | EG49: =SUM(EG50:EG53) -> 2269.293 | EH49: =SUM(EH50:EH53) -> 2258.5332 | EI49: =SUM(EI50:EI53) -> 2441.2069 | ... EM49: =SUM(EM50:EM53) -> 2687.8348 | EN49: =SUM(EB49:EM49) -> 25636.821 | EO49: =SUM(EO50:EO53) -> 1749.2058 | EP49: =SUM(EP50:EP53) -> 1233.9898 | EQ49: =SUM(EQ50:EQ53) -> 0 | ER49: =SUM(ER50:ER53) -> 0 | ES49: =SUM(ES50:ES53) -> 0 | ET49: =SUM(ET50:ET53) -> 0 | EU49: =SUM(EU50:EU53) -> 0 | EV49: =SUM(EV50:EV53) -> 0 | ... EZ49: =SUM(EZ50:EZ53) -> 0 | FA49: =SUM(EO49:EZ49) -> 2983.1957 | FC49: =IFERROR((( _xlfn.XLOOKUP((DATE(YEAR($FC$5),MONTH($FC$5),1)),UCA.AGRO.DATE,$B49:$FA49) / _xlfn.XLOOKUP((DATE(YEAR($FC$5)-1,MONTH($FC$5),1)),UCA.AGRO.DATE,$B49:$FA49) )-1)*100,"") -> 1.72979 | FD49: =IFERROR(((FF49/FE49)-1)*100,"") -> 4.3863655 | FE49: =SUMIFS($B49:$FA49,UCA.AGRO.DATE,">="&DATE(YEAR($FC$5)-1,1,1),UCA.AGRO.DATE,"<="&DATE(YEAR($FC$5)-1,MONTH($FC$5),1)) -> 21984.659 | FF49: =SUMIFS($B49:$FA49,UCA.AGRO.DATE,">="&DATE(YEAR($FC$5),1,1),UCA.AGRO.DATE,"<="&$FC$5) -> 22948.986 | FH49: =SUM(B49:FA49) -> 483042.74 | FJ49: =IF(EXACT(A49,FI49)=TRUE,"OK","VER") -> VER
A50: Carne de Ave | B50: 1756 | C50: 2201 | D50: 2125 | E50: 2210 | F50: 1579 | G50: 1461 | H50: 1491 | I50: 1198 | J50: 1018 | K50: 1089 | L50: 1179 | M50: 1297 | N50: =SUM(B50:M50) -> 18604 | O50: 883 | P50: 838 | Q50: 630 | R50: 790 | S50: 1168 | T50: 1129 | U50: 864 | V50: 917 | W50: 839 | X50: 605 | Y50: 795 | Z50: 949 | AA50: =SUM(O50:Z50) -> 10407 | AB50: 311 | AC50: 805 | AD50: 1155 | AE50: 995 | AF50: 1415 | AG50: 1393 | AH50: 1181 | AI50: 1028 | AJ50: 1065 | AK50: 913 | AL50: 904 | AM50: 878 | AN50: =SUM(AB50:AM50) -> 12043 | AO50: 749 | AP50: 583 | AQ50: 991 | AR50: 1200 | AS50: 1095 | AT50: 1252 | AU50: 1188 | AV50: 1593 | AW50: 1200 | AX50: 1788 | AY50: 1264 | AZ50: 1827 | BA50: =SUM(AO50:AZ50) -> 14730 | BB50: 1044 | BC50: 719 | BD50: 1278 | BE50: 1624 | BF50: 1516 | BG50: 1640 | BH50: 1615 | BI50: 2084 | BJ50: 1571 | BK50: 2372 | BL50: 1545 | BM50: 2198 | BN50: =SUM(BB50:BM50) -> 19206 | BO50: 1093.8022 | BP50: 733.91091 | BQ50: 1241.4843 | BR50: 1571.3887 | BS50: 1498.4083 | BT50: 1635.0065 | BU50: 1603.8933 | BV50: 1934.4619 | BW50: 1465.0568 | BX50: 2240.8741 | BY50: 1456.4963 | BZ50: 2111.3451 | CA50: 18586.129 | CB50: 1074.6691 | CC50: 712.49091 | CD50: 1207.3058 | CE50: 1526.932 | CF50: 1471.3887 | CG50: 1666.3677 | CH50: 1639.4168 | CI50: 1996.8641 | CJ50: 1592.6833 | CK50: 2340.5461 | CL50: 1528.3154 | CM50: 2144.0227 | CN50: 18901.003 | CO50: 1202.8108 | CP50: 755.57592 | CQ50: 1244.2316 | CR50: 1584.23 | CS50: 1492.3001 | CT50: 1644.6827 | CU50: 1585.2451 | CV50: 1943.1207 | CW50: 1499.2286 | CX50: 2260.0334 | CY50: 1419.9556 | CZ50: 1982.4677 | DA50: 18613.882 | DB50: 1149.0778 | DC50: 697.62869 | DD50: 1189.6039 | DE50: 1481.2771 | DF50: 1464.5846 | DG50: 1609.4513 | DH50: 1544.692 | DI50: 1894.053 | DJ50: 1423.7207 | DK50: 2150.4979 | DL50: 1358.2491 | DM50: 1898.7851 | DN50: 17861.621 | DO50: 1098.4073 | DP50: 662.86127 | DQ50: 1181.289 | DR50: 1464.0384 | DS50: 1440.3195 | DT50: 1585.9916 | DU50: 1536.3647 | DV50: 1841.0992 | DW50: 1430.4093 | DX50: 2246.2753 | DY50: 1361.7828 | DZ50: 1880.3711 | EA50: 17729.21 | EB50: 1127.45 | EC50: 676.01596 | ED50: 1210.536 | EE50: 1504.1531 | EF50: 1483.2447 | EG50: 1653.503 | EH50: 1666.6032 | EI50: 1869.3269 | EJ50: 1492.039 | EK50: 2280.9963 | EL50: 1374.9333 | EM50: 1889.387 | EN50: 18228.188 | EO50: 1142.8445 | EP50: 698.8838 | FA50: =SUM(EO50:EZ50) -> 1841.7283 | FC50: =IFERROR((( _xlfn.XLOOKUP((DATE(YEAR($FC$5),MONTH($FC$5),1)),UCA.AGRO.DATE,$B50:$FA50) / _xlfn.XLOOKUP((DATE(YEAR($FC$5)-1,MONTH($FC$5),1)),UCA.AGRO.DATE,$B50:$FA50) )-1)*100,"") -> 0.96568603 | FD50: =IFERROR(((FF50/FE50)-1)*100,"") -> 3.091476 | FE50: =SUMIFS($B50:$FA50,UCA.AGRO.DATE,">="&DATE(YEAR($FC$5)-1,1,1),UCA.AGRO.DATE,"<="&DATE(YEAR($FC$5)-1,MONTH($FC$5),1)) -> 15848.839 | FF50: =SUMIFS($B50:$FA50,UCA.AGRO.DATE,">="&DATE(YEAR($FC$5),1,1),UCA.AGRO.DATE,"<="&$FC$5) -> 16338.802 | FH50: =SUM(B50:FA50) -> 373503.52 | FJ50: =IF(EXACT(A50,FI50)=TRUE,"OK","VER") -> VER
A51: Carne de Porcino | B51: 93 | C51: 93 | D51: 90 | E51: 95 | F51: 101 | G51: 99 | H51: 104 | I51: 101 | J51: 98 | K51: 96 | L51: 101 | M51: 119 | N51: =SUM(B51:M51) -> 1190 | O51: 103 | P51: 103 | Q51: 101 | R51: 101 | S51: 93 | T51: 109 | U51: 101 | V51: 110 | W51: 101 | X51: 102 | Y51: 98 | Z51: 113 | AA51: =SUM(O51:Z51) -> 1235 | AB51: 91 | AC51: 89 | AD51: 86 | AE51: 84 | AF51: 82 | AG51: 77 | AH51: 72 | AI51: 47 | AJ51: 42 | AK51: 47 | AL51: 41 | AM51: 116 | AN51: =SUM(AB51:AM51) -> 874 | AO51: 76 | AP51: 74 | AQ51: 76 | AR51: 78 | AS51: 77 | AT51: 72 | AU51: 74 | AV51: 53 | AW51: 55 | AX51: 57 | AY51: 68 | AZ51: 105 | BA51: =SUM(AO51:AZ51) -> 865 | BB51: 100 | BC51: 97 | BD51: 97 | BE51: 94 | BF51: 93 | BG51: 98 | BH51: 92 | BI51: 75 | BJ51: 77 | BK51: 74 | BL51: 92 | BM51: 142 | BN51: =SUM(BB51:BM51) -> 1131 | BO51: 67.449 | BP51: 66.84407 | BQ51: 72.3 | BR51: 62.941 | BS51: 55.02 | BT51: 104.94606 | BU51: 64.7434 | BV51: 72.54 | BW51: 77.282 | BX51: 84.666 | BY51: 91.2 | BZ51: 163.08 | CA51: 983.01153 | CB51: 104.28 | CC51: 91.26 | CD51: 80.46 | CE51: 80.16 | CF51: 74.64 | CG51: 70.8 | CH51: 60 | CI51: 69.06 | CJ51: 67.8 | CK51: 60.12 | CL51: 54.78 | CM51: 145.62 | CN51: 958.98 | CO51: 92.06 | CP51: 81.033333 | CQ51: 79.093333 | CR51: 69.285 | CS51: 73.5 | CT51: 76.966667 | CU51: 67.133333 | CV51: 69.48 | CW51: 68.34 | CX51: 63.6 | CY51: 56.053139 | CZ51: 153.29333 | DA51: 949.83814 | DB51: 80.16 | DC51: 84.18 | DD51: 93.48 | DE51: 89.0917 | DF51: 83.16 | DG51: 89.76 | DH51: 102.6 | DI51: 107.94 | DJ51: 122.76 | DK51: 111.54 | DL51: 114.06 | DM51: 145.08 | DN51: 1223.8117 | DO51: 85.086667 | DP51: 88.818667 | DQ51: 102.52 | DR51: 94.053667 | DS51: 93.513333 | DT51: 97.38 | DU51: 107.83333 | DV51: 114.60667 | DW51: 127.91333 | DX51: 123.30667 | DY51: 121.22667 | DZ51: 160.47667 | EA51: 1316.7357 | EB51: 136.02 | EC51: 138.54 | ED51: 129.18 | EE51: 129.48 | EF51: 149.72 | EG51: 151.32 | EH51: 139.38 | EI51: 142.2 | EJ51: 182.7 | EK51: 167.4 | EL51: 177.39 | EM51: 245.52 | EN51: 1888.85 | EO51: 145.02 | EP51: 140.49333 | FA51: =SUM(EO51:EZ51) -> 285.51333 | FC51: =IFERROR((( _xlfn.XLOOKUP((DATE(YEAR($FC$5),MONTH($FC$5),1)),UCA.AGRO.DATE,$B51:$FA51) / _xlfn.XLOOKUP((DATE(YEAR($FC$5)-1,MONTH($FC$5),1)),UCA.AGRO.DATE,$B51:$FA51) )-1)*100,"") -> 46.32919 | FD51: =IFERROR(((FF51/FE51)-1)*100,"") -> 42.124732 | FE51: =SUMIFS($B51:$FA51,UCA.AGRO.DATE,">="&DATE(YEAR($FC$5)-1,1,1),UCA.AGRO.DATE,"<="&DATE(YEAR($FC$5)-1,MONTH($FC$5),1)) -> 1156.259 | FF51: =SUMIFS($B51:$FA51,UCA.AGRO.DATE,">="&DATE(YEAR($FC$5),1,1),UCA.AGRO.DATE,"<="&$FC$5) -> 1643.33 | FH51: =SUM(B51:FA51) -> 25803.481 | FJ51: =IF(EXACT(A51,FI51)=TRUE,"OK","VER") -> VER
A52: Carne de Vacuno | B52: 127 | C52: 121 | D52: 123 | E52: 131 | F52: 134 | G52: 130 | H52: 136 | I52: 137 | J52: 134 | K52: 151 | L52: 157 | M52: 150 | N52: =SUM(B52:M52) -> 1631 | O52: 149 | P52: 145 | Q52: 145 | R52: 151 | S52: 140 | T52: 146 | U52: 154 | V52: 155 | W52: 146 | X52: 147 | Y52: 143 | Z52: 154 | AA52: =SUM(O52:Z52) -> 1775 | AB52: 149 | AC52: 145 | AD52: 141 | AE52: 168 | AF52: 166 | AG52: 137 | AH52: 137 | AI52: 179 | AJ52: 182 | AK52: 189 | AL52: 191 | AM52: 233 | AN52: =SUM(AB52:AM52) -> 2017 | AO52: 168 | AP52: 136 | AQ52: 167 | AR52: 152 | AS52: 151 | AT52: 149 | AU52: 141 | AV52: 161 | AW52: 169 | AX52: 176 | AY52: 186 | AZ52: 211 | BA52: =SUM(AO52:AZ52) -> 1967 | BB52: 258 | BC52: 249 | BD52: 284 | BE52: 296 | BF52: 297 | BG52: 335 | BH52: 328 | BI52: 333 | BJ52: 380 | BK52: 395 | BL52: 395 | BM52: 423 | BN52: =SUM(BB52:BM52) -> 3973 | BO52: 271.16527 | BP52: 259.1829 | BQ52: 280.6049 | BR52: 306.69 | BS52: 277.4464 | BT52: 341.03893 | BU52: 364.7299 | BV52: 354.78431 | BW52: 393.56463 | BX52: 393.41863 | BY52: 396.7451 | BZ52: 442.42157 | CA52: 4081.7925 | CB52: 273.27941 | CC52: 283.90757 | CD52: 291.27451 | CE52: 344.7451 | CF52: 316.35294 | CG52: 384.75 | CH52: 355.5 | CI52: 393.756 | CJ52: 400.5 | CK52: 381.25 | CL52: 387 | CM52: 462 | CN52: 4274.3155 | CO52: 255.751 | CP52: 290.84804 | CQ52: 312.31863 | CR52: 366.03431 | CS52: 333.41176 | CT52: 422 | CU52: 407 | CV52: 395.5 | CW52: 414.5 | CX52: 391.25 | CY52: 383.06171 | CZ52: 399 | DA52: 4370.6755 | DB52: 365.001 | DC52: 381.5 | DD52: 433.75 | DE52: 423.81 | DF52: 365.25 | DG52: 341.75 | DH52: 398 | DI52: 479.5 | DJ52: 553.25 | DK52: 512.75 | DL52: 506.998 | DM52: 596.75 | DN52: 5358.309 | DO52: 373.40686 | DP52: 391.11765 | DQ52: 452.05202 | DR52: 440.77941 | DS52: 383.95588 | DT52: 353.70588 | DU52: 412.29412 | DV52: 491.90196 | DW52: 567.2451 | DX52: 526.17157 | DY52: 520.27647 | DZ52: 612.25 | EA52: 5525.1569 | EB52: 485.25 | EC52: 421.25 | ED52: 422 | EE52: 397.5 | EF52: 414 | EG52: 458 | EH52: 445.75 | EI52: 422.5 | EJ52: 471.25 | EK52: 473 | EL52: 485.5 | EM52: 541.35784 | EN52: 5437.3578 | EO52: 455.68137 | EP52: 389.71569 | FA52: =SUM(EO52:EZ52) -> 845.39706 | FC52: =IFERROR((( _xlfn.XLOOKUP((DATE(YEAR($FC$5),MONTH($FC$5),1)),UCA.AGRO.DATE,$B52:$FA52) / _xlfn.XLOOKUP((DATE(YEAR($FC$5)-1,MONTH($FC$5),1)),UCA.AGRO.DATE,$B52:$FA52) )-1)*100,"") -> -6.684229 | FD52: =IFERROR(((FF52/FE52)-1)*100,"") -> -0.34413275 | FE52: =SUMIFS($B52:$FA52,UCA.AGRO.DATE,">="&DATE(YEAR($FC$5)-1,1,1),UCA.AGRO.DATE,"<="&DATE(YEAR($FC$5)-1,MONTH($FC$5),1)) -> 4912.9069 | FF52: =SUMIFS($B52:$FA52,UCA.AGRO.DATE,">="&DATE(YEAR($FC$5),1,1),UCA.AGRO.DATE,"<="&$FC$5) -> 4896 | FH52: =SUM(B52:FA52) -> 82512.009 | FJ52: =IF(EXACT(A52,FI52)=TRUE,"OK","VER") -> VER
A53: Carne de Ovino | D53: 1 | E53: 1 | F53: 1 | G53: 1 | H53: 1 | I53: 1 | J53: 1 | K53: 1 | M53: 1 | N53: =SUM(B53:M53) -> 9 | R53: 1 | S53: 1 | T53: 1 | U53: 1 | W53: 1 | X53: 1 | Y53: 2 | Z53: 2 | AA53: =SUM(O53:Z53) -> 10 | AB53: 2 | AC53: 2 | AD53: 2 | AE53: 2 | AF53: 2 | AG53: 2 | AH53: 2 | AI53: 2 | AJ53: 3 | AK53: 3 | AL53: 3 | AM53: 5 | AN53: =SUM(AB53:AM53) -> 30 | AO53: 4 | AP53: 2 | AQ53: 3 | AR53: 3 | AS53: 2 | AT53: 2 | AU53: 2 | AV53: 2 | AW53: 2 | AX53: 2 | AY53: 3 | AZ53: 4 | BA53: =SUM(AO53:AZ53) -> 31 | BB53: 4 | BC53: 4 | BD53: 4 | BE53: 4 | BF53: 5 | BG53: 5 | BH53: 6 | BI53: 6 | BJ53: 7 | BK53: 7 | BL53: 8 | BM53: 9 | BN53: =SUM(BB53:BM53) -> 69 | BO53: 4.17 | BP53: 4.12 | BQ53: 4.391 | BR53: 3.8525 | BS53: 4.92 | BT53: 5.54017 | BU53: 5.88 | BV53: 5.76 | BW53: 6.94 | BX53: 7.59 | BY53: 7.82 | BZ53: 8.92 | CA53: 69.90367 | CB53: 4.42 | CC53: 4.15 | CD53: 4.602 | CE53: 4.04 | CF53: 5.0464 | CG53: 5.693 | CH53: 5.98 | CI53: 6.03 | CJ53: 7.12 | CK53: 7.1125 | CL53: 8.04 | CM53: 10.26 | CN53: 72.4939 | CO53: 4.53 | CP53: 4.41 | CQ53: 4.698 | CR53: 4.1335 | CS53: 5.2855 | CT53: 5.73 | CU53: 6.32 | CV53: 6.057 | CW53: 7.135 | CX53: 7.16 | CY53: 7.93675 | CZ53: 11.07 | DA53: 74.46575 | DB53: 4.8 | DC53: 4.533625 | DD53: 4.818 | DE53: 4.09125 | DF53: 5.1575 | DG53: 5.5845 | DH53: 6.349 | DI53: 6.4 | DJ53: 7.614 | DK53: 7.29 | DL53: 8.275 | DM53: 10.38 | DN53: 75.292875 | DO53: 5.108 | DP53: 4.565 | DQ53: 4.548 | DR53: 3.91 | DS53: 5.04075 | DT53: 5.8575 | DU53: 6.495 | DV53: 6.63 | DW53: 7.87 | DX53: 7.82 | DY53: 8.81 | DZ53: 11.07 | EA53: 77.72425 | EB53: 5.65 | EC53: 4.685 | ED53: 4.74 | EE53: 3.992 | EF53: 5.67 | EG53: 6.47 | EH53: 6.8 | EI53: 7.18 | EJ53: 8.485 | EK53: 8.105 | EL53: 9.077625 | EM53: 11.57 | EN53: 82.424625 | EO53: 5.66 | EP53: 4.897 | FA53: =SUM(EO53:EZ53) -> 10.557 | FC53: =IFERROR((( _xlfn.XLOOKUP((DATE(YEAR($FC$5),MONTH($FC$5),1)),UCA.AGRO.DATE,$B53:$FA53) / _xlfn.XLOOKUP((DATE(YEAR($FC$5)-1,MONTH($FC$5),1)),UCA.AGRO.DATE,$B53:$FA53) )-1)*100,"") -> 3.0377412 | FD53: =IFERROR(((FF53/FE53)-1)*100,"") -> 6.3017362 | FE53: =SUMIFS($B53:$FA53,UCA.AGRO.DATE,">="&DATE(YEAR($FC$5)-1,1,1),UCA.AGRO.DATE,"<="&DATE(YEAR($FC$5)-1,MONTH($FC$5),1)) -> 66.65425 | FF53: =SUMIFS($B53:$FA53,UCA.AGRO.DATE,">="&DATE(YEAR($FC$5),1,1),UCA.AGRO.DATE,"<="&$FC$5) -> 70.854625 | FH53: =SUM(B53:FA53) -> 1223.7241 | FJ53: =IF(EXACT(A53,FI53)=TRUE,"OK","VER") -> VER
A54: Leche | B54: 379 | C54: 398 | D54: 408 | E54: 420 | F54: 424 | G54: 419 | H54: 426 | I54: 415 | J54: 415 | K54: 441 | L54: 485 | M54: 486 | N54: =SUM(B54:M54) -> 5116 | O54: 522 | P54: 524 | Q54: 556 | R54: 630 | S54: 635 | T54: 660 | U54: 691 | V54: 543 | W54: 622 | X54: 651 | Y54: 641 | Z54: 665 | AA54: =SUM(O54:Z54) -> 7340 | AB54: 680 | AC54: 615 | AD54: 686 | AE54: 666 | AF54: 680 | AG54: 642 | AH54: 656 | AI54: 422 | AJ54: 295 | AK54: 341 | AL54: 372 | AM54: 344 | AN54: =SUM(AB54:AM54) -> 6399 | AO54: 568 | AP54: 553 | AQ54: 578 | AR54: 559 | AS54: 555 | AT54: 555 | AU54: 529 | AV54: 487 | AW54: 346 | AX54: 360 | AY54: 383 | AZ54: 362 | BA54: =SUM(AO54:AZ54) -> 5835 | BB54: 521 | BC54: 529 | BD54: 551 | BE54: 496 | BF54: 546 | BG54: 502 | BH54: 510 | BI54: 475 | BJ54: 376 | BK54: 341 | BL54: 375 | BM54: 375 | BN54: =SUM(BB54:BM54) -> 5597 | BO54: 506.0871 | BP54: 504.33 | BQ54: 580.789 | BR54: 496.03086 | BS54: 483.78405 | BT54: 434.78405 | BU54: 432.169 | BV54: 390.38479 | BW54: 330.23944 | BX54: 332.74463 | BY54: 333.89844 | BZ54: 340.3438 | CA54: 5165.5852 | CB54: 443.63343 | CC54: 443.07616 | CD54: 475.85763 | CE54: 397.30967 | CF54: 383.0243 | CG54: 362.93281 | CH54: 355.33477 | CI54: 343.61392 | CJ54: 295.3166 | CK54: 324.19856 | CL54: 299.81092 | CM54: 291.27452 | CN54: 4415.3833 | CO54: 371.34038 | CP54: 389.3594 | CQ54: 392.76691 | CR54: 354.62794 | CS54: 355.26405 | CT54: 355.49941 | CU54: 353.80956 | CV54: 330.67794 | CW54: 283.42317 | CX54: 293.89581 | CY54: 273.11847 | CZ54: 273.87841 | DA54: 4027.6614 | DB54: 336.09113 | DC54: 365.94341 | DD54: 365.79373 | DE54: 336.7056 | DF54: 337.068 | DG54: 335.97335 | DH54: 345.88973 | DI54: 315.74696 | DJ54: 275.67584 | DK54: 269.92707 | DL54: 254.86177 | DM54: 244.92329 | DN54: 3784.5999 | DO54: 305.00412 | DP54: 325.47 | DQ54: 345.15783 | DR54: 305.259 | DS54: 305.28996 | DT54: 345.36842 | DU54: 340.46649 | DV54: 318.429 | DW54: 285.81334 | DX54: 265.88354 | DY54: 245.80715 | DZ54: 245.7163 | EA54: 3633.6651 | EB54: 245.66985 | EC54: 245.60069 | ED54: 245.62133 | EE54: 245.69772 | EF54: 245.77927 | EG54: 245.87115 | EH54: 245.96509 | EI54: 246.03941 | EJ54: 246.10755 | EK54: 246.18187 | EL54: 246.53595 | EM54: 246.61028 | EN54: 2951.6802 | EO54: 246.69802 | EP54: 252.36948 | FA54: =SUM(EO54:EZ54) -> 499.0675 | FC54: =IFERROR((( _xlfn.XLOOKUP((DATE(YEAR($FC$5),MONTH($FC$5),1)),UCA.AGRO.DATE,$B54:$FA54) / _xlfn.XLOOKUP((DATE(YEAR($FC$5)-1,MONTH($FC$5),1)),UCA.AGRO.DATE,$B54:$FA54) )-1)*100,"") -> 0.29649415 | FD54: =IFERROR(((FF54/FE54)-1)*100,"") -> -20.156118 | FE54: =SUMIFS($B54:$FA54,UCA.AGRO.DATE,">="&DATE(YEAR($FC$5)-1,1,1),UCA.AGRO.DATE,"<="&DATE(YEAR($FC$5)-1,MONTH($FC$5),1)) -> 3387.9488 | FF54: =SUMIFS($B54:$FA54,UCA.AGRO.DATE,">="&DATE(YEAR($FC$5),1,1),UCA.AGRO.DATE,"<="&$FC$5) -> 2705.0699 | FH54: =SUM(B54:FA54) -> 109529.29 | FJ54: =IF(EXACT(A54,FI54)=TRUE,"OK","VER") -> VER
A55: Huevos | B55: 347 | C55: 353 | D55: 370 | E55: 365 | F55: 355 | G55: 345 | H55: 356 | I55: 363 | J55: 347 | K55: 323 | L55: 281 | M55: 284 | N55: =SUM(B55:M55) -> 4089 | O55: 272 | P55: 282 | Q55: 307 | R55: 294 | S55: 319 | T55: 315 | U55: 323 | V55: 345 | W55: 378 | X55: 371 | Y55: 353 | Z55: 388 | AA55: =SUM(O55:Z55) -> 3947 | AB55: 412 | AC55: 413 | AD55: 375 | AE55: 383 | AF55: 352 | AG55: 321 | AH55: 304 | AI55: 315 | AJ55: 320 | AK55: 326 | AL55: 344 | AM55: 312 | AN55: =SUM(AB55:AM55) -> 4177 | AO55: 277 | AP55: 302.4928 | AQ55: 285.53194 | AR55: 291 | AS55: 284 | AT55: 292 | AU55: 295 | AV55: 338 | AW55: 308 | AX55: 297 | AY55: 290 | AZ55: 282 | BA55: =SUM(AO55:AZ55) -> 3542.0247 | BB55: 314 | BC55: 332 | BD55: 302 | BE55: 320 | BF55: 299 | BG55: 297 | BH55: 306 | BI55: 341 | BJ55: 328 | BK55: 301 | BL55: 286 | BM55: 285 | BN55: =SUM(BB55:BM55) -> 3711 | BO55: 314.79967 | BP55: 332.57235 | BQ55: 312.19614 | BR55: 317.23123 | BS55: 296.54582 | BT55: 295.23121 | BU55: 305.23645 | BV55: 338.56 | BW55: 330.245 | BX55: 300.2547 | BY55: 280.124 | BZ55: 280.245 | CA55: 3703.2416 | CB55: 310.254 | CC55: 308.3568 | CD55: 301.247 | CE55: 310.6897 | CF55: 290.647 | CG55: 290.3178 | CH55: 301.6733 | CI55: 299.36271 | CJ55: 324.33386 | CK55: 292.8511 | CL55: 267.40772 | CM55: 265.69459 | CN55: 3562.8356 | CO55: 311.45147 | CP55: 310.05184 | CQ55: 295.53505 | CR55: 295.56293 | CS55: 279.39155 | CT55: 276.53031 | CU55: 290.68218 | CV55: 293.64753 | CW55: 320.24933 | CX55: 285.5661 | CY55: 260.18416 | CZ55: 263.28117 | DA55: 3482.1336 | DB55: 300.29247 | DC55: 292.90153 | DD55: 282.21947 | DE55: 285.1375 | DF55: 269.78617 | DG55: 265.23872 | DH55: 275.36296 | DI55: 283.36296 | DJ55: 305.65228 | DK55: 270.29247 | DL55: 246.38095 | DM55: 250.29247 | DN55: 3326.92 | DO55: 290.818 | DP55: 280.054 | DQ55: 267.61734 | DR55: 269.208 | DS55: 256.898 | DT55: 258.126 | DU55: 270.713 | DV55: 275.7138 | DW55: 301.178 | DX55: 268.08183 | DY55: 240.768 | DZ55: 242.835 | EA55: 3222.011 | EB55: 288.913 | EC55: 282.688 | ED55: 270.2057 | EE55: 271.5578 | EF55: 259.4401 | EG55: 260.6607 | EH55: 272.6756 | EI55: 278.2223 | EJ55: 297.60209 | EK55: 263.8878 | EL55: 259.5083 | EM55: 245.58554 | EN55: 3250.9469 | EO55: 274.1954 | EP55: 275.54843 | FA55: =SUM(EO55:EZ55) -> 549.74383 | FC55: =IFERROR((( _xlfn.XLOOKUP((DATE(YEAR($FC$5),MONTH($FC$5),1)),UCA.AGRO.DATE,$B55:$FA55) / _xlfn.XLOOKUP((DATE(YEAR($FC$5)-1,MONTH($FC$5),1)),UCA.AGRO.DATE,$B55:$FA55) )-1)*100,"") -> 7.783551 | FD55: =IFERROR(((FF55/FE55)-1)*100,"") -> 0.87894857 | FE55: =SUMIFS($B55:$FA55,UCA.AGRO.DATE,">="&DATE(YEAR($FC$5)-1,1,1),UCA.AGRO.DATE,"<="&DATE(YEAR($FC$5)-1,MONTH($FC$5),1)) -> 2979.176 | FF55: =SUMIFS($B55:$FA55,UCA.AGRO.DATE,">="&DATE(YEAR($FC$5),1,1),UCA.AGRO.DATE,"<="&$FC$5) -> 3005.3614 | FH55: =SUM(B55:FA55) -> 81127.714 | FJ55: =IF(EXACT(A55,FI55)=TRUE,"OK","VER") -> VER
A57: Fuente: Oficina de Información Agraria - Dirección Regional del Minagri de Ucayali.
A58: 1/ Preliminar. | EB58: 115173.96 | EC58: 119174.88 | ED58: 109325.59 | EE58: 81068.498 | EF58: 101696.19 | EG58: 125055.85 | EH58: 90320.008 | EI58: 83805.127 | EJ58: 94043.909 | EK58: 87098.2 | EL58: 147324.3 | EM58: 0 | EN58: 1154086.5
A59: 2/ Valor Bruto de Producción a Precios 1994 (Miles de nuevos soles) | EB59: =EB11-EB58 -> -18.261 | EC59: =EC11-EC58 -> -39.23 | ED59: =ED11-ED58 -> -157.16 | EE59: =EE11-EE58 -> -67.75 | EF59: =EF11-EF58 -> 3512.751 | EG59: =EG11-EG58 -> -10130.489 | EH59: =EH11-EH58 -> 5902.415 | EI59: =EI11-EI58 -> 27407.711 | ... EO59: =EO11-EO58 -> 136460.79
A60: 3/ Peso de animal en pie.

Sheet 02.XLS
A1: Cuadro N° 02
A2: UCAYALI: PRODUCCIÓN DE OTROS PRODUCTOS AGRÍCOLAS 1/
A3: (VBP y toneladas métricas)
B4: 2015 | N4: Total | O4: 2016 | AA4: Total | AB4: 2017 | AN4: Total | AO4: 2018 | BA4: Total | BB4: 2019 | BN4: Total | BO4: 2020 | CA4: Total | CB4: 2021 | CN4: Total | CO4: 2022 | DA4: Total | DB4: 2023 | DN4: Total | DO4: 2024 | EA4: Total | EB4: 2025 | EN4: Total | EO4: 2026 | FA4: Total | FC4: =CONCATENATE("Var.% ",FF4,"/",FF4-1) -> Var.% 2025/2024 | FE4: =FF4-1 -> 2024 | FF4: =YEAR(FC5) -> 2025 | FH4: PARA COMPROBAR
B5: 42005 | C5: 42036 | D5: 42064 | E5: 42095 | F5: 42125 | G5: 42156 | H5: 42186 | I5: 42217 | J5: 42248 | K5: 42278 | L5: 42309 | M5: 42339 | N5: =YEAR(M5) -> 2015 | O5: 42370 | P5: 42401 | Q5: 42430 | R5: 42461 | S5: 42491 | T5: 42522 | U5: 42552 | V5: 42583 | W5: 42614 | X5: 42644 | Y5: 42675 | Z5: 42705 | AA5: =YEAR(Z5) -> 2016 | AB5: 42736 | AC5: 42767 | AD5: 42795 | AE5: 42826 | AF5: 42856 | AG5: 42887 | AH5: 42917 | AI5: 42948 | AJ5: 42979 | AK5: 43009 | AL5: 43040 | AM5: 43070 | AN5: =YEAR(AM5) -> 2017 | AO5: 43101 | AP5: 43132 | AQ5: 43160 | AR5: 43191 | AS5: 43221 | AT5: 43252 | AU5: 43282 | AV5: 43313 | AW5: 43344 | AX5: 43374 | AY5: 43405 | AZ5: 43435 | BA5: =YEAR(AZ5) -> 2018 | BB5: 43466 | BC5: 43497 | BD5: 43525 | BE5: 43556 | BF5: 43586 | BG5: 43617 | BH5: 43647 | BI5: 43678 | BJ5: 43709 | BK5: 43739 | BL5: 43770 | BM5: 43800 | BN5: =YEAR(BM5) -> 2019 | BO5: 43831 | BP5: 43862 | BQ5: 43891 | BR5: 43922 | BS5: 43952 | BT5: 43983 | BU5: 44013 | BV5: 44044 | BW5: 44075 | BX5: 44105 | BY5: 44136 | BZ5: 44166 | CA5: =YEAR(BZ5) -> 2020 | CB5: 44197 | CC5: 44228 | CD5: 44256 | CE5: 44287 | CF5: 44317 | CG5: 44348 | CH5: 44378 | CI5: 44409 | CJ5: 44440 | CK5: 44470 | CL5: 44501 | CM5: 44531 | CN5: =YEAR(CM5) -> 2021 | CO5: 44562 | CP5: 44593 | CQ5: 44621 | CR5: 44652 | CS5: 44682 | CT5: 44713 | CU5: 44743 | CV5: 44774 | CW5: 44805 | CX5: 44835 | CY5: 44866 | CZ5: 44896 | DA5: =YEAR(CZ5) -> 2022 | DB5: 44927 | DC5: 44958 | DD5: 44986 | DE5: 45017 | DF5: 45047 | DG5: 45078 | DH5: 45108 | DI5: 45139 | DJ5: 45170 | DK5: 45200 | DL5: 45231 | DM5: 45261 | DN5: =YEAR(DM5) -> 2023 | DO5: 45292 | DP5: 45323 | DQ5: 45352 | DR5: 45383 | DS5: 45413 | DT5: 45444 | DU5: 45474 | DV5: 45505 | DW5: 45536 | DX5: 45566 | DY5: 45597 | DZ5: 45627 | EA5: =YEAR(DZ5) -> 2024 | EB5: 45658 | EC5: 45689 | ED5: 45717 | EE5: 45748 | EF5: 45778 | EG5: 45809 | EH5: 45839 | EI5: 45870 | EJ5: 45901 | EK5: 45931 | EL5: 45962 | EM5: 45992 | EN5: =YEAR(EM5) -> 2025 | EO5: 46023 | EP5: 46054 | EQ5: 46082 | ER5: 46113 | ES5: 46143 | ET5: 46174 | EU5: 46204 | EV5: 46235 | EW5: 46266 | EX5: 46296 | EY5: 46327 | EZ5: 46357 | FA5: =YEAR(EZ5) -> 2026 | FC5: =EL5 -> 45962 | FD5: =CONCATENATE("Ene.-",TEXT(FC5,"MMM.")) -> Ene.-Nov. | FE5: =FD5 -> Ene.-Nov. | FF5: =FD5 -> Ene.-Nov. | FH5: NO BORRRAR
