Workbook
Name SMN.AGRO.DATE: '01.XLS'!$B$5:$JN$5
Name SMN.AGRO.NAME: '01.XLS'!$A$7:$A$59
Name SMN.AGRO.VAL: '01.XLS'!$B$7:$JN$59
Name SMN.ASERRADA.DATE: '09.XLS'!$B$5:$LN$5
Name SMN.ASERRADA.NAME: '09.XLS'!$A$7:$A$39
Name SMN.ASERRADA.VAL: '09.XLS'!$B$7:$LN$39
Name SMN.COSECHA.DATE: '05.XLS'!$B$5:$KA$5
Name SMN.COSECHA.NAME: '05.XLS'!$A$7:$A$41
Name SMN.COSECHA.VAL: '05.XLS'!$B$7:$KA$41
Name SMN.GGL.DATE: 'GASTO G.L.'!$B$5:$IN$5
Name SMN.GGL.NAME: 'GASTO G.L.'!$A$7:$A$21
Name SMN.GGL.VAL: 'GASTO G.L.'!$B$7:$IN$21
Name SMN.GGN.DATE: 'GASTO G.N.'!$B$5:$IN$5
Name SMN.GGN.NAME: 'GASTO G.N.'!$A$7:$A$21
Name SMN.GGN.VAL: 'GASTO G.N.'!$B$7:$IN$21
Name SMN.GGR.DATE: 'GASTO G.R.'!$B$5:$IN$5
Name SMN.GGR.NAME: 'GASTO G.R.'!$A$7:$A$21
Name SMN.GGR.VAL: 'GASTO G.R.'!$B$7:$IN$21
Name SMN.IGL.DATE: 'INVERSION G.L.'!$B$5:$IN$5
Name SMN.IGL.NAME: 'INVERSION G.L.'!$A$7:$A$37
Name SMN.IGL.VAL: 'INVERSION G.L.'!$B$7:$IN$37
Name SMN.IGN.DATE: 'INVERSION G.N.'!$B$5:$IN$5
Name SMN.IGN.NAME: 'INVERSION G.N.'!$A$7:$A$37
Name SMN.IGN.VAL: 'INVERSION G.N.'!$B$7:$IN$37
Name SMN.IGR.DATE: 'INVERSION G.R.'!$B$5:$IN$5
Name SMN.IGR.NAME: 'INVERSION G.R.'!$A$7:$A$38
Name SMN.IGR.VAL: 'INVERSION G.R.'!$B$7:$IN$38
Name SMN.MANUFACTURA.DATE: '10 - Base 2007'!$B$5:$KA$5
Name SMN.MANUFACTURA.NAME: '10 - Base 2007'!$A$7:$A$20
Name SMN.MANUFACTURA.VAL: '10 - Base 2007'!$B$7:$KA$20
Name SMN.MANUFACTURAVAR.DATE: '10 - Base 2007'!$B$27:$KA$27
Name SMN.MANUFACTURAVAR.NAME: '10 - Base 2007'!$A$29:$A$42
Name SMN.MANUFACTURAVAR.VAL: '10 - Base 2007'!$B$29:$KA$42
Name SMN.PESCA.DATE: '07.XLS'!$B$5:$JN$5
Name SMN.PESCA.NAME: '07.XLS'!$A$7:$A$24
Name SMN.PESCA.VAL: '07.XLS'!$B$7:$JN$24
Name SMN.ROLLIZA.DATE: '08.XLS'!$B$5:$LN$5
Name SMN.ROLLIZA.NAME: '08.XLS'!$A$7:$A$39
Name SMN.ROLLIZA.VAL: '08.XLS'!$B$7:$LN$39
Name SMN.SIEMBRA.DATE: '03.XLS'!$B$5:$JN$5
Name SMN.SIEMBRA.NAME: '03.XLS'!$A$7:$A$38
Name SMN.SIEMBRA.VAL: '03.XLS'!$B$7:$JN$38
Name SMN.X.DATE: '14.XLS'!$B$5:$KA$5
Name SMN.X.NAME: '14.XLS'!$A$7:$A$36
Name SMN.X.VAL: '14.XLS'!$B$7:$KA$36

Sheet 01.XLS
A1: Cuadro Nº 01
A2: SAN MARTÍN: PRODUCCIÓN AGROPECUARIA 1/
A3: (VBP y toneladas métricas)
B4: =YEAR(B5) -> 2006 | N4: Total | O4: =YEAR(O5) -> 2007 | AA4: Total | AB4: =YEAR(AB5) -> 2008 | AN4: Total | AO4: =YEAR(AO5) -> 2009 | BA4: Total | BB4: =YEAR(BB5) -> 2010 | BN4: Total | BO4: =YEAR(BO5) -> 2011 | CA4: Total | CB4: =YEAR(CB5) -> 2012 | CN4: Total | CO4: =YEAR(CO5) -> 2013 | DA4: Total | DB4: =YEAR(DB5) -> 2014 | DN4: Total | DO4: =YEAR(DO5) -> 2015 | EA4: Total | EB4: =YEAR(EB5) -> 2016 | EN4: Total | EO4: =YEAR(EO5) -> 2017 | FA4: Total | FB4: =YEAR(FB5) -> 2018 | FN4: Total | FO4: =YEAR(FO5) -> 2019 | GA4: Total | GB4: =YEAR(GB5) -> 2020 | GN4: Total | GO4: =YEAR(GO5) -> 2021 | HA4: Total | HB4: =YEAR(HB5) -> 2022 | HN4: Total | HO4: =YEAR(HO5) -> 2023 | IA4: Total | IB4: =YEAR(IB5) -> 2024 | IN4: Total | IO4: =YEAR(IO5) -> 2025 | JA4: Total | JB4: =YEAR(JB5) -> 2026 | JN4: Total | JP4: =CONCATENATE("Var.% ",JS4,"/",JS4-1) -> Var.% 2025/2024 | JR4: =JS4-1 -> 2024 | JS4: =YEAR(JP5) -> 2025 | JU4: PARA COMPROBAR
B5: 38718 | C5: 38749 | D5: 38777 | E5: 38808 | F5: 38838 | G5: 38869 | H5: 38899 | I5: 38930 | J5: 38961 | K5: 38991 | L5: 39022 | M5: 39052 | N5: =YEAR(M5) -> 2006 | O5: 39083 | P5: 39114 | Q5: 39142 | R5: 39173 | S5: 39203 | T5: 39234 | U5: 39264 | V5: 39295 | W5: 39326 | X5: 39356 | Y5: 39387 | Z5: 39417 | AA5: =YEAR(Z5) -> 2007 | AB5: 39448 | AC5: 39479 | AD5: 39508 | AE5: 39539 | AF5: 39569 | AG5: 39600 | AH5: 39630 | AI5: 39661 | AJ5: 39692 | AK5: 39722 | AL5: 39753 | AM5: 39783 | AN5: =YEAR(AM5) -> 2008 | AO5: 39814 | AP5: 39845 | AQ5: 39873 | AR5: 39904 | AS5: 39934 | AT5: 39965 | AU5: 39995 | AV5: 40026 | AW5: 40057 | AX5: 40087 | AY5: 40118 | AZ5: 40148 | BA5: =YEAR(AZ5) -> 2009 | BB5: 40179 | BC5: 40210 | BD5: 40238 | BE5: 40269 | BF5: 40299 | BG5: 40330 | BH5: 40360 | BI5: 40391 | BJ5: 40422 | BK5: 40452 | BL5: 40483 | BM5: 40513 | BN5: =YEAR(BM5) -> 2010 | BO5: 40544 | BP5: 40575 | BQ5: 40603 | BR5: 40634 | BS5: 40664 | BT5: 40695 | BU5: 40725 | BV5: 40756 | BW5: 40787 | BX5: 40817 | BY5: 40848 | BZ5: 40878 | CA5: =YEAR(BZ5) -> 2011 | CB5: 40909 | CC5: 40940 | CD5: 40969 | CE5: 41000 | CF5: 41030 | CG5: 41061 | CH5: 41091 | CI5: 41122 | CJ5: 41153 | CK5: 41183 | CL5: 41214 | CM5: 41244 | CN5: =YEAR(CM5) -> 2012 | CO5: 41275 | CP5: 41306 | CQ5: 41334 | CR5: 41365 | CS5: 41395 | CT5: 41426 | CU5: 41456 | CV5: 41487 | CW5: 41518 | CX5: 41548 | CY5: 41579 | CZ5: 41609 | DA5: =YEAR(CZ5) -> 2013 | DB5: 41640 | DC5: 41671 | DD5: 41699 | DE5: 41730 | DF5: 41760 | DG5: 41791 | DH5: 41821 | DI5: 41852 | DJ5: 41883 | DK5: 41913 | DL5: 41944 | DM5: 41974 | DN5: =YEAR(DM5) -> 2014 | DO5: 42005 | DP5: 42036 | DQ5: 42064 | DR5: 42095 | DS5: 42125 | DT5: 42156 | DU5: 42186 | DV5: 42217 | DW5: 42248 | DX5: 42278 | DY5: 42309 | DZ5: 42339 | EA5: =YEAR(DZ5) -> 2015 | EB5: 42370 | EC5: 42401 | ED5: 42430 | EE5: 42461 | EF5: 42491 | EG5: 42522 | EH5: 42552 | EI5: 42583 | EJ5: 42614 | EK5: 42644 | EL5: 42675 | EM5: 42705 | EN5: =YEAR(EM5) -> 2016 | EO5: 42736 | EP5: 42767 | EQ5: 42795 | ER5: 42826 | ES5: 42856 | ET5: 42887 | EU5: 42917 | EV5: 42948 | EW5: 42979 | EX5: 43009 | EY5: 43040 | EZ5: 43070 | FA5: =YEAR(EZ5) -> 2017 | FB5: 43101 | FC5: 43132 | FD5: 43160 | FE5: 43191 | FF5: 43221 | FG5: 43252 | FH5: 43282 | FI5: 43313 | FJ5: 43344 | FK5: 43374 | FL5: 43405 | FM5: 43435 | FN5: =YEAR(FM5) -> 2018 | FO5: 43466 | FP5: 43497 | FQ5: 43525 | FR5: 43556 | FS5: 43586 | FT5: 43617 | FU5: 43647 | FV5: 43678 | FW5: 43709 | FX5: 43739 | FY5: 43770 | FZ5: 43800 | GA5: =YEAR(FZ5) -> 2019 | GB5: 43831 | GC5: 43862 | GD5: 43891 | GE5: 43922 | GF5: 43952 | GG5: 43983 | GH5: 44013 | GI5: 44044 | GJ5: 44075 | GK5: 44105 | GL5: 44136 | GM5: 44166 | GN5: =YEAR(GM5) -> 2020 | GO5: 44197 | GP5: 44228 | GQ5: 44256 | GR5: 44287 | GS5: 44317 | GT5: 44348 | GU5: 44378 | GV5: 44409 | GW5: 44440 | GX5: 44470 | GY5: 44501 | GZ5: 44531 | HA5: =YEAR(GZ5) -> 2021 | HB5: 44562 | HC5: 44593 | HD5: 44621 | HE5: 44652 | HF5: 44682 | HG5: 44713 | HH5: 44743 | HI5: 44774 | HJ5: 44805 | HK5: 44835 | HL5: 44866 | HM5: 44896 | HN5: =YEAR(HM5) -> 2022 | HO5: 44927 | HP5: 44958 | HQ5: 44986 | HR5: 45017 | HS5: 45047 | HT5: 45078 | HU5: 45108 | HV5: 45139 | HW5: 45170 | HX5: 45200 | HY5: 45231 | HZ5: 45261 | IA5: =YEAR(HZ5) -> 2023 | IB5: 45292 | IC5: 45323 | ID5: 45352 | IE5: 45383 | IF5: 45413 | IG5: 45444 | IH5: 45474 | II5: 45505 | IJ5: 45536 | IK5: 45566 | IL5: 45597 | IM5: 45627 | IN5: =YEAR(IM5) -> 2024 | IO5: 45658 | IP5: 45689 | IQ5: 45717 | IR5: 45748 | IS5: 45778 | IT5: 45809 | IU5: 45839 | IV5: 45870 | IW5: 45901 | IX5: 45931 | IY5: 45962 | IZ5: 45992 | JA5: =YEAR(IZ5) -> 2025 | JB5: 46023 | JC5: 46054 | JD5: 46082 | JE5: 46113 | JF5: 46143 | JG5: 46174 | JH5: 46204 | JI5: 46235 | JJ5: 46266 | JK5: 46296 | JL5: 46327 | JM5: 46357 | JN5: =YEAR(JM5) -> 2026 | JP5: =IZ5 -> 45992 | JQ5: =CONCATENATE("Ene.-",TEXT(JP5,"MMM.")) -> Ene.-Dic. | JR5: =JQ5 -> Ene.-Dic. | JS5: =JQ5 -> Ene.-Dic. | JU5: NO BORRRAR
A7: TOTAL AGROPECUARIO 2/ | B7: =SUM(B8:B9) -> 116436.32 | C7: =SUM(C8:C9) -> 93654.678 | D7: =SUM(D8:D9) -> 89011.912 | E7: =SUM(E8:E9) -> 114832.57 | F7: =SUM(F8:F9) -> 136755.18 | G7: =SUM(G8:G9) -> 127371.48 | H7: =SUM(H8:H9) -> 112513.93 | I7: =SUM(I8:I9) -> 90722.123 | ... M7: =SUM(M8:M9) -> 59007.12 | N7: =SUM(B7:M7) -> 1151958.2 | O7: =SUM(O8:O9) -> 76416.141 | P7: =SUM(P8:P9) -> 92823.466 | Q7: =SUM(Q8:Q9) -> 89473.759 | R7: =SUM(R8:R9) -> 106303.26 | S7: =SUM(S8:S9) -> 120719.38 | T7: =SUM(T8:T9) -> 112994.52 | U7: =SUM(U8:U9) -> 107860.58 | V7: =SUM(V8:V9) -> 105132.3 | ... Z7: =SUM(Z8:Z9) -> 78374.89 | AA7: =SUM(O7:Z7) -> 1119947.2 | AB7: =SUM(AB8:AB9) -> 91518.694 | AC7: =SUM(AC8:AC9) -> 120214.13 | AD7: =SUM(AD8:AD9) -> 121111.67 | AE7: =SUM(AE8:AE9) -> 126628.07 | AF7: =SUM(AF8:AF9) -> 145682.82 | AG7: =SUM(AG8:AG9) -> 123929.56 | AH7: =SUM(AH8:AH9) -> 126608.68 | AI7: =SUM(AI8:AI9) -> 98743.35 | ... AM7: =SUM(AM8:AM9) -> 99183.693 | AN7: =SUM(AB7:AM7) -> 1337755.3 | AO7: =SUM(AO8:AO9) -> 90986.466 | AP7: =SUM(AP8:AP9) -> 114990.97 | AQ7: =SUM(AQ8:AQ9) -> 126026.23 | AR7: =SUM(AR8:AR9) -> 158061.35 | AS7: =SUM(AS8:AS9) -> 163815.28 | AT7: =SUM(AT8:AT9) -> 149662.49 | AU7: =SUM(AU8:AU9) -> 125996.51 | AV7: =SUM(AV8:AV9) -> 101120.76 | ... AZ7: =SUM(AZ8:AZ9) -> 93261.074 | BA7: =SUM(AO7:AZ7) -> 1415023.8 | BB7: =SUM(BB8:BB9) -> 90457.141 | BC7: =SUM(BC8:BC9) -> 107749.79 | BD7: =SUM(BD8:BD9) -> 117490.06 | BE7: =SUM(BE8:BE9) -> 137328.3 | BF7: =SUM(BF8:BF9) -> 179714.17 | BG7: =SUM(BG8:BG9) -> 148783 | BH7: =SUM(BH8:BH9) -> 118285.66 | BI7: =SUM(BI8:BI9) -> 99755.084 | ... BM7: =SUM(BM8:BM9) -> 99683.061 | BN7: =SUM(BB7:BM7) -> 1410026.9 | BO7: =SUM(BO8:BO9) -> 91432.745 | BP7: =SUM(BP8:BP9) -> 113571.9 | BQ7: =SUM(BQ8:BQ9) -> 122888.63 | BR7: =SUM(BR8:BR9) -> 184087.08 | BS7: =SUM(BS8:BS9) -> 183431.99 | BT7: =SUM(BT8:BT9) -> 161677.38 | BU7: =SUM(BU8:BU9) -> 127986.75 | BV7: =SUM(BV8:BV9) -> 110754.67 | ... BZ7: =SUM(BZ8:BZ9) -> 99402.03 | CA7: =SUM(BO7:BZ7) -> 1503639.4 | CB7: =SUM(CB8:CB9) -> 124892.34 | CC7: =SUM(CC8:CC9) -> 133483.77 | CD7: =SUM(CD8:CD9) -> 123360.39 | CE7: =SUM(CE8:CE9) -> 188518.56 | CF7: =SUM(CF8:CF9) -> 215536.1 | CG7: =SUM(CG8:CG9) -> 192359.33 | CH7: =SUM(CH8:CH9) -> 140291.73 | CI7: =SUM(CI8:CI9) -> 113371.61 | ... CM7: =SUM(CM8:CM9) -> 105552.58 | CN7: =SUM(CB7:CM7) -> 1681144.8 | CO7: =SUM(CO8:CO9) -> 103907.23 | CP7: =SUM(CP8:CP9) -> 122368.48 | CQ7: =SUM(CQ8:CQ9) -> 140133.38 | CR7: =SUM(CR8:CR9) -> 171775.13 | CS7: =SUM(CS8:CS9) -> 182674.14 | CT7: =SUM(CT8:CT9) -> 174700.2 | CU7: =SUM(CU8:CU9) -> 126969.2 | CV7: =SUM(CV8:CV9) -> 120529.54 | ... CZ7: =SUM(CZ8:CZ9) -> 118249.21 | DA7: =SUM(CO7:CZ7) -> 1611319.1 | DB7: =SUM(DB8:DB9) -> 124239.64 | DC7: =SUM(DC8:DC9) -> 135953.24 | DD7: =SUM(DD8:DD9) -> 150064.82 | DE7: =SUM(DE8:DE9) -> 176177.08 | DF7: =SUM(DF8:DF9) -> 210017.86 | DG7: =SUM(DG8:DG9) -> 203398.47 | DH7: =SUM(DH8:DH9) -> 160358.2 | DI7: =SUM(DI8:DI9) -> 132271.23 | ... DM7: =SUM(DM8:DM9) -> 127603.98 | DN7: =SUM(DB7:DM7) -> 1787130.9 | DO7: =SUM(DO8:DO9) -> 116371.87 | DP7: =SUM(DP8:DP9) -> 132311.15 | DQ7: =SUM(DQ8:DQ9) -> 158283.69 | DR7: =SUM(DR8:DR9) -> 221459.28 | DS7: =SUM(DS8:DS9) -> 262569.88 | DT7: =SUM(DT8:DT9) -> 222808.71 | DU7: =SUM(DU8:DU9) -> 165863.96 | DV7: =SUM(DV8:DV9) -> 133179.79 | ... DZ7: =SUM(DZ8:DZ9) -> 150111.92 | EA7: =SUM(DO7:DZ7) -> 1942637.9 | EB7: =SUM(EB8:EB9) -> 117931.44 | EC7: =SUM(EC8:EC9) -> 143436.93 | ED7: =SUM(ED8:ED9) -> 138925.84 | EE7: =SUM(EE8:EE9) -> 245919.15 | EF7: =SUM(EF8:EF9) -> 269605.82 | EG7: =SUM(EG8:EG9) -> 228013.33 | EH7: =SUM(EH8:EH9) -> 172861.47 | EI7: =SUM(EI8:EI9) -> 138523.22 | ... EM7: =SUM(EM8:EM9) -> 145574.86 | EN7: =SUM(EB7:EM7) -> 1996861.8 | EO7: =SUM(EO8:EO9) -> 130238.12 | EP7: =SUM(EP8:EP9) -> 147756.95 | EQ7: =SUM(EQ8:EQ9) -> 166398.02 | ER7: =SUM(ER8:ER9) -> 271127.52 | ES7: =SUM(ES8:ES9) -> 293038.26 | ET7: =SUM(ET8:ET9) -> 237568.97 | EU7: =SUM(EU8:EU9) -> 183258.92 | EV7: =SUM(EV8:EV9) -> 148854.95 | ... EZ7: =SUM(EZ8:EZ9) -> 153475.19 | FA7: =SUM(EO7:EZ7) -> 2184103.2 | FB7: =SUM(FB8:FB9) -> 149748.41 | FC7: =SUM(FC8:FC9) -> 169078.13 | FD7: =SUM(FD8:FD9) -> 187666.98 | FE7: =SUM(FE8:FE9) -> 281507.62 | FF7: =SUM(FF8:FF9) -> 304931.15 | FG7: =SUM(FG8:FG9) -> 219169.43 | FH7: =SUM(FH8:FH9) -> 173199.56 | FI7: =SUM(FI8:FI9) -> 154873.18 | ... FM7: =SUM(FM8:FM9) -> 150344.53 | FN7: =SUM(FB7:FM7) -> 2206735.3 | FO7: =SUM(FO8:FO9) -> 149243.42 | FP7: =SUM(FP8:FP9) -> 166295.46 | FQ7: =SUM(FQ8:FQ9) -> 182401.32 | FR7: =SUM(FR8:FR9) -> 274682.24 | FS7: =SUM(FS8:FS9) -> 252237.34 | FT7: =SUM(FT8:FT9) -> 235349.64 | FU7: =SUM(FU8:FU9) -> 200074.5 | FV7: =SUM(FV8:FV9) -> 147181.8 | ... FZ7: =SUM(FZ8:FZ9) -> 162005.76 | GA7: =SUM(FO7:FZ7) -> 2189083.2 | GB7: =SUM(GB8:GB9) -> 166332.4 | GC7: =SUM(GC8:GC9) -> 201933.86 | GD7: =SUM(GD8:GD9) -> 212122.78 | GE7: =SUM(GE8:GE9) -> 296956.92 | GF7: =SUM(GF8:GF9) -> 271866.36 | GG7: =SUM(GG8:GG9) -> 241006.26 | GH7: =SUM(GH8:GH9) -> 188169.12 | GI7: =SUM(GI8:GI9) -> 166923.58 | ... GM7: =SUM(GM8:GM9) -> 162322.41 | GN7: =SUM(GB7:GM7) -> 2376516.6 | GO7: =SUM(GO8:GO9) -> 151091.36 | GP7: =SUM(GP8:GP9) -> 194691.96 | GQ7: =SUM(GQ8:GQ9) -> 187032.44 | GR7: =SUM(GR8:GR9) -> 278540.33 | GS7: =SUM(GS8:GS9) -> 272569.96 | GT7: =SUM(GT8:GT9) -> 257379.97 | GU7: =SUM(GU8:GU9) -> 210375.63 | GV7: =SUM(GV8:GV9) -> 162344.96 | ... GZ7: =SUM(GZ8:GZ9) -> 189829.5 | HA7: =SUM(GO7:GZ7) -> 2415615 | HB7: =SUM(HB8:HB9) -> 179593.61 | HC7: =SUM(HC8:HC9) -> 188242.01 | HD7: =SUM(HD8:HD9) -> 198297.76 | HE7: =SUM(HE8:HE9) -> 270144.64 | HF7: =SUM(HF8:HF9) -> 272155.56 | HG7: =SUM(HG8:HG9) -> 265138.03 | HH7: =SUM(HH8:HH9) -> 217722.38 | HI7: =SUM(HI8:HI9) -> 176808.33 | ... HM7: =SUM(HM8:HM9) -> 182672.46 | HN7: =SUM(HB7:HM7) -> 2444593.4 | HO7: =SUM(HO8:HO9) -> 196466.89 | HP7: =SUM(HP8:HP9) -> 203087.04 | HQ7: =SUM(HQ8:HQ9) -> 220183.18 | HR7: =SUM(HR8:HR9) -> 276672.84 | HS7: =SUM(HS8:HS9) -> 289703.08 | HT7: =SUM(HT8:HT9) -> 287343.94 | HU7: =SUM(HU8:HU9) -> 219942.09 | HV7: =SUM(HV8:HV9) -> 177320.79 | ... HZ7: =SUM(HZ8:HZ9) -> 182251.55 | IA7: =SUM(HO7:HZ7) -> 2574439.4 | IB7: =SUM(IB8:IB9) -> 188333.85 | IC7: =SUM(IC8:IC9) -> 198469.16 | ID7: =SUM(ID8:ID9) -> 208831.6 | IE7: =SUM(IE8:IE9) -> 275260.05 | IF7: =SUM(IF8:IF9) -> 300346.3 | IG7: =SUM(IG8:IG9) -> 285771.01 | IH7: =SUM(IH8:IH9) -> 242523.15 | II7: =SUM(II8:II9) -> 174956.98 | ... IM7: =SUM(IM8:IM9) -> 151007.6 | IN7: =SUM(IB7:IM7) -> 2467534.9 | IO7: =SUM(IO8:IO9) -> 156213.19 | IP7: =SUM(IP8:IP9) -> 171672.51 | IQ7: =SUM(IQ8:IQ9) -> 224579.59 | IR7: =SUM(IR8:IR9) -> 282017.29 | IS7: =SUM(IS8:IS9) -> 303935.6 | IT7: =SUM(IT8:IT9) -> 291408.41 | IU7: =SUM(IU8:IU9) -> 253305.93 | IV7: =SUM(IV8:IV9) -> 187659.61 | ... IZ7: =SUM(IZ8:IZ9) -> 163807.48 | JA7: =SUM(IO7:IZ7) -> 2490700.8 | JB7: =SUM(JB8:JB9) -> 171817.08 | JC7: =SUM(JC8:JC9) -> 169143.26 | JD7: =SUM(JD8:JD9) -> 0 | JE7: =SUM(JE8:JE9) -> 0 | JF7: =SUM(JF8:JF9) -> 0 | JG7: =SUM(JG8:JG9) -> 0 | JH7: =SUM(JH8:JH9) -> 0 | JI7: =SUM(JI8:JI9) -> 0 | ... JM7: =SUM(JM8:JM9) -> 0 | JN7: =SUM(JB7:JM7) -> 340960.34 | JP7: =IFERROR((( _xlfn.XLOOKUP((DATE(YEAR($JP$5),MONTH($JP$5),1)),SMN.AGRO.DATE,$B7:$JN7) / _xlfn.XLOOKUP((DATE(YEAR($JP$5)-1,MONTH($JP$5),1)),SMN.AGRO.DATE,$B7:$JN7) )-1)*100,"") -> 8.4763145 | JQ7: =IFERROR(((JS7/JR7)-1)*100,"") -> 0.93882513 | JR7: =SUMIFS($B7:$JN7,SMN.AGRO.DATE,">="&DATE(YEAR($JP$5)-1,1,1),SMN.AGRO.DATE,"<="&DATE(YEAR($JP$5)-1,MONTH($JP$5),1)) -> 2467534.9 | JS7: =SUMIFS($B7:$JN7,SMN.AGRO.DATE,">="&DATE(YEAR($JP$5),1,1),SMN.AGRO.DATE,"<="&$JP$5) -> 2490700.8
A8: TOTAL AGRÍCOLA 2/ | B8: 108531.77 | C8: 85945.052 | D8: 80660.203 | E8: 106313.83 | F8: 128519.71 | G8: 118497.68 | H8: 104340.73 | I8: 81941.2 | J8: 59079.982 | K8: 63520.534 | L8: 62314.486 | M8: 49561.85 | N8: =SUM(B8:M8) -> 1049227 | O8: 67274.001 | P8: 84148.432 | Q8: 79879.234 | R8: 96546.007 | S8: 111044.59 | T8: 102267.77 | U8: 97615.615 | V8: 94680.654 | W8: 63046.033 | X8: 60980.854 | Y8: 74687.501 | Z8: 67340.062 | AA8: =SUM(O8:Z8) -> 999510.75 | AB8: 79288.584 | AC8: 107551.71 | AD8: 107985.29 | AE8: 113608.19 | AF8: 132465.34 | AG8: 109841.36 | AH8: 113497.51 | AI8: 85175.387 | AJ8: 75196.329 | AK8: 73561.895 | AL8: 92792.11 | AM8: 83475.142 | AN8: =SUM(AB8:AM8) -> 1174438.8 | AO8: 76475.439 | AP8: 99950.081 | AQ8: 110327.62 | AR8: 143709.65 | AS8: 148146.22 | AT8: 132262.47 | AU8: 110265.84 | AV8: 87064.434 | AW8: 76290.307 | AX8: 78781.295 | AY8: 94934.41 | AZ8: 77212.074 | BA8: =SUM(AO8:AZ8) -> 1235419.8 | BB8: 78078.182 | BC8: 94758.629 | BD8: 104745.78 | BE8: 124620.93 | BF8: 166296.83 | BG8: 135561 | BH8: 105803.84 | BI8: 86841.577 | BJ8: 82228.685 | BK8: 85924.676 | BL8: 102035.79 | BM8: 86193.199 | BN8: =SUM(BB8:BM8) -> 1253089.1 | BO8: 77478.535 | BP8: 99460.454 | BQ8: 108379 | BR8: 169818.16 | BS8: 168764.49 | BT8: 146031.89 | BU8: 112528.9 | BV8: 95144.435 | BW8: 83672.187 | BX8: 87203.298 | BY8: 90571.55 | BZ8: 82143.311 | CA8: =SUM(BO8:BZ8) -> 1321196.2 | CB8: 108565.81 | CC8: 117373.41 | CD8: 108134.15 | CE8: 173489.61 | CF8: 198085.18 | CG8: 175683.38 | CH8: 123119.52 | CI8: 97172.46 | CJ8: 85893.789 | CK8: 93630.749 | CL8: 115539.31 | CM8: 90376.625 | CN8: =SUM(CB8:CM8) -> 1487064 | CO8: 88457.363 | CP8: 106253.72 | CQ8: 124953.75 | CR8: 155672.01 | CS8: 167317.65 | CT8: 158620.1 | CU8: 111134.37 | CV8: 105581.76 | CW8: 92838.116 | CX8: 100526 | CY8: 108301.15 | CZ8: 101252.98 | DA8: =SUM(CO8:CZ8) -> 1420909 | DB8: 107195.56 | DC8: 119358.63 | DD8: 131886.42 | DE8: 158651.52 | DF8: 192545.21 | DG8: 186110.8 | DH8: 141860.33 | DI8: 113553.8 | DJ8: 89157.906 | DK8: 108498.36 | DL8: 118530.29 | DM8: 110265.68 | DN8: =SUM(DB8:DM8) -> 1577614.5 | DO8: 98978.293 | DP8: 115550.95 | DQ8: 139901.12 | DR8: 203492.97 | DS8: 243770.48 | DT8: 204366.94 | DU8: 146566.19 | DV8: 114375.68 | DW8: 107696.35 | DX8: 102379.89 | DY8: 111967.67 | DZ8: 130103.19 | EA8: =SUM(DO8:DZ8) -> 1719149.7 | EB8: 99361.917 | EC8: 125255.3 | ED8: 119438.32 | EE8: 226310.73 | EF8: 250020.86 | EG8: 207652.14 | EH8: 151959.05 | EI8: 117820.72 | EJ8: 105137.98 | EK8: 107906.28 | EL8: 122568.38 | EM8: 123405.77 | EN8: =SUM(EB8:EM8) -> 1756837.5 | EO8: 110238.24 | EP8: 128405.14 | EQ8: 146428.48 | ER8: 250283.95 | ES8: 272296.08 | ET8: 217431.37 | EU8: 162553.04 | EV8: 127701.22 | EW8: 125022.22 | EX8: 137510.18 | EY8: 128270.12 | EZ8: 131244.15 | FA8: =SUM(EO8:EZ8) -> 1937384.2 | FB8: 128980.28 | FC8: 148882.92 | FD8: 166074.5 | FE8: 260263.15 | FF8: 282834.53 | FG8: 197958.29 | FH8: 151031.96 | FI8: 133121.46 | FJ8: 107072.13 | FK8: 113320.55 | FL8: 134184.03 | FM8: 127710.91 | FN8: =SUM(FB8:FM8) -> 1951434.7 | FO8: 122539.17 | FP8: 140566.61 | FQ8: 156002.91 | FR8: 246628.75 | FS8: 224447.04 | FT8: 208717.95 | FU8: 171798.18 | FV8: 119522.68 | FW8: 109880.96 | FX8: 106543.26 | FY8: 124307.94 | FZ8: 133054.65 | GA8: =SUM(FO8:FZ8) -> 1864010.1 | GB8: 141301.46 | GC8: 175352.62 | GD8: 186242.18 | GE8: 270067.6 | GF8: 244949.7 | GG8: 215809.73 | GH8: 161349.38 | GI8: 141226.01 | GJ8: 124918.51 | GK8: 126016.15 | GL8: 142843.13 | GM8: 134124.29 | GN8: =SUM(GB8:GM8) -> 2064200.8 | GO8: 126412.15 | GP8: 168971.65 | GQ8: 160717.15 | GR8: 251014.73 | GS8: 244394.74 | GT8: 230931.42 | GU8: 182544.95 | GV8: 136767.05 | GW8: 137596.82 | GX8: 135544.93 | GY8: 162126.95 | GZ8: 160418.6 | HA8: =SUM(GO8:GZ8) -> 2097441.1 | HB8: 153651.92 | HC8: 161911.93 | HD8: 170986.62 | HE8: 242137.43 | HF8: 244146.88 | HG8: 238483.89 | HH8: 191038.64 | HI8: 151477.55 | HJ8: 130552.46 | HK8: 130482.51 | HL8: 157498.67 | HM8: 154627.03 | HN8: =SUM(HB8:HM8) -> 2126995.5 | HO8: 171162.31 | HP8: 177721.89 | HQ8: 193748.6 | HR8: 249438.87 | HS8: 261838.47 | HT8: 261452.37 | HU8: 194094.03 | HV8: 153311.57 | HW8: 148697.64 | HX8: 140332.62 | HY8: 159567.69 | HZ8: 154781.84 | IA8: =SUM(HO8:HZ8) -> 2266147.9 | IB8: 163273.66 | IC8: 173939.01 | ID8: 182891.34 | IE8: 247598.41 | IF8: 272446.37 | IG8: 259229.34 | IH8: 216109.7 | II8: 150392.29 | IJ8: 119832.14 | IK8: 123363.48 | IL8: 124657.59 | IM8: 123734.51 | IN8: 2157467.8 | IO8: 129811.17 | IP8: 146425.18 | IQ8: 197686.25 | IR8: 253150.49 | IS8: 274201.03 | IT8: 263954.58 | IU8: 226045.69 | IV8: 162604.49 | IW8: 127980.05 | IX8: 124425.62 | IY8: 128229.47 | IZ8: 135615.76 | JA8: 2170129.8 | JB8: 144500.16 | JC8: 142773.53 | JN8: =SUM(JB8:JM8) -> 287273.7 | JP8: =IFERROR((( _xlfn.XLOOKUP((DATE(YEAR($JP$5),MONTH($JP$5),1)),SMN.AGRO.DATE,$B8:$JN8) / _xlfn.XLOOKUP((DATE(YEAR($JP$5)-1,MONTH($JP$5),1)),SMN.AGRO.DATE,$B8:$JN8) )-1)*100,"") -> 9.6022069 | JQ8: =IFERROR(((JS8/JR8)-1)*100,"") -> 0.58688825 | JR8: =SUMIFS($B8:$JN8,SMN.AGRO.DATE,">="&DATE(YEAR($JP$5)-1,1,1),SMN.AGRO.DATE,"<="&DATE(YEAR($JP$5)-1,MONTH($JP$5),1)) -> 2157467.8 | JS8: =SUMIFS($B8:$JN8,SMN.AGRO.DATE,">="&DATE(YEAR($JP$5),1,1),SMN.AGRO.DATE,"<="&$JP$5) -> 2170129.8
A9: TOTAL PECUARIO 2/ | B9: 7904.552 | C9: 7709.6252 | D9: 8351.7082 | E9: 8518.7363 | F9: 8235.4711 | G9: 8873.8017 | H9: 8173.1973 | I9: 8780.9237 | J9: 9085.9626 | K9: 8720.253 | L9: 8931.6574 | M9: 9445.2698 | N9: =SUM(B9:M9) -> 102731.16 | O9: 9142.1404 | P9: 8675.0336 | Q9: 9594.5249 | R9: 9757.2488 | S9: 9674.7847 | T9: 10726.755 | U9: 10244.969 | V9: 10451.644 | W9: 10463.464 | X9: 10345.366 | Y9: 10325.648 | Z9: 11034.828 | AA9: =SUM(O9:Z9) -> 120436.41 | AB9: 12230.111 | AC9: 12662.423 | AD9: 13126.381 | AE9: 13019.876 | AF9: 13217.475 | AG9: 14088.199 | AH9: 13111.17 | AI9: 13567.963 | AJ9: 13977.535 | AK9: 14728.905 | AL9: 13877.849 | AM9: 15708.551 | AN9: =SUM(AB9:AM9) -> 163316.44 | AO9: 14511.027 | AP9: 15040.884 | AQ9: 15698.613 | AR9: 14351.698 | AS9: 15669.062 | AT9: 17400.017 | AU9: 15730.667 | AV9: 14056.321 | AW9: 14052.637 | AX9: 13364 | AY9: 13680 | AZ9: 16049 | BA9: =SUM(AO9:AZ9) -> 179603.93 | BB9: 12378.959 | BC9: 12991.162 | BD9: 12744.278 | BE9: 12707.379 | BF9: 13417.337 | BG9: 13222.002 | BH9: 12481.822 | BI9: 12913.507 | BJ9: 13756.811 | BK9: 13776.167 | BL9: 13058.448 | BM9: 13489.862 | BN9: =SUM(BB9:BM9) -> 156937.73 | BO9: 13954.21 | BP9: 14111.448 | BQ9: 14509.627 | BR9: 14268.919 | BS9: 14667.507 | BT9: 15645.499 | BU9: 15457.854 | BV9: 15610.232 | BW9: 15364.176 | BX9: 14896.487 | BY9: 16698.518 | BZ9: 17258.718 | CA9: =SUM(BO9:BZ9) -> 182443.19 | CB9: 16326.535 | CC9: 16110.366 | CD9: 15226.231 | CE9: 15028.951 | CF9: 17450.915 | CG9: 16675.956 | CH9: 17172.204 | CI9: 16199.15 | CJ9: 17816.497 | CK9: 14730.845 | CL9: 16167.179 | CM9: 15175.956 | CN9: =SUM(CB9:CM9) -> 194080.78 | CO9: 15449.871 | CP9: 16114.758 | CQ9: 15179.629 | CR9: 16103.115 | CS9: 15356.487 | CT9: 16080.099 | CU9: 15834.832 | CV9: 14947.786 | CW9: 15462.428 | CX9: 15901.935 | CY9: 16982.94 | CZ9: 16996.239 | DA9: =SUM(CO9:CZ9) -> 190410.12 | DB9: 17044.086 | DC9: 16594.61 | DD9: 18178.401 | DE9: 17525.559 | DF9: 17472.655 | DG9: 17287.668 | DH9: 18497.872 | DI9: 18717.433 | DJ9: 17421.116 | DK9: 16794.047 | DL9: 16644.675 | DM9: 17338.293 | DN9: =SUM(DB9:DM9) -> 209516.41 | DO9: 17393.578 | DP9: 16760.193 | DQ9: 18382.564 | DR9: 17966.31 | DS9: 18799.404 | DT9: 18441.764 | DU9: 19297.775 | DV9: 18804.105 | DW9: 18839.137 | DX9: 19612.337 | DY9: 19182.22 | DZ9: 20008.739 | EA9: =SUM(DO9:DZ9) -> 223488.13 | EB9: 18569.522 | EC9: 18181.625 | ED9: 19487.517 | EE9: 19608.426 | EF9: 19584.953 | EG9: 20361.19 | EH9: 20902.421 | EI9: 20702.496 | EJ9: 20125.141 | EK9: 20308.473 | EL9: 20023.472 | EM9: 22169.093 | EN9: =SUM(EB9:EM9) -> 240024.33 | EO9: 19999.879 | EP9: 19351.819 | EQ9: 19969.542 | ER9: 20843.566 | ES9: 20742.18 | ET9: 20137.602 | EU9: 20705.876 | EV9: 21153.725 | EW9: 20882.32 | EX9: 20479.88 | EY9: 20221.599 | EZ9: 22231.037 | FA9: =SUM(EO9:EZ9) -> 246719.02 | FB9: 20768.127 | FC9: 20195.209 | FD9: 21592.482 | FE9: 21244.469 | FF9: 22096.615 | FG9: 21211.138 | FH9: 22167.599 | FI9: 21751.718 | FJ9: 20791.354 | FK9: 20628.52 | FL9: 20219.756 | FM9: 22633.628 | FN9: =SUM(FB9:FM9) -> 255300.62 | FO9: 26704.254 | FP9: 25728.845 | FQ9: 26398.417 | FR9: 28053.493 | FS9: 27790.298 | FT9: 26631.691 | FU9: 28276.322 | FV9: 27659.112 | FW9: 26784.194 | FX9: 26353.718 | FY9: 25741.626 | FZ9: 28951.101 | GA9: =SUM(FO9:FZ9) -> 325073.07 | GB9: 25030.947 | GC9: 26581.239 | GD9: 25880.593 | GE9: 26889.313 | GF9: 26916.663 | GG9: 25196.533 | GH9: 26819.739 | GI9: 25697.564 | GJ9: 25632.356 | GK9: 25023.349 | GL9: 24449.429 | GM9: 28198.114 | GN9: =SUM(GB9:GM9) -> 312315.84 | GO9: 24679.209 | GP9: 25720.308 | GQ9: 26315.283 | GR9: 27525.601 | GS9: 28175.218 | GT9: 26448.546 | GU9: 27830.682 | GV9: 25577.909 | GW9: 25298.099 | GX9: 25740.932 | GY9: 25451.212 | GZ9: 29410.903 | HA9: =SUM(GO9:GZ9) -> 318173.9 | HB9: 25941.691 | HC9: 26330.073 | HD9: 27311.142 | HE9: 28007.209 | HF9: 28008.683 | HG9: 26654.141 | HH9: 26683.744 | HI9: 25330.78 | HJ9: 25151.08 | HK9: 25277.621 | HL9: 24856.288 | HM9: 28045.426 | HN9: =SUM(HB9:HM9) -> 317597.88 | HO9: 25304.586 | HP9: 25365.152 | HQ9: 26434.581 | HR9: 27233.969 | HS9: 27864.603 | HT9: 25891.569 | HU9: 25848.065 | HV9: 24009.221 | HW9: 24067.138 | HX9: 24394.337 | HY9: 24408.566 | HZ9: 27469.713 | IA9: =SUM(HO9:HZ9) -> 308291.5 | IB9: 25060.19 | IC9: 24530.149 | ID9: 25940.261 | IE9: 27661.645 | IF9: 27899.936 | IG9: 26541.673 | IH9: 26413.449 | II9: 24564.686 | IJ9: 24632.987 | IK9: 24680.517 | IL9: 24868.5 | IM9: 27273.087 | IN9: 310067.08 | IO9: 26402.014 | IP9: 25247.336 | IQ9: 26893.334 | IR9: 28866.805 | IS9: 29734.566 | IT9: 27453.831 | IU9: 27260.242 | IV9: 25055.123 | IW9: 24873.636 | IX9: 25313.509 | IY9: 25278.875 | IZ9: 28191.722 | JA9: 320570.99 | JB9: 27316.914 | JC9: 26369.728 | JN9: =SUM(JB9:JM9) -> 53686.642 | JP9: =IFERROR((( _xlfn.XLOOKUP((DATE(YEAR($JP$5),MONTH($JP$5),1)),SMN.AGRO.DATE,$B9:$JN9) / _xlfn.XLOOKUP((DATE(YEAR($JP$5)-1,MONTH($JP$5),1)),SMN.AGRO.DATE,$B9:$JN9) )-1)*100,"") -> 3.3682844 | JQ9: =IFERROR(((JS9/JR9)-1)*100,"") -> 3.3876259 | JR9: =SUMIFS($B9:$JN9,SMN.AGRO.DATE,">="&DATE(YEAR($JP$5)-1,1,1),SMN.AGRO.DATE,"<="&DATE(YEAR($JP$5)-1,MONTH($JP$5),1)) -> 310067.08 | JS9: =SUMIFS($B9:$JN9,SMN.AGRO.DATE,">="&DATE(YEAR($JP$5),1,1),SMN.AGRO.DATE,"<="&$JP$5) -> 320570.99
A11: TOTAL AGRÍCOLA | B11: =SUM(B13:B41,B43) -> 347420 | C11: =SUM(C13:C41,C43) -> 320918.03 | D11: =SUM(D13:D41,D43) -> 300526 | E11: =SUM(E13:E41,E43) -> 287841 | F11: =SUM(F13:F41,F43) -> 300599 | G11: =SUM(G13:G41,G43) -> 305359.5 | H11: =SUM(H13:H41,H43) -> 307108.99 | I11: =SUM(I13:I41,I43) -> 273686.5 | ... M11: =SUM(M13:M41,M43) -> 253028.5 | N11: =SUM(B11:M11) -> 3471408 | O11: =SUM(O13:O41,O43) -> 303626 | P11: =SUM(P13:P41,P43) -> 321645 | Q11: =SUM(Q13:Q41,Q43) -> 313371 | R11: =SUM(R13:R41,R43) -> 286938 | S11: =SUM(S13:S41,S43) -> 306321 | T11: =SUM(T13:T41,T43) -> 310347 | U11: =SUM(U13:U41,U43) -> 314627.5 | V11: =SUM(V13:V41,V43) -> 324546 | ... Z11: =SUM(Z13:Z41,Z43) -> 292366 | AA11: =SUM(O11:Z11) -> 3617761.5 | AB11: =SUM(AB13:AB41,AB43) -> 319289 | AC11: =SUM(AC13:AC41,AC43) -> 349602 | AD11: =SUM(AD13:AD41,AD43) -> 331627 | AE11: =SUM(AE13:AE41,AE43) -> 313960 | AF11: =SUM(AF13:AF41,AF43) -> 335326 | AG11: =SUM(AG13:AG41,AG43) -> 328797 | AH11: =SUM(AH13:AH41,AH43) -> 366086 | AI11: =SUM(AI13:AI41,AI43) -> 324828 | ... AM11: =SUM(AM13:AM41,AM43) -> 320015 | AN11: =SUM(AB11:AM11) -> 3981629 | AO11: =SUM(AO13:AO41,AO43) -> 317324.5 | AP11: =SUM(AP13:AP41,AP43) -> 361841 | AQ11: =SUM(AQ13:AQ41,AQ43) -> 347473.25 | AR11: =SUM(AR13:AR41,AR43) -> 357350 | AS11: =SUM(AS13:AS41,AS43) -> 354325.9 | AT11: =SUM(AT13:AT41,AT43) -> 354375 | AU11: =SUM(AU13:AU41,AU43) -> 353351 | AV11: =SUM(AV13:AV41,AV43) -> 334921.33 | ... AZ11: =SUM(AZ13:AZ41,AZ43) -> 322210 | BA11: =SUM(AO11:AZ11) -> 4099924.1 | BB11: =SUM(BB13:BB41,BB43) -> 323805.95 | BC11: =SUM(BC13:BC41,BC43) -> 354298.4 | BD11: =SUM(BD13:BD41,BD43) -> 347644.87 | BE11: =SUM(BE13:BE41,BE43) -> 335629.17 | BF11: =SUM(BF13:BF41,BF43) -> 372026.51 | BG11: =SUM(BG13:BG41,BG43) -> 361658.3 | BH11: =SUM(BH13:BH41,BH43) -> 356062.23 | BI11: =SUM(BI13:BI41,BI43) -> 344368.08 | ... BM11: =SUM(BM13:BM41,BM43) -> 373437.16 | BN11: =SUM(BB11:BM11) -> 4255425.7 | BO11: =SUM(BO13:BO41,BO43) -> 353604.7 | BP11: =SUM(BP13:BP41,BP43) -> 396866.07 | BQ11: =SUM(BQ13:BQ41,BQ43) -> 384531.5 | BR11: =SUM(BR13:BR41,BR43) -> 413001 | BS11: =SUM(BS13:BS41,BS43) -> 400781.2 | BT11: =SUM(BT13:BT41,BT43) -> 387651.4 | BU11: =SUM(BU13:BU41,BU43) -> 385991 | BV11: =SUM(BV13:BV41,BV43) -> 384856 | ... BZ11: =SUM(BZ13:BZ41,BZ43) -> 389544.35 | CA11: =SUM(BO11:BZ11) -> 4650458.4 | CB11: =SUM(CB13:CB41,CB43) -> 389959 | CC11: =SUM(CC13:CC41,CC43) -> 403149 | CD11: =SUM(CD13:CD41,CD43) -> 360168 | CE11: =SUM(CE13:CE41,CE43) -> 381865 | CF11: =SUM(CF13:CF41,CF43) -> 394428 | CG11: =SUM(CG13:CG41,CG43) -> 405433 | CH11: =SUM(CH13:CH41,CH43) -> 391182 | CI11: =SUM(CI13:CI41,CI43) -> 368984 | ... CM11: =SUM(CM13:CM41,CM43) -> 393515 | CN11: =SUM(CB11:CM11) -> 4645392 | CO11: =SUM(CO13:CO41,CO43) -> 382241.55 | CP11: =SUM(CP13:CP41,CP43) -> 410064.65 | CQ11: =SUM(CQ13:CQ41,CQ43) -> 410643.95 | CR11: =SUM(CR13:CR41,CR43) -> 400190.35 | CS11: =SUM(CS13:CS41,CS43) -> 399684.66 | CT11: =SUM(CT13:CT41,CT43) -> 429937.2 | CU11: =SUM(CU13:CU41,CU43) -> 402609.4 | CV11: =SUM(CV13:CV41,CV43) -> 398597.68 | ... CZ11: =SUM(CZ13:CZ41,CZ43) -> 431575.35 | DA11: =SUM(CO11:CZ11) -> 4849853.8 | DB11: =SUM(DB13:DB41,DB43) -> 402135.35 | DC11: =SUM(DC13:DC41,DC43) -> 434754.3 | DD11: =SUM(DD13:DD41,DD43) -> 429154.4 | DE11: =SUM(DE13:DE41,DE43) -> 413229.15 | DF11: =SUM(DF13:DF41,DF43) -> 429619 | DG11: =SUM(DG13:DG41,DG43) -> 451348 | DH11: =SUM(DH13:DH41,DH43) -> 437276 | DI11: =SUM(DI13:DI41,DI43) -> 405912.1 | ... DM11: =SUM(DM13:DM41,DM43) -> 424471 | DN11: =SUM(DB11:DM11) -> 5064638.3 | DO11: =SUM(DO13:DO41,DO43) -> 413052 | DP11: =SUM(DP13:DP41,DP43) -> 422844.2 | DQ11: =SUM(DQ13:DQ41,DQ43) -> 443775.9 | DR11: =SUM(DR13:DR41,DR43) -> 433015.4 | DS11: =SUM(DS13:DS41,DS43) -> 443224.1 | DT11: =SUM(DT13:DT41,DT43) -> 461901.2 | DU11: =SUM(DU13:DU41,DU43) -> 447868.8 | DV11: =SUM(DV13:DV41,DV43) -> 433332.4 | ... DZ11: =SUM(DZ13:DZ41,DZ43) -> 460745.75 | EA11: =SUM(DO11:DZ11) -> 5246800.4 | EB11: =SUM(EB13:EB41,EB43) -> 414032 | EC11: =SUM(EC13:EC41,EC43) -> 463610 | ED11: =SUM(ED13:ED41,ED43) -> 421497 | EE11: =SUM(EE13:EE41,EE43) -> 448982.66 | EF11: =SUM(EF13:EF41,EF43) -> 445690 | EG11: =SUM(EG13:EG41,EG43) -> 454935 | EH11: =SUM(EH13:EH41,EH43) -> 461065 | EI11: =SUM(EI13:EI41,EI43) -> 423839 | ... EM11: =SUM(EM13:EM41,EM43) -> 478521.7 | EN11: =SUM(EB11:EM11) -> 5344396.4 | EO11: =SUM(EO13:EO41,EO43) -> 461526.2 | EP11: =SUM(EP13:EP41,EP43) -> 489465.2 | EQ11: =SUM(EQ13:EQ41,EQ43) -> 490873 | ER11: =SUM(ER13:ER41,ER43) -> 489355 | ES11: =SUM(ES13:ES41,ES43) -> 493854 | ET11: =SUM(ET13:ET41,ET43) -> 507267 | EU11: =SUM(EU13:EU41,EU43) -> 486298 | EV11: =SUM(EV13:EV41,EV43) -> 479286 | ... EZ11: =SUM(EZ13:EZ41,EZ43) -> 521336.2 | FA11: =SUM(EO11:EZ11) -> 5929984.6 | FB11: =SUM(FB13:FB41,FB43) -> 499441 | FC11: =SUM(FC13:FC41,FC43) -> 509942 | FD11: =SUM(FD13:FD41,FD43) -> 495409 | FE11: =SUM(FE13:FE41,FE43) -> 499768 | FF11: =SUM(FF13:FF41,FF43) -> 536325 | FG11: =SUM(FG13:FG41,FG43) -> 479096 | FH11: =SUM(FH13:FH41,FH43) -> 485143 | FI11: =SUM(FI13:FI41,FI43) -> 479642 | ... FM11: =SUM(FM13:FM41,FM43) -> 495397 | FN11: =SUM(FB11:FM11) -> 5898834 | FO11: =SUM(FO13:FO41,FO43) -> 470909 | FP11: =SUM(FP13:FP41,FP43) -> 478191 | FQ11: =SUM(FQ13:FQ41,FQ43) -> 456131 | FR11: =SUM(FR13:FR41,FR43) -> 466305 | FS11: =SUM(FS13:FS41,FS43) -> 474293 | FT11: =SUM(FT13:FT41,FT43) -> 470511 | FU11: =SUM(FU13:FU41,FU43) -> 471265 | FV11: =SUM(FV13:FV41,FV43) -> 432048 | ... FZ11: =SUM(FZ13:FZ41,FZ43) -> 478585 | GA11: =SUM(FO11:FZ11) -> 5509794 | GB11: =SUM(GB13:GB41,GB43) -> 518599.97 | GC11: =SUM(GC13:GC41,GC43) -> 550917.83 | GD11: =SUM(GD13:GD41,GD43) -> 515150.83 | GE11: =SUM(GE13:GE41,GE43) -> 518480.16 | GF11: =SUM(GF13:GF41,GF43) -> 543035.94 | GG11: =SUM(GG13:GG41,GG43) -> 514067.2 | GH11: =SUM(GH13:GH41,GH43) -> 496608.97 | GI11: =SUM(GI13:GI41,GI43) -> 481958.17 | ... GM11: =SUM(GM13:GM41,GM43) -> 516136.75 | GN11: =SUM(GB11:GM11) -> 6119827.8 | GO11: =SUM(GO13:GO41,GO43) -> 512654.49 | GP11: =SUM(GP13:GP41,GP43) -> 551538.56 | GQ11: =SUM(GQ13:GQ41,GQ43) -> 511957.89 | GR11: =SUM(GR13:GR41,GR43) -> 527713.85 | GS11: =SUM(GS13:GS41,GS43) -> 542640.19 | GT11: =SUM(GT13:GT41,GT43) -> 542086.75 | GU11: =SUM(GU13:GU41,GU43) -> 526540.29 | GV11: =SUM(GV13:GV41,GV43) -> 498228.43 | ... GZ11: =SUM(GZ13:GZ41,GZ43) -> 566098.68 | HA11: =SUM(GO11:GZ11) -> 6324236.7 | HB11: =SUM(HB13:HB41,HB43) -> 551351.05 | HC11: =SUM(HC13:HC41,HC43) -> 538428.89 | HD11: =SUM(HD13:HD41,HD43) -> 522245.3 | HE11: =SUM(HE13:HE41,HE43) -> 530109.03 | HF11: =SUM(HF13:HF41,HF43) -> 536660.23 | HG11: =SUM(HG13:HG41,HG43) -> 539397.71 | HH11: =SUM(HH13:HH41,HH43) -> 529850.79 | HI11: =SUM(HI13:HI41,HI43) -> 502596.01 | ... HM11: =SUM(HM13:HM41,HM43) -> 548090.11 | HN11: =SUM(HB11:HM11) -> 6300832.3 | HO11: =SUM(HO13:HO41,HO43) -> 573721.75 | HP11: =SUM(HP13:HP41,HP43) -> 566790.72 | HQ11: =SUM(HQ13:HQ41,HQ43) -> 549624.85 | HR11: =SUM(HR13:HR41,HR43) -> 545933.6 | HS11: =SUM(HS13:HS41,HS43) -> 565304.42 | HT11: =SUM(HT13:HT41,HT43) -> 591854.21 | HU11: =SUM(HU13:HU41,HU43) -> 562639.96 | HV11: =SUM(HV13:HV41,HV43) -> 528359.16 | ... HZ11: =SUM(HZ13:HZ41,HZ43) -> 578039.92 | IA11: =SUM(HO11:HZ11) -> 6656569.3 | IB11: =SUM(IB13:IB41,IB43) -> 577566.45 | IC11: =SUM(IC13:IC41,IC43) -> 587099.77 | ID11: =SUM(ID13:ID41,ID43) -> 543311.28 | IE11: =SUM(IE13:IE41,IE43) -> 565706.9 | IF11: =SUM(IF13:IF41,IF43) -> 565696.29 | IG11: =SUM(IG13:IG41,IG43) -> 571898.18 | IH11: =SUM(IH13:IH41,IH43) -> 560143.6 | II11: =SUM(II13:II41,II43) -> 485562.82 | ... IM11: =SUM(IM13:IM41,IM43) -> 551837.81 | IN11: =SUM(IB11:IM11) -> 6473458.3 | IO11: =SUM(IO13:IO41,IO43) -> 539334.99 | IP11: =SUM(IP13:IP41,IP43) -> 552677.81 | IQ11: =SUM(IQ13:IQ41,IQ43) -> 586044.05 | IR11: =SUM(IR13:IR41,IR43) -> 579863.91 | IS11: =SUM(IS13:IS41,IS43) -> 603796 | IT11: =SUM(IT13:IT41,IT43) -> 596284.92 | IU11: =SUM(IU13:IU41,IU43) -> 591808.21 | IV11: =SUM(IV13:IV41,IV43) -> 519557.33 | ... IZ11: =SUM(IZ13:IZ41,IZ43) -> 581479.97 | JA11: =SUM(IO11:IZ11) -> 6722679.3 | JB11: =SUM(JB13:JB41,JB43) -> 535390.78 | JC11: =SUM(JC13:JC41,JC43) -> 540297.51 | JD11: =SUM(JD13:JD41,JD43) -> 0 | JE11: =SUM(JE13:JE41,JE43) -> 0 | JF11: =SUM(JF13:JF41,JF43) -> 0 | JG11: =SUM(JG13:JG41,JG43) -> 0 | JH11: =SUM(JH13:JH41,JH43) -> 0 | JI11: =SUM(JI13:JI41,JI43) -> 0 | ... JM11: =SUM(JM13:JM41,JM43) -> 0 | JN11: =SUM(JB11:JM11) -> 1075688.3 | JP11: =IFERROR((( _xlfn.XLOOKUP((DATE(YEAR($JP$5),MONTH($JP$5),1)),SMN.AGRO.DATE,$B11:$JN11) / _xlfn.XLOOKUP((DATE(YEAR($JP$5)-1,MONTH($JP$5),1)),SMN.AGRO.DATE,$B11:$JN11) )-1)*100,"") -> 5.3715348 | JQ11: =IFERROR(((JS11/JR11)-1)*100,"") -> 3.8498901 | JR11: =SUMIFS($B11:$JN11,SMN.AGRO.DATE,">="&DATE(YEAR($JP$5)-1,1,1),SMN.AGRO.DATE,"<="&DATE(YEAR($JP$5)-1,MONTH($JP$5),1)) -> 6473458.3 | JS11: =SUMIFS($B11:$JN11,SMN.AGRO.DATE,">="&DATE(YEAR($JP$5),1,1),SMN.AGRO.DATE,"<="&$JP$5) -> 6722679.3
A13: Algodón | G13: 90 | H13: 3887 | I13: 6317 | J13: 3389 | K13: 20 | N13: =SUM(B13:M13) -> 13703 | S13: 2 | T13: 382 | U13: 1574 | V13: 2620 | W13: 2130 | X13: 893 | AA13: =SUM(O13:Z13) -> 7601 | AG13: 15 | AH13: 552 | AI13: 2286 | AJ13: 2079 | AK13: 384 | AL13: 42 | AN13: =SUM(AB13:AM13) -> 5358 | AT13: 2 | AU13: 171 | AV13: 1391 | AW13: 1621.73 | AX13: 504 | AY13: 64 | BA13: =SUM(AO13:AZ13) -> 3753.73 | BH13: 80 | BI13: 668 | BJ13: 886 | BK13: 400 | BL13: 102 | BN13: =SUM(BB13:BM13) -> 2136 | BU13: 88 | BV13: 1343 | BW13: 864 | BX13: 1644 | CA13: =SUM(BO13:BZ13) -> 3939 | CH13: 7 | CI13: 189 | CJ13: 411 | CK13: 1451 | CN13: =SUM(CB13:CM13) -> 2058 | CU13: 35.7 | CV13: 731.9 | CW13: 892.18 | CX13: 32.9 | CY13: 48.1 | DA13: =SUM(CO13:CZ13) -> 1740.78 | DH13: 99 | DI13: 233 | DJ13: 191 | DK13: 135 | DL13: 5 | DN13: =SUM(DB13:DM13) -> 663 | DV13: 155 | DW13: 81 | DX13: 50 | EA13: =SUM(DO13:DZ13) -> 286 | EH13: 10 | EI13: 79 | EJ13: 20 | EK13: 4 | EN13: =SUM(EB13:EM13) -> 113 | EV13: 1 | FA13: =SUM(EO13:EZ13) -> 1 | FN13: =SUM(FB13:FM13) -> 0 | GA13: =SUM(FO13:FZ13) -> 0 | GN13: =SUM(GB13:GM13) -> 0 | HA13: =SUM(GO13:GZ13) -> 0 | HI13: 153 | HJ13: 495.5 | HK13: 93 | HN13: =SUM(HB13:HM13) -> 741.5 | HV13: 99.4 | HW13: 865.8 | IA13: =SUM(HO13:HZ13) -> 965.2 | IB13: 0 | IC13: 0 | ID13: 0 | IE13: 0 | IF13: 0 | IG13: 0 | IH13: 0 | II13: 56 | IJ13: 109 | IK13: 451 | IL13: 0 | IM13: 0 | IN13: 616 | IO13: 0 | IP13: 0 | IQ13: 0 | IR13: 0 | IS13: 0 | IT13: 0 | IU13: 0 | IV13: 51.05 | IW13: 62.55 | IX13: 47.8 | IY13: 196 | IZ13: 0 | JA13: 357.4 | JB13: 0 | JC13: 0 | JN13: =SUM(JB13:JM13) -> 0 | JP13: =IFERROR((( _xlfn.XLOOKUP((DATE(YEAR($JP$5),MONTH($JP$5),1)),SMN.AGRO.DATE,$B13:$JN13) / _xlfn.XLOOKUP((DATE(YEAR($JP$5)-1,MONTH($JP$5),1)),SMN.AGRO.DATE,$B13:$JN13) )-1)*100,"") | JQ13: =IFERROR(((JS13/JR13)-1)*100,"") -> -41.980519 | JR13: =SUMIFS($B13:$JN13,SMN.AGRO.DATE,">="&DATE(YEAR($JP$5)-1,1,1),SMN.AGRO.DATE,"<="&DATE(YEAR($JP$5)-1,MONTH($JP$5),1)) -> 616 | JS13: =SUMIFS($B13:$JN13,SMN.AGRO.DATE,">="&DATE(YEAR($JP$5),1,1),SMN.AGRO.DATE,"<="&$JP$5) -> 357.4 | JU13: =SUM(B13:JN13) -> 88065.22 | JV13: Algodón | JW13: =IF(EXACT(A13,JV13)=TRUE,"OK","VER") -> OK
A14: Arroz Cáscara | B14: 78659 | C14: 40367 | D14: 25341 | E14: 25832 | F14: 55069 | G14: 58356 | H14: 32895 | I14: 24452 | J14: 26437 | K14: 42550 | L14: 39760 | M14: 25302 | N14: =SUM(B14:M14) -> 475020 | O14: 30915 | P14: 24750 | Q14: 19345 | R14: 19204 | S14: 35306 | T14: 44511 | U14: 38494 | V14: 28719 | W14: 29946 | X14: 31536 | Y14: 51525 | Z14: 40497 | AA14: =SUM(O14:Z14) -> 394748 | AB14: 33143 | AC14: 29904 | AD14: 37439 | AE14: 35744 | AF14: 51927 | AG14: 49072 | AH14: 48945 | AI14: 27185 | AJ14: 36652 | AK14: 37260 | AL14: 63651 | AM14: 55773 | AN14: =SUM(AB14:AM14) -> 506695 | AO14: 37949 | AP14: 36246 | AQ14: 31678 | AR14: 56263 | AS14: 61453 | AT14: 66196 | AU14: 43924 | AV14: 31348 | AW14: 37073.23 | AX14: 47620 | AY14: 67395 | AZ14: 44529 | BA14: =SUM(AO14:AZ14) -> 561674.23 | BB14: 34788 | BC14: 39163 | BD14: 34282 | BE14: 33829 | BF14: 54560 | BG14: 55289 | BH14: 39791 | BI14: 32943 | BJ14: 33831 | BK14: 39683 | BL14: 58862 | BM14: 43263 | BN14: =SUM(BB14:BM14) -> 500284 | BO14: 32263 | BP14: 34187 | BQ14: 32712 | BR14: 57896 | BS14: 55207 | BT14: 47317 | BU14: 42232 | BV14: 38752 | BW14: 39922 | BX14: 45449 | BY14: 46333 | BZ14: 46512 | CA14: =SUM(BO14:BZ14) -> 518782 | CB14: 61558 | CC14: 45399 | CD14: 37186 | CE14: 51517 | CF14: 50690 | CG14: 68188 | CH14: 47669 | CI14: 35800 | CJ14: 33424 | CK14: 37079 | CL14: 66678 | CM14: 40370 | CN14: =SUM(CB14:CM14) -> 575558 | CO14: 37058 | CP14: 38179 | CQ14: 50919 | CR14: 45532 | CS14: 55594 | CT14: 59729 | CU14: 43703 | CV14: 39016 | CW14: 39395 | CX14: 49253 | CY14: 54439 | CZ14: 47011 | DA14: =SUM(CO14:CZ14) -> 559828 | DB14: 42085 | DC14: 47631 | DD14: 51819 | DE14: 47912 | DF14: 59051 | DG14: 67499 | DH14: 58455 | DI14: 47950 | DJ14: 37336 | DK14: 58322 | DL14: 68410 | DM14: 60981 | DN14: =SUM(DB14:DM14) -> 647451 | DO14: 41125 | DP14: 44689 | DQ14: 47187 | DR14: 56862 | DS14: 61396 | DT14: 66681 | DU14: 65672 | DV14: 51747 | DW14: 47783 | DX14: 55097 | DY14: 63592 | DZ14: 80668 | EA14: =SUM(DO14:DZ14) -> 682499 | EB14: 46488 | EC14: 48162 | ED14: 47594 | EE14: 60302 | EF14: 63874 | EG14: 69944 | EH14: 62702 | EI14: 56592 | EJ14: 54479 | EK14: 56072 | EL14: 71000 | EM14: 73082 | EN14: =SUM(EB14:EM14) -> 710291 | EO14: 59296 | EP14: 60264 | EQ14: 62366 | ER14: 58530 | ES14: 68817 | ET14: 77999 | EU14: 69551 | EV14: 68009 | EW14: 67034 | EX14: 84529 | EY14: 68967 | EZ14: 77525 | FA14: =SUM(EO14:EZ14) -> 822887 | FB14: 72147 | FC14: 69594 | FD14: 63655 | FE14: 69021 | FF14: 70133 | FG14: 65346 | FH14: 68438 | FI14: 58861 | FJ14: 52385 | FK14: 56060 | FL14: 77920 | FM14: 74209 | FN14: =SUM(FB14:FM14) -> 797769 | FO14: 62866 | FP14: 57352 | FQ14: 56692 | FR14: 66722 | FS14: 71397 | FT14: 74439 | FU14: 72387 | FV14: 58205 | FW14: 54415 | FX14: 49906 | FY14: 66046 | FZ14: 74529 | GA14: =SUM(FO14:FZ14) -> 764956 | GB14: 67425 | GC14: 75251.69 | GD14: 79752.9 | GE14: 77880 | GF14: 83212.85 | GG14: 86109 | GH14: 65157.98 | GI14: 63093.89 | GJ14: 54573.5 | GK14: 59217.929 | GL14: 81317.859 | GM14: 70289.105 | GN14: =SUM(GB14:GM14) -> 863281.7 | GO14: 54058.408 | GP14: 71164.889 | GQ14: 59931.92 | GR14: 80060.39 | GS14: 81472.864 | GT14: 89099 | GU14: 74768.84 | GV14: 59971.92 | GW14: 66650.309 | GX14: 70435.09 | GY14: 85932.95 | GZ14: 82172.3 | HA14: =SUM(GO14:GZ14) -> 875718.88 | HB14: 54981.85 | HC14: 67254 | HD14: 68106.73 | HE14: 84434.55 | HF14: 82294.96 | HG14: 87878.81 | HH14: 72235 | HI14: 69547.4 | HJ14: 61911.39 | HK14: 63021.5 | HL14: 83036.5 | HM14: 73681.5 | HN14: =SUM(HB14:HM14) -> 868384.19 | HO14: 61448 | HP14: 70011.5 | HQ14: 70501 | HR14: 71591.5 | HS14: 79986 | HT14: 86673 | HU14: 70026.5 | HV14: 70482 | HW14: 73743.4 | HX14: 77064 | HY14: 93705.3 | HZ14: 86241 | IA14: =SUM(HO14:HZ14) -> 911473.2 | IB14: 65686 | IC14: 68139 | ID14: 66248 | IE14: 74587.7 | IF14: 81028 | IG14: 86307.1 | IH14: 82376.8 | II14: 66421.8 | IJ14: 59321.9 | IK14: 68908.4 | IL14: 72255.15 | IM14: 69212.9 | IN14: 860492.75 | IO14: 49265.7 | IP14: 60288.7 | IQ14: 68280.7 | IR14: 70947.8 | IS14: 81000.5 | IT14: 75799 | IU14: 85874 | IV14: 70397.6 | IW14: 67160.6 | IX14: 71077.6 | IY14: 75651.3 | IZ14: 71484.1 | JA14: 847227.6 | JB14: 59426 | JC14: 66775.86 | JN14: =SUM(JB14:JM14) -> 126201.86 | JP14: =IFERROR((( _xlfn.XLOOKUP((DATE(YEAR($JP$5),MONTH($JP$5),1)),SMN.AGRO.DATE,$B14:$JN14) / _xlfn.XLOOKUP((DATE(YEAR($JP$5)-1,MONTH($JP$5),1)),SMN.AGRO.DATE,$B14:$JN14) )-1)*100,"") -> 3.2814692 | JQ14: =IFERROR(((JS14/JR14)-1)*100,"") -> -1.541576 | JR14: =SUMIFS($B14:$JN14,SMN.AGRO.DATE,">="&DATE(YEAR($JP$5)-1,1,1),SMN.AGRO.DATE,"<="&DATE(YEAR($JP$5)-1,MONTH($JP$5),1)) -> 860492.75 | JS14: =SUMIFS($B14:$JN14,SMN.AGRO.DATE,">="&DATE(YEAR($JP$5),1,1),SMN.AGRO.DATE,"<="&$JP$5) -> 847227.6 | JU14: =SUM(B14:JN14) -> 27742445 | JV14: Arroz Cáscara | JW14: =IF(EXACT(A14,JV14)=TRUE,"OK","VER") -> OK
A15: Cacao | B15: 440 | C15: 461 | D15: 505 | E15: 567 | F15: 543 | G15: 533 | H15: 586 | I15: 532 | J15: 463 | K15: 491 | L15: 433 | M15: 410 | N15: =SUM(B15:M15) -> 5964 | O15: 570 | P15: 561 | Q15: 640 | R15: 738 | S15: 842 | T15: 925 | U15: 866 | V15: 750 | W15: 644 | X15: 635 | Y15: 622 | Z15: 619 | AA15: =SUM(O15:Z15) -> 8412 | AB15: 675 | AC15: 690 | AD15: 758 | AE15: 810 | AF15: 1141 | AG15: 978 | AH15: 913 | AI15: 884 | AJ15: 934 | AK15: 1024 | AL15: 984 | AM15: 1020 | AN15: =SUM(AB15:AM15) -> 10811 | AO15: 714 | AP15: 719 | AQ15: 849 | AR15: 1075 | AS15: 1424 | AT15: 1277 | AU15: 1066 | AV15: 1008 | AW15: 1181.22 | AX15: 1062.34 | AY15: 996 | AZ15: 1018 | BA15: =SUM(AO15:AZ15) -> 12389.56 | BB15: 1131 | BC15: 1135 | BD15: 1223 | BE15: 1353 | BF15: 1877 | BG15: 2022 | BH15: 1904 | BI15: 1728 | BJ15: 1848 | BK15: 2173 | BL15: 2348 | BM15: 2258 | BN15: =SUM(BB15:BM15) -> 21000 | BO15: 1410 | BP15: 1288 | BQ15: 1460 | BR15: 1699 | BS15: 1938 | BT15: 2087 | BU15: 1802 | BV15: 1490 | BW15: 1284 | BX15: 1490 | BY15: 2082 | BZ15: 1611 | CA15: =SUM(BO15:BZ15) -> 19641 | CB15: 1431 | CC15: 1432 | CD15: 1499 | CE15: 1863 | CF15: 2259 | CG15: 2453 | CH15: 2429 | CI15: 2621 | CJ15: 2428 | CK15: 2848 | CL15: 2707 | CM15: 2768 | CN15: =SUM(CB15:CM15) -> 26738 | CO15: 1764 | CP15: 2002 | CQ15: 1932 | CR15: 2310 | CS15: 2815 | CT15: 2927 | CU15: 2707 | CV15: 2695 | CW15: 2824 | CX15: 3071 | CY15: 3527 | CZ15: 3553 | DA15: =SUM(CO15:CZ15) -> 32127 | DB15: 2530 | DC15: 2628 | DD15: 2604 | DE15: 3080 | DF15: 3400 | DG15: 3725 | DH15: 3286 | DI15: 3380 | DJ15: 2981 | DK15: 3389 | DL15: 3512 | DM15: 3768 | DN15: =SUM(DB15:DM15) -> 38283 | DO15: 2750 | DP15: 3406 | DQ15: 2955 | DR15: 3146 | DS15: 3795 | DT15: 4589 | DU15: 3338 | DV15: 3182 | DW15: 4052 | DX15: 3350 | DY15: 3613 | DZ15: 4431 | EA15: =SUM(DO15:DZ15) -> 42607 | EB15: 2858 | EC15: 2966 | ED15: 3053 | EE15: 3552 | EF15: 4592 | EG15: 5195 | EH15: 4344 | EI15: 3595 | EJ15: 3433 | EK15: 4002 | EL15: 4196 | EM15: 4211 | EN15: =SUM(EB15:EM15) -> 45997 | EO15: 2657 | EP15: 3463 | EQ15: 3141 | ER15: 4094 | ES15: 5086 | ET15: 5038 | EU15: 4958 | EV15: 4418 | EW15: 4477 | EX15: 4543 | EY15: 5138 | EZ15: 4427 | FA15: =SUM(EO15:EZ15) -> 51440 | FB15: 3709 | FC15: 4096 | FD15: 3875 | FE15: 4532 | FF15: 5432 | FG15: 5409 | FH15: 5232 | FI15: 5063 | FJ15: 4402 | FK15: 4783 | FL15: 4790 | FM15: 4815 | FN15: =SUM(FB15:FM15) -> 56138 | FO15: 4036 | FP15: 4400 | FQ15: 4574 | FR15: 4572 | FS15: 5159 | FT15: 5594 | FU15: 4607 | FV15: 4209 | FW15: 3652 | FX15: 4381 | FY15: 5021 | FZ15: 3980 | GA15: =SUM(FO15:FZ15) -> 54185 | GB15: 5323.4 | GC15: 5443.2 | GD15: 5041.7 | GE15: 5927.5 | GF15: 5817.6 | GG15: 6405.4 | GH15: 5769.5 | GI15: 5583.9 | GJ15: 4971.7 | GK15: 5572.4 | GL15: 5564.54 | GM15: 5365.6 | GN15: =SUM(GB15:GM15) -> 66786.44 | GO15: 3771.6 | GP15: 4398 | GQ15: 4526.3 | GR15: 5439.8 | GS15: 6887.8 | GT15: 7498.5 | GU15: 5495.3 | GV15: 5257.3 | GW15: 4411.9 | GX15: 4713.41 | GY15: 5866.7 | GZ15: 5129.3 | HA15: =SUM(GO15:GZ15) -> 63395.91 | HB15: 4242.1 | HC15: 4793.7 | HD15: 5496.7 | HE15: 5799.3 | HF15: 6902.9 | HG15: 7554.5 | HH15: 6180.3 | HI15: 5118.7 | HJ15: 4768.2 | HK15: 4642.6 | HL15: 5317.1 | HM15: 5596.4 | HN15: =SUM(HB15:HM15) -> 66412.5 | HO15: 4385.6 | HP15: 5084.5 | HQ15: 5488.4 | HR15: 5703.3 | HS15: 7583.9 | HT15: 7781.5 | HU15: 6792.2 | HV15: 4837.7 | HW15: 5045.1 | HX15: 4120.5 | HY15: 4279.8 | HZ15: 4016.3 | IA15: =SUM(HO15:HZ15) -> 65118.8 | IB15: 4507.9 | IC15: 5041 | ID15: 5816.5 | IE15: 7607.5 | IF15: 8792.85 | IG15: 7956.03 | IH15: 6590.1 | II15: 4324.5 | IJ15: 4033.3 | IK15: 3080 | IL15: 3114.3 | IM15: 2897.5 | IN15: 63761.48 | IO15: 3339.5 | IP15: 3481.1 | IQ15: 5809.03 | IR15: 8955.7 | IS15: 9540.8 | IT15: 9429 | IU15: 7925.5 | IV15: 4546.7 | IW15: 3687.2 | IX15: 3040 | IY15: 2870 | IZ15: 3077.75 | JA15: 65702.28 | JB15: 2586.7 | JC15: 2934.25 | JN15: =SUM(JB15:JM15) -> 5520.95 | JP15: =IFERROR((( _xlfn.XLOOKUP((DATE(YEAR($JP$5),MONTH($JP$5),1)),SMN.AGRO.DATE,$B15:$JN15) / _xlfn.XLOOKUP((DATE(YEAR($JP$5)-1,MONTH($JP$5),1)),SMN.AGRO.DATE,$B15:$JN15) )-1)*100,"") -> 6.2208801 | JQ15: =IFERROR(((JS15/JR15)-1)*100,"") -> 3.043844 | JR15: =SUMIFS($B15:$JN15,SMN.AGRO.DATE,">="&DATE(YEAR($JP$5)-1,1,1),SMN.AGRO.DATE,"<="&DATE(YEAR($JP$5)-1,MONTH($JP$5),1)) -> 63761.48 | JS15: =SUMIFS($B15:$JN15,SMN.AGRO.DATE,">="&DATE(YEAR($JP$5),1,1),SMN.AGRO.DATE,"<="&$JP$5) -> 65702.28 | JU15: =SUM(B15:JN15) -> 1644861.8 | JV15: Cacao | JW15: =IF(EXACT(A15,JV15)=TRUE,"OK","VER") -> OK
A16: Café | B16: 173 | C16: 1048 | D16: 3732 | E16: 11054 | F16: 11248 | G16: 7515 | H16: 2921 | I16: 1605 | N16: =SUM(B16:M16) -> 39296 | O16: 269 | P16: 2377 | Q16: 5632 | R16: 10286 | S16: 10312 | T16: 6525 | U16: 2807 | V16: 951 | W16: 124 | X16: 17 | Y16: 8 | Z16: 6 | AA16: =SUM(O16:Z16) -> 39314 | AB16: 1613 | AC16: 4364 | AD16: 6938 | AE16: 10308 | AF16: 11150 | AG16: 6565 | AH16: 2322 | AI16: 1135 | AJ16: 39 | AK16: 27 | AL16: 10 | AM16: 3 | AN16: =SUM(AB16:AM16) -> 44474 | AO16: 1138 | AP16: 2577 | AQ16: 6794 | AR16: 12194 | AS16: 12227 | AT16: 8136 | AU16: 3936 | AV16: 1051 | AW16: 391.55 | AX16: 111.8 | AY16: 85 | AZ16: 2 | BA16: =SUM(AO16:AZ16) -> 48643.35 | BB16: 1024 | BC16: 2519 | BD16: 6315 | BE16: 12272 | BF16: 16117 | BG16: 8923 | BH16: 3947 | BI16: 992 | BJ16: 313 | BK16: 256 | BL16: 183 | BM16: 54 | BN16: =SUM(BB16:BM16) -> 52915 | BO16: 158 | BP16: 1772 | BQ16: 6038 | BR16: 16264 | BS16: 16265 | BT16: 12510 | BU16: 5050 | BV16: 1936 | BW16: 700 | BX16: 199 | BY16: 195 | BZ16: 84 | CA16: =SUM(BO16:BZ16) -> 61171 | CB16: 337 | CC16: 2510 | CD16: 5864 | CE16: 17714 | CF16: 21542 | CG16: 13512 | CH16: 4473 | CI16: 1343 | CJ16: 499 | CK16: 461 | CL16: 416 | CM16: 42 | CN16: =SUM(CB16:CM16) -> 68713 | CO16: 201 | CP16: 1415 | CQ16: 4678 | CR16: 14359 | CS16: 13779 | CT16: 9746 | CU16: 2455 | CV16: 834 | CW16: 168 | CX16: 169 | CY16: 31 | CZ16: 34 | DA16: =SUM(CO16:CZ16) -> 47869 | DB16: 192 | DC16: 1248 | DD16: 5519 | DE16: 12944 | DF16: 17410 | DG16: 12886 | DH16: 4690 | DI16: 1633 | DJ16: 150 | DK16: 148 | DL16: 1 | DN16: =SUM(DB16:DM16) -> 56821 | DO16: 284 | DP16: 2353 | DQ16: 7658 | DR16: 21059 | DS16: 27507 | DT16: 16420 | DU16: 5074 | DV16: 1015 | DW16: 372 | DX16: 211 | DY16: 104 | DZ16: 108 | EA16: =SUM(DO16:DZ16) -> 82165 | EB16: 199 | EC16: 2432 | ED16: 4456 | EE16: 24594 | EF16: 27495 | EG16: 15785 | EH16: 5855 | EI16: 1241 | EJ16: 85 | EK16: 119 | EL16: 37 | EM16: 22 | EN16: =SUM(EB16:EM16) -> 82320 | EO16: 196 | EP16: 1824 | EQ16: 6184 | ER16: 28993 | ES16: 30518 | ET16: 16511 | EU16: 6643 | EV16: 103 | EW16: 99 | EX16: 66 | EY16: 35 | EZ16: 25 | FA16: =SUM(EO16:EZ16) -> 91197 | FB16: 185 | FC16: 2582 | FD16: 9028 | FE16: 28455 | FF16: 31872 | FG16: 14757 | FH16: 3702 | FI16: 546 | FJ16: 113 | FK16: 97 | FL16: 38 | FM16: 49 | FN16: =SUM(FB16:FM16) -> 91424 | FO16: 183 | FP16: 3060 | FQ16: 9296 | FR16: 27302 | FS16: 20463 | FT16: 14741 | FU16: 6556 | FV16: 1422 | FW16: 622 | FX16: 60 | FY16: 42 | FZ16: 1693 | GA16: =SUM(FO16:FZ16) -> 85440 | GB16: 244.3 | GC16: 3570 | GD16: 10023.5 | GE16: 27525.5 | GF16: 20140.5 | GG16: 13350.5 | GH16: 4158.5 | GI16: 1834.5 | GJ16: 1702.5 | GK16: 124.5 | GL16: 73 | GM16: 61.6 | GN16: =SUM(GB16:GM16) -> 82808.9 | GO16: 640.5 | GP16: 4221.2 | GQ16: 8160 | GR16: 22655.5 | GS16: 18521.5 | GT16: 12119.8 | GU16: 6506.5 | GV16: 2029 | GW16: 2308 | GX16: 355.3 | GY16: 264.5 | GZ16: 211.8 | HA16: =SUM(GO16:GZ16) -> 77993.6 | HB16: 1647 | HC16: 4047.5 | HD16: 7454 | HE16: 19981.1 | HF16: 18962.5 | HG16: 13148.6 | HH16: 5802.5 | HI16: 2113.5 | HJ16: 1242.5 | HK16: 315.5 | HL16: 299 | HM16: 231 | HN16: =SUM(HB16:HM16) -> 75244.7 | HO16: 1766 | HP16: 4439 | HQ16: 10766 | HR16: 23006 | HS16: 21140 | HT16: 13305.5 | HU16: 3970 | HV16: 1979 | HW16: 365 | HX16: 146.5 | HY16: 123 | HZ16: 148 | IA16: =SUM(HO16:HZ16) -> 81154 | IB16: 1801 | IC16: 4239.5 | ID16: 9278.5 | IE16: 20453 | IF16: 22331 | IG16: 14085.5 | IH16: 6144 | II16: 3436.2 | IJ16: 1135 | IK16: 0 | IL16: 0 | IM16: 0 | IN16: 82903.7 | IO16: 1572.8 | IP16: 4027.5 | IQ16: 10431 | IR16: 20797 | IS16: 21573.7 | IT16: 14450.5 | IU16: 6169.5 | IV16: 4361.6 | IW16: 1235 | IX16: 0 | IY16: 0 | IZ16: 0 | JA16: 84618.6 | JB16: 1194 | JC16: 2497 | JN16: =SUM(JB16:JM16) -> 3691 | JP16: =IFERROR((( _xlfn.XLOOKUP((DATE(YEAR($JP$5),MONTH($JP$5),1)),SMN.AGRO.DATE,$B16:$JN16) / _xlfn.XLOOKUP((DATE(YEAR($JP$5)-1,MONTH($JP$5),1)),SMN.AGRO.DATE,$B16:$JN16) )-1)*100,"") | JQ16: =IFERROR(((JS16/JR16)-1)*100,"") -> 2.0685446 | JR16: =SUMIFS($B16:$JN16,SMN.AGRO.DATE,">="&DATE(YEAR($JP$5)-1,1,1),SMN.AGRO.DATE,"<="&DATE(YEAR($JP$5)-1,MONTH($JP$5),1)) -> 82903.7 | JS16: =SUMIFS($B16:$JN16,SMN.AGRO.DATE,">="&DATE(YEAR($JP$5),1,1),SMN.AGRO.DATE,"<="&$JP$5) -> 84618.6 | JU16: =SUM(B16:JN16) -> 2760353.7 | JV16: Café | JW16: =IF(EXACT(A16,JV16)=TRUE,"OK","VER") -> OK
A17: Camu Camu | N17: =SUM(B17:M17) -> 0 | AA17: =SUM(O17:Z17) -> 0 | AN17: =SUM(AB17:AM17) -> 0 | BA17: =SUM(AO17:AZ17) -> 0 | BN17: =SUM(BB17:BM17) -> 0 | CA17: =SUM(BO17:BZ17) -> 0 | CN17: =SUM(CB17:CM17) -> 0 | DA17: =SUM(CO17:CZ17) -> 0 | DN17: =SUM(DB17:DM17) -> 0 | EA17: =SUM(DO17:DZ17) -> 0 | EN17: =SUM(EB17:EM17) -> 0 | FA17: =SUM(EO17:EZ17) -> 0 | FN17: =SUM(FB17:FM17) -> 0 | GA17: =SUM(FO17:FZ17) -> 0 | GN17: =SUM(GB17:GM17) -> 0 | HA17: =SUM(GO17:GZ17) -> 0 | HN17: =SUM(HB17:HM17) -> 0 | IA17: =SUM(HO17:HZ17) -> 0 | IB17: 0 | IC17: 0 | ID17: 0 | IE17: 0 | IF17: 0 | IG17: 0 | IH17: 0 | II17: 0 | IJ17: 0 | IK17: 0 | IL17: 0 | IM17: 0 | IN17: 0 | IO17: 0 | IP17: 0 | IQ17: 0 | IR17: 0 | IS17: 0 | IT17: 0 | IU17: 0 | IV17: 0 | IW17: 0 | IX17: 0 | IY17: 0 | IZ17: 0 | JA17: 0 | JB17: 0 | JC17: 0 | JN17: =SUM(JB17:JM17) -> 0 | JP17: =IFERROR((( _xlfn.XLOOKUP((DATE(YEAR($JP$5),MONTH($JP$5),1)),SMN.AGRO.DATE,$B17:$JN17) / _xlfn.XLOOKUP((DATE(YEAR($JP$5)-1,MONTH($JP$5),1)),SMN.AGRO.DATE,$B17:$JN17) )-1)*100,"") | JQ17: =IFERROR(((JS17/JR17)-1)*100,"") | JR17: =SUMIFS($B17:$JN17,SMN.AGRO.DATE,">="&DATE(YEAR($JP$5)-1,1,1),SMN.AGRO.DATE,"<="&DATE(YEAR($JP$5)-1,MONTH($JP$5),1)) -> 0 | JS17: =SUMIFS($B17:$JN17,SMN.AGRO.DATE,">="&DATE(YEAR($JP$5),1,1),SMN.AGRO.DATE,"<="&$JP$5) -> 0 | JU17: =SUM(B17:JN17) -> 0 | JV17: Camu Camu | JW17: =IF(EXACT(A17,JV17)=TRUE,"OK","VER") -> OK
A18: Caña de Azúcar | B18: 14920 | C18: 15524 | D18: 16571 | E18: 17656 | F18: 17362 | G18: 17024 | H18: 17201 | I18: 16452 | J18: 15706 | K18: 14959 | L18: 14563 | M18: 15597 | N18: =SUM(B18:M18) -> 193535 | O18: 15932 | P18: 16800 | Q18: 17483 | R18: 17472 | S18: 18246 | T18: 18468 | U18: 18401 | V18: 18652 | W18: 17996 | X18: 17858 | Y18: 17535 | Z18: 25701 | AA18: =SUM(O18:Z18) -> 220544 | AB18: 17905 | AC18: 18684 | AD18: 18431 | AE18: 18684 | AF18: 19520 | AG18: 19515 | AH18: 19952 | AI18: 22301 | AJ18: 21188 | AK18: 21740 | AL18: 22067 | AM18: 19946 | AN18: =SUM(AB18:AM18) -> 239933 | AO18: 20271 | AP18: 22025 | AQ18: 20549 | AR18: 22652 | AS18: 20728 | AT18: 22945 | AU18: 23298 | AV18: 22711 | AW18: 22525 | AX18: 22530 | AY18: 22545 | AZ18: 12754 | BA18: =SUM(AO18:AZ18) -> 255533 | BB18: 20981 | BC18: 23722 | BD18: 20710 | BE18: 22142 | BF18: 22375 | BG18: 22593 | BH18: 22893 | BI18: 22780 | BJ18: 22183 | BK18: 24583 | BL18: 21936 | BM18: 21197 | BN18: =SUM(BB18:BM18) -> 268095 | BO18: 22047 | BP18: 22898 | BQ18: 25477 | BR18: 23164 | BS18: 24680 | BT18: 23419 | BU18: 25823 | BV18: 23500 | BW18: 26154 | BX18: 22886 | BY18: 25728 | BZ18: 18299 | CA18: =SUM(BO18:BZ18) -> 284075 | CB18: 15579 | CC18: 28819 | CD18: 15589 | CE18: 14939 | CF18: 15064 | CG18: 14575 | CH18: 18007 | CI18: 17715 | CJ18: 17178 | CK18: 17232 | CL18: 17050 | CM18: 16418 | CN18: =SUM(CB18:CM18) -> 208165 | CO18: 24512.95 | CP18: 22693.35 | CQ18: 22817.35 | CR18: 22274.2 | CS18: 22752.95 | CT18: 34401.05 | CU18: 27320.2 | CV18: 26591.5 | CW18: 26728.6 | CX18: 26613.83 | CY18: 27084.8 | CZ18: 26901.25 | DA18: =SUM(CO18:CZ18) -> 310692.03 | DB18: 23599.9 | DC18: 23183 | DD18: 23981 | DE18: 23808 | DF18: 24610 | DG18: 31888 | DH18: 28465 | DI18: 28161 | DJ18: 27804 | DK18: 27861 | DL18: 27897 | DM18: 24458 | DN18: =SUM(DB18:DM18) -> 315715.9 | DO18: 21954 | DP18: 21856 | DQ18: 27856 | DR18: 18955 | DS18: 23317 | DT18: 23816 | DU18: 23993 | DV18: 23051 | DW18: 24738 | DX18: 23834 | DY18: 24537 | DZ18: 25894 | EA18: =SUM(DO18:DZ18) -> 283801 | EB18: 16627 | EC18: 17988 | ED18: 19782 | EE18: 18330 | EF18: 22129 | EG18: 21135 | EH18: 19274 | EI18: 16900 | EJ18: 19175 | EK18: 18232 | EL18: 19819 | EM18: 19282 | EN18: =SUM(EB18:EM18) -> 228673 | EO18: 13898 | EP18: 17462 | EQ18: 17256 | ER18: 13718 | ES18: 16473 | ET18: 12861 | EU18: 10086 | EV18: 12766 | EW18: 15310 | EX18: 14553 | EY18: 16835 | EZ18: 14663 | FA18: =SUM(EO18:EZ18) -> 175881 | FB18: 12173 | FC18: 12689 | FD18: 12023 | FE18: 10746 | FF18: 15506 | FG18: 8618 | FH18: 9625 | FI18: 8421 | FJ18: 11818 | FK18: 9801 | FL18: 12191 | FM18: 11310 | FN18: =SUM(FB18:FM18) -> 134921 | FO18: 13826 | FP18: 15081 | FQ18: 13648 | FR18: 13578 | FS18: 13898 | FT18: 10738 | FU18: 10477 | FV18: 10546 | FW18: 12580 | FX18: 15039 | FY18: 12415 | FZ18: 11701 | GA18: =SUM(FO18:FZ18) -> 153527 | GB18: 11065 | GC18: 13229 | GD18: 12072 | GE18: 12034 | GF18: 12405 | GG18: 9703 | GH18: 9304 | GI18: 7196 | GJ18: 10616 | GK18: 9275 | GL18: 10000 | GM18: 9839 | GN18: =SUM(GB18:GM18) -> 126738 | GO18: 16209 | GP18: 17618 | GQ18: 18089 | GR18: 15814 | GS18: 15081 | GT18: 13308 | GU18: 13369 | GV18: 12372 | GW18: 14454 | GX18: 11624 | GY18: 10124 | GZ18: 10964.5 | HA18: =SUM(GO18:GZ18) -> 169026.5 | HB18: 11184.5 | HC18: 14558 | HD18: 16675 | HE18: 14935 | HF18: 14060 | HG18: 13737 | HH18: 12335 | HI18: 12656.5 | HJ18: 13763 | HK18: 11337 | HL18: 10832 | HM18: 10462 | HN18: =SUM(HB18:HM18) -> 156535 | HO18: 11106.1 | HP18: 12883 | HQ18: 18247 | HR18: 16386 | HS18: 13974.45 | HT18: 14744 | HU18: 12225 | HV18: 12370.5 | HW18: 14687 | HX18: 11619 | HY18: 10155 | HZ18: 9138 | IA18: =SUM(HO18:HZ18) -> 157535.05 | IB18: 12112 | IC18: 13203 | ID18: 14579 | IE18: 13667 | IF18: 14223 | IG18: 12939 | IH18: 13031 | II18: 11457 | IJ18: 11582 | IK18: 10920.5 | IL18: 11240 | IM18: 12016 | IN18: 150969.5 | IO18: 14006 | IP18: 13868 | IQ18: 15022 | IR18: 13350 | IS18: 14052 | IT18: 11035 | IU18: 11378 | IV18: 10421 | IW18: 9446 | IX18: 10110 | IY18: 9530 | IZ18: 9606 | JA18: 141824 | JB18: 9609 | JC18: 11079 | JN18: =SUM(JB18:JM18) -> 20688 | JP18: =IFERROR((( _xlfn.XLOOKUP((DATE(YEAR($JP$5),MONTH($JP$5),1)),SMN.AGRO.DATE,$B18:$JN18) / _xlfn.XLOOKUP((DATE(YEAR($JP$5)-1,MONTH($JP$5),1)),SMN.AGRO.DATE,$B18:$JN18) )-1)*100,"") -> -20.056591 | JQ18: =IFERROR(((JS18/JR18)-1)*100,"") -> -6.0578461 | JR18: =SUMIFS($B18:$JN18,SMN.AGRO.DATE,">="&DATE(YEAR($JP$5)-1,1,1),SMN.AGRO.DATE,"<="&DATE(YEAR($JP$5)-1,MONTH($JP$5),1)) -> 150969.5 | JS18: =SUMIFS($B18:$JN18,SMN.AGRO.DATE,">="&DATE(YEAR($JP$5),1,1),SMN.AGRO.DATE,"<="&$JP$5) -> 141824 | JU18: =SUM(B18:JN18) -> 8392814 | JV18: Caña de Azúcar | JW18: =IF(EXACT(A18,JV18)=TRUE,"OK","VER") -> OK
A19: Cocotero | B19: 818 | C19: 916 | D19: 879 | E19: 968 | F19: 920 | G19: 906 | H19: 851 | I19: 835 | J19: 772 | K19: 792 | L19: 730 | M19: 833 | N19: =SUM(B19:M19) -> 10220 | O19: 864 | P19: 890 | Q19: 955 | R19: 953 | S19: 907 | T19: 908 | U19: 926 | V19: 878 | W19: 876 | X19: 805 | Y19: 784 | Z19: 765 | AA19: =SUM(O19:Z19) -> 10511 | AB19: 852 | AC19: 893 | AD19: 933 | AE19: 1044 | AF19: 920 | AG19: 999 | AH19: 916 | AI19: 841 | AJ19: 873 | AK19: 817 | AL19: 931 | AM19: 788 | AN19: =SUM(AB19:AM19) -> 10807 | AO19: 742 | AP19: 856 | AQ19: 915 | AR19: 887 | AS19: 751 | AT19: 670 | AU19: 711 | AV19: 810 | AW19: 977 | AX19: 935 | AY19: 752 | AZ19: 580 | BA19: =SUM(AO19:AZ19) -> 9586 | BB19: 801 | BC19: 968 | BD19: 880 | BE19: 962 | BF19: 757 | BG19: 867 | BH19: 1060 | BI19: 1022 | BJ19: 982 | BK19: 1118 | BL19: 1005 | BM19: 1048 | BN19: =SUM(BB19:BM19) -> 11470 | BO19: 871 | BP19: 1083 | BQ19: 1010 | BR19: 1012 | BS19: 970 | BT19: 906 | BU19: 898 | BV19: 869 | BW19: 839 | BX19: 842 | BY19: 1624 | BZ19: 713 | CA19: =SUM(BO19:BZ19) -> 11637 | CB19: 1098 | CC19: 1005 | CD19: 1029 | CE19: 1042 | CF19: 1088 | CG19: 1032 | CH19: 1294 | CI19: 1428 | CJ19: 1538 | CK19: 1566 | CL19: 1592 | CM19: 1362 | CN19: =SUM(CB19:CM19) -> 15074 | CO19: 1019 | CP19: 1012.4 | CQ19: 906.85 | CR19: 831.2 | CS19: 856.15 | CT19: 1018.9 | CU19: 1337 | CV19: 1017 | CW19: 1029.45 | CX19: 1105.48 | CY19: 1307.879 | CZ19: 1204.5 | DA19: =SUM(CO19:CZ19) -> 12645.809 | DB19: 1068 | DC19: 1285 | DD19: 1075 | DE19: 1424 | DF19: 1445 | DG19: 1670 | DH19: 1536 | DI19: 1457 | DJ19: 1239 | DK19: 1597 | DL19: 1322 | DM19: 1429 | DN19: =SUM(DB19:DM19) -> 16547 | DO19: 1073 | DP19: 1525 | DQ19: 1974 | DR19: 907 | DS19: 1296 | DT19: 1021 | DU19: 929 | DV19: 1470 | DW19: 1101 | DX19: 1581 | DY19: 1062 | DZ19: 2162 | EA19: =SUM(DO19:DZ19) -> 16101 | EB19: 898 | EC19: 906 | ED19: 1078 | EE19: 1294 | EF19: 1119 | EG19: 1033 | EH19: 1044 | EI19: 1157 | EJ19: 1103 | EK19: 1270 | EL19: 1124 | EM19: 1214 | EN19: =SUM(EB19:EM19) -> 13240 | EO19: 1119 | EP19: 896 | EQ19: 971 | ER19: 1073 | ES19: 1013 | ET19: 940 | EU19: 867 | EV19: 845 | EW19: 1020 | EX19: 1039 | EY19: 860 | EZ19: 926 | FA19: =SUM(EO19:EZ19) -> 11569 | FB19: 747 | FC19: 824 | FD19: 863 | FE19: 787 | FF19: 1182 | FG19: 740 | FH19: 674 | FI19: 623 | FJ19: 729 | FK19: 723 | FL19: 752 | FM19: 727 | FN19: =SUM(FB19:FM19) -> 9371 | FO19: 816 | FP19: 882 | FQ19: 658 | FR19: 614 | FS19: 627 | FT19: 637 | FU19: 571 | FV19: 547 | FW19: 584 | FX19: 655 | FY19: 673 | FZ19: 678 | GA19: =SUM(FO19:FZ19) -> 7942 | GB19: 559 | GC19: 678 | GD19: 722 | GE19: 602 | GF19: 597.5 | GG19: 549 | GH19: 518 | GI19: 552 | GJ19: 564 | GK19: 675 | GL19: 658 | GM19: 617 | GN19: =SUM(GB19:GM19) -> 7291.5 | GO19: 774.6 | GP19: 777.3 | GQ19: 838.1 | GR19: 743 | GS19: 806 | GT19: 682 | GU19: 619.65 | GV19: 627 | GW19: 693.85 | GX19: 724 | GY19: 681.5 | GZ19: 787.8 | HA19: =SUM(GO19:GZ19) -> 8754.8 | HB19: 773.8 | HC19: 879.5 | HD19: 946.1 | HE19: 933 | HF19: 937 | HG19: 953.8 | HH19: 883 | HI19: 852.1 | HJ19: 811.5 | HK19: 873.5 | HL19: 885 | HM19: 957.25 | HN19: =SUM(HB19:HM19) -> 10685.55 | HO19: 845.5 | HP19: 1011 | HQ19: 981 | HR19: 983 | HS19: 962 | HT19: 989.6 | HU19: 888.5 | HV19: 839.2 | HW19: 785.3 | HX19: 838 | HY19: 879 | HZ19: 805 | IA19: =SUM(HO19:HZ19) -> 10807.1 | IB19: 899.5 | IC19: 1088 | ID19: 1030 | IE19: 1049 | IF19: 871 | IG19: 902 | IH19: 809 | II19: 755.4 | IJ19: 703.8 | IK19: 839 | IL19: 907.5 | IM19: 1015 | IN19: 10869.2 | IO19: 935 | IP19: 1101 | IQ19: 1011.5 | IR19: 1096 | IS19: 992 | IT19: 973 | IU19: 948 | IV19: 881 | IW19: 818.6 | IX19: 968 | IY19: 964 | IZ19: 1116.5 | JA19: 11804.6 | JB19: 819 | JC19: 1036 | JN19: =SUM(JB19:JM19) -> 1855 | JP19: =IFERROR((( _xlfn.XLOOKUP((DATE(YEAR($JP$5),MONTH($JP$5),1)),SMN.AGRO.DATE,$B19:$JN19) / _xlfn.XLOOKUP((DATE(YEAR($JP$5)-1,MONTH($JP$5),1)),SMN.AGRO.DATE,$B19:$JN19) )-1)*100,"") -> 10 | JQ19: =IFERROR(((JS19/JR19)-1)*100,"") -> 8.6059692 | JR19: =SUMIFS($B19:$JN19,SMN.AGRO.DATE,">="&DATE(YEAR($JP$5)-1,1,1),SMN.AGRO.DATE,"<="&DATE(YEAR($JP$5)-1,MONTH($JP$5),1)) -> 10869.2 | JS19: =SUMIFS($B19:$JN19,SMN.AGRO.DATE,">="&DATE(YEAR($JP$5),1,1),SMN.AGRO.DATE,"<="&$JP$5) -> 11804.6 | JU19: =SUM(B19:JN19) -> 457577.12 | JV19: Cocotero | JW19: =IF(EXACT(A19,JV19)=TRUE,"OK","VER") -> OK
A20: Frijol Caupí Chiclayo | B20: 146 | C20: 70 | D20: 100 | E20: 71 | F20: 64 | G20: 83 | H20: 101 | I20: 115 | J20: 84 | K20: 23 | L20: 60 | M20: 52 | N20: =SUM(B20:M20) -> 969 | O20: 66 | P20: 46 | Q20: 33 | R20: 25 | S20: 47 | T20: 58 | U20: 70 | V20: 226 | W20: 58 | X20: 35 | Y20: 42 | Z20: 49 | AA20: =SUM(O20:Z20) -> 755 | AB20: 38 | AC20: 36 | AD20: 40 | AE20: 46 | AF20: 56 | AG20: 58 | AH20: 46 | AI20: 73 | AJ20: 66 | AK20: 42 | AL20: 65 | AM20: 64 | AN20: =SUM(AB20:AM20) -> 630 | AO20: 81 | AP20: 74 | AQ20: 75 | AR20: 99 | AS20: 84 | AT20: 82 | AU20: 97 | AV20: 87 | AW20: 101 | AX20: 81 | AY20: 87 | AZ20: 81 | BA20: =SUM(AO20:AZ20) -> 1029 | BB20: 72 | BC20: 83 | BD20: 56 | BE20: 87 | BF20: 78 | BG20: 113 | BH20: 119 | BI20: 95 | BJ20: 119 | BK20: 67 | BL20: 97 | BM20: 99 | BN20: =SUM(BB20:BM20) -> 1085 | BO20: 98 | BP20: 100 | BQ20: 87 | BR20: 94 | BS20: 118 | BT20: 113 | BU20: 110 | BV20: 104 | BW20: 110 | BX20: 84 | BY20: 81 | BZ20: 91 | CA20: =SUM(BO20:BZ20) -> 1190 | CB20: 89 | CC20: 77 | CD20: 72 | CE20: 81 | CF20: 85 | CG20: 83 | CH20: 87 | CI20: 95 | CJ20: 99 | CK20: 76 | CL20: 73 | CM20: 69 | CN20: =SUM(CB20:CM20) -> 986 | CO20: 74 | CP20: 68 | CQ20: 87 | CR20: 103 | CS20: 98 | CT20: 88 | CU20: 110 | CV20: 106 | CW20: 94 | CX20: 74 | CY20: 88 | CZ20: 79 | DA20: =SUM(CO20:CZ20) -> 1069 | DB20: 103 | DC20: 73.8 | DD20: 72 | DE20: 106 | DF20: 115 | DG20: 97 | DH20: 124 | DI20: 109.1 | DJ20: 109 | DK20: 65 | DL20: 91 | DM20: 92 | DN20: =SUM(DB20:DM20) -> 1156.9 | DO20: 87 | DP20: 78 | DQ20: 74 | DR20: 141 | DS20: 157 | DT20: 125 | DU20: 96 | DV20: 126 | DW20: 95 | DX20: 102 | DY20: 116 | DZ20: 88 | EA20: =SUM(DO20:DZ20) -> 1285 | EB20: 72 | EC20: 90 | ED20: 71 | EE20: 111 | EF20: 111 | EG20: 98 | EH20: 96 | EI20: 122 | EJ20: 92 | EK20: 63 | EL20: 71 | EM20: 90 | EN20: =SUM(EB20:EM20) -> 1087 | EO20: 67 | EP20: 69 | EQ20: 72 | ER20: 89 | ES20: 99 | ET20: 98 | EU20: 101 | EV20: 89 | EW20: 74 | EX20: 66 | EY20: 73 | EZ20: 81 | FA20: =SUM(EO20:EZ20) -> 978 | FB20: 79 | FC20: 67 | FD20: 78 | FE20: 97 | FF20: 87 | FG20: 96 | FH20: 97 | FI20: 94 | FJ20: 84 | FK20: 70 | FL20: 71 | FM20: 85 | FN20: =SUM(FB20:FM20) -> 1005 | FO20: 85 | FP20: 76 | FQ20: 79 | FR20: 84 | FS20: 99 | FT20: 102 | FU20: 105 | FV20: 103 | FW20: 102 | FX20: 85 | FY20: 79 | FZ20: 100 | GA20: =SUM(FO20:FZ20) -> 1099 | GB20: 92.809 | GC20: 91.14 | GD20: 89.34 | GE20: 114.95 | GF20: 116.844 | GG20: 74 | GH20: 112.779 | GI20: 77.369 | GJ20: 65.68 | GK20: 67.875 | GL20: 80.754 | GM20: 87.615 | GN20: =SUM(GB20:GM20) -> 1071.155 | GO20: 91.745 | GP20: 87.34 | GQ20: 105.605 | GR20: 115.54 | GS20: 117.8 | GT20: 98.28 | GU20: 125.289 | GV20: 119.509 | GW20: 105.74 | GX20: 91.03 | GY20: 105.758 | GZ20: 106.329 | HA20: =SUM(GO20:GZ20) -> 1269.965 | HB20: 102.63 | HC20: 104 | HD20: 114.39 | HE20: 127.18 | HF20: 130.95 | HG20: 127.06 | HH20: 113.17 | HI20: 125.62 | HJ20: 107.17 | HK20: 65.73 | HL20: 74.39 | HM20: 80.17 | HN20: =SUM(HB20:HM20) -> 1272.46 | HO20: 112.7 | HP20: 97.47 | HQ20: 111.38 | HR20: 108.03 | HS20: 136.6 | HT20: 120.35 | HU20: 147.19 | HV20: 165.77 | HW20: 128.3 | HX20: 98.4 | HY20: 102.86 | HZ20: 119.72 | IA20: =SUM(HO20:HZ20) -> 1448.77 | IB20: 111.3 | IC20: 75.89 | ID20: 109.6 | IE20: 111.32 | IF20: 110.68 | IG20: 96.74 | IH20: 123.3 | II20: 84.54 | IJ20: 147.5 | IK20: 119.7 | IL20: 89.7 | IM20: 67.48 | IN20: 1247.75 | IO20: 74.1 | IP20: 64 | IQ20: 60.98 | IR20: 74.9 | IS20: 59.02 | IT20: 66.49 | IU20: 72.59 | IV20: 62.62 | IW20: 136.6 | IX20: 111.7 | IY20: 116.3 | IZ20: 53.22 | JA20: 952.52 | JB20: 67.3 | JC20: 50.8 | JN20: =SUM(JB20:JM20) -> 118.1 | JP20: =IFERROR((( _xlfn.XLOOKUP((DATE(YEAR($JP$5),MONTH($JP$5),1)),SMN.AGRO.DATE,$B20:$JN20) / _xlfn.XLOOKUP((DATE(YEAR($JP$5)-1,MONTH($JP$5),1)),SMN.AGRO.DATE,$B20:$JN20) )-1)*100,"") -> -21.132187 | JQ20: =IFERROR(((JS20/JR20)-1)*100,"") -> -23.66099 | JR20: =SUMIFS($B20:$JN20,SMN.AGRO.DATE,">="&DATE(YEAR($JP$5)-1,1,1),SMN.AGRO.DATE,"<="&DATE(YEAR($JP$5)-1,MONTH($JP$5),1)) -> 1247.75 | JS20: =SUMIFS($B20:$JN20,SMN.AGRO.DATE,">="&DATE(YEAR($JP$5),1,1),SMN.AGRO.DATE,"<="&$JP$5) -> 952.52 | JU20: =SUM(B20:JN20) -> 43409.24 | JV20: Frijol Caupí Chiclayo | JW20: =IF(EXACT(A20,JV20)=TRUE,"OK","VER") -> OK
A21: Frijol Grano Seco | B21: 67 | C21: 31 | D21: 70 | E21: 433 | F21: 604 | G21: 198 | H21: 307 | I21: 368 | J21: 979 | K21: 702 | L21: 292 | M21: 140 | N21: =SUM(B21:M21) -> 4191 | O21: 134 | P21: 43 | Q21: 65 | R21: 464 | S21: 154 | T21: 58 | U21: 221 | V21: 714 | W21: 1036 | X21: 588 | Y21: 303 | Z21: 91 | AA21: =SUM(O21:Z21) -> 3871 | AB21: 51 | AC21: 31 | AD21: 21 | AE21: 474 | AF21: 169 | AG21: 100 | AH21: 135 | AI21: 726 | AJ21: 1003 | AK21: 414 | AL21: 135 | AM21: 126 | AN21: =SUM(AB21:AM21) -> 3385 | AO21: 34 | AP21: 36 | AQ21: 26 | AR21: 289 | AS21: 275 | AT21: 46 | AU21: 350 | AV21: 1005 | AW21: 1555.4 | AX21: 259 | AY21: 89 | AZ21: 45 | BA21: =SUM(AO21:AZ21) -> 4009.4 | BB21: 49 | BC21: 53 | BD21: 57 | BE21: 253 | BF21: 795 | BG21: 123 | BH21: 190 | BI21: 737 | BJ21: 1544 | BK21: 878 | BL21: 219 | BM21: 165 | BN21: =SUM(BB21:BM21) -> 5063 | BO21: 108 | BP21: 86 | BQ21: 230 | BR21: 547 | BS21: 442 | BT21: 112 | BU21: 237 | BV21: 1010 | BW21: 2180 | BX21: 494 | BY21: 252 | BZ21: 84 | CA21: =SUM(BO21:BZ21) -> 5782 | CB21: 99 | CC21: 80 | CD21: 381 | CE21: 508 | CF21: 485 | CG21: 104 | CH21: 142 | CI21: 933 | CJ21: 1640 | CK21: 744 | CL21: 305 | CM21: 176 | CN21: =SUM(CB21:CM21) -> 5597 | CO21: 112 | CP21: 153 | CQ21: 228 | CR21: 336 | CS21: 530 | CT21: 113 | CU21: 381 | CV21: 1376 | CW21: 1120 | CX21: 241 | CY21: 225 | CZ21: 111 | DA21: =SUM(CO21:CZ21) -> 4926 | DB21: 92 | DC21: 45 | DD21: 154 | DE21: 310 | DF21: 250 | DG21: 39 | DH21: 403 | DI21: 997 | DJ21: 1199 | DK21: 434 | DL21: 157 | DM21: 41 | DN21: =SUM(DB21:DM21) -> 4121 | DO21: 34 | DP21: 49 | DQ21: 374 | DR21: 236 | DS21: 204 | DT21: 54 | DU21: 122 | DV21: 1094 | DW21: 1075 | DX21: 491 | DY21: 207 | DZ21: 217 | EA21: =SUM(DO21:DZ21) -> 4157 | EB21: 71 | EC21: 83 | ED21: 87 | EE21: 218 | EF21: 174 | EG21: 76 | EH21: 1109 | EI21: 829 | EJ21: 755 | EK21: 262 | EL21: 194 | EM21: 38 | EN21: =SUM(EB21:EM21) -> 3896 | EO21: 38 | EP21: 15 | EQ21: 32 | ER21: 119 | ES21: 130 | ET21: 96 | EU21: 143 | EV21: 1035 | EW21: 1001 | EX21: 395 | EY21: 170 | EZ21: 161 | FA21: =SUM(EO21:EZ21) -> 3335 | FB21: 65 | FC21: 46 | FD21: 104 | FE21: 86 | FF21: 70 | FG21: 86 | FH21: 101 | FI21: 1301 | FJ21: 847 | FK21: 400 | FL21: 109 | FM21: 52 | FN21: =SUM(FB21:FM21) -> 3267 | FO21: 57 | FP21: 63 | FQ21: 110 | FR21: 136 | FS21: 117 | FT21: 135 | FU21: 468 | FV21: 678 | FW21: 680 | FX21: 305 | FY21: 177 | FZ21: 112 | GA21: =SUM(FO21:FZ21) -> 3038 | GB21: 50.2 | GC21: 28.3 | GD21: 119.7 | GE21: 116.577 | GF21: 100.87 | GG21: 52.2 | GH21: 453.115 | GI21: 610.458 | GJ21: 617.157 | GK21: 438.98 | GL21: 139.479 | GM21: 73.179 | GN21: =SUM(GB21:GM21) -> 2800.215 | GO21: 86.46 | GP21: 54.519 | GQ21: 233.14 | GR21: 202.54 | GS21: 99.34 | GT21: 85.4 | GU21: 137.455 | GV21: 1089.979 | GW21: 1059.317 | GX21: 521.08 | GY21: 238.519 | GZ21: 125.159 | HA21: =SUM(GO21:GZ21) -> 3932.908 | HB21: 81.74 | HC21: 49.59 | HD21: 248.34 | HE21: 216.48 | HF21: 140.2 | HG21: 86.42 | HH21: 187.96 | HI21: 489.74 | HJ21: 991.44 | HK21: 463.2 | HL21: 228.3 | HM21: 83.16 | HN21: =SUM(HB21:HM21) -> 3266.57 | HO21: 167.74 | HP21: 143.76 | HQ21: 461.55 | HR21: 137.08 | HS21: 65.08 | HT21: 92.84 | HU21: 252.68 | HV21: 524.68 | HW21: 1102.92 | HX21: 532.6 | HY21: 288.3 | HZ21: 143.8 | IA21: =SUM(HO21:HZ21) -> 3913.03 | IB21: 96.87 | IC21: 37.41 | ID21: 267.56 | IE21: 182.3 | IF21: 102.76 | IG21: 17.88 | IH21: 100.16 | II21: 266.29 | IJ21: 711.57 | IK21: 404.27 | IL21: 223.7 | IM21: 69.3 | IN21: 2480.07 | IO21: 82.99 | IP21: 12.81 | IQ21: 173.54 | IR21: 111.26 | IS21: 83.18 | IT21: 19.33 | IU21: 34.72 | IV21: 233.1 | IW21: 596.48 | IX21: 328.75 | IY21: 216.6 | IZ21: 114.76 | JA21: 2007.52 | JB21: 69.58 | JC21: 10.1 | JN21: =SUM(JB21:JM21) -> 79.68 | JP21: =IFERROR((( _xlfn.XLOOKUP((DATE(YEAR($JP$5),MONTH($JP$5),1)),SMN.AGRO.DATE,$B21:$JN21) / _xlfn.XLOOKUP((DATE(YEAR($JP$5)-1,MONTH($JP$5),1)),SMN.AGRO.DATE,$B21:$JN21) )-1)*100,"") -> 65.598846 | JQ21: =IFERROR(((JS21/JR21)-1)*100,"") -> -19.053898 | JR21: =SUMIFS($B21:$JN21,SMN.AGRO.DATE,">="&DATE(YEAR($JP$5)-1,1,1),SMN.AGRO.DATE,"<="&DATE(YEAR($JP$5)-1,MONTH($JP$5),1)) -> 2480.07 | JS21: =SUMIFS($B21:$JN21,SMN.AGRO.DATE,">="&DATE(YEAR($JP$5),1,1),SMN.AGRO.DATE,"<="&$JP$5) -> 2007.52 | JU21: =SUM(B21:JN21) -> 154236.79 | JV21: Frijol Grano Seco | JW21: =IF(EXACT(A21,JV21)=TRUE,"OK","VER") -> OK
A22: Limón Dulce | B22: 19 | C22: 21 | D22: 29 | E22: 32 | F22: 31 | G22: 30 | H22: 27 | I22: 24 | J22: 22 | K22: 18 | L22: 18 | M22: 23 | N22: =SUM(B22:M22) -> 294 | O22: 20 | P22: 25 | Q22: 33 | R22: 33 | S22: 26 | T22: 27 | U22: 25 | V22: 28 | W22: 24 | X22: 24 | Y22: 26 | Z22: 25 | AA22: =SUM(O22:Z22) -> 316 | AB22: 21 | AC22: 27 | AD22: 32 | AE22: 38 | AF22: 27 | AG22: 23 | AH22: 17 | AI22: 31 | AJ22: 25 | AK22: 24 | AL22: 23 | AM22: 40 | AN22: =SUM(AB22:AM22) -> 328 | AO22: 19 | AP22: 29 | AQ22: 22 | AR22: 21 | AS22: 20 | AT22: 18 | AU22: 17 | AV22: 15 | AW22: 15 | AX22: 15 | AY22: 12 | AZ22: 14 | BA22: =SUM(AO22:AZ22) -> 217 | BB22: 22 | BC22: 30 | BD22: 29 | BE22: 32 | BF22: 41 | BG22: 27 | BH22: 40 | BI22: 14 | BJ22: 17 | BK22: 22 | BL22: 26 | BM22: 819 | BN22: =SUM(BB22:BM22) -> 1119 | BO22: 24 | BP22: 28 | BQ22: 42 | BR22: 49 | BS22: 26 | BT22: 23 | BU22: 21 | BV22: 18 | BW22: 14 | BX22: 13 | BY22: 13 | BZ22: 16 | CA22: =SUM(BO22:BZ22) -> 287 | CB22: 24 | CC22: 20 | CD22: 20 | CE22: 21 | CF22: 16 | CG22: 75 | CH22: 15 | CI22: 13 | CJ22: 5 | CK22: 5 | CL22: 6 | CM22: 5 | CN22: =SUM(CB22:CM22) -> 225 | CO22: 20.35 | CP22: 29.8 | CQ22: 34.6 | CR22: 22.75 | CS22: 25.5 | CT22: 32.85 | CU22: 25.55 | CV22: 25.95 | CW22: 22.55 | CX22: 17.1 | CY22: 20.65 | CZ22: 19.7 | DA22: =SUM(CO22:CZ22) -> 297.35 | DB22: 21 | DC22: 32 | DD22: 47 | DE22: 33 | DF22: 26 | DG22: 23 | DH22: 18 | DI22: 16 | DJ22: 16 | DK22: 17 | DL22: 17 | DM22: 17 | DN22: =SUM(DB22:DM22) -> 283 | DO22: 15 | DP22: 83 | DQ22: 54 | DR22: 5 | DS22: 5 | DT22: 6 | DU22: 2 | DV22: 1 | DX22: 1 | EA22: =SUM(DO22:DZ22) -> 172 | EB22: 1 | EC22: 2 | ED22: 3 | EE22: 3 | EF22: 5 | EG22: 6 | EH22: 1 | EN22: =SUM(EB22:EM22) -> 21 | EP22: 2 | EQ22: 2 | ER22: 5 | ES22: 6 | ET22: 3 | EY22: 1 | EZ22: 1 | FA22: =SUM(EO22:EZ22) -> 20 | FC22: 2 | FD22: 3 | FE22: 2 | FF22: 2 | FG22: 1 | FN22: =SUM(FB22:FM22) -> 10 | FQ22: 3 | FR22: 3 | FS22: 2 | FT22: 1 | FU22: 1 | GA22: =SUM(FO22:FZ22) -> 10 | GC22: 2 | GD22: 2 | GE22: 1 | GF22: 0.9 | GJ22: 7 | GN22: =SUM(GB22:GM22) -> 12.9 | GP22: 1.5 | GQ22: 1.5 | GR22: 2 | GS22: 1.2 | GT22: 0.7 | GU22: 0.5 | GV22: 1.1 | GW22: 0.9 | HA22: =SUM(GO22:GZ22) -> 9.4 | HC22: 1.2 | HD22: 1.5 | HE22: 3.5 | HF22: 3 | HG22: 3.5 | HH22: 2.7 | HI22: 2.5 | HJ22: 2.2 | HK22: 1.2 | HN22: =SUM(HB22:HM22) -> 21.3 | HP22: 2 | HQ22: 7 | HR22: 9 | HS22: 6 | HY22: 3 | HZ22: 4 | IA22: =SUM(HO22:HZ22) -> 31 | IB22: 3 | IC22: 5 | ID22: 8 | IE22: 6 | IF22: 7 | IG22: 0 | IH22: 0 | II22: 0 | IJ22: 0 | IK22: 0 | IL22: 3 | IM22: 2 | IN22: 34 | IO22: 1 | IP22: 2 | IQ22: 5 | IR22: 7 | IS22: 5 | IT22: 2 | IU22: 1.5 | IV22: 0 | IW22: 0 | IX22: 0 | IY22: 3 | IZ22: 2 | JA22: 28.5 | JB22: 0 | JC22: 0 | JN22: =SUM(JB22:JM22) -> 0 | JP22: =IFERROR((( _xlfn.XLOOKUP((DATE(YEAR($JP$5),MONTH($JP$5),1)),SMN.AGRO.DATE,$B22:$JN22) / _xlfn.XLOOKUP((DATE(YEAR($JP$5)-1,MONTH($JP$5),1)),SMN.AGRO.DATE,$B22:$JN22) )-1)*100,"") -> 0 | JQ22: =IFERROR(((JS22/JR22)-1)*100,"") -> -16.176471 | JR22: =SUMIFS($B22:$JN22,SMN.AGRO.DATE,">="&DATE(YEAR($JP$5)-1,1,1),SMN.AGRO.DATE,"<="&DATE(YEAR($JP$5)-1,MONTH($JP$5),1)) -> 34 | JS22: =SUMIFS($B22:$JN22,SMN.AGRO.DATE,">="&DATE(YEAR($JP$5),1,1),SMN.AGRO.DATE,"<="&$JP$5) -> 28.5 | JU22: =SUM(B22:JN22) -> 7472.9 | JV22: Limón Dulce | JW22: =IF(EXACT(A22,JV22)=TRUE,"OK","VER") -> OK
A23: Limón Sutil | B23: 253 | C23: 442 | D23: 644 | E23: 806 | F23: 867 | G23: 747 | H23: 568 | I23: 366 | J23: 169 | K23: 128 | L23: 110 | M23: 185 | N23: =SUM(B23:M23) -> 5285 | O23: 263 | P23: 518 | Q23: 827 | R23: 792 | S23: 735 | T23: 647 | U23: 418 | V23: 312 | W23: 225 | X23: 207 | Y23: 192 | Z23: 241 | AA23: =SUM(O23:Z23) -> 5377 | AB23: 337 | AC23: 541 | AD23: 794 | AE23: 858 | AF23: 709 | AG23: 570 | AH23: 389 | AI23: 310 | AJ23: 591 | AK23: 239 | AL23: 267 | AM23: 276 | AN23: =SUM(AB23:AM23) -> 5881 | AO23: 343 | AP23: 487 | AQ23: 890 | AR23: 983 | AS23: 768 | AT23: 549 | AU23: 348 | AV23: 183 | AW23: 186 | AX23: 174 | AY23: 158 | AZ23: 195 | BA23: =SUM(AO23:AZ23) -> 5264 | BB23: 372 | BC23: 492 | BD23: 559 | BE23: 564 | BF23: 642 | BG23: 569 | BH23: 465 | BI23: 337 | BJ23: 295 | BK23: 357 | BL23: 388 | BM23: 373 | BN23: =SUM(BB23:BM23) -> 5413 | BO23: 369 | BP23: 514 | BQ23: 678 | BR23: 831 | BS23: 679 | BT23: 490 | BU23: 309 | BV23: 204 | BW23: 172 | BX23: 178 | BY23: 209 | BZ23: 225 | CA23: =SUM(BO23:BZ23) -> 4858 | CB23: 392 | CC23: 537 | CD23: 847 | CE23: 1125 | CF23: 891 | CG23: 540 | CH23: 391 | CI23: 259 | CJ23: 184 | CK23: 208 | CL23: 224 | CM23: 231 | CN23: =SUM(CB23:CM23) -> 5829 | CO23: 373 | CP23: 560 | CQ23: 849 | CR23: 1086 | CS23: 993 | CT23: 665 | CU23: 423 | CV23: 217 | CW23: 164 | CX23: 186 | CY23: 292 | CZ23: 226 | DA23: =SUM(CO23:CZ23) -> 6034 | DB23: 391 | DC23: 568 | DD23: 752 | DE23: 954 | DF23: 1001 | DG23: 624 | DH23: 363 | DI23: 253 | DJ23: 185 | DK23: 164 | DL23: 231 | DM23: 230 | DN23: =SUM(DB23:DM23) -> 5716 | DO23: 355 | DP23: 542 | DQ23: 965 | DR23: 1004 | DS23: 659 | DT23: 428 | DU23: 222 | DV23: 175 | DW23: 111 | DX23: 140 | DY23: 191 | DZ23: 266 | EA23: =SUM(DO23:DZ23) -> 5058 | EB23: 187 | EC23: 365 | ED23: 613 | EE23: 1095 | EF23: 913 | EG23: 523 | EH23: 236 | EI23: 128 | EJ23: 116 | EK23: 131 | EL23: 158 | EM23: 181 | EN23: =SUM(EB23:EM23) -> 4646 | EO23: 200 | EP23: 319 | EQ23: 644 | ER23: 1202 | ES23: 803 | ET23: 399 | EU23: 208 | EV23: 120 | EW23: 108 | EX23: 126 | EY23: 166 | EZ23: 216 | FA23: =SUM(EO23:EZ23) -> 4511 | FB23: 227 | FC23: 330 | FD23: 681 | FE23: 1031 | FF23: 977 | FG23: 545 | FH23: 254 | FI23: 188 | FJ23: 138 | FK23: 127 | FL23: 161 | FM23: 216 | FN23: =SUM(FB23:FM23) -> 4875 | FO23: 239 | FP23: 316 | FQ23: 480 | FR23: 465 | FS23: 455 | FT23: 347 | FU23: 175 | FV23: 323 | FW23: 107 | FX23: 144 | FY23: 203 | FZ23: 215 | GA23: =SUM(FO23:FZ23) -> 3469 | GB23: 344.97 | GC23: 374.45 | GD23: 607.5 | GE23: 705.5 | GF23: 608.4 | GG23: 425.7 | GH23: 316.2 | GI23: 255.9 | GJ23: 233.5 | GK23: 233.15 | GL23: 293 | GM23: 345.3 | GN23: =SUM(GB23:GM23) -> 4743.57 | GO23: 381.5 | GP23: 479.5 | GQ23: 659 | GR23: 740.8 | GS23: 671.5 | GT23: 419 | GU23: 342.5 | GV23: 289.5 | GW23: 223.9 | GX23: 232.6 | GY23: 279.5 | GZ23: 292.25 | HA23: =SUM(GO23:GZ23) -> 5011.55 | HB23: 328 | HC23: 420.9 | HD23: 654.8 | HE23: 750.5 | HF23: 576 | HG23: 420.5 | HH23: 305.5 | HI23: 204.8 | HJ23: 194.6 | HK23: 206.4 | HL23: 239 | HM23: 289 | HN23: =SUM(HB23:HM23) -> 4590 | HO23: 351 | HP23: 578.41 | HQ23: 818 | HR23: 841.5 | HS23: 654.1 | HT23: 517 | HU23: 248 | HV23: 127 | HW23: 131.25 | HX23: 221 | HY23: 350.5 | HZ23: 352.5 | IA23: =SUM(HO23:HZ23) -> 5190.26 | IB23: 369 | IC23: 615 | ID23: 964.9 | IE23: 972.7 | IF23: 844.2 | IG23: 609.5 | IH23: 320 | II23: 212.2 | IJ23: 131.8 | IK23: 196.3 | IL23: 298.2 | IM23: 549 | IN23: 6082.8 | IO23: 355 | IP23: 581.7 | IQ23: 752.65 | IR23: 837.6 | IS23: 725 | IT23: 556 | IU23: 419 | IV23: 242.3 | IW23: 228.44 | IX23: 310.4 | IY23: 407.5 | IZ23: 618.5 | JA23: 6034.09 | JB23: 322 | JC23: 601 | JN23: =SUM(JB23:JM23) -> 923 | JP23: =IFERROR((( _xlfn.XLOOKUP((DATE(YEAR($JP$5),MONTH($JP$5),1)),SMN.AGRO.DATE,$B23:$JN23) / _xlfn.XLOOKUP((DATE(YEAR($JP$5)-1,MONTH($JP$5),1)),SMN.AGRO.DATE,$B23:$JN23) )-1)*100,"") -> 12.659381 | JQ23: =IFERROR(((JS23/JR23)-1)*100,"") -> -0.80078253 | JR23: =SUMIFS($B23:$JN23,SMN.AGRO.DATE,">="&DATE(YEAR($JP$5)-1,1,1),SMN.AGRO.DATE,"<="&DATE(YEAR($JP$5)-1,MONTH($JP$5),1)) -> 6082.8 | JS23: =SUMIFS($B23:$JN23,SMN.AGRO.DATE,">="&DATE(YEAR($JP$5),1,1),SMN.AGRO.DATE,"<="&$JP$5) -> 6034.09 | JU23: =SUM(B23:JN23) -> 209582.54 | JV23: Limón Sutil | JW23: =IF(EXACT(A23,JV23)=TRUE,"OK","VER") -> OK
A24: Maíz Amarillo Duro | B24: 17405 | C24: 21953 | D24: 14499 | E24: 2375 | F24: 346 | G24: 10518 | H24: 38686 | I24: 15408 | J24: 806 | K24: 1057 | L24: 2269 | M24: 1564 | N24: =SUM(B24:M24) -> 126886 | O24: 10808 | P24: 27469 | Q24: 4938 | R24: 955 | S24: 414 | T24: 2513 | U24: 27359 | V24: 43045 | W24: 1738 | X24: 1123 | Y24: 2730 | Z24: 4212 | AA24: =SUM(O24:Z24) -> 127304 | AB24: 11661 | AC24: 36683 | AD24: 11761 | AE24: 356 | AF24: 368 | AG24: 3539 | AH24: 39608 | AI24: 21776 | AJ24: 1005 | AK24: 2096 | AL24: 2524 | AM24: 1551 | AN24: =SUM(AB24:AM24) -> 132928 | AO24: 8632 | AP24: 31021 | AQ24: 20710 | AR24: 2283 | AS24: 227 | AT24: 2653 | AU24: 28331 | AV24: 21703 | AW24: 1721 | AX24: 3328 | AY24: 3462 | AZ24: 6913 | BA24: =SUM(AO24:AZ24) -> 130984 | BB24: 12238 | BC24: 16850 | BD24: 12561 | BE24: 900 | BF24: 245 | BG24: 10376 | BH24: 15893 | BI24: 16478 | BJ24: 4575 | BK24: 4947 | BL24: 4661 | BM24: 2137 | BN24: =SUM(BB24:BM24) -> 101861 | BO24: 12221 | BP24: 28108 | BQ24: 11988 | BR24: 742 | BS24: 216 | BT24: 6549 | BU24: 17199 | BV24: 11745 | BW24: 2134 | BX24: 3823 | BY24: 5480 | BZ24: 4234 | CA24: =SUM(BO24:BZ24) -> 104439 | CB24: 19468 | CC24: 34550 | CD24: 10734 | CE24: 356 | CF24: 4062 | CG24: 8095 | CH24: 20424 | CI24: 11891 | CJ24: 2619 | CK24: 2269 | CL24: 4428 | CM24: 4055 | CN24: =SUM(CB24:CM24) -> 122951 | CO24: 12227 | CP24: 27199 | CQ24: 18987 | CR24: 348 | CS24: 4514 | CT24: 16725 | CU24: 15322 | CV24: 18458 | CW24: 594 | CX24: 2054 | CY24: 2793 | CZ24: 1768 | DA24: =SUM(CO24:CZ24) -> 120989 | DB24: 16221 | DC24: 29140 | DD24: 13091 | DE24: 1803 | DF24: 4110 | DG24: 16961 | DH24: 23786 | DI24: 11618 | DJ24: 1448 | DK24: 2248 | DL24: 2835 | DM24: 2006 | DN24: =SUM(DB24:DM24) -> 125267 | DO24: 14681 | DP24: 16745 | DQ24: 12028 | DR24: 4736 | DS24: 7086 | DT24: 16294 | DU24: 19177 | DV24: 15617 | DW24: 6737 | DX24: 3027 | DY24: 2545 | DZ24: 3560 | EA24: =SUM(DO24:DZ24) -> 122233 | EB24: 12500 | EC24: 25905 | ED24: 4620 | EE24: 458 | EF24: 2671 | EG24: 16835 | EH24: 16230 | EI24: 11369 | EJ24: 4286 | EK24: 1915 | EL24: 2543 | EM24: 2934 | EN24: =SUM(EB24:EM24) -> 102266 | EO24: 11499 | EP24: 15262 | EQ24: 8270 | ER24: 270 | ES24: 2013 | ET24: 15109 | EU24: 17058 | EV24: 11464 | EW24: 4462 | EX24: 1531 | EY24: 2098 | EZ24: 2791 | FA24: =SUM(EO24:EZ24) -> 91827 | FB24: 12901 | FC24: 24284 | FD24: 13084 | FE24: 298 | FF24: 2860 | FG24: 14248 | FH24: 17913 | FI24: 20397 | FJ24: 744 | FK24: 1016 | FL24: 1510 | FM24: 1197 | FN24: =SUM(FB24:FM24) -> 110452 | FO24: 14862 | FP24: 26449 | FQ24: 3851 | FR24: 496 | FS24: 4341 | FT24: 19760 | FU24: 28840 | FV24: 3006 | FW24: 3188 | FX24: 1263 | FY24: 2223 | FZ24: 2631 | GA24: =SUM(FO24:FZ24) -> 110910 | GB24: 18932 | GC24: 35962.239 | GD24: 5014.6 | GE24: 923 | GF24: 7667 | GG24: 15568 | GH24: 24222 | GI24: 10350.9 | GJ24: 1924 | GK24: 2362.4 | GL24: 1230 | GM24: 2671 | GN24: =SUM(GB24:GM24) -> 126827.14 | GO24: 19730 | GP24: 31993 | GQ24: 2647 | GR24: 4296 | GS24: 11394.5 | GT24: 25545.5 | GU24: 23860 | GV24: 4870 | GW24: 2245 | GX24: 2511 | GY24: 12103 | GZ24: 15201.5 | HA24: =SUM(GO24:GZ24) -> 156396.5 | HB24: 44227 | HC24: 20523 | HD24: 3445 | HE24: 1204 | HF24: 4886.5 | HG24: 28685.5 | HH24: 36323.9 | HI24: 8887.3 | HJ24: 1605.1 | HK24: 3186 | HL24: 6792 | HM24: 15951.5 | HN24: =SUM(HB24:HM24) -> 175716.8 | HO24: 56834 | HP24: 33842 | HQ24: 6310 | HR24: 4411 | HS24: 12751.5 | HT24: 58640 | HU24: 47907 | HV24: 6104 | HW24: 5578 | HX24: 4636.9 | HY24: 8812 | HZ24: 18578.5 | IA24: =SUM(HO24:HZ24) -> 264404.9 | IB24: 43395 | IC24: 34863 | ID24: 6355 | IE24: 2027.4 | IF24: 12905.8 | IG24: 54684.5 | IH24: 50932.3 | II24: 14992.5 | IJ24: 1572.1 | IK24: 1869.2 | IL24: 2055.11 | IM24: 5572 | IN24: 231223.91 | IO24: 28425.4 | IP24: 20696.5 | IQ24: 18262 | IR24: 1785 | IS24: 9640.6 | IT24: 57410 | IU24: 49531.5 | IV24: 18246.5 | IW24: 2142.5 | IX24: 2456.25 | IY24: 2142 | IZ24: 7975.35 | JA24: 218713.6 | JB24: 44328.3 | JC24: 24427.6 | JN24: =SUM(JB24:JM24) -> 68755.9 | JP24: =IFERROR((( _xlfn.XLOOKUP((DATE(YEAR($JP$5),MONTH($JP$5),1)),SMN.AGRO.DATE,$B24:$JN24) / _xlfn.XLOOKUP((DATE(YEAR($JP$5)-1,MONTH($JP$5),1)),SMN.AGRO.DATE,$B24:$JN24) )-1)*100,"") -> 43.132627 | JQ24: =IFERROR(((JS24/JR24)-1)*100,"") -> -5.4104742 | JR24: =SUMIFS($B24:$JN24,SMN.AGRO.DATE,">="&DATE(YEAR($JP$5)-1,1,1),SMN.AGRO.DATE,"<="&DATE(YEAR($JP$5)-1,MONTH($JP$5),1)) -> 231223.91 | JS24: =SUMIFS($B24:$JN24,SMN.AGRO.DATE,">="&DATE(YEAR($JP$5),1,1),SMN.AGRO.DATE,"<="&$JP$5) -> 218713.6 | JU24: =SUM(B24:JN24) -> 5746671.5 | JV24: Maíz Amarillo Duro | JW24: =IF(EXACT(A24,JV24)=TRUE,"OK","VER") -> OK
A25: Mandarina | B25: 9 | C25: 45 | D25: 185 | E25: 313 | F25: 361 | G25: 278 | H25: 201 | I25: 96 | J25: 26 | K25: 4 | N25: =SUM(B25:M25) -> 1518 | O25: 18 | P25: 54 | Q25: 99 | R25: 149 | S25: 282 | T25: 278 | U25: 192 | V25: 124 | W25: 101 | X25: 100 | Y25: 76 | Z25: 77 | AA25: =SUM(O25:Z25) -> 1550 | AB25: 25 | AC25: 53 | AD25: 111 | AE25: 201 | AF25: 247 | AG25: 247 | AH25: 197 | AI25: 141 | AJ25: 118 | AK25: 77 | AL25: 41 | AM25: 28 | AN25: =SUM(AB25:AM25) -> 1486 | AO25: 24 | AP25: 66 | AQ25: 86 | AR25: 225 | AS25: 251 | AT25: 250 | AU25: 153 | AV25: 86 | AW25: 68 | AX25: 68 | AY25: 26 | AZ25: 52 | BA25: =SUM(AO25:AZ25) -> 1355 | BB25: 33 | BC25: 64 | BD25: 50 | BE25: 72 | BF25: 136 | BG25: 88 | BH25: 133 | BI25: 122 | BJ25: 170 | BK25: 188 | BL25: 215 | BM25: 159 | BN25: =SUM(BB25:BM25) -> 1430 | BO25: 46 | BP25: 51 | BQ25: 46 | BR25: 48 | BS25: 93 | BT25: 62 | BU25: 48 | BV25: 19 | BW25: 30 | BX25: 70 | BY25: 155 | BZ25: 137 | CA25: =SUM(BO25:BZ25) -> 805 | CB25: 33 | CC25: 44 | CD25: 75 | CE25: 134 | CF25: 233 | CG25: 180 | CH25: 101 | CI25: 61 | CJ25: 37 | CK25: 106 | CL25: 144 | CM25: 54 | CN25: =SUM(CB25:CM25) -> 1202 | CO25: 31 | CP25: 54 | CQ25: 67 | CR25: 73 | CS25: 80 | CT25: 140 | CU25: 106 | CV25: 87 | CW25: 83 | CX25: 102 | CY25: 106 | CZ25: 24 | DA25: =SUM(CO25:CZ25) -> 953 | DB25: 46 | DC25: 72 | DD25: 43 | DE25: 73 | DF25: 112 | DG25: 97 | DH25: 108 | DI25: 92 | DJ25: 105 | DK25: 106 | DL25: 105 | DM25: 71 | DN25: =SUM(DB25:DM25) -> 1030 | DO25: 34 | DP25: 51 | DQ25: 88 | DR25: 125 | DS25: 159 | DT25: 33 | DU25: 9 | DV25: 5 | DW25: 6 | DX25: 6 | DY25: 3 | DZ25: 1 | EA25: =SUM(DO25:DZ25) -> 520 | EB25: 15 | EC25: 72 | ED25: 54 | EE25: 109 | EF25: 140 | EG25: 25 | EH25: 11 | EI25: 3 | EJ25: 14 | EK25: 8 | EL25: 2 | EM25: 2 | EN25: =SUM(EB25:EM25) -> 455 | EO25: 2 | EP25: 50 | EQ25: 39 | ER25: 136 | ES25: 79 | ET25: 48 | EU25: 24 | EV25: 8 | EW25: 9 | EX25: 6 | EY25: 5 | EZ25: 5 | FA25: =SUM(EO25:EZ25) -> 411 | FB25: 16 | FC25: 48 | FD25: 49 | FE25: 127 | FF25: 110 | FG25: 28 | FH25: 13 | FI25: 13 | FJ25: 15 | FK25: 3 | FL25: 5 | FM25: 9 | FN25: =SUM(FB25:FM25) -> 436 | FO25: 17 | FP25: 31 | FQ25: 14 | FR25: 39 | FS25: 48 | FT25: 23 | FU25: 12 | FV25: 6 | FW25: 4 | FX25: 4 | FY25: 6 | FZ25: 8 | GA25: =SUM(FO25:FZ25) -> 212 | GB25: 35 | GC25: 35 | GD25: 24.5 | GE25: 104 | GF25: 101.5 | GG25: 42.5 | GH25: 25.5 | GI25: 18 | GJ25: 13 | GK25: 19.5 | GL25: 8.5 | GM25: 7 | GN25: =SUM(GB25:GM25) -> 434 | GO25: 25 | GP25: 42 | GQ25: 35 | GR25: 95 | GS25: 105 | GT25: 42 | GU25: 38 | GV25: 17 | GW25: 10 | GX25: 16 | GY25: 8.8 | GZ25: 9.5 | HA25: =SUM(GO25:GZ25) -> 443.3 | HB25: 24 | HC25: 46 | HD25: 48 | HE25: 119 | HF25: 122 | HG25: 68 | HH25: 65 | HI25: 38.5 | HJ25: 8 | HK25: 12 | HL25: 12 | HM25: 8 | HN25: =SUM(HB25:HM25) -> 570.5 | HO25: 11 | HP25: 35 | HQ25: 35 | HR25: 61 | HS25: 111.5 | HT25: 85 | HU25: 61 | HV25: 26 | HW25: 6 | HX25: 13.5 | HY25: 17 | HZ25: 24 | IA25: =SUM(HO25:HZ25) -> 486 | IB25: 14 | IC25: 33 | ID25: 79 | IE25: 110 | IF25: 122 | IG25: 91 | IH25: 10 | II25: 0 | IJ25: 2 | IK25: 2 | IL25: 13 | IM25: 11 | IN25: 487 | IO25: 2.5 | IP25: 9 | IQ25: 29 | IR25: 37 | IS25: 77 | IT25: 61 | IU25: 28 | IV25: 0 | IW25: 0 | IX25: 0 | IY25: 20 | IZ25: 17 | JA25: 280.5 | JB25: 3 | JC25: 13 | JN25: =SUM(JB25:JM25) -> 16 | JP25: =IFERROR((( _xlfn.XLOOKUP((DATE(YEAR($JP$5),MONTH($JP$5),1)),SMN.AGRO.DATE,$B25:$JN25) / _xlfn.XLOOKUP((DATE(YEAR($JP$5)-1,MONTH($JP$5),1)),SMN.AGRO.DATE,$B25:$JN25) )-1)*100,"") -> 54.545455 | JQ25: =IFERROR(((JS25/JR25)-1)*100,"") -> -42.402464 | JR25: =SUMIFS($B25:$JN25,SMN.AGRO.DATE,">="&DATE(YEAR($JP$5)-1,1,1),SMN.AGRO.DATE,"<="&DATE(YEAR($JP$5)-1,MONTH($JP$5),1)) -> 487 | JS25: =SUMIFS($B25:$JN25,SMN.AGRO.DATE,">="&DATE(YEAR($JP$5),1,1),SMN.AGRO.DATE,"<="&$JP$5) -> 280.5 | JU25: =SUM(B25:JN25) -> 32160.6 | JV25: Mandarina | JW25: =IF(EXACT(A25,JV25)=TRUE,"OK","VER") -> OK
A26: Mango | B26: 604 | J26: 30 | K26: 740 | L26: 1226 | M26: 818 | N26: =SUM(B26:M26) -> 3418 | O26: 447 | X26: 523 | Y26: 1320 | Z26: 1192 | AA26: =SUM(O26:Z26) -> 3482 | AB26: 179 | AC26: 10 | AK26: 215 | AL26: 2411 | AM26: 756 | AN26: =SUM(AB26:AM26) -> 3571 | AO26: 142 | AP26: 7 | AX26: 82 | AY26: 1076 | AZ26: 605 | BA26: =SUM(AO26:AZ26) -> 1912 | BB26: 88 | BK26: 363 | BL26: 1280 | BM26: 1001 | BN26: =SUM(BB26:BM26) -> 2732 | BO26: 120 | BP26: 19 | BR26: 2 | BY26: 1014 | BZ26: 747 | CA26: =SUM(BO26:BZ26) -> 1902 | CB26: 116 | CC26: 9 | CK26: 236 | CL26: 1085 | CM26: 1417 | CN26: =SUM(CB26:CM26) -> 2863 | CO26: 136 | CP26: 18 | CV26: 30 | CW26: 124 | CX26: 420 | CY26: 1177 | CZ26: 844 | DA26: =SUM(CO26:CZ26) -> 2749 | DB26: 102 | DC26: 19 | DJ26: 30 | DK26: 209 | DL26: 1145 | DM26: 1350 | DN26: =SUM(DB26:DM26) -> 2855 | DO26: 149 | DP26: 36 | DW26: 20 | DX26: 284 | DY26: 1019 | DZ26: 1021 | EA26: =SUM(DO26:DZ26) -> 2529 | EB26: 199 | EC26: 85 | ED26: 29 | EJ26: 31 | EK26: 296 | EL26: 874 | EM26: 560 | EN26: =SUM(EB26:EM26) -> 2074 | EO26: 74 | EP26: 107 | EQ26: 20 | EX26: 182 | EY26: 522 | EZ26: 376 | FA26: =SUM(EO26:EZ26) -> 1281 | FB26: 65 | FC26: 65 | FK26: 216 | FL26: 610 | FM26: 270 | FN26: =SUM(FB26:FM26) -> 1226 | FO26: 71 | FP26: 32 | FQ26: 11 | FX26: 172 | FY26: 436 | FZ26: 270 | GA26: =SUM(FO26:FZ26) -> 992 | GB26: 96 | GC26: 90 | GD26: 67.4 | GK26: 227 | GL26: 474 | GM26: 364 | GN26: =SUM(GB26:GM26) -> 1318.4 | GO26: 140 | GP26: 229 | GQ26: 18 | GW26: 40 | GX26: 295 | GY26: 455 | GZ26: 543 | HA26: =SUM(GO26:GZ26) -> 1720 | HB26: 130.5 | HC26: 200 | HJ26: 38 | HK26: 348 | HL26: 421 | HM26: 493 | HN26: =SUM(HB26:HM26) -> 1630.5 | HO26: 170 | HP26: 198 | HQ26: 18 | HR26: 15 | HW26: 52 | HX26: 319 | HY26: 397.5 | HZ26: 434 | IA26: =SUM(HO26:HZ26) -> 1603.5 | IB26: 166.5 | IC26: 90 | ID26: 33 | IE26: 19 | IF26: 0 | IG26: 0 | IH26: 0 | II26: 0 | IJ26: 0 | IK26: 224 | IL26: 425 | IM26: 390 | IN26: 1347.5 | IO26: 339.5 | IP26: 136 | IQ26: 82 | IR26: 20.5 | IS26: 0 | IT26: 0 | IU26: 0 | IV26: 0 | IW26: 0 | IX26: 169 | IY26: 402 | IZ26: 392 | JA26: 1541 | JB26: 265 | JC26: 102 | JN26: =SUM(JB26:JM26) -> 367 | JP26: =IFERROR((( _xlfn.XLOOKUP((DATE(YEAR($JP$5),MONTH($JP$5),1)),SMN.AGRO.DATE,$B26:$JN26) / _xlfn.XLOOKUP((DATE(YEAR($JP$5)-1,MONTH($JP$5),1)),SMN.AGRO.DATE,$B26:$JN26) )-1)*100,"") -> 0.51282051 | JQ26: =IFERROR(((JS26/JR26)-1)*100,"") -> 14.359926 | JR26: =SUMIFS($B26:$JN26,SMN.AGRO.DATE,">="&DATE(YEAR($JP$5)-1,1,1),SMN.AGRO.DATE,"<="&DATE(YEAR($JP$5)-1,MONTH($JP$5),1)) -> 1347.5 | JS26: =SUMIFS($B26:$JN26,SMN.AGRO.DATE,">="&DATE(YEAR($JP$5),1,1),SMN.AGRO.DATE,"<="&$JP$5) -> 1541 | JU26: =SUM(B26:JN26) -> 86227.8 | JV26: Mango | JW26: =IF(EXACT(A26,JV26)=TRUE,"OK","VER") -> OK
A27: Maní | B27: 19 | C27: 31 | D27: 33 | E27: 84 | F27: 29 | G27: 21 | H27: 31 | I27: 52 | J27: 134 | K27: 29 | L27: 139 | M27: 32 | N27: =SUM(B27:M27) -> 634 | O27: 27 | P27: 27 | R27: 10 | S27: 15 | T27: 25 | U27: 25 | V27: 49 | W27: 231 | X27: 88 | Y27: 74 | Z27: 32 | AA27: =SUM(O27:Z27) -> 603 | AB27: 19 | AC27: 8 | AD27: 17 | AE27: 16 | AF27: 9 | AG27: 19 | AH27: 25 | AI27: 78 | AJ27: 175 | AK27: 197 | AL27: 68 | AM27: 83 | AN27: =SUM(AB27:AM27) -> 714 | AO27: 46 | AP27: 39 | AQ27: 41 | AR27: 116 | AS27: 53 | AT27: 53 | AU27: 52 | AV27: 121 | AW27: 149 | AX27: 121 | AY27: 39 | AZ27: 37 | BA27: =SUM(AO27:AZ27) -> 867 | BB27: 28 | BC27: 39 | BD27: 24 | BE27: 30 | BF27: 114 | BG27: 58 | BH27: 57 | BI27: 132 | BJ27: 148 | BK27: 54 | BL27: 33 | BM27: 32 | BN27: =SUM(BB27:BM27) -> 749 | BO27: 53 | BP27: 56 | BQ27: 43 | BR27: 34 | BS27: 45 | BT27: 45 | BU27: 44 | BV27: 137 | BW27: 218 | BX27: 74 | BY27: 23 | BZ27: 23 | CA27: =SUM(BO27:BZ27) -> 795 | CB27: 28 | CC27: 29 | CD27: 29 | CE27: 56 | CF27: 23 | CG27: 29 | CH27: 31 | CI27: 135 | CJ27: 196 | CK27: 120 | CL27: 83 | CM27: 31 | CN27: =SUM(CB27:CM27) -> 790 | CO27: 30 | CP27: 25 | CQ27: 33 | CR27: 34 | CS27: 83 | CT27: 36 | CU27: 31 | CV27: 182 | CW27: 241 | CX27: 96 | CY27: 30 | CZ27: 20 | DA27: =SUM(CO27:CZ27) -> 841 | DB27: 28 | DC27: 28 | DD27: 21 | DE27: 36 | DF27: 48 | DG27: 32 | DH27: 65 | DI27: 189 | DJ27: 237 | DK27: 114 | DL27: 33 | DM27: 30 | DN27: =SUM(DB27:DM27) -> 861 | DO27: 33 | DP27: 42 | DQ27: 30 | DR27: 26 | DS27: 28 | DT27: 31 | DU27: 28 | DV27: 151 | DW27: 136 | DX27: 56 | DY27: 96 | DZ27: 16 | EA27: =SUM(DO27:DZ27) -> 673 | EB27: 20 | EC27: 23 | ED27: 13 | EE27: 18 | EF27: 21 | EG27: 20 | EH27: 35 | EI27: 145 | EJ27: 117 | EK27: 24 | EL27: 40 | EM27: 34 | EN27: =SUM(EB27:EM27) -> 510 | EO27: 21 | EP27: 21 | EQ27: 17 | ER27: 27 | ES27: 20 | ET27: 19 | EU27: 29 | EV27: 161 | EW27: 108 | EX27: 23 | EY27: 28 | EZ27: 32 | FA27: =SUM(EO27:EZ27) -> 506 | FB27: 26 | FC27: 27 | FD27: 25 | FE27: 30 | FF27: 24 | FG27: 25 | FH27: 28 | FI27: 86 | FJ27: 106 | FK27: 33 | FL27: 38 | FM27: 27 | FN27: =SUM(FB27:FM27) -> 475 | FO27: 31 | FP27: 20 | FQ27: 19 | FR27: 22 | FS27: 26 | FT27: 25 | FU27: 20 | FV27: 102 | FW27: 124 | FX27: 28 | FY27: 50 | FZ27: 35 | GA27: =SUM(FO27:FZ27) -> 502 | GB27: 30 | GC27: 23 | GD27: 18 | GE27: 27 | GF27: 32.4 | GG27: 24 | GH27: 29 | GI27: 97 | GJ27: 95 | GK27: 30 | GL27: 25 | GM27: 31 | GN27: =SUM(GB27:GM27) -> 461.4 | GO27: 42.2 | GP27: 22.15 | GQ27: 29.4 | GR27: 27.6 | GS27: 32.2 | GT27: 30.4 | GU27: 28.48 | GV27: 115.03 | GW27: 127.58 | GX27: 36.92 | GY27: 26 | GZ27: 29.36 | HA27: =SUM(GO27:GZ27) -> 547.32 | HB27: 29.3 | HC27: 22.5 | HD27: 27.05 | HE27: 31.85 | HF27: 47.94 | HG27: 42.1 | HH27: 42.9 | HI27: 127.6 | HJ27: 213.1 | HK27: 39.65 | HL27: 35.92 | HM27: 17.3 | HN27: =SUM(HB27:HM27) -> 677.21 | HO27: 45.55 | HP27: 44 | HQ27: 31 | HR27: 30.5 | HS27: 51.8 | HT27: 41.6 | HU27: 50 | HV27: 140.82 | HW27: 181 | HX27: 45.9 | HY27: 46.9 | HZ27: 60.7 | IA27: =SUM(HO27:HZ27) -> 769.77 | IB27: 32.2 | IC27: 22 | ID27: 9.9 | IE27: 27.2 | IF27: 31.3 | IG27: 5.7 | IH27: 8.9 | II27: 89.4 | IJ27: 104.1 | IK27: 16.8 | IL27: 16.1 | IM27: 23.4 | IN27: 387 | IO27: 30.8 | IP27: 33.9 | IQ27: 15.65 | IR27: 15.95 | IS27: 29.4 | IT27: 20.5 | IU27: 24.1 | IV27: 75 | IW27: 77.6 | IX27: 27.2 | IY27: 35.2 | IZ27: 19.7 | JA27: 405 | JB27: 26.2 | JC27: 16.7 | JN27: =SUM(JB27:JM27) -> 42.9 | JP27: =IFERROR((( _xlfn.XLOOKUP((DATE(YEAR($JP$5),MONTH($JP$5),1)),SMN.AGRO.DATE,$B27:$JN27) / _xlfn.XLOOKUP((DATE(YEAR($JP$5)-1,MONTH($JP$5),1)),SMN.AGRO.DATE,$B27:$JN27) )-1)*100,"") -> -15.811966 | JQ27: =IFERROR(((JS27/JR27)-1)*100,"") -> 4.6511628 | JR27: =SUMIFS($B27:$JN27,SMN.AGRO.DATE,">="&DATE(YEAR($JP$5)-1,1,1),SMN.AGRO.DATE,"<="&DATE(YEAR($JP$5)-1,MONTH($JP$5),1)) -> 387 | JS27: =SUMIFS($B27:$JN27,SMN.AGRO.DATE,">="&DATE(YEAR($JP$5),1,1),SMN.AGRO.DATE,"<="&$JP$5) -> 405 | JU27: =SUM(B27:JN27) -> 25621.2 | JV27: Maní | JW27: =IF(EXACT(A27,JV27)=TRUE,"OK","VER") -> OK
A28: Naranja | B28: 758 | C28: 1340 | D28: 2639 | E28: 3211 | F28: 3326 | G28: 3070 | H28: 2148 | I28: 1148 | J28: 867 | K28: 784 | L28: 605 | M28: 716 | N28: =SUM(B28:M28) -> 20612 | O28: 834 | P28: 1163 | Q28: 2302 | R28: 2652 | S28: 3296 | T28: 3256 | U28: 2678 | V28: 1829 | W28: 1341 | X28: 854 | Y28: 717 | Z28: 673 | AA28: =SUM(O28:Z28) -> 21595 | AB28: 1041 | AC28: 1476 | AD28: 2643 | AE28: 3437 | AF28: 3384 | AG28: 2665 | AH28: 2649 | AI28: 2288 | AJ28: 1529 | AK28: 1240 | AL28: 1263 | AM28: 809 | AN28: =SUM(AB28:AM28) -> 24424 | AO28: 1202 | AP28: 1701 | AQ28: 2810 | AR28: 3404 | AS28: 2774 | AT28: 2307 | AU28: 2176 | AV28: 2689 | AW28: 1637 | AX28: 1292 | AY28: 842 | AZ28: 655 | BA28: =SUM(AO28:AZ28) -> 23489 | BB28: 1118 | BC28: 1701 | BD28: 2471 | BE28: 3385 | BF28: 2911 | BG28: 2856 | BH28: 2613 | BI28: 2307 | BJ28: 1514 | BK28: 1403 | BL28: 1210 | BM28: 1032 | BN28: =SUM(BB28:BM28) -> 24521 | BO28: 1000 | BP28: 1532 | BQ28: 2614 | BR28: 2937 | BS28: 2664 | BT28: 1737 | BU28: 2816 | BV28: 2473 | BW28: 1459 | BX28: 1425 | BY28: 1489 | BZ28: 1509 | CA28: =SUM(BO28:BZ28) -> 23655 | CB28: 1536 | CC28: 2328 | CD28: 2510 | CE28: 4151 | CF28: 4285 | CG28: 3140 | CH28: 2906 | CI28: 2601 | CJ28: 1554 | CK28: 1131 | CL28: 1428 | CM28: 1326 | CN28: =SUM(CB28:CM28) -> 28896 | CO28: 1275 | CP28: 2110 | CQ28: 2180 | CR28: 4201 | CS28: 4491 | CT28: 3644 | CU28: 3436 | CV28: 2568 | CW28: 1442 | CX28: 1089 | CY28: 985 | CZ28: 940 | DA28: =SUM(CO28:CZ28) -> 28361 | DB28: 997 | DC28: 2055 | DD28: 2346 | DE28: 4787 | DF28: 4494 | DG28: 3714 | DH28: 4091 | DI28: 3522 | DJ28: 2045 | DK28: 1337 | DL28: 497 | DM28: 564 | DN28: =SUM(DB28:DM28) -> 30449 | DO28: 994 | DP28: 2424 | DQ28: 3858 | DR28: 5346 | DS28: 5079 | DT28: 5087 | DU28: 5889 | DV28: 3703 | DW28: 2003 | DX28: 1500 | DY28: 1485 | DZ28: 1455 | EA28: =SUM(DO28:DZ28) -> 38823 | EB28: 1640 | EC28: 2103 | ED28: 5074 | EE28: 10717 | EF28: 15419 | EG28: 7733 | EH28: 5218 | EI28: 3292 | EJ28: 1016 | EK28: 894 | EL28: 523 | EM28: 416 | EN28: =SUM(EB28:EM28) -> 54045 | EO28: 357 | EP28: 1962 | EQ28: 5141 | ER28: 12223 | ES28: 16201 | ET28: 9351 | EU28: 3150 | EV28: 2716 | EW28: 1205 | EX28: 1289 | EY28: 1632 | EZ28: 1403 | FA28: =SUM(EO28:EZ28) -> 56630 | FB28: 622 | FC28: 1841 | FD28: 4296 | FE28: 11892 | FF28: 10793 | FG28: 2697 | FH28: 3686 | FI28: 3960 | FJ28: 1730 | FK28: 2225 | FL28: 3728 | FM28: 1243 | FN28: =SUM(FB28:FM28) -> 48713 | FO28: 887 | FP28: 2168 | FQ28: 1568 | FR28: 1353 | FS28: 6451 | FT28: 2729 | FU28: 7110 | FV28: 8053 | FW28: 4955 | FX28: 5441 | FY28: 2700 | FZ28: 2784 | GA28: =SUM(FO28:FZ28) -> 46199 | GB28: 6222.65 | GC28: 4135 | GD28: 5053 | GE28: 9929 | GF28: 8436.25 | GG28: 5122 | GH28: 10970.5 | GI28: 10980.5 | GJ28: 6168.3 | GK28: 6738.2 | GL28: 3056.1 | GM28: 6148 | GN28: =SUM(GB28:GM28) -> 82959.5 | GO28: 2153.5 | GP28: 3067 | GQ28: 3955 | GR28: 9229 | GS28: 11075 | GT28: 11137.5 | GU28: 13023.5 | GV28: 8848.5 | GW28: 2734.5 | GX28: 2816 | GY28: 5376.5 | GZ28: 6943.25 | HA28: =SUM(GO28:GZ28) -> 80359.25 | HB28: 2352.5 | HC28: 3182 | HD28: 4193.5 | HE28: 7120 | HF28: 9248.5 | HG28: 11849.5 | HH28: 16113 | HI28: 13747 | HJ28: 3538 | HK28: 2013.6 | HL28: 6861.2 | HM28: 7527 | HN28: =SUM(HB28:HM28) -> 87745.8 | HO28: 2949 | HP28: 4044 | HQ28: 4829 | HR28: 7550 | HS28: 6606 | HT28: 9673 | HU28: 19331 | HV28: 14591 | HW28: 3458 | HX28: 1946 | HY28: 5130.5 | HZ28: 5643 | IA28: =SUM(HO28:HZ28) -> 85750.5 | IB28: 2755.5 | IC28: 3452.5 | ID28: 5159.1 | IE28: 7366 | IF28: 5607 | IG28: 9996.7 | IH28: 20446.5 | II28: 9773 | IJ28: 1636 | IK28: 1051 | IL28: 1661 | IM28: 3110 | IN28: 72014.3 | IO28: 1662.5 | IP28: 2607 | IQ28: 3465 | IR28: 4815.5 | IS28: 5428 | IT28: 6925 | IU28: 21900 | IV28: 9859.5 | IW28: 2158.25 | IX28: 1487.25 | IY28: 1927.5 | IZ28: 6998 | JA28: 69233.5 | JB28: 1843 | JC28: 1622 | JN28: =SUM(JB28:JM28) -> 3465 | JP28: =IFERROR((( _xlfn.XLOOKUP((DATE(YEAR($JP$5),MONTH($JP$5),1)),SMN.AGRO.DATE,$B28:$JN28) / _xlfn.XLOOKUP((DATE(YEAR($JP$5)-1,MONTH($JP$5),1)),SMN.AGRO.DATE,$B28:$JN28) )-1)*100,"") -> 125.01608 | JQ28: =IFERROR(((JS28/JR28)-1)*100,"") -> -3.8614553 | JR28: =SUMIFS($B28:$JN28,SMN.AGRO.DATE,">="&DATE(YEAR($JP$5)-1,1,1),SMN.AGRO.DATE,"<="&DATE(YEAR($JP$5)-1,MONTH($JP$5),1)) -> 72014.3 | JS28: =SUMIFS($B28:$JN28,SMN.AGRO.DATE,">="&DATE(YEAR($JP$5),1,1),SMN.AGRO.DATE,"<="&$JP$5) -> 69233.5 | JU28: =SUM(B28:JN28) -> 1903879.7 | JV28: Naranja | JW28: =IF(EXACT(A28,JV28)=TRUE,"OK","VER") -> OK
A29: Palma Aceitera | B29: 18946 | C29: 17766 | D29: 15333 | E29: 12429 | F29: 14232 | G29: 12396 | H29: 10351 | I29: 12513 | J29: 14827 | K29: 12923 | L29: 15206 | M29: 18161 | N29: =SUM(B29:M29) -> 175083 | O29: 19861 | P29: 16432 | Q29: 17563 | R29: 12361 | S29: 14853 | T29: 11650 | U29: 13269 | V29: 16821 | W29: 17131 | X29: 19796 | Y29: 18812 | Z29: 18870 | AA29: =SUM(O29:Z29) -> 197419 | AB29: 28634 | AC29: 24916 | AD29: 25322 | AE29: 22237 | AF29: 25242 | AG29: 26055 | AH29: 25777 | AI29: 24978 | AJ29: 28089 | AK29: 29052 | AL29: 24254 | AM29: 26624 | AN29: =SUM(AB29:AM29) -> 311180 | AO29: 18831 | AP29: 17776 | AQ29: 23087 | AR29: 23446 | AS29: 24848 | AT29: 23700 | AU29: 24874 | AV29: 27676 | AW29: 18817.04 | AX29: 20444 | AY29: 20815 | AZ29: 21116 | BA29: =SUM(AO29:AZ29) -> 265430.04 | BB29: 19046 | BC29: 14621 | BD29: 17170 | BE29: 18360 | BF29: 18613 | BG29: 16062 | BH29: 21287 | BI29: 17014 | BJ29: 24045 | BK29: 21749 | BL29: 21455 | BM29: 21631 | BN29: =SUM(BB29:BM29) -> 231053 | BO29: 21577 | BP29: 19683 | BQ29: 21494 | BR29: 18819 | BS29: 20889 | BT29: 19463 | BU29: 17827 | BV29: 19435 | BW29: 20770 | BX29: 25144 | BY29: 26580 | BZ29: 26646 | CA29: =SUM(BO29:BZ29) -> 258327 | CB29: 22717 | CC29: 23540 | CD29: 22052 | CE29: 21946 | CF29: 27299 | CG29: 25864 | CH29: 26020 | CI29: 26462 | CJ29: 27697 | CK29: 32276 | CL29: 32323 | CM29: 33524 | CN29: =SUM(CB29:CM29) -> 321720 | CO29: 32370 | CP29: 25035 | CQ29: 24095 | CR29: 23391 | CS29: 23181 | CT29: 17683 | CU29: 22696 | CV29: 26726.379 | CW29: 31875 | CX29: 35710 | CY29: 34911 | CZ29: 32956 | DA29: =SUM(CO29:CZ29) -> 330629.38 | DB29: 31321 | DC29: 26893 | DD29: 27810 | DE29: 27248 | DF29: 28199 | DG29: 23630 | DH29: 23714 | DI29: 27370 | DJ29: 29637 | DK29: 31472 | DL29: 33672 | DM29: 32130 | DN29: =SUM(DB29:DM29) -> 343096 | DO29: 33871 | DP29: 25458 | DQ29: 27375 | DR29: 27845 | DS29: 28244 | DT29: 27564 | DU29: 31140 | DV29: 31189 | DW29: 32788 | DX29: 30061 | DY29: 39958 | DZ29: 34026 | EA29: =SUM(DO29:DZ29) -> 369519 | EB29: 31925 | EC29: 28972 | ED29: 29834 | EE29: 27368 | EF29: 25888 | EG29: 23842 | EH29: 25429 | EI29: 33583 | EJ29: 38796 | EK29: 39616 | EL29: 37827 | EM29: 38584 | EN29: =SUM(EB29:EM29) -> 381664 | EO29: 39105 | EP29: 29449 | EQ29: 32294 | ER29: 26992 | ES29: 27158 | ET29: 24475 | EU29: 29960 | EV29: 36195 | EW29: 38527 | EX29: 45389 | EY29: 41940 | EZ29: 39432 | FA29: =SUM(EO29:EZ29) -> 410916 | FB29: 36608 | FC29: 29011 | FD29: 31976 | FE29: 32247 | FF29: 29627 | FG29: 28700 | FH29: 34100 | FI29: 40193 | FJ29: 35987 | FK29: 43075 | FL29: 46431 | FM29: 40391 | FN29: =SUM(FB29:FM29) -> 428346 | FO29: 37019 | FP29: 29051 | FQ29: 33773 | FR29: 33225 | FS29: 30397 | FT29: 27133 | FU29: 30215 | FV29: 38725 | FW29: 40540 | FX29: 43997 | FY29: 44897 | FZ29: 42931 | GA29: =SUM(FO29:FZ29) -> 431903 | GB29: 36383.04 | GC29: 32925.61 | GD29: 30756.79 | GE29: 29834.18 | GF29: 34951.23 | GG29: 26177 | GH29: 31005 | GI29: 38863 | GJ29: 40677 | GK29: 45853 | GL29: 43975 | GM29: 39590 | GN29: =SUM(GB29:GM29) -> 430990.85 | GO29: 41964.782 | GP29: 33332.215 | GQ29: 39469.525 | GR29: 33922.327 | GS29: 35707.785 | GT29: 34008.824 | GU29: 36684.623 | GV29: 37419.844 | GW29: 46549.778 | GX29: 54389.57 | GY29: 55185.97 | GZ29: 60222.47 | HA29: =SUM(GO29:GZ29) -> 508857.71 | HB29: 53242.53 | HC29: 44665.6 | HD29: 43057.67 | HE29: 37160.57 | HF29: 38429.66 | HG29: 35514.27 | HH29: 40122.61 | HI29: 52873.4 | HJ29: 47077.6 | HK29: 66923.8 | HL29: 69112.588 | HM29: 63343.9 | HN29: =SUM(HB29:HM29) -> 591524.2 | HO29: 57516 | HP29: 41661.02 | HQ29: 45226.28 | HR29: 38281.94 | HS29: 38856.84 | HT29: 40468.37 | HU29: 38811.01 | HV29: 56050.04 | HW29: 64187.37 | HX29: 66975.36 | HY29: 60170.97 | HZ29: 51972.22 | IA29: =SUM(HO29:HZ29) -> 600177.42 | IB29: 49301.18 | IC29: 38415.07 | ID29: 37671.22 | IE29: 37949.88 | IF29: 36630.65 | IG29: 33730.58 | IH29: 46802 | II29: 48172.89 | IJ29: 46673 | IK29: 64507 | IL29: 56682 | IM29: 48360 | IN29: 544895.47 | IO29: 43646 | IP29: 35774 | IQ29: 42922 | IR29: 41721 | IS29: 44840 | IT29: 39963 | IU29: 42205 | IV29: 45729.86 | IW29: 46976 | IX29: 54699.91 | IY29: 45938.23 | IZ29: 55286.16 | JA29: 539701.16 | JB29: 43178 | JC29: 35507.6 | JN29: =SUM(JB29:JM29) -> 78685.6 | JP29: =IFERROR((( _xlfn.XLOOKUP((DATE(YEAR($JP$5),MONTH($JP$5),1)),SMN.AGRO.DATE,$B29:$JN29) / _xlfn.XLOOKUP((DATE(YEAR($JP$5)-1,MONTH($JP$5),1)),SMN.AGRO.DATE,$B29:$JN29) )-1)*100,"") -> 14.322084 | JQ29: =IFERROR(((JS29/JR29)-1)*100,"") -> -0.95326724 | JR29: =SUMIFS($B29:$JN29,SMN.AGRO.DATE,">="&DATE(YEAR($JP$5)-1,1,1),SMN.AGRO.DATE,"<="&DATE(YEAR($JP$5)-1,MONTH($JP$5),1)) -> 544895.47 | JS29: =SUMIFS($B29:$JN29,SMN.AGRO.DATE,">="&DATE(YEAR($JP$5),1,1),SMN.AGRO.DATE,"<="&$JP$5) -> 539701.16 | JU29: =SUM(B29:JN29) -> 15502236 | JV29: Palma Aceitera | JW29: =IF(EXACT(A29,JV29)=TRUE,"OK","VER") -> OK
A30: Palto | B30: 68 | C30: 101 | D30: 114 | E30: 113 | F30: 108 | G30: 91 | H30: 68 | I30: 43 | J30: 33 | K30: 34 | L30: 35 | M30: 54 | N30: =SUM(B30:M30) -> 862 | O30: 70 | P30: 93 | Q30: 89 | R30: 99 | S30: 92 | T30: 84 | U30: 62 | V30: 53 | W30: 51 | X30: 42 | Y30: 45 | Z30: 44 | AA30: =SUM(O30:Z30) -> 824 | AB30: 78 | AC30: 108 | AD30: 115 | AE30: 111 | AF30: 105 | AG30: 81 | AH30: 61 | AI30: 49 | AJ30: 56 | AK30: 37 | AL30: 72 | AM30: 61 | AN30: =SUM(AB30:AM30) -> 934 | AO30: 93 | AP30: 113 | AQ30: 98 | AR30: 88 | AS30: 61 | AT30: 24 | AU30: 18 | AV30: 23 | AW30: 46 | AX30: 87 | AY30: 99 | AZ30: 51 | BA30: =SUM(AO30:AZ30) -> 801 | BB30: 80 | BC30: 134 | BD30: 162 | BE30: 189 | BF30: 104 | BG30: 74 | BH30: 36 | BI30: 32 | BJ30: 31 | BK30: 15 | BL30: 45 | BM30: 38 | BN30: =SUM(BB30:BM30) -> 940 | BO30: 54 | BP30: 120 | BQ30: 66 | BR30: 86 | BS30: 102 | BT30: 71 | BU30: 32 | BV30: 15 | BW30: 6 | BX30: 32 | BY30: 74 | BZ30: 28 | CA30: =SUM(BO30:BZ30) -> 686 | CB30: 95 | CC30: 106 | CD30: 91 | CE30: 107 | CF30: 72 | CG30: 37 | CH30: 10 | CI30: 2 | CJ30: 37 | CK30: 104 | CL30: 119 | CM30: 144 | CN30: =SUM(CB30:CM30) -> 924 | CO30: 89 | CP30: 95 | CQ30: 136 | CR30: 155 | CS30: 104 | CT30: 66 | CU30: 48 | CV30: 22 | CW30: 20 | CX30: 42 | CY30: 61 | CZ30: 47 | DA30: =SUM(CO30:CZ30) -> 885 | DB30: 105 | DC30: 97 | DD30: 96 | DE30: 151 | DF30: 117 | DG30: 84 | DH30: 43 | DI30: 12 | DJ30: 10 | DK30: 28 | DL30: 59 | DM30: 92 | DN30: =SUM(DB30:DM30) -> 894 | DO30: 83 | DP30: 76 | DQ30: 95 | DR30: 10 | DW30: 30 | DX30: 97 | DY30: 196 | DZ30: 137 | EA30: =SUM(DO30:DZ30) -> 724 | EB30: 15 | EC30: 13 | ED30: 20 | EE30: 9 | EF30: 3 | EJ30: 18 | EK30: 53 | EL30: 98 | EM30: 75 | EN30: =SUM(EB30:EM30) -> 304 | EO30: 3 | EP30: 12 | EQ30: 19 | ER30: 11 | ES30: 1 | EX30: 41 | EY30: 124 | EZ30: 102 | FA30: =SUM(EO30:EZ30) -> 313 | FB30: 20 | FC30: 18 | FD30: 35 | FE30: 8 | FF30: 4 | FK30: 52 | FL30: 128 | FM30: 92 | FN30: =SUM(FB30:FM30) -> 357 | FO30: 32 | FP30: 36 | FQ30: 28 | FR30: 5 | FT30: 5 | FU30: 1 | FV30: 2 | FW30: 6 | FX30: 65 | FY30: 162 | FZ30: 75 | GA30: =SUM(FO30:FZ30) -> 417 | GB30: 41.3 | GC30: 49.5 | GD30: 32 | GE30: 12.5 | GF30: 7.8 | GG30: 9.65 | GH30: 2 | GI30: 2 | GJ30: 2 | GK30: 79.5 | GL30: 167.1 | GM30: 90.2 | GN30: =SUM(GB30:GM30) -> 495.55 | GO30: 59 | GP30: 49 | GQ30: 56 | GR30: 33 | GS30: 8 | GT30: 20 | GU30: 4.8 | GV30: 15 | GW30: 10 | GX30: 83 | GY30: 153.5 | GZ30: 106 | HA30: =SUM(GO30:GZ30) -> 597.3 | HB30: 71.5 | HC30: 79 | HD30: 93.5 | HE30: 69 | HF30: 38 | HG30: 28 | HH30: 7 | HI30: 11 | HJ30: 27.5 | HK30: 117 | HL30: 161 | HM30: 135.5 | HN30: =SUM(HB30:HM30) -> 838 | HO30: 67.5 | HP30: 53 | HQ30: 67.5 | HR30: 44 | HS30: 30 | HT30: 15 | HU30: 7 | HV30: 16 | HW30: 13 | HX30: 106 | HY30: 125.5 | HZ30: 126 | IA30: =SUM(HO30:HZ30) -> 670.5 | IB30: 60 | IC30: 56 | ID30: 75 | IE30: 64 | IF30: 49.5 | IG30: 27.5 | IH30: 20 | II30: 16 | IJ30: 10 | IK30: 61 | IL30: 81 | IM30: 75 | IN30: 595 | IO30: 47.5 | IP30: 38 | IQ30: 58.5 | IR30: 32.5 | IS30: 42.5 | IT30: 24 | IU30: 33 | IV30: 26 | IW30: 26 | IX30: 110 | IY30: 134 | IZ30: 137 | JA30: 709 | JB30: 65 | JC30: 69 | JN30: =SUM(JB30:JM30) -> 134 | JP30: =IFERROR((( _xlfn.XLOOKUP((DATE(YEAR($JP$5),MONTH($JP$5),1)),SMN.AGRO.DATE,$B30:$JN30) / _xlfn.XLOOKUP((DATE(YEAR($JP$5)-1,MONTH($JP$5),1)),SMN.AGRO.DATE,$B30:$JN30) )-1)*100,"") -> 82.666667 | JQ30: =IFERROR(((JS30/JR30)-1)*100,"") -> 19.159664 | JR30: =SUMIFS($B30:$JN30,SMN.AGRO.DATE,">="&DATE(YEAR($JP$5)-1,1,1),SMN.AGRO.DATE,"<="&DATE(YEAR($JP$5)-1,MONTH($JP$5),1)) -> 595 | JS30: =SUMIFS($B30:$JN30,SMN.AGRO.DATE,">="&DATE(YEAR($JP$5),1,1),SMN.AGRO.DATE,"<="&$JP$5) -> 709 | JU30: =SUM(B30:JN30) -> 27808.7 | JV30: Palto | JW30: =IF(EXACT(A30,JV30)=TRUE,"OK","VER") -> OK
A31: Papaya | B31: 672 | C31: 752 | D31: 1116 | E31: 1278 | F31: 1234 | G31: 1318 | H31: 1225 | I31: 1075 | J31: 744 | K31: 705 | L31: 763 | M31: 1017 | N31: =SUM(B31:M31) -> 11899 | O31: 1197 | P31: 1543 | Q31: 1607 | R31: 1740 | S31: 1626 | T31: 1629 | U31: 1721 | V31: 1648 | W31: 1751 | X31: 2180 | Y31: 2027 | Z31: 1966 | AA31: =SUM(O31:Z31) -> 20635 | AB31: 1398 | AC31: 1521 | AD31: 1841 | AE31: 1996 | AF31: 2015 | AG31: 1875 | AH31: 1991 | AI31: 1846 | AJ31: 1686 | AK31: 1763 | AL31: 1763 | AM31: 1404 | AN31: =SUM(AB31:AM31) -> 21099 | AO31: 1804 | AP31: 2301 | AQ31: 1894 | AR31: 1768 | AS31: 1610 | AT31: 1534 | AU31: 1699 | AV31: 1708 | AW31: 2009 | AX31: 2387 | AY31: 2340 | AZ31: 1407 | BA31: =SUM(AO31:AZ31) -> 22461 | BB31: 2305 | BC31: 2344 | BD31: 2667 | BE31: 3138 | BF31: 3232 | BG31: 2925 | BH31: 3449 | BI31: 3745 | BJ31: 3406 | BK31: 3715 | BL31: 3872 | BM31: 3606 | BN31: =SUM(BB31:BM31) -> 38404 | BO31: 1967 | BP31: 1936 | BQ31: 2097 | BR31: 2289 | BS31: 2477 | BT31: 2486 | BU31: 2689 | BV31: 2622 | BW31: 2484 | BX31: 2640 | BY31: 3141 | BZ31: 2353 | CA31: =SUM(BO31:BZ31) -> 29181 | CB31: 1523 | CC31: 1756 | CD31: 1463 | CE31: 1972 | CF31: 2367 | CG31: 2533 | CH31: 2861 | CI31: 3002 | CJ31: 2713 | CK31: 3115 | CL31: 3467 | CM31: 2604 | CN31: =SUM(CB31:CM31) -> 29376 | CO31: 1698 | CP31: 2153 | CQ31: 1934 | CR31: 2441 | CS31: 2294 | CT31: 2710 | CU31: 2705 | CV31: 3162 | CW31: 3660 | CX31: 3294 | CY31: 3337 | CZ31: 3048 | DA31: =SUM(CO31:CZ31) -> 32436 | DB31: 1696 | DC31: 2010 | DD31: 1900 | DE31: 2265 | DF31: 2113 | DG31: 2301 | DH31: 2217 | DI31: 2174 | DJ31: 2291 | DK31: 2384 | DL31: 2283 | DM31: 2086 | DN31: =SUM(DB31:DM31) -> 25720 | DO31: 1298 | DP31: 1532 | DQ31: 1493 | DR31: 1155 | DS31: 1247 | DT31: 1197 | DU31: 1336 | DV31: 1466 | DW31: 1663 | DX31: 1561 | DY31: 1469 | DZ31: 1347 | EA31: =SUM(DO31:DZ31) -> 16764 | EB31: 1428 | EC31: 1693 | ED31: 1597 | EE31: 1728 | EF31: 1704 | EG31: 1529 | EH31: 1617 | EI31: 1418 | EJ31: 1538 | EK31: 1828 | EL31: 1625 | EM31: 1640 | EN31: =SUM(EB31:EM31) -> 19345 | EO31: 1275 | EP31: 1545 | EQ31: 1817 | ER31: 1716 | ES31: 1461 | ET31: 1497 | EU31: 1445 | EV31: 1386 | EW31: 1519 | EX31: 1410 | EY31: 1582 | EZ31: 1423 | FA31: =SUM(EO31:EZ31) -> 18076 | FB31: 1163 | FC31: 1462 | FD31: 1486 | FE31: 1487 | FF31: 1350 | FG31: 1748 | FH31: 1701 | FI31: 1337 | FJ31: 1461 | FK31: 1389 | FL31: 1432 | FM31: 1288 | FN31: =SUM(FB31:FM31) -> 17304 | FO31: 1313 | FP31: 1739 | FQ31: 1408 | FR31: 1624 | FS31: 1821 | FT31: 2104 | FU31: 2050 | FV31: 1855 | FW31: 1416 | FX31: 2054 | FY31: 2388 | FZ31: 2290 | GA31: =SUM(FO31:FZ31) -> 22062 | GB31: 2321 | GC31: 1953 | GD31: 2152.5 | GE31: 2155.5 | GF31: 2582 | GG31: 2677.8 | GH31: 3480 | GI31: 3142 | GJ31: 3575 | GK31: 3469 | GL31: 3054.5 | GM31: 2911 | GN31: =SUM(GB31:GM31) -> 33473.3 | GO31: 2346.5 | GP31: 1892 | GQ31: 2025 | GR31: 2019 | GS31: 2093 | GT31: 3280 | GU31: 2332 | GV31: 1943 | GW31: 2067 | GX31: 2104 | GY31: 2113 | GZ31: 2235 | HA31: =SUM(GO31:GZ31) -> 26449.5 | HB31: 1994 | HC31: 1682 | HD31: 2062 | HE31: 1812 | HF31: 1977 | HG31: 3340 | HH31: 2658 | HI31: 2417 | HJ31: 2452 | HK31: 2323 | HL31: 2346 | HM31: 2283 | HN31: =SUM(HB31:HM31) -> 27346 | HO31: 1851 | HP31: 2035 | HQ31: 1749 | HR31: 1572 | HS31: 1821 | HT31: 2943 | HU31: 2149 | HV31: 2209 | HW31: 2131 | HX31: 1848 | HY31: 1872 | HZ31: 1862 | IA31: =SUM(HO31:HZ31) -> 24042 | IB31: 2214 | IC31: 2204 | ID31: 1955 | IE31: 1785 | IF31: 2035 | IG31: 3237 | IH31: 2525 | II31: 2050 | IJ31: 2152 | IK31: 1906 | IL31: 2083 | IM31: 2415 | IN31: 26561 | IO31: 2551 | IP31: 2075 | IQ31: 2014.7 | IR31: 1784 | IS31: 2243 | IT31: 3963.5 | IU31: 3081 | IV31: 2242 | IW31: 2153 | IX31: 2009 | IY31: 2183 | IZ31: 2536.5 | JA31: 28835.7 | JB31: 2469 | JC31: 1952 | JN31: =SUM(JB31:JM31) -> 4421 | JP31: =IFERROR((( _xlfn.XLOOKUP((DATE(YEAR($JP$5),MONTH($JP$5),1)),SMN.AGRO.DATE,$B31:$JN31) / _xlfn.XLOOKUP((DATE(YEAR($JP$5)-1,MONTH($JP$5),1)),SMN.AGRO.DATE,$B31:$JN31) )-1)*100,"") -> 5.0310559 | JQ31: =IFERROR(((JS31/JR31)-1)*100,"") -> 8.5640601 | JR31: =SUMIFS($B31:$JN31,SMN.AGRO.DATE,">="&DATE(YEAR($JP$5)-1,1,1),SMN.AGRO.DATE,"<="&DATE(YEAR($JP$5)-1,MONTH($JP$5),1)) -> 26561 | JS31: =SUMIFS($B31:$JN31,SMN.AGRO.DATE,">="&DATE(YEAR($JP$5),1,1),SMN.AGRO.DATE,"<="&$JP$5) -> 28835.7 | JU31: =SUM(B31:JN31) -> 991781 | JV31: Papaya | JW31: =IF(EXACT(A31,JV31)=TRUE,"OK","VER") -> OK
A32: Pijuayo Fruto | B32: 3506 | C32: 3761 | D32: 3405 | E32: 2 | N32: =SUM(B32:M32) -> 10674 | O32: 3491 | P32: 3733 | Q32: 3387 | R32: 2 | AA32: =SUM(O32:Z32) -> 10613 | AB32: 3295 | AC32: 3430 | AD32: 3719 | AE32: 2 | AN32: =SUM(AB32:AM32) -> 10446 | AO32: 3257 | AP32: 3532 | AQ32: 3949 | BA32: =SUM(AO32:AZ32) -> 10738 | BB32: 3346 | BC32: 3859 | BD32: 3724 | BN32: =SUM(BB32:BM32) -> 10929 | BO32: 3198 | BP32: 4214 | BQ32: 3528 | BR32: 51 | BS32: 38 | CA32: =SUM(BO32:BZ32) -> 11029 | CB32: 3180 | CC32: 72 | CD32: 25 | CK32: 120 | CL32: 180 | CM32: 180 | CN32: =SUM(CB32:CM32) -> 3757 | CO32: 3428 | CP32: 4352 | CQ32: 3490 | CR32: 389 | CS32: 1658 | DA32: =SUM(CO32:CZ32) -> 13317 | DB32: 3442 | DC32: 4365 | DD32: 3623 | DE32: 461 | DM32: 108 | DN32: =SUM(DB32:DM32) -> 11999 | DO32: 3435 | DP32: 3833 | DQ32: 3732 | DX32: 10 | DY32: 20 | DZ32: 17 | EA32: =SUM(DO32:DZ32) -> 11047 | EB32: 2054 | EC32: 8420 | ED32: 7206 | EE32: 2018 | EF32: 3 | EG32: 3 | EH32: 3 | EM32: 10 | EN32: =SUM(EB32:EM32) -> 19717 | EO32: 85 | EP32: 8088 | EQ32: 8253 | ER32: 4064 | ES32: 4 | ET32: 1 | FA32: =SUM(EO32:EZ32) -> 20495 | FB32: 5143 | FC32: 8663 | FD32: 4477 | FE32: 3520 | FM32: 2 | FN32: =SUM(FB32:FM32) -> 21805 | FO32: 85 | FP32: 67 | FQ32: 13 | FR32: 10 | FS32: 1 | FT32: 1 | FU32: 1 | FV32: 5 | FW32: 1 | FX32: 2 | FY32: 4 | FZ32: 4 | GA32: =SUM(FO32:FZ32) -> 194 | GB32: 5098 | GC32: 8500 | GD32: 4340 | GE32: 3633 | GF32: 79 | GG32: 66 | GH32: 70 | GI32: 41 | GJ32: 47 | GK32: 60 | GL32: 54 | GM32: 57 | GN32: =SUM(GB32:GM32) -> 22045 | GO32: 5586 | GP32: 8094 | GQ32: 5123 | GR32: 3259 | GS32: 52 | GT32: 42 | GU32: 47.5 | GV32: 47 | GW32: 58 | GX32: 50 | GY32: 59.5 | GZ32: 67 | HA32: =SUM(GO32:GZ32) -> 22485 | HB32: 5486 | HC32: 7705 | HD32: 5226 | HE32: 3102 | HF32: 35.5 | HG32: 28.5 | HH32: 9 | HI32: 6 | HJ32: 7.5 | HK32: 5.5 | HL32: 4 | HM32: 8 | HN32: =SUM(HB32:HM32) -> 21623 | HO32: 6827 | HP32: 7645 | HQ32: 4588 | HR32: 24 | HS32: 2 | HY32: 1 | HZ32: 58.5 | IA32: =SUM(HO32:HZ32) -> 19145.5 | IB32: 85 | IC32: 5727 | ID32: 8263 | IE32: 5653 | IF32: 8 | IG32: 0 | IH32: 0 | II32: 0 | IJ32: 0 | IK32: 0 | IL32: 1 | IM32: 5 | IN32: 19742 | IO32: 19 | IP32: 5605 | IQ32: 8163 | IR32: 4987 | IS32: 3 | IT32: 0 | IU32: 0 | IV32: 0 | IW32: 0 | IX32: 0 | IY32: 0.5 | IZ32: 5.5 | JA32: 18783 | JB32: 10 | JC32: 87 | JN32: =SUM(JB32:JM32) -> 97 | JP32: =IFERROR((( _xlfn.XLOOKUP((DATE(YEAR($JP$5),MONTH($JP$5),1)),SMN.AGRO.DATE,$B32:$JN32) / _xlfn.XLOOKUP((DATE(YEAR($JP$5)-1,MONTH($JP$5),1)),SMN.AGRO.DATE,$B32:$JN32) )-1)*100,"") -> 10 | JQ32: =IFERROR(((JS32/JR32)-1)*100,"") -> -4.8576639 | JR32: =SUMIFS($B32:$JN32,SMN.AGRO.DATE,">="&DATE(YEAR($JP$5)-1,1,1),SMN.AGRO.DATE,"<="&DATE(YEAR($JP$5)-1,MONTH($JP$5),1)) -> 19742 | JS32: =SUMIFS($B32:$JN32,SMN.AGRO.DATE,">="&DATE(YEAR($JP$5),1,1),SMN.AGRO.DATE,"<="&$JP$5) -> 18783 | JU32: =SUM(B32:JN32) -> 581361 | JV32: Pijuayo Fruto | JW32: =IF(EXACT(A32,JV32)=TRUE,"OK","VER") -> OK
A33: Piña | B33: 901 | C33: 14 | J33: 776 | K33: 4110 | L33: 4911 | M33: 1742 | N33: =SUM(B33:M33) -> 12454 | O33: 2027 | P33: 978 | Q33: 693 | R33: 465 | S33: 361 | T33: 132 | U33: 148 | V33: 169 | W33: 666 | X33: 2637 | Y33: 3186 | Z33: 2765 | AA33: =SUM(O33:Z33) -> 14227 | AB33: 1393 | AC33: 967 | AD33: 914 | AE33: 180 | AF33: 189 | AG33: 113 | AH33: 233 | AI33: 136 | AJ33: 401 | AK33: 3658 | AL33: 4725 | AM33: 1740 | AN33: =SUM(AB33:AM33) -> 14649 | AO33: 1065 | AP33: 112 | AQ33: 246 | AR33: 160 | AS33: 85 | AT33: 123 | AU33: 193 | AV33: 159 | AW33: 1442 | AX33: 2098 | AY33: 4835 | AZ33: 5254 | BA33: =SUM(AO33:AZ33) -> 15772 | BB33: 1178 | BC33: 860 | BD33: 751 | BE33: 247 | BF33: 160 | BG33: 119 | BH33: 223 | BI33: 283 | BJ33: 1089 | BK33: 1821 | BL33: 4065 | BM33: 4481 | BN33: =SUM(BB33:BM33) -> 15277 | BO33: 961 | BP33: 910 | BQ33: 771 | BR33: 769 | BS33: 796 | BT33: 790 | BU33: 868 | BV33: 879 | BW33: 891 | BX33: 2414 | BY33: 2002 | BZ33: 1108 | CA33: =SUM(BO33:BZ33) -> 13159 | CB33: 1054 | CC33: 1031 | CD33: 846 | CE33: 784 | CF33: 763 | CG33: 743 | CH33: 797 | CI33: 958 | CJ33: 809 | CK33: 2348 | CL33: 3848 | CM33: 1868 | CN33: =SUM(CB33:CM33) -> 15849 | CO33: 1131 | CP33: 526 | CQ33: 407 | CR33: 381 | CS33: 419 | CT33: 826 | CU33: 745 | CV33: 416 | CW33: 902 | CX33: 2057 | CY33: 4679 | CZ33: 4091 | DA33: =SUM(CO33:CZ33) -> 16580 | DB33: 1505 | DC33: 1071 | DD33: 1269 | DE33: 1005 | DF33: 658 | DG33: 825 | DH33: 204 | DI33: 186 | DJ33: 896 | DK33: 2565 | DL33: 3650 | DM33: 3808 | DN33: =SUM(DB33:DM33) -> 17642 | DO33: 1538 | DP33: 1396 | DQ33: 1712 | DR33: 997 | DS33: 930 | DT33: 636 | DU33: 671 | DV33: 717 | DW33: 650 | DX33: 715 | DY33: 1294 | DZ33: 982 | EA33: =SUM(DO33:DZ33) -> 12238 | EB33: 429 | EC33: 772 | ED33: 773 | EE33: 868 | EF33: 598 | EG33: 507 | EH33: 863 | EI33: 861 | EJ33: 1289 | EK33: 1326 | EL33: 1852 | EM33: 1576 | EN33: =SUM(EB33:EM33) -> 11714 | EO33: 596 | EP33: 781 | EQ33: 846 | ER33: 1030 | ES33: 882 | ET33: 863 | EU33: 607 | EV33: 927 | EW33: 757 | EX33: 944 | EY33: 1324 | EZ33: 1175 | FA33: =SUM(EO33:EZ33) -> 10732 | FB33: 720 | FC33: 788 | FD33: 865 | FE33: 1402 | FF33: 1035 | FG33: 769 | FH33: 784 | FI33: 885 | FJ33: 833 | FK33: 1047 | FL33: 1244 | FM33: 1011 | FN33: =SUM(FB33:FM33) -> 11383 | FO33: 662 | FP33: 675 | FQ33: 772 | FR33: 839 | FS33: 771 | FT33: 669 | FU33: 656 | FV33: 606 | FW33: 741 | FX33: 625 | FY33: 823 | FZ33: 874 | GA33: =SUM(FO33:FZ33) -> 8713 | GB33: 1413 | GC33: 1365.5 | GD33: 1576.5 | GE33: 1358 | GF33: 1676.5 | GG33: 1351 | GH33: 1086.5 | GI33: 1126 | GJ33: 924 | GK33: 1205 | GL33: 1306.5 | GM33: 1124.5 | GN33: =SUM(GB33:GM33) -> 15513 | GO33: 1131.5 | GP33: 1194 | GQ33: 2008.5 | GR33: 1272 | GS33: 1801.5 | GT33: 2001 | GU33: 1591.5 | GV33: 1525 | GW33: 1955 | GX33: 1415 | GY33: 1610 | GZ33: 2160 | HA33: =SUM(GO33:GZ33) -> 19665 | HB33: 1180.5 | HC33: 1243.5 | HD33: 1323 | HE33: 1135.3 | HF33: 1220.5 | HG33: 1253 | HH33: 1281 | HI33: 1308 | HJ33: 1309.5 | HK33: 1503 | HL33: 1439.5 | HM33: 1527.5 | HN33: =SUM(HB33:HM33) -> 15724.3 | HO33: 1424.8 | HP33: 1421 | HQ33: 1468 | HR33: 1459 | HS33: 1542 | HT33: 1631 | HU33: 1170 | HV33: 1204 | HW33: 1191 | HX33: 1145 | HY33: 1301.5 | HZ33: 1291 | IA33: =SUM(HO33:HZ33) -> 16248.3 | IB33: 1316.5 | IC33: 1410 | ID33: 1350 | IE33: 1370 | IF33: 1471 | IG33: 1499 | IH33: 1395 | II33: 1378 | IJ33: 1547 | IK33: 1723 | IL33: 1391 | IM33: 1427 | IN33: 17277.5 | IO33: 1919 | IP33: 1864 | IQ33: 1681 | IR33: 1887 | IS33: 1877 | IT33: 2036 | IU33: 2075 | IV33: 2136 | IW33: 2136 | IX33: 2345 | IY33: 2552 | IZ33: 2237.5 | JA33: 24745.5 | JB33: 2149.6 | JC33: 942.5 | JN33: =SUM(JB33:JM33) -> 3092.1 | JP33: =IFERROR((( _xlfn.XLOOKUP((DATE(YEAR($JP$5),MONTH($JP$5),1)),SMN.AGRO.DATE,$B33:$JN33) / _xlfn.XLOOKUP((DATE(YEAR($JP$5)-1,MONTH($JP$5),1)),SMN.AGRO.DATE,$B33:$JN33) )-1)*100,"") -> 56.797477 | JQ33: =IFERROR(((JS33/JR33)-1)*100,"") -> 43.223846 | JR33: =SUMIFS($B33:$JN33,SMN.AGRO.DATE,">="&DATE(YEAR($JP$5)-1,1,1),SMN.AGRO.DATE,"<="&DATE(YEAR($JP$5)-1,MONTH($JP$5),1)) -> 17277.5 | JS33: =SUMIFS($B33:$JN33,SMN.AGRO.DATE,">="&DATE(YEAR($JP$5),1,1),SMN.AGRO.DATE,"<="&$JP$5) -> 24745.5 | JU33: =SUM(B33:JN33) -> 605309.4 | JV33: Piña | JW33: =IF(EXACT(A33,JV33)=TRUE,"OK","VER") -> OK
A34: Plátano | B34: 24183 | C34: 25044 | D34: 25980 | E34: 26842 | F34: 24582 | G34: 25921 | H34: 26890 | I34: 26571 | J34: 24534 | K34: 23399 | L34: 22940 | M34: 24182 | N34: =SUM(B34:M34) -> 301068 | O34: 25036 | P34: 25783 | Q34: 26610 | R34: 25790 | S34: 27160 | T34: 28130 | U34: 25737 | V34: 24670 | W34: 23174 | X34: 23835 | Y34: 23284 | Z34: 25367 | AA34: =SUM(O34:Z34) -> 304576 | AB34: 25998 | AC34: 26988 | AD34: 26188 | AE34: 25696 | AF34: 27150 | AG34: 26659 | AH34: 27118 | AI34: 27274 | AJ34: 27504 | AK34: 29130 | AL34: 28043 | AM34: 27139 | AN34: =SUM(AB34:AM34) -> 324887 | AO34: 25290 | AP34: 28060 | AQ34: 27549 | AR34: 26998 | AS34: 27045 | AT34: 27737 | AU34: 27085 | AV34: 26282 | AW34: 27097.5 | AX34: 26858 | AY34: 28269 | AZ34: 24780 | BA34: =SUM(AO34:AZ34) -> 323050.5 | BB34: 28298 | BC34: 31082 | BD34: 28603 | BE34: 29142 | BF34: 36761 | BG34: 31798 | BH34: 36291 | BI34: 34164 | BJ34: 36535 | BK34: 36697 | BL34: 36266 | BM34: 37698 | BN34: =SUM(BB34:BM34) -> 403335 | BO34: 33409 | BP34: 33071 | BQ34: 33855 | BR34: 33766 | BS34: 34804 | BT34: 30013 | BU34: 30000 | BV34: 30351 | BW34: 28777 | BX34: 27122 | BY34: 32214 | BZ34: 22016 | CA34: =SUM(BO34:BZ34) -> 369398 | CB34: 37966 | CC34: 36830 | CD34: 32931 | CE34: 36484 | CF34: 39446 | CG34: 40358 | CH34: 38718 | CI34: 41496 | CJ34: 40256 | CK34: 40401 | CL34: 39424 | CM34: 37661 | CN34: =SUM(CB34:CM34) -> 461971 | CO34: 37538 | CP34: 35099 | CQ34: 38067 | CR34: 35590 | CS34: 38284 | CT34: 39655 | CU34: 40719 | CV34: 41999 | CW34: 41880 | CX34: 42808 | CY34: 41925 | CZ34: 42966 | DA34: =SUM(CO34:CZ34) -> 476530 | DB34: 38277 | DC34: 38163 | DD34: 38686 | DE34: 37969 | DF34: 40853 | DG34: 41166 | DH34: 39222 | DI34: 37792 | DJ34: 37615 | DK34: 38752 | DL34: 40344 | DM34: 34789 | DN34: =SUM(DB34:DM34) -> 463628 | DO34: 34049 | DP34: 30812 | DQ34: 34381 | DR34: 28936 | DS34: 33069 | DT34: 32286 | DU34: 33859 | DV34: 33999 | DW34: 36949 | DX34: 30621 | DY34: 23889 | DZ34: 30761 | EA34: =SUM(DO34:DZ34) -> 383611 | EB34: 30889 | EC34: 31627 | ED34: 32103 | EE34: 31386 | EF34: 32175 | EG34: 32396 | EH34: 34644 | EI34: 33280 | EJ34: 30294 | EK34: 30555 | EL34: 32483 | EM34: 33700 | EN34: =SUM(EB34:EM34) -> 385532 | EO34: 31039 | EP34: 33135 | EQ34: 34283 | ER34: 31226 | ES34: 30222 | ET34: 32304 | EU34: 31755 | EV34: 32070 | EW34: 36033 | EX34: 33989 | EY34: 34361 | EZ34: 37207 | FA34: =SUM(EO34:EZ34) -> 397624 | FB34: 33487 | FC34: 34140 | FD34: 33802 | FE34: 32830 | FF34: 32266 | FG34: 32159 | FH34: 32445 | FI34: 30193 | FJ34: 32504 | FK34: 32352 | FL34: 33612 | FM34: 33128 | FN34: =SUM(FB34:FM34) -> 392918 | FO34: 33487 | FP34: 34140 | FQ34: 33802 | FR34: 32830 | FS34: 32266 | FT34: 32159 | FU34: 32445 | FV34: 30193 | FW34: 32504 | FX34: 32352 | FY34: 33612 | FZ34: 33128 | GA34: =SUM(FO34:FZ34) -> 392918 | GB34: 36047 | GC34: 35308.75 | GD34: 35149 | GE34: 36365.5 | GF34: 36475 | GG34: 35751 | GH34: 34520 | GI34: 34916 | GJ34: 38024 | GK34: 37021 | GL34: 37795 | GM34: 40706 | GN34: =SUM(GB34:GM34) -> 438078.25 | GO34: 36587 | GP34: 38155 | GQ34: 37002 | GR34: 38834 | GS34: 37038 | GT34: 36849 | GU34: 37354 | GV34: 37540 | GW34: 39186 | GX34: 40812.5 | GY34: 40022 | GZ34: 43648 | HA34: =SUM(GO34:GZ34) -> 463027.5 | HB34: 37111 | HC34: 39822 | HD34: 38982 | HE34: 39962 | HF34: 40916 | HG34: 38865 | HH34: 38060.5 | HI34: 36768 | HJ34: 38034 | HK34: 36011 | HL34: 38195 | HM34: 37989 | HN34: =SUM(HB34:HM34) -> 460715.5 | HO34: 37560 | HP34: 40580 | HQ34: 39248 | HR34: 40408 | HS34: 41427 | HT34: 39725 | HU34: 37447 | HV34: 40514 | HW34: 37129 | HX34: 37086.5 | HY34: 39718 | HZ34: 37419 | IA34: =SUM(HO34:HZ34) -> 468261.5 | IB34: 40281 | IC34: 41043 | ID34: 40913 | IE34: 37739 | IF34: 39271 | IG34: 36105.4 | IH34: 33887 | II34: 33356 | IJ34: 30393 | IK34: 31948 | IL34: 34289 | IM34: 38325 | IN34: 437550.4 | IO34: 39147 | IP34: 40777 | IQ34: 39128 | IR34: 38041 | IS34: 40714 | IT34: 38376 | IU34: 37116 | IV34: 36940 | IW34: 36327 | IX34: 37338 | IY34: 41464 | IZ34: 46834 | JA34: 472202 | JB34: 45572 | JC34: 42349 | JN34: =SUM(JB34:JM34) -> 87921 | JP34: =IFERROR((( _xlfn.XLOOKUP((DATE(YEAR($JP$5),MONTH($JP$5),1)),SMN.AGRO.DATE,$B34:$JN34) / _xlfn.XLOOKUP((DATE(YEAR($JP$5)-1,MONTH($JP$5),1)),SMN.AGRO.DATE,$B34:$JN34) )-1)*100,"") -> 22.202218 | JQ34: =IFERROR(((JS34/JR34)-1)*100,"") -> 7.9194534 | JR34: =SUMIFS($B34:$JN34,SMN.AGRO.DATE,">="&DATE(YEAR($JP$5)-1,1,1),SMN.AGRO.DATE,"<="&DATE(YEAR($JP$5)-1,MONTH($JP$5),1)) -> 437550.4 | JS34: =SUMIFS($B34:$JN34,SMN.AGRO.DATE,">="&DATE(YEAR($JP$5),1,1),SMN.AGRO.DATE,"<="&$JP$5) -> 472202 | JU34: =SUM(B34:JN34) -> 16417605 | JV34: Plátano | JW34: =IF(EXACT(A34,JV34)=TRUE,"OK","VER") -> OK
A35: Sacha Inchi | N35: =SUM(B35:M35) -> 0 | O35: 75 | P35: 130 | Q35: 106 | R35: 106 | S35: 157 | T35: 129 | U35: 124 | V35: 112 | W35: 121 | X35: 133 | Y35: 123 | Z35: 132 | AA35: =SUM(O35:Z35) -> 1448 | AB35: 139 | AC35: 161 | AD35: 150 | AE35: 153 | AF35: 147 | AG35: 132 | AH35: 274 | AI35: 310 | AJ35: 307 | AK35: 272 | AL35: 296 | AM35: 375 | AN35: =SUM(AB35:AM35) -> 2716 | AO35: 130 | AP35: 124 | AQ35: 113 | AR35: 96 | AS35: 108 | AT35: 106 | AU35: 104 | AV35: 87 | AW35: 86 | AX35: 69 | AY35: 61 | AZ35: 67 | BA35: =SUM(AO35:AZ35) -> 1151 | BB35: 127 | BC35: 142 | BD35: 180 | BE35: 199 | BF35: 226 | BG35: 133 | BH35: 206 | BI35: 234 | BJ35: 358 | BK35: 216 | BL35: 233 | BM35: 153 | BN35: =SUM(BB35:BM35) -> 2407 | BO35: 85 | BP35: 75 | BQ35: 83 | BR35: 89 | BS35: 114 | BT35: 101 | BU35: 175 | BV35: 173 | BW35: 183 | BX35: 176 | BY35: 223 | BZ35: 212 | CA35: =SUM(BO35:BZ35) -> 1689 | CB35: 30 | CC35: 27 | CD35: 41 | CE35: 38 | CF35: 51 | CG35: 46 | CH35: 47 | CI35: 57 | CJ35: 61 | CK35: 54 | CL35: 70 | CM35: 85 | CN35: =SUM(CB35:CM35) -> 607 | CO35: 55 | CP35: 76 | CQ35: 87 | CR35: 104 | CS35: 101.86 | CT35: 148.4 | CU35: 170 | CV35: 144 | CW35: 145.65 | CX35: 121 | CY35: 102 | CZ35: 81 | DA35: =SUM(CO35:CZ35) -> 1335.91 | DB35: 107 | DC35: 105 | DD35: 110 | DE35: 119 | DF35: 96 | DG35: 225 | DH35: 151 | DI35: 165 | DJ35: 155 | DK35: 165 | DL35: 167 | DM35: 170 | DN35: =SUM(DB35:DM35) -> 1735 | DO35: 34 | DP35: 40 | DQ35: 38 | DR35: 39 | DS35: 37 | DT35: 39 | DU35: 35 | DV35: 33 | DW35: 45 | DX35: 35 | DY35: 40 | DZ35: 35 | EA35: =SUM(DO35:DZ35) -> 450 | EB35: 81 | EC35: 82 | ED35: 100 | EE35: 54 | EF35: 51 | EG35: 76 | EH35: 81 | EI35: 87 | EJ35: 119 | EK35: 105 | EL35: 110 | EM35: 116 | EN35: =SUM(EB35:EM35) -> 1062 | EO35: 76 | EP35: 99 | EQ35: 127 | ER35: 86 | ES35: 118 | ET35: 110 | EU35: 142 | EV35: 168 | EW35: 218 | EX35: 220 | EY35: 206 | EZ35: 174 | FA35: =SUM(EO35:EZ35) -> 1744 | FB35: 152 | FC35: 168 | FD35: 142 | FE35: 187 | FF35: 178 | FG35: 165 | FH35: 190 | FI35: 205 | FJ35: 186 | FK35: 174 | FL35: 216 | FM35: 231 | FN35: =SUM(FB35:FM35) -> 2194 | FO35: 206 | FP35: 166 | FQ35: 178 | FR35: 211 | FS35: 196 | FT35: 150 | FU35: 140 | FV35: 171 | FW35: 168 | FX35: 119 | FY35: 148 | FZ35: 140 | GA35: =SUM(FO35:FZ35) -> 1993 | GB35: 61 | GC35: 90 | GD35: 62 | GE35: 85 | GF35: 105.4 | GG35: 100 | GH35: 108 | GI35: 103 | GJ35: 107 | GK35: 88 | GL35: 101 | GM35: 111 | GN35: =SUM(GB35:GM35) -> 1121.4 | GO35: 118.5 | GP35: 129 | GQ35: 134 | GR35: 103.5 | GS35: 67 | GT35: 85.5 | GU35: 94.5 | GV35: 69.2 | GW35: 83.8 | GX35: 75.5 | GY35: 41 | GZ35: 126 | HA35: =SUM(GO35:GZ35) -> 1127.5 | HB35: 124.5 | HC35: 136 | HD35: 152.3 | HE35: 106.3 | HF35: 69.5 | HG35: 100.2 | HH35: 92.5 | HI35: 73 | HJ35: 72 | HK35: 80.3 | HL35: 70.5 | HM35: 132 | HN35: =SUM(HB35:HM35) -> 1209.1 | HO35: 154 | HP35: 190 | HQ35: 196 | HR35: 156 | HS35: 145 | HT35: 177 | HU35: 140.5 | HV35: 134 | HW35: 139 | HX35: 143.5 | HY35: 147 | HZ35: 136 | IA35: =SUM(HO35:HZ35) -> 1858 | IB35: 96 | IC35: 109.5 | ID35: 114.5 | IE35: 116 | IF35: 115 | IG35: 133 | IH35: 128.5 | II35: 101.5 | IJ35: 99.5 | IK35: 84 | IL35: 74.5 | IM35: 89 | IN35: 1261 | IO35: 65 | IP35: 57 | IQ35: 64 | IR35: 66 | IS35: 70 | IT35: 86 | IU35: 95.5 | IV35: 83 | IW35: 87 | IX35: 77.5 | IY35: 70 | IZ35: 73 | JA35: 894 | JB35: 66 | JC35: 74.5 | JN35: =SUM(JB35:JM35) -> 140.5 | JP35: =IFERROR((( _xlfn.XLOOKUP((DATE(YEAR($JP$5),MONTH($JP$5),1)),SMN.AGRO.DATE,$B35:$JN35) / _xlfn.XLOOKUP((DATE(YEAR($JP$5)-1,MONTH($JP$5),1)),SMN.AGRO.DATE,$B35:$JN35) )-1)*100,"") -> -17.977528 | JQ35: =IFERROR(((JS35/JR35)-1)*100,"") -> -29.103886 | JR35: =SUMIFS($B35:$JN35,SMN.AGRO.DATE,">="&DATE(YEAR($JP$5)-1,1,1),SMN.AGRO.DATE,"<="&DATE(YEAR($JP$5)-1,MONTH($JP$5),1)) -> 1261 | JS35: =SUMIFS($B35:$JN35,SMN.AGRO.DATE,">="&DATE(YEAR($JP$5),1,1),SMN.AGRO.DATE,"<="&$JP$5) -> 894 | JU35: =SUM(B35:JN35) -> 56286.82 | JV35: Sacha Inchi | JW35: =IF(EXACT(A35,JV35)=TRUE,"OK","VER") -> OK
A36: Sacha Papa | B36: 14 | C36: 9 | D36: 9 | E36: 9 | F36: 9 | G36: 9 | H36: 9 | I36: 9 | J36: 9 | K36: 5 | L36: 5 | M36: 5 | N36: =SUM(B36:M36) -> 101 | O36: 9 | P36: 9 | Q36: 14 | R36: 9 | S36: 7 | T36: 5 | U36: 9 | V36: 5 | W36: 5 | X36: 11 | Y36: 5 | Z36: 5 | AA36: =SUM(O36:Z36) -> 93 | AB36: 5 | AC36: 5 | AD36: 5 | AE36: 5 | AF36: 5 | AG36: 5 | AH36: 5 | AI36: 5 | AJ36: 5 | AK36: 5 | AL36: 5 | AM36: 5 | AN36: =SUM(AB36:AM36) -> 60 | AO36: 5 | AP36: 5 | AQ36: 5 | AR36: 5 | AS36: 5 | AT36: 5 | AU36: 5 | AV36: 5 | AW36: 5 | AX36: 5 | AY36: 5 | AZ36: 5 | BA36: =SUM(AO36:AZ36) -> 60 | BB36: 4 | BC36: 5 | BD36: 4 | BE36: 5 | BF36: 4 | BG36: 5 | BH36: 5 | BI36: 33 | BJ36: 4 | BK36: 5 | BL36: 9 | BM36: 4 | BN36: =SUM(BB36:BM36) -> 87 | BO36: 5 | BP36: 5 | BQ36: 5 | BR36: 5 | BS36: 5 | BT36: 5 | BU36: 5 | BV36: 5 | BW36: 17 | BX36: 5 | BY36: 5 | BZ36: 5 | CA36: =SUM(BO36:BZ36) -> 72 | CB36: 7 | CC36: 6 | CD36: 9 | CE36: 15 | CF36: 8 | CG36: 5 | CH36: 8 | CI36: 5 | CJ36: 5 | CK36: 5 | CL36: 5 | CM36: 5 | CN36: =SUM(CB36:CM36) -> 83 | CO36: 5 | CP36: 9 | CQ36: 9 | CR36: 9 | CS36: 9 | CT36: 9 | CU36: 9 | CV36: 9 | CW36: 9 | CX36: 9 | CY36: 9 | CZ36: 9 | DA36: =SUM(CO36:CZ36) -> 104 | DB36: 5 | DC36: 5 | DD36: 5 | DE36: 5 | DF36: 5 | DG36: 5 | DH36: 5 | DI36: 5 | DJ36: 5 | DK36: 5 | DL36: 5 | DM36: 5 | DN36: =SUM(DB36:DM36) -> 60 | DO36: 5 | DP36: 5 | DQ36: 5 | DR36: 5 | DS36: 5 | DT36: 5 | DU36: 5 | DV36: 5 | DW36: 5 | DX36: 5 | DY36: 5 | DZ36: 5 | EA36: =SUM(DO36:DZ36) -> 60 | EB36: 5 | EC36: 6 | ED36: 6 | EE36: 6 | EF36: 6 | EG36: 6 | EH36: 6 | EI36: 5 | EJ36: 5 | EK36: 5 | EL36: 5 | EM36: 5 | EN36: =SUM(EB36:EM36) -> 66 | EO36: 6 | EP36: 6 | EQ36: 6 | ER36: 6 | ES36: 6 | ET36: 6 | EU36: 6 | EV36: 6 | EW36: 6 | EX36: 6 | EY36: 6 | EZ36: 6 | FA36: =SUM(EO36:EZ36) -> 72 | FB36: 6 | FC36: 6 | FD36: 6 | FE36: 6 | FF36: 6 | FG36: 6 | FH36: 7 | FI36: 7 | FJ36: 7 | FK36: 7 | FL36: 7 | FM36: 7 | FN36: =SUM(FB36:FM36) -> 78 | FO36: 7 | FP36: 7 | FQ36: 7 | FR36: 7 | FS36: 7 | FT36: 7 | FU36: 7 | FV36: 7 | FW36: 3 | FX36: 7 | FY36: 7 | FZ36: 7 | GA36: =SUM(FO36:FZ36) -> 80 | GB36: 7 | GC36: 7 | GD36: 7 | GE36: 7 | GF36: 7 | GG36: 7 | GH36: 7 | GI36: 7 | GJ36: 7 | GK36: 7 | GL36: 7 | GM36: 7 | GN36: =SUM(GB36:GM36) -> 84 | GO36: 7 | GP36: 7 | GQ36: 7 | GR36: 7 | GS36: 7 | GT36: 7 | GU36: 6.95 | GV36: 6.9 | GW36: 6.6 | GX36: 7 | GY36: 7 | GZ36: 7 | HA36: =SUM(GO36:GZ36) -> 83.45 | HB36: 7 | HD36: 7 | HE36: 7.2 | HF36: 7.2 | HG36: 7.2 | HH36: 5 | HI36: 3.9 | HJ36: 3.8 | HK36: 3.8 | HL36: 3.8 | HM36: 3.8 | HN36: =SUM(HB36:HM36) -> 59.7 | HY36: 6.5 | IA36: =SUM(HO36:HZ36) -> 6.5 | IB36: 0 | IC36: 0 | ID36: 0 | IE36: 0 | IF36: 0 | IG36: 0 | IH36: 0 | II36: 0 | IJ36: 0 | IK36: 0 | IL36: 0 | IM36: 0 | IN36: 0 | IO36: 0 | IP36: 0 | IQ36: 0 | IR36: 0 | IS36: 0 | IT36: 0 | IU36: 0 | IV36: 0 | IW36: 0 | IX36: 0 | IY36: 0 | IZ36: 0 | JA36: 0 | JB36: 0 | JC36: 0 | JN36: =SUM(JB36:JM36) -> 0 | JP36: =IFERROR((( _xlfn.XLOOKUP((DATE(YEAR($JP$5),MONTH($JP$5),1)),SMN.AGRO.DATE,$B36:$JN36) / _xlfn.XLOOKUP((DATE(YEAR($JP$5)-1,MONTH($JP$5),1)),SMN.AGRO.DATE,$B36:$JN36) )-1)*100,"") | JQ36: =IFERROR(((JS36/JR36)-1)*100,"") | JR36: =SUMIFS($B36:$JN36,SMN.AGRO.DATE,">="&DATE(YEAR($JP$5)-1,1,1),SMN.AGRO.DATE,"<="&DATE(YEAR($JP$5)-1,MONTH($JP$5),1)) -> 0 | JS36: =SUMIFS($B36:$JN36,SMN.AGRO.DATE,">="&DATE(YEAR($JP$5),1,1),SMN.AGRO.DATE,"<="&$JP$5) -> 0 | JU36: =SUM(B36:JN36) -> 2619.3 | JV36: Sacha Papa | JW36: =IF(EXACT(A36,JV36)=TRUE,"OK","VER") -> OK
A37: Soya | B37: 11 | C37: 6 | D37: 7 | E37: 10 | F37: 5 | G37: 5 | H37: 7 | I37: 173 | J37: 7 | K37: 4 | L37: 92 | M37: 7 | N37: =SUM(B37:M37) -> 334 | O37: 11 | P37: 1 | Q37: 2 | R37: 15 | S37: 4 | T37: 44 | U37: 44 | V37: 4 | W37: 3 | X37: 6 | Y37: 78 | Z37: 54 | AA37: =SUM(O37:Z37) -> 266 | AB37: 4 | AC37: 5 | AD37: 5 | AE37: 3 | AF37: 5 | AG37: 6 | AH37: 7 | AI37: 108 | AJ37: 9 | AK37: 131 | AL37: 10 | AM37: 6 | AN37: =SUM(AB37:AM37) -> 299 | AO37: 9 | AP37: 7 | AQ37: 9 | AR37: 11 | AS37: 1 | AT37: 11 | AU37: 216 | AV37: 9 | AW37: 90 | AX37: 12 | AY37: 13 | AZ37: 14 | BA37: =SUM(AO37:AZ37) -> 402 | BB37: 11 | BC37: 9 | BD37: 5 | BE37: 10 | BF37: 8 | BG37: 11 | BH37: 9 | BI37: 11 | BJ37: 11 | BK37: 10 | BL37: 9 | BM37: 12 | BN37: =SUM(BB37:BM37) -> 116 | BO37: 9 | BP37: 11 | BQ37: 13 | BR37: 16 | BS37: 17 | BT37: 18 | BU37: 16 | BV37: 15 | BW37: 18 | BX37: 13 | BY37: 21 | BZ37: 16 | CA37: =SUM(BO37:BZ37) -> 183 | CB37: 15 | CC37: 32 | CD37: 3 | CE37: 1 | CF37: 4 | CG37: 6 | CI37: 9 | CJ37: 4 | CK37: 5 | CL37: 4 | CM37: 11 | CN37: =SUM(CB37:CM37) -> 94 | CO37: 13 | CP37: 4 | CQ37: 6 | CR37: 6 | CS37: 6 | CT37: 84 | CU37: 312 | CV37: 13 | CW37: 6 | CX37: 4 | CY37: 7 | CZ37: 6 | DA37: =SUM(CO37:CZ37) -> 467 | DB37: 6 | DC37: 8 | DD37: 11 | DE37: 8 | DF37: 58 | DG37: 6 | DH37: 6 | DI37: 77 | DJ37: 4 | DK37: 2 | DL37: 61 | DM37: 4 | DN37: =SUM(DB37:DM37) -> 251 | DO37: 4 | DP37: 4 | DQ37: 2 | DR37: 4 | DS37: 2 | DT37: 4 | DU37: 4 | DV37: 4 | DW37: 2 | DX37: 2 | DY37: 4 | DZ37: 4 | EA37: =SUM(DO37:DZ37) -> 40 | EB37: 2 | EC37: 5 | EE37: 5 | EF37: 4 | EG37: 2 | EH37: 5 | EI37: 4 | EJ37: 5 | EL37: 2 | EM37: 4 | EN37: =SUM(EB37:EM37) -> 38 | EO37: 4 | EP37: 2 | EQ37: 4 | ER37: 4 | ES37: 5 | ET37: 5 | EU37: 2 | EV37: 5 | EW37: 4 | EX37: 5 | EY37: 5 | EZ37: 4 | FA37: =SUM(EO37:EZ37) -> 49 | FB37: 4 | FC37: 9 | FD37: 7 | FE37: 6 | FF37: 6 | FG37: 4 | FH37: 4 | FI37: 7 | FJ37: 6 | FK37: 6 | FL37: 6 | FM37: 4 | FN37: =SUM(FB37:FM37) -> 69 | FO37: 4 | FP37: 5 | FQ37: 2 | FR37: 6 | FS37: 5 | FT37: 4 | FU37: 6 | FV37: 9 | FW37: 131 | FX37: 5 | FY37: 4 | FZ37: 9 | GA37: =SUM(FO37:FZ37) -> 190 | GB37: 19 | GC37: 4 | GD37: 6 | GE37: 6 | GF37: 4.3 | GG37: 7 | GH37: 4 | GI37: 4 | GJ37: 4 | GK37: 7 | GL37: 4 | GM37: 7 | GN37: =SUM(GB37:GM37) -> 76.3 | GO37: 6.4 | GP37: 4.35 | GQ37: 6.5 | GR37: 4.35 | GS37: 8.7 | GT37: 4.25 | GU37: 4.3 | GV37: 8.55 | GW37: 6.4 | GX37: 6.3 | GY37: 4.25 | GZ37: 4.3 | HA37: =SUM(GO37:GZ37) -> 68.65 | HB37: 4.55 | HC37: 3.6 | HD37: 4.6 | HE37: 2.2 | HF37: 3.4 | HG37: 3.7 | HH37: 3.7 | HI37: 1.8 | HJ37: 1.8 | HK37: 2.4 | HN37: =SUM(HB37:HM37) -> 31.75 | HP37: 5.4 | HQ37: 1.2 | HT37: 3.5 | HU37: 3.6 | HV37: 10 | HW37: 4.3 | HZ37: 7.9 | IA37: =SUM(HO37:HZ37) -> 35.9 | IB37: 4.2 | IC37: 4.5 | ID37: 0 | IE37: 6 | IF37: 0 | IG37: 0 | IH37: 0 | II37: 0 | IJ37: 0 | IK37: 0 | IL37: 0 | IM37: 0 | IN37: 14.7 | IO37: 0 | IP37: 0 | IQ37: 0 | IR37: 0 | IS37: 0 | IT37: 0 | IU37: 0 | IV37: 0 | IW37: 0 | IX37: 0 | IY37: 0 | IZ37: 0 | JA37: 0 | JB37: 0 | JC37: 0 | JN37: =SUM(JB37:JM37) -> 0 | JP37: =IFERROR((( _xlfn.XLOOKUP((DATE(YEAR($JP$5),MONTH($JP$5),1)),SMN.AGRO.DATE,$B37:$JN37) / _xlfn.XLOOKUP((DATE(YEAR($JP$5)-1,MONTH($JP$5),1)),SMN.AGRO.DATE,$B37:$JN37) )-1)*100,"") | JQ37: =IFERROR(((JS37/JR37)-1)*100,"") -> -100 | JR37: =SUMIFS($B37:$JN37,SMN.AGRO.DATE,">="&DATE(YEAR($JP$5)-1,1,1),SMN.AGRO.DATE,"<="&DATE(YEAR($JP$5)-1,MONTH($JP$5),1)) -> 14.7 | JS37: =SUMIFS($B37:$JN37,SMN.AGRO.DATE,">="&DATE(YEAR($JP$5),1,1),SMN.AGRO.DATE,"<="&$JP$5) -> 0 | JU37: =SUM(B37:JN37) -> 6050.6 | JV37: Soya | JW37: =IF(EXACT(A37,JV37)=TRUE,"OK","VER") -> OK
A38: Tomate | B38: 286 | C38: 324 | D38: 264 | E38: 265 | F38: 313 | G38: 251 | H38: 398 | I38: 345 | J38: 322 | K38: 391 | L38: 258 | M38: 246 | N38: =SUM(B38:M38) -> 3663 | O38: 180 | P38: 200 | Q38: 158 | R38: 230 | S38: 103 | T38: 220 | U38: 230 | V38: 222 | W38: 269 | X38: 401 | Y38: 140 | Z38: 220 | AA38: =SUM(O38:Z38) -> 2573 | AB38: 211 | AC38: 180 | AD38: 260 | AE38: 294 | AF38: 250 | AG38: 228 | AH38: 299 | AI38: 353 | AJ38: 333 | AK38: 248 | AL38: 211 | AM38: 311 | AN38: =SUM(AB38:AM38) -> 3178 | AO38: 240 | AP38: 181 | AQ38: 181 | AR38: 268 | AS38: 242 | AT38: 209 | AU38: 196 | AV38: 196 | AW38: 258 | AX38: 228 | AY38: 227 | AZ38: 238 | BA38: =SUM(AO38:AZ38) -> 2664 | BB38: 201 | BC38: 187 | BD38: 159 | BE38: 101 | BF38: 288 | BG38: 233 | BH38: 271 | BI38: 237 | BJ38: 161 | BK38: 204.288 | BL38: 121 | BM38: 113 | BN38: =SUM(BB38:BM38) -> 2276.288 | BO38: 157 | BP38: 147 | BQ38: 197 | BR38: 157 | BS38: 138 | BT38: 158 | BU38: 163 | BV38: 242 | BW38: 219 | BX38: 131 | BY38: 91 | BZ38: 131 | CA38: =SUM(BO38:BZ38) -> 1931 | CB38: 162 | CC38: 145 | CD38: 135 | CE38: 153 | CF38: 212 | CG38: 122 | CH38: 143 | CI38: 205 | CJ38: 166 | CK38: 141 | CL38: 120 | CM38: 155 | CN38: =SUM(CB38:CM38) -> 1859 | CO38: 144 | CP38: 136 | CQ38: 102 | CR38: 96 | CS38: 150 | CT38: 94 | CU38: 150 | CV38: 192 | CW38: 146 | CX38: 102 | CY38: 141 | CZ38: 210 | DA38: =SUM(CO38:CZ38) -> 1663 | DB38: 160 | DC38: 115 | DD38: 130 | DE38: 179 | DF38: 130 | DG38: 123 | DH38: 193 | DI38: 256 | DJ38: 224 | DK38: 244 | DL38: 150 | DM38: 115 | DN38: =SUM(DB38:DM38) -> 2019 | DO38: 142 | DP38: 167 | DQ38: 127 | DR38: 104 | DS38: 132 | DT38: 97 | DU38: 105 | DV38: 118 | DW38: 70 | DX38: 136 | DY38: 127 | DZ38: 231 | EA38: =SUM(DO38:DZ38) -> 1556 | EB38: 82 | EC38: 74 | ED38: 92 | EE38: 80 | EF38: 86 | EG38: 82 | EH38: 103 | EI38: 185 | EJ38: 186 | EK38: 226 | EL38: 126 | EM38: 113 | EN38: =SUM(EB38:EM38) -> 1435 | EO38: 80 | EP38: 101 | EQ38: 76 | ER38: 94 | ES38: 76 | ET38: 93 | EU38: 104 | EV38: 133 | EW38: 106 | EX38: 176 | EY38: 154 | EZ38: 112 | FA38: =SUM(EO38:EZ38) -> 1305 | FB38: 234 | FC38: 108 | FD38: 145 | FE38: 115 | FF38: 110 | FG38: 115 | FH38: 128 | FI38: 173 | FJ38: 305 | FK38: 217 | FL38: 225 | FM38: 189 | FN38: =SUM(FB38:FM38) -> 2064 | FO38: 137 | FP38: 130 | FQ38: 106 | FR38: 194 | FS38: 135 | FT38: 178 | FU38: 162 | FV38: 302 | FW38: 335 | FX38: 381 | FY38: 373 | FZ38: 344 | GA38: =SUM(FO38:FZ38) -> 2777 | GB38: 310 | GC38: 237 | GD38: 295 | GE38: 210 | GF38: 204 | GG38: 116 | GH38: 135 | GI38: 221 | GJ38: 224 | GK38: 196 | GL38: 300 | GM38: 330 | GN38: =SUM(GB38:GM38) -> 2778 | GO38: 291.5 | GP38: 221.5 | GQ38: 195.5 | GR38: 198 | GS38: 263 | GT38: 229 | GU38: 193.15 | GV38: 294 | GW38: 296.97 | GX38: 403.98 | GY38: 354 | GZ38: 374.95 | HA38: =SUM(GO38:GZ38) -> 3315.55 | HB38: 147.9 | HC38: 113.2 | HD38: 148.4 | HE38: 189.2 | HF38: 180.87 | HG38: 149.4 | HH38: 152.6 | HI38: 164.7 | HJ38: 248.8 | HK38: 226.82 | HL38: 223.92 | HM38: 280.98 | HN38: =SUM(HB38:HM38) -> 2226.79 | HO38: 400.4 | HP38: 171.5 | HQ38: 141 | HR38: 300 | HS38: 214 | HT38: 188 | HU38: 141.5 | HV38: 183.5 | HW38: 285 | HX38: 170.2 | HY38: 380.2 | HZ38: 275.5 | IA38: =SUM(HO38:HZ38) -> 2850.8 | IB38: 286.8 | IC38: 128.9 | ID38: 159.5 | IE38: 198.7 | IF38: 174.7 | IG38: 168 | IH38: 255 | II38: 236 | IJ38: 215 | IK38: 297 | IL38: 238.7 | IM38: 214.6 | IN38: 2572.9 | IO38: 165.5 | IP38: 115 | IQ38: 66.5 | IR38: 176.5 | IS38: 216.3 | IT38: 145.5 | IU38: 178.2 | IV38: 279.5 | IW38: 305.5 | IX38: 304 | IY38: 329 | IZ38: 364.48 | JA38: 2645.98 | JB38: 187.4 | JC38: 64.1 | JN38: =SUM(JB38:JM38) -> 251.5 | JP38: =IFERROR((( _xlfn.XLOOKUP((DATE(YEAR($JP$5),MONTH($JP$5),1)),SMN.AGRO.DATE,$B38:$JN38) / _xlfn.XLOOKUP((DATE(YEAR($JP$5)-1,MONTH($JP$5),1)),SMN.AGRO.DATE,$B38:$JN38) )-1)*100,"") -> 69.841566 | JQ38: =IFERROR(((JS38/JR38)-1)*100,"") -> 2.8403747 | JR38: =SUMIFS($B38:$JN38,SMN.AGRO.DATE,">="&DATE(YEAR($JP$5)-1,1,1),SMN.AGRO.DATE,"<="&DATE(YEAR($JP$5)-1,MONTH($JP$5),1)) -> 2572.9 | JS38: =SUMIFS($B38:$JN38,SMN.AGRO.DATE,">="&DATE(YEAR($JP$5),1,1),SMN.AGRO.DATE,"<="&$JP$5) -> 2645.98 | JU38: =SUM(B38:JN38) -> 95209.616 | JV38: Tomate | JW38: =IF(EXACT(A38,JV38)=TRUE,"OK","VER") -> OK
A39: Uva (Vid) | B39: 104 | C39: 140 | D39: 135 | E39: 143 | F39: 157 | G39: 126 | H39: 193 | I39: 184 | J39: 115 | K39: 140 | L39: 123 | M39: 134 | N39: =SUM(B39:M39) -> 1694 | O39: 104 | P39: 106 | Q39: 129 | R39: 136 | S39: 119 | T39: 173 | U39: 181 | V39: 188 | W39: 188 | X39: 134 | Y39: 146 | Z39: 138 | AA39: =SUM(O39:Z39) -> 1742 | AB39: 114 | AC39: 110 | AD39: 106 | AE39: 152 | AF39: 124 | AG39: 109 | AH39: 157 | AI39: 170 | AJ39: 166 | AK39: 160 | AL39: 177 | AM39: 173 | AN39: =SUM(AB39:AM39) -> 1718 | AO39: 110 | AP39: 219 | AQ39: 228 | AR39: 129 | AS39: 184 | AT39: 159 | AU39: 149 | AV39: 137 | AW39: 106 | AX39: 80 | AY39: 93 | AZ39: 114 | BA39: =SUM(AO39:AZ39) -> 1708 | BB39: 116 | BC39: 207 | BD39: 137 | BE39: 122 | BF39: 106 | BG39: 92 | BH39: 145 | BI39: 66 | BJ39: 77 | BK39: 61 | BL39: 69 | BM39: 81 | BN39: =SUM(BB39:BM39) -> 1279 | BO39: 122 | BP39: 153 | BQ39: 144 | BR39: 150 | BS39: 149 | BT39: 177 | BU39: 151 | BV39: 107 | BW39: 125 | BX39: 90 | BY39: 149 | BZ39: 117 | CA39: =SUM(BO39:BZ39) -> 1634 | CB39: 82 | CC39: 115 | CD39: 143 | CE39: 193 | CF39: 165 | CG39: 172 | CH39: 103 | CI39: 91 | CJ39: 111 | CK39: 85 | CL39: 145 | CM39: 148 | CN39: =SUM(CB39:CM39) -> 1553 | CO39: 104 | CP39: 102 | CQ39: 143 | CR39: 169 | CS39: 188 | CT39: 149 | CU39: 138 | CV39: 107 | CW39: 108 | CX39: 103 | CY39: 130 | CZ39: 124 | DA39: =SUM(CO39:CZ39) -> 1565 | DB39: 117 | DC39: 92 | DD39: 123 | DE39: 157 | DF39: 209 | DG39: 167 | DH39: 154 | DI39: 177 | DJ39: 116 | DK39: 102 | DL39: 102 | DM39: 81 | DN39: =SUM(DB39:DM39) -> 1597 | DO39: 94 | DP39: 72 | DQ39: 93 | DR39: 145 | DS39: 173 | DT39: 167 | DU39: 84 | DV39: 62 | DW39: 69 | DX39: 93 | DY39: 50 | DZ39: 62 | EA39: =SUM(DO39:DZ39) -> 1164 | EB39: 40 | EC39: 51 | ED39: 51 | EE39: 157 | EF39: 194 | EG39: 171 | EH39: 97 | EI39: 72 | EJ39: 46 | EK39: 74 | EL39: 62 | EM39: 114 | EN39: =SUM(EB39:EM39) -> 1129 | EO39: 35 | EP39: 44 | EQ39: 30 | ER39: 150 | ES39: 163 | ET39: 178 | EU39: 46 | EV39: 60 | EW39: 46 | EX39: 78 | EY39: 60 | EZ39: 66 | FA39: =SUM(EO39:EZ39) -> 956 | FB39: 42 | FC39: 53 | FD39: 41 | FE39: 173 | FF39: 165 | FG39: 150 | FH39: 67 | FI39: 70 | FJ39: 75 | FK39: 84 | FL39: 60 | FM39: 107 | FN39: =SUM(FB39:FM39) -> 1087 | FO39: 50 | FP39: 60 | FQ39: 36 | FR39: 72 | FS39: 172 | FT39: 150 | FU39: 62 | FV39: 62 | FW39: 59 | FX39: 91 | FY39: 61 | FZ39: 67 | GA39: =SUM(FO39:FZ39) -> 942 | GB39: 59 | GC39: 73 | GD39: 60 | GE39: 78 | GF39: 168.5 | GG39: 132 | GH39: 60 | GI39: 73 | GJ39: 66 | GK39: 101 | GL39: 75.5 | GM39: 90 | GN39: =SUM(GB39:GM39) -> 1036 | GO39: 65 | GP39: 76 | GQ39: 59 | GR39: 81 | GS39: 149 | GT39: 152 | GU39: 56 | GV39: 48 | GW39: 74 | GX39: 108 | GY39: 87 | GZ39: 82 | HA39: =SUM(GO39:GZ39) -> 1037 | HB39: 74.5 | HC39: 106.5 | HD39: 92 | HE39: 98.5 | HF39: 163.5 | HG39: 205 | HH39: 96 | HI39: 56.5 | HJ39: 77.5 | HK39: 138 | HL39: 347 | HM39: 88.5 | HN39: =SUM(HB39:HM39) -> 1543.5 | HO39: 78 | HP39: 76 | HQ39: 66.5 | HR39: 90 | HS39: 134.5 | HT39: 150.5 | HU39: 75.5 | HV39: 69 | HW39: 75 | HX39: 130 | HY39: 317 | HZ39: 108 | IA39: =SUM(HO39:HZ39) -> 1370 | IB39: 109 | IC39: 106 | ID39: 101 | IE39: 105 | IF39: 105 | IG39: 95 | IH39: 77 | II39: 70 | IJ39: 85.9 | IK39: 90.5 | IL39: 222.5 | IM39: 103 | IN39: 1269.9 | IO39: 73 | IP39: 96 | IQ39: 111 | IR39: 108 | IS39: 101 | IT39: 115 | IU39: 109 | IV39: 79.5 | IW39: 94.7 | IX39: 98.5 | IY39: 219 | IZ39: 116 | JA39: 1320.7 | JB39: 107 | JC39: 132 | JN39: =SUM(JB39:JM39) -> 239 | JP39: =IFERROR((( _xlfn.XLOOKUP((DATE(YEAR($JP$5),MONTH($JP$5),1)),SMN.AGRO.DATE,$B39:$JN39) / _xlfn.XLOOKUP((DATE(YEAR($JP$5)-1,MONTH($JP$5),1)),SMN.AGRO.DATE,$B39:$JN39) )-1)*100,"") -> 12.621359 | JQ39: =IFERROR(((JS39/JR39)-1)*100,"") -> 4.000315 | JR39: =SUMIFS($B39:$JN39,SMN.AGRO.DATE,">="&DATE(YEAR($JP$5)-1,1,1),SMN.AGRO.DATE,"<="&DATE(YEAR($JP$5)-1,MONTH($JP$5),1)) -> 1269.9 | JS39: =SUMIFS($B39:$JN39,SMN.AGRO.DATE,">="&DATE(YEAR($JP$5),1,1),SMN.AGRO.DATE,"<="&$JP$5) -> 1320.7 | JU39: =SUM(B39:JN39) -> 55168.2 | JV39: Uva (Vid) | JW39: =IF(EXACT(A39,JV39)=TRUE,"OK","VER") -> OK
A40: Yuca | B40: 7848 | C40: 6576 | D40: 8424 | E40: 6602 | F40: 4278 | G40: 3388 | H40: 5532 | I40: 5700 | J40: 5508 | K40: 5652 | L40: 5718 | M40: 5546 | N40: =SUM(B40:M40) -> 70772 | O40: 5400 | P40: 5953 | Q40: 5184 | R40: 5178 | S40: 5800 | T40: 5637 | U40: 4892 | V40: 4998 | W40: 5237 | X40: 5376 | Y40: 4720 | Z40: 4791 | AA40: =SUM(O40:Z40) -> 63166 | AB40: 5174 | AC40: 4718 | AD40: 5166 | AE40: 4533 | AF40: 4548 | AG40: 4807 | AH40: 5223 | AI40: 5496 | AJ40: 5221 | AK40: 6077 | AL40: 5637 | AM40: 5729 | AN40: =SUM(AB40:AM40) -> 62329 | AO40: 5423 | AP40: 6230 | AQ40: 5946 | AR40: 5726 | AS40: 5828 | AT40: 6168 | AU40: 5614 | AV40: 5772 | AW40: 6222.35 | AX40: 6631 | AY40: 5761 | AZ40: 5618 | BA40: =SUM(AO40:AZ40) -> 70939.35 | BB40: 5411 | BC40: 5531 | BD40: 5795 | BE40: 5899 | BF40: 6096 | BG40: 7068 | BH40: 7380 | BI40: 7243 | BJ40: 7964 | BK40: 7757 | BL40: 8195 | BM40: 7425 | BN40: =SUM(BB40:BM40) -> 81764 | BO40: 6701 | BP40: 7742 | BQ40: 7723 | BR40: 7796 | BS40: 8083 | BT40: 8542 | BU40: 9261 | BV40: 9440 | BW40: 10094 | BX40: 8690 | BY40: 9096 | BZ40: 8170 | CA40: =SUM(BO40:BZ40) -> 101338 | CB40: 8940 | CC40: 8165 | CD40: 8979 | CE40: 9765 | CF40: 10143 | CG40: 9548 | CH40: 9129 | CI40: 9734 | CJ40: 9804 | CK40: 9753 | CL40: 10990 | CM40: 9123 | CN40: =SUM(CB40:CM40) -> 114073 | CO40: 8376 | CP40: 8832 | CQ40: 7947 | CR40: 8907 | CS40: 9049 | CT40: 9994 | CU40: 10913 | CV40: 9276 | CW40: 9413 | CX40: 9383 | CY40: 9820 | CZ40: 9046 | DA40: =SUM(CO40:CZ40) -> 110956 | DB40: 8491 | DC40: 8654 | DD40: 8769 | DE40: 8935 | DF40: 8798 | DG40: 8142 | DH40: 9033 | DI40: 9612 | DJ40: 9305 | DK40: 9377 | DL40: 9604 | DM40: 8951 | DN40: =SUM(DB40:DM40) -> 107671 | DO40: 7934 | DP40: 8147 | DQ40: 7347.5 | DR40: 8908 | DS40: 8150 | DT40: 8240 | DU40: 9087 | DV40: 8074 | DW40: 8771 | DX40: 8267 | DY40: 10651 | DZ40: 8534 | EA40: =SUM(DO40:DZ40) -> 102110.5 | EB40: 7926 | EC40: 8288 | ED40: 7849 | EE40: 7955 | EF40: 8942 | EG40: 8303 | EH40: 9022 | EI40: 7780 | EJ40: 9234 | EK40: 8012 | EL40: 9053 | EM40: 7524 | EN40: =SUM(EB40:EM40) -> 99888 | EO40: 7809 | EP40: 8149 | EQ40: 7236 | ER40: 7818 | ES40: 8691 | ET40: 7937 | EU40: 6663 | EV40: 7362 | EW40: 8801 | EX40: 7412 | EY40: 7991 | EZ40: 7319 | FA40: =SUM(EO40:EZ40) -> 93188 | FB40: 7027 | FC40: 7414 | FD40: 7063 | FE40: 7718 | FF40: 8845 | FG40: 7614 | FH40: 6929 | FI40: 8110 | FJ40: 7185 | FK40: 6784 | FL40: 6657 | FM40: 7152 | FN40: =SUM(FB40:FM40) -> 88498 | FO40: 6293 | FP40: 6532 | FQ40: 7459 | FR40: 7465 | FS40: 7661 | FT40: 8005 | FU40: 7295 | FV40: 7026 | FW40: 6914 | FX40: 6846 | FY40: 7516 | FZ40: 7013 | GA40: =SUM(FO40:FZ40) -> 86025 | GB40: 7470.5 | GC40: 8810 | GD40: 10393 | GE40: 7200 | GF40: 10970 | GG40: 7042 | GH40: 6735 | GI40: 6094 | GJ40: 6816.5 | GK40: 6811 | GL40: 10668 | GM40: 8701 | GN40: =SUM(GB40:GM40) -> 97711 | GO40: 7369 | GP40: 10351 | GQ40: 8646 | GR40: 9092 | GS40: 8441 | GT40: 7840 | GU40: 7648.85 | GV40: 8247 | GW40: 7363.3 | GX40: 8612.95 | GY40: 11490.3 | GZ40: 10170 | HA40: =SUM(GO40:GZ40) -> 105271.4 | HB40: 9161.6 | HC40: 8820.6 | HD40: 10271.22 | HE40: 9258 | HF40: 9416.95 | HG40: 8726.55 | HH40: 8086.95 | HI40: 8618.15 | HJ40: 8477.5 | HK40: 9567 | HL40: 12419.22 | HM40: 10899 | HN40: =SUM(HB40:HM40) -> 113722.74 | HO40: 10019.26 | HP40: 11092.26 | HQ40: 13770.54 | HR40: 12749.55 | HS40: 11162.45 | HT40: 10259.75 | HU40: 10433.48 | HV40: 12562.55 | HW40: 13670.58 | HX40: 9625.15 | HY40: 12345.62 | HZ40: 10142.23 | IA40: =SUM(HO40:HZ40) -> 137833.42 | IB40: 8449 | IC40: 8723 | ID40: 11183 | IE40: 9188 | IF40: 9942.5 | IG40: 9288 | IH40: 10226.74 | II40: 9070.5 | IJ40: 9486.5 | IK40: 7736.2 | IL40: 8598.8 | IM40: 7948.68 | IN40: 109840.92 | IO40: 6134.2 | IP40: 4376.5 | IQ40: 8296.3 | IR40: 9100.4 | IS40: 9236.3 | IT40: 10083.2 | IU40: 10736.8 | IV40: 9762.7 | IW40: 10434 | IX40: 8770.5 | IY40: 9348.6 | IZ40: 8362.4 | JA40: 104641.9 | JB40: 8739.7 | JC40: 8483 | JN40: =SUM(JB40:JM40) -> 17222.7 | JP40: =IFERROR((( _xlfn.XLOOKUP((DATE(YEAR($JP$5),MONTH($JP$5),1)),SMN.AGRO.DATE,$B40:$JN40) / _xlfn.XLOOKUP((DATE(YEAR($JP$5)-1,MONTH($JP$5),1)),SMN.AGRO.DATE,$B40:$JN40) )-1)*100,"") -> 5.2048894 | JQ40: =IFERROR(((JS40/JR40)-1)*100,"") -> -4.7332269 | JR40: =SUMIFS($B40:$JN40,SMN.AGRO.DATE,">="&DATE(YEAR($JP$5)-1,1,1),SMN.AGRO.DATE,"<="&DATE(YEAR($JP$5)-1,MONTH($JP$5),1)) -> 109840.92 | JS40: =SUMIFS($B40:$JN40,SMN.AGRO.DATE,">="&DATE(YEAR($JP$5),1,1),SMN.AGRO.DATE,"<="&$JP$5) -> 104641.9 | JU40: =SUM(B40:JN40) -> 3877923.9 | JV40: Yuca | JW40: =IF(EXACT(A40,JV40)=TRUE,"OK","VER") -> OK
A41: Tabaco | B41: 59 | C41: 12 | D41: 9 | F41: 6 | G41: 9 | H41: 6 | I41: 9 | K41: 8 | M41: 6 | N41: =SUM(B41:M41) -> 124 | O41: 6 | P41: 7 | Q41: 1 | R41: 3 | S41: 6 | T41: 6 | U41: 7 | V41: 5 | W41: 10 | AA41: =SUM(O41:Z41) -> 51 | AC41: 18 | AD41: 19 | AE41: 12 | AF41: 5 | AG41: 19 | AJ41: 30 | AM41: 11 | AN41: =SUM(AB41:AM41) -> 114 | AO41: 26 | AQ41: 26 | AS41: 7 | BA41: =SUM(AO41:AZ41) -> 59 | BC41: 15 | BD41: 13 | BE41: 40 | BF41: 44 | BG41: 59 | BJ41: 25 | BM41: 25 | BN41: =SUM(BB41:BM41) -> 221 | BO41: 25 | BP41: 28 | BR41: 15 | BS41: 28 | BT41: 13 | BU41: 13 | BV41: 13 | BW41: 10 | BX41: 13 | BY41: 13 | BZ41: 25 | CA41: =SUM(BO41:BZ41) -> 196 | CB41: 25 | CC41: 31 | CJ41: 10 | CK41: 15 | CM41: 18 | CN41: =SUM(CB41:CM41) -> 99 | CO41: 13 | CP41: 13 | CX41: 25 | CY41: 50 | CZ41: 25 | DA41: =SUM(CO41:CZ41) -> 126 | DC41: 30 | DD41: 29 | DE41: 130 | DI41: 200 | DJ41: 100 | DL41: 160 | DM41: 140 | DN41: =SUM(DB41:DM41) -> 789 | DO41: 140 | DP41: 160 | DQ41: 180 | DR41: 120 | DS41: 160 | DT41: 140 | DW41: 300 | DX41: 140 | DY41: 160 | EA41: =SUM(DO41:DZ41) -> 1500 | EC41: 300 | EE41: 300 | EG41: 600 | EJ41: 300 | EL41: 300 | EN41: =SUM(EB41:EM41) -> 1800 | EO41: 300 | EQ41: 320 | ES41: 300 | EU41: 300 | EW41: 300 | EY41: 300 | FA41: =SUM(EO41:EZ41) -> 1820 | FB41: 300 | FD41: 300 | FF41: 300 | FH41: 200 | FJ41: 300 | FM41: 300 | FN41: =SUM(FB41:FM41) -> 1700 | FO41: 300 | FQ41: 300 | FS41: 300 | FU41: 300 | FW41: 300 | FZ41: 300 | GA41: =SUM(FO41:FZ41) -> 1800 | GD41: 300 | GF41: 300 | GH41: 300 | GJ41: 300 | GL41: 300 | GN41: =SUM(GB41:GM41) -> 1500 | GO41: 300 | GQ41: 300 | GS41: 300 | GU41: 300 | GW41: 300 | GY41: 300 | HA41: =SUM(GO41:GZ41) -> 1800 | HB41: 300 | HD41: 300 | HF41: 300 | HH41: 300 | HJ41: 300 | HL41: 300 | HN41: =SUM(HB41:HM41) -> 1800 | HO41: 300 | HP41: 300 | HQ41: 300 | HR41: 300 | HS41: 300 | HT41: 300 | HU41: 300 | HV41: 290 | HW41: 290 | HX41: 282 | HY41: 300 | HZ41: 300 | IA41: =SUM(HO41:HZ41) -> 3562 | IB41: 300 | IC41: 320 | ID41: 300 | IE41: 310 | IF41: 300 | IG41: 300 | IH41: 300 | II41: 300 | IJ41: 300 | IK41: 300 | IL41: 300 | IM41: 300 | IN41: =SUM(IB41:IM41) -> 3630 | IO41: 700 | IP41: 700 | IQ41: 700 | IR41: 700 | IS41: 700 | IT41: 700 | IU41: 700 | IV41: 700 | IW41: 700 | IX41: 700 | IY41: 700 | JA41: =SUM(IO41:IZ41) -> 7700 | JN41: =SUM(JB41:JM41) -> 0 | JP41: =IFERROR((( _xlfn.XLOOKUP((DATE(YEAR($JP$5),MONTH($JP$5),1)),SMN.AGRO.DATE,$B41:$JN41) / _xlfn.XLOOKUP((DATE(YEAR($JP$5)-1,MONTH($JP$5),1)),SMN.AGRO.DATE,$B41:$JN41) )-1)*100,"") -> -100 | JQ41: =IFERROR(((JS41/JR41)-1)*100,"") -> 112.12121 | JR41: =SUMIFS($B41:$JN41,SMN.AGRO.DATE,">="&DATE(YEAR($JP$5)-1,1,1),SMN.AGRO.DATE,"<="&DATE(YEAR($JP$5)-1,MONTH($JP$5),1)) -> 3630 | JS41: =SUMIFS($B41:$JN41,SMN.AGRO.DATE,">="&DATE(YEAR($JP$5),1,1),SMN.AGRO.DATE,"<="&$JP$5) -> 7700 | JU41: =SUM(B41:JN41) -> 60782 | JV41: ZZ Tabaco | JW41: =IF(EXACT(A41,JV41)=TRUE,"OK","VER") -> VER
A43: Otros agrícolas | B43: {=SUMPRODUCT(('02.XLS'!$A$6:$A$47=$A43)*('02.XLS'!$B$5:$JN$5=B$5)*('02.XLS'!$B$6:$JN$47))} -> 176532 | C43: {=SUMPRODUCT(('02.XLS'!$A$6:$A$47=$A43)*('02.XLS'!$B$5:$JN$5=C$5)*('02.XLS'!$B$6:$JN$47))} -> 184164.03 | D43: {=SUMPRODUCT(('02.XLS'!$A$6:$A$47=$A43)*('02.XLS'!$B$5:$JN$5=D$5)*('02.XLS'!$B$6:$JN$47))} -> 180503 | E43: {=SUMPRODUCT(('02.XLS'!$A$6:$A$47=$A43)*('02.XLS'!$B$5:$JN$5=E$5)*('02.XLS'!$B$6:$JN$47))} -> 176746 | F43: {=SUMPRODUCT(('02.XLS'!$A$6:$A$47=$A43)*('02.XLS'!$B$5:$JN$5=F$5)*('02.XLS'!$B$6:$JN$47))} -> 164905 | G43: {=SUMPRODUCT(('02.XLS'!$A$6:$A$47=$A43)*('02.XLS'!$B$5:$JN$5=G$5)*('02.XLS'!$B$6:$JN$47))} -> 162476.5 | H43: {=SUMPRODUCT(('02.XLS'!$A$6:$A$47=$A43)*('02.XLS'!$B$5:$JN$5=H$5)*('02.XLS'!$B$6:$JN$47))} -> 162019.99 | I43: {=SUMPRODUCT(('02.XLS'!$A$6:$A$47=$A43)*('02.XLS'!$B$5:$JN$5=I$5)*('02.XLS'!$B$6:$JN$47))} -> 159294.5 | ... M43: {=SUMPRODUCT(('02.XLS'!$A$6:$A$47=$A43)*('02.XLS'!$B$5:$JN$5=M$5)*('02.XLS'!$B$6:$JN$47))} -> 156256.5 | N43: =SUM(B43:M43) -> 1981135 | O43: {=SUMPRODUCT(('02.XLS'!$A$6:$A$47=$A43)*('02.XLS'!$B$5:$JN$5=O$5)*('02.XLS'!$B$6:$JN$47))} -> 184992 | P43: {=SUMPRODUCT(('02.XLS'!$A$6:$A$47=$A43)*('02.XLS'!$B$5:$JN$5=P$5)*('02.XLS'!$B$6:$JN$47))} -> 191954 | Q43: {=SUMPRODUCT(('02.XLS'!$A$6:$A$47=$A43)*('02.XLS'!$B$5:$JN$5=Q$5)*('02.XLS'!$B$6:$JN$47))} -> 205476 | R43: {=SUMPRODUCT(('02.XLS'!$A$6:$A$47=$A43)*('02.XLS'!$B$5:$JN$5=R$5)*('02.XLS'!$B$6:$JN$47))} -> 187071 | S43: {=SUMPRODUCT(('02.XLS'!$A$6:$A$47=$A43)*('02.XLS'!$B$5:$JN$5=S$5)*('02.XLS'!$B$6:$JN$47))} -> 185449 | T43: {=SUMPRODUCT(('02.XLS'!$A$6:$A$47=$A43)*('02.XLS'!$B$5:$JN$5=T$5)*('02.XLS'!$B$6:$JN$47))} -> 183927 | U43: {=SUMPRODUCT(('02.XLS'!$A$6:$A$47=$A43)*('02.XLS'!$B$5:$JN$5=U$5)*('02.XLS'!$B$6:$JN$47))} -> 174147.5 | V43: {=SUMPRODUCT(('02.XLS'!$A$6:$A$47=$A43)*('02.XLS'!$B$5:$JN$5=V$5)*('02.XLS'!$B$6:$JN$47))} -> 176754 | ... Z43: {=SUMPRODUCT(('02.XLS'!$A$6:$A$47=$A43)*('02.XLS'!$B$5:$JN$5=Z$5)*('02.XLS'!$B$6:$JN$47))} -> 163834 | AA43: =SUM(O43:Z43) -> 2154145.5 | AB43: {=SUMPRODUCT(('02.XLS'!$A$6:$A$47=$A43)*('02.XLS'!$B$5:$JN$5=AB$5)*('02.XLS'!$B$6:$JN$47))} -> 185286 | AC43: {=SUMPRODUCT(('02.XLS'!$A$6:$A$47=$A43)*('02.XLS'!$B$5:$JN$5=AC$5)*('02.XLS'!$B$6:$JN$47))} -> 193075 | AD43: {=SUMPRODUCT(('02.XLS'!$A$6:$A$47=$A43)*('02.XLS'!$B$5:$JN$5=AD$5)*('02.XLS'!$B$6:$JN$47))} -> 187899 | AE43: {=SUMPRODUCT(('02.XLS'!$A$6:$A$47=$A43)*('02.XLS'!$B$5:$JN$5=AE$5)*('02.XLS'!$B$6:$JN$47))} -> 186570 | AF43: {=SUMPRODUCT(('02.XLS'!$A$6:$A$47=$A43)*('02.XLS'!$B$5:$JN$5=AF$5)*('02.XLS'!$B$6:$JN$47))} -> 185914 | AG43: {=SUMPRODUCT(('02.XLS'!$A$6:$A$47=$A43)*('02.XLS'!$B$5:$JN$5=AG$5)*('02.XLS'!$B$6:$JN$47))} -> 184343 | AH43: {=SUMPRODUCT(('02.XLS'!$A$6:$A$47=$A43)*('02.XLS'!$B$5:$JN$5=AH$5)*('02.XLS'!$B$6:$JN$47))} -> 188275 | AI43: {=SUMPRODUCT(('02.XLS'!$A$6:$A$47=$A43)*('02.XLS'!$B$5:$JN$5=AI$5)*('02.XLS'!$B$6:$JN$47))} -> 184048 | ... AM43: {=SUMPRODUCT(('02.XLS'!$A$6:$A$47=$A43)*('02.XLS'!$B$5:$JN$5=AM$5)*('02.XLS'!$B$6:$JN$47))} -> 175174 | AN43: =SUM(AB43:AM43) -> 2236595 | AO43: {=SUMPRODUCT(('02.XLS'!$A$6:$A$47=$A43)*('02.XLS'!$B$5:$JN$5=AO$5)*('02.XLS'!$B$6:$JN$47))} -> 189704.5 | AP43: {=SUMPRODUCT(('02.XLS'!$A$6:$A$47=$A43)*('02.XLS'!$B$5:$JN$5=AP$5)*('02.XLS'!$B$6:$JN$47))} -> 207298 | AQ43: {=SUMPRODUCT(('02.XLS'!$A$6:$A$47=$A43)*('02.XLS'!$B$5:$JN$5=AQ$5)*('02.XLS'!$B$6:$JN$47))} -> 198697.25 | AR43: {=SUMPRODUCT(('02.XLS'!$A$6:$A$47=$A43)*('02.XLS'!$B$5:$JN$5=AR$5)*('02.XLS'!$B$6:$JN$47))} -> 198164 | AS43: {=SUMPRODUCT(('02.XLS'!$A$6:$A$47=$A43)*('02.XLS'!$B$5:$JN$5=AS$5)*('02.XLS'!$B$6:$JN$47))} -> 193266.9 | AT43: {=SUMPRODUCT(('02.XLS'!$A$6:$A$47=$A43)*('02.XLS'!$B$5:$JN$5=AT$5)*('02.XLS'!$B$6:$JN$47))} -> 189415 | AU43: {=SUMPRODUCT(('02.XLS'!$A$6:$A$47=$A43)*('02.XLS'!$B$5:$JN$5=AU$5)*('02.XLS'!$B$6:$JN$47))} -> 188568 | AV43: {=SUMPRODUCT(('02.XLS'!$A$6:$A$47=$A43)*('02.XLS'!$B$5:$JN$5=AV$5)*('02.XLS'!$B$6:$JN$47))} -> 188659.33 | ... AZ43: {=SUMPRODUCT(('02.XLS'!$A$6:$A$47=$A43)*('02.XLS'!$B$5:$JN$5=AZ$5)*('02.XLS'!$B$6:$JN$47))} -> 196066 | BA43: =SUM(AO43:AZ43) -> 2323982 | BB43: {=SUMPRODUCT(('02.XLS'!$A$6:$A$47=$A43)*('02.XLS'!$B$5:$JN$5=BB$5)*('02.XLS'!$B$6:$JN$47))} -> 190937.95 | BC43: {=SUMPRODUCT(('02.XLS'!$A$6:$A$47=$A43)*('02.XLS'!$B$5:$JN$5=BC$5)*('02.XLS'!$B$6:$JN$47))} -> 208483.4 | BD43: {=SUMPRODUCT(('02.XLS'!$A$6:$A$47=$A43)*('02.XLS'!$B$5:$JN$5=BD$5)*('02.XLS'!$B$6:$JN$47))} -> 209057.87 | BE43: {=SUMPRODUCT(('02.XLS'!$A$6:$A$47=$A43)*('02.XLS'!$B$5:$JN$5=BE$5)*('02.XLS'!$B$6:$JN$47))} -> 202296.17 | BF43: {=SUMPRODUCT(('02.XLS'!$A$6:$A$47=$A43)*('02.XLS'!$B$5:$JN$5=BF$5)*('02.XLS'!$B$6:$JN$47))} -> 205736.51 | BG43: {=SUMPRODUCT(('02.XLS'!$A$6:$A$47=$A43)*('02.XLS'!$B$5:$JN$5=BG$5)*('02.XLS'!$B$6:$JN$47))} -> 199175.3 | BH43: {=SUMPRODUCT(('02.XLS'!$A$6:$A$47=$A43)*('02.XLS'!$B$5:$JN$5=BH$5)*('02.XLS'!$B$6:$JN$47))} -> 197575.23 | BI43: {=SUMPRODUCT(('02.XLS'!$A$6:$A$47=$A43)*('02.XLS'!$B$5:$JN$5=BI$5)*('02.XLS'!$B$6:$JN$47))} -> 200951.08 | ... BM43: {=SUMPRODUCT(('02.XLS'!$A$6:$A$47=$A43)*('02.XLS'!$B$5:$JN$5=BM$5)*('02.XLS'!$B$6:$JN$47))} -> 224533.16 | BN43: =SUM(BB43:BM43) -> 2467464.4 | BO43: {=SUMPRODUCT(('02.XLS'!$A$6:$A$47=$A43)*('02.XLS'!$B$5:$JN$5=BO$5)*('02.XLS'!$B$6:$JN$47))} -> 214546.7 | BP43: {=SUMPRODUCT(('02.XLS'!$A$6:$A$47=$A43)*('02.XLS'!$B$5:$JN$5=BP$5)*('02.XLS'!$B$6:$JN$47))} -> 237049.07 | BQ43: {=SUMPRODUCT(('02.XLS'!$A$6:$A$47=$A43)*('02.XLS'!$B$5:$JN$5=BQ$5)*('02.XLS'!$B$6:$JN$47))} -> 232130.5 | BR43: {=SUMPRODUCT(('02.XLS'!$A$6:$A$47=$A43)*('02.XLS'!$B$5:$JN$5=BR$5)*('02.XLS'!$B$6:$JN$47))} -> 243674 | BS43: {=SUMPRODUCT(('02.XLS'!$A$6:$A$47=$A43)*('02.XLS'!$B$5:$JN$5=BS$5)*('02.XLS'!$B$6:$JN$47))} -> 229798.2 | BT43: {=SUMPRODUCT(('02.XLS'!$A$6:$A$47=$A43)*('02.XLS'!$B$5:$JN$5=BT$5)*('02.XLS'!$B$6:$JN$47))} -> 230444.4 | BU43: {=SUMPRODUCT(('02.XLS'!$A$6:$A$47=$A43)*('02.XLS'!$B$5:$JN$5=BU$5)*('02.XLS'!$B$6:$JN$47))} -> 228114 | BV43: {=SUMPRODUCT(('02.XLS'!$A$6:$A$47=$A43)*('02.XLS'!$B$5:$JN$5=BV$5)*('02.XLS'!$B$6:$JN$47))} -> 237959 | ... BZ43: {=SUMPRODUCT(('02.XLS'!$A$6:$A$47=$A43)*('02.XLS'!$B$5:$JN$5=BZ$5)*('02.XLS'!$B$6:$JN$47))} -> 254432.35 | CA43: =SUM(BO43:BZ43) -> 2818677.4 | CB43: {=SUMPRODUCT(('02.XLS'!$A$6:$A$47=$A43)*('02.XLS'!$B$5:$JN$5=CB$5)*('02.XLS'!$B$6:$JN$47))} -> 212375 | CC43: {=SUMPRODUCT(('02.XLS'!$A$6:$A$47=$A43)*('02.XLS'!$B$5:$JN$5=CC$5)*('02.XLS'!$B$6:$JN$47))} -> 214454 | CD43: {=SUMPRODUCT(('02.XLS'!$A$6:$A$47=$A43)*('02.XLS'!$B$5:$JN$5=CD$5)*('02.XLS'!$B$6:$JN$47))} -> 217615 | CE43: {=SUMPRODUCT(('02.XLS'!$A$6:$A$47=$A43)*('02.XLS'!$B$5:$JN$5=CE$5)*('02.XLS'!$B$6:$JN$47))} -> 216900 | CF43: {=SUMPRODUCT(('02.XLS'!$A$6:$A$47=$A43)*('02.XLS'!$B$5:$JN$5=CF$5)*('02.XLS'!$B$6:$JN$47))} -> 213175 | CG43: {=SUMPRODUCT(('02.XLS'!$A$6:$A$47=$A43)*('02.XLS'!$B$5:$JN$5=CG$5)*('02.XLS'!$B$6:$JN$47))} -> 213993 | CH43: {=SUMPRODUCT(('02.XLS'!$A$6:$A$47=$A43)*('02.XLS'!$B$5:$JN$5=CH$5)*('02.XLS'!$B$6:$JN$47))} -> 215370 | CI43: {=SUMPRODUCT(('02.XLS'!$A$6:$A$47=$A43)*('02.XLS'!$B$5:$JN$5=CI$5)*('02.XLS'!$B$6:$JN$47))} -> 211879 | ... CM43: {=SUMPRODUCT(('02.XLS'!$A$6:$A$47=$A43)*('02.XLS'!$B$5:$JN$5=CM$5)*('02.XLS'!$B$6:$JN$47))} -> 239665 | CN43: =SUM(CB43:CM43) -> 2627782 | CO43: {=SUMPRODUCT(('02.XLS'!$A$6:$A$47=$A43)*('02.XLS'!$B$5:$JN$5=CO$5)*('02.XLS'!$B$6:$JN$47))} -> 218444.25 | CP43: {=SUMPRODUCT(('02.XLS'!$A$6:$A$47=$A43)*('02.XLS'!$B$5:$JN$5=CP$5)*('02.XLS'!$B$6:$JN$47))} -> 238114.1 | CQ43: {=SUMPRODUCT(('02.XLS'!$A$6:$A$47=$A43)*('02.XLS'!$B$5:$JN$5=CQ$5)*('02.XLS'!$B$6:$JN$47))} -> 230502.15 | CR43: {=SUMPRODUCT(('02.XLS'!$A$6:$A$47=$A43)*('02.XLS'!$B$5:$JN$5=CR$5)*('02.XLS'!$B$6:$JN$47))} -> 237042.2 | CS43: {=SUMPRODUCT(('02.XLS'!$A$6:$A$47=$A43)*('02.XLS'!$B$5:$JN$5=CS$5)*('02.XLS'!$B$6:$JN$47))} -> 217629.2 | CT43: {=SUMPRODUCT(('02.XLS'!$A$6:$A$47=$A43)*('02.XLS'!$B$5:$JN$5=CT$5)*('02.XLS'!$B$6:$JN$47))} -> 229253 | CU43: {=SUMPRODUCT(('02.XLS'!$A$6:$A$47=$A43)*('02.XLS'!$B$5:$JN$5=CU$5)*('02.XLS'!$B$6:$JN$47))} -> 226611.95 | CV43: {=SUMPRODUCT(('02.XLS'!$A$6:$A$47=$A43)*('02.XLS'!$B$5:$JN$5=CV$5)*('02.XLS'!$B$6:$JN$47))} -> 222595.95 | ... CZ43: {=SUMPRODUCT(('02.XLS'!$A$6:$A$47=$A43)*('02.XLS'!$B$5:$JN$5=CZ$5)*('02.XLS'!$B$6:$JN$47))} -> 256230.9 | DA43: =SUM(CO43:CZ43) -> 2732137.6 | DB43: {=SUMPRODUCT(('02.XLS'!$A$6:$A$47=$A43)*('02.XLS'!$B$5:$JN$5=DB$5)*('02.XLS'!$B$6:$JN$47))} -> 229427.45 | DC43: {=SUMPRODUCT(('02.XLS'!$A$6:$A$47=$A43)*('02.XLS'!$B$5:$JN$5=DC$5)*('02.XLS'!$B$6:$JN$47))} -> 245138.5 | DD43: {=SUMPRODUCT(('02.XLS'!$A$6:$A$47=$A43)*('02.XLS'!$B$5:$JN$5=DD$5)*('02.XLS'!$B$6:$JN$47))} -> 245069.4 | DE43: {=SUMPRODUCT(('02.XLS'!$A$6:$A$47=$A43)*('02.XLS'!$B$5:$JN$5=DE$5)*('02.XLS'!$B$6:$JN$47))} -> 237327.15 | DF43: {=SUMPRODUCT(('02.XLS'!$A$6:$A$47=$A43)*('02.XLS'!$B$5:$JN$5=DF$5)*('02.XLS'!$B$6:$JN$47))} -> 232311 | DG43: {=SUMPRODUCT(('02.XLS'!$A$6:$A$47=$A43)*('02.XLS'!$B$5:$JN$5=DG$5)*('02.XLS'!$B$6:$JN$47))} -> 235419 | DH43: {=SUMPRODUCT(('02.XLS'!$A$6:$A$47=$A43)*('02.XLS'!$B$5:$JN$5=DH$5)*('02.XLS'!$B$6:$JN$47))} -> 236845 | DI43: {=SUMPRODUCT(('02.XLS'!$A$6:$A$47=$A43)*('02.XLS'!$B$5:$JN$5=DI$5)*('02.XLS'!$B$6:$JN$47))} -> 228276 | ... DM43: {=SUMPRODUCT(('02.XLS'!$A$6:$A$47=$A43)*('02.XLS'!$B$5:$JN$5=DM$5)*('02.XLS'!$B$6:$JN$47))} -> 246955 | DN43: =SUM(DB43:DM43) -> 2840317.5 | DO43: {=SUMPRODUCT(('02.XLS'!$A$6:$A$47=$A43)*('02.XLS'!$B$5:$JN$5=DO$5)*('02.XLS'!$B$6:$JN$47))} -> 246857 | DP43: {=SUMPRODUCT(('02.XLS'!$A$6:$A$47=$A43)*('02.XLS'!$B$5:$JN$5=DP$5)*('02.XLS'!$B$6:$JN$47))} -> 257263.2 | DQ43: {=SUMPRODUCT(('02.XLS'!$A$6:$A$47=$A43)*('02.XLS'!$B$5:$JN$5=DQ$5)*('02.XLS'!$B$6:$JN$47))} -> 262094.4 | DR43: {=SUMPRODUCT(('02.XLS'!$A$6:$A$47=$A43)*('02.XLS'!$B$5:$JN$5=DR$5)*('02.XLS'!$B$6:$JN$47))} -> 252199.4 | DS43: {=SUMPRODUCT(('02.XLS'!$A$6:$A$47=$A43)*('02.XLS'!$B$5:$JN$5=DS$5)*('02.XLS'!$B$6:$JN$47))} -> 240387.1 | DT43: {=SUMPRODUCT(('02.XLS'!$A$6:$A$47=$A43)*('02.XLS'!$B$5:$JN$5=DT$5)*('02.XLS'!$B$6:$JN$47))} -> 256941.2 | DU43: {=SUMPRODUCT(('02.XLS'!$A$6:$A$47=$A43)*('02.XLS'!$B$5:$JN$5=DU$5)*('02.XLS'!$B$6:$JN$47))} -> 246991.8 | DV43: {=SUMPRODUCT(('02.XLS'!$A$6:$A$47=$A43)*('02.XLS'!$B$5:$JN$5=DV$5)*('02.XLS'!$B$6:$JN$47))} -> 256173.4 | ... DZ43: {=SUMPRODUCT(('02.XLS'!$A$6:$A$47=$A43)*('02.XLS'!$B$5:$JN$5=DZ$5)*('02.XLS'!$B$6:$JN$47))} -> 264717.75 | EA43: =SUM(DO43:DZ43) -> 3063107.9 | EB43: {=SUMPRODUCT(('02.XLS'!$A$6:$A$47=$A43)*('02.XLS'!$B$5:$JN$5=EB$5)*('02.XLS'!$B$6:$JN$47))} -> 257381 | EC43: {=SUMPRODUCT(('02.XLS'!$A$6:$A$47=$A43)*('02.XLS'!$B$5:$JN$5=EC$5)*('02.XLS'!$B$6:$JN$47))} -> 282125 | ED43: {=SUMPRODUCT(('02.XLS'!$A$6:$A$47=$A43)*('02.XLS'!$B$5:$JN$5=ED$5)*('02.XLS'!$B$6:$JN$47))} -> 255339 | EE43: {=SUMPRODUCT(('02.XLS'!$A$6:$A$47=$A43)*('02.XLS'!$B$5:$JN$5=EE$5)*('02.XLS'!$B$6:$JN$47))} -> 256247.66 | EF43: {=SUMPRODUCT(('02.XLS'!$A$6:$A$47=$A43)*('02.XLS'!$B$5:$JN$5=EF$5)*('02.XLS'!$B$6:$JN$47))} -> 237373 | EG43: {=SUMPRODUCT(('02.XLS'!$A$6:$A$47=$A43)*('02.XLS'!$B$5:$JN$5=EG$5)*('02.XLS'!$B$6:$JN$47))} -> 249010 | EH43: {=SUMPRODUCT(('02.XLS'!$A$6:$A$47=$A43)*('02.XLS'!$B$5:$JN$5=EH$5)*('02.XLS'!$B$6:$JN$47))} -> 273030 | EI43: {=SUMPRODUCT(('02.XLS'!$A$6:$A$47=$A43)*('02.XLS'!$B$5:$JN$5=EI$5)*('02.XLS'!$B$6:$JN$47))} -> 251112 | ... EM43: {=SUMPRODUCT(('02.XLS'!$A$6:$A$47=$A43)*('02.XLS'!$B$5:$JN$5=EM$5)*('02.XLS'!$B$6:$JN$47))} -> 292994.7 | EN43: =SUM(EB43:EM43) -> 3171068.4 | EO43: {=SUMPRODUCT(('02.XLS'!$A$6:$A$47=$A43)*('02.XLS'!$B$5:$JN$5=EO$5)*('02.XLS'!$B$6:$JN$47))} -> 291689.2 | EP43: {=SUMPRODUCT(('02.XLS'!$A$6:$A$47=$A43)*('02.XLS'!$B$5:$JN$5=EP$5)*('02.XLS'!$B$6:$JN$47))} -> 306338.2 | EQ43: {=SUMPRODUCT(('02.XLS'!$A$6:$A$47=$A43)*('02.XLS'!$B$5:$JN$5=EQ$5)*('02.XLS'!$B$6:$JN$47))} -> 301407 | ER43: {=SUMPRODUCT(('02.XLS'!$A$6:$A$47=$A43)*('02.XLS'!$B$5:$JN$5=ER$5)*('02.XLS'!$B$6:$JN$47))} -> 295679 | ES43: {=SUMPRODUCT(('02.XLS'!$A$6:$A$47=$A43)*('02.XLS'!$B$5:$JN$5=ES$5)*('02.XLS'!$B$6:$JN$47))} -> 283509 | ET43: {=SUMPRODUCT(('02.XLS'!$A$6:$A$47=$A43)*('02.XLS'!$B$5:$JN$5=ET$5)*('02.XLS'!$B$6:$JN$47))} -> 301326 | EU43: {=SUMPRODUCT(('02.XLS'!$A$6:$A$47=$A43)*('02.XLS'!$B$5:$JN$5=EU$5)*('02.XLS'!$B$6:$JN$47))} -> 302450 | EV43: {=SUMPRODUCT(('02.XLS'!$A$6:$A$47=$A43)*('02.XLS'!$B$5:$JN$5=EV$5)*('02.XLS'!$B$6:$JN$47))} -> 299239 | ... EZ43: {=SUMPRODUCT(('02.XLS'!$A$6:$A$47=$A43)*('02.XLS'!$B$5:$JN$5=EZ$5)*('02.XLS'!$B$6:$JN$47))} -> 331684.2 | FA43: =SUM(EO43:EZ43) -> 3660220.6 | FB43: {=SUMPRODUCT(('02.XLS'!$A$6:$A$47=$A43)*('02.XLS'!$B$5:$JN$5=FB$5)*('02.XLS'!$B$6:$JN$47))} -> 311573 | FC43: {=SUMPRODUCT(('02.XLS'!$A$6:$A$47=$A43)*('02.XLS'!$B$5:$JN$5=FC$5)*('02.XLS'!$B$6:$JN$47))} -> 311607 | FD43: {=SUMPRODUCT(('02.XLS'!$A$6:$A$47=$A43)*('02.XLS'!$B$5:$JN$5=FD$5)*('02.XLS'!$B$6:$JN$47))} -> 307300 | FE43: {=SUMPRODUCT(('02.XLS'!$A$6:$A$47=$A43)*('02.XLS'!$B$5:$JN$5=FE$5)*('02.XLS'!$B$6:$JN$47))} -> 292965 | FF43: {=SUMPRODUCT(('02.XLS'!$A$6:$A$47=$A43)*('02.XLS'!$B$5:$JN$5=FF$5)*('02.XLS'!$B$6:$JN$47))} -> 323385 | FG43: {=SUMPRODUCT(('02.XLS'!$A$6:$A$47=$A43)*('02.XLS'!$B$5:$JN$5=FG$5)*('02.XLS'!$B$6:$JN$47))} -> 295070 | FH43: {=SUMPRODUCT(('02.XLS'!$A$6:$A$47=$A43)*('02.XLS'!$B$5:$JN$5=FH$5)*('02.XLS'!$B$6:$JN$47))} -> 298825 | FI43: {=SUMPRODUCT(('02.XLS'!$A$6:$A$47=$A43)*('02.XLS'!$B$5:$JN$5=FI$5)*('02.XLS'!$B$6:$JN$47))} -> 298909 | ... FM43: {=SUMPRODUCT(('02.XLS'!$A$6:$A$47=$A43)*('02.XLS'!$B$5:$JN$5=FM$5)*('02.XLS'!$B$6:$JN$47))} -> 317286 | FN43: =SUM(FB43:FM43) -> 3670949 | FO43: {=SUMPRODUCT(('02.XLS'!$A$6:$A$47=$A43)*('02.XLS'!$B$5:$JN$5=FO$5)*('02.XLS'!$B$6:$JN$47))} -> 293338 | FP43: {=SUMPRODUCT(('02.XLS'!$A$6:$A$47=$A43)*('02.XLS'!$B$5:$JN$5=FP$5)*('02.XLS'!$B$6:$JN$47))} -> 295653 | FQ43: {=SUMPRODUCT(('02.XLS'!$A$6:$A$47=$A43)*('02.XLS'!$B$5:$JN$5=FQ$5)*('02.XLS'!$B$6:$JN$47))} -> 287244 | FR43: {=SUMPRODUCT(('02.XLS'!$A$6:$A$47=$A43)*('02.XLS'!$B$5:$JN$5=FR$5)*('02.XLS'!$B$6:$JN$47))} -> 274431 | FS43: {=SUMPRODUCT(('02.XLS'!$A$6:$A$47=$A43)*('02.XLS'!$B$5:$JN$5=FS$5)*('02.XLS'!$B$6:$JN$47))} -> 277478 | FT43: {=SUMPRODUCT(('02.XLS'!$A$6:$A$47=$A43)*('02.XLS'!$B$5:$JN$5=FT$5)*('02.XLS'!$B$6:$JN$47))} -> 270675 | FU43: {=SUMPRODUCT(('02.XLS'!$A$6:$A$47=$A43)*('02.XLS'!$B$5:$JN$5=FU$5)*('02.XLS'!$B$6:$JN$47))} -> 266596 | FV43: {=SUMPRODUCT(('02.XLS'!$A$6:$A$47=$A43)*('02.XLS'!$B$5:$JN$5=FV$5)*('02.XLS'!$B$6:$JN$47))} -> 265885 | ... FZ43: {=SUMPRODUCT(('02.XLS'!$A$6:$A$47=$A43)*('02.XLS'!$B$5:$JN$5=FZ$5)*('02.XLS'!$B$6:$JN$47))} -> 292667 | GA43: =SUM(FO43:FZ43) -> 3327299 | GB43: {=SUMPRODUCT(('02.XLS'!$A$6:$A$47=$A43)*('02.XLS'!$B$5:$JN$5=GB$5)*('02.XLS'!$B$6:$JN$47))} -> 318949.8 | GC43: {=SUMPRODUCT(('02.XLS'!$A$6:$A$47=$A43)*('02.XLS'!$B$5:$JN$5=GC$5)*('02.XLS'!$B$6:$JN$47))} -> 322681.45 | GD43: {=SUMPRODUCT(('02.XLS'!$A$6:$A$47=$A43)*('02.XLS'!$B$5:$JN$5=GD$5)*('02.XLS'!$B$6:$JN$47))} -> 311412.9 | GE43: {=SUMPRODUCT(('02.XLS'!$A$6:$A$47=$A43)*('02.XLS'!$B$5:$JN$5=GE$5)*('02.XLS'!$B$6:$JN$47))} -> 301645.45 | GF43: {=SUMPRODUCT(('02.XLS'!$A$6:$A$47=$A43)*('02.XLS'!$B$5:$JN$5=GF$5)*('02.XLS'!$B$6:$JN$47))} -> 316267.6 | GG43: {=SUMPRODUCT(('02.XLS'!$A$6:$A$47=$A43)*('02.XLS'!$B$5:$JN$5=GG$5)*('02.XLS'!$B$6:$JN$47))} -> 303205.45 | GH43: {=SUMPRODUCT(('02.XLS'!$A$6:$A$47=$A43)*('02.XLS'!$B$5:$JN$5=GH$5)*('02.XLS'!$B$6:$JN$47))} -> 298059.4 | GI43: {=SUMPRODUCT(('02.XLS'!$A$6:$A$47=$A43)*('02.XLS'!$B$5:$JN$5=GI$5)*('02.XLS'!$B$6:$JN$47))} -> 296715.75 | ... GM43: {=SUMPRODUCT(('02.XLS'!$A$6:$A$47=$A43)*('02.XLS'!$B$5:$JN$5=GM$5)*('02.XLS'!$B$6:$JN$47))} -> 326512.65 | GN43: =SUM(GB43:GM43) -> 3707390.4 | GO43: {=SUMPRODUCT(('02.XLS'!$A$6:$A$47=$A43)*('02.XLS'!$B$5:$JN$5=GO$5)*('02.XLS'!$B$6:$JN$47))} -> 318717.8 | GP43: {=SUMPRODUCT(('02.XLS'!$A$6:$A$47=$A43)*('02.XLS'!$B$5:$JN$5=GP$5)*('02.XLS'!$B$6:$JN$47))} -> 323878.1 | GQ43: {=SUMPRODUCT(('02.XLS'!$A$6:$A$47=$A43)*('02.XLS'!$B$5:$JN$5=GQ$5)*('02.XLS'!$B$6:$JN$47))} -> 317696.9 | GR43: {=SUMPRODUCT(('02.XLS'!$A$6:$A$47=$A43)*('02.XLS'!$B$5:$JN$5=GR$5)*('02.XLS'!$B$6:$JN$47))} -> 299467.5 | GS43: {=SUMPRODUCT(('02.XLS'!$A$6:$A$47=$A43)*('02.XLS'!$B$5:$JN$5=GS$5)*('02.XLS'!$B$6:$JN$47))} -> 310438.5 | GT43: {=SUMPRODUCT(('02.XLS'!$A$6:$A$47=$A43)*('02.XLS'!$B$5:$JN$5=GT$5)*('02.XLS'!$B$6:$JN$47))} -> 297502.1 | GU43: {=SUMPRODUCT(('02.XLS'!$A$6:$A$47=$A43)*('02.XLS'!$B$5:$JN$5=GU$5)*('02.XLS'!$B$6:$JN$47))} -> 301907.1 | GV43: {=SUMPRODUCT(('02.XLS'!$A$6:$A$47=$A43)*('02.XLS'!$B$5:$JN$5=GV$5)*('02.XLS'!$B$6:$JN$47))} -> 315457.1 | ... GZ43: {=SUMPRODUCT(('02.XLS'!$A$6:$A$47=$A43)*('02.XLS'!$B$5:$JN$5=GZ$5)*('02.XLS'!$B$6:$JN$47))} -> 324379.91 | HA43: =SUM(GO43:GZ43) -> 3725871.2 | HB43: {=SUMPRODUCT(('02.XLS'!$A$6:$A$47=$A43)*('02.XLS'!$B$5:$JN$5=HB$5)*('02.XLS'!$B$6:$JN$47))} -> 322340.55 | HC43: {=SUMPRODUCT(('02.XLS'!$A$6:$A$47=$A43)*('02.XLS'!$B$5:$JN$5=HC$5)*('02.XLS'!$B$6:$JN$47))} -> 317970 | HD43: {=SUMPRODUCT(('02.XLS'!$A$6:$A$47=$A43)*('02.XLS'!$B$5:$JN$5=HD$5)*('02.XLS'!$B$6:$JN$47))} -> 313114.5 | HE43: {=SUMPRODUCT(('02.XLS'!$A$6:$A$47=$A43)*('02.XLS'!$B$5:$JN$5=HE$5)*('02.XLS'!$B$6:$JN$47))} -> 301551.3 | HF43: {=SUMPRODUCT(('02.XLS'!$A$6:$A$47=$A43)*('02.XLS'!$B$5:$JN$5=HF$5)*('02.XLS'!$B$6:$JN$47))} -> 305589.7 | HG43: {=SUMPRODUCT(('02.XLS'!$A$6:$A$47=$A43)*('02.XLS'!$B$5:$JN$5=HG$5)*('02.XLS'!$B$6:$JN$47))} -> 286621.6 | HH43: {=SUMPRODUCT(('02.XLS'!$A$6:$A$47=$A43)*('02.XLS'!$B$5:$JN$5=HH$5)*('02.XLS'!$B$6:$JN$47))} -> 288386 | HI43: {=SUMPRODUCT(('02.XLS'!$A$6:$A$47=$A43)*('02.XLS'!$B$5:$JN$5=HI$5)*('02.XLS'!$B$6:$JN$47))} -> 286230.3 | ... HM43: {=SUMPRODUCT(('02.XLS'!$A$6:$A$47=$A43)*('02.XLS'!$B$5:$JN$5=HM$5)*('02.XLS'!$B$6:$JN$47))} -> 316021.65 | HN43: =SUM(HB43:HM43) -> 3608973.1 | HO43: {=SUMPRODUCT(('02.XLS'!$A$6:$A$47=$A43)*('02.XLS'!$B$5:$JN$5=HO$5)*('02.XLS'!$B$6:$JN$47))} -> 317331.6 | HP43: {=SUMPRODUCT(('02.XLS'!$A$6:$A$47=$A43)*('02.XLS'!$B$5:$JN$5=HP$5)*('02.XLS'!$B$6:$JN$47))} -> 329146.9 | HQ43: {=SUMPRODUCT(('02.XLS'!$A$6:$A$47=$A43)*('02.XLS'!$B$5:$JN$5=HQ$5)*('02.XLS'!$B$6:$JN$47))} -> 324198.5 | HR43: {=SUMPRODUCT(('02.XLS'!$A$6:$A$47=$A43)*('02.XLS'!$B$5:$JN$5=HR$5)*('02.XLS'!$B$6:$JN$47))} -> 319716.2 | HS43: {=SUMPRODUCT(('02.XLS'!$A$6:$A$47=$A43)*('02.XLS'!$B$5:$JN$5=HS$5)*('02.XLS'!$B$6:$JN$47))} -> 325640.7 | HT43: {=SUMPRODUCT(('02.XLS'!$A$6:$A$47=$A43)*('02.XLS'!$B$5:$JN$5=HT$5)*('02.XLS'!$B$6:$JN$47))} -> 303329.7 | HU43: {=SUMPRODUCT(('02.XLS'!$A$6:$A$47=$A43)*('02.XLS'!$B$5:$JN$5=HU$5)*('02.XLS'!$B$6:$JN$47))} -> 310062.3 | HV43: {=SUMPRODUCT(('02.XLS'!$A$6:$A$47=$A43)*('02.XLS'!$B$5:$JN$5=HV$5)*('02.XLS'!$B$6:$JN$47))} -> 302830 | ... HZ43: {=SUMPRODUCT(('02.XLS'!$A$6:$A$47=$A43)*('02.XLS'!$B$5:$JN$5=HZ$5)*('02.XLS'!$B$6:$JN$47))} -> 348633.05 | IA43: =SUM(HO43:HZ43) -> 3789856.4 | IB43: {=SUMPRODUCT(('02.XLS'!$A$6:$A$47=$A43)*('02.XLS'!$B$5:$JN$5=IB$5)*('02.XLS'!$B$6:$JN$47))} -> 343114 | IC43: {=SUMPRODUCT(('02.XLS'!$A$6:$A$47=$A43)*('02.XLS'!$B$5:$JN$5=IC$5)*('02.XLS'!$B$6:$JN$47))} -> 357948.5 | ID43: {=SUMPRODUCT(('02.XLS'!$A$6:$A$47=$A43)*('02.XLS'!$B$5:$JN$5=ID$5)*('02.XLS'!$B$6:$JN$47))} -> 331288 | IE43: {=SUMPRODUCT(('02.XLS'!$A$6:$A$47=$A43)*('02.XLS'!$B$5:$JN$5=IE$5)*('02.XLS'!$B$6:$JN$47))} -> 343036.2 | IF43: {=SUMPRODUCT(('02.XLS'!$A$6:$A$47=$A43)*('02.XLS'!$B$5:$JN$5=IF$5)*('02.XLS'!$B$6:$JN$47))} -> 328617.35 | IG43: {=SUMPRODUCT(('02.XLS'!$A$6:$A$47=$A43)*('02.XLS'!$B$5:$JN$5=IG$5)*('02.XLS'!$B$6:$JN$47))} -> 299623.05 | IH43: {=SUMPRODUCT(('02.XLS'!$A$6:$A$47=$A43)*('02.XLS'!$B$5:$JN$5=IH$5)*('02.XLS'!$B$6:$JN$47))} -> 283635.3 | II43: {=SUMPRODUCT(('02.XLS'!$A$6:$A$47=$A43)*('02.XLS'!$B$5:$JN$5=II$5)*('02.XLS'!$B$6:$JN$47))} -> 278943.1 | ... IM43: {=SUMPRODUCT(('02.XLS'!$A$6:$A$47=$A43)*('02.XLS'!$B$5:$JN$5=IM$5)*('02.XLS'!$B$6:$JN$47))} -> 357639.95 | IN43: =SUM(IB43:IM43) -> 3823330.5 | IO43: {=SUMPRODUCT(('02.XLS'!$A$6:$A$47=$A43)*('02.XLS'!$B$5:$JN$5=IO$5)*('02.XLS'!$B$6:$JN$47))} -> 344775 | IP43: {=SUMPRODUCT(('02.XLS'!$A$6:$A$47=$A43)*('02.XLS'!$B$5:$JN$5=IP$5)*('02.XLS'!$B$6:$JN$47))} -> 354291.1 | IQ43: {=SUMPRODUCT(('02.XLS'!$A$6:$A$47=$A43)*('02.XLS'!$B$5:$JN$5=IQ$5)*('02.XLS'!$B$6:$JN$47))} -> 359439 | IR43: {=SUMPRODUCT(('02.XLS'!$A$6:$A$47=$A43)*('02.XLS'!$B$5:$JN$5=IR$5)*('02.XLS'!$B$6:$JN$47))} -> 358409.3 | IS43: {=SUMPRODUCT(('02.XLS'!$A$6:$A$47=$A43)*('02.XLS'!$B$5:$JN$5=IS$5)*('02.XLS'!$B$6:$JN$47))} -> 360546.7 | IT43: {=SUMPRODUCT(('02.XLS'!$A$6:$A$47=$A43)*('02.XLS'!$B$5:$JN$5=IT$5)*('02.XLS'!$B$6:$JN$47))} -> 324045.9 | IU43: {=SUMPRODUCT(('02.XLS'!$A$6:$A$47=$A43)*('02.XLS'!$B$5:$JN$5=IU$5)*('02.XLS'!$B$6:$JN$47))} -> 311172.3 | IV43: {=SUMPRODUCT(('02.XLS'!$A$6:$A$47=$A43)*('02.XLS'!$B$5:$JN$5=IV$5)*('02.XLS'!$B$6:$JN$47))} -> 302200.8 | ... IZ43: {=SUMPRODUCT(('02.XLS'!$A$6:$A$47=$A43)*('02.XLS'!$B$5:$JN$5=IZ$5)*('02.XLS'!$B$6:$JN$47))} -> 364052.55 | JA43: =SUM(IO43:IZ43) -> 4069769.6 | JB43: {=SUMPRODUCT(('02.XLS'!$A$6:$A$47=$A43)*('02.XLS'!$B$5:$JN$5=JB$5)*('02.XLS'!$B$6:$JN$47))} -> 312288 | JC43: {=SUMPRODUCT(('02.XLS'!$A$6:$A$47=$A43)*('02.XLS'!$B$5:$JN$5=JC$5)*('02.XLS'!$B$6:$JN$47))} -> 339471.5 | JD43: {=SUMPRODUCT(('02.XLS'!$A$6:$A$47=$A43)*('02.XLS'!$B$5:$JN$5=JD$5)*('02.XLS'!$B$6:$JN$47))} -> 0 | JE43: {=SUMPRODUCT(('02.XLS'!$A$6:$A$47=$A43)*('02.XLS'!$B$5:$JN$5=JE$5)*('02.XLS'!$B$6:$JN$47))} -> 0 | JF43: {=SUMPRODUCT(('02.XLS'!$A$6:$A$47=$A43)*('02.XLS'!$B$5:$JN$5=JF$5)*('02.XLS'!$B$6:$JN$47))} -> 0 | JG43: {=SUMPRODUCT(('02.XLS'!$A$6:$A$47=$A43)*('02.XLS'!$B$5:$JN$5=JG$5)*('02.XLS'!$B$6:$JN$47))} -> 0 | JH43: {=SUMPRODUCT(('02.XLS'!$A$6:$A$47=$A43)*('02.XLS'!$B$5:$JN$5=JH$5)*('02.XLS'!$B$6:$JN$47))} -> 0 | JI43: {=SUMPRODUCT(('02.XLS'!$A$6:$A$47=$A43)*('02.XLS'!$B$5:$JN$5=JI$5)*('02.XLS'!$B$6:$JN$47))} -> 0 | ... JM43: {=SUMPRODUCT(('02.XLS'!$A$6:$A$47=$A43)*('02.XLS'!$B$5:$JN$5=JM$5)*('02.XLS'!$B$6:$JN$47))} -> 0 | JN43: =SUM(JB43:JM43) -> 651759.5 | JP43: =IFERROR((( _xlfn.XLOOKUP((DATE(YEAR($JP$5),MONTH($JP$5),1)),SMN.AGRO.DATE,$B43:$JN43) / _xlfn.XLOOKUP((DATE(YEAR($JP$5)-1,MONTH($JP$5),1)),SMN.AGRO.DATE,$B43:$JN43) )-1)*100,"") -> 1.7930323 | JQ43: =IFERROR(((JS43/JR43)-1)*100,"") -> 6.4456664 | JR43: =SUMIFS($B43:$JN43,SMN.AGRO.DATE,">="&DATE(YEAR($JP$5)-1,1,1),SMN.AGRO.DATE,"<="&DATE(YEAR($JP$5)-1,MONTH($JP$5),1)) -> 3823330.5 | JS43: =SUMIFS($B43:$JN43,SMN.AGRO.DATE,">="&DATE(YEAR($JP$5),1,1),SMN.AGRO.DATE,"<="&$JP$5) -> 4069769.6
A44: Stevia | B44: {=SUMPRODUCT(('02.XLS'!$A$6:$A$47=$A44)*('02.XLS'!$B$5:$JN$5=B$5)*('02.XLS'!$B$6:$JN$47))} -> 0 | C44: {=SUMPRODUCT(('02.XLS'!$A$6:$A$47=$A44)*('02.XLS'!$B$5:$JN$5=C$5)*('02.XLS'!$B$6:$JN$47))} -> 0 | D44: {=SUMPRODUCT(('02.XLS'!$A$6:$A$47=$A44)*('02.XLS'!$B$5:$JN$5=D$5)*('02.XLS'!$B$6:$JN$47))} -> 0 | E44: {=SUMPRODUCT(('02.XLS'!$A$6:$A$47=$A44)*('02.XLS'!$B$5:$JN$5=E$5)*('02.XLS'!$B$6:$JN$47))} -> 0 | F44: {=SUMPRODUCT(('02.XLS'!$A$6:$A$47=$A44)*('02.XLS'!$B$5:$JN$5=F$5)*('02.XLS'!$B$6:$JN$47))} -> 0 | G44: {=SUMPRODUCT(('02.XLS'!$A$6:$A$47=$A44)*('02.XLS'!$B$5:$JN$5=G$5)*('02.XLS'!$B$6:$JN$47))} -> 0 | H44: {=SUMPRODUCT(('02.XLS'!$A$6:$A$47=$A44)*('02.XLS'!$B$5:$JN$5=H$5)*('02.XLS'!$B$6:$JN$47))} -> 0 | I44: {=SUMPRODUCT(('02.XLS'!$A$6:$A$47=$A44)*('02.XLS'!$B$5:$JN$5=I$5)*('02.XLS'!$B$6:$JN$47))} -> 0 | ... M44: {=SUMPRODUCT(('02.XLS'!$A$6:$A$47=$A44)*('02.XLS'!$B$5:$JN$5=M$5)*('02.XLS'!$B$6:$JN$47))} -> 0 | N44: =SUM(B44:M44) -> 0 | O44: {=SUMPRODUCT(('02.XLS'!$A$6:$A$47=$A44)*('02.XLS'!$B$5:$JN$5=O$5)*('02.XLS'!$B$6:$JN$47))} -> 0 | P44: {=SUMPRODUCT(('02.XLS'!$A$6:$A$47=$A44)*('02.XLS'!$B$5:$JN$5=P$5)*('02.XLS'!$B$6:$JN$47))} -> 0 | Q44: {=SUMPRODUCT(('02.XLS'!$A$6:$A$47=$A44)*('02.XLS'!$B$5:$JN$5=Q$5)*('02.XLS'!$B$6:$JN$47))} -> 0 | R44: {=SUMPRODUCT(('02.XLS'!$A$6:$A$47=$A44)*('02.XLS'!$B$5:$JN$5=R$5)*('02.XLS'!$B$6:$JN$47))} -> 0 | S44: {=SUMPRODUCT(('02.XLS'!$A$6:$A$47=$A44)*('02.XLS'!$B$5:$JN$5=S$5)*('02.XLS'!$B$6:$JN$47))} -> 0 | T44: {=SUMPRODUCT(('02.XLS'!$A$6:$A$47=$A44)*('02.XLS'!$B$5:$JN$5=T$5)*('02.XLS'!$B$6:$JN$47))} -> 0 | U44: {=SUMPRODUCT(('02.XLS'!$A$6:$A$47=$A44)*('02.XLS'!$B$5:$JN$5=U$5)*('02.XLS'!$B$6:$JN$47))} -> 0 | V44: {=SUMPRODUCT(('02.XLS'!$A$6:$A$47=$A44)*('02.XLS'!$B$5:$JN$5=V$5)*('02.XLS'!$B$6:$JN$47))} -> 0 | ... Z44: {=SUMPRODUCT(('02.XLS'!$A$6:$A$47=$A44)*('02.XLS'!$B$5:$JN$5=Z$5)*('02.XLS'!$B$6:$JN$47))} -> 0 | AA44: =SUM(O44:Z44) -> 0 | AB44: {=SUMPRODUCT(('02.XLS'!$A$6:$A$47=$A44)*('02.XLS'!$B$5:$JN$5=AB$5)*('02.XLS'!$B$6:$JN$47))} -> 0 | AC44: {=SUMPRODUCT(('02.XLS'!$A$6:$A$47=$A44)*('02.XLS'!$B$5:$JN$5=AC$5)*('02.XLS'!$B$6:$JN$47))} -> 0 | AD44: {=SUMPRODUCT(('02.XLS'!$A$6:$A$47=$A44)*('02.XLS'!$B$5:$JN$5=AD$5)*('02.XLS'!$B$6:$JN$47))} -> 0 | AE44: {=SUMPRODUCT(('02.XLS'!$A$6:$A$47=$A44)*('02.XLS'!$B$5:$JN$5=AE$5)*('02.XLS'!$B$6:$JN$47))} -> 0 | AF44: {=SUMPRODUCT(('02.XLS'!$A$6:$A$47=$A44)*('02.XLS'!$B$5:$JN$5=AF$5)*('02.XLS'!$B$6:$JN$47))} -> 0 | AG44: {=SUMPRODUCT(('02.XLS'!$A$6:$A$47=$A44)*('02.XLS'!$B$5:$JN$5=AG$5)*('02.XLS'!$B$6:$JN$47))} -> 0 | AH44: {=SUMPRODUCT(('02.XLS'!$A$6:$A$47=$A44)*('02.XLS'!$B$5:$JN$5=AH$5)*('02.XLS'!$B$6:$JN$47))} -> 0 | AI44: {=SUMPRODUCT(('02.XLS'!$A$6:$A$47=$A44)*('02.XLS'!$B$5:$JN$5=AI$5)*('02.XLS'!$B$6:$JN$47))} -> 0 | ... AM44: {=SUMPRODUCT(('02.XLS'!$A$6:$A$47=$A44)*('02.XLS'!$B$5:$JN$5=AM$5)*('02.XLS'!$B$6:$JN$47))} -> 0 | AN44: =SUM(AB44:AM44) -> 0 | AO44: {=SUMPRODUCT(('02.XLS'!$A$6:$A$47=$A44)*('02.XLS'!$B$5:$JN$5=AO$5)*('02.XLS'!$B$6:$JN$47))} -> 0 | AP44: {=SUMPRODUCT(('02.XLS'!$A$6:$A$47=$A44)*('02.XLS'!$B$5:$JN$5=AP$5)*('02.XLS'!$B$6:$JN$47))} -> 0 | AQ44: {=SUMPRODUCT(('02.XLS'!$A$6:$A$47=$A44)*('02.XLS'!$B$5:$JN$5=AQ$5)*('02.XLS'!$B$6:$JN$47))} -> 0 | AR44: {=SUMPRODUCT(('02.XLS'!$A$6:$A$47=$A44)*('02.XLS'!$B$5:$JN$5=AR$5)*('02.XLS'!$B$6:$JN$47))} -> 0 | AS44: {=SUMPRODUCT(('02.XLS'!$A$6:$A$47=$A44)*('02.XLS'!$B$5:$JN$5=AS$5)*('02.XLS'!$B$6:$JN$47))} -> 0 | AT44: {=SUMPRODUCT(('02.XLS'!$A$6:$A$47=$A44)*('02.XLS'!$B$5:$JN$5=AT$5)*('02.XLS'!$B$6:$JN$47))} -> 0 | AU44: {=SUMPRODUCT(('02.XLS'!$A$6:$A$47=$A44)*('02.XLS'!$B$5:$JN$5=AU$5)*('02.XLS'!$B$6:$JN$47))} -> 0 | AV44: {=SUMPRODUCT(('02.XLS'!$A$6:$A$47=$A44)*('02.XLS'!$B$5:$JN$5=AV$5)*('02.XLS'!$B$6:$JN$47))} -> 0 | ... AZ44: {=SUMPRODUCT(('02.XLS'!$A$6:$A$47=$A44)*('02.XLS'!$B$5:$JN$5=AZ$5)*('02.XLS'!$B$6:$JN$47))} -> 0 | BA44: =SUM(AO44:AZ44) -> 0 | BB44: {=SUMPRODUCT(('02.XLS'!$A$6:$A$47=$A44)*('02.XLS'!$B$5:$JN$5=BB$5)*('02.XLS'!$B$6:$JN$47))} -> 0 | BC44: {=SUMPRODUCT(('02.XLS'!$A$6:$A$47=$A44)*('02.XLS'!$B$5:$JN$5=BC$5)*('02.XLS'!$B$6:$JN$47))} -> 0 | BD44: {=SUMPRODUCT(('02.XLS'!$A$6:$A$47=$A44)*('02.XLS'!$B$5:$JN$5=BD$5)*('02.XLS'!$B$6:$JN$47))} -> 0 | BE44: {=SUMPRODUCT(('02.XLS'!$A$6:$A$47=$A44)*('02.XLS'!$B$5:$JN$5=BE$5)*('02.XLS'!$B$6:$JN$47))} -> 0 | BF44: {=SUMPRODUCT(('02.XLS'!$A$6:$A$47=$A44)*('02.XLS'!$B$5:$JN$5=BF$5)*('02.XLS'!$B$6:$JN$47))} -> 0 | BG44: {=SUMPRODUCT(('02.XLS'!$A$6:$A$47=$A44)*('02.XLS'!$B$5:$JN$5=BG$5)*('02.XLS'!$B$6:$JN$47))} -> 0 | BH44: {=SUMPRODUCT(('02.XLS'!$A$6:$A$47=$A44)*('02.XLS'!$B$5:$JN$5=BH$5)*('02.XLS'!$B$6:$JN$47))} -> 0 | BI44: {=SUMPRODUCT(('02.XLS'!$A$6:$A$47=$A44)*('02.XLS'!$B$5:$JN$5=BI$5)*('02.XLS'!$B$6:$JN$47))} -> 0 | ... BM44: {=SUMPRODUCT(('02.XLS'!$A$6:$A$47=$A44)*('02.XLS'!$B$5:$JN$5=BM$5)*('02.XLS'!$B$6:$JN$47))} -> 0 | BN44: =SUM(BB44:BM44) -> 0 | BO44: {=SUMPRODUCT(('02.XLS'!$A$6:$A$47=$A44)*('02.XLS'!$B$5:$JN$5=BO$5)*('02.XLS'!$B$6:$JN$47))} -> 0 | BP44: {=SUMPRODUCT(('02.XLS'!$A$6:$A$47=$A44)*('02.XLS'!$B$5:$JN$5=BP$5)*('02.XLS'!$B$6:$JN$47))} -> 0 | BQ44: {=SUMPRODUCT(('02.XLS'!$A$6:$A$47=$A44)*('02.XLS'!$B$5:$JN$5=BQ$5)*('02.XLS'!$B$6:$JN$47))} -> 0 | BR44: {=SUMPRODUCT(('02.XLS'!$A$6:$A$47=$A44)*('02.XLS'!$B$5:$JN$5=BR$5)*('02.XLS'!$B$6:$JN$47))} -> 0 | BS44: {=SUMPRODUCT(('02.XLS'!$A$6:$A$47=$A44)*('02.XLS'!$B$5:$JN$5=BS$5)*('02.XLS'!$B$6:$JN$47))} -> 0 | BT44: {=SUMPRODUCT(('02.XLS'!$A$6:$A$47=$A44)*('02.XLS'!$B$5:$JN$5=BT$5)*('02.XLS'!$B$6:$JN$47))} -> 0 | BU44: {=SUMPRODUCT(('02.XLS'!$A$6:$A$47=$A44)*('02.XLS'!$B$5:$JN$5=BU$5)*('02.XLS'!$B$6:$JN$47))} -> 0 | BV44: {=SUMPRODUCT(('02.XLS'!$A$6:$A$47=$A44)*('02.XLS'!$B$5:$JN$5=BV$5)*('02.XLS'!$B$6:$JN$47))} -> 0 | ... BZ44: {=SUMPRODUCT(('02.XLS'!$A$6:$A$47=$A44)*('02.XLS'!$B$5:$JN$5=BZ$5)*('02.XLS'!$B$6:$JN$47))} -> 0 | CA44: =SUM(BO44:BZ44) -> 0 | CB44: {=SUMPRODUCT(('02.XLS'!$A$6:$A$47=$A44)*('02.XLS'!$B$5:$JN$5=CB$5)*('02.XLS'!$B$6:$JN$47))} -> 0 | CC44: {=SUMPRODUCT(('02.XLS'!$A$6:$A$47=$A44)*('02.XLS'!$B$5:$JN$5=CC$5)*('02.XLS'!$B$6:$JN$47))} -> 0 | CD44: {=SUMPRODUCT(('02.XLS'!$A$6:$A$47=$A44)*('02.XLS'!$B$5:$JN$5=CD$5)*('02.XLS'!$B$6:$JN$47))} -> 0 | CE44: {=SUMPRODUCT(('02.XLS'!$A$6:$A$47=$A44)*('02.XLS'!$B$5:$JN$5=CE$5)*('02.XLS'!$B$6:$JN$47))} -> 27 | CF44: {=SUMPRODUCT(('02.XLS'!$A$6:$A$47=$A44)*('02.XLS'!$B$5:$JN$5=CF$5)*('02.XLS'!$B$6:$JN$47))} -> 38 | CG44: {=SUMPRODUCT(('02.XLS'!$A$6:$A$47=$A44)*('02.XLS'!$B$5:$JN$5=CG$5)*('02.XLS'!$B$6:$JN$47))} -> 45 | CH44: {=SUMPRODUCT(('02.XLS'!$A$6:$A$47=$A44)*('02.XLS'!$B$5:$JN$5=CH$5)*('02.XLS'!$B$6:$JN$47))} -> 48 | CI44: {=SUMPRODUCT(('02.XLS'!$A$6:$A$47=$A44)*('02.XLS'!$B$5:$JN$5=CI$5)*('02.XLS'!$B$6:$JN$47))} -> 25 | ... CM44: {=SUMPRODUCT(('02.XLS'!$A$6:$A$47=$A44)*('02.XLS'!$B$5:$JN$5=CM$5)*('02.XLS'!$B$6:$JN$47))} -> 80 | CN44: =SUM(CB44:CM44) -> 385 | CO44: {=SUMPRODUCT(('02.XLS'!$A$6:$A$47=$A44)*('02.XLS'!$B$5:$JN$5=CO$5)*('02.XLS'!$B$6:$JN$47))} -> 10 | CP44: {=SUMPRODUCT(('02.XLS'!$A$6:$A$47=$A44)*('02.XLS'!$B$5:$JN$5=CP$5)*('02.XLS'!$B$6:$JN$47))} -> 12 | CQ44: {=SUMPRODUCT(('02.XLS'!$A$6:$A$47=$A44)*('02.XLS'!$B$5:$JN$5=CQ$5)*('02.XLS'!$B$6:$JN$47))} -> 10 | CR44: {=SUMPRODUCT(('02.XLS'!$A$6:$A$47=$A44)*('02.XLS'!$B$5:$JN$5=CR$5)*('02.XLS'!$B$6:$JN$47))} -> 20 | CS44: {=SUMPRODUCT(('02.XLS'!$A$6:$A$47=$A44)*('02.XLS'!$B$5:$JN$5=CS$5)*('02.XLS'!$B$6:$JN$47))} -> 18 | CT44: {=SUMPRODUCT(('02.XLS'!$A$6:$A$47=$A44)*('02.XLS'!$B$5:$JN$5=CT$5)*('02.XLS'!$B$6:$JN$47))} -> 25 | CU44: {=SUMPRODUCT(('02.XLS'!$A$6:$A$47=$A44)*('02.XLS'!$B$5:$JN$5=CU$5)*('02.XLS'!$B$6:$JN$47))} -> 80 | CV44: {=SUMPRODUCT(('02.XLS'!$A$6:$A$47=$A44)*('02.XLS'!$B$5:$JN$5=CV$5)*('02.XLS'!$B$6:$JN$47))} -> 88 | ... CZ44: {=SUMPRODUCT(('02.XLS'!$A$6:$A$47=$A44)*('02.XLS'!$B$5:$JN$5=CZ$5)*('02.XLS'!$B$6:$JN$47))} -> 185 | DA44: =SUM(CO44:CZ44) -> 943 | DB44: {=SUMPRODUCT(('02.XLS'!$A$6:$A$47=$A44)*('02.XLS'!$B$5:$JN$5=DB$5)*('02.XLS'!$B$6:$JN$47))} -> 0 | DC44: {=SUMPRODUCT(('02.XLS'!$A$6:$A$47=$A44)*('02.XLS'!$B$5:$JN$5=DC$5)*('02.XLS'!$B$6:$JN$47))} -> 0 | DD44: {=SUMPRODUCT(('02.XLS'!$A$6:$A$47=$A44)*('02.XLS'!$B$5:$JN$5=DD$5)*('02.XLS'!$B$6:$JN$47))} -> 0 | DE44: {=SUMPRODUCT(('02.XLS'!$A$6:$A$47=$A44)*('02.XLS'!$B$5:$JN$5=DE$5)*('02.XLS'!$B$6:$JN$47))} -> 67 | DF44: {=SUMPRODUCT(('02.XLS'!$A$6:$A$47=$A44)*('02.XLS'!$B$5:$JN$5=DF$5)*('02.XLS'!$B$6:$JN$47))} -> 145 | DG44: {=SUMPRODUCT(('02.XLS'!$A$6:$A$47=$A44)*('02.XLS'!$B$5:$JN$5=DG$5)*('02.XLS'!$B$6:$JN$47))} -> 300 | DH44: {=SUMPRODUCT(('02.XLS'!$A$6:$A$47=$A44)*('02.XLS'!$B$5:$JN$5=DH$5)*('02.XLS'!$B$6:$JN$47))} -> 275 | DI44: {=SUMPRODUCT(('02.XLS'!$A$6:$A$47=$A44)*('02.XLS'!$B$5:$JN$5=DI$5)*('02.XLS'!$B$6:$JN$47))} -> 172 | ... DM44: {=SUMPRODUCT(('02.XLS'!$A$6:$A$47=$A44)*('02.XLS'!$B$5:$JN$5=DM$5)*('02.XLS'!$B$6:$JN$47))} -> 200 | DN44: =SUM(DB44:DM44) -> 1737 | DO44: {=SUMPRODUCT(('02.XLS'!$A$6:$A$47=$A44)*('02.XLS'!$B$5:$JN$5=DO$5)*('02.XLS'!$B$6:$JN$47))} -> 112 | DP44: {=SUMPRODUCT(('02.XLS'!$A$6:$A$47=$A44)*('02.XLS'!$B$5:$JN$5=DP$5)*('02.XLS'!$B$6:$JN$47))} -> 50 | DQ44: {=SUMPRODUCT(('02.XLS'!$A$6:$A$47=$A44)*('02.XLS'!$B$5:$JN$5=DQ$5)*('02.XLS'!$B$6:$JN$47))} -> 50 | DR44: {=SUMPRODUCT(('02.XLS'!$A$6:$A$47=$A44)*('02.XLS'!$B$5:$JN$5=DR$5)*('02.XLS'!$B$6:$JN$47))} -> 65 | DS44: {=SUMPRODUCT(('02.XLS'!$A$6:$A$47=$A44)*('02.XLS'!$B$5:$JN$5=DS$5)*('02.XLS'!$B$6:$JN$47))} -> 130 | DT44: {=SUMPRODUCT(('02.XLS'!$A$6:$A$47=$A44)*('02.XLS'!$B$5:$JN$5=DT$5)*('02.XLS'!$B$6:$JN$47))} -> 152 | DU44: {=SUMPRODUCT(('02.XLS'!$A$6:$A$47=$A44)*('02.XLS'!$B$5:$JN$5=DU$5)*('02.XLS'!$B$6:$JN$47))} -> 160 | DV44: {=SUMPRODUCT(('02.XLS'!$A$6:$A$47=$A44)*('02.XLS'!$B$5:$JN$5=DV$5)*('02.XLS'!$B$6:$JN$47))} -> 170 | ... DZ44: {=SUMPRODUCT(('02.XLS'!$A$6:$A$47=$A44)*('02.XLS'!$B$5:$JN$5=DZ$5)*('02.XLS'!$B$6:$JN$47))} -> 220 | EA44: =SUM(DO44:DZ44) -> 1669 | EB44: {=SUMPRODUCT(('02.XLS'!$A$6:$A$47=$A44)*('02.XLS'!$B$5:$JN$5=EB$5)*('02.XLS'!$B$6:$JN$47))} -> 140 | EC44: {=SUMPRODUCT(('02.XLS'!$A$6:$A$47=$A44)*('02.XLS'!$B$5:$JN$5=EC$5)*('02.XLS'!$B$6:$JN$47))} -> 150 | ED44: {=SUMPRODUCT(('02.XLS'!$A$6:$A$47=$A44)*('02.XLS'!$B$5:$JN$5=ED$5)*('02.XLS'!$B$6:$JN$47))} -> 90 | EE44: {=SUMPRODUCT(('02.XLS'!$A$6:$A$47=$A44)*('02.XLS'!$B$5:$JN$5=EE$5)*('02.XLS'!$B$6:$JN$47))} -> 78 | EF44: {=SUMPRODUCT(('02.XLS'!$A$6:$A$47=$A44)*('02.XLS'!$B$5:$JN$5=EF$5)*('02.XLS'!$B$6:$JN$47))} -> 250 | EG44: {=SUMPRODUCT(('02.XLS'!$A$6:$A$47=$A44)*('02.XLS'!$B$5:$JN$5=EG$5)*('02.XLS'!$B$6:$JN$47))} -> 160 | EH44: {=SUMPRODUCT(('02.XLS'!$A$6:$A$47=$A44)*('02.XLS'!$B$5:$JN$5=EH$5)*('02.XLS'!$B$6:$JN$47))} -> 220 | EI44: {=SUMPRODUCT(('02.XLS'!$A$6:$A$47=$A44)*('02.XLS'!$B$5:$JN$5=EI$5)*('02.XLS'!$B$6:$JN$47))} -> 230 | ... EM44: {=SUMPRODUCT(('02.XLS'!$A$6:$A$47=$A44)*('02.XLS'!$B$5:$JN$5=EM$5)*('02.XLS'!$B$6:$JN$47))} -> 248 | EN44: =SUM(EB44:EM44) -> 2084 | EO44: {=SUMPRODUCT(('02.XLS'!$A$6:$A$47=$A44)*('02.XLS'!$B$5:$JN$5=EO$5)*('02.XLS'!$B$6:$JN$47))} -> 152 | EP44: {=SUMPRODUCT(('02.XLS'!$A$6:$A$47=$A44)*('02.XLS'!$B$5:$JN$5=EP$5)*('02.XLS'!$B$6:$JN$47))} -> 120 | EQ44: {=SUMPRODUCT(('02.XLS'!$A$6:$A$47=$A44)*('02.XLS'!$B$5:$JN$5=EQ$5)*('02.XLS'!$B$6:$JN$47))} -> 130 | ER44: {=SUMPRODUCT(('02.XLS'!$A$6:$A$47=$A44)*('02.XLS'!$B$5:$JN$5=ER$5)*('02.XLS'!$B$6:$JN$47))} -> 150 | ES44: {=SUMPRODUCT(('02.XLS'!$A$6:$A$47=$A44)*('02.XLS'!$B$5:$JN$5=ES$5)*('02.XLS'!$B$6:$JN$47))} -> 180 | ET44: {=SUMPRODUCT(('02.XLS'!$A$6:$A$47=$A44)*('02.XLS'!$B$5:$JN$5=ET$5)*('02.XLS'!$B$6:$JN$47))} -> 180 | EU44: {=SUMPRODUCT(('02.XLS'!$A$6:$A$47=$A44)*('02.XLS'!$B$5:$JN$5=EU$5)*('02.XLS'!$B$6:$JN$47))} -> 185 | EV44: {=SUMPRODUCT(('02.XLS'!$A$6:$A$47=$A44)*('02.XLS'!$B$5:$JN$5=EV$5)*('02.XLS'!$B$6:$JN$47))} -> 250 | ... EZ44: {=SUMPRODUCT(('02.XLS'!$A$6:$A$47=$A44)*('02.XLS'!$B$5:$JN$5=EZ$5)*('02.XLS'!$B$6:$JN$47))} -> 195 | FA44: =SUM(EO44:EZ44) -> 2142 | FB44: {=SUMPRODUCT(('02.XLS'!$A$6:$A$47=$A44)*('02.XLS'!$B$5:$JN$5=FB$5)*('02.XLS'!$B$6:$JN$47))} -> 185 | FC44: {=SUMPRODUCT(('02.XLS'!$A$6:$A$47=$A44)*('02.XLS'!$B$5:$JN$5=FC$5)*('02.XLS'!$B$6:$JN$47))} -> 200 | FD44: {=SUMPRODUCT(('02.XLS'!$A$6:$A$47=$A44)*('02.XLS'!$B$5:$JN$5=FD$5)*('02.XLS'!$B$6:$JN$47))} -> 150 | FE44: {=SUMPRODUCT(('02.XLS'!$A$6:$A$47=$A44)*('02.XLS'!$B$5:$JN$5=FE$5)*('02.XLS'!$B$6:$JN$47))} -> 180 | FF44: {=SUMPRODUCT(('02.XLS'!$A$6:$A$47=$A44)*('02.XLS'!$B$5:$JN$5=FF$5)*('02.XLS'!$B$6:$JN$47))} -> 192 | FG44: {=SUMPRODUCT(('02.XLS'!$A$6:$A$47=$A44)*('02.XLS'!$B$5:$JN$5=FG$5)*('02.XLS'!$B$6:$JN$47))} -> 200 | FH44: {=SUMPRODUCT(('02.XLS'!$A$6:$A$47=$A44)*('02.XLS'!$B$5:$JN$5=FH$5)*('02.XLS'!$B$6:$JN$47))} -> 195 | FI44: {=SUMPRODUCT(('02.XLS'!$A$6:$A$47=$A44)*('02.XLS'!$B$5:$JN$5=FI$5)*('02.XLS'!$B$6:$JN$47))} -> 210 | ... FM44: {=SUMPRODUCT(('02.XLS'!$A$6:$A$47=$A44)*('02.XLS'!$B$5:$JN$5=FM$5)*('02.XLS'!$B$6:$JN$47))} -> 232 | FN44: =SUM(FB44:FM44) -> 2409 | FO44: {=SUMPRODUCT(('02.XLS'!$A$6:$A$47=$A44)*('02.XLS'!$B$5:$JN$5=FO$5)*('02.XLS'!$B$6:$JN$47))} -> 200 | FP44: {=SUMPRODUCT(('02.XLS'!$A$6:$A$47=$A44)*('02.XLS'!$B$5:$JN$5=FP$5)*('02.XLS'!$B$6:$JN$47))} -> 230 | FQ44: {=SUMPRODUCT(('02.XLS'!$A$6:$A$47=$A44)*('02.XLS'!$B$5:$JN$5=FQ$5)*('02.XLS'!$B$6:$JN$47))} -> 235 | FR44: {=SUMPRODUCT(('02.XLS'!$A$6:$A$47=$A44)*('02.XLS'!$B$5:$JN$5=FR$5)*('02.XLS'!$B$6:$JN$47))} -> 260 | FS44: {=SUMPRODUCT(('02.XLS'!$A$6:$A$47=$A44)*('02.XLS'!$B$5:$JN$5=FS$5)*('02.XLS'!$B$6:$JN$47))} -> 205 | FT44: {=SUMPRODUCT(('02.XLS'!$A$6:$A$47=$A44)*('02.XLS'!$B$5:$JN$5=FT$5)*('02.XLS'!$B$6:$JN$47))} -> 230 | FU44: {=SUMPRODUCT(('02.XLS'!$A$6:$A$47=$A44)*('02.XLS'!$B$5:$JN$5=FU$5)*('02.XLS'!$B$6:$JN$47))} -> 220 | FV44: {=SUMPRODUCT(('02.XLS'!$A$6:$A$47=$A44)*('02.XLS'!$B$5:$JN$5=FV$5)*('02.XLS'!$B$6:$JN$47))} -> 135 | ... FZ44: {=SUMPRODUCT(('02.XLS'!$A$6:$A$47=$A44)*('02.XLS'!$B$5:$JN$5=FZ$5)*('02.XLS'!$B$6:$JN$47))} -> 190 | GA44: =SUM(FO44:FZ44) -> 2475 | GB44: {=SUMPRODUCT(('02.XLS'!$A$6:$A$47=$A44)*('02.XLS'!$B$5:$JN$5=GB$5)*('02.XLS'!$B$6:$JN$47))} -> 0 | GC44: {=SUMPRODUCT(('02.XLS'!$A$6:$A$47=$A44)*('02.XLS'!$B$5:$JN$5=GC$5)*('02.XLS'!$B$6:$JN$47))} -> 0 | GD44: {=SUMPRODUCT(('02.XLS'!$A$6:$A$47=$A44)*('02.XLS'!$B$5:$JN$5=GD$5)*('02.XLS'!$B$6:$JN$47))} -> 0 | GE44: {=SUMPRODUCT(('02.XLS'!$A$6:$A$47=$A44)*('02.XLS'!$B$5:$JN$5=GE$5)*('02.XLS'!$B$6:$JN$47))} -> 0 | GF44: {=SUMPRODUCT(('02.XLS'!$A$6:$A$47=$A44)*('02.XLS'!$B$5:$JN$5=GF$5)*('02.XLS'!$B$6:$JN$47))} -> 0 | GG44: {=SUMPRODUCT(('02.XLS'!$A$6:$A$47=$A44)*('02.XLS'!$B$5:$JN$5=GG$5)*('02.XLS'!$B$6:$JN$47))} -> 0 | GH44: {=SUMPRODUCT(('02.XLS'!$A$6:$A$47=$A44)*('02.XLS'!$B$5:$JN$5=GH$5)*('02.XLS'!$B$6:$JN$47))} -> 0 | GI44: {=SUMPRODUCT(('02.XLS'!$A$6:$A$47=$A44)*('02.XLS'!$B$5:$JN$5=GI$5)*('02.XLS'!$B$6:$JN$47))} -> 0 | ... GM44: {=SUMPRODUCT(('02.XLS'!$A$6:$A$47=$A44)*('02.XLS'!$B$5:$JN$5=GM$5)*('02.XLS'!$B$6:$JN$47))} -> 0 | GN44: =SUM(GB44:GM44) -> 0 | GO44: {=SUMPRODUCT(('02.XLS'!$A$6:$A$47=$A44)*('02.XLS'!$B$5:$JN$5=GO$5)*('02.XLS'!$B$6:$JN$47))} -> 0 | GP44: {=SUMPRODUCT(('02.XLS'!$A$6:$A$47=$A44)*('02.XLS'!$B$5:$JN$5=GP$5)*('02.XLS'!$B$6:$JN$47))} -> 0 | GQ44: {=SUMPRODUCT(('02.XLS'!$A$6:$A$47=$A44)*('02.XLS'!$B$5:$JN$5=GQ$5)*('02.XLS'!$B$6:$JN$47))} -> 0 | GR44: {=SUMPRODUCT(('02.XLS'!$A$6:$A$47=$A44)*('02.XLS'!$B$5:$JN$5=GR$5)*('02.XLS'!$B$6:$JN$47))} -> 0 | GS44: {=SUMPRODUCT(('02.XLS'!$A$6:$A$47=$A44)*('02.XLS'!$B$5:$JN$5=GS$5)*('02.XLS'!$B$6:$JN$47))} -> 0 | GT44: {=SUMPRODUCT(('02.XLS'!$A$6:$A$47=$A44)*('02.XLS'!$B$5:$JN$5=GT$5)*('02.XLS'!$B$6:$JN$47))} -> 0 | GU44: {=SUMPRODUCT(('02.XLS'!$A$6:$A$47=$A44)*('02.XLS'!$B$5:$JN$5=GU$5)*('02.XLS'!$B$6:$JN$47))} -> 0 | GV44: {=SUMPRODUCT(('02.XLS'!$A$6:$A$47=$A44)*('02.XLS'!$B$5:$JN$5=GV$5)*('02.XLS'!$B$6:$JN$47))} -> 0 | ... GZ44: {=SUMPRODUCT(('02.XLS'!$A$6:$A$47=$A44)*('02.XLS'!$B$5:$JN$5=GZ$5)*('02.XLS'!$B$6:$JN$47))} -> 0 | HA44: =SUM(GO44:GZ44) -> 0 | HB44: {=SUMPRODUCT(('02.XLS'!$A$6:$A$47=$A44)*('02.XLS'!$B$5:$JN$5=HB$5)*('02.XLS'!$B$6:$JN$47))} -> 0 | HC44: {=SUMPRODUCT(('02.XLS'!$A$6:$A$47=$A44)*('02.XLS'!$B$5:$JN$5=HC$5)*('02.XLS'!$B$6:$JN$47))} -> 0 | HD44: {=SUMPRODUCT(('02.XLS'!$A$6:$A$47=$A44)*('02.XLS'!$B$5:$JN$5=HD$5)*('02.XLS'!$B$6:$JN$47))} -> 0 | HE44: {=SUMPRODUCT(('02.XLS'!$A$6:$A$47=$A44)*('02.XLS'!$B$5:$JN$5=HE$5)*('02.XLS'!$B$6:$JN$47))} -> 0 | HF44: {=SUMPRODUCT(('02.XLS'!$A$6:$A$47=$A44)*('02.XLS'!$B$5:$JN$5=HF$5)*('02.XLS'!$B$6:$JN$47))} -> 0 | HG44: {=SUMPRODUCT(('02.XLS'!$A$6:$A$47=$A44)*('02.XLS'!$B$5:$JN$5=HG$5)*('02.XLS'!$B$6:$JN$47))} -> 0 | HH44: {=SUMPRODUCT(('02.XLS'!$A$6:$A$47=$A44)*('02.XLS'!$B$5:$JN$5=HH$5)*('02.XLS'!$B$6:$JN$47))} -> 0 | HI44: {=SUMPRODUCT(('02.XLS'!$A$6:$A$47=$A44)*('02.XLS'!$B$5:$JN$5=HI$5)*('02.XLS'!$B$6:$JN$47))} -> 0 | ... HM44: {=SUMPRODUCT(('02.XLS'!$A$6:$A$47=$A44)*('02.XLS'!$B$5:$JN$5=HM$5)*('02.XLS'!$B$6:$JN$47))} -> 0 | HN44: =SUM(HB44:HM44) -> 0 | HO44: {=SUMPRODUCT(('02.XLS'!$A$6:$A$47=$A44)*('02.XLS'!$B$5:$JN$5=HO$5)*('02.XLS'!$B$6:$JN$47))} -> 0 | HP44: {=SUMPRODUCT(('02.XLS'!$A$6:$A$47=$A44)*('02.XLS'!$B$5:$JN$5=HP$5)*('02.XLS'!$B$6:$JN$47))} -> 0 | HQ44: {=SUMPRODUCT(('02.XLS'!$A$6:$A$47=$A44)*('02.XLS'!$B$5:$JN$5=HQ$5)*('02.XLS'!$B$6:$JN$47))} -> 0 | HR44: {=SUMPRODUCT(('02.XLS'!$A$6:$A$47=$A44)*('02.XLS'!$B$5:$JN$5=HR$5)*('02.XLS'!$B$6:$JN$47))} -> 0 | HS44: {=SUMPRODUCT(('02.XLS'!$A$6:$A$47=$A44)*('02.XLS'!$B$5:$JN$5=HS$5)*('02.XLS'!$B$6:$JN$47))} -> 0 | HT44: {=SUMPRODUCT(('02.XLS'!$A$6:$A$47=$A44)*('02.XLS'!$B$5:$JN$5=HT$5)*('02.XLS'!$B$6:$JN$47))} -> 0 | HU44: {=SUMPRODUCT(('02.XLS'!$A$6:$A$47=$A44)*('02.XLS'!$B$5:$JN$5=HU$5)*('02.XLS'!$B$6:$JN$47))} -> 0 | HV44: {=SUMPRODUCT(('02.XLS'!$A$6:$A$47=$A44)*('02.XLS'!$B$5:$JN$5=HV$5)*('02.XLS'!$B$6:$JN$47))} -> 0 | ... HZ44: {=SUMPRODUCT(('02.XLS'!$A$6:$A$47=$A44)*('02.XLS'!$B$5:$JN$5=HZ$5)*('02.XLS'!$B$6:$JN$47))} -> 0 | IA44: =SUM(HO44:HZ44) -> 0 | IB44: {=SUMPRODUCT(('02.XLS'!$A$6:$A$47=$A44)*('02.XLS'!$B$5:$JN$5=IB$5)*('02.XLS'!$B$6:$JN$47))} -> 0 | IC44: {=SUMPRODUCT(('02.XLS'!$A$6:$A$47=$A44)*('02.XLS'!$B$5:$JN$5=IC$5)*('02.XLS'!$B$6:$JN$47))} -> 0 | ID44: {=SUMPRODUCT(('02.XLS'!$A$6:$A$47=$A44)*('02.XLS'!$B$5:$JN$5=ID$5)*('02.XLS'!$B$6:$JN$47))} -> 0 | IE44: {=SUMPRODUCT(('02.XLS'!$A$6:$A$47=$A44)*('02.XLS'!$B$5:$JN$5=IE$5)*('02.XLS'!$B$6:$JN$47))} -> 0 | IF44: {=SUMPRODUCT(('02.XLS'!$A$6:$A$47=$A44)*('02.XLS'!$B$5:$JN$5=IF$5)*('02.XLS'!$B$6:$JN$47))} -> 0 | IG44: {=SUMPRODUCT(('02.XLS'!$A$6:$A$47=$A44)*('02.XLS'!$B$5:$JN$5=IG$5)*('02.XLS'!$B$6:$JN$47))} -> 0 | IH44: {=SUMPRODUCT(('02.XLS'!$A$6:$A$47=$A44)*('02.XLS'!$B$5:$JN$5=IH$5)*('02.XLS'!$B$6:$JN$47))} -> 0 | II44: {=SUMPRODUCT(('02.XLS'!$A$6:$A$47=$A44)*('02.XLS'!$B$5:$JN$5=II$5)*('02.XLS'!$B$6:$JN$47))} -> 0 | ... IM44: {=SUMPRODUCT(('02.XLS'!$A$6:$A$47=$A44)*('02.XLS'!$B$5:$JN$5=IM$5)*('02.XLS'!$B$6:$JN$47))} -> 0 | IN44: =SUM(IB44:IM44) -> 0 | IO44: {=SUMPRODUCT(('02.XLS'!$A$6:$A$47=$A44)*('02.XLS'!$B$5:$JN$5=IO$5)*('02.XLS'!$B$6:$JN$47))} -> 0 | IP44: {=SUMPRODUCT(('02.XLS'!$A$6:$A$47=$A44)*('02.XLS'!$B$5:$JN$5=IP$5)*('02.XLS'!$B$6:$JN$47))} -> 0 | IQ44: {=SUMPRODUCT(('02.XLS'!$A$6:$A$47=$A44)*('02.XLS'!$B$5:$JN$5=IQ$5)*('02.XLS'!$B$6:$JN$47))} -> 0 | IR44: {=SUMPRODUCT(('02.XLS'!$A$6:$A$47=$A44)*('02.XLS'!$B$5:$JN$5=IR$5)*('02.XLS'!$B$6:$JN$47))} -> 0 | IS44: {=SUMPRODUCT(('02.XLS'!$A$6:$A$47=$A44)*('02.XLS'!$B$5:$JN$5=IS$5)*('02.XLS'!$B$6:$JN$47))} -> 0 | IT44: {=SUMPRODUCT(('02.XLS'!$A$6:$A$47=$A44)*('02.XLS'!$B$5:$JN$5=IT$5)*('02.XLS'!$B$6:$JN$47))} -> 0 | IU44: {=SUMPRODUCT(('02.XLS'!$A$6:$A$47=$A44)*('02.XLS'!$B$5:$JN$5=IU$5)*('02.XLS'!$B$6:$JN$47))} -> 0 | IV44: {=SUMPRODUCT(('02.XLS'!$A$6:$A$47=$A44)*('02.XLS'!$B$5:$JN$5=IV$5)*('02.XLS'!$B$6:$JN$47))} -> 0 | ... IZ44: {=SUMPRODUCT(('02.XLS'!$A$6:$A$47=$A44)*('02.XLS'!$B$5:$JN$5=IZ$5)*('02.XLS'!$B$6:$JN$47))} -> 0 | JA44: =SUM(IO44:IZ44) -> 0 | JB44: {=SUMPRODUCT(('02.XLS'!$A$6:$A$47=$A44)*('02.XLS'!$B$5:$JN$5=JB$5)*('02.XLS'!$B$6:$JN$47))} -> 0 | JC44: {=SUMPRODUCT(('02.XLS'!$A$6:$A$47=$A44)*('02.XLS'!$B$5:$JN$5=JC$5)*('02.XLS'!$B$6:$JN$47))} -> 0 | JD44: {=SUMPRODUCT(('02.XLS'!$A$6:$A$47=$A44)*('02.XLS'!$B$5:$JN$5=JD$5)*('02.XLS'!$B$6:$JN$47))} -> 0 | JE44: {=SUMPRODUCT(('02.XLS'!$A$6:$A$47=$A44)*('02.XLS'!$B$5:$JN$5=JE$5)*('02.XLS'!$B$6:$JN$47))} -> 0 | JF44: {=SUMPRODUCT(('02.XLS'!$A$6:$A$47=$A44)*('02.XLS'!$B$5:$JN$5=JF$5)*('02.XLS'!$B$6:$JN$47))} -> 0 | JG44: {=SUMPRODUCT(('02.XLS'!$A$6:$A$47=$A44)*('02.XLS'!$B$5:$JN$5=JG$5)*('02.XLS'!$B$6:$JN$47))} -> 0 | JH44: {=SUMPRODUCT(('02.XLS'!$A$6:$A$47=$A44)*('02.XLS'!$B$5:$JN$5=JH$5)*('02.XLS'!$B$6:$JN$47))} -> 0 | JI44: {=SUMPRODUCT(('02.XLS'!$A$6:$A$47=$A44)*('02.XLS'!$B$5:$JN$5=JI$5)*('02.XLS'!$B$6:$JN$47))} -> 0 | ... JM44: {=SUMPRODUCT(('02.XLS'!$A$6:$A$47=$A44)*('02.XLS'!$B$5:$JN$5=JM$5)*('02.XLS'!$B$6:$JN$47))} -> 0 | JN44: =SUM(JB44:JM44) -> 0 | JP44: =IFERROR((( _xlfn.XLOOKUP((DATE(YEAR($JP$5),MONTH($JP$5),1)),SMN.AGRO.DATE,$B44:$JN44) / _xlfn.XLOOKUP((DATE(YEAR($JP$5)-1,MONTH($JP$5),1)),SMN.AGRO.DATE,$B44:$JN44) )-1)*100,"") | JQ44: =IFERROR(((JS44/JR44)-1)*100,"") | JR44: =SUMIFS($B44:$JN44,SMN.AGRO.DATE,">="&DATE(YEAR($JP$5)-1,1,1),SMN.AGRO.DATE,"<="&DATE(YEAR($JP$5)-1,MONTH($JP$5),1)) -> 0 | JS44: =SUMIFS($B44:$JN44,SMN.AGRO.DATE,">="&DATE(YEAR($JP$5),1,1),SMN.AGRO.DATE,"<="&$JP$5) -> 0
